Workbook
Name Ambar: 'Справочник подстановки'!$S$3:$S$4
Name Autonomy: 'Справочник подстановки'!$A$3:$A$4
Name ColumnCount: 'Справочник подстановки'!$C$3:$C$8
Name CountPilotBore: 'Справочник подстановки'!$E$3:$E$7
Name DrillRig: 'Справочник подстановки'!$N$3:$N$4
Name Grp: 'Справочник подстановки'!$H$3:$H$4
Name GrpCount: 'Справочник подстановки'!$I$3:$I$17
Name GrpType: 'Справочник подстановки'!$J$3:$J$4
Name MnogoZab: 'Справочник подстановки'!$F$3
Name MudPumpType: 'Справочник подстановки'!$O$3:$O$4
Name MudType: 'Справочник подстановки'!$P$3:$P$8
Name Nnb: 'Справочник подстановки'!$Q$3:$Q$11
Name Npv: 'Справочник подстановки'!$L$3:$L$6
Name Perforation: 'Справочник подстановки'!$R$3:$R$11
Name PilotBore: 'Справочник подстановки'!$D$3:$D$5
Name ProductBoresCount: 'Справочник подстановки'!$G$3:$G$8
Name WellFunc: 'Справочник подстановки'!$K$3:$K$7
Name WellType: 'Справочник подстановки'!$B$3:$B$12
Name Виновник: 'Справочник подстановки'!$M$3:$M$4

Sheet Уделки ЗБС 9 типов
A1: ="Отчет по стоимости скважин с учетом НЗС прошлых лет на отчетную дату по ЭБ и ЗБС по "&'Текущий год'!A2 -> Отчет по стоимости скважин с учетом НЗС прошлых лет на отчетную дату по ЭБ и ЗБС по
A4: № п/п | B4: Месторождение | C4: № куста | D4: № скважины | E4: Автономия | G4: Тип скважины | H4: Назначение скважины | I4: Кол-во обсадных колонн | J4: Наличие пилотного/ ликвидированного по геологическим причинам ствола | K4: Кол-во пилотных стволов (ликвидированных по геологич.причинам) | L4: МСС (многоствольная/ многозабойная скважина) | M4: Кол-во стволов | N4: ГРП/ МГРП | O4: Количество стадий ГРП/ МГРП | P4: Тип ГРП | Q4: Проходка выполненный объем | R4: Проходка по законченным бурением скважинам (Заполняется после окончания бурения) | X4: Длина ликвидированного ствола по ТЕХНИЧЕСКИМ причинам (не включается в основную проходку) | Y4: Глубина скважины до фактического забоя | AA4: ЗБС (включая углубления) | AC4: Отход от вертикали | AD4: Измеренная по стволу глубина спуска обсадных колонн | AK4: Диаметр обсадных колонн | AQ4: Отбор керна | AR4: Сроки строительства | AT4: Сроки бурения | AX4: Календарное время бурения по скважине (Выполнение прошлый год + текущий), сут ПОСЛЕ ОКОНЧАНИЯ БУРЕНИЯ КАЛЕНДАРНОЕ ВРЕМЯ ДОЛЖНО РАВНЯТЬСЯ ВРЕМЕНИ ПО ЗАКОНЧЕННЫМ БУРЕНИЕМ | BA4: Календарное время бурения по скв.зак.бурением, сут (заполняется только по скв.зак.бур. За весь период бурения скважины) | BD4: Сроки освоения | BF4: Продолжительность освоения, сут (заполняется после окончания освоения) | BL4: Дата сдачи скважины в эксплуатацию,или на ВНР | BM4: Продолжительность ВНР | BN4: Амбарное / Без амбарное бурение | BO4: Характеристика бурового станка | BX4: Характеристика бурового раствора | CE4: Характеристика ННБ | CK4: ВМР на скважине (виды ВМР на скважине в шт. и м/км должны соответствовать суммам по ВМР, включенным в стоимость строительства данной скважины) | CR4: Продолжительность ВМР | CX4: Перечень работ по вывозу и интенсификацции притока | DB4: Пусковой дебит | DC4: Полная стоимость строительства скважины (без НДС) тыс. руб. (не включается строительство и обустройство кустовой площадки, ФА, НКТ, ГНО) | YF4: Комментарии
E5: По электроэнергии (отсутствие ВЛ) | F5: По доступности (отсутствие дорог) | G5: ННС ГС ННС Юра ГС Юра ННС Палеозой ГС Палеозой ННС Бажен ГС Бажен БННС БГС | H5: Добывающая Нагнетательная Водозаборная Газовая | I5: 2-6 | J5: пилот/ перебур/ пилот + перебур | K5: 1-5 | L5: МСС | M5: 1-5 | N5: Проведение ГРП/ МГРП | O5: 1-15 | P5: Проппантный/ Кислотный | Q5: Всего | R5: Всего | S5: В том числе: Длина пилотного ствола или сумма стволов | T5: Длина ликвидированного ствола по геологическим причинам (перебур) | U5: Длина горизонтального участка 1 | V5: Длина горизонтального участка 2 | W5: Длина горизонтального участка 3 | Y5: по вертикали | Z5: по стволу | AA5: Длина бокового ствола | AB5: Измеренная по стволу глубина зарезки "окна" / башмака | AT5: Дата начала бурения | AV5: Дата окончания бурения | AX5: Всего, в том числе: | AY5: Производительное время | AZ5: Непроизводительное время | BA5: Всего, в том числе: | BB5: Производительное время | BC5: Непроизводительное время | BD5: Дата начала освоения | BE5: Дата окончания освоения | BF5: Время работы бригады КРС | BI5: ГРП | BJ5: ГНКТ | BK5: Прочие | CE5: Подрядчик по ННБ | CF5: Кондуктор | CG5: Технич. колонна 1 | CH5: Технич. колонна 2 | CI5: Экспл. колонна | CJ5: Хвостовик | CK5: Мобилизация / демобилизация БУ, указывается расстояние | CL5: Переезд (перевозка) БУ между кустами (местами дислокации), указывается расстояние | CM5: Передвижка БУ, указывается длина передвижки | CN5: Монтаж БУ | CO5: Стаскивание БУ | CP5: Демонтаж БУ | CQ5: Наличие Водных преград | CX5: Перфорация | CZ5: ГРП | DB5: Всего | DC5: ИТОГО руб. | DD5: При ЗБС | DF5: ВМР (виды ВМР на скважине в шт. и м/км должны соответствовать суммам по ВМР, включенным в стоимость строительства данной скважины) | DN5: Бурение | QW5: Освоение | XK5: Оборудование | XQ5: Подготовка площвдки
AD6: Направление | AE6: Кондуктор | AF6: Технич. колонна 1 | AG6: Технич. колонна 2 | AH6: Экспл. колонна | AI6: Хвостовик | AK6: Направление | AL6: Кондуктор | AM6: Технич. колонна 1 | AN6: Технич. колонна 2 | AO6: Экспл. колонна | AP6: Хвостовик | AR6: Начала стр-ва | AS6: Ввода скважины в эксплуатацию по фонду | BO6: Наименование БУ | BP6: Наличие СВП | BQ6: Номинальная грузоподъемность БУ | BR6: Буровые Насосы | BT6: Система очистки | BX6: Подрядчик по растворам | BY6: Система раствора | DD6: Подрядчик по подгот. работам | DE6: Подготовка скважины к реконструкции бригадой КРС | DF6: Подрядчик по ВМР | DG6: Всего, в т.ч. | DH6: Мобилизация / Демобилизация | DI6: Переезд (перевозка) БУ между кустами (местами дислокации) | DJ6: Передвижка | DK6: Монтаж | DL6: Демонтаж | DM6: Прочие работы | DN6: Всего, в т.ч. | DO6: Бурение (полные затраты на бурового подрядчика за исключением ВМР, перевозки и переработки бурового шлама) | EO6: в том числе: Услуги АвИЭС | EP6: Услуги АвИЭС (при условии, что услуги оказывает отдельный подрядчик) | FK6: Вырезка окна | GF6: Услуги направленного бурения и телеметрии (включая ГЗД) | HA6: Услуги ГИС при бурении | HV6: Услуги ГТИ | IQ6: Цементирование | JL6: Сопровождение буровых растворов | KG6: Долотное сопровождение | LB6: Керноотбор | LW6: Оборудование МГРП/ подвеска хвостовика | MR6: Затраты на перевозку, хранение, утилизацию (переработку) шлама и бурового раствора, а так же на рекультивацию | NM6: Супервайзинг при бурении | OH6: МТО (материалы, предоставляемые подрядчику на давальческой основе при бурении) | PC6: Авиа перевозки за счет Заказчика | PD6: Водные перевозки за счет Заказчика | PE6: Консультационные услуги, в том числе услуги НТЦ | PZ6: Экологические платежи в бюджет | QA6: Разработка проектной документации | QV6: Прочие затраты при бурении | QW6: Всего, в т.ч. | QX6: Стоимость услуг бригад освоения, ТКРС | RS6: Освоение скважин струйными насосами | SN6: Услуги по глушению, приготовлению раствора глушения (в т.ч. раствор), промывке, ОПЗ | TI6: Стоимость ГИС при освоении, включая перфорацию | UD6: Затраты на проведение ГРП | UY6: Затраты на ГНКТ | VT6: МТО (материалы, предоставляемые подрядчику на давальческой основе при освоении) кроме проппанта | WO6: Супервайзинг при освоении (этап освоение + ГРП + ГНКТ) | XJ6: Прочие затраты в освоении | XK6: ОНВСС | XQ6: Подготовка площадки
AI7: Глубина "Голова" подвески (по стволу) м | AJ7: Глубина спуска (по стволу) м | AT7: Число | AU7: Время | AV7: Число | AW7: Время | BF7: Всего | BG7: ПВ | BH7: НПВ | BR7: Количество | BS7: Тип | BT7: Марка вибросит | BU7: Количество | BV7: Марка центрифуг | BW7: Количество | BY7: Направление | BZ7: Кондуктор | CA7: Технич. колонна 1 | CB7: Технич. колонна 2 | CC7: Экспл. колонна | CD7: Хвостовик | CR7: Мобилизация / Демобилизация | CS7: Переезд (перевозка) БУ между кустами | CT7: Передвижка БУ | CU7: Монтаж | CV7: Стаскивание | CW7: Демонтаж | CX7: Сумма длин участков перфорации | CY7: Тип перфорации | CZ7: Объем проппанта | DA7: Объем проппанта на 1 стадию | DO7: Подрядчик по ЭБ и ЗБС 1 | DP7: Подрядчик по ЭБ и ЗБС 2 | DQ7: Подрядчик по ЭБ и ЗБС 3 | DR7: Подрядчик по ЭБ и ЗБС 4 | DS7: Подрядчик по ЭБ и ЗБС 5 | DT7: Подрядчик по ЭБ и ЗБС 6 | DU7: Подрядчик по ЭБ и ЗБС 7 | DV7: Подрядчик по ЭБ и ЗБС 8 | DW7: Подрядчик по ЭБ и ЗБС 9 | DX7: Подрядчик по ЭБ и ЗБС 10 | DY7: Подрядчик по ЭБ и ЗБС 11 | DZ7: Подрядчик по ЭБ и ЗБС 12 | EA7: Подрядчик по ЭБ и ЗБС 13 | EB7: Подрядчик по ЭБ и ЗБС 14 | EC7: Подрядчик по ЭБ и ЗБС 15 | ED7: Подрядчик по ЭБ и ЗБС 16 | EE7: Подрядчик по ЭБ и ЗБС 17 | EF7: Подрядчик по ЭБ и ЗБС 18 | EG7: Подрядчик по ЭБ и ЗБС 19 | EH7: Подрядчик по ЭБ и ЗБС 20 | EI7: Подрядчик по ЭБ и ЗБС 21 | EJ7: Подрядчик по ЭБ и ЗБС 22 | EK7: Подрядчик по ЭБ и ЗБС 23 | EL7: Подрядчик по ЭБ и ЗБС 24 | EM7: Подрядчик по ЭБ и ЗБС 25 | EN7: Всего | EO7: Всего | EP7: Подрядчик по АвИЭС 1 | EQ7: Подрядчик по АвИЭС 2 | ER7: Подрядчик по АвИЭС 3 | ES7: Подрядчик по АвИЭС 4 | ET7: Подрядчик по АвИЭС 5 | EU7: Подрядчик по АвИЭС 6 | EV7: Подрядчик по АвИЭС 7 | EW7: Подрядчик по АвИЭС 8 | EX7: Подрядчик по АвИЭС 9 | EY7: Подрядчик по АвИЭС 10 | EZ7: Подрядчик по АвИЭС 11 | FA7: Подрядчик по АвИЭС 12 | FB7: Подрядчик по АвИЭС 13 | FC7: Подрядчик по АвИЭС 14 | FD7: Подрядчик по АвИЭС 15 | FE7: Подрядчик по АвИЭС 16 | FF7: Подрядчик по АвИЭС 17 | FG7: Подрядчик по АвИЭС 18 | FH7: Подрядчик по АвИЭС 19 | FI7: Подрядчик по АвИЭС 20 | FJ7: Всего | FK7: Подрядчик по вырезке 1 | FL7: Подрядчик по вырезке 2 | FM7: Подрядчик по вырезке 3 | FN7: Подрядчик по вырезке 4 | FO7: Подрядчик по вырезке 5 | FP7: Подрядчик по вырезке 6 | FQ7: Подрядчик по вырезке 7 | FR7: Подрядчик по вырезке 8 | FS7: Подрядчик по вырезке 9 | FT7: Подрядчик по вырезке 10 | FU7: Подрядчик по вырезке 11 | FV7: Подрядчик по вырезке 12 | FW7: Подрядчик по вырезке 13 | FX7: Подрядчик по вырезке 14 | FY7: Подрядчик по вырезке 15 | FZ7: Подрядчик по вырезке 16 | GA7: Подрядчик по вырезке 17 | GB7: Подрядчик по вырезке 18 | GC7: Подрядчик по вырезке 19 | GD7: Подрядчик по вырезке 20 | GE7: Всего | GF7: Подрядчик по ННБ 1 | GG7: Подрядчик по ННБ 2 | GH7: Подрядчик по ННБ 3 | GI7: Подрядчик по ННБ 4 | GJ7: Подрядчик по ННБ 5 | GK7: Подрядчик по ННБ 6 | GL7: Подрядчик по ННБ 7 | GM7: Подрядчик по ННБ 8 | GN7: Подрядчик по ННБ 9 | GO7: Подрядчик по ННБ 10 | GP7: Подрядчик по ННБ 11 | GQ7: Подрядчик по ННБ 12 | GR7: Подрядчик по ННБ 13 | GS7: Подрядчик по ННБ 14 | GT7: Подрядчик по ННБ 15 | GU7: Подрядчик по ННБ 16 | GV7: Подрядчик по ННБ 17 | GW7: Подрядчик по ННБ 18 | GX7: Подрядчик по ННБ 19 | GY7: Подрядчик по ННБ 20 | GZ7: Всего | HA7: Подрядчик по ГИС 1 | HB7: Подрядчик по ГИС 2 | HC7: Подрядчик по ГИС 3 | HD7: Подрядчик по ГИС 4 | HE7: Подрядчик по ГИС 5 | HF7: Подрядчик по ГИС 6 | HG7: Подрядчик по ГИС 7 | HH7: Подрядчик по ГИС 8 | HI7: Подрядчик по ГИС 9 | HJ7: Подрядчик по ГИС 10 | HK7: Подрядчик по ГИС 11 | HL7: Подрядчик по ГИС 12 | HM7: Подрядчик по ГИС 13 | HN7: Подрядчик по ГИС 14 | HO7: Подрядчик по ГИС 15 | HP7: Подрядчик по ГИС 16 | HQ7: Подрядчик по ГИС 17 | HR7: Подрядчик по ГИС 18 | HS7: Подрядчик по ГИС 19 | HT7: Подрядчик по ГИС 20 | HU7: Всего | HV7: Подрядчик по ГТИ 1 | HW7: Подрядчик по ГТИ 2 | HX7: Подрядчик по ГТИ 3 | HY7: Подрядчик по ГТИ 4 | HZ7: Подрядчик по ГТИ 5 | IA7: Подрядчик по ГТИ 6 | IB7: Подрядчик по ГТИ 7 | IC7: Подрядчик по ГТИ 8 | ID7: Подрядчик по ГТИ 9 | IE7: Подрядчик по ГТИ 10 | IF7: Подрядчик по ГТИ 11 | IG7: Подрядчик по ГТИ 12 | IH7: Подрядчик по ГТИ 13 | II7: Подрядчик по ГТИ 14 | IJ7: Подрядчик по ГТИ 15 | IK7: Подрядчик по ГТИ 16 | IL7: Подрядчик по ГТИ 17 | IM7: Подрядчик по ГТИ 18 | IN7: Подрядчик по ГТИ 19 | IO7: Подрядчик по ГТИ 20 | IP7: Всего | IQ7: Подрядчик по Цементированию 1 | IR7: Подрядчик по Цементированию 2 | IS7: Подрядчик по Цементированию 3 | IT7: Подрядчик по Цементированию 4 | IU7: Подрядчик по Цементированию 5 | IV7: Подрядчик по Цементированию 6 | IW7: Подрядчик по Цементированию 7 | IX7: Подрядчик по Цементированию 8 | IY7: Подрядчик по Цементированию 9 | IZ7: Подрядчик по Цементированию 10 | JA7: Подрядчик по Цементированию 11 | JB7: Подрядчик по Цементированию 12 | JC7: Подрядчик по Цементированию 13 | JD7: Подрядчик по Цементированию 14 | JE7: Подрядчик по Цементированию 15 | JF7: Подрядчик по Цементированию 16 | JG7: Подрядчик по Цементированию 17 | JH7: Подрядчик по Цементированию 18 | JI7: Подрядчик по Цементированию 19 | JJ7: Подрядчик по Цементированию 20 | JK7: Всего | JL7: Подрядчик по растворам 1 | JM7: Подрядчик по растворам 2 | JN7: Подрядчик по растворам 3 | JO7: Подрядчик по растворам 4 | JP7: Подрядчик по растворам 5 | JQ7: Подрядчик по растворам 6 | JR7: Подрядчик по растворам 7 | JS7: Подрядчик по растворам 8 | JT7: Подрядчик по растворам 9 | JU7: Подрядчик по растворам 10 | JV7: Подрядчик по растворам 11 | JW7: Подрядчик по растворам 12 | JX7: Подрядчик по растворам 13 | JY7: Подрядчик по растворам 14 | JZ7: Подрядчик по растворам 15 | KA7: Подрядчик по растворам 16 | KB7: Подрядчик по растворам 17 | KC7: Подрядчик по растворам 18 | KD7: Подрядчик по растворам 19 | KE7: Подрядчик по растворам 20 | KF7: Всего | KG7: Подрядчик по Долотному сервису 1 | KH7: Подрядчик по Долотному сервису 2 | KI7: Подрядчик по Долотному сервису 3 | KJ7: Подрядчик по Долотному сервису 4 | KK7: Подрядчик по Долотному сервису 5 | KL7: Подрядчик по Долотному сервису 6 | KM7: Подрядчик по Долотному сервису 7 | KN7: Подрядчик по Долотному сервису 8 | KO7: Подрядчик по Долотному сервису 9 | KP7: Подрядчик по Долотному сервису 10 | KQ7: Подрядчик по Долотному сервису 11 | KR7: Подрядчик по Долотному сервису 12 | KS7: Подрядчик по Долотному сервису 13 | KT7: Подрядчик по Долотному сервису 14 | KU7: Подрядчик по Долотному сервису 15 | KV7: Подрядчик по Долотному сервису 16 | KW7: Подрядчик по Долотному сервису 17 | KX7: Подрядчик по Долотному сервису 18 | KY7: Подрядчик по Долотному сервису 19 | KZ7: Подрядчик по Долотному сервису 20 | LA7: Всего | LB7: Подрядчик по Отбору керна 1 | LC7: Подрядчик по Отбору керна 2 | LD7: Подрядчик по Отбору керна 3 | LE7: Подрядчик по Отбору керна 4 | LF7: Подрядчик по Отбору керна 5 | LG7: Подрядчик по Отбору керна 6 | LH7: Подрядчик по Отбору керна 7 | LI7: Подрядчик по Отбору керна 8 | LJ7: Подрядчик по Отбору керна 9 | LK7: Подрядчик по Отбору керна 10 | LL7: Подрядчик по Отбору керна 11 | LM7: Подрядчик по Отбору керна 12 | LN7: Подрядчик по Отбору керна 13 | LO7: Подрядчик по Отбору керна 14 | LP7: Подрядчик по Отбору керна 15 | LQ7: Подрядчик по Отбору керна 16 | LR7: Подрядчик по Отбору керна 17 | LS7: Подрядчик по Отбору керна 18 | LT7: Подрядчик по Отбору керна 19 | LU7: Подрядчик по Отбору керна 20 | LV7: Всего | LW7: Подрядчик по Хвостовикам 1 | LX7: Подрядчик по Хвостовикам 2 | LY7: Подрядчик по Хвостовикам 3 | LZ7: Подрядчик по Хвостовикам 4 | MA7: Подрядчик по Хвостовикам 5 | MB7: Подрядчик по Хвостовикам 6 | MC7: Подрядчик по Хвостовикам 7 | MD7: Подрядчик по Хвостовикам 8 | ME7: Подрядчик по Хвостовикам 9 | MF7: Подрядчик по Хвостовикам 10 | MG7: Подрядчик по Хвостовикам 11 | MH7: Подрядчик по Хвостовикам 12 | MI7: Подрядчик по Хвостовикам 13 | MJ7: Подрядчик по Хвостовикам 14 | MK7: Подрядчик по Хвостовикам 15 | ML7: Подрядчик по Хвостовикам 16 | MM7: Подрядчик по Хвостовикам 17 | MN7: Подрядчик по Хвостовикам 18 | MO7: Подрядчик по Хвостовикам 19 | MP7: Подрядчик по Хвостовикам 20 | MQ7: Всего | MR7: Подрядчик по Шламу 1 | MS7: Подрядчик по Шламу 2 | MT7: Подрядчик по Шламу 3 | MU7: Подрядчик по Шламу 4 | MV7: Подрядчик по Шламу 5 | MW7: Подрядчик по Шламу 6 | MX7: Подрядчик по Шламу 7 | MY7: Подрядчик по Шламу 8 | MZ7: Подрядчик по Шламу 9 | NA7: Подрядчик по Шламу 10 | NB7: Подрядчик по Шламу 11 | NC7: Подрядчик по Шламу 12 | ND7: Подрядчик по Шламу 13 | NE7: Подрядчик по Шламу 14 | NF7: Подрядчик по Шламу 15 | NG7: Подрядчик по Шламу 16 | NH7: Подрядчик по Шламу 17 | NI7: Подрядчик по Шламу 18 | NJ7: Подрядчик по Шламу 19 | NK7: Подрядчик по Шламу 20 | NL7: Всего | NM7: Подрядчик по Супервайзингу 1 | NN7: Подрядчик по Супервайзингу 2 | NO7: Подрядчик по Супервайзингу 3 | NP7: Подрядчик по Супервайзингу 4 | NQ7: Подрядчик по Супервайзингу 5 | NR7: Подрядчик по Супервайзингу 6 | NS7: Подрядчик по Супервайзингу 7 | NT7: Подрядчик по Супервайзингу 8 | NU7: Подрядчик по Супервайзингу 9 | NV7: Подрядчик по Супервайзингу 10 | NW7: Подрядчик по Супервайзингу 11 | NX7: Подрядчик по Супервайзингу 12 | NY7: Подрядчик по Супервайзингу 13 | NZ7: Подрядчик по Супервайзингу 14 | OA7: Подрядчик по Супервайзингу 15 | OB7: Подрядчик по Супервайзингу 16 | OC7: Подрядчик по Супервайзингу 17 | OD7: Подрядчик по Супервайзингу 18 | OE7: Подрядчик по Супервайзингу 19 | OF7: Подрядчик по Супервайзингу 20 | OG7: Всего | OH7: Обсадные колонны (в т.ч. оснастка) | OI7: Услуги УМТС (ТЗР на обсадные колонны) | OJ7: Дизтопливо | OK7: Услуги УМТС (ТЗР на дизтопливо) | OL7: Цемент | OM7: Услуги УМТС (ТЗР цемент) | ON7: Протектор (ГПН-Восток) | OO7: Услуги УМТС (ТЗР на протектор) | OP7: Галит (Хантос) | OQ7: Услуги УМТС (ТЗР на галит) | OR7: Нефть на техничекие нужны | OS7: прочее | OT7: прочее | OU7: прочее | OV7: прочее | OW7: прочее | OX7: прочее | OY7: прочее | OZ7: прочее | PA7: прочее | PB7: Всего | PE7: Подрядчик по Консультационным услугам 1 | PF7: Подрядчик по Консультационным услугам 2 | PG7: Подрядчик по Консультационным услугам 3 | PH7: Подрядчик по Консультационным услугам 4 | PI7: Подрядчик по Консультационным услугам 5 | PJ7: Подрядчик по Консультационным услугам 6 | PK7: Подрядчик по Консультационным услугам 7 | PL7: Подрядчик по Консультационным услугам 8 | PM7: Подрядчик по Консультационным услугам 9 | PN7: Подрядчик по Консультационным услугам 10 | PO7: Подрядчик по Консультационным услугам 11 | PP7: Подрядчик по Консультационным услугам 12 | PQ7: Подрядчик по Консультационным услугам 13 | PR7: Подрядчик по Консультационным услугам 14 | PS7: Подрядчик по Консультационным услугам 15 | PT7: Подрядчик по Консультационным услугам 16 | PU7: Подрядчик по Консультационным услугам 17 | PV7: Подрядчик по Консультационным услугам 18 | PW7: Подрядчик по Консультационным услугам 19 | PX7: Подрядчик по Консультационным услугам 20 | PY7: Всего | QA7: Подрядчик по Проектной док-ии 1 | QB7: Подрядчик по Проектной док-ии 2 | QC7: Подрядчик по Проектной док-ии 3 | QD7: Подрядчик по Проектной док-ии 4 | QE7: Подрядчик по Проектной док-ии 5 | QF7: Подрядчик по Проектной док-ии 6 | QG7: Подрядчик по Проектной док-ии 7 | QH7: Подрядчик по Проектной док-ии 8 | QI7: Подрядчик по Проектной док-ии 9 | QJ7: Подрядчик по Проектной док-ии 10 | QK7: Подрядчик по Проектной док-ии 11 | QL7: Подрядчик по Проектной док-ии 12 | QM7: Подрядчик по Проектной док-ии 13 | QN7: Подрядчик по Проектной док-ии 14 | QO7: Подрядчик по Проектной док-ии 15 | QP7: Подрядчик по Проектной док-ии 16 | QQ7: Подрядчик по Проектной док-ии 17 | QR7: Подрядчик по Проектной док-ии 18 | QS7: Подрядчик по Проектной док-ии 19 | QT7: Подрядчик по Проектной док-ии 20 | QU7: Всего | QX7: Подрядчик по Освоению 1 | QY7: Подрядчик по Освоению 2 | QZ7: Подрядчик по Освоению 3 | RA7: Подрядчик по Освоению 4 | RB7: Подрядчик по Освоению 5 | RC7: Подрядчик по Освоению 6 | RD7: Подрядчик по Освоению 7 | RE7: Подрядчик по Освоению 8 | RF7: Подрядчик по Освоению 9 | RG7: Подрядчик по Освоению 10 | RH7: Подрядчик по Освоению 11 | RI7: Подрядчик по Освоению 12 | RJ7: Подрядчик по Освоению 13 | RK7: Подрядчик по Освоению 14 | RL7: Подрядчик по Освоению 15 | RM7: Подрядчик по Освоению 16 | RN7: Подрядчик по Освоению 17 | RO7: Подрядчик по Освоению 18 | RP7: Подрядчик по Освоению 19 | RQ7: Подрядчик по Освоению 20 | RR7: Всего | RS7: Подрядчик по Освоению стр.насосами 1 | RT7: Подрядчик по Освоению стр.насосами 2 | RU7: Подрядчик по Освоению стр.насосами 3 | RV7: Подрядчик по Освоению стр.насосами 4 | RW7: Подрядчик по Освоению стр.насосами 5 | RX7: Подрядчик по Освоению стр.насосами 6 | RY7: Подрядчик по Освоению стр.насосами 7 | RZ7: Подрядчик по Освоению стр.насосами 8 | SA7: Подрядчик по Освоению стр.насосами 9 | SB7: Подрядчик по Освоению стр.насосами 10 | SC7: Подрядчик по Освоению стр.насосами 11 | SD7: Подрядчик по Освоению стр.насосами 12 | SE7: Подрядчик по Освоению стр.насосами 13 | SF7: Подрядчик по Освоению стр.насосами 14 | SG7: Подрядчик по Освоению стр.насосами 15 | SH7: Подрядчик по Освоению стр.насосами 16 | SI7: Подрядчик по Освоению стр.насосами 17 | SJ7: Подрядчик по Освоению стр.насосами 18 | SK7: Подрядчик по Освоению стр.насосами 19 | SL7: Подрядчик по Освоению стр.насосами 20 | SM7: Всего | SN7: Подрядчик по Глушению, ОПЗ и проч 1 | SO7: Подрядчик по Глушению, ОПЗ и проч 2 | SP7: Подрядчик по Глушению, ОПЗ и проч 3 | SQ7: Подрядчик по Глушению, ОПЗ и проч 4 | SR7: Подрядчик по Глушению, ОПЗ и проч 5 | SS7: Подрядчик по Глушению, ОПЗ и проч 6 | ST7: Подрядчик по Глушению, ОПЗ и проч 7 | SU7: Подрядчик по Глушению, ОПЗ и проч 8 | SV7: Подрядчик по Глушению, ОПЗ и проч 9 | SW7: Подрядчик по Глушению, ОПЗ и проч 10 | SX7: Подрядчик по Глушению, ОПЗ и проч 11 | SY7: Подрядчик по Глушению, ОПЗ и проч 12 | SZ7: Подрядчик по Глушению, ОПЗ и проч 13 | TA7: Подрядчик по Глушению, ОПЗ и проч 14 | TB7: Подрядчик по Глушению, ОПЗ и проч 15 | TC7: Подрядчик по Глушению, ОПЗ и проч 16 | TD7: Подрядчик по Глушению, ОПЗ и проч 17 | TE7: Подрядчик по Глушению, ОПЗ и проч 18 | TF7: Подрядчик по Глушению, ОПЗ и проч 19 | TG7: Подрядчик по Глушению, ОПЗ и проч 20 | TH7: Всего | TI7: Подрядчик по ГИС при освоении 1 | TJ7: Подрядчик по ГИС при освоении 2 | TK7: Подрядчик по ГИС при освоении 3 | TL7: Подрядчик по ГИС при освоении 4 | TM7: Подрядчик по ГИС при освоении 5 | TN7: Подрядчик по ГИС при освоении 6 | TO7: Подрядчик по ГИС при освоении 7 | TP7: Подрядчик по ГИС при освоении 8 | TQ7: Подрядчик по ГИС при освоении 9 | TR7: Подрядчик по ГИС при освоении 10 | TS7: Подрядчик по ГИС при освоении 11 | TT7: Подрядчик по ГИС при освоении 12 | TU7: Подрядчик по ГИС при освоении 13 | TV7: Подрядчик по ГИС при освоении 14 | TW7: Подрядчик по ГИС при освоении 15 | TX7: Подрядчик по ГИС при освоении 16 | TY7: Подрядчик по ГИС при освоении 17 | TZ7: Подрядчик по ГИС при освоении 18 | UA7: Подрядчик по ГИС при освоении 19 | UB7: Подрядчик по ГИС при освоении 20 | UC7: Всего | UD7: Подрядчик по ГРП 1 | UE7: Подрядчик по ГРП 2 | UF7: Подрядчик по ГРП 3 | UG7: Подрядчик по ГРП 4 | UH7: Подрядчик по ГРП 5 | UI7: Подрядчик по ГРП 6 | UJ7: Подрядчик по ГРП 7 | UK7: Подрядчик по ГРП 8 | UL7: Подрядчик по ГРП 9 | UM7: Подрядчик по ГРП 10 | UN7: Подрядчик по ГРП 11 | UO7: Подрядчик по ГРП 12 | UP7: Подрядчик по ГРП 13 | UQ7: Подрядчик по ГРП 14 | UR7: Подрядчик по ГРП 15 | US7: Подрядчик по ГРП 16 | UT7: Подрядчик по ГРП 17 | UU7: Подрядчик по ГРП 18 | UV7: Подрядчик по ГРП 19 | UW7: Подрядчик по ГРП 20 | UX7: Всего | UY7: Подрядчик по ГНКТ 1 | UZ7: Подрядчик по ГНКТ 2 | VA7: Подрядчик по ГНКТ 3 | VB7: Подрядчик по ГНКТ 4 | VC7: Подрядчик по ГНКТ 5 | VD7: Подрядчик по ГНКТ 6 | VE7: Подрядчик по ГНКТ 7 | VF7: Подрядчик по ГНКТ 8 | VG7: Подрядчик по ГНКТ 9 | VH7: Подрядчик по ГНКТ 10 | VI7: Подрядчик по ГНКТ 11 | VJ7: Подрядчик по ГНКТ 12 | VK7: Подрядчик по ГНКТ 13 | VL7: Подрядчик по ГНКТ 14 | VM7: Подрядчик по ГНКТ 15 | VN7: Подрядчик по ГНКТ 16 | VO7: Подрядчик по ГНКТ 17 | VP7: Подрядчик по ГНКТ 18 | VQ7: Подрядчик по ГНКТ 19 | VR7: Подрядчик по ГНКТ 20 | VS7: Всего | VT7: Техн.жидкость глушения | VU7: Услуги УМТС (ТЗР на жидкость глушения) | VV7: Хим. реагенты | VW7: Услуги УМТС (ТЗР хим. реагенты) | VX7: Кварцевый песок | VY7: Услуги УМТС (ТЗР на кварцевый песок) | VZ7: Проппант | WA7: Услуги УМТС (ТЗР на проппант) | WB7: Кислота | WC7: Услуги УМТС (ТЗР на кислоту) | WD7: Пакер (ГПН-Восток) | WE7: Услуги УМТС (ТЗР на пакер) | WF7: прочее | WG7: прочее | WH7: прочее | WI7: прочее | WJ7: прочее | WK7: прочее | WL7: прочее | WM7: прочее | WN7: Всего | WO7: Подрядчик по Супервайзингу при освоении 1 | WP7: Подрядчик по Супервайзингу при освоении 2 | WQ7: Подрядчик по Супервайзингу при освоении 3 | WR7: Подрядчик по Супервайзингу при освоении 4 | WS7: Подрядчик по Супервайзингу при освоении 5 | WT7: Подрядчик по Супервайзингу при освоении 6 | WU7: Подрядчик по Супервайзингу при освоении 7 | WV7: Подрядчик по Супервайзингу при освоении 8 | WW7: Подрядчик по Супервайзингу при освоении 9 | WX7: Подрядчик по Супервайзингу при освоении 10 | WY7: Подрядчик по Супервайзингу при освоении 11 | WZ7: Подрядчик по Супервайзингу при освоении 12 | XA7: Подрядчик по Супервайзингу при освоении 13 | XB7: Подрядчик по Супервайзингу при освоении 14 | XC7: Подрядчик по Супервайзингу при освоении 15 | XD7: Подрядчик по Супервайзингу при освоении 16 | XE7: Подрядчик по Супервайзингу при освоении 17 | XF7: Подрядчик по Супервайзингу при освоении 18 | XG7: Подрядчик по Супервайзингу при освоении 19 | XH7: Подрядчик по Супервайзингу при освоении 20 | XI7: Всего | XK7: ФА | XL7: НКТ | XM7: Прочее | XN7: Прочее | XO7: Прочее | XP7: Всего | XQ7: Подрядчик по подготовке площадки 1 | XR7: Подрядчик по подготовке площадки 2 | XS7: Подрядчик по подготовке площадки 3 | XT7: Подрядчик по подготовке площадки 4 | XU7: Подрядчик по подготовке площадки 5 | XV7: Подрядчик по подготовке площадки 6 | XW7: Подрядчик по подготовке площадки 7 | XX7: Подрядчик по подготовке площадки 8 | XY7: Подрядчик по подготовке площадки 9 | XZ7: Подрядчик по подготовке площадки 10 | YA7: Подрядчик по подготовке площадки 11 | YB7: Подрядчик по подготовке площадки 12 | YC7: Подрядчик по подготовке площадки 13 | YD7: Подрядчик по подготовке площадки 14 | YE7: Всего
A8: 1 | B8: =A8+1 -> 2 | C8: =B8+1 -> 3 | D8: =C8+1 -> 4 | E8: =D8+1 -> 5 | F8: =E8+1 -> 6 | G8: =F8+1 -> 7 | H8: =G8+1 -> 8 | I8: =H8+1 -> 9 | ... YE8: =YD8+1 -> 655 | YF8: =XJ8+1 -> 635
B9: После занесения месторождения в справочник, необходимо выбрать из списка | E9: Под автономностью понимается отсутствие подключения к высоковольтным линиям централизованного электроснабжения во время бурения Да - Наличие автономии Нет - Отсутствие автономии | F9: Под автономностью понимается отсутствие проезда к месторождению / участку месторождения наземным транспортом в течение более 6 месяцев в году Да - Наличие автономии Нет - Отсутствие автономии | Q9: Заполняется по всем скважинам на отчетную дату | R9: Включает пилотный ствол и перебур по геологии | S9: Длина участка, который не входит в протяженность ствола действующей скважины, планового пилотного ствола или перебура ("перебуры по технологии" не включаются). Указать сумму длин при наличии 2х и более пилотных стволов и/или перебуров | AC9: От устья до забоя, в т.ч. по ГС | AR9: С момента спуска первого инструмента КНБК | AS9: Если скважина не введена в эксплуатацию (напр. "сухая" скважина, переведенная в пьезометр.), указывается дата окончания строительства по КС | AV9: Только для скважин, законченных бурением | BE9: Если скважина является переходящей, то в графе "дата окончания " прописывается "перех" | BN9: Амбарное/ Без амбарное | CK9: Указывается расстояние | CL9: При наличчи, указывается расстояние между кустами | CM9: При наличии, указывается длина передвижки от скважины к скважин на одном кусту | CN9: Указывается кол-во | CO9: Указывается кол-во | CP9: Указывается кол-во | CQ9: Заполняется только для переездов и мобилизации Да Нет | CY9: Комулятивная, щелевая, отсутствует | CZ9: Весь объем проппанта по всем проводимым при освоении ГРП на скважине | DD9: Указывается подрядчик, выполняющий подгот. работы (после занесения подрядчика в справочник, необходимо выбрать из списка) | DF9: Указывается подрядчик, выполняющий ВМР (после занесения подрядчика в справочник, необходимо выбрать из списка) | DK9: Включает в себя монтаж БУ, ПНР, бур.вод.колодца, монтаж АвИЭС и проч.оборуд. | DL9: Включает в себя стаскивание и демонтаж БУ, ликв.вод.колодца, демонтаж АвИЭС и проч.оборуд. | GZ9: Стоимость аренды оборудования и услуг соответствующего персонала для направленного бурения, услуги ГИС/измерений во время бурения (MWD, LWD и услуги персонала) | HU9: ГИС на кабеле (инструменте) и другие виды ГИС, проводимые не в процессе бурения (при этом в рамках цикла бурения, не включая ГИС при освоении) | IP9: Все геолого-технические, геолого-геохимические исследования во время бурения (газо-каротаж) | JK9: Включая цемент и услуги по цементированию | KF9: Включая хим. реагенты и добавки для раствора | LA9: Включая долота и прочие материалы связанные с долотным сервисом | NL9: Включая вывоз, переработка и утилизация буровых отходов | OH9: Стоимость обсадной трубы (включая стоимость хвостовиков) на складе предприятия, без затрат доставки до куста и ПРР на кусту | QV9: Все затраты, не отнесенные ни в одну из предложенных статей, но относящиеся к бурению скважин, включая затраты УСС | RR9: Включая оплаченные простои | UC9: Включая свабирование, сопровождение компрессирования, и др. возможные работы. | UX9: Всего затраты подрядчика на проведение всех проппантных ГРП при освоении скважины без учета стоимости пропанта | XJ9: Прокат оборудования, транспорт и т.п.
A10: № п/п | B10: Выбрать из списка | C10: текст | D10: текст | E10: Выбрать из списка | F10: Выбрать из списка | G10: Выбрать из списка | H10: Выбрать из списка | I10: Выбрать из списка | J10: Выбрать из списка | K10: Выбрать из списка | L10: Выбрать из списка | M10: Выбрать из списка | N10: Выбрать из списка | O10: Выбрать из списка | P10: Выбрать из списка | Q10: м | R10: м | S10: м | U10: м | V10: м | W10: м | Y10: м | Z10: м | AA10: м | AB10: м | AC10: м | AD10: м | AE10: м | AF10: м | AG10: м | AH10: м | AI10: м | AJ10: м | AK10: мм | AL10: мм | AM10: мм | AN10: мм | AO10: мм | AP10: мм | AQ10: м | AR10: ДД.ММ.ГГ | AS10: ДД.ММ.ГГ | AT10: ДД.ММ.ГГ | AU10: 00:00 | AV10: ДД.ММ.ГГ | AW10: 00:00 | AX10: сут | AY10: сут | AZ10: сут | BA10: сут | BB10: сут | BC10: сут | BD10: ДД.ММ.ГГ | BE10: ДД.ММ.ГГ | BF10: сут | BG10: сут | BH10: сут | BI10: сут | BJ10: сут | BK10: сут | BL10: ДД.ММ.ГГ | BM10: сут | BN10: Выбрать из списка | BO10: текст | BP10: Выбрать из списка | BQ10: тн | BR10: шт | BS10: Выбрать из списка | BT10: Текст | BU10: шт | BV10: Текст | BW10: шт | BX10: Выбрать из списка | BY10: Выбрать из списка | BZ10: Выбрать из списка | CA10: Выбрать из списка | CB10: Выбрать из списка | CC10: Выбрать из списка | CD10: Выбрать из списка | CE10: Выбрать из списка | CF10: Выбрать из списка | CG10: Выбрать из списка | CH10: Выбрать из списка | CI10: Выбрать из списка | CJ10: Выбрать из списка | CK10: км | CL10: км | CM10: м | CN10: Кол-во, Шт. | CO10: Кол-во, Шт. | CP10: Кол-во, Шт. | CQ10: Да = 1 | CR10: сут | CS10: сут | CT10: сут | CU10: сут | CV10: сут | CW10: сут | CX10: м | CY10: текст (Выбрать из списка) | CZ10: тн | DA10: тн | DB10: тн/сут | DC10: руб. | DD10: текст (Выбрать из списка) | DE10: руб. | DF10: текст (Выбрать из списка) | DG10: руб. | DH10: руб. | DI10: руб. | DJ10: руб. | DK10: руб. | DL10: руб. | DM10: руб. | DN10: руб. | DO10: руб. | DP10: руб. | DQ10: руб. | DR10: руб. | DS10: руб. | DT10: руб. | DU10: руб. | DV10: руб. | DW10: руб. | DX10: руб. | DY10: руб. | DZ10: руб. | EA10: руб. | EB10: руб. | EC10: руб. | ED10: руб. | EE10: руб. | EF10: руб. | EG10: руб. | EH10: руб. | EI10: руб. | EJ10: руб. | EK10: руб. | EL10: руб. | EM10: руб. | EN10: руб. | EO10: руб. | EP10: руб. | EQ10: руб. | ER10: руб. | ES10: руб. | ET10: руб. | EU10: руб. | EV10: руб. | EW10: руб. | EX10: руб. | EY10: руб. | EZ10: руб. | FA10: руб. | FB10: руб. | FC10: руб. | FD10: руб. | FE10: руб. | FF10: руб. | FG10: руб. | FH10: руб. | FI10: руб. | FJ10: руб. | FK10: руб. | FL10: руб. | FM10: руб. | FN10: руб. | FO10: руб. | FP10: руб. | FQ10: руб. | FR10: руб. | FS10: руб. | FT10: руб. | FU10: руб. | FV10: руб. | FW10: руб. | FX10: руб. | FY10: руб. | FZ10: руб. | GA10: руб. | GB10: руб. | GC10: руб. | GD10: руб. | GE10: руб. | GF10: руб. | GG10: руб. | GH10: руб. | GI10: руб. | GJ10: руб. | GK10: руб. | GL10: руб. | GM10: руб. | GN10: руб. | GO10: руб. | GP10: руб. | GQ10: руб. | GR10: руб. | GS10: руб. | GT10: руб. | GU10: руб. | GV10: руб. | GW10: руб. | GX10: руб. | GY10: руб. | GZ10: руб. | HA10: руб. | HB10: руб. | HC10: руб. | HD10: руб. | HE10: руб. | HF10: руб. | HG10: руб. | HH10: руб. | HI10: руб. | HJ10: руб. | HK10: руб. | HL10: руб. | HM10: руб. | HN10: руб. | HO10: руб. | HP10: руб. | HQ10: руб. | HR10: руб. | HS10: руб. | HT10: руб. | HU10: руб. | HV10: руб. | HW10: руб. | HX10: руб. | HY10: руб. | HZ10: руб. | IA10: руб. | IB10: руб. | IC10: руб. | ID10: руб. | IE10: руб. | IF10: руб. | IG10: руб. | IH10: руб. | II10: руб. | IJ10: руб. | IK10: руб. | IL10: руб. | IM10: руб. | IN10: руб. | IO10: руб. | IP10: руб. | IQ10: руб. | IR10: руб. | IS10: руб. | IT10: руб. | IU10: руб. | IV10: руб. | IW10: руб. | IX10: руб. | IY10: руб. | IZ10: руб. | JA10: руб. | JB10: руб. | JC10: руб. | JD10: руб. | JE10: руб. | JF10: руб. | JG10: руб. | JH10: руб. | JI10: руб. | JJ10: руб. | JK10: руб. | JL10: руб. | JM10: руб. | JN10: руб. | JO10: руб. | JP10: руб. | JQ10: руб. | JR10: руб. | JS10: руб. | JT10: руб. | JU10: руб. | JV10: руб. | JW10: руб. | JX10: руб. | JY10: руб. | JZ10: руб. | KA10: руб. | KB10: руб. | KC10: руб. | KD10: руб. | KE10: руб. | KF10: руб. | KG10: руб. | KH10: руб. | KI10: руб. | KJ10: руб. | KK10: руб. | KL10: руб. | KM10: руб. | KN10: руб. | KO10: руб. | KP10: руб. | KQ10: руб. | KR10: руб. | KS10: руб. | KT10: руб. | KU10: руб. | KV10: руб. | KW10: руб. | KX10: руб. | KY10: руб. | KZ10: руб. | LA10: руб. | LB10: руб. | LC10: руб. | LD10: руб. | LE10: руб. | LF10: руб. | LG10: руб. | LH10: руб. | LI10: руб. | LJ10: руб. | LK10: руб. | LL10: руб. | LM10: руб. | LN10: руб. | LO10: руб. | LP10: руб. | LQ10: руб. | LR10: руб. | LS10: руб. | LT10: руб. | LU10: руб. | LV10: руб. | LW10: руб. | LX10: руб. | LY10: руб. | LZ10: руб. | MA10: руб. | MB10: руб. | MC10: руб. | MD10: руб. | ME10: руб. | MF10: руб. | MG10: руб. | MH10: руб. | MI10: руб. | MJ10: руб. | MK10: руб. | ML10: руб. | MM10: руб. | MN10: руб. | MO10: руб. | MP10: руб. | MQ10: руб. | MR10: руб. | MS10: руб. | MT10: руб. | MU10: руб. | MV10: руб. | MW10: руб. | MX10: руб. | MY10: руб. | MZ10: руб. | NA10: руб. | NB10: руб. | NC10: руб. | ND10: руб. | NE10: руб. | NF10: руб. | NG10: руб. | NH10: руб. | NI10: руб. | NJ10: руб. | NK10: руб. | NL10: руб. | NM10: руб. | NN10: руб. | NO10: руб. | NP10: руб. | NQ10: руб. | NR10: руб. | NS10: руб. | NT10: руб. | NU10: руб. | NV10: руб. | NW10: руб. | NX10: руб. | NY10: руб. | NZ10: руб. | OA10: руб. | OB10: руб. | OC10: руб. | OD10: руб. | OE10: руб. | OF10: руб. | OG10: руб. | OH10: руб. | OI10: руб. | OJ10: руб. | OK10: руб. | OL10: руб. | OM10: руб. | ON10: руб. | OO10: руб. | OP10: руб. | OQ10: руб. | OR10: руб. | OS10: руб. | PB10: руб. | PC10: руб. | PD10: руб. | PE10: руб. | PF10: руб. | PG10: руб. | PH10: руб. | PI10: руб. | PJ10: руб. | PK10: руб. | PL10: руб. | PM10: руб. | PN10: руб. | PO10: руб. | PP10: руб. | PQ10: руб. | PR10: руб. | PS10: руб. | PT10: руб. | PU10: руб. | PV10: руб. | PW10: руб. | PX10: руб. | PY10: руб. | PZ10: руб. | QA10: руб. | QB10: руб. | QC10: руб. | QD10: руб. | QE10: руб. | QF10: руб. | QG10: руб. | QH10: руб. | QI10: руб. | QJ10: руб. | QK10: руб. | QL10: руб. | QM10: руб. | QN10: руб. | QO10: руб. | QP10: руб. | QQ10: руб. | QR10: руб. | QS10: руб. | QT10: руб. | QU10: руб. | QV10: руб. | QW10: руб. | QX10: руб. | QY10: руб. | QZ10: руб. | RA10: руб. | RB10: руб. | RC10: руб. | RD10: руб. | RE10: руб. | RF10: руб. | RG10: руб. | RH10: руб. | RI10: руб. | RJ10: руб. | RK10: руб. | RL10: руб. | RM10: руб. | RN10: руб. | RO10: руб. | RP10: руб. | RQ10: руб. | RR10: руб. | RS10: руб. | RT10: руб. | RU10: руб. | RV10: руб. | RW10: руб. | RX10: руб. | RY10: руб. | RZ10: руб. | SA10: руб. | SB10: руб. | SC10: руб. | SD10: руб. | SE10: руб. | SF10: руб. | SG10: руб. | SH10: руб. | SI10: руб. | SJ10: руб. | SK10: руб. | SL10: руб. | SM10: руб. | SN10: руб. | SO10: руб. | SP10: руб. | SQ10: руб. | SR10: руб. | SS10: руб. | ST10: руб. | SU10: руб. | SV10: руб. | SW10: руб. | SX10: руб. | SY10: руб. | SZ10: руб. | TA10: руб. | TB10: руб. | TC10: руб. | TD10: руб. | TE10: руб. | TF10: руб. | TG10: руб. | TH10: руб. | TI10: руб. | TJ10: руб. | TK10: руб. | TL10: руб. | TM10: руб. | TN10: руб. | TO10: руб. | TP10: руб. | TQ10: руб. | TR10: руб. | TS10: руб. | TT10: руб. | TU10: руб. | TV10: руб. | TW10: руб. | TX10: руб. | TY10: руб. | TZ10: руб. | UA10: руб. | UB10: руб. | UC10: руб. | UD10: руб. | UE10: руб. | UF10: руб. | UG10: руб. | UH10: руб. | UI10: руб. | UJ10: руб. | UK10: руб. | UL10: руб. | UM10: руб. | UN10: руб. | UO10: руб. | UP10: руб. | UQ10: руб. | UR10: руб. | US10: руб. | UT10: руб. | UU10: руб. | UV10: руб. | UW10: руб. | UX10: руб. | UY10: руб. | UZ10: руб. | VA10: руб. | VB10: руб. | VC10: руб. | VD10: руб. | VE10: руб. | VF10: руб. | VG10: руб. | VH10: руб. | VI10: руб. | VJ10: руб. | VK10: руб. | VL10: руб. | VM10: руб. | VN10: руб. | VO10: руб. | VP10: руб. | VQ10: руб. | VR10: руб. | VS10: руб. | VT10: руб. | VU10: руб. | VV10: руб. | VW10: руб. | VX10: руб. | VY10: руб. | VZ10: руб. | WA10: руб. | WB10: руб. | WC10: руб. | WF10: руб. | WN10: руб. | WO10: руб. | WP10: руб. | WQ10: руб. | WR10: руб. | WS10: руб. | WT10: руб. | WU10: руб. | WV10: руб. | WW10: руб. | WX10: руб. | WY10: руб. | WZ10: руб. | XA10: руб. | XB10: руб. | XC10: руб. | XD10: руб. | XE10: руб. | XF10: руб. | XG10: руб. | XH10: руб. | XI10: руб. | XJ10: руб. | XK10: руб. | XL10: руб. | XM10: руб. | XN10: руб. | XO10: руб. | XP10: руб. | XQ10: руб. | XR10: руб. | XS10: руб. | XT10: руб. | XU10: руб. | XV10: руб. | XW10: руб. | XX10: руб. | XY10: руб. | XZ10: руб. | YA10: руб. | YB10: руб. | YC10: руб. | YD10: руб. | YE10: руб. | YF10: Текст
A11: 1 | B11: БННС | C11: БННС | D11: =COUNTIF('Полная ст-ть с уч.НЗС (Авто)'!$YO$11:INDIRECT("'Полная ст-ть с уч.НЗС (Авто)'!YO"&$J$26),C11) -> 0 | I11: =IF($D11=0,0,SUMIF('Полная ст-ть с уч.НЗС (Авто)'!$YO$11:INDIRECT("'Полная ст-ть с уч.НЗС (Авто)'!YO"&$J$26),$C11,'Полная ст-ть с уч.НЗС (Авто)'!I$11:INDIRECT("'Полная ст-ть с уч.НЗС (Авто)'!I"&$J$26))/$D11) -> 0 | K11: =IF($D11=0,0,SUMIF('Полная ст-ть с уч.НЗС (Авто)'!$YO$11:INDIRECT("'Полная ст-ть с уч.НЗС (Авто)'!YO"&$J$26),$C11,'Полная ст-ть с уч.НЗС (Авто)'!K$11:INDIRECT("'Полная ст-ть с уч.НЗС (Авто)'!K"&$J$26))/$D11) -> 0 | M11: =IF($D11=0,0,SUMIF('Полная ст-ть с уч.НЗС (Авто)'!$YO$11:INDIRECT("'Полная ст-ть с уч.НЗС (Авто)'!YO"&$J$26),$C11,'Полная ст-ть с уч.НЗС (Авто)'!M$11:INDIRECT("'Полная ст-ть с уч.НЗС (Авто)'!M"&$J$26))/$D11) -> 0 | O11: =IF($D11=0,0,SUMIF('Полная ст-ть с уч.НЗС (Авто)'!$YO$11:INDIRECT("'Полная ст-ть с уч.НЗС (Авто)'!YO"&$J$26),$C11,'Полная ст-ть с уч.НЗС (Авто)'!O$11:INDIRECT("'Полная ст-ть с уч.НЗС (Авто)'!O"&$J$26))/$D11) -> 0 | Q11: =IF($D11=0,0,SUMIF('Полная ст-ть с уч.НЗС (Авто)'!$YO$11:INDIRECT("'Полная ст-ть с уч.НЗС (Авто)'!YO"&$J$26),$C11,'Полная ст-ть с уч.НЗС (Авто)'!Q$11:INDIRECT("'Полная ст-ть с уч.НЗС (Авто)'!Q"&$J$26))/$D11) -> 0 | R11: =IF($D11=0,0,SUMIF('Полная ст-ть с уч.НЗС (Авто)'!$YO$11:INDIRECT("'Полная ст-ть с уч.НЗС (Авто)'!YO"&$J$26),$C11,'Полная ст-ть с уч.НЗС (Авто)'!R$11:INDIRECT("'Полная ст-ть с уч.НЗС (Авто)'!R"&$J$26))/$D11) -> 0 | S11: =IF($D11=0,0,SUMIF('Полная ст-ть с уч.НЗС (Авто)'!$YO$11:INDIRECT("'Полная ст-ть с уч.НЗС (Авто)'!YO"&$J$26),$C11,'Полная ст-ть с уч.НЗС (Авто)'!S$11:INDIRECT("'Полная ст-ть с уч.НЗС (Авто)'!S"&$J$26))/$D11) -> 0 | T11: =IF($D11=0,0,SUMIF('Полная ст-ть с уч.НЗС (Авто)'!$YO$11:INDIRECT("'Полная ст-ть с уч.НЗС (Авто)'!YO"&$J$26),$C11,'Полная ст-ть с уч.НЗС (Авто)'!T$11:INDIRECT("'Полная ст-ть с уч.НЗС (Авто)'!T"&$J$26))/$D11) -> 0 | U11: =IF($D11=0,0,SUMIF('Полная ст-ть с уч.НЗС (Авто)'!$YO$11:INDIRECT("'Полная ст-ть с уч.НЗС (Авто)'!YO"&$J$26),$C11,'Полная ст-ть с уч.НЗС (Авто)'!U$11:INDIRECT("'Полная ст-ть с уч.НЗС (Авто)'!U"&$J$26))/$D11) -> 0 | V11: =IF($D11=0,0,SUMIF('Полная ст-ть с уч.НЗС (Авто)'!$YO$11:INDIRECT("'Полная ст-ть с уч.НЗС (Авто)'!YO"&$J$26),$C11,'Полная ст-ть с уч.НЗС (Авто)'!V$11:INDIRECT("'Полная ст-ть с уч.НЗС (Авто)'!V"&$J$26))/$D11) -> 0 | W11: =IF($D11=0,0,SUMIF('Полная ст-ть с уч.НЗС (Авто)'!$YO$11:INDIRECT("'Полная ст-ть с уч.НЗС (Авто)'!YO"&$J$26),$C11,'Полная ст-ть с уч.НЗС (Авто)'!W$11:INDIRECT("'Полная ст-ть с уч.НЗС (Авто)'!W"&$J$26))/$D11) -> 0 | X11: =IF($D11=0,0,SUMIF('Полная ст-ть с уч.НЗС (Авто)'!$YO$11:INDIRECT("'Полная ст-ть с уч.НЗС (Авто)'!YO"&$J$26),$C11,'Полная ст-ть с уч.НЗС (Авто)'!X$11:INDIRECT("'Полная ст-ть с уч.НЗС (Авто)'!X"&$J$26))/$D11) -> 0 | Y11: =IF($D11=0,0,SUMIF('Полная ст-ть с уч.НЗС (Авто)'!$YO$11:INDIRECT("'Полная ст-ть с уч.НЗС (Авто)'!YO"&$J$26),$C11,'Полная ст-ть с уч.НЗС (Авто)'!Y$11:INDIRECT("'Полная ст-ть с уч.НЗС (Авто)'!Y"&$J$26))/$D11) -> 0 | Z11: =IF($D11=0,0,SUMIF('Полная ст-ть с уч.НЗС (Авто)'!$YO$11:INDIRECT("'Полная ст-ть с уч.НЗС (Авто)'!YO"&$J$26),$C11,'Полная ст-ть с уч.НЗС (Авто)'!Z$11:INDIRECT("'Полная ст-ть с уч.НЗС (Авто)'!Z"&$J$26))/$D11) -> 0 | AA11: =IF($D11=0,0,SUMIF('Полная ст-ть с уч.НЗС (Авто)'!$YO$11:INDIRECT("'Полная ст-ть с уч.НЗС (Авто)'!YO"&$J$26),$C11,'Полная ст-ть с уч.НЗС (Авто)'!AA$11:INDIRECT("'Полная ст-ть с уч.НЗС (Авто)'!AA"&$J$26))/$D11) -> 0 | AB11: =IF($D11=0,0,SUMIF('Полная ст-ть с уч.НЗС (Авто)'!$YO$11:INDIRECT("'Полная ст-ть с уч.НЗС (Авто)'!YO"&$J$26),$C11,'Полная ст-ть с уч.НЗС (Авто)'!AB$11:INDIRECT("'Полная ст-ть с уч.НЗС (Авто)'!AB"&$J$26))/$D11) -> 0 | AC11: =IF($D11=0,0,SUMIF('Полная ст-ть с уч.НЗС (Авто)'!$YO$11:INDIRECT("'Полная ст-ть с уч.НЗС (Авто)'!YO"&$J$26),$C11,'Полная ст-ть с уч.НЗС (Авто)'!AC$11:INDIRECT("'Полная ст-ть с уч.НЗС (Авто)'!AC"&$J$26))/$D11) -> 0 | AD11: =IF($D11=0,0,SUMIF('Полная ст-ть с уч.НЗС (Авто)'!$YO$11:INDIRECT("'Полная ст-ть с уч.НЗС (Авто)'!YO"&$J$26),$C11,'Полная ст-ть с уч.НЗС (Авто)'!AD$11:INDIRECT("'Полная ст-ть с уч.НЗС (Авто)'!AD"&$J$26))/$D11) -> 0 | AE11: =IF($D11=0,0,SUMIF('Полная ст-ть с уч.НЗС (Авто)'!$YO$11:INDIRECT("'Полная ст-ть с уч.НЗС (Авто)'!YO"&$J$26),$C11,'Полная ст-ть с уч.НЗС (Авто)'!AE$11:INDIRECT("'Полная ст-ть с уч.НЗС (Авто)'!AE"&$J$26))/$D11) -> 0 | AF11: =IF($D11=0,0,SUMIF('Полная ст-ть с уч.НЗС (Авто)'!$YO$11:INDIRECT("'Полная ст-ть с уч.НЗС (Авто)'!YO"&$J$26),$C11,'Полная ст-ть с уч.НЗС (Авто)'!AF$11:INDIRECT("'Полная ст-ть с уч.НЗС (Авто)'!AF"&$J$26))/$D11) -> 0 | AG11: =IF($D11=0,0,SUMIF('Полная ст-ть с уч.НЗС (Авто)'!$YO$11:INDIRECT("'Полная ст-ть с уч.НЗС (Авто)'!YO"&$J$26),$C11,'Полная ст-ть с уч.НЗС (Авто)'!AG$11:INDIRECT("'Полная ст-ть с уч.НЗС (Авто)'!AG"&$J$26))/$D11) -> 0 | AH11: =IF($D11=0,0,SUMIF('Полная ст-ть с уч.НЗС (Авто)'!$YO$11:INDIRECT("'Полная ст-ть с уч.НЗС (Авто)'!YO"&$J$26),$C11,'Полная ст-ть с уч.НЗС (Авто)'!AH$11:INDIRECT("'Полная ст-ть с уч.НЗС (Авто)'!AH"&$J$26))/$D11) -> 0 | AI11: =IF($D11=0,0,SUMIF('Полная ст-ть с уч.НЗС (Авто)'!$YO$11:INDIRECT("'Полная ст-ть с уч.НЗС (Авто)'!YO"&$J$26),$C11,'Полная ст-ть с уч.НЗС (Авто)'!AI$11:INDIRECT("'Полная ст-ть с уч.НЗС (Авто)'!AI"&$J$26))/$D11) -> 0 | AJ11: =IF($D11=0,0,SUMIF('Полная ст-ть с уч.НЗС (Авто)'!$YO$11:INDIRECT("'Полная ст-ть с уч.НЗС (Авто)'!YO"&$J$26),$C11,'Полная ст-ть с уч.НЗС (Авто)'!AJ$11:INDIRECT("'Полная ст-ть с уч.НЗС (Авто)'!AJ"&$J$26))/$D11) -> 0 | AK11: =IF($D11=0,0,SUMIF('Полная ст-ть с уч.НЗС (Авто)'!$YO$11:INDIRECT("'Полная ст-ть с уч.НЗС (Авто)'!YO"&$J$26),$C11,'Полная ст-ть с уч.НЗС (Авто)'!AK$11:INDIRECT("'Полная ст-ть с уч.НЗС (Авто)'!AK"&$J$26))/$D11) -> 0 | AL11: =IF($D11=0,0,SUMIF('Полная ст-ть с уч.НЗС (Авто)'!$YO$11:INDIRECT("'Полная ст-ть с уч.НЗС (Авто)'!YO"&$J$26),$C11,'Полная ст-ть с уч.НЗС (Авто)'!AL$11:INDIRECT("'Полная ст-ть с уч.НЗС (Авто)'!AL"&$J$26))/$D11) -> 0 | AM11: =IF($D11=0,0,SUMIF('Полная ст-ть с уч.НЗС (Авто)'!$YO$11:INDIRECT("'Полная ст-ть с уч.НЗС (Авто)'!YO"&$J$26),$C11,'Полная ст-ть с уч.НЗС (Авто)'!AM$11:INDIRECT("'Полная ст-ть с уч.НЗС (Авто)'!AM"&$J$26))/$D11) -> 0 | AN11: =IF($D11=0,0,SUMIF('Полная ст-ть с уч.НЗС (Авто)'!$YO$11:INDIRECT("'Полная ст-ть с уч.НЗС (Авто)'!YO"&$J$26),$C11,'Полная ст-ть с уч.НЗС (Авто)'!AN$11:INDIRECT("'Полная ст-ть с уч.НЗС (Авто)'!AN"&$J$26))/$D11) -> 0 | AO11: =IF($D11=0,0,SUMIF('Полная ст-ть с уч.НЗС (Авто)'!$YO$11:INDIRECT("'Полная ст-ть с уч.НЗС (Авто)'!YO"&$J$26),$C11,'Полная ст-ть с уч.НЗС (Авто)'!AO$11:INDIRECT("'Полная ст-ть с уч.НЗС (Авто)'!AO"&$J$26))/$D11) -> 0 | AP11: =IF($D11=0,0,SUMIF('Полная ст-ть с уч.НЗС (Авто)'!$YO$11:INDIRECT("'Полная ст-ть с уч.НЗС (Авто)'!YO"&$J$26),$C11,'Полная ст-ть с уч.НЗС (Авто)'!AP$11:INDIRECT("'Полная ст-ть с уч.НЗС (Авто)'!AP"&$J$26))/$D11) -> 0 | AQ11: =IF($D11=0,0,SUMIF('Полная ст-ть с уч.НЗС (Авто)'!$YO$11:INDIRECT("'Полная ст-ть с уч.НЗС (Авто)'!YO"&$J$26),$C11,'Полная ст-ть с уч.НЗС (Авто)'!AQ$11:INDIRECT("'Полная ст-ть с уч.НЗС (Авто)'!AQ"&$J$26))/$D11) -> 0 | AX11: =IF($D11=0,0,SUMIF('Полная ст-ть с уч.НЗС (Авто)'!$YO$11:INDIRECT("'Полная ст-ть с уч.НЗС (Авто)'!YO"&$J$26),$C11,'Полная ст-ть с уч.НЗС (Авто)'!AX$11:INDIRECT("'Полная ст-ть с уч.НЗС (Авто)'!AX"&$J$26))/$D11) -> 0 | AY11: =IF($D11=0,0,SUMIF('Полная ст-ть с уч.НЗС (Авто)'!$YO$11:INDIRECT("'Полная ст-ть с уч.НЗС (Авто)'!YO"&$J$26),$C11,'Полная ст-ть с уч.НЗС (Авто)'!AY$11:INDIRECT("'Полная ст-ть с уч.НЗС (Авто)'!AY"&$J$26))/$D11) -> 0 | AZ11: =IF($D11=0,0,SUMIF('Полная ст-ть с уч.НЗС (Авто)'!$YO$11:INDIRECT("'Полная ст-ть с уч.НЗС (Авто)'!YO"&$J$26),$C11,'Полная ст-ть с уч.НЗС (Авто)'!AZ$11:INDIRECT("'Полная ст-ть с уч.НЗС (Авто)'!AZ"&$J$26))/$D11) -> 0 | BA11: =IF($D11=0,0,SUMIF('Полная ст-ть с уч.НЗС (Авто)'!$YO$11:INDIRECT("'Полная ст-ть с уч.НЗС (Авто)'!YO"&$J$26),$C11,'Полная ст-ть с уч.НЗС (Авто)'!BA$11:INDIRECT("'Полная ст-ть с уч.НЗС (Авто)'!BA"&$J$26))/$D11) -> 0 | BB11: =IF($D11=0,0,SUMIF('Полная ст-ть с уч.НЗС (Авто)'!$YO$11:INDIRECT("'Полная ст-ть с уч.НЗС (Авто)'!YO"&$J$26),$C11,'Полная ст-ть с уч.НЗС (Авто)'!BB$11:INDIRECT("'Полная ст-ть с уч.НЗС (Авто)'!BB"&$J$26))/$D11) -> 0 | BC11: =IF($D11=0,0,SUMIF('Полная ст-ть с уч.НЗС (Авто)'!$YO$11:INDIRECT("'Полная ст-ть с уч.НЗС (Авто)'!YO"&$J$26),$C11,'Полная ст-ть с уч.НЗС (Авто)'!BC$11:INDIRECT("'Полная ст-ть с уч.НЗС (Авто)'!BC"&$J$26))/$D11) -> 0 | BF11: =IF($D11=0,0,SUMIF('Полная ст-ть с уч.НЗС (Авто)'!$YO$11:INDIRECT("'Полная ст-ть с уч.НЗС (Авто)'!YO"&$J$26),$C11,'Полная ст-ть с уч.НЗС (Авто)'!BF$11:INDIRECT("'Полная ст-ть с уч.НЗС (Авто)'!BF"&$J$26))/$D11) -> 0 | BG11: =IF($D11=0,0,SUMIF('Полная ст-ть с уч.НЗС (Авто)'!$YO$11:INDIRECT("'Полная ст-ть с уч.НЗС (Авто)'!YO"&$J$26),$C11,'Полная ст-ть с уч.НЗС (Авто)'!BG$11:INDIRECT("'Полная ст-ть с уч.НЗС (Авто)'!BG"&$J$26))/$D11) -> 0 | BH11: =IF($D11=0,0,SUMIF('Полная ст-ть с уч.НЗС (Авто)'!$YO$11:INDIRECT("'Полная ст-ть с уч.НЗС (Авто)'!YO"&$J$26),$C11,'Полная ст-ть с уч.НЗС (Авто)'!BH$11:INDIRECT("'Полная ст-ть с уч.НЗС (Авто)'!BH"&$J$26))/$D11) -> 0 | BI11: =IF($D11=0,0,SUMIF('Полная ст-ть с уч.НЗС (Авто)'!$YO$11:INDIRECT("'Полная ст-ть с уч.НЗС (Авто)'!YO"&$J$26),$C11,'Полная ст-ть с уч.НЗС (Авто)'!BI$11:INDIRECT("'Полная ст-ть с уч.НЗС (Авто)'!BI"&$J$26))/$D11) -> 0 | BJ11: =IF($D11=0,0,SUMIF('Полная ст-ть с уч.НЗС (Авто)'!$YO$11:INDIRECT("'Полная ст-ть с уч.НЗС (Авто)'!YO"&$J$26),$C11,'Полная ст-ть с уч.НЗС (Авто)'!BJ$11:INDIRECT("'Полная ст-ть с уч.НЗС (Авто)'!BJ"&$J$26))/$D11) -> 0 | BK11: =IF($D11=0,0,SUMIF('Полная ст-ть с уч.НЗС (Авто)'!$YO$11:INDIRECT("'Полная ст-ть с уч.НЗС (Авто)'!YO"&$J$26),$C11,'Полная ст-ть с уч.НЗС (Авто)'!BK$11:INDIRECT("'Полная ст-ть с уч.НЗС (Авто)'!BK"&$J$26))/$D11) -> 0 | BM11: =IF($D11=0,0,SUMIF('Полная ст-ть с уч.НЗС (Авто)'!$YO$11:INDIRECT("'Полная ст-ть с уч.НЗС (Авто)'!YO"&$J$26),$C11,'Полная ст-ть с уч.НЗС (Авто)'!BM$11:INDIRECT("'Полная ст-ть с уч.НЗС (Авто)'!BM"&$J$26))/$D11) -> 0 | BQ11: =IF($D11=0,0,SUMIF('Полная ст-ть с уч.НЗС (Авто)'!$YO$11:INDIRECT("'Полная ст-ть с уч.НЗС (Авто)'!YO"&$J$26),$C11,'Полная ст-ть с уч.НЗС (Авто)'!BQ$11:INDIRECT("'Полная ст-ть с уч.НЗС (Авто)'!BQ"&$J$26))/$D11) -> 0 | CK11: =IF($D11=0,0,SUMIF('Полная ст-ть с уч.НЗС (Авто)'!$YO$11:INDIRECT("'Полная ст-ть с уч.НЗС (Авто)'!YO"&$J$26),$C11,'Полная ст-ть с уч.НЗС (Авто)'!CK$11:INDIRECT("'Полная ст-ть с уч.НЗС (Авто)'!CK"&$J$26))/$D11) -> 0 | CL11: =IF($D11=0,0,SUMIF('Полная ст-ть с уч.НЗС (Авто)'!$YO$11:INDIRECT("'Полная ст-ть с уч.НЗС (Авто)'!YO"&$J$26),$C11,'Полная ст-ть с уч.НЗС (Авто)'!CL$11:INDIRECT("'Полная ст-ть с уч.НЗС (Авто)'!CL"&$J$26))/$D11) -> 0 | CM11: =IF($D11=0,0,SUMIF('Полная ст-ть с уч.НЗС (Авто)'!$YO$11:INDIRECT("'Полная ст-ть с уч.НЗС (Авто)'!YO"&$J$26),$C11,'Полная ст-ть с уч.НЗС (Авто)'!CM$11:INDIRECT("'Полная ст-ть с уч.НЗС (Авто)'!CM"&$J$26))/$D11) -> 0 | CN11: =IF($D11=0,0,SUMIF('Полная ст-ть с уч.НЗС (Авто)'!$YO$11:INDIRECT("'Полная ст-ть с уч.НЗС (Авто)'!YO"&$J$26),$C11,'Полная ст-ть с уч.НЗС (Авто)'!CN$11:INDIRECT("'Полная ст-ть с уч.НЗС (Авто)'!CN"&$J$26))/$D11) -> 0 | CO11: =IF($D11=0,0,SUMIF('Полная ст-ть с уч.НЗС (Авто)'!$YO$11:INDIRECT("'Полная ст-ть с уч.НЗС (Авто)'!YO"&$J$26),$C11,'Полная ст-ть с уч.НЗС (Авто)'!CO$11:INDIRECT("'Полная ст-ть с уч.НЗС (Авто)'!CO"&$J$26))/$D11) -> 0 | CP11: =IF($D11=0,0,SUMIF('Полная ст-ть с уч.НЗС (Авто)'!$YO$11:INDIRECT("'Полная ст-ть с уч.НЗС (Авто)'!YO"&$J$26),$C11,'Полная ст-ть с уч.НЗС (Авто)'!CP$11:INDIRECT("'Полная ст-ть с уч.НЗС (Авто)'!CO"&$J$26))/$D11) -> 0 | CQ11: =IF($D11=0,0,SUMIF('Полная ст-ть с уч.НЗС (Авто)'!$YO$11:INDIRECT("'Полная ст-ть с уч.НЗС (Авто)'!YO"&$J$26),$C11,'Полная ст-ть с уч.НЗС (Авто)'!CQ$11:INDIRECT("'Полная ст-ть с уч.НЗС (Авто)'!CQ"&$J$26))/$D11) -> 0 | CR11: =IF($D11=0,0,SUMIF('Полная ст-ть с уч.НЗС (Авто)'!$YO$11:INDIRECT("'Полная ст-ть с уч.НЗС (Авто)'!YO"&$J$26),$C11,'Полная ст-ть с уч.НЗС (Авто)'!CR$11:INDIRECT("'Полная ст-ть с уч.НЗС (Авто)'!CR"&$J$26))/$D11) -> 0 | CS11: =IF($D11=0,0,SUMIF('Полная ст-ть с уч.НЗС (Авто)'!$YO$11:INDIRECT("'Полная ст-ть с уч.НЗС (Авто)'!YO"&$J$26),$C11,'Полная ст-ть с уч.НЗС (Авто)'!CS$11:INDIRECT("'Полная ст-ть с уч.НЗС (Авто)'!CS"&$J$26))/$D11) -> 0 | CT11: =IF($D11=0,0,SUMIF('Полная ст-ть с уч.НЗС (Авто)'!$YO$11:INDIRECT("'Полная ст-ть с уч.НЗС (Авто)'!YO"&$J$26),$C11,'Полная ст-ть с уч.НЗС (Авто)'!CT$11:INDIRECT("'Полная ст-ть с уч.НЗС (Авто)'!CT"&$J$26))/$D11) -> 0 | CU11: =IF($D11=0,0,SUMIF('Полная ст-ть с уч.НЗС (Авто)'!$YO$11:INDIRECT("'Полная ст-ть с уч.НЗС (Авто)'!YO"&$J$26),$C11,'Полная ст-ть с уч.НЗС (Авто)'!CU$11:INDIRECT("'Полная ст-ть с уч.НЗС (Авто)'!CU"&$J$26))/$D11) -> 0 | CV11: =IF($D11=0,0,SUMIF('Полная ст-ть с уч.НЗС (Авто)'!$YO$11:INDIRECT("'Полная ст-ть с уч.НЗС (Авто)'!YO"&$J$26),$C11,'Полная ст-ть с уч.НЗС (Авто)'!CV$11:INDIRECT("'Полная ст-ть с уч.НЗС (Авто)'!CV"&$J$26))/$D11) -> 0 | CW11: =IF($D11=0,0,SUMIF('Полная ст-ть с уч.НЗС (Авто)'!$YO$11:INDIRECT("'Полная ст-ть с уч.НЗС (Авто)'!YO"&$J$26),$C11,'Полная ст-ть с уч.НЗС (Авто)'!CW$11:INDIRECT("'Полная ст-ть с уч.НЗС (Авто)'!CW"&$J$26))/$D11) -> 0 | CX11: =IF($D11=0,0,SUMIF('Полная ст-ть с уч.НЗС (Авто)'!$YO$11:INDIRECT("'Полная ст-ть с уч.НЗС (Авто)'!YO"&$J$26),$C11,'Полная ст-ть с уч.НЗС (Авто)'!CX$11:INDIRECT("'Полная ст-ть с уч.НЗС (Авто)'!CX"&$J$26))/$D11) -> 0 | CY11: =IF($D11=0,0,SUMIF('Полная ст-ть с уч.НЗС (Авто)'!$YO$11:INDIRECT("'Полная ст-ть с уч.НЗС (Авто)'!YO"&$J$26),$C11,'Полная ст-ть с уч.НЗС (Авто)'!CY$11:INDIRECT("'Полная ст-ть с уч.НЗС (Авто)'!CY"&$J$26))/$D11) -> 0 | CZ11: =IF($D11=0,0,SUMIF('Полная ст-ть с уч.НЗС (Авто)'!$YO$11:INDIRECT("'Полная ст-ть с уч.НЗС (Авто)'!YO"&$J$26),$C11,'Полная ст-ть с уч.НЗС (Авто)'!CZ$11:INDIRECT("'Полная ст-ть с уч.НЗС (Авто)'!CZ"&$J$26))/$D11) -> 0 | DA11: =IF($D11=0,0,SUMIF('Полная ст-ть с уч.НЗС (Авто)'!$YO$11:INDIRECT("'Полная ст-ть с уч.НЗС (Авто)'!YO"&$J$26),$C11,'Полная ст-ть с уч.НЗС (Авто)'!DA$11:INDIRECT("'Полная ст-ть с уч.НЗС (Авто)'!DA"&$J$26))/$D11) -> 0 | DB11: =IF($D11=0,0,SUMIF('Полная ст-ть с уч.НЗС (Авто)'!$YO$11:INDIRECT("'Полная ст-ть с уч.НЗС (Авто)'!YO"&$J$26),$C11,'Полная ст-ть с уч.НЗС (Авто)'!DB$11:INDIRECT("'Полная ст-ть с уч.НЗС (Авто)'!DB"&$J$26))/$D11) -> 0 | DC11: =IF($D11=0,0,SUMIF('Полная ст-ть с уч.НЗС (Авто)'!$YO$11:INDIRECT("'Полная ст-ть с уч.НЗС (Авто)'!YO"&$J$26),$C11,'Полная ст-ть с уч.НЗС (Авто)'!DC$11:INDIRECT("'Полная ст-ть с уч.НЗС (Авто)'!DC"&$J$26))/$D11) -> 0 | DE11: =IF($D11=0,0,SUMIF('Полная ст-ть с уч.НЗС (Авто)'!$YO$11:INDIRECT("'Полная ст-ть с уч.НЗС (Авто)'!YO"&$J$26),$C11,'Полная ст-ть с уч.НЗС (Авто)'!DE$11:INDIRECT("'Полная ст-ть с уч.НЗС (Авто)'!DE"&$J$26))/$D11) -> 0 | DG11: =IF($D11=0,0,SUMIF('Полная ст-ть с уч.НЗС (Авто)'!$YO$11:INDIRECT("'Полная ст-ть с уч.НЗС (Авто)'!YO"&$J$26),$C11,'Полная ст-ть с уч.НЗС (Авто)'!DG$11:INDIRECT("'Полная ст-ть с уч.НЗС (Авто)'!DG"&$J$26))/$D11) -> 0 | DH11: =IF($D11=0,0,SUMIF('Полная ст-ть с уч.НЗС (Авто)'!$YO$11:INDIRECT("'Полная ст-ть с уч.НЗС (Авто)'!YO"&$J$26),$C11,'Полная ст-ть с уч.НЗС (Авто)'!DH$11:INDIRECT("'Полная ст-ть с уч.НЗС (Авто)'!DH"&$J$26))/$D11) -> 0 | DI11: =IF($D11=0,0,SUMIF('Полная ст-ть с уч.НЗС (Авто)'!$YO$11:INDIRECT("'Полная ст-ть с уч.НЗС (Авто)'!YO"&$J$26),$C11,'Полная ст-ть с уч.НЗС (Авто)'!DI$11:INDIRECT("'Полная ст-ть с уч.НЗС (Авто)'!DI"&$J$26))/$D11) -> 0 | DJ11: =IF($D11=0,0,SUMIF('Полная ст-ть с уч.НЗС (Авто)'!$YO$11:INDIRECT("'Полная ст-ть с уч.НЗС (Авто)'!YO"&$J$26),$C11,'Полная ст-ть с уч.НЗС (Авто)'!DJ$11:INDIRECT("'Полная ст-ть с уч.НЗС (Авто)'!DJ"&$J$26))/$D11) -> 0 | DK11: =IF($D11=0,0,SUMIF('Полная ст-ть с уч.НЗС (Авто)'!$YO$11:INDIRECT("'Полная ст-ть с уч.НЗС (Авто)'!YO"&$J$26),$C11,'Полная ст-ть с уч.НЗС (Авто)'!DK$11:INDIRECT("'Полная ст-ть с уч.НЗС (Авто)'!DK"&$J$26))/$D11) -> 0 | DL11: =IF($D11=0,0,SUMIF('Полная ст-ть с уч.НЗС (Авто)'!$YO$11:INDIRECT("'Полная ст-ть с уч.НЗС (Авто)'!YO"&$J$26),$C11,'Полная ст-ть с уч.НЗС (Авто)'!DL$11:INDIRECT("'Полная ст-ть с уч.НЗС (Авто)'!DL"&$J$26))/$D11) -> 0 | DM11: =IF($D11=0,0,SUMIF('Полная ст-ть с уч.НЗС (Авто)'!$YO$11:INDIRECT("'Полная ст-ть с уч.НЗС (Авто)'!YO"&$J$26),$C11,'Полная ст-ть с уч.НЗС (Авто)'!DM$11:INDIRECT("'Полная ст-ть с уч.НЗС (Авто)'!DM"&$J$26))/$D11) -> 0 | DN11: =IF($D11=0,0,SUMIF('Полная ст-ть с уч.НЗС (Авто)'!$YO$11:INDIRECT("'Полная ст-ть с уч.НЗС (Авто)'!YO"&$J$26),$C11,'Полная ст-ть с уч.НЗС (Авто)'!DN$11:INDIRECT("'Полная ст-ть с уч.НЗС (Авто)'!DN"&$J$26))/$D11) -> 0 | DO11: =IF($D11=0,0,SUMIF('Полная ст-ть с уч.НЗС (Авто)'!$YO$11:INDIRECT("'Полная ст-ть с уч.НЗС (Авто)'!YO"&$J$26),$C11,'Полная ст-ть с уч.НЗС (Авто)'!DO$11:INDIRECT("'Полная ст-ть с уч.НЗС (Авто)'!DO"&$J$26))/$D11) -> 0 | DP11: =IF($D11=0,0,SUMIF('Полная ст-ть с уч.НЗС (Авто)'!$YO$11:INDIRECT("'Полная ст-ть с уч.НЗС (Авто)'!YO"&$J$26),$C11,'Полная ст-ть с уч.НЗС (Авто)'!DP$11:INDIRECT("'Полная ст-ть с уч.НЗС (Авто)'!DP"&$J$26))/$D11) -> 0 | DQ11: =IF($D11=0,0,SUMIF('Полная ст-ть с уч.НЗС (Авто)'!$YO$11:INDIRECT("'Полная ст-ть с уч.НЗС (Авто)'!YO"&$J$26),$C11,'Полная ст-ть с уч.НЗС (Авто)'!DQ$11:INDIRECT("'Полная ст-ть с уч.НЗС (Авто)'!DQ"&$J$26))/$D11) -> 0 | DR11: =IF($D11=0,0,SUMIF('Полная ст-ть с уч.НЗС (Авто)'!$YO$11:INDIRECT("'Полная ст-ть с уч.НЗС (Авто)'!YO"&$J$26),$C11,'Полная ст-ть с уч.НЗС (Авто)'!DR$11:INDIRECT("'Полная ст-ть с уч.НЗС (Авто)'!DR"&$J$26))/$D11) -> 0 | DS11: =IF($D11=0,0,SUMIF('Полная ст-ть с уч.НЗС (Авто)'!$YO$11:INDIRECT("'Полная ст-ть с уч.НЗС (Авто)'!YO"&$J$26),$C11,'Полная ст-ть с уч.НЗС (Авто)'!DS$11:INDIRECT("'Полная ст-ть с уч.НЗС (Авто)'!DS"&$J$26))/$D11) -> 0 | DT11: =IF($D11=0,0,SUMIF('Полная ст-ть с уч.НЗС (Авто)'!$YO$11:INDIRECT("'Полная ст-ть с уч.НЗС (Авто)'!YO"&$J$26),$C11,'Полная ст-ть с уч.НЗС (Авто)'!DT$11:INDIRECT("'Полная ст-ть с уч.НЗС (Авто)'!DT"&$J$26))/$D11) -> 0 | DU11: =IF($D11=0,0,SUMIF('Полная ст-ть с уч.НЗС (Авто)'!$YO$11:INDIRECT("'Полная ст-ть с уч.НЗС (Авто)'!YO"&$J$26),$C11,'Полная ст-ть с уч.НЗС (Авто)'!DU$11:INDIRECT("'Полная ст-ть с уч.НЗС (Авто)'!DU"&$J$26))/$D11) -> 0 | DV11: =IF($D11=0,0,SUMIF('Полная ст-ть с уч.НЗС (Авто)'!$YO$11:INDIRECT("'Полная ст-ть с уч.НЗС (Авто)'!YO"&$J$26),$C11,'Полная ст-ть с уч.НЗС (Авто)'!DV$11:INDIRECT("'Полная ст-ть с уч.НЗС (Авто)'!DV"&$J$26))/$D11) -> 0 | DW11: =IF($D11=0,0,SUMIF('Полная ст-ть с уч.НЗС (Авто)'!$YO$11:INDIRECT("'Полная ст-ть с уч.НЗС (Авто)'!YO"&$J$26),$C11,'Полная ст-ть с уч.НЗС (Авто)'!DW$11:INDIRECT("'Полная ст-ть с уч.НЗС (Авто)'!DW"&$J$26))/$D11) -> 0 | DX11: =IF($D11=0,0,SUMIF('Полная ст-ть с уч.НЗС (Авто)'!$YO$11:INDIRECT("'Полная ст-ть с уч.НЗС (Авто)'!YO"&$J$26),$C11,'Полная ст-ть с уч.НЗС (Авто)'!DX$11:INDIRECT("'Полная ст-ть с уч.НЗС (Авто)'!DX"&$J$26))/$D11) -> 0 | DY11: =IF($D11=0,0,SUMIF('Полная ст-ть с уч.НЗС (Авто)'!$YO$11:INDIRECT("'Полная ст-ть с уч.НЗС (Авто)'!YO"&$J$26),$C11,'Полная ст-ть с уч.НЗС (Авто)'!DY$11:INDIRECT("'Полная ст-ть с уч.НЗС (Авто)'!DY"&$J$26))/$D11) -> 0 | DZ11: =IF($D11=0,0,SUMIF('Полная ст-ть с уч.НЗС (Авто)'!$YO$11:INDIRECT("'Полная ст-ть с уч.НЗС (Авто)'!YO"&$J$26),$C11,'Полная ст-ть с уч.НЗС (Авто)'!DZ$11:INDIRECT("'Полная ст-ть с уч.НЗС (Авто)'!DZ"&$J$26))/$D11) -> 0 | EA11: =IF($D11=0,0,SUMIF('Полная ст-ть с уч.НЗС (Авто)'!$YO$11:INDIRECT("'Полная ст-ть с уч.НЗС (Авто)'!YO"&$J$26),$C11,'Полная ст-ть с уч.НЗС (Авто)'!EA$11:INDIRECT("'Полная ст-ть с уч.НЗС (Авто)'!EA"&$J$26))/$D11) -> 0 | EB11: =IF($D11=0,0,SUMIF('Полная ст-ть с уч.НЗС (Авто)'!$YO$11:INDIRECT("'Полная ст-ть с уч.НЗС (Авто)'!YO"&$J$26),$C11,'Полная ст-ть с уч.НЗС (Авто)'!EB$11:INDIRECT("'Полная ст-ть с уч.НЗС (Авто)'!EB"&$J$26))/$D11) -> 0 | EC11: =IF($D11=0,0,SUMIF('Полная ст-ть с уч.НЗС (Авто)'!$YO$11:INDIRECT("'Полная ст-ть с уч.НЗС (Авто)'!YO"&$J$26),$C11,'Полная ст-ть с уч.НЗС (Авто)'!EC$11:INDIRECT("'Полная ст-ть с уч.НЗС (Авто)'!EC"&$J$26))/$D11) -> 0 | ED11: =IF($D11=0,0,SUMIF('Полная ст-ть с уч.НЗС (Авто)'!$YO$11:INDIRECT("'Полная ст-ть с уч.НЗС (Авто)'!YO"&$J$26),$C11,'Полная ст-ть с уч.НЗС (Авто)'!ED$11:INDIRECT("'Полная ст-ть с уч.НЗС (Авто)'!ED"&$J$26))/$D11) -> 0 | EE11: =IF($D11=0,0,SUMIF('Полная ст-ть с уч.НЗС (Авто)'!$YO$11:INDIRECT("'Полная ст-ть с уч.НЗС (Авто)'!YO"&$J$26),$C11,'Полная ст-ть с уч.НЗС (Авто)'!EE$11:INDIRECT("'Полная ст-ть с уч.НЗС (Авто)'!EE"&$J$26))/$D11) -> 0 | EF11: =IF($D11=0,0,SUMIF('Полная ст-ть с уч.НЗС (Авто)'!$YO$11:INDIRECT("'Полная ст-ть с уч.НЗС (Авто)'!YO"&$J$26),$C11,'Полная ст-ть с уч.НЗС (Авто)'!EF$11:INDIRECT("'Полная ст-ть с уч.НЗС (Авто)'!EF"&$J$26))/$D11) -> 0 | EG11: =IF($D11=0,0,SUMIF('Полная ст-ть с уч.НЗС (Авто)'!$YO$11:INDIRECT("'Полная ст-ть с уч.НЗС (Авто)'!YO"&$J$26),$C11,'Полная ст-ть с уч.НЗС (Авто)'!EG$11:INDIRECT("'Полная ст-ть с уч.НЗС (Авто)'!EG"&$J$26))/$D11) -> 0 | EH11: =IF($D11=0,0,SUMIF('Полная ст-ть с уч.НЗС (Авто)'!$YO$11:INDIRECT("'Полная ст-ть с уч.НЗС (Авто)'!YO"&$J$26),$C11,'Полная ст-ть с уч.НЗС (Авто)'!EH$11:INDIRECT("'Полная ст-ть с уч.НЗС (Авто)'!EH"&$J$26))/$D11) -> 0 | EI11: =IF($D11=0,0,SUMIF('Полная ст-ть с уч.НЗС (Авто)'!$YO$11:INDIRECT("'Полная ст-ть с уч.НЗС (Авто)'!YO"&$J$26),$C11,'Полная ст-ть с уч.НЗС (Авто)'!EI$11:INDIRECT("'Полная ст-ть с уч.НЗС (Авто)'!EI"&$J$26))/$D11) -> 0 | EJ11: =IF($D11=0,0,SUMIF('Полная ст-ть с уч.НЗС (Авто)'!$YO$11:INDIRECT("'Полная ст-ть с уч.НЗС (Авто)'!YO"&$J$26),$C11,'Полная ст-ть с уч.НЗС (Авто)'!EJ$11:INDIRECT("'Полная ст-ть с уч.НЗС (Авто)'!EJ"&$J$26))/$D11) -> 0 | EK11: =IF($D11=0,0,SUMIF('Полная ст-ть с уч.НЗС (Авто)'!$YO$11:INDIRECT("'Полная ст-ть с уч.НЗС (Авто)'!YO"&$J$26),$C11,'Полная ст-ть с уч.НЗС (Авто)'!EK$11:INDIRECT("'Полная ст-ть с уч.НЗС (Авто)'!EK"&$J$26))/$D11) -> 0 | EL11: =IF($D11=0,0,SUMIF('Полная ст-ть с уч.НЗС (Авто)'!$YO$11:INDIRECT("'Полная ст-ть с уч.НЗС (Авто)'!YO"&$J$26),$C11,'Полная ст-ть с уч.НЗС (Авто)'!EL$11:INDIRECT("'Полная ст-ть с уч.НЗС (Авто)'!EL"&$J$26))/$D11) -> 0 | EM11: =IF($D11=0,0,SUMIF('Полная ст-ть с уч.НЗС (Авто)'!$YO$11:INDIRECT("'Полная ст-ть с уч.НЗС (Авто)'!YO"&$J$26),$C11,'Полная ст-ть с уч.НЗС (Авто)'!EM$11:INDIRECT("'Полная ст-ть с уч.НЗС (Авто)'!EM"&$J$26))/$D11) -> 0 | EN11: =IF($D11=0,0,SUMIF('Полная ст-ть с уч.НЗС (Авто)'!$YO$11:INDIRECT("'Полная ст-ть с уч.НЗС (Авто)'!YO"&$J$26),$C11,'Полная ст-ть с уч.НЗС (Авто)'!EN$11:INDIRECT("'Полная ст-ть с уч.НЗС (Авто)'!EN"&$J$26))/$D11) -> 0 | EO11: =IF($D11=0,0,SUMIF('Полная ст-ть с уч.НЗС (Авто)'!$YO$11:INDIRECT("'Полная ст-ть с уч.НЗС (Авто)'!YO"&$J$26),$C11,'Полная ст-ть с уч.НЗС (Авто)'!EO$11:INDIRECT("'Полная ст-ть с уч.НЗС (Авто)'!EO"&$J$26))/$D11) -> 0 | EP11: =IF($D11=0,0,SUMIF('Полная ст-ть с уч.НЗС (Авто)'!$YO$11:INDIRECT("'Полная ст-ть с уч.НЗС (Авто)'!YO"&$J$26),$C11,'Полная ст-ть с уч.НЗС (Авто)'!EP$11:INDIRECT("'Полная ст-ть с уч.НЗС (Авто)'!EP"&$J$26))/$D11) -> 0 | EQ11: =IF($D11=0,0,SUMIF('Полная ст-ть с уч.НЗС (Авто)'!$YO$11:INDIRECT("'Полная ст-ть с уч.НЗС (Авто)'!YO"&$J$26),$C11,'Полная ст-ть с уч.НЗС (Авто)'!EQ$11:INDIRECT("'Полная ст-ть с уч.НЗС (Авто)'!EQ"&$J$26))/$D11) -> 0 | ER11: =IF($D11=0,0,SUMIF('Полная ст-ть с уч.НЗС (Авто)'!$YO$11:INDIRECT("'Полная ст-ть с уч.НЗС (Авто)'!YO"&$J$26),$C11,'Полная ст-ть с уч.НЗС (Авто)'!ER$11:INDIRECT("'Полная ст-ть с уч.НЗС (Авто)'!ER"&$J$26))/$D11) -> 0 | ES11: =IF($D11=0,0,SUMIF('Полная ст-ть с уч.НЗС (Авто)'!$YO$11:INDIRECT("'Полная ст-ть с уч.НЗС (Авто)'!YO"&$J$26),$C11,'Полная ст-ть с уч.НЗС (Авто)'!ES$11:INDIRECT("'Полная ст-ть с уч.НЗС (Авто)'!ES"&$J$26))/$D11) -> 0 | ET11: =IF($D11=0,0,SUMIF('Полная ст-ть с уч.НЗС (Авто)'!$YO$11:INDIRECT("'Полная ст-ть с уч.НЗС (Авто)'!YO"&$J$26),$C11,'Полная ст-ть с уч.НЗС (Авто)'!ET$11:INDIRECT("'Полная ст-ть с уч.НЗС (Авто)'!ET"&$J$26))/$D11) -> 0 | EU11: =IF($D11=0,0,SUMIF('Полная ст-ть с уч.НЗС (Авто)'!$YO$11:INDIRECT("'Полная ст-ть с уч.НЗС (Авто)'!YO"&$J$26),$C11,'Полная ст-ть с уч.НЗС (Авто)'!EU$11:INDIRECT("'Полная ст-ть с уч.НЗС (Авто)'!EU"&$J$26))/$D11) -> 0 | EV11: =IF($D11=0,0,SUMIF('Полная ст-ть с уч.НЗС (Авто)'!$YO$11:INDIRECT("'Полная ст-ть с уч.НЗС (Авто)'!YO"&$J$26),$C11,'Полная ст-ть с уч.НЗС (Авто)'!EV$11:INDIRECT("'Полная ст-ть с уч.НЗС (Авто)'!EV"&$J$26))/$D11) -> 0 | EW11: =IF($D11=0,0,SUMIF('Полная ст-ть с уч.НЗС (Авто)'!$YO$11:INDIRECT("'Полная ст-ть с уч.НЗС (Авто)'!YO"&$J$26),$C11,'Полная ст-ть с уч.НЗС (Авто)'!EW$11:INDIRECT("'Полная ст-ть с уч.НЗС (Авто)'!EW"&$J$26))/$D11) -> 0 | EX11: =IF($D11=0,0,SUMIF('Полная ст-ть с уч.НЗС (Авто)'!$YO$11:INDIRECT("'Полная ст-ть с уч.НЗС (Авто)'!YO"&$J$26),$C11,'Полная ст-ть с уч.НЗС (Авто)'!EX$11:INDIRECT("'Полная ст-ть с уч.НЗС (Авто)'!EX"&$J$26))/$D11) -> 0 | EY11: =IF($D11=0,0,SUMIF('Полная ст-ть с уч.НЗС (Авто)'!$YO$11:INDIRECT("'Полная ст-ть с уч.НЗС (Авто)'!YO"&$J$26),$C11,'Полная ст-ть с уч.НЗС (Авто)'!EY$11:INDIRECT("'Полная ст-ть с уч.НЗС (Авто)'!EY"&$J$26))/$D11) -> 0 | EZ11: =IF($D11=0,0,SUMIF('Полная ст-ть с уч.НЗС (Авто)'!$YO$11:INDIRECT("'Полная ст-ть с уч.НЗС (Авто)'!YO"&$J$26),$C11,'Полная ст-ть с уч.НЗС (Авто)'!EZ$11:INDIRECT("'Полная ст-ть с уч.НЗС (Авто)'!EZ"&$J$26))/$D11) -> 0 | FA11: =IF($D11=0,0,SUMIF('Полная ст-ть с уч.НЗС (Авто)'!$YO$11:INDIRECT("'Полная ст-ть с уч.НЗС (Авто)'!YO"&$J$26),$C11,'Полная ст-ть с уч.НЗС (Авто)'!FA$11:INDIRECT("'Полная ст-ть с уч.НЗС (Авто)'!FA"&$J$26))/$D11) -> 0 | FB11: =IF($D11=0,0,SUMIF('Полная ст-ть с уч.НЗС (Авто)'!$YO$11:INDIRECT("'Полная ст-ть с уч.НЗС (Авто)'!YO"&$J$26),$C11,'Полная ст-ть с уч.НЗС (Авто)'!FB$11:INDIRECT("'Полная ст-ть с уч.НЗС (Авто)'!FB"&$J$26))/$D11) -> 0 | FC11: =IF($D11=0,0,SUMIF('Полная ст-ть с уч.НЗС (Авто)'!$YO$11:INDIRECT("'Полная ст-ть с уч.НЗС (Авто)'!YO"&$J$26),$C11,'Полная ст-ть с уч.НЗС (Авто)'!FC$11:INDIRECT("'Полная ст-ть с уч.НЗС (Авто)'!FC"&$J$26))/$D11) -> 0 | FD11: =IF($D11=0,0,SUMIF('Полная ст-ть с уч.НЗС (Авто)'!$YO$11:INDIRECT("'Полная ст-ть с уч.НЗС (Авто)'!YO"&$J$26),$C11,'Полная ст-ть с уч.НЗС (Авто)'!FD$11:INDIRECT("'Полная ст-ть с уч.НЗС (Авто)'!FD"&$J$26))/$D11) -> 0 | FE11: =IF($D11=0,0,SUMIF('Полная ст-ть с уч.НЗС (Авто)'!$YO$11:INDIRECT("'Полная ст-ть с уч.НЗС (Авто)'!YO"&$J$26),$C11,'Полная ст-ть с уч.НЗС (Авто)'!FE$11:INDIRECT("'Полная ст-ть с уч.НЗС (Авто)'!FE"&$J$26))/$D11) -> 0 | FF11: =IF($D11=0,0,SUMIF('Полная ст-ть с уч.НЗС (Авто)'!$YO$11:INDIRECT("'Полная ст-ть с уч.НЗС (Авто)'!YO"&$J$26),$C11,'Полная ст-ть с уч.НЗС (Авто)'!FF$11:INDIRECT("'Полная ст-ть с уч.НЗС (Авто)'!FF"&$J$26))/$D11) -> 0 | FG11: =IF($D11=0,0,SUMIF('Полная ст-ть с уч.НЗС (Авто)'!$YO$11:INDIRECT("'Полная ст-ть с уч.НЗС (Авто)'!YO"&$J$26),$C11,'Полная ст-ть с уч.НЗС (Авто)'!FG$11:INDIRECT("'Полная ст-ть с уч.НЗС (Авто)'!FG"&$J$26))/$D11) -> 0 | FH11: =IF($D11=0,0,SUMIF('Полная ст-ть с уч.НЗС (Авто)'!$YO$11:INDIRECT("'Полная ст-ть с уч.НЗС (Авто)'!YO"&$J$26),$C11,'Полная ст-ть с уч.НЗС (Авто)'!FH$11:INDIRECT("'Полная ст-ть с уч.НЗС (Авто)'!FH"&$J$26))/$D11) -> 0 | FI11: =IF($D11=0,0,SUMIF('Полная ст-ть с уч.НЗС (Авто)'!$YO$11:INDIRECT("'Полная ст-ть с уч.НЗС (Авто)'!YO"&$J$26),$C11,'Полная ст-ть с уч.НЗС (Авто)'!FI$11:INDIRECT("'Полная ст-ть с уч.НЗС (Авто)'!FI"&$J$26))/$D11) -> 0 | FJ11: =IF($D11=0,0,SUMIF('Полная ст-ть с уч.НЗС (Авто)'!$YO$11:INDIRECT("'Полная ст-ть с уч.НЗС (Авто)'!YO"&$J$26),$C11,'Полная ст-ть с уч.НЗС (Авто)'!FJ$11:INDIRECT("'Полная ст-ть с уч.НЗС (Авто)'!FJ"&$J$26))/$D11) -> 0 | FK11: =IF($D11=0,0,SUMIF('Полная ст-ть с уч.НЗС (Авто)'!$YO$11:INDIRECT("'Полная ст-ть с уч.НЗС (Авто)'!YO"&$J$26),$C11,'Полная ст-ть с уч.НЗС (Авто)'!FK$11:INDIRECT("'Полная ст-ть с уч.НЗС (Авто)'!FK"&$J$26))/$D11) -> 0 | FL11: =IF($D11=0,0,SUMIF('Полная ст-ть с уч.НЗС (Авто)'!$YO$11:INDIRECT("'Полная ст-ть с уч.НЗС (Авто)'!YO"&$J$26),$C11,'Полная ст-ть с уч.НЗС (Авто)'!FL$11:INDIRECT("'Полная ст-ть с уч.НЗС (Авто)'!FL"&$J$26))/$D11) -> 0 | FM11: =IF($D11=0,0,SUMIF('Полная ст-ть с уч.НЗС (Авто)'!$YO$11:INDIRECT("'Полная ст-ть с уч.НЗС (Авто)'!YO"&$J$26),$C11,'Полная ст-ть с уч.НЗС (Авто)'!FM$11:INDIRECT("'Полная ст-ть с уч.НЗС (Авто)'!FM"&$J$26))/$D11) -> 0 | FN11: =IF($D11=0,0,SUMIF('Полная ст-ть с уч.НЗС (Авто)'!$YO$11:INDIRECT("'Полная ст-ть с уч.НЗС (Авто)'!YO"&$J$26),$C11,'Полная ст-ть с уч.НЗС (Авто)'!FN$11:INDIRECT("'Полная ст-ть с уч.НЗС (Авто)'!FN"&$J$26))/$D11) -> 0 | FO11: =IF($D11=0,0,SUMIF('Полная ст-ть с уч.НЗС (Авто)'!$YO$11:INDIRECT("'Полная ст-ть с уч.НЗС (Авто)'!YO"&$J$26),$C11,'Полная ст-ть с уч.НЗС (Авто)'!FO$11:INDIRECT("'Полная ст-ть с уч.НЗС (Авто)'!FO"&$J$26))/$D11) -> 0 | FP11: =IF($D11=0,0,SUMIF('Полная ст-ть с уч.НЗС (Авто)'!$YO$11:INDIRECT("'Полная ст-ть с уч.НЗС (Авто)'!YO"&$J$26),$C11,'Полная ст-ть с уч.НЗС (Авто)'!FP$11:INDIRECT("'Полная ст-ть с уч.НЗС (Авто)'!FP"&$J$26))/$D11) -> 0 | FQ11: =IF($D11=0,0,SUMIF('Полная ст-ть с уч.НЗС (Авто)'!$YO$11:INDIRECT("'Полная ст-ть с уч.НЗС (Авто)'!YO"&$J$26),$C11,'Полная ст-ть с уч.НЗС (Авто)'!FQ$11:INDIRECT("'Полная ст-ть с уч.НЗС (Авто)'!FQ"&$J$26))/$D11) -> 0 | FR11: =IF($D11=0,0,SUMIF('Полная ст-ть с уч.НЗС (Авто)'!$YO$11:INDIRECT("'Полная ст-ть с уч.НЗС (Авто)'!YO"&$J$26),$C11,'Полная ст-ть с уч.НЗС (Авто)'!FR$11:INDIRECT("'Полная ст-ть с уч.НЗС (Авто)'!FR"&$J$26))/$D11) -> 0 | FS11: =IF($D11=0,0,SUMIF('Полная ст-ть с уч.НЗС (Авто)'!$YO$11:INDIRECT("'Полная ст-ть с уч.НЗС (Авто)'!YO"&$J$26),$C11,'Полная ст-ть с уч.НЗС (Авто)'!FS$11:INDIRECT("'Полная ст-ть с уч.НЗС (Авто)'!FS"&$J$26))/$D11) -> 0 | FT11: =IF($D11=0,0,SUMIF('Полная ст-ть с уч.НЗС (Авто)'!$YO$11:INDIRECT("'Полная ст-ть с уч.НЗС (Авто)'!YO"&$J$26),$C11,'Полная ст-ть с уч.НЗС (Авто)'!FT$11:INDIRECT("'Полная ст-ть с уч.НЗС (Авто)'!FT"&$J$26))/$D11) -> 0 | FU11: =IF($D11=0,0,SUMIF('Полная ст-ть с уч.НЗС (Авто)'!$YO$11:INDIRECT("'Полная ст-ть с уч.НЗС (Авто)'!YO"&$J$26),$C11,'Полная ст-ть с уч.НЗС (Авто)'!FU$11:INDIRECT("'Полная ст-ть с уч.НЗС (Авто)'!FU"&$J$26))/$D11) -> 0 | FV11: =IF($D11=0,0,SUMIF('Полная ст-ть с уч.НЗС (Авто)'!$YO$11:INDIRECT("'Полная ст-ть с уч.НЗС (Авто)'!YO"&$J$26),$C11,'Полная ст-ть с уч.НЗС (Авто)'!FV$11:INDIRECT("'Полная ст-ть с уч.НЗС (Авто)'!FV"&$J$26))/$D11) -> 0 | FW11: =IF($D11=0,0,SUMIF('Полная ст-ть с уч.НЗС (Авто)'!$YO$11:INDIRECT("'Полная ст-ть с уч.НЗС (Авто)'!YO"&$J$26),$C11,'Полная ст-ть с уч.НЗС (Авто)'!FW$11:INDIRECT("'Полная ст-ть с уч.НЗС (Авто)'!FW"&$J$26))/$D11) -> 0 | FX11: =IF($D11=0,0,SUMIF('Полная ст-ть с уч.НЗС (Авто)'!$YO$11:INDIRECT("'Полная ст-ть с уч.НЗС (Авто)'!YO"&$J$26),$C11,'Полная ст-ть с уч.НЗС (Авто)'!FX$11:INDIRECT("'Полная ст-ть с уч.НЗС (Авто)'!FX"&$J$26))/$D11) -> 0 | FY11: =IF($D11=0,0,SUMIF('Полная ст-ть с уч.НЗС (Авто)'!$YO$11:INDIRECT("'Полная ст-ть с уч.НЗС (Авто)'!YO"&$J$26),$C11,'Полная ст-ть с уч.НЗС (Авто)'!FY$11:INDIRECT("'Полная ст-ть с уч.НЗС (Авто)'!FY"&$J$26))/$D11) -> 0 | FZ11: =IF($D11=0,0,SUMIF('Полная ст-ть с уч.НЗС (Авто)'!$YO$11:INDIRECT("'Полная ст-ть с уч.НЗС (Авто)'!YO"&$J$26),$C11,'Полная ст-ть с уч.НЗС (Авто)'!FZ$11:INDIRECT("'Полная ст-ть с уч.НЗС (Авто)'!FZ"&$J$26))/$D11) -> 0 | GA11: =IF($D11=0,0,SUMIF('Полная ст-ть с уч.НЗС (Авто)'!$YO$11:INDIRECT("'Полная ст-ть с уч.НЗС (Авто)'!YO"&$J$26),$C11,'Полная ст-ть с уч.НЗС (Авто)'!GA$11:INDIRECT("'Полная ст-ть с уч.НЗС (Авто)'!GA"&$J$26))/$D11) -> 0 | GB11: =IF($D11=0,0,SUMIF('Полная ст-ть с уч.НЗС (Авто)'!$YO$11:INDIRECT("'Полная ст-ть с уч.НЗС (Авто)'!YO"&$J$26),$C11,'Полная ст-ть с уч.НЗС (Авто)'!GB$11:INDIRECT("'Полная ст-ть с уч.НЗС (Авто)'!GB"&$J$26))/$D11) -> 0 | GC11: =IF($D11=0,0,SUMIF('Полная ст-ть с уч.НЗС (Авто)'!$YO$11:INDIRECT("'Полная ст-ть с уч.НЗС (Авто)'!YO"&$J$26),$C11,'Полная ст-ть с уч.НЗС (Авто)'!GC$11:INDIRECT("'Полная ст-ть с уч.НЗС (Авто)'!GC"&$J$26))/$D11) -> 0 | GD11: =IF($D11=0,0,SUMIF('Полная ст-ть с уч.НЗС (Авто)'!$YO$11:INDIRECT("'Полная ст-ть с уч.НЗС (Авто)'!YO"&$J$26),$C11,'Полная ст-ть с уч.НЗС (Авто)'!GD$11:INDIRECT("'Полная ст-ть с уч.НЗС (Авто)'!GD"&$J$26))/$D11) -> 0 | GE11: =IF($D11=0,0,SUMIF('Полная ст-ть с уч.НЗС (Авто)'!$YO$11:INDIRECT("'Полная ст-ть с уч.НЗС (Авто)'!YO"&$J$26),$C11,'Полная ст-ть с уч.НЗС (Авто)'!GE$11:INDIRECT("'Полная ст-ть с уч.НЗС (Авто)'!GE"&$J$26))/$D11) -> 0 | GF11: =IF($D11=0,0,SUMIF('Полная ст-ть с уч.НЗС (Авто)'!$YO$11:INDIRECT("'Полная ст-ть с уч.НЗС (Авто)'!YO"&$J$26),$C11,'Полная ст-ть с уч.НЗС (Авто)'!GF$11:INDIRECT("'Полная ст-ть с уч.НЗС (Авто)'!GF"&$J$26))/$D11) -> 0 | GG11: =IF($D11=0,0,SUMIF('Полная ст-ть с уч.НЗС (Авто)'!$YO$11:INDIRECT("'Полная ст-ть с уч.НЗС (Авто)'!YO"&$J$26),$C11,'Полная ст-ть с уч.НЗС (Авто)'!GG$11:INDIRECT("'Полная ст-ть с уч.НЗС (Авто)'!GG"&$J$26))/$D11) -> 0 | GH11: =IF($D11=0,0,SUMIF('Полная ст-ть с уч.НЗС (Авто)'!$YO$11:INDIRECT("'Полная ст-ть с уч.НЗС (Авто)'!YO"&$J$26),$C11,'Полная ст-ть с уч.НЗС (Авто)'!GH$11:INDIRECT("'Полная ст-ть с уч.НЗС (Авто)'!GH"&$J$26))/$D11) -> 0 | GI11: =IF($D11=0,0,SUMIF('Полная ст-ть с уч.НЗС (Авто)'!$YO$11:INDIRECT("'Полная ст-ть с уч.НЗС (Авто)'!YO"&$J$26),$C11,'Полная ст-ть с уч.НЗС (Авто)'!GI$11:INDIRECT("'Полная ст-ть с уч.НЗС (Авто)'!GI"&$J$26))/$D11) -> 0 | GJ11: =IF($D11=0,0,SUMIF('Полная ст-ть с уч.НЗС (Авто)'!$YO$11:INDIRECT("'Полная ст-ть с уч.НЗС (Авто)'!YO"&$J$26),$C11,'Полная ст-ть с уч.НЗС (Авто)'!GJ$11:INDIRECT("'Полная ст-ть с уч.НЗС (Авто)'!GJ"&$J$26))/$D11) -> 0 | GK11: =IF($D11=0,0,SUMIF('Полная ст-ть с уч.НЗС (Авто)'!$YO$11:INDIRECT("'Полная ст-ть с уч.НЗС (Авто)'!YO"&$J$26),$C11,'Полная ст-ть с уч.НЗС (Авто)'!GK$11:INDIRECT("'Полная ст-ть с уч.НЗС (Авто)'!GK"&$J$26))/$D11) -> 0 | GL11: =IF($D11=0,0,SUMIF('Полная ст-ть с уч.НЗС (Авто)'!$YO$11:INDIRECT("'Полная ст-ть с уч.НЗС (Авто)'!YO"&$J$26),$C11,'Полная ст-ть с уч.НЗС (Авто)'!GL$11:INDIRECT("'Полная ст-ть с уч.НЗС (Авто)'!GL"&$J$26))/$D11) -> 0 | GM11: =IF($D11=0,0,SUMIF('Полная ст-ть с уч.НЗС (Авто)'!$YO$11:INDIRECT("'Полная ст-ть с уч.НЗС (Авто)'!YO"&$J$26),$C11,'Полная ст-ть с уч.НЗС (Авто)'!GM$11:INDIRECT("'Полная ст-ть с уч.НЗС (Авто)'!GM"&$J$26))/$D11) -> 0 | GN11: =IF($D11=0,0,SUMIF('Полная ст-ть с уч.НЗС (Авто)'!$YO$11:INDIRECT("'Полная ст-ть с уч.НЗС (Авто)'!YO"&$J$26),$C11,'Полная ст-ть с уч.НЗС (Авто)'!GN$11:INDIRECT("'Полная ст-ть с уч.НЗС (Авто)'!GN"&$J$26))/$D11) -> 0 | GO11: =IF($D11=0,0,SUMIF('Полная ст-ть с уч.НЗС (Авто)'!$YO$11:INDIRECT("'Полная ст-ть с уч.НЗС (Авто)'!YO"&$J$26),$C11,'Полная ст-ть с уч.НЗС (Авто)'!GO$11:INDIRECT("'Полная ст-ть с уч.НЗС (Авто)'!GO"&$J$26))/$D11) -> 0 | GP11: =IF($D11=0,0,SUMIF('Полная ст-ть с уч.НЗС (Авто)'!$YO$11:INDIRECT("'Полная ст-ть с уч.НЗС (Авто)'!YO"&$J$26),$C11,'Полная ст-ть с уч.НЗС (Авто)'!GP$11:INDIRECT("'Полная ст-ть с уч.НЗС (Авто)'!GP"&$J$26))/$D11) -> 0 | GQ11: =IF($D11=0,0,SUMIF('Полная ст-ть с уч.НЗС (Авто)'!$YO$11:INDIRECT("'Полная ст-ть с уч.НЗС (Авто)'!YO"&$J$26),$C11,'Полная ст-ть с уч.НЗС (Авто)'!GQ$11:INDIRECT("'Полная ст-ть с уч.НЗС (Авто)'!GP"&$J$26))/$D11) -> 0 | GR11: =IF($D11=0,0,SUMIF('Полная ст-ть с уч.НЗС (Авто)'!$YO$11:INDIRECT("'Полная ст-ть с уч.НЗС (Авто)'!YO"&$J$26),$C11,'Полная ст-ть с уч.НЗС (Авто)'!GR$11:INDIRECT("'Полная ст-ть с уч.НЗС (Авто)'!GR"&$J$26))/$D11) -> 0 | GS11: =IF($D11=0,0,SUMIF('Полная ст-ть с уч.НЗС (Авто)'!$YO$11:INDIRECT("'Полная ст-ть с уч.НЗС (Авто)'!YO"&$J$26),$C11,'Полная ст-ть с уч.НЗС (Авто)'!GS$11:INDIRECT("'Полная ст-ть с уч.НЗС (Авто)'!GS"&$J$26))/$D11) -> 0 | GT11: =IF($D11=0,0,SUMIF('Полная ст-ть с уч.НЗС (Авто)'!$YO$11:INDIRECT("'Полная ст-ть с уч.НЗС (Авто)'!YO"&$J$26),$C11,'Полная ст-ть с уч.НЗС (Авто)'!GT$11:INDIRECT("'Полная ст-ть с уч.НЗС (Авто)'!GT"&$J$26))/$D11) -> 0 | GU11: =IF($D11=0,0,SUMIF('Полная ст-ть с уч.НЗС (Авто)'!$YO$11:INDIRECT("'Полная ст-ть с уч.НЗС (Авто)'!YO"&$J$26),$C11,'Полная ст-ть с уч.НЗС (Авто)'!GU$11:INDIRECT("'Полная ст-ть с уч.НЗС (Авто)'!GU"&$J$26))/$D11) -> 0 | GV11: =IF($D11=0,0,SUMIF('Полная ст-ть с уч.НЗС (Авто)'!$YO$11:INDIRECT("'Полная ст-ть с уч.НЗС (Авто)'!YO"&$J$26),$C11,'Полная ст-ть с уч.НЗС (Авто)'!GV$11:INDIRECT("'Полная ст-ть с уч.НЗС (Авто)'!GV"&$J$26))/$D11) -> 0 | GW11: =IF($D11=0,0,SUMIF('Полная ст-ть с уч.НЗС (Авто)'!$YO$11:INDIRECT("'Полная ст-ть с уч.НЗС (Авто)'!YO"&$J$26),$C11,'Полная ст-ть с уч.НЗС (Авто)'!GW$11:INDIRECT("'Полная ст-ть с уч.НЗС (Авто)'!GW"&$J$26))/$D11) -> 0 | GX11: =IF($D11=0,0,SUMIF('Полная ст-ть с уч.НЗС (Авто)'!$YO$11:INDIRECT("'Полная ст-ть с уч.НЗС (Авто)'!YO"&$J$26),$C11,'Полная ст-ть с уч.НЗС (Авто)'!GX$11:INDIRECT("'Полная ст-ть с уч.НЗС (Авто)'!GX"&$J$26))/$D11) -> 0 | GY11: =IF($D11=0,0,SUMIF('Полная ст-ть с уч.НЗС (Авто)'!$YO$11:INDIRECT("'Полная ст-ть с уч.НЗС (Авто)'!YO"&$J$26),$C11,'Полная ст-ть с уч.НЗС (Авто)'!GY$11:INDIRECT("'Полная ст-ть с уч.НЗС (Авто)'!GY"&$J$26))/$D11) -> 0 | GZ11: =IF($D11=0,0,SUMIF('Полная ст-ть с уч.НЗС (Авто)'!$YO$11:INDIRECT("'Полная ст-ть с уч.НЗС (Авто)'!YO"&$J$26),$C11,'Полная ст-ть с уч.НЗС (Авто)'!GZ$11:INDIRECT("'Полная ст-ть с уч.НЗС (Авто)'!GZ"&$J$26))/$D11) -> 0 | HA11: =IF($D11=0,0,SUMIF('Полная ст-ть с уч.НЗС (Авто)'!$YO$11:INDIRECT("'Полная ст-ть с уч.НЗС (Авто)'!YO"&$J$26),$C11,'Полная ст-ть с уч.НЗС (Авто)'!HA$11:INDIRECT("'Полная ст-ть с уч.НЗС (Авто)'!HA"&$J$26))/$D11) -> 0 | HB11: =IF($D11=0,0,SUMIF('Полная ст-ть с уч.НЗС (Авто)'!$YO$11:INDIRECT("'Полная ст-ть с уч.НЗС (Авто)'!YO"&$J$26),$C11,'Полная ст-ть с уч.НЗС (Авто)'!HB$11:INDIRECT("'Полная ст-ть с уч.НЗС (Авто)'!HB"&$J$26))/$D11) -> 0 | HC11: =IF($D11=0,0,SUMIF('Полная ст-ть с уч.НЗС (Авто)'!$YO$11:INDIRECT("'Полная ст-ть с уч.НЗС (Авто)'!YO"&$J$26),$C11,'Полная ст-ть с уч.НЗС (Авто)'!HC$11:INDIRECT("'Полная ст-ть с уч.НЗС (Авто)'!HC"&$J$26))/$D11) -> 0 | HD11: =IF($D11=0,0,SUMIF('Полная ст-ть с уч.НЗС (Авто)'!$YO$11:INDIRECT("'Полная ст-ть с уч.НЗС (Авто)'!YO"&$J$26),$C11,'Полная ст-ть с уч.НЗС (Авто)'!HD$11:INDIRECT("'Полная ст-ть с уч.НЗС (Авто)'!HD"&$J$26))/$D11) -> 0 | HE11: =IF($D11=0,0,SUMIF('Полная ст-ть с уч.НЗС (Авто)'!$YO$11:INDIRECT("'Полная ст-ть с уч.НЗС (Авто)'!YO"&$J$26),$C11,'Полная ст-ть с уч.НЗС (Авто)'!HE$11:INDIRECT("'Полная ст-ть с уч.НЗС (Авто)'!HE"&$J$26))/$D11) -> 0 | HF11: =IF($D11=0,0,SUMIF('Полная ст-ть с уч.НЗС (Авто)'!$YO$11:INDIRECT("'Полная ст-ть с уч.НЗС (Авто)'!YO"&$J$26),$C11,'Полная ст-ть с уч.НЗС (Авто)'!HF$11:INDIRECT("'Полная ст-ть с уч.НЗС (Авто)'!HF"&$J$26))/$D11) -> 0 | HG11: =IF($D11=0,0,SUMIF('Полная ст-ть с уч.НЗС (Авто)'!$YO$11:INDIRECT("'Полная ст-ть с уч.НЗС (Авто)'!YO"&$J$26),$C11,'Полная ст-ть с уч.НЗС (Авто)'!HG$11:INDIRECT("'Полная ст-ть с уч.НЗС (Авто)'!HG"&$J$26))/$D11) -> 0 | HH11: =IF($D11=0,0,SUMIF('Полная ст-ть с уч.НЗС (Авто)'!$YO$11:INDIRECT("'Полная ст-ть с уч.НЗС (Авто)'!YO"&$J$26),$C11,'Полная ст-ть с уч.НЗС (Авто)'!HH$11:INDIRECT("'Полная ст-ть с уч.НЗС (Авто)'!HH"&$J$26))/$D11) -> 0 | HI11: =IF($D11=0,0,SUMIF('Полная ст-ть с уч.НЗС (Авто)'!$YO$11:INDIRECT("'Полная ст-ть с уч.НЗС (Авто)'!YO"&$J$26),$C11,'Полная ст-ть с уч.НЗС (Авто)'!HI$11:INDIRECT("'Полная ст-ть с уч.НЗС (Авто)'!HI"&$J$26))/$D11) -> 0 | HJ11: =IF($D11=0,0,SUMIF('Полная ст-ть с уч.НЗС (Авто)'!$YO$11:INDIRECT("'Полная ст-ть с уч.НЗС (Авто)'!YO"&$J$26),$C11,'Полная ст-ть с уч.НЗС (Авто)'!HJ$11:INDIRECT("'Полная ст-ть с уч.НЗС (Авто)'!HJ"&$J$26))/$D11) -> 0 | HK11: =IF($D11=0,0,SUMIF('Полная ст-ть с уч.НЗС (Авто)'!$YO$11:INDIRECT("'Полная ст-ть с уч.НЗС (Авто)'!YO"&$J$26),$C11,'Полная ст-ть с уч.НЗС (Авто)'!HK$11:INDIRECT("'Полная ст-ть с уч.НЗС (Авто)'!HK"&$J$26))/$D11) -> 0 | HL11: =IF($D11=0,0,SUMIF('Полная ст-ть с уч.НЗС (Авто)'!$YO$11:INDIRECT("'Полная ст-ть с уч.НЗС (Авто)'!YO"&$J$26),$C11,'Полная ст-ть с уч.НЗС (Авто)'!HL$11:INDIRECT("'Полная ст-ть с уч.НЗС (Авто)'!HL"&$J$26))/$D11) -> 0 | HM11: =IF($D11=0,0,SUMIF('Полная ст-ть с уч.НЗС (Авто)'!$YO$11:INDIRECT("'Полная ст-ть с уч.НЗС (Авто)'!YO"&$J$26),$C11,'Полная ст-ть с уч.НЗС (Авто)'!HM$11:INDIRECT("'Полная ст-ть с уч.НЗС (Авто)'!HM"&$J$26))/$D11) -> 0 | HN11: =IF($D11=0,0,SUMIF('Полная ст-ть с уч.НЗС (Авто)'!$YO$11:INDIRECT("'Полная ст-ть с уч.НЗС (Авто)'!YO"&$J$26),$C11,'Полная ст-ть с уч.НЗС (Авто)'!HN$11:INDIRECT("'Полная ст-ть с уч.НЗС (Авто)'!HN"&$J$26))/$D11) -> 0 | HO11: =IF($D11=0,0,SUMIF('Полная ст-ть с уч.НЗС (Авто)'!$YO$11:INDIRECT("'Полная ст-ть с уч.НЗС (Авто)'!YO"&$J$26),$C11,'Полная ст-ть с уч.НЗС (Авто)'!HO$11:INDIRECT("'Полная ст-ть с уч.НЗС (Авто)'!HO"&$J$26))/$D11) -> 0 | HP11: =IF($D11=0,0,SUMIF('Полная ст-ть с уч.НЗС (Авто)'!$YO$11:INDIRECT("'Полная ст-ть с уч.НЗС (Авто)'!YO"&$J$26),$C11,'Полная ст-ть с уч.НЗС (Авто)'!HP$11:INDIRECT("'Полная ст-ть с уч.НЗС (Авто)'!HP"&$J$26))/$D11) -> 0 | HQ11: =IF($D11=0,0,SUMIF('Полная ст-ть с уч.НЗС (Авто)'!$YO$11:INDIRECT("'Полная ст-ть с уч.НЗС (Авто)'!YO"&$J$26),$C11,'Полная ст-ть с уч.НЗС (Авто)'!HQ$11:INDIRECT("'Полная ст-ть с уч.НЗС (Авто)'!HQ"&$J$26))/$D11) -> 0 | HR11: =IF($D11=0,0,SUMIF('Полная ст-ть с уч.НЗС (Авто)'!$YO$11:INDIRECT("'Полная ст-ть с уч.НЗС (Авто)'!YO"&$J$26),$C11,'Полная ст-ть с уч.НЗС (Авто)'!HR$11:INDIRECT("'Полная ст-ть с уч.НЗС (Авто)'!HR"&$J$26))/$D11) -> 0 | HS11: =IF($D11=0,0,SUMIF('Полная ст-ть с уч.НЗС (Авто)'!$YO$11:INDIRECT("'Полная ст-ть с уч.НЗС (Авто)'!YO"&$J$26),$C11,'Полная ст-ть с уч.НЗС (Авто)'!HS$11:INDIRECT("'Полная ст-ть с уч.НЗС (Авто)'!HS"&$J$26))/$D11) -> 0 | HT11: =IF($D11=0,0,SUMIF('Полная ст-ть с уч.НЗС (Авто)'!$YO$11:INDIRECT("'Полная ст-ть с уч.НЗС (Авто)'!YO"&$J$26),$C11,'Полная ст-ть с уч.НЗС (Авто)'!HT$11:INDIRECT("'Полная ст-ть с уч.НЗС (Авто)'!HT"&$J$26))/$D11) -> 0 | HU11: =IF($D11=0,0,SUMIF('Полная ст-ть с уч.НЗС (Авто)'!$YO$11:INDIRECT("'Полная ст-ть с уч.НЗС (Авто)'!YO"&$J$26),$C11,'Полная ст-ть с уч.НЗС (Авто)'!HU$11:INDIRECT("'Полная ст-ть с уч.НЗС (Авто)'!HU"&$J$26))/$D11) -> 0 | HV11: =IF($D11=0,0,SUMIF('Полная ст-ть с уч.НЗС (Авто)'!$YO$11:INDIRECT("'Полная ст-ть с уч.НЗС (Авто)'!YO"&$J$26),$C11,'Полная ст-ть с уч.НЗС (Авто)'!HV$11:INDIRECT("'Полная ст-ть с уч.НЗС (Авто)'!HV"&$J$26))/$D11) -> 0 | HW11: =IF($D11=0,0,SUMIF('Полная ст-ть с уч.НЗС (Авто)'!$YO$11:INDIRECT("'Полная ст-ть с уч.НЗС (Авто)'!YO"&$J$26),$C11,'Полная ст-ть с уч.НЗС (Авто)'!HW$11:INDIRECT("'Полная ст-ть с уч.НЗС (Авто)'!HW"&$J$26))/$D11) -> 0 | HX11: =IF($D11=0,0,SUMIF('Полная ст-ть с уч.НЗС (Авто)'!$YO$11:INDIRECT("'Полная ст-ть с уч.НЗС (Авто)'!YO"&$J$26),$C11,'Полная ст-ть с уч.НЗС (Авто)'!HX$11:INDIRECT("'Полная ст-ть с уч.НЗС (Авто)'!HX"&$J$26))/$D11) -> 0 | HY11: =IF($D11=0,0,SUMIF('Полная ст-ть с уч.НЗС (Авто)'!$YO$11:INDIRECT("'Полная ст-ть с уч.НЗС (Авто)'!YO"&$J$26),$C11,'Полная ст-ть с уч.НЗС (Авто)'!HY$11:INDIRECT("'Полная ст-ть с уч.НЗС (Авто)'!HY"&$J$26))/$D11) -> 0 | HZ11: =IF($D11=0,0,SUMIF('Полная ст-ть с уч.НЗС (Авто)'!$YO$11:INDIRECT("'Полная ст-ть с уч.НЗС (Авто)'!YO"&$J$26),$C11,'Полная ст-ть с уч.НЗС (Авто)'!HZ$11:INDIRECT("'Полная ст-ть с уч.НЗС (Авто)'!HZ"&$J$26))/$D11) -> 0 | IA11: =IF($D11=0,0,SUMIF('Полная ст-ть с уч.НЗС (Авто)'!$YO$11:INDIRECT("'Полная ст-ть с уч.НЗС (Авто)'!YO"&$J$26),$C11,'Полная ст-ть с уч.НЗС (Авто)'!IA$11:INDIRECT("'Полная ст-ть с уч.НЗС (Авто)'!IA"&$J$26))/$D11) -> 0 | IB11: =IF($D11=0,0,SUMIF('Полная ст-ть с уч.НЗС (Авто)'!$YO$11:INDIRECT("'Полная ст-ть с уч.НЗС (Авто)'!YO"&$J$26),$C11,'Полная ст-ть с уч.НЗС (Авто)'!IB$11:INDIRECT("'Полная ст-ть с уч.НЗС (Авто)'!IB"&$J$26))/$D11) -> 0 | IC11: =IF($D11=0,0,SUMIF('Полная ст-ть с уч.НЗС (Авто)'!$YO$11:INDIRECT("'Полная ст-ть с уч.НЗС (Авто)'!YO"&$J$26),$C11,'Полная ст-ть с уч.НЗС (Авто)'!IC$11:INDIRECT("'Полная ст-ть с уч.НЗС (Авто)'!IC"&$J$26))/$D11) -> 0 | ID11: =IF($D11=0,0,SUMIF('Полная ст-ть с уч.НЗС (Авто)'!$YO$11:INDIRECT("'Полная ст-ть с уч.НЗС (Авто)'!YO"&$J$26),$C11,'Полная ст-ть с уч.НЗС (Авто)'!ID$11:INDIRECT("'Полная ст-ть с уч.НЗС (Авто)'!ID"&$J$26))/$D11) -> 0 | IE11: =IF($D11=0,0,SUMIF('Полная ст-ть с уч.НЗС (Авто)'!$YO$11:INDIRECT("'Полная ст-ть с уч.НЗС (Авто)'!YO"&$J$26),$C11,'Полная ст-ть с уч.НЗС (Авто)'!IE$11:INDIRECT("'Полная ст-ть с уч.НЗС (Авто)'!IE"&$J$26))/$D11) -> 0 | IF11: =IF($D11=0,0,SUMIF('Полная ст-ть с уч.НЗС (Авто)'!$YO$11:INDIRECT("'Полная ст-ть с уч.НЗС (Авто)'!YO"&$J$26),$C11,'Полная ст-ть с уч.НЗС (Авто)'!IF$11:INDIRECT("'Полная ст-ть с уч.НЗС (Авто)'!IF"&$J$26))/$D11) -> 0 | IG11: =IF($D11=0,0,SUMIF('Полная ст-ть с уч.НЗС (Авто)'!$YO$11:INDIRECT("'Полная ст-ть с уч.НЗС (Авто)'!YO"&$J$26),$C11,'Полная ст-ть с уч.НЗС (Авто)'!IG$11:INDIRECT("'Полная ст-ть с уч.НЗС (Авто)'!IG"&$J$26))/$D11) -> 0 | IH11: =IF($D11=0,0,SUMIF('Полная ст-ть с уч.НЗС (Авто)'!$YO$11:INDIRECT("'Полная ст-ть с уч.НЗС (Авто)'!YO"&$J$26),$C11,'Полная ст-ть с уч.НЗС (Авто)'!IH$11:INDIRECT("'Полная ст-ть с уч.НЗС (Авто)'!IH"&$J$26))/$D11) -> 0 | II11: =IF($D11=0,0,SUMIF('Полная ст-ть с уч.НЗС (Авто)'!$YO$11:INDIRECT("'Полная ст-ть с уч.НЗС (Авто)'!YO"&$J$26),$C11,'Полная ст-ть с уч.НЗС (Авто)'!II$11:INDIRECT("'Полная ст-ть с уч.НЗС (Авто)'!II"&$J$26))/$D11) -> 0 | IJ11: =IF($D11=0,0,SUMIF('Полная ст-ть с уч.НЗС (Авто)'!$YO$11:INDIRECT("'Полная ст-ть с уч.НЗС (Авто)'!YO"&$J$26),$C11,'Полная ст-ть с уч.НЗС (Авто)'!IJ$11:INDIRECT("'Полная ст-ть с уч.НЗС (Авто)'!IJ"&$J$26))/$D11) -> 0 | IK11: =IF($D11=0,0,SUMIF('Полная ст-ть с уч.НЗС (Авто)'!$YO$11:INDIRECT("'Полная ст-ть с уч.НЗС (Авто)'!YO"&$J$26),$C11,'Полная ст-ть с уч.НЗС (Авто)'!IK$11:INDIRECT("'Полная ст-ть с уч.НЗС (Авто)'!IK"&$J$26))/$D11) -> 0 | IL11: =IF($D11=0,0,SUMIF('Полная ст-ть с уч.НЗС (Авто)'!$YO$11:INDIRECT("'Полная ст-ть с уч.НЗС (Авто)'!YO"&$J$26),$C11,'Полная ст-ть с уч.НЗС (Авто)'!IL$11:INDIRECT("'Полная ст-ть с уч.НЗС (Авто)'!IL"&$J$26))/$D11) -> 0 | IM11: =IF($D11=0,0,SUMIF('Полная ст-ть с уч.НЗС (Авто)'!$YO$11:INDIRECT("'Полная ст-ть с уч.НЗС (Авто)'!YO"&$J$26),$C11,'Полная ст-ть с уч.НЗС (Авто)'!IM$11:INDIRECT("'Полная ст-ть с уч.НЗС (Авто)'!IM"&$J$26))/$D11) -> 0 | IN11: =IF($D11=0,0,SUMIF('Полная ст-ть с уч.НЗС (Авто)'!$YO$11:INDIRECT("'Полная ст-ть с уч.НЗС (Авто)'!YO"&$J$26),$C11,'Полная ст-ть с уч.НЗС (Авто)'!IN$11:INDIRECT("'Полная ст-ть с уч.НЗС (Авто)'!IN"&$J$26))/$D11) -> 0 | IO11: =IF($D11=0,0,SUMIF('Полная ст-ть с уч.НЗС (Авто)'!$YO$11:INDIRECT("'Полная ст-ть с уч.НЗС (Авто)'!YO"&$J$26),$C11,'Полная ст-ть с уч.НЗС (Авто)'!IO$11:INDIRECT("'Полная ст-ть с уч.НЗС (Авто)'!IO"&$J$26))/$D11) -> 0 | IP11: =IF($D11=0,0,SUMIF('Полная ст-ть с уч.НЗС (Авто)'!$YO$11:INDIRECT("'Полная ст-ть с уч.НЗС (Авто)'!YO"&$J$26),$C11,'Полная ст-ть с уч.НЗС (Авто)'!IP$11:INDIRECT("'Полная ст-ть с уч.НЗС (Авто)'!IP"&$J$26))/$D11) -> 0 | IQ11: =IF($D11=0,0,SUMIF('Полная ст-ть с уч.НЗС (Авто)'!$YO$11:INDIRECT("'Полная ст-ть с уч.НЗС (Авто)'!YO"&$J$26),$C11,'Полная ст-ть с уч.НЗС (Авто)'!IQ$11:INDIRECT("'Полная ст-ть с уч.НЗС (Авто)'!IQ"&$J$26))/$D11) -> 0 | IR11: =IF($D11=0,0,SUMIF('Полная ст-ть с уч.НЗС (Авто)'!$YO$11:INDIRECT("'Полная ст-ть с уч.НЗС (Авто)'!YO"&$J$26),$C11,'Полная ст-ть с уч.НЗС (Авто)'!IR$11:INDIRECT("'Полная ст-ть с уч.НЗС (Авто)'!IR"&$J$26))/$D11) -> 0 | IS11: =IF($D11=0,0,SUMIF('Полная ст-ть с уч.НЗС (Авто)'!$YO$11:INDIRECT("'Полная ст-ть с уч.НЗС (Авто)'!YO"&$J$26),$C11,'Полная ст-ть с уч.НЗС (Авто)'!IS$11:INDIRECT("'Полная ст-ть с уч.НЗС (Авто)'!IS"&$J$26))/$D11) -> 0 | IT11: =IF($D11=0,0,SUMIF('Полная ст-ть с уч.НЗС (Авто)'!$YO$11:INDIRECT("'Полная ст-ть с уч.НЗС (Авто)'!YO"&$J$26),$C11,'Полная ст-ть с уч.НЗС (Авто)'!IT$11:INDIRECT("'Полная ст-ть с уч.НЗС (Авто)'!IT"&$J$26))/$D11) -> 0 | IU11: =IF($D11=0,0,SUMIF('Полная ст-ть с уч.НЗС (Авто)'!$YO$11:INDIRECT("'Полная ст-ть с уч.НЗС (Авто)'!YO"&$J$26),$C11,'Полная ст-ть с уч.НЗС (Авто)'!IU$11:INDIRECT("'Полная ст-ть с уч.НЗС (Авто)'!IU"&$J$26))/$D11) -> 0 | IV11: =IF($D11=0,0,SUMIF('Полная ст-ть с уч.НЗС (Авто)'!$YO$11:INDIRECT("'Полная ст-ть с уч.НЗС (Авто)'!YO"&$J$26),$C11,'Полная ст-ть с уч.НЗС (Авто)'!IV$11:INDIRECT("'Полная ст-ть с уч.НЗС (Авто)'!IV"&$J$26))/$D11) -> 0 | IW11: =IF($D11=0,0,SUMIF('Полная ст-ть с уч.НЗС (Авто)'!$YO$11:INDIRECT("'Полная ст-ть с уч.НЗС (Авто)'!YO"&$J$26),$C11,'Полная ст-ть с уч.НЗС (Авто)'!IW$11:INDIRECT("'Полная ст-ть с уч.НЗС (Авто)'!IW"&$J$26))/$D11) -> 0 | IX11: =IF($D11=0,0,SUMIF('Полная ст-ть с уч.НЗС (Авто)'!$YO$11:INDIRECT("'Полная ст-ть с уч.НЗС (Авто)'!YO"&$J$26),$C11,'Полная ст-ть с уч.НЗС (Авто)'!IX$11:INDIRECT("'Полная ст-ть с уч.НЗС (Авто)'!IX"&$J$26))/$D11) -> 0 | IY11: =IF($D11=0,0,SUMIF('Полная ст-ть с уч.НЗС (Авто)'!$YO$11:INDIRECT("'Полная ст-ть с уч.НЗС (Авто)'!YO"&$J$26),$C11,'Полная ст-ть с уч.НЗС (Авто)'!IY$11:INDIRECT("'Полная ст-ть с уч.НЗС (Авто)'!IY"&$J$26))/$D11) -> 0 | IZ11: =IF($D11=0,0,SUMIF('Полная ст-ть с уч.НЗС (Авто)'!$YO$11:INDIRECT("'Полная ст-ть с уч.НЗС (Авто)'!YO"&$J$26),$C11,'Полная ст-ть с уч.НЗС (Авто)'!IZ$11:INDIRECT("'Полная ст-ть с уч.НЗС (Авто)'!IZ"&$J$26))/$D11) -> 0 | JA11: =IF($D11=0,0,SUMIF('Полная ст-ть с уч.НЗС (Авто)'!$YO$11:INDIRECT("'Полная ст-ть с уч.НЗС (Авто)'!YO"&$J$26),$C11,'Полная ст-ть с уч.НЗС (Авто)'!JA$11:INDIRECT("'Полная ст-ть с уч.НЗС (Авто)'!JA"&$J$26))/$D11) -> 0 | JB11: =IF($D11=0,0,SUMIF('Полная ст-ть с уч.НЗС (Авто)'!$YO$11:INDIRECT("'Полная ст-ть с уч.НЗС (Авто)'!YO"&$J$26),$C11,'Полная ст-ть с уч.НЗС (Авто)'!JB$11:INDIRECT("'Полная ст-ть с уч.НЗС (Авто)'!JB"&$J$26))/$D11) -> 0 | JC11: =IF($D11=0,0,SUMIF('Полная ст-ть с уч.НЗС (Авто)'!$YO$11:INDIRECT("'Полная ст-ть с уч.НЗС (Авто)'!YO"&$J$26),$C11,'Полная ст-ть с уч.НЗС (Авто)'!JC$11:INDIRECT("'Полная ст-ть с уч.НЗС (Авто)'!JC"&$J$26))/$D11) -> 0 | JD11: =IF($D11=0,0,SUMIF('Полная ст-ть с уч.НЗС (Авто)'!$YO$11:INDIRECT("'Полная ст-ть с уч.НЗС (Авто)'!YO"&$J$26),$C11,'Полная ст-ть с уч.НЗС (Авто)'!JD$11:INDIRECT("'Полная ст-ть с уч.НЗС (Авто)'!JD"&$J$26))/$D11) -> 0 | JE11: =IF($D11=0,0,SUMIF('Полная ст-ть с уч.НЗС (Авто)'!$YO$11:INDIRECT("'Полная ст-ть с уч.НЗС (Авто)'!YO"&$J$26),$C11,'Полная ст-ть с уч.НЗС (Авто)'!JE$11:INDIRECT("'Полная ст-ть с уч.НЗС (Авто)'!JE"&$J$26))/$D11) -> 0 | JF11: =IF($D11=0,0,SUMIF('Полная ст-ть с уч.НЗС (Авто)'!$YO$11:INDIRECT("'Полная ст-ть с уч.НЗС (Авто)'!YO"&$J$26),$C11,'Полная ст-ть с уч.НЗС (Авто)'!JF$11:INDIRECT("'Полная ст-ть с уч.НЗС (Авто)'!JF"&$J$26))/$D11) -> 0 | JG11: =IF($D11=0,0,SUMIF('Полная ст-ть с уч.НЗС (Авто)'!$YO$11:INDIRECT("'Полная ст-ть с уч.НЗС (Авто)'!YO"&$J$26),$C11,'Полная ст-ть с уч.НЗС (Авто)'!JG$11:INDIRECT("'Полная ст-ть с уч.НЗС (Авто)'!JG"&$J$26))/$D11) -> 0 | JH11: =IF($D11=0,0,SUMIF('Полная ст-ть с уч.НЗС (Авто)'!$YO$11:INDIRECT("'Полная ст-ть с уч.НЗС (Авто)'!YO"&$J$26),$C11,'Полная ст-ть с уч.НЗС (Авто)'!JH$11:INDIRECT("'Полная ст-ть с уч.НЗС (Авто)'!JH"&$J$26))/$D11) -> 0 | JI11: =IF($D11=0,0,SUMIF('Полная ст-ть с уч.НЗС (Авто)'!$YO$11:INDIRECT("'Полная ст-ть с уч.НЗС (Авто)'!YO"&$J$26),$C11,'Полная ст-ть с уч.НЗС (Авто)'!JI$11:INDIRECT("'Полная ст-ть с уч.НЗС (Авто)'!JI"&$J$26))/$D11) -> 0 | JJ11: =IF($D11=0,0,SUMIF('Полная ст-ть с уч.НЗС (Авто)'!$YO$11:INDIRECT("'Полная ст-ть с уч.НЗС (Авто)'!YO"&$J$26),$C11,'Полная ст-ть с уч.НЗС (Авто)'!JJ$11:INDIRECT("'Полная ст-ть с уч.НЗС (Авто)'!JJ"&$J$26))/$D11) -> 0 | JK11: =IF($D11=0,0,SUMIF('Полная ст-ть с уч.НЗС (Авто)'!$YO$11:INDIRECT("'Полная ст-ть с уч.НЗС (Авто)'!YO"&$J$26),$C11,'Полная ст-ть с уч.НЗС (Авто)'!JK$11:INDIRECT("'Полная ст-ть с уч.НЗС (Авто)'!JK"&$J$26))/$D11) -> 0 | JL11: =IF($D11=0,0,SUMIF('Полная ст-ть с уч.НЗС (Авто)'!$YO$11:INDIRECT("'Полная ст-ть с уч.НЗС (Авто)'!YO"&$J$26),$C11,'Полная ст-ть с уч.НЗС (Авто)'!JL$11:INDIRECT("'Полная ст-ть с уч.НЗС (Авто)'!JL"&$J$26))/$D11) -> 0 | JM11: =IF($D11=0,0,SUMIF('Полная ст-ть с уч.НЗС (Авто)'!$YO$11:INDIRECT("'Полная ст-ть с уч.НЗС (Авто)'!YO"&$J$26),$C11,'Полная ст-ть с уч.НЗС (Авто)'!JM$11:INDIRECT("'Полная ст-ть с уч.НЗС (Авто)'!JM"&$J$26))/$D11) -> 0 | JN11: =IF($D11=0,0,SUMIF('Полная ст-ть с уч.НЗС (Авто)'!$YO$11:INDIRECT("'Полная ст-ть с уч.НЗС (Авто)'!YO"&$J$26),$C11,'Полная ст-ть с уч.НЗС (Авто)'!JN$11:INDIRECT("'Полная ст-ть с уч.НЗС (Авто)'!JN"&$J$26))/$D11) -> 0 | JO11: =IF($D11=0,0,SUMIF('Полная ст-ть с уч.НЗС (Авто)'!$YO$11:INDIRECT("'Полная ст-ть с уч.НЗС (Авто)'!YO"&$J$26),$C11,'Полная ст-ть с уч.НЗС (Авто)'!JO$11:INDIRECT("'Полная ст-ть с уч.НЗС (Авто)'!JO"&$J$26))/$D11) -> 0 | JP11: =IF($D11=0,0,SUMIF('Полная ст-ть с уч.НЗС (Авто)'!$YO$11:INDIRECT("'Полная ст-ть с уч.НЗС (Авто)'!YO"&$J$26),$C11,'Полная ст-ть с уч.НЗС (Авто)'!JP$11:INDIRECT("'Полная ст-ть с уч.НЗС (Авто)'!JP"&$J$26))/$D11) -> 0 | JQ11: =IF($D11=0,0,SUMIF('Полная ст-ть с уч.НЗС (Авто)'!$YO$11:INDIRECT("'Полная ст-ть с уч.НЗС (Авто)'!YO"&$J$26),$C11,'Полная ст-ть с уч.НЗС (Авто)'!JQ$11:INDIRECT("'Полная ст-ть с уч.НЗС (Авто)'!JQ"&$J$26))/$D11) -> 0 | JR11: =IF($D11=0,0,SUMIF('Полная ст-ть с уч.НЗС (Авто)'!$YO$11:INDIRECT("'Полная ст-ть с уч.НЗС (Авто)'!YO"&$J$26),$C11,'Полная ст-ть с уч.НЗС (Авто)'!JR$11:INDIRECT("'Полная ст-ть с уч.НЗС (Авто)'!JR"&$J$26))/$D11) -> 0 | JS11: =IF($D11=0,0,SUMIF('Полная ст-ть с уч.НЗС (Авто)'!$YO$11:INDIRECT("'Полная ст-ть с уч.НЗС (Авто)'!YO"&$J$26),$C11,'Полная ст-ть с уч.НЗС (Авто)'!JS$11:INDIRECT("'Полная ст-ть с уч.НЗС (Авто)'!JS"&$J$26))/$D11) -> 0 | JT11: =IF($D11=0,0,SUMIF('Полная ст-ть с уч.НЗС (Авто)'!$YO$11:INDIRECT("'Полная ст-ть с уч.НЗС (Авто)'!YO"&$J$26),$C11,'Полная ст-ть с уч.НЗС (Авто)'!JT$11:INDIRECT("'Полная ст-ть с уч.НЗС (Авто)'!JT"&$J$26))/$D11) -> 0 | JU11: =IF($D11=0,0,SUMIF('Полная ст-ть с уч.НЗС (Авто)'!$YO$11:INDIRECT("'Полная ст-ть с уч.НЗС (Авто)'!YO"&$J$26),$C11,'Полная ст-ть с уч.НЗС (Авто)'!JU$11:INDIRECT("'Полная ст-ть с уч.НЗС (Авто)'!JU"&$J$26))/$D11) -> 0 | JV11: =IF($D11=0,0,SUMIF('Полная ст-ть с уч.НЗС (Авто)'!$YO$11:INDIRECT("'Полная ст-ть с уч.НЗС (Авто)'!YO"&$J$26),$C11,'Полная ст-ть с уч.НЗС (Авто)'!JV$11:INDIRECT("'Полная ст-ть с уч.НЗС (Авто)'!JV"&$J$26))/$D11) -> 0 | JW11: =IF($D11=0,0,SUMIF('Полная ст-ть с уч.НЗС (Авто)'!$YO$11:INDIRECT("'Полная ст-ть с уч.НЗС (Авто)'!YO"&$J$26),$C11,'Полная ст-ть с уч.НЗС (Авто)'!JW$11:INDIRECT("'Полная ст-ть с уч.НЗС (Авто)'!JW"&$J$26))/$D11) -> 0 | JX11: =IF($D11=0,0,SUMIF('Полная ст-ть с уч.НЗС (Авто)'!$YO$11:INDIRECT("'Полная ст-ть с уч.НЗС (Авто)'!YO"&$J$26),$C11,'Полная ст-ть с уч.НЗС (Авто)'!JX$11:INDIRECT("'Полная ст-ть с уч.НЗС (Авто)'!JX"&$J$26))/$D11) -> 0 | JY11: =IF($D11=0,0,SUMIF('Полная ст-ть с уч.НЗС (Авто)'!$YO$11:INDIRECT("'Полная ст-ть с уч.НЗС (Авто)'!YO"&$J$26),$C11,'Полная ст-ть с уч.НЗС (Авто)'!JY$11:INDIRECT("'Полная ст-ть с уч.НЗС (Авто)'!JY"&$J$26))/$D11) -> 0 | JZ11: =IF($D11=0,0,SUMIF('Полная ст-ть с уч.НЗС (Авто)'!$YO$11:INDIRECT("'Полная ст-ть с уч.НЗС (Авто)'!YO"&$J$26),$C11,'Полная ст-ть с уч.НЗС (Авто)'!JZ$11:INDIRECT("'Полная ст-ть с уч.НЗС (Авто)'!JZ"&$J$26))/$D11) -> 0 | KA11: =IF($D11=0,0,SUMIF('Полная ст-ть с уч.НЗС (Авто)'!$YO$11:INDIRECT("'Полная ст-ть с уч.НЗС (Авто)'!YO"&$J$26),$C11,'Полная ст-ть с уч.НЗС (Авто)'!KA$11:INDIRECT("'Полная ст-ть с уч.НЗС (Авто)'!KA"&$J$26))/$D11) -> 0 | KB11: =IF($D11=0,0,SUMIF('Полная ст-ть с уч.НЗС (Авто)'!$YO$11:INDIRECT("'Полная ст-ть с уч.НЗС (Авто)'!YO"&$J$26),$C11,'Полная ст-ть с уч.НЗС (Авто)'!KB$11:INDIRECT("'Полная ст-ть с уч.НЗС (Авто)'!KB"&$J$26))/$D11) -> 0 | KC11: =IF($D11=0,0,SUMIF('Полная ст-ть с уч.НЗС (Авто)'!$YO$11:INDIRECT("'Полная ст-ть с уч.НЗС (Авто)'!YO"&$J$26),$C11,'Полная ст-ть с уч.НЗС (Авто)'!KC$11:INDIRECT("'Полная ст-ть с уч.НЗС (Авто)'!KC"&$J$26))/$D11) -> 0 | KD11: =IF($D11=0,0,SUMIF('Полная ст-ть с уч.НЗС (Авто)'!$YO$11:INDIRECT("'Полная ст-ть с уч.НЗС (Авто)'!YO"&$J$26),$C11,'Полная ст-ть с уч.НЗС (Авто)'!KD$11:INDIRECT("'Полная ст-ть с уч.НЗС (Авто)'!KD"&$J$26))/$D11) -> 0 | KE11: =IF($D11=0,0,SUMIF('Полная ст-ть с уч.НЗС (Авто)'!$YO$11:INDIRECT("'Полная ст-ть с уч.НЗС (Авто)'!YO"&$J$26),$C11,'Полная ст-ть с уч.НЗС (Авто)'!KE$11:INDIRECT("'Полная ст-ть с уч.НЗС (Авто)'!KE"&$J$26))/$D11) -> 0 | KF11: =IF($D11=0,0,SUMIF('Полная ст-ть с уч.НЗС (Авто)'!$YO$11:INDIRECT("'Полная ст-ть с уч.НЗС (Авто)'!YO"&$J$26),$C11,'Полная ст-ть с уч.НЗС (Авто)'!KF$11:INDIRECT("'Полная ст-ть с уч.НЗС (Авто)'!KF"&$J$26))/$D11) -> 0 | KG11: =IF($D11=0,0,SUMIF('Полная ст-ть с уч.НЗС (Авто)'!$YO$11:INDIRECT("'Полная ст-ть с уч.НЗС (Авто)'!YO"&$J$26),$C11,'Полная ст-ть с уч.НЗС (Авто)'!KG$11:INDIRECT("'Полная ст-ть с уч.НЗС (Авто)'!KG"&$J$26))/$D11) -> 0 | KH11: =IF($D11=0,0,SUMIF('Полная ст-ть с уч.НЗС (Авто)'!$YO$11:INDIRECT("'Полная ст-ть с уч.НЗС (Авто)'!YO"&$J$26),$C11,'Полная ст-ть с уч.НЗС (Авто)'!KH$11:INDIRECT("'Полная ст-ть с уч.НЗС (Авто)'!KH"&$J$26))/$D11) -> 0 | KI11: =IF($D11=0,0,SUMIF('Полная ст-ть с уч.НЗС (Авто)'!$YO$11:INDIRECT("'Полная ст-ть с уч.НЗС (Авто)'!YO"&$J$26),$C11,'Полная ст-ть с уч.НЗС (Авто)'!KI$11:INDIRECT("'Полная ст-ть с уч.НЗС (Авто)'!KI"&$J$26))/$D11) -> 0 | KJ11: =IF($D11=0,0,SUMIF('Полная ст-ть с уч.НЗС (Авто)'!$YO$11:INDIRECT("'Полная ст-ть с уч.НЗС (Авто)'!YO"&$J$26),$C11,'Полная ст-ть с уч.НЗС (Авто)'!KJ$11:INDIRECT("'Полная ст-ть с уч.НЗС (Авто)'!KJ"&$J$26))/$D11) -> 0 | KK11: =IF($D11=0,0,SUMIF('Полная ст-ть с уч.НЗС (Авто)'!$YO$11:INDIRECT("'Полная ст-ть с уч.НЗС (Авто)'!YO"&$J$26),$C11,'Полная ст-ть с уч.НЗС (Авто)'!KK$11:INDIRECT("'Полная ст-ть с уч.НЗС (Авто)'!KK"&$J$26))/$D11) -> 0 | KL11: =IF($D11=0,0,SUMIF('Полная ст-ть с уч.НЗС (Авто)'!$YO$11:INDIRECT("'Полная ст-ть с уч.НЗС (Авто)'!YO"&$J$26),$C11,'Полная ст-ть с уч.НЗС (Авто)'!KL$11:INDIRECT("'Полная ст-ть с уч.НЗС (Авто)'!KL"&$J$26))/$D11) -> 0 | KM11: =IF($D11=0,0,SUMIF('Полная ст-ть с уч.НЗС (Авто)'!$YO$11:INDIRECT("'Полная ст-ть с уч.НЗС (Авто)'!YO"&$J$26),$C11,'Полная ст-ть с уч.НЗС (Авто)'!KM$11:INDIRECT("'Полная ст-ть с уч.НЗС (Авто)'!KM"&$J$26))/$D11) -> 0 | KN11: =IF($D11=0,0,SUMIF('Полная ст-ть с уч.НЗС (Авто)'!$YO$11:INDIRECT("'Полная ст-ть с уч.НЗС (Авто)'!YO"&$J$26),$C11,'Полная ст-ть с уч.НЗС (Авто)'!KN$11:INDIRECT("'Полная ст-ть с уч.НЗС (Авто)'!KN"&$J$26))/$D11) -> 0 | KO11: =IF($D11=0,0,SUMIF('Полная ст-ть с уч.НЗС (Авто)'!$YO$11:INDIRECT("'Полная ст-ть с уч.НЗС (Авто)'!YO"&$J$26),$C11,'Полная ст-ть с уч.НЗС (Авто)'!KO$11:INDIRECT("'Полная ст-ть с уч.НЗС (Авто)'!KO"&$J$26))/$D11) -> 0 | KP11: =IF($D11=0,0,SUMIF('Полная ст-ть с уч.НЗС (Авто)'!$YO$11:INDIRECT("'Полная ст-ть с уч.НЗС (Авто)'!YO"&$J$26),$C11,'Полная ст-ть с уч.НЗС (Авто)'!KP$11:INDIRECT("'Полная ст-ть с уч.НЗС (Авто)'!KP"&$J$26))/$D11) -> 0 | KQ11: =IF($D11=0,0,SUMIF('Полная ст-ть с уч.НЗС (Авто)'!$YO$11:INDIRECT("'Полная ст-ть с уч.НЗС (Авто)'!YO"&$J$26),$C11,'Полная ст-ть с уч.НЗС (Авто)'!KQ$11:INDIRECT("'Полная ст-ть с уч.НЗС (Авто)'!KQ"&$J$26))/$D11) -> 0 | KR11: =IF($D11=0,0,SUMIF('Полная ст-ть с уч.НЗС (Авто)'!$YO$11:INDIRECT("'Полная ст-ть с уч.НЗС (Авто)'!YO"&$J$26),$C11,'Полная ст-ть с уч.НЗС (Авто)'!KR$11:INDIRECT("'Полная ст-ть с уч.НЗС (Авто)'!KR"&$J$26))/$D11) -> 0 | KS11: =IF($D11=0,0,SUMIF('Полная ст-ть с уч.НЗС (Авто)'!$YO$11:INDIRECT("'Полная ст-ть с уч.НЗС (Авто)'!YO"&$J$26),$C11,'Полная ст-ть с уч.НЗС (Авто)'!KS$11:INDIRECT("'Полная ст-ть с уч.НЗС (Авто)'!KS"&$J$26))/$D11) -> 0 | KT11: =IF($D11=0,0,SUMIF('Полная ст-ть с уч.НЗС (Авто)'!$YO$11:INDIRECT("'Полная ст-ть с уч.НЗС (Авто)'!YO"&$J$26),$C11,'Полная ст-ть с уч.НЗС (Авто)'!KT$11:INDIRECT("'Полная ст-ть с уч.НЗС (Авто)'!KT"&$J$26))/$D11) -> 0 | KU11: =IF($D11=0,0,SUMIF('Полная ст-ть с уч.НЗС (Авто)'!$YO$11:INDIRECT("'Полная ст-ть с уч.НЗС (Авто)'!YO"&$J$26),$C11,'Полная ст-ть с уч.НЗС (Авто)'!KU$11:INDIRECT("'Полная ст-ть с уч.НЗС (Авто)'!KU"&$J$26))/$D11) -> 0 | KV11: =IF($D11=0,0,SUMIF('Полная ст-ть с уч.НЗС (Авто)'!$YO$11:INDIRECT("'Полная ст-ть с уч.НЗС (Авто)'!YO"&$J$26),$C11,'Полная ст-ть с уч.НЗС (Авто)'!KV$11:INDIRECT("'Полная ст-ть с уч.НЗС (Авто)'!KV"&$J$26))/$D11) -> 0 | KW11: =IF($D11=0,0,SUMIF('Полная ст-ть с уч.НЗС (Авто)'!$YO$11:INDIRECT("'Полная ст-ть с уч.НЗС (Авто)'!YO"&$J$26),$C11,'Полная ст-ть с уч.НЗС (Авто)'!KW$11:INDIRECT("'Полная ст-ть с уч.НЗС (Авто)'!KW"&$J$26))/$D11) -> 0 | KX11: =IF($D11=0,0,SUMIF('Полная ст-ть с уч.НЗС (Авто)'!$YO$11:INDIRECT("'Полная ст-ть с уч.НЗС (Авто)'!YO"&$J$26),$C11,'Полная ст-ть с уч.НЗС (Авто)'!KX$11:INDIRECT("'Полная ст-ть с уч.НЗС (Авто)'!KX"&$J$26))/$D11) -> 0 | KY11: =IF($D11=0,0,SUMIF('Полная ст-ть с уч.НЗС (Авто)'!$YO$11:INDIRECT("'Полная ст-ть с уч.НЗС (Авто)'!YO"&$J$26),$C11,'Полная ст-ть с уч.НЗС (Авто)'!KY$11:INDIRECT("'Полная ст-ть с уч.НЗС (Авто)'!KY"&$J$26))/$D11) -> 0 | KZ11: =IF($D11=0,0,SUMIF('Полная ст-ть с уч.НЗС (Авто)'!$YO$11:INDIRECT("'Полная ст-ть с уч.НЗС (Авто)'!YO"&$J$26),$C11,'Полная ст-ть с уч.НЗС (Авто)'!KZ$11:INDIRECT("'Полная ст-ть с уч.НЗС (Авто)'!KZ"&$J$26))/$D11) -> 0 | LA11: =IF($D11=0,0,SUMIF('Полная ст-ть с уч.НЗС (Авто)'!$YO$11:INDIRECT("'Полная ст-ть с уч.НЗС (Авто)'!YO"&$J$26),$C11,'Полная ст-ть с уч.НЗС (Авто)'!LA$11:INDIRECT("'Полная ст-ть с уч.НЗС (Авто)'!LA"&$J$26))/$D11) -> 0 | LB11: =IF($D11=0,0,SUMIF('Полная ст-ть с уч.НЗС (Авто)'!$YO$11:INDIRECT("'Полная ст-ть с уч.НЗС (Авто)'!YO"&$J$26),$C11,'Полная ст-ть с уч.НЗС (Авто)'!LB$11:INDIRECT("'Полная ст-ть с уч.НЗС (Авто)'!LB"&$J$26))/$D11) -> 0 | LC11: =IF($D11=0,0,SUMIF('Полная ст-ть с уч.НЗС (Авто)'!$YO$11:INDIRECT("'Полная ст-ть с уч.НЗС (Авто)'!YO"&$J$26),$C11,'Полная ст-ть с уч.НЗС (Авто)'!LC$11:INDIRECT("'Полная ст-ть с уч.НЗС (Авто)'!LC"&$J$26))/$D11) -> 0 | LD11: =IF($D11=0,0,SUMIF('Полная ст-ть с уч.НЗС (Авто)'!$YO$11:INDIRECT("'Полная ст-ть с уч.НЗС (Авто)'!YO"&$J$26),$C11,'Полная ст-ть с уч.НЗС (Авто)'!LD$11:INDIRECT("'Полная ст-ть с уч.НЗС (Авто)'!LD"&$J$26))/$D11) -> 0 | LE11: =IF($D11=0,0,SUMIF('Полная ст-ть с уч.НЗС (Авто)'!$YO$11:INDIRECT("'Полная ст-ть с уч.НЗС (Авто)'!YO"&$J$26),$C11,'Полная ст-ть с уч.НЗС (Авто)'!LE$11:INDIRECT("'Полная ст-ть с уч.НЗС (Авто)'!LE"&$J$26))/$D11) -> 0 | LF11: =IF($D11=0,0,SUMIF('Полная ст-ть с уч.НЗС (Авто)'!$YO$11:INDIRECT("'Полная ст-ть с уч.НЗС (Авто)'!YO"&$J$26),$C11,'Полная ст-ть с уч.НЗС (Авто)'!LF$11:INDIRECT("'Полная ст-ть с уч.НЗС (Авто)'!LF"&$J$26))/$D11) -> 0 | LG11: =IF($D11=0,0,SUMIF('Полная ст-ть с уч.НЗС (Авто)'!$YO$11:INDIRECT("'Полная ст-ть с уч.НЗС (Авто)'!YO"&$J$26),$C11,'Полная ст-ть с уч.НЗС (Авто)'!LG$11:INDIRECT("'Полная ст-ть с уч.НЗС (Авто)'!LG"&$J$26))/$D11) -> 0 | LH11: =IF($D11=0,0,SUMIF('Полная ст-ть с уч.НЗС (Авто)'!$YO$11:INDIRECT("'Полная ст-ть с уч.НЗС (Авто)'!YO"&$J$26),$C11,'Полная ст-ть с уч.НЗС (Авто)'!LH$11:INDIRECT("'Полная ст-ть с уч.НЗС (Авто)'!LH"&$J$26))/$D11) -> 0 | LI11: =IF($D11=0,0,SUMIF('Полная ст-ть с уч.НЗС (Авто)'!$YO$11:INDIRECT("'Полная ст-ть с уч.НЗС (Авто)'!YO"&$J$26),$C11,'Полная ст-ть с уч.НЗС (Авто)'!LI$11:INDIRECT("'Полная ст-ть с уч.НЗС (Авто)'!LI"&$J$26))/$D11) -> 0 | LJ11: =IF($D11=0,0,SUMIF('Полная ст-ть с уч.НЗС (Авто)'!$YO$11:INDIRECT("'Полная ст-ть с уч.НЗС (Авто)'!YO"&$J$26),$C11,'Полная ст-ть с уч.НЗС (Авто)'!LJ$11:INDIRECT("'Полная ст-ть с уч.НЗС (Авто)'!LJ"&$J$26))/$D11) -> 0 | LK11: =IF($D11=0,0,SUMIF('Полная ст-ть с уч.НЗС (Авто)'!$YO$11:INDIRECT("'Полная ст-ть с уч.НЗС (Авто)'!YO"&$J$26),$C11,'Полная ст-ть с уч.НЗС (Авто)'!LK$11:INDIRECT("'Полная ст-ть с уч.НЗС (Авто)'!LK"&$J$26))/$D11) -> 0 | LL11: =IF($D11=0,0,SUMIF('Полная ст-ть с уч.НЗС (Авто)'!$YO$11:INDIRECT("'Полная ст-ть с уч.НЗС (Авто)'!YO"&$J$26),$C11,'Полная ст-ть с уч.НЗС (Авто)'!LL$11:INDIRECT("'Полная ст-ть с уч.НЗС (Авто)'!LL"&$J$26))/$D11) -> 0 | LM11: =IF($D11=0,0,SUMIF('Полная ст-ть с уч.НЗС (Авто)'!$YO$11:INDIRECT("'Полная ст-ть с уч.НЗС (Авто)'!YO"&$J$26),$C11,'Полная ст-ть с уч.НЗС (Авто)'!LM$11:INDIRECT("'Полная ст-ть с уч.НЗС (Авто)'!LM"&$J$26))/$D11) -> 0 | LN11: =IF($D11=0,0,SUMIF('Полная ст-ть с уч.НЗС (Авто)'!$YO$11:INDIRECT("'Полная ст-ть с уч.НЗС (Авто)'!YO"&$J$26),$C11,'Полная ст-ть с уч.НЗС (Авто)'!LN$11:INDIRECT("'Полная ст-ть с уч.НЗС (Авто)'!LN"&$J$26))/$D11) -> 0 | LO11: =IF($D11=0,0,SUMIF('Полная ст-ть с уч.НЗС (Авто)'!$YO$11:INDIRECT("'Полная ст-ть с уч.НЗС (Авто)'!YO"&$J$26),$C11,'Полная ст-ть с уч.НЗС (Авто)'!LO$11:INDIRECT("'Полная ст-ть с уч.НЗС (Авто)'!LO"&$J$26))/$D11) -> 0 | LP11: =IF($D11=0,0,SUMIF('Полная ст-ть с уч.НЗС (Авто)'!$YO$11:INDIRECT("'Полная ст-ть с уч.НЗС (Авто)'!YO"&$J$26),$C11,'Полная ст-ть с уч.НЗС (Авто)'!LP$11:INDIRECT("'Полная ст-ть с уч.НЗС (Авто)'!LP"&$J$26))/$D11) -> 0 | LQ11: =IF($D11=0,0,SUMIF('Полная ст-ть с уч.НЗС (Авто)'!$YO$11:INDIRECT("'Полная ст-ть с уч.НЗС (Авто)'!YO"&$J$26),$C11,'Полная ст-ть с уч.НЗС (Авто)'!LQ$11:INDIRECT("'Полная ст-ть с уч.НЗС (Авто)'!LQ"&$J$26))/$D11) -> 0 | LR11: =IF($D11=0,0,SUMIF('Полная ст-ть с уч.НЗС (Авто)'!$YO$11:INDIRECT("'Полная ст-ть с уч.НЗС (Авто)'!YO"&$J$26),$C11,'Полная ст-ть с уч.НЗС (Авто)'!LR$11:INDIRECT("'Полная ст-ть с уч.НЗС (Авто)'!LR"&$J$26))/$D11) -> 0 | LS11: =IF($D11=0,0,SUMIF('Полная ст-ть с уч.НЗС (Авто)'!$YO$11:INDIRECT("'Полная ст-ть с уч.НЗС (Авто)'!YO"&$J$26),$C11,'Полная ст-ть с уч.НЗС (Авто)'!LS$11:INDIRECT("'Полная ст-ть с уч.НЗС (Авто)'!LS"&$J$26))/$D11) -> 0 | LT11: =IF($D11=0,0,SUMIF('Полная ст-ть с уч.НЗС (Авто)'!$YO$11:INDIRECT("'Полная ст-ть с уч.НЗС (Авто)'!YO"&$J$26),$C11,'Полная ст-ть с уч.НЗС (Авто)'!LT$11:INDIRECT("'Полная ст-ть с уч.НЗС (Авто)'!LT"&$J$26))/$D11) -> 0 | LU11: =IF($D11=0,0,SUMIF('Полная ст-ть с уч.НЗС (Авто)'!$YO$11:INDIRECT("'Полная ст-ть с уч.НЗС (Авто)'!YO"&$J$26),$C11,'Полная ст-ть с уч.НЗС (Авто)'!LU$11:INDIRECT("'Полная ст-ть с уч.НЗС (Авто)'!LU"&$J$26))/$D11) -> 0 | LV11: =IF($D11=0,0,SUMIF('Полная ст-ть с уч.НЗС (Авто)'!$YO$11:INDIRECT("'Полная ст-ть с уч.НЗС (Авто)'!YO"&$J$26),$C11,'Полная ст-ть с уч.НЗС (Авто)'!LV$11:INDIRECT("'Полная ст-ть с уч.НЗС (Авто)'!LV"&$J$26))/$D11) -> 0 | LW11: =IF($D11=0,0,SUMIF('Полная ст-ть с уч.НЗС (Авто)'!$YO$11:INDIRECT("'Полная ст-ть с уч.НЗС (Авто)'!YO"&$J$26),$C11,'Полная ст-ть с уч.НЗС (Авто)'!LW$11:INDIRECT("'Полная ст-ть с уч.НЗС (Авто)'!LW"&$J$26))/$D11) -> 0 | LX11: =IF($D11=0,0,SUMIF('Полная ст-ть с уч.НЗС (Авто)'!$YO$11:INDIRECT("'Полная ст-ть с уч.НЗС (Авто)'!YO"&$J$26),$C11,'Полная ст-ть с уч.НЗС (Авто)'!LX$11:INDIRECT("'Полная ст-ть с уч.НЗС (Авто)'!LX"&$J$26))/$D11) -> 0 | LY11: =IF($D11=0,0,SUMIF('Полная ст-ть с уч.НЗС (Авто)'!$YO$11:INDIRECT("'Полная ст-ть с уч.НЗС (Авто)'!YO"&$J$26),$C11,'Полная ст-ть с уч.НЗС (Авто)'!LY$11:INDIRECT("'Полная ст-ть с уч.НЗС (Авто)'!LY"&$J$26))/$D11) -> 0 | LZ11: =IF($D11=0,0,SUMIF('Полная ст-ть с уч.НЗС (Авто)'!$YO$11:INDIRECT("'Полная ст-ть с уч.НЗС (Авто)'!YO"&$J$26),$C11,'Полная ст-ть с уч.НЗС (Авто)'!LZ$11:INDIRECT("'Полная ст-ть с уч.НЗС (Авто)'!LZ"&$J$26))/$D11) -> 0 | MA11: =IF($D11=0,0,SUMIF('Полная ст-ть с уч.НЗС (Авто)'!$YO$11:INDIRECT("'Полная ст-ть с уч.НЗС (Авто)'!YO"&$J$26),$C11,'Полная ст-ть с уч.НЗС (Авто)'!MA$11:INDIRECT("'Полная ст-ть с уч.НЗС (Авто)'!MA"&$J$26))/$D11) -> 0 | MB11: =IF($D11=0,0,SUMIF('Полная ст-ть с уч.НЗС (Авто)'!$YO$11:INDIRECT("'Полная ст-ть с уч.НЗС (Авто)'!YO"&$J$26),$C11,'Полная ст-ть с уч.НЗС (Авто)'!MB$11:INDIRECT("'Полная ст-ть с уч.НЗС (Авто)'!MB"&$J$26))/$D11) -> 0 | MC11: =IF($D11=0,0,SUMIF('Полная ст-ть с уч.НЗС (Авто)'!$YO$11:INDIRECT("'Полная ст-ть с уч.НЗС (Авто)'!YO"&$J$26),$C11,'Полная ст-ть с уч.НЗС (Авто)'!MC$11:INDIRECT("'Полная ст-ть с уч.НЗС (Авто)'!MC"&$J$26))/$D11) -> 0 | MD11: =IF($D11=0,0,SUMIF('Полная ст-ть с уч.НЗС (Авто)'!$YO$11:INDIRECT("'Полная ст-ть с уч.НЗС (Авто)'!YO"&$J$26),$C11,'Полная ст-ть с уч.НЗС (Авто)'!MD$11:INDIRECT("'Полная ст-ть с уч.НЗС (Авто)'!MD"&$J$26))/$D11) -> 0 | ME11: =IF($D11=0,0,SUMIF('Полная ст-ть с уч.НЗС (Авто)'!$YO$11:INDIRECT("'Полная ст-ть с уч.НЗС (Авто)'!YO"&$J$26),$C11,'Полная ст-ть с уч.НЗС (Авто)'!ME$11:INDIRECT("'Полная ст-ть с уч.НЗС (Авто)'!ME"&$J$26))/$D11) -> 0 | MF11: =IF($D11=0,0,SUMIF('Полная ст-ть с уч.НЗС (Авто)'!$YO$11:INDIRECT("'Полная ст-ть с уч.НЗС (Авто)'!YO"&$J$26),$C11,'Полная ст-ть с уч.НЗС (Авто)'!MF$11:INDIRECT("'Полная ст-ть с уч.НЗС (Авто)'!MF"&$J$26))/$D11) -> 0 | MG11: =IF($D11=0,0,SUMIF('Полная ст-ть с уч.НЗС (Авто)'!$YO$11:INDIRECT("'Полная ст-ть с уч.НЗС (Авто)'!YO"&$J$26),$C11,'Полная ст-ть с уч.НЗС (Авто)'!MG$11:INDIRECT("'Полная ст-ть с уч.НЗС (Авто)'!MG"&$J$26))/$D11) -> 0 | MH11: =IF($D11=0,0,SUMIF('Полная ст-ть с уч.НЗС (Авто)'!$YO$11:INDIRECT("'Полная ст-ть с уч.НЗС (Авто)'!YO"&$J$26),$C11,'Полная ст-ть с уч.НЗС (Авто)'!MH$11:INDIRECT("'Полная ст-ть с уч.НЗС (Авто)'!MH"&$J$26))/$D11) -> 0 | MI11: =IF($D11=0,0,SUMIF('Полная ст-ть с уч.НЗС (Авто)'!$YO$11:INDIRECT("'Полная ст-ть с уч.НЗС (Авто)'!YO"&$J$26),$C11,'Полная ст-ть с уч.НЗС (Авто)'!MI$11:INDIRECT("'Полная ст-ть с уч.НЗС (Авто)'!MI"&$J$26))/$D11) -> 0 | MJ11: =IF($D11=0,0,SUMIF('Полная ст-ть с уч.НЗС (Авто)'!$YO$11:INDIRECT("'Полная ст-ть с уч.НЗС (Авто)'!YO"&$J$26),$C11,'Полная ст-ть с уч.НЗС (Авто)'!MJ$11:INDIRECT("'Полная ст-ть с уч.НЗС (Авто)'!MJ"&$J$26))/$D11) -> 0 | MK11: =IF($D11=0,0,SUMIF('Полная ст-ть с уч.НЗС (Авто)'!$YO$11:INDIRECT("'Полная ст-ть с уч.НЗС (Авто)'!YO"&$J$26),$C11,'Полная ст-ть с уч.НЗС (Авто)'!MK$11:INDIRECT("'Полная ст-ть с уч.НЗС (Авто)'!MK"&$J$26))/$D11) -> 0 | ML11: =IF($D11=0,0,SUMIF('Полная ст-ть с уч.НЗС (Авто)'!$YO$11:INDIRECT("'Полная ст-ть с уч.НЗС (Авто)'!YO"&$J$26),$C11,'Полная ст-ть с уч.НЗС (Авто)'!ML$11:INDIRECT("'Полная ст-ть с уч.НЗС (Авто)'!ML"&$J$26))/$D11) -> 0 | MM11: =IF($D11=0,0,SUMIF('Полная ст-ть с уч.НЗС (Авто)'!$YO$11:INDIRECT("'Полная ст-ть с уч.НЗС (Авто)'!YO"&$J$26),$C11,'Полная ст-ть с уч.НЗС (Авто)'!MM$11:INDIRECT("'Полная ст-ть с уч.НЗС (Авто)'!MM"&$J$26))/$D11) -> 0 | MN11: =IF($D11=0,0,SUMIF('Полная ст-ть с уч.НЗС (Авто)'!$YO$11:INDIRECT("'Полная ст-ть с уч.НЗС (Авто)'!YO"&$J$26),$C11,'Полная ст-ть с уч.НЗС (Авто)'!MN$11:INDIRECT("'Полная ст-ть с уч.НЗС (Авто)'!MN"&$J$26))/$D11) -> 0 | MO11: =IF($D11=0,0,SUMIF('Полная ст-ть с уч.НЗС (Авто)'!$YO$11:INDIRECT("'Полная ст-ть с уч.НЗС (Авто)'!YO"&$J$26),$C11,'Полная ст-ть с уч.НЗС (Авто)'!MO$11:INDIRECT("'Полная ст-ть с уч.НЗС (Авто)'!MO"&$J$26))/$D11) -> 0 | MP11: =IF($D11=0,0,SUMIF('Полная ст-ть с уч.НЗС (Авто)'!$YO$11:INDIRECT("'Полная ст-ть с уч.НЗС (Авто)'!YO"&$J$26),$C11,'Полная ст-ть с уч.НЗС (Авто)'!MP$11:INDIRECT("'Полная ст-ть с уч.НЗС (Авто)'!MP"&$J$26))/$D11) -> 0 | MQ11: =IF($D11=0,0,SUMIF('Полная ст-ть с уч.НЗС (Авто)'!$YO$11:INDIRECT("'Полная ст-ть с уч.НЗС (Авто)'!YO"&$J$26),$C11,'Полная ст-ть с уч.НЗС (Авто)'!MQ$11:INDIRECT("'Полная ст-ть с уч.НЗС (Авто)'!MQ"&$J$26))/$D11) -> 0 | MR11: =IF($D11=0,0,SUMIF('Полная ст-ть с уч.НЗС (Авто)'!$YO$11:INDIRECT("'Полная ст-ть с уч.НЗС (Авто)'!YO"&$J$26),$C11,'Полная ст-ть с уч.НЗС (Авто)'!MR$11:INDIRECT("'Полная ст-ть с уч.НЗС (Авто)'!MR"&$J$26))/$D11) -> 0 | MS11: =IF($D11=0,0,SUMIF('Полная ст-ть с уч.НЗС (Авто)'!$YO$11:INDIRECT("'Полная ст-ть с уч.НЗС (Авто)'!YO"&$J$26),$C11,'Полная ст-ть с уч.НЗС (Авто)'!MS$11:INDIRECT("'Полная ст-ть с уч.НЗС (Авто)'!MS"&$J$26))/$D11) -> 0 | MT11: =IF($D11=0,0,SUMIF('Полная ст-ть с уч.НЗС (Авто)'!$YO$11:INDIRECT("'Полная ст-ть с уч.НЗС (Авто)'!YO"&$J$26),$C11,'Полная ст-ть с уч.НЗС (Авто)'!MT$11:INDIRECT("'Полная ст-ть с уч.НЗС (Авто)'!MT"&$J$26))/$D11) -> 0 | MU11: =IF($D11=0,0,SUMIF('Полная ст-ть с уч.НЗС (Авто)'!$YO$11:INDIRECT("'Полная ст-ть с уч.НЗС (Авто)'!YO"&$J$26),$C11,'Полная ст-ть с уч.НЗС (Авто)'!MU$11:INDIRECT("'Полная ст-ть с уч.НЗС (Авто)'!MU"&$J$26))/$D11) -> 0 | MV11: =IF($D11=0,0,SUMIF('Полная ст-ть с уч.НЗС (Авто)'!$YO$11:INDIRECT("'Полная ст-ть с уч.НЗС (Авто)'!YO"&$J$26),$C11,'Полная ст-ть с уч.НЗС (Авто)'!MV$11:INDIRECT("'Полная ст-ть с уч.НЗС (Авто)'!MV"&$J$26))/$D11) -> 0 | MW11: =IF($D11=0,0,SUMIF('Полная ст-ть с уч.НЗС (Авто)'!$YO$11:INDIRECT("'Полная ст-ть с уч.НЗС (Авто)'!YO"&$J$26),$C11,'Полная ст-ть с уч.НЗС (Авто)'!MW$11:INDIRECT("'Полная ст-ть с уч.НЗС (Авто)'!MW"&$J$26))/$D11) -> 0 | MX11: =IF($D11=0,0,SUMIF('Полная ст-ть с уч.НЗС (Авто)'!$YO$11:INDIRECT("'Полная ст-ть с уч.НЗС (Авто)'!YO"&$J$26),$C11,'Полная ст-ть с уч.НЗС (Авто)'!MX$11:INDIRECT("'Полная ст-ть с уч.НЗС (Авто)'!MX"&$J$26))/$D11) -> 0 | MY11: =IF($D11=0,0,SUMIF('Полная ст-ть с уч.НЗС (Авто)'!$YO$11:INDIRECT("'Полная ст-ть с уч.НЗС (Авто)'!YO"&$J$26),$C11,'Полная ст-ть с уч.НЗС (Авто)'!MY$11:INDIRECT("'Полная ст-ть с уч.НЗС (Авто)'!MY"&$J$26))/$D11) -> 0 | MZ11: =IF($D11=0,0,SUMIF('Полная ст-ть с уч.НЗС (Авто)'!$YO$11:INDIRECT("'Полная ст-ть с уч.НЗС (Авто)'!YO"&$J$26),$C11,'Полная ст-ть с уч.НЗС (Авто)'!MZ$11:INDIRECT("'Полная ст-ть с уч.НЗС (Авто)'!MZ"&$J$26))/$D11) -> 0 | NA11: =IF($D11=0,0,SUMIF('Полная ст-ть с уч.НЗС (Авто)'!$YO$11:INDIRECT("'Полная ст-ть с уч.НЗС (Авто)'!YO"&$J$26),$C11,'Полная ст-ть с уч.НЗС (Авто)'!NA$11:INDIRECT("'Полная ст-ть с уч.НЗС (Авто)'!NA"&$J$26))/$D11) -> 0 | NB11: =IF($D11=0,0,SUMIF('Полная ст-ть с уч.НЗС (Авто)'!$YO$11:INDIRECT("'Полная ст-ть с уч.НЗС (Авто)'!YO"&$J$26),$C11,'Полная ст-ть с уч.НЗС (Авто)'!NB$11:INDIRECT("'Полная ст-ть с уч.НЗС (Авто)'!NB"&$J$26))/$D11) -> 0 | NC11: =IF($D11=0,0,SUMIF('Полная ст-ть с уч.НЗС (Авто)'!$YO$11:INDIRECT("'Полная ст-ть с уч.НЗС (Авто)'!YO"&$J$26),$C11,'Полная ст-ть с уч.НЗС (Авто)'!NC$11:INDIRECT("'Полная ст-ть с уч.НЗС (Авто)'!NC"&$J$26))/$D11) -> 0 | ND11: =IF($D11=0,0,SUMIF('Полная ст-ть с уч.НЗС (Авто)'!$YO$11:INDIRECT("'Полная ст-ть с уч.НЗС (Авто)'!YO"&$J$26),$C11,'Полная ст-ть с уч.НЗС (Авто)'!ND$11:INDIRECT("'Полная ст-ть с уч.НЗС (Авто)'!ND"&$J$26))/$D11) -> 0 | NE11: =IF($D11=0,0,SUMIF('Полная ст-ть с уч.НЗС (Авто)'!$YO$11:INDIRECT("'Полная ст-ть с уч.НЗС (Авто)'!YO"&$J$26),$C11,'Полная ст-ть с уч.НЗС (Авто)'!NE$11:INDIRECT("'Полная ст-ть с уч.НЗС (Авто)'!NE"&$J$26))/$D11) -> 0 | NF11: =IF($D11=0,0,SUMIF('Полная ст-ть с уч.НЗС (Авто)'!$YO$11:INDIRECT("'Полная ст-ть с уч.НЗС (Авто)'!YO"&$J$26),$C11,'Полная ст-ть с уч.НЗС (Авто)'!NF$11:INDIRECT("'Полная ст-ть с уч.НЗС (Авто)'!NF"&$J$26))/$D11) -> 0 | NG11: =IF($D11=0,0,SUMIF('Полная ст-ть с уч.НЗС (Авто)'!$YO$11:INDIRECT("'Полная ст-ть с уч.НЗС (Авто)'!YO"&$J$26),$C11,'Полная ст-ть с уч.НЗС (Авто)'!NG$11:INDIRECT("'Полная ст-ть с уч.НЗС (Авто)'!NG"&$J$26))/$D11) -> 0 | NH11: =IF($D11=0,0,SUMIF('Полная ст-ть с уч.НЗС (Авто)'!$YO$11:INDIRECT("'Полная ст-ть с уч.НЗС (Авто)'!YO"&$J$26),$C11,'Полная ст-ть с уч.НЗС (Авто)'!NH$11:INDIRECT("'Полная ст-ть с уч.НЗС (Авто)'!NH"&$J$26))/$D11) -> 0 | NI11: =IF($D11=0,0,SUMIF('Полная ст-ть с уч.НЗС (Авто)'!$YO$11:INDIRECT("'Полная ст-ть с уч.НЗС (Авто)'!YO"&$J$26),$C11,'Полная ст-ть с уч.НЗС (Авто)'!NI$11:INDIRECT("'Полная ст-ть с уч.НЗС (Авто)'!NI"&$J$26))/$D11) -> 0 | NJ11: =IF($D11=0,0,SUMIF('Полная ст-ть с уч.НЗС (Авто)'!$YO$11:INDIRECT("'Полная ст-ть с уч.НЗС (Авто)'!YO"&$J$26),$C11,'Полная ст-ть с уч.НЗС (Авто)'!NJ$11:INDIRECT("'Полная ст-ть с уч.НЗС (Авто)'!NJ"&$J$26))/$D11) -> 0 | NK11: =IF($D11=0,0,SUMIF('Полная ст-ть с уч.НЗС (Авто)'!$YO$11:INDIRECT("'Полная ст-ть с уч.НЗС (Авто)'!YO"&$J$26),$C11,'Полная ст-ть с уч.НЗС (Авто)'!NK$11:INDIRECT("'Полная ст-ть с уч.НЗС (Авто)'!NK"&$J$26))/$D11) -> 0 | NL11: =IF($D11=0,0,SUMIF('Полная ст-ть с уч.НЗС (Авто)'!$YO$11:INDIRECT("'Полная ст-ть с уч.НЗС (Авто)'!YO"&$J$26),$C11,'Полная ст-ть с уч.НЗС (Авто)'!NL$11:INDIRECT("'Полная ст-ть с уч.НЗС (Авто)'!NL"&$J$26))/$D11) -> 0 | NM11: =IF($D11=0,0,SUMIF('Полная ст-ть с уч.НЗС (Авто)'!$YO$11:INDIRECT("'Полная ст-ть с уч.НЗС (Авто)'!YO"&$J$26),$C11,'Полная ст-ть с уч.НЗС (Авто)'!NM$11:INDIRECT("'Полная ст-ть с уч.НЗС (Авто)'!NM"&$J$26))/$D11) -> 0 | NN11: =IF($D11=0,0,SUMIF('Полная ст-ть с уч.НЗС (Авто)'!$YO$11:INDIRECT("'Полная ст-ть с уч.НЗС (Авто)'!YO"&$J$26),$C11,'Полная ст-ть с уч.НЗС (Авто)'!NN$11:INDIRECT("'Полная ст-ть с уч.НЗС (Авто)'!NN"&$J$26))/$D11) -> 0 | NO11: =IF($D11=0,0,SUMIF('Полная ст-ть с уч.НЗС (Авто)'!$YO$11:INDIRECT("'Полная ст-ть с уч.НЗС (Авто)'!YO"&$J$26),$C11,'Полная ст-ть с уч.НЗС (Авто)'!NO$11:INDIRECT("'Полная ст-ть с уч.НЗС (Авто)'!NO"&$J$26))/$D11) -> 0 | NP11: =IF($D11=0,0,SUMIF('Полная ст-ть с уч.НЗС (Авто)'!$YO$11:INDIRECT("'Полная ст-ть с уч.НЗС (Авто)'!YO"&$J$26),$C11,'Полная ст-ть с уч.НЗС (Авто)'!NP$11:INDIRECT("'Полная ст-ть с уч.НЗС (Авто)'!NP"&$J$26))/$D11) -> 0 | NQ11: =IF($D11=0,0,SUMIF('Полная ст-ть с уч.НЗС (Авто)'!$YO$11:INDIRECT("'Полная ст-ть с уч.НЗС (Авто)'!YO"&$J$26),$C11,'Полная ст-ть с уч.НЗС (Авто)'!NQ$11:INDIRECT("'Полная ст-ть с уч.НЗС (Авто)'!NQ"&$J$26))/$D11) -> 0 | NR11: =IF($D11=0,0,SUMIF('Полная ст-ть с уч.НЗС (Авто)'!$YO$11:INDIRECT("'Полная ст-ть с уч.НЗС (Авто)'!YO"&$J$26),$C11,'Полная ст-ть с уч.НЗС (Авто)'!NR$11:INDIRECT("'Полная ст-ть с уч.НЗС (Авто)'!NR"&$J$26))/$D11) -> 0 | NS11: =IF($D11=0,0,SUMIF('Полная ст-ть с уч.НЗС (Авто)'!$YO$11:INDIRECT("'Полная ст-ть с уч.НЗС (Авто)'!YO"&$J$26),$C11,'Полная ст-ть с уч.НЗС (Авто)'!NS$11:INDIRECT("'Полная ст-ть с уч.НЗС (Авто)'!NS"&$J$26))/$D11) -> 0 | NT11: =IF($D11=0,0,SUMIF('Полная ст-ть с уч.НЗС (Авто)'!$YO$11:INDIRECT("'Полная ст-ть с уч.НЗС (Авто)'!YO"&$J$26),$C11,'Полная ст-ть с уч.НЗС (Авто)'!NT$11:INDIRECT("'Полная ст-ть с уч.НЗС (Авто)'!NT"&$J$26))/$D11) -> 0 | NU11: =IF($D11=0,0,SUMIF('Полная ст-ть с уч.НЗС (Авто)'!$YO$11:INDIRECT("'Полная ст-ть с уч.НЗС (Авто)'!YO"&$J$26),$C11,'Полная ст-ть с уч.НЗС (Авто)'!NU$11:INDIRECT("'Полная ст-ть с уч.НЗС (Авто)'!NU"&$J$26))/$D11) -> 0 | NV11: =IF($D11=0,0,SUMIF('Полная ст-ть с уч.НЗС (Авто)'!$YO$11:INDIRECT("'Полная ст-ть с уч.НЗС (Авто)'!YO"&$J$26),$C11,'Полная ст-ть с уч.НЗС (Авто)'!NV$11:INDIRECT("'Полная ст-ть с уч.НЗС (Авто)'!NV"&$J$26))/$D11) -> 0 | NW11: =IF($D11=0,0,SUMIF('Полная ст-ть с уч.НЗС (Авто)'!$YO$11:INDIRECT("'Полная ст-ть с уч.НЗС (Авто)'!YO"&$J$26),$C11,'Полная ст-ть с уч.НЗС (Авто)'!NW$11:INDIRECT("'Полная ст-ть с уч.НЗС (Авто)'!NW"&$J$26))/$D11) -> 0 | NX11: =IF($D11=0,0,SUMIF('Полная ст-ть с уч.НЗС (Авто)'!$YO$11:INDIRECT("'Полная ст-ть с уч.НЗС (Авто)'!YO"&$J$26),$C11,'Полная ст-ть с уч.НЗС (Авто)'!NX$11:INDIRECT("'Полная ст-ть с уч.НЗС (Авто)'!NX"&$J$26))/$D11) -> 0 | NY11: =IF($D11=0,0,SUMIF('Полная ст-ть с уч.НЗС (Авто)'!$YO$11:INDIRECT("'Полная ст-ть с уч.НЗС (Авто)'!YO"&$J$26),$C11,'Полная ст-ть с уч.НЗС (Авто)'!NY$11:INDIRECT("'Полная ст-ть с уч.НЗС (Авто)'!NY"&$J$26))/$D11) -> 0 | NZ11: =IF($D11=0,0,SUMIF('Полная ст-ть с уч.НЗС (Авто)'!$YO$11:INDIRECT("'Полная ст-ть с уч.НЗС (Авто)'!YO"&$J$26),$C11,'Полная ст-ть с уч.НЗС (Авто)'!NZ$11:INDIRECT("'Полная ст-ть с уч.НЗС (Авто)'!NZ"&$J$26))/$D11) -> 0 | OA11: =IF($D11=0,0,SUMIF('Полная ст-ть с уч.НЗС (Авто)'!$YO$11:INDIRECT("'Полная ст-ть с уч.НЗС (Авто)'!YO"&$J$26),$C11,'Полная ст-ть с уч.НЗС (Авто)'!OA$11:INDIRECT("'Полная ст-ть с уч.НЗС (Авто)'!OA"&$J$26))/$D11) -> 0 | OB11: =IF($D11=0,0,SUMIF('Полная ст-ть с уч.НЗС (Авто)'!$YO$11:INDIRECT("'Полная ст-ть с уч.НЗС (Авто)'!YO"&$J$26),$C11,'Полная ст-ть с уч.НЗС (Авто)'!OB$11:INDIRECT("'Полная ст-ть с уч.НЗС (Авто)'!OB"&$J$26))/$D11) -> 0 | OC11: =IF($D11=0,0,SUMIF('Полная ст-ть с уч.НЗС (Авто)'!$YO$11:INDIRECT("'Полная ст-ть с уч.НЗС (Авто)'!YO"&$J$26),$C11,'Полная ст-ть с уч.НЗС (Авто)'!OC$11:INDIRECT("'Полная ст-ть с уч.НЗС (Авто)'!OC"&$J$26))/$D11) -> 0 | OD11: =IF($D11=0,0,SUMIF('Полная ст-ть с уч.НЗС (Авто)'!$YO$11:INDIRECT("'Полная ст-ть с уч.НЗС (Авто)'!YO"&$J$26),$C11,'Полная ст-ть с уч.НЗС (Авто)'!OD$11:INDIRECT("'Полная ст-ть с уч.НЗС (Авто)'!OD"&$J$26))/$D11) -> 0 | OE11: =IF($D11=0,0,SUMIF('Полная ст-ть с уч.НЗС (Авто)'!$YO$11:INDIRECT("'Полная ст-ть с уч.НЗС (Авто)'!YO"&$J$26),$C11,'Полная ст-ть с уч.НЗС (Авто)'!OE$11:INDIRECT("'Полная ст-ть с уч.НЗС (Авто)'!OE"&$J$26))/$D11) -> 0 | OF11: =IF($D11=0,0,SUMIF('Полная ст-ть с уч.НЗС (Авто)'!$YO$11:INDIRECT("'Полная ст-ть с уч.НЗС (Авто)'!YO"&$J$26),$C11,'Полная ст-ть с уч.НЗС (Авто)'!OF$11:INDIRECT("'Полная ст-ть с уч.НЗС (Авто)'!OF"&$J$26))/$D11) -> 0 | OG11: =IF($D11=0,0,SUMIF('Полная ст-ть с уч.НЗС (Авто)'!$YO$11:INDIRECT("'Полная ст-ть с уч.НЗС (Авто)'!YO"&$J$26),$C11,'Полная ст-ть с уч.НЗС (Авто)'!OG$11:INDIRECT("'Полная ст-ть с уч.НЗС (Авто)'!OG"&$J$26))/$D11) -> 0 | OH11: =IF($D11=0,0,SUMIF('Полная ст-ть с уч.НЗС (Авто)'!$YO$11:INDIRECT("'Полная ст-ть с уч.НЗС (Авто)'!YO"&$J$26),$C11,'Полная ст-ть с уч.НЗС (Авто)'!OH$11:INDIRECT("'Полная ст-ть с уч.НЗС (Авто)'!OH"&$J$26))/$D11) -> 0 | OI11: =IF($D11=0,0,SUMIF('Полная ст-ть с уч.НЗС (Авто)'!$YO$11:INDIRECT("'Полная ст-ть с уч.НЗС (Авто)'!YO"&$J$26),$C11,'Полная ст-ть с уч.НЗС (Авто)'!OI$11:INDIRECT("'Полная ст-ть с уч.НЗС (Авто)'!OI"&$J$26))/$D11) -> 0 | OJ11: =IF($D11=0,0,SUMIF('Полная ст-ть с уч.НЗС (Авто)'!$YO$11:INDIRECT("'Полная ст-ть с уч.НЗС (Авто)'!YO"&$J$26),$C11,'Полная ст-ть с уч.НЗС (Авто)'!OJ$11:INDIRECT("'Полная ст-ть с уч.НЗС (Авто)'!OJ"&$J$26))/$D11) -> 0 | OK11: =IF($D11=0,0,SUMIF('Полная ст-ть с уч.НЗС (Авто)'!$YO$11:INDIRECT("'Полная ст-ть с уч.НЗС (Авто)'!YO"&$J$26),$C11,'Полная ст-ть с уч.НЗС (Авто)'!OK$11:INDIRECT("'Полная ст-ть с уч.НЗС (Авто)'!OK"&$J$26))/$D11) -> 0 | OL11: =IF($D11=0,0,SUMIF('Полная ст-ть с уч.НЗС (Авто)'!$YO$11:INDIRECT("'Полная ст-ть с уч.НЗС (Авто)'!YO"&$J$26),$C11,'Полная ст-ть с уч.НЗС (Авто)'!OL$11:INDIRECT("'Полная ст-ть с уч.НЗС (Авто)'!OL"&$J$26))/$D11) -> 0 | OM11: =IF($D11=0,0,SUMIF('Полная ст-ть с уч.НЗС (Авто)'!$YO$11:INDIRECT("'Полная ст-ть с уч.НЗС (Авто)'!YO"&$J$26),$C11,'Полная ст-ть с уч.НЗС (Авто)'!OM$11:INDIRECT("'Полная ст-ть с уч.НЗС (Авто)'!OM"&$J$26))/$D11) -> 0 | ON11: =IF($D11=0,0,SUMIF('Полная ст-ть с уч.НЗС (Авто)'!$YO$11:INDIRECT("'Полная ст-ть с уч.НЗС (Авто)'!YO"&$J$26),$C11,'Полная ст-ть с уч.НЗС (Авто)'!ON$11:INDIRECT("'Полная ст-ть с уч.НЗС (Авто)'!ON"&$J$26))/$D11) -> 0 | OO11: =IF($D11=0,0,SUMIF('Полная ст-ть с уч.НЗС (Авто)'!$YO$11:INDIRECT("'Полная ст-ть с уч.НЗС (Авто)'!YO"&$J$26),$C11,'Полная ст-ть с уч.НЗС (Авто)'!OO$11:INDIRECT("'Полная ст-ть с уч.НЗС (Авто)'!OO"&$J$26))/$D11) -> 0 | OP11: =IF($D11=0,0,SUMIF('Полная ст-ть с уч.НЗС (Авто)'!$YO$11:INDIRECT("'Полная ст-ть с уч.НЗС (Авто)'!YO"&$J$26),$C11,'Полная ст-ть с уч.НЗС (Авто)'!OP$11:INDIRECT("'Полная ст-ть с уч.НЗС (Авто)'!OP"&$J$26))/$D11) -> 0 | OQ11: =IF($D11=0,0,SUMIF('Полная ст-ть с уч.НЗС (Авто)'!$YO$11:INDIRECT("'Полная ст-ть с уч.НЗС (Авто)'!YO"&$J$26),$C11,'Полная ст-ть с уч.НЗС (Авто)'!OQ$11:INDIRECT("'Полная ст-ть с уч.НЗС (Авто)'!OQ"&$J$26))/$D11) -> 0 | OR11: =IF($D11=0,0,SUMIF('Полная ст-ть с уч.НЗС (Авто)'!$YO$11:INDIRECT("'Полная ст-ть с уч.НЗС (Авто)'!YO"&$J$26),$C11,'Полная ст-ть с уч.НЗС (Авто)'!OR$11:INDIRECT("'Полная ст-ть с уч.НЗС (Авто)'!OR"&$J$26))/$D11) -> 0 | OS11: =IF($D11=0,0,SUMIF('Полная ст-ть с уч.НЗС (Авто)'!$YO$11:INDIRECT("'Полная ст-ть с уч.НЗС (Авто)'!YO"&$J$26),$C11,'Полная ст-ть с уч.НЗС (Авто)'!OS$11:INDIRECT("'Полная ст-ть с уч.НЗС (Авто)'!OS"&$J$26))/$D11) -> 0 | OT11: =IF($D11=0,0,SUMIF('Полная ст-ть с уч.НЗС (Авто)'!$YO$11:INDIRECT("'Полная ст-ть с уч.НЗС (Авто)'!YO"&$J$26),$C11,'Полная ст-ть с уч.НЗС (Авто)'!OT$11:INDIRECT("'Полная ст-ть с уч.НЗС (Авто)'!OT"&$J$26))/$D11) -> 0 | OU11: =IF($D11=0,0,SUMIF('Полная ст-ть с уч.НЗС (Авто)'!$YO$11:INDIRECT("'Полная ст-ть с уч.НЗС (Авто)'!YO"&$J$26),$C11,'Полная ст-ть с уч.НЗС (Авто)'!OU$11:INDIRECT("'Полная ст-ть с уч.НЗС (Авто)'!OU"&$J$26))/$D11) -> 0 | OV11: =IF($D11=0,0,SUMIF('Полная ст-ть с уч.НЗС (Авто)'!$YO$11:INDIRECT("'Полная ст-ть с уч.НЗС (Авто)'!YO"&$J$26),$C11,'Полная ст-ть с уч.НЗС (Авто)'!OV$11:INDIRECT("'Полная ст-ть с уч.НЗС (Авто)'!OV"&$J$26))/$D11) -> 0 | OW11: =IF($D11=0,0,SUMIF('Полная ст-ть с уч.НЗС (Авто)'!$YO$11:INDIRECT("'Полная ст-ть с уч.НЗС (Авто)'!YO"&$J$26),$C11,'Полная ст-ть с уч.НЗС (Авто)'!OW$11:INDIRECT("'Полная ст-ть с уч.НЗС (Авто)'!OW"&$J$26))/$D11) -> 0 | OX11: =IF($D11=0,0,SUMIF('Полная ст-ть с уч.НЗС (Авто)'!$YO$11:INDIRECT("'Полная ст-ть с уч.НЗС (Авто)'!YO"&$J$26),$C11,'Полная ст-ть с уч.НЗС (Авто)'!OX$11:INDIRECT("'Полная ст-ть с уч.НЗС (Авто)'!OX"&$J$26))/$D11) -> 0 | OY11: =IF($D11=0,0,SUMIF('Полная ст-ть с уч.НЗС (Авто)'!$YO$11:INDIRECT("'Полная ст-ть с уч.НЗС (Авто)'!YO"&$J$26),$C11,'Полная ст-ть с уч.НЗС (Авто)'!OY$11:INDIRECT("'Полная ст-ть с уч.НЗС (Авто)'!OY"&$J$26))/$D11) -> 0 | OZ11: =IF($D11=0,0,SUMIF('Полная ст-ть с уч.НЗС (Авто)'!$YO$11:INDIRECT("'Полная ст-ть с уч.НЗС (Авто)'!YO"&$J$26),$C11,'Полная ст-ть с уч.НЗС (Авто)'!OZ$11:INDIRECT("'Полная ст-ть с уч.НЗС (Авто)'!OZ"&$J$26))/$D11) -> 0 | PA11: =IF($D11=0,0,SUMIF('Полная ст-ть с уч.НЗС (Авто)'!$YO$11:INDIRECT("'Полная ст-ть с уч.НЗС (Авто)'!YO"&$J$26),$C11,'Полная ст-ть с уч.НЗС (Авто)'!PA$11:INDIRECT("'Полная ст-ть с уч.НЗС (Авто)'!PA"&$J$26))/$D11) -> 0 | PB11: =IF($D11=0,0,SUMIF('Полная ст-ть с уч.НЗС (Авто)'!$YO$11:INDIRECT("'Полная ст-ть с уч.НЗС (Авто)'!YO"&$J$26),$C11,'Полная ст-ть с уч.НЗС (Авто)'!PB$11:INDIRECT("'Полная ст-ть с уч.НЗС (Авто)'!PB"&$J$26))/$D11) -> 0 | PC11: =IF($D11=0,0,SUMIF('Полная ст-ть с уч.НЗС (Авто)'!$YO$11:INDIRECT("'Полная ст-ть с уч.НЗС (Авто)'!YO"&$J$26),$C11,'Полная ст-ть с уч.НЗС (Авто)'!PC$11:INDIRECT("'Полная ст-ть с уч.НЗС (Авто)'!PC"&$J$26))/$D11) -> 0 | PD11: =IF($D11=0,0,SUMIF('Полная ст-ть с уч.НЗС (Авто)'!$YO$11:INDIRECT("'Полная ст-ть с уч.НЗС (Авто)'!YO"&$J$26),$C11,'Полная ст-ть с уч.НЗС (Авто)'!PD$11:INDIRECT("'Полная ст-ть с уч.НЗС (Авто)'!PD"&$J$26))/$D11) -> 0 | PE11: =IF($D11=0,0,SUMIF('Полная ст-ть с уч.НЗС (Авто)'!$YO$11:INDIRECT("'Полная ст-ть с уч.НЗС (Авто)'!YO"&$J$26),$C11,'Полная ст-ть с уч.НЗС (Авто)'!PE$11:INDIRECT("'Полная ст-ть с уч.НЗС (Авто)'!PE"&$J$26))/$D11) -> 0 | PF11: =IF($D11=0,0,SUMIF('Полная ст-ть с уч.НЗС (Авто)'!$YO$11:INDIRECT("'Полная ст-ть с уч.НЗС (Авто)'!YO"&$J$26),$C11,'Полная ст-ть с уч.НЗС (Авто)'!PF$11:INDIRECT("'Полная ст-ть с уч.НЗС (Авто)'!PF"&$J$26))/$D11) -> 0 | PG11: =IF($D11=0,0,SUMIF('Полная ст-ть с уч.НЗС (Авто)'!$YO$11:INDIRECT("'Полная ст-ть с уч.НЗС (Авто)'!YO"&$J$26),$C11,'Полная ст-ть с уч.НЗС (Авто)'!PG$11:INDIRECT("'Полная ст-ть с уч.НЗС (Авто)'!PG"&$J$26))/$D11) -> 0 | PH11: =IF($D11=0,0,SUMIF('Полная ст-ть с уч.НЗС (Авто)'!$YO$11:INDIRECT("'Полная ст-ть с уч.НЗС (Авто)'!YO"&$J$26),$C11,'Полная ст-ть с уч.НЗС (Авто)'!PH$11:INDIRECT("'Полная ст-ть с уч.НЗС (Авто)'!PH"&$J$26))/$D11) -> 0 | PI11: =IF($D11=0,0,SUMIF('Полная ст-ть с уч.НЗС (Авто)'!$YO$11:INDIRECT("'Полная ст-ть с уч.НЗС (Авто)'!YO"&$J$26),$C11,'Полная ст-ть с уч.НЗС (Авто)'!PI$11:INDIRECT("'Полная ст-ть с уч.НЗС (Авто)'!PI"&$J$26))/$D11) -> 0 | PJ11: =IF($D11=0,0,SUMIF('Полная ст-ть с уч.НЗС (Авто)'!$YO$11:INDIRECT("'Полная ст-ть с уч.НЗС (Авто)'!YO"&$J$26),$C11,'Полная ст-ть с уч.НЗС (Авто)'!PJ$11:INDIRECT("'Полная ст-ть с уч.НЗС (Авто)'!PJ"&$J$26))/$D11) -> 0 | PK11: =IF($D11=0,0,SUMIF('Полная ст-ть с уч.НЗС (Авто)'!$YO$11:INDIRECT("'Полная ст-ть с уч.НЗС (Авто)'!YO"&$J$26),$C11,'Полная ст-ть с уч.НЗС (Авто)'!PK$11:INDIRECT("'Полная ст-ть с уч.НЗС (Авто)'!PK"&$J$26))/$D11) -> 0 | PL11: =IF($D11=0,0,SUMIF('Полная ст-ть с уч.НЗС (Авто)'!$YO$11:INDIRECT("'Полная ст-ть с уч.НЗС (Авто)'!YO"&$J$26),$C11,'Полная ст-ть с уч.НЗС (Авто)'!PL$11:INDIRECT("'Полная ст-ть с уч.НЗС (Авто)'!PL"&$J$26))/$D11) -> 0 | PM11: =IF($D11=0,0,SUMIF('Полная ст-ть с уч.НЗС (Авто)'!$YO$11:INDIRECT("'Полная ст-ть с уч.НЗС (Авто)'!YO"&$J$26),$C11,'Полная ст-ть с уч.НЗС (Авто)'!PM$11:INDIRECT("'Полная ст-ть с уч.НЗС (Авто)'!PM"&$J$26))/$D11) -> 0 | PN11: =IF($D11=0,0,SUMIF('Полная ст-ть с уч.НЗС (Авто)'!$YO$11:INDIRECT("'Полная ст-ть с уч.НЗС (Авто)'!YO"&$J$26),$C11,'Полная ст-ть с уч.НЗС (Авто)'!PN$11:INDIRECT("'Полная ст-ть с уч.НЗС (Авто)'!PN"&$J$26))/$D11) -> 0 | PO11: =IF($D11=0,0,SUMIF('Полная ст-ть с уч.НЗС (Авто)'!$YO$11:INDIRECT("'Полная ст-ть с уч.НЗС (Авто)'!YO"&$J$26),$C11,'Полная ст-ть с уч.НЗС (Авто)'!PO$11:INDIRECT("'Полная ст-ть с уч.НЗС (Авто)'!PO"&$J$26))/$D11) -> 0 | PP11: =IF($D11=0,0,SUMIF('Полная ст-ть с уч.НЗС (Авто)'!$YO$11:INDIRECT("'Полная ст-ть с уч.НЗС (Авто)'!YO"&$J$26),$C11,'Полная ст-ть с уч.НЗС (Авто)'!PP$11:INDIRECT("'Полная ст-ть с уч.НЗС (Авто)'!PP"&$J$26))/$D11) -> 0 | PQ11: =IF($D11=0,0,SUMIF('Полная ст-ть с уч.НЗС (Авто)'!$YO$11:INDIRECT("'Полная ст-ть с уч.НЗС (Авто)'!YO"&$J$26),$C11,'Полная ст-ть с уч.НЗС (Авто)'!PQ$11:INDIRECT("'Полная ст-ть с уч.НЗС (Авто)'!PQ"&$J$26))/$D11) -> 0 | PR11: =IF($D11=0,0,SUMIF('Полная ст-ть с уч.НЗС (Авто)'!$YO$11:INDIRECT("'Полная ст-ть с уч.НЗС (Авто)'!YO"&$J$26),$C11,'Полная ст-ть с уч.НЗС (Авто)'!PR$11:INDIRECT("'Полная ст-ть с уч.НЗС (Авто)'!PR"&$J$26))/$D11) -> 0 | PS11: =IF($D11=0,0,SUMIF('Полная ст-ть с уч.НЗС (Авто)'!$YO$11:INDIRECT("'Полная ст-ть с уч.НЗС (Авто)'!YO"&$J$26),$C11,'Полная ст-ть с уч.НЗС (Авто)'!PS$11:INDIRECT("'Полная ст-ть с уч.НЗС (Авто)'!PS"&$J$26))/$D11) -> 0 | PT11: =IF($D11=0,0,SUMIF('Полная ст-ть с уч.НЗС (Авто)'!$YO$11:INDIRECT("'Полная ст-ть с уч.НЗС (Авто)'!YO"&$J$26),$C11,'Полная ст-ть с уч.НЗС (Авто)'!PT$11:INDIRECT("'Полная ст-ть с уч.НЗС (Авто)'!PT"&$J$26))/$D11) -> 0 | PU11: =IF($D11=0,0,SUMIF('Полная ст-ть с уч.НЗС (Авто)'!$YO$11:INDIRECT("'Полная ст-ть с уч.НЗС (Авто)'!YO"&$J$26),$C11,'Полная ст-ть с уч.НЗС (Авто)'!PU$11:INDIRECT("'Полная ст-ть с уч.НЗС (Авто)'!PU"&$J$26))/$D11) -> 0 | PV11: =IF($D11=0,0,SUMIF('Полная ст-ть с уч.НЗС (Авто)'!$YO$11:INDIRECT("'Полная ст-ть с уч.НЗС (Авто)'!YO"&$J$26),$C11,'Полная ст-ть с уч.НЗС (Авто)'!PV$11:INDIRECT("'Полная ст-ть с уч.НЗС (Авто)'!PV"&$J$26))/$D11) -> 0 | PW11: =IF($D11=0,0,SUMIF('Полная ст-ть с уч.НЗС (Авто)'!$YO$11:INDIRECT("'Полная ст-ть с уч.НЗС (Авто)'!YO"&$J$26),$C11,'Полная ст-ть с уч.НЗС (Авто)'!PW$11:INDIRECT("'Полная ст-ть с уч.НЗС (Авто)'!PW"&$J$26))/$D11) -> 0 | PX11: =IF($D11=0,0,SUMIF('Полная ст-ть с уч.НЗС (Авто)'!$YO$11:INDIRECT("'Полная ст-ть с уч.НЗС (Авто)'!YO"&$J$26),$C11,'Полная ст-ть с уч.НЗС (Авто)'!PX$11:INDIRECT("'Полная ст-ть с уч.НЗС (Авто)'!PX"&$J$26))/$D11) -> 0 | PY11: =IF($D11=0,0,SUMIF('Полная ст-ть с уч.НЗС (Авто)'!$YO$11:INDIRECT("'Полная ст-ть с уч.НЗС (Авто)'!YO"&$J$26),$C11,'Полная ст-ть с уч.НЗС (Авто)'!PY$11:INDIRECT("'Полная ст-ть с уч.НЗС (Авто)'!PY"&$J$26))/$D11) -> 0 | PZ11: =IF($D11=0,0,SUMIF('Полная ст-ть с уч.НЗС (Авто)'!$YO$11:INDIRECT("'Полная ст-ть с уч.НЗС (Авто)'!YO"&$J$26),$C11,'Полная ст-ть с уч.НЗС (Авто)'!PZ$11:INDIRECT("'Полная ст-ть с уч.НЗС (Авто)'!PZ"&$J$26))/$D11) -> 0 | QA11: =IF($D11=0,0,SUMIF('Полная ст-ть с уч.НЗС (Авто)'!$YO$11:INDIRECT("'Полная ст-ть с уч.НЗС (Авто)'!YO"&$J$26),$C11,'Полная ст-ть с уч.НЗС (Авто)'!QA$11:INDIRECT("'Полная ст-ть с уч.НЗС (Авто)'!QA"&$J$26))/$D11) -> 0 | QB11: =IF($D11=0,0,SUMIF('Полная ст-ть с уч.НЗС (Авто)'!$YO$11:INDIRECT("'Полная ст-ть с уч.НЗС (Авто)'!YO"&$J$26),$C11,'Полная ст-ть с уч.НЗС (Авто)'!QB$11:INDIRECT("'Полная ст-ть с уч.НЗС (Авто)'!QB"&$J$26))/$D11) -> 0 | QC11: =IF($D11=0,0,SUMIF('Полная ст-ть с уч.НЗС (Авто)'!$YO$11:INDIRECT("'Полная ст-ть с уч.НЗС (Авто)'!YO"&$J$26),$C11,'Полная ст-ть с уч.НЗС (Авто)'!QC$11:INDIRECT("'Полная ст-ть с уч.НЗС (Авто)'!QC"&$J$26))/$D11) -> 0 | QD11: =IF($D11=0,0,SUMIF('Полная ст-ть с уч.НЗС (Авто)'!$YO$11:INDIRECT("'Полная ст-ть с уч.НЗС (Авто)'!YO"&$J$26),$C11,'Полная ст-ть с уч.НЗС (Авто)'!QD$11:INDIRECT("'Полная ст-ть с уч.НЗС (Авто)'!QD"&$J$26))/$D11) -> 0 | QE11: =IF($D11=0,0,SUMIF('Полная ст-ть с уч.НЗС (Авто)'!$YO$11:INDIRECT("'Полная ст-ть с уч.НЗС (Авто)'!YO"&$J$26),$C11,'Полная ст-ть с уч.НЗС (Авто)'!QE$11:INDIRECT("'Полная ст-ть с уч.НЗС (Авто)'!QE"&$J$26))/$D11) -> 0 | QF11: =IF($D11=0,0,SUMIF('Полная ст-ть с уч.НЗС (Авто)'!$YO$11:INDIRECT("'Полная ст-ть с уч.НЗС (Авто)'!YO"&$J$26),$C11,'Полная ст-ть с уч.НЗС (Авто)'!QF$11:INDIRECT("'Полная ст-ть с уч.НЗС (Авто)'!QF"&$J$26))/$D11) -> 0 | QG11: =IF($D11=0,0,SUMIF('Полная ст-ть с уч.НЗС (Авто)'!$YO$11:INDIRECT("'Полная ст-ть с уч.НЗС (Авто)'!YO"&$J$26),$C11,'Полная ст-ть с уч.НЗС (Авто)'!QG$11:INDIRECT("'Полная ст-ть с уч.НЗС (Авто)'!QG"&$J$26))/$D11) -> 0 | QH11: =IF($D11=0,0,SUMIF('Полная ст-ть с уч.НЗС (Авто)'!$YO$11:INDIRECT("'Полная ст-ть с уч.НЗС (Авто)'!YO"&$J$26),$C11,'Полная ст-ть с уч.НЗС (Авто)'!QH$11:INDIRECT("'Полная ст-ть с уч.НЗС (Авто)'!QH"&$J$26))/$D11) -> 0 | QI11: =IF($D11=0,0,SUMIF('Полная ст-ть с уч.НЗС (Авто)'!$YO$11:INDIRECT("'Полная ст-ть с уч.НЗС (Авто)'!YO"&$J$26),$C11,'Полная ст-ть с уч.НЗС (Авто)'!QI$11:INDIRECT("'Полная ст-ть с уч.НЗС (Авто)'!QI"&$J$26))/$D11) -> 0 | QJ11: =IF($D11=0,0,SUMIF('Полная ст-ть с уч.НЗС (Авто)'!$YO$11:INDIRECT("'Полная ст-ть с уч.НЗС (Авто)'!YO"&$J$26),$C11,'Полная ст-ть с уч.НЗС (Авто)'!QJ$11:INDIRECT("'Полная ст-ть с уч.НЗС (Авто)'!QJ"&$J$26))/$D11) -> 0 | QK11: =IF($D11=0,0,SUMIF('Полная ст-ть с уч.НЗС (Авто)'!$YO$11:INDIRECT("'Полная ст-ть с уч.НЗС (Авто)'!YO"&$J$26),$C11,'Полная ст-ть с уч.НЗС (Авто)'!QK$11:INDIRECT("'Полная ст-ть с уч.НЗС (Авто)'!QK"&$J$26))/$D11) -> 0 | QL11: =IF($D11=0,0,SUMIF('Полная ст-ть с уч.НЗС (Авто)'!$YO$11:INDIRECT("'Полная ст-ть с уч.НЗС (Авто)'!YO"&$J$26),$C11,'Полная ст-ть с уч.НЗС (Авто)'!QL$11:INDIRECT("'Полная ст-ть с уч.НЗС (Авто)'!QL"&$J$26))/$D11) -> 0 | QM11: =IF($D11=0,0,SUMIF('Полная ст-ть с уч.НЗС (Авто)'!$YO$11:INDIRECT("'Полная ст-ть с уч.НЗС (Авто)'!YO"&$J$26),$C11,'Полная ст-ть с уч.НЗС (Авто)'!QM$11:INDIRECT("'Полная ст-ть с уч.НЗС (Авто)'!QM"&$J$26))/$D11) -> 0 | QN11: =IF($D11=0,0,SUMIF('Полная ст-ть с уч.НЗС (Авто)'!$YO$11:INDIRECT("'Полная ст-ть с уч.НЗС (Авто)'!YO"&$J$26),$C11,'Полная ст-ть с уч.НЗС (Авто)'!QN$11:INDIRECT("'Полная ст-ть с уч.НЗС (Авто)'!QN"&$J$26))/$D11) -> 0 | QO11: =IF($D11=0,0,SUMIF('Полная ст-ть с уч.НЗС (Авто)'!$YO$11:INDIRECT("'Полная ст-ть с уч.НЗС (Авто)'!YO"&$J$26),$C11,'Полная ст-ть с уч.НЗС (Авто)'!QO$11:INDIRECT("'Полная ст-ть с уч.НЗС (Авто)'!QO"&$J$26))/$D11) -> 0 | QP11: =IF($D11=0,0,SUMIF('Полная ст-ть с уч.НЗС (Авто)'!$YO$11:INDIRECT("'Полная ст-ть с уч.НЗС (Авто)'!YO"&$J$26),$C11,'Полная ст-ть с уч.НЗС (Авто)'!QP$11:INDIRECT("'Полная ст-ть с уч.НЗС (Авто)'!QP"&$J$26))/$D11) -> 0 | QQ11: =IF($D11=0,0,SUMIF('Полная ст-ть с уч.НЗС (Авто)'!$YO$11:INDIRECT("'Полная ст-ть с уч.НЗС (Авто)'!YO"&$J$26),$C11,'Полная ст-ть с уч.НЗС (Авто)'!QQ$11:INDIRECT("'Полная ст-ть с уч.НЗС (Авто)'!QQ"&$J$26))/$D11) -> 0 | QR11: =IF($D11=0,0,SUMIF('Полная ст-ть с уч.НЗС (Авто)'!$YO$11:INDIRECT("'Полная ст-ть с уч.НЗС (Авто)'!YO"&$J$26),$C11,'Полная ст-ть с уч.НЗС (Авто)'!QR$11:INDIRECT("'Полная ст-ть с уч.НЗС (Авто)'!QR"&$J$26))/$D11) -> 0 | QS11: =IF($D11=0,0,SUMIF('Полная ст-ть с уч.НЗС (Авто)'!$YO$11:INDIRECT("'Полная ст-ть с уч.НЗС (Авто)'!YO"&$J$26),$C11,'Полная ст-ть с уч.НЗС (Авто)'!QS$11:INDIRECT("'Полная ст-ть с уч.НЗС (Авто)'!QS"&$J$26))/$D11) -> 0 | QT11: =IF($D11=0,0,SUMIF('Полная ст-ть с уч.НЗС (Авто)'!$YO$11:INDIRECT("'Полная ст-ть с уч.НЗС (Авто)'!YO"&$J$26),$C11,'Полная ст-ть с уч.НЗС (Авто)'!QT$11:INDIRECT("'Полная ст-ть с уч.НЗС (Авто)'!QT"&$J$26))/$D11) -> 0 | QU11: =IF($D11=0,0,SUMIF('Полная ст-ть с уч.НЗС (Авто)'!$YO$11:INDIRECT("'Полная ст-ть с уч.НЗС (Авто)'!YO"&$J$26),$C11,'Полная ст-ть с уч.НЗС (Авто)'!QU$11:INDIRECT("'Полная ст-ть с уч.НЗС (Авто)'!QU"&$J$26))/$D11) -> 0 | QV11: =IF($D11=0,0,SUMIF('Полная ст-ть с уч.НЗС (Авто)'!$YO$11:INDIRECT("'Полная ст-ть с уч.НЗС (Авто)'!YO"&$J$26),$C11,'Полная ст-ть с уч.НЗС (Авто)'!QV$11:INDIRECT("'Полная ст-ть с уч.НЗС (Авто)'!QV"&$J$26))/$D11) -> 0 | QW11: =IF($D11=0,0,SUMIF('Полная ст-ть с уч.НЗС (Авто)'!$YO$11:INDIRECT("'Полная ст-ть с уч.НЗС (Авто)'!YO"&$J$26),$C11,'Полная ст-ть с уч.НЗС (Авто)'!QW$11:INDIRECT("'Полная ст-ть с уч.НЗС (Авто)'!QW"&$J$26))/$D11) -> 0 | QX11: =IF($D11=0,0,SUMIF('Полная ст-ть с уч.НЗС (Авто)'!$YO$11:INDIRECT("'Полная ст-ть с уч.НЗС (Авто)'!YO"&$J$26),$C11,'Полная ст-ть с уч.НЗС (Авто)'!QX$11:INDIRECT("'Полная ст-ть с уч.НЗС (Авто)'!QX"&$J$26))/$D11) -> 0 | QY11: =IF($D11=0,0,SUMIF('Полная ст-ть с уч.НЗС (Авто)'!$YO$11:INDIRECT("'Полная ст-ть с уч.НЗС (Авто)'!YO"&$J$26),$C11,'Полная ст-ть с уч.НЗС (Авто)'!QY$11:INDIRECT("'Полная ст-ть с уч.НЗС (Авто)'!QY"&$J$26))/$D11) -> 0 | QZ11: =IF($D11=0,0,SUMIF('Полная ст-ть с уч.НЗС (Авто)'!$YO$11:INDIRECT("'Полная ст-ть с уч.НЗС (Авто)'!YO"&$J$26),$C11,'Полная ст-ть с уч.НЗС (Авто)'!QZ$11:INDIRECT("'Полная ст-ть с уч.НЗС (Авто)'!QZ"&$J$26))/$D11) -> 0 | RA11: =IF($D11=0,0,SUMIF('Полная ст-ть с уч.НЗС (Авто)'!$YO$11:INDIRECT("'Полная ст-ть с уч.НЗС (Авто)'!YO"&$J$26),$C11,'Полная ст-ть с уч.НЗС (Авто)'!RA$11:INDIRECT("'Полная ст-ть с уч.НЗС (Авто)'!RA"&$J$26))/$D11) -> 0 | RB11: =IF($D11=0,0,SUMIF('Полная ст-ть с уч.НЗС (Авто)'!$YO$11:INDIRECT("'Полная ст-ть с уч.НЗС (Авто)'!YO"&$J$26),$C11,'Полная ст-ть с уч.НЗС (Авто)'!RB$11:INDIRECT("'Полная ст-ть с уч.НЗС (Авто)'!RB"&$J$26))/$D11) -> 0 | RC11: =IF($D11=0,0,SUMIF('Полная ст-ть с уч.НЗС (Авто)'!$YO$11:INDIRECT("'Полная ст-ть с уч.НЗС (Авто)'!YO"&$J$26),$C11,'Полная ст-ть с уч.НЗС (Авто)'!RC$11:INDIRECT("'Полная ст-ть с уч.НЗС (Авто)'!RC"&$J$26))/$D11) -> 0 | RD11: =IF($D11=0,0,SUMIF('Полная ст-ть с уч.НЗС (Авто)'!$YO$11:INDIRECT("'Полная ст-ть с уч.НЗС (Авто)'!YO"&$J$26),$C11,'Полная ст-ть с уч.НЗС (Авто)'!RD$11:INDIRECT("'Полная ст-ть с уч.НЗС (Авто)'!RD"&$J$26))/$D11) -> 0 | RE11: =IF($D11=0,0,SUMIF('Полная ст-ть с уч.НЗС (Авто)'!$YO$11:INDIRECT("'Полная ст-ть с уч.НЗС (Авто)'!YO"&$J$26),$C11,'Полная ст-ть с уч.НЗС (Авто)'!RE$11:INDIRECT("'Полная ст-ть с уч.НЗС (Авто)'!RE"&$J$26))/$D11) -> 0 | RF11: =IF($D11=0,0,SUMIF('Полная ст-ть с уч.НЗС (Авто)'!$YO$11:INDIRECT("'Полная ст-ть с уч.НЗС (Авто)'!YO"&$J$26),$C11,'Полная ст-ть с уч.НЗС (Авто)'!RF$11:INDIRECT("'Полная ст-ть с уч.НЗС (Авто)'!RF"&$J$26))/$D11) -> 0 | RG11: =IF($D11=0,0,SUMIF('Полная ст-ть с уч.НЗС (Авто)'!$YO$11:INDIRECT("'Полная ст-ть с уч.НЗС (Авто)'!YO"&$J$26),$C11,'Полная ст-ть с уч.НЗС (Авто)'!RG$11:INDIRECT("'Полная ст-ть с уч.НЗС (Авто)'!RG"&$J$26))/$D11) -> 0 | RH11: =IF($D11=0,0,SUMIF('Полная ст-ть с уч.НЗС (Авто)'!$YO$11:INDIRECT("'Полная ст-ть с уч.НЗС (Авто)'!YO"&$J$26),$C11,'Полная ст-ть с уч.НЗС (Авто)'!RH$11:INDIRECT("'Полная ст-ть с уч.НЗС (Авто)'!RH"&$J$26))/$D11) -> 0 | RI11: =IF($D11=0,0,SUMIF('Полная ст-ть с уч.НЗС (Авто)'!$YO$11:INDIRECT("'Полная ст-ть с уч.НЗС (Авто)'!YO"&$J$26),$C11,'Полная ст-ть с уч.НЗС (Авто)'!RI$11:INDIRECT("'Полная ст-ть с уч.НЗС (Авто)'!RI"&$J$26))/$D11) -> 0 | RJ11: =IF($D11=0,0,SUMIF('Полная ст-ть с уч.НЗС (Авто)'!$YO$11:INDIRECT("'Полная ст-ть с уч.НЗС (Авто)'!YO"&$J$26),$C11,'Полная ст-ть с уч.НЗС (Авто)'!RJ$11:INDIRECT("'Полная ст-ть с уч.НЗС (Авто)'!RJ"&$J$26))/$D11) -> 0 | RK11: =IF($D11=0,0,SUMIF('Полная ст-ть с уч.НЗС (Авто)'!$YO$11:INDIRECT("'Полная ст-ть с уч.НЗС (Авто)'!YO"&$J$26),$C11,'Полная ст-ть с уч.НЗС (Авто)'!RK$11:INDIRECT("'Полная ст-ть с уч.НЗС (Авто)'!RK"&$J$26))/$D11) -> 0 | RL11: =IF($D11=0,0,SUMIF('Полная ст-ть с уч.НЗС (Авто)'!$YO$11:INDIRECT("'Полная ст-ть с уч.НЗС (Авто)'!YO"&$J$26),$C11,'Полная ст-ть с уч.НЗС (Авто)'!RL$11:INDIRECT("'Полная ст-ть с уч.НЗС (Авто)'!RL"&$J$26))/$D11) -> 0 | RM11: =IF($D11=0,0,SUMIF('Полная ст-ть с уч.НЗС (Авто)'!$YO$11:INDIRECT("'Полная ст-ть с уч.НЗС (Авто)'!YO"&$J$26),$C11,'Полная ст-ть с уч.НЗС (Авто)'!RM$11:INDIRECT("'Полная ст-ть с уч.НЗС (Авто)'!RM"&$J$26))/$D11) -> 0 | RN11: =IF($D11=0,0,SUMIF('Полная ст-ть с уч.НЗС (Авто)'!$YO$11:INDIRECT("'Полная ст-ть с уч.НЗС (Авто)'!YO"&$J$26),$C11,'Полная ст-ть с уч.НЗС (Авто)'!RN$11:INDIRECT("'Полная ст-ть с уч.НЗС (Авто)'!RN"&$J$26))/$D11) -> 0 | RO11: =IF($D11=0,0,SUMIF('Полная ст-ть с уч.НЗС (Авто)'!$YO$11:INDIRECT("'Полная ст-ть с уч.НЗС (Авто)'!YO"&$J$26),$C11,'Полная ст-ть с уч.НЗС (Авто)'!RO$11:INDIRECT("'Полная ст-ть с уч.НЗС (Авто)'!RO"&$J$26))/$D11) -> 0 | RP11: =IF($D11=0,0,SUMIF('Полная ст-ть с уч.НЗС (Авто)'!$YO$11:INDIRECT("'Полная ст-ть с уч.НЗС (Авто)'!YO"&$J$26),$C11,'Полная ст-ть с уч.НЗС (Авто)'!RP$11:INDIRECT("'Полная ст-ть с уч.НЗС (Авто)'!RP"&$J$26))/$D11) -> 0 | RQ11: =IF($D11=0,0,SUMIF('Полная ст-ть с уч.НЗС (Авто)'!$YO$11:INDIRECT("'Полная ст-ть с уч.НЗС (Авто)'!YO"&$J$26),$C11,'Полная ст-ть с уч.НЗС (Авто)'!RQ$11:INDIRECT("'Полная ст-ть с уч.НЗС (Авто)'!RQ"&$J$26))/$D11) -> 0 | RR11: =IF($D11=0,0,SUMIF('Полная ст-ть с уч.НЗС (Авто)'!$YO$11:INDIRECT("'Полная ст-ть с уч.НЗС (Авто)'!YO"&$J$26),$C11,'Полная ст-ть с уч.НЗС (Авто)'!RR$11:INDIRECT("'Полная ст-ть с уч.НЗС (Авто)'!RR"&$J$26))/$D11) -> 0 | RS11: =IF($D11=0,0,SUMIF('Полная ст-ть с уч.НЗС (Авто)'!$YO$11:INDIRECT("'Полная ст-ть с уч.НЗС (Авто)'!YO"&$J$26),$C11,'Полная ст-ть с уч.НЗС (Авто)'!RS$11:INDIRECT("'Полная ст-ть с уч.НЗС (Авто)'!RS"&$J$26))/$D11) -> 0 | RT11: =IF($D11=0,0,SUMIF('Полная ст-ть с уч.НЗС (Авто)'!$YO$11:INDIRECT("'Полная ст-ть с уч.НЗС (Авто)'!YO"&$J$26),$C11,'Полная ст-ть с уч.НЗС (Авто)'!RT$11:INDIRECT("'Полная ст-ть с уч.НЗС (Авто)'!RT"&$J$26))/$D11) -> 0 | RU11: =IF($D11=0,0,SUMIF('Полная ст-ть с уч.НЗС (Авто)'!$YO$11:INDIRECT("'Полная ст-ть с уч.НЗС (Авто)'!YO"&$J$26),$C11,'Полная ст-ть с уч.НЗС (Авто)'!RU$11:INDIRECT("'Полная ст-ть с уч.НЗС (Авто)'!RU"&$J$26))/$D11) -> 0 | RV11: =IF($D11=0,0,SUMIF('Полная ст-ть с уч.НЗС (Авто)'!$YO$11:INDIRECT("'Полная ст-ть с уч.НЗС (Авто)'!YO"&$J$26),$C11,'Полная ст-ть с уч.НЗС (Авто)'!RV$11:INDIRECT("'Полная ст-ть с уч.НЗС (Авто)'!RV"&$J$26))/$D11) -> 0 | RW11: =IF($D11=0,0,SUMIF('Полная ст-ть с уч.НЗС (Авто)'!$YO$11:INDIRECT("'Полная ст-ть с уч.НЗС (Авто)'!YO"&$J$26),$C11,'Полная ст-ть с уч.НЗС (Авто)'!RW$11:INDIRECT("'Полная ст-ть с уч.НЗС (Авто)'!RW"&$J$26))/$D11) -> 0 | RX11: =IF($D11=0,0,SUMIF('Полная ст-ть с уч.НЗС (Авто)'!$YO$11:INDIRECT("'Полная ст-ть с уч.НЗС (Авто)'!YO"&$J$26),$C11,'Полная ст-ть с уч.НЗС (Авто)'!RX$11:INDIRECT("'Полная ст-ть с уч.НЗС (Авто)'!RX"&$J$26))/$D11) -> 0 | RY11: =IF($D11=0,0,SUMIF('Полная ст-ть с уч.НЗС (Авто)'!$YO$11:INDIRECT("'Полная ст-ть с уч.НЗС (Авто)'!YO"&$J$26),$C11,'Полная ст-ть с уч.НЗС (Авто)'!RY$11:INDIRECT("'Полная ст-ть с уч.НЗС (Авто)'!RY"&$J$26))/$D11) -> 0 | RZ11: =IF($D11=0,0,SUMIF('Полная ст-ть с уч.НЗС (Авто)'!$YO$11:INDIRECT("'Полная ст-ть с уч.НЗС (Авто)'!YO"&$J$26),$C11,'Полная ст-ть с уч.НЗС (Авто)'!RZ$11:INDIRECT("'Полная ст-ть с уч.НЗС (Авто)'!RZ"&$J$26))/$D11) -> 0 | SA11: =IF($D11=0,0,SUMIF('Полная ст-ть с уч.НЗС (Авто)'!$YO$11:INDIRECT("'Полная ст-ть с уч.НЗС (Авто)'!YO"&$J$26),$C11,'Полная ст-ть с уч.НЗС (Авто)'!SA$11:INDIRECT("'Полная ст-ть с уч.НЗС (Авто)'!SA"&$J$26))/$D11) -> 0 | SB11: =IF($D11=0,0,SUMIF('Полная ст-ть с уч.НЗС (Авто)'!$YO$11:INDIRECT("'Полная ст-ть с уч.НЗС (Авто)'!YO"&$J$26),$C11,'Полная ст-ть с уч.НЗС (Авто)'!SB$11:INDIRECT("'Полная ст-ть с уч.НЗС (Авто)'!SB"&$J$26))/$D11) -> 0 | SC11: =IF($D11=0,0,SUMIF('Полная ст-ть с уч.НЗС (Авто)'!$YO$11:INDIRECT("'Полная ст-ть с уч.НЗС (Авто)'!YO"&$J$26),$C11,'Полная ст-ть с уч.НЗС (Авто)'!SC$11:INDIRECT("'Полная ст-ть с уч.НЗС (Авто)'!SC"&$J$26))/$D11) -> 0 | SD11: =IF($D11=0,0,SUMIF('Полная ст-ть с уч.НЗС (Авто)'!$YO$11:INDIRECT("'Полная ст-ть с уч.НЗС (Авто)'!YO"&$J$26),$C11,'Полная ст-ть с уч.НЗС (Авто)'!SD$11:INDIRECT("'Полная ст-ть с уч.НЗС (Авто)'!SD"&$J$26))/$D11) -> 0 | SE11: =IF($D11=0,0,SUMIF('Полная ст-ть с уч.НЗС (Авто)'!$YO$11:INDIRECT("'Полная ст-ть с уч.НЗС (Авто)'!YO"&$J$26),$C11,'Полная ст-ть с уч.НЗС (Авто)'!SE$11:INDIRECT("'Полная ст-ть с уч.НЗС (Авто)'!SE"&$J$26))/$D11) -> 0 | SF11: =IF($D11=0,0,SUMIF('Полная ст-ть с уч.НЗС (Авто)'!$YO$11:INDIRECT("'Полная ст-ть с уч.НЗС (Авто)'!YO"&$J$26),$C11,'Полная ст-ть с уч.НЗС (Авто)'!SF$11:INDIRECT("'Полная ст-ть с уч.НЗС (Авто)'!SF"&$J$26))/$D11) -> 0 | SG11: =IF($D11=0,0,SUMIF('Полная ст-ть с уч.НЗС (Авто)'!$YO$11:INDIRECT("'Полная ст-ть с уч.НЗС (Авто)'!YO"&$J$26),$C11,'Полная ст-ть с уч.НЗС (Авто)'!SG$11:INDIRECT("'Полная ст-ть с уч.НЗС (Авто)'!SG"&$J$26))/$D11) -> 0 | SH11: =IF($D11=0,0,SUMIF('Полная ст-ть с уч.НЗС (Авто)'!$YO$11:INDIRECT("'Полная ст-ть с уч.НЗС (Авто)'!YO"&$J$26),$C11,'Полная ст-ть с уч.НЗС (Авто)'!SH$11:INDIRECT("'Полная ст-ть с уч.НЗС (Авто)'!SH"&$J$26))/$D11) -> 0 | SI11: =IF($D11=0,0,SUMIF('Полная ст-ть с уч.НЗС (Авто)'!$YO$11:INDIRECT("'Полная ст-ть с уч.НЗС (Авто)'!YO"&$J$26),$C11,'Полная ст-ть с уч.НЗС (Авто)'!SI$11:INDIRECT("'Полная ст-ть с уч.НЗС (Авто)'!SI"&$J$26))/$D11) -> 0 | SJ11: =IF($D11=0,0,SUMIF('Полная ст-ть с уч.НЗС (Авто)'!$YO$11:INDIRECT("'Полная ст-ть с уч.НЗС (Авто)'!YO"&$J$26),$C11,'Полная ст-ть с уч.НЗС (Авто)'!SJ$11:INDIRECT("'Полная ст-ть с уч.НЗС (Авто)'!SJ"&$J$26))/$D11) -> 0 | SK11: =IF($D11=0,0,SUMIF('Полная ст-ть с уч.НЗС (Авто)'!$YO$11:INDIRECT("'Полная ст-ть с уч.НЗС (Авто)'!YO"&$J$26),$C11,'Полная ст-ть с уч.НЗС (Авто)'!SK$11:INDIRECT("'Полная ст-ть с уч.НЗС (Авто)'!SK"&$J$26))/$D11) -> 0 | SL11: =IF($D11=0,0,SUMIF('Полная ст-ть с уч.НЗС (Авто)'!$YO$11:INDIRECT("'Полная ст-ть с уч.НЗС (Авто)'!YO"&$J$26),$C11,'Полная ст-ть с уч.НЗС (Авто)'!SL$11:INDIRECT("'Полная ст-ть с уч.НЗС (Авто)'!SL"&$J$26))/$D11) -> 0 | SM11: =IF($D11=0,0,SUMIF('Полная ст-ть с уч.НЗС (Авто)'!$YO$11:INDIRECT("'Полная ст-ть с уч.НЗС (Авто)'!YO"&$J$26),$C11,'Полная ст-ть с уч.НЗС (Авто)'!SM$11:INDIRECT("'Полная ст-ть с уч.НЗС (Авто)'!SM"&$J$26))/$D11) -> 0 | SN11: =IF($D11=0,0,SUMIF('Полная ст-ть с уч.НЗС (Авто)'!$YO$11:INDIRECT("'Полная ст-ть с уч.НЗС (Авто)'!YO"&$J$26),$C11,'Полная ст-ть с уч.НЗС (Авто)'!SN$11:INDIRECT("'Полная ст-ть с уч.НЗС (Авто)'!SN"&$J$26))/$D11) -> 0 | SO11: =IF($D11=0,0,SUMIF('Полная ст-ть с уч.НЗС (Авто)'!$YO$11:INDIRECT("'Полная ст-ть с уч.НЗС (Авто)'!YO"&$J$26),$C11,'Полная ст-ть с уч.НЗС (Авто)'!SO$11:INDIRECT("'Полная ст-ть с уч.НЗС (Авто)'!SO"&$J$26))/$D11) -> 0 | SP11: =IF($D11=0,0,SUMIF('Полная ст-ть с уч.НЗС (Авто)'!$YO$11:INDIRECT("'Полная ст-ть с уч.НЗС (Авто)'!YO"&$J$26),$C11,'Полная ст-ть с уч.НЗС (Авто)'!SP$11:INDIRECT("'Полная ст-ть с уч.НЗС (Авто)'!SP"&$J$26))/$D11) -> 0 | SQ11: =IF($D11=0,0,SUMIF('Полная ст-ть с уч.НЗС (Авто)'!$YO$11:INDIRECT("'Полная ст-ть с уч.НЗС (Авто)'!YO"&$J$26),$C11,'Полная ст-ть с уч.НЗС (Авто)'!SQ$11:INDIRECT("'Полная ст-ть с уч.НЗС (Авто)'!SQ"&$J$26))/$D11) -> 0 | SR11: =IF($D11=0,0,SUMIF('Полная ст-ть с уч.НЗС (Авто)'!$YO$11:INDIRECT("'Полная ст-ть с уч.НЗС (Авто)'!YO"&$J$26),$C11,'Полная ст-ть с уч.НЗС (Авто)'!SR$11:INDIRECT("'Полная ст-ть с уч.НЗС (Авто)'!SR"&$J$26))/$D11) -> 0 | SS11: =IF($D11=0,0,SUMIF('Полная ст-ть с уч.НЗС (Авто)'!$YO$11:INDIRECT("'Полная ст-ть с уч.НЗС (Авто)'!YO"&$J$26),$C11,'Полная ст-ть с уч.НЗС (Авто)'!SS$11:INDIRECT("'Полная ст-ть с уч.НЗС (Авто)'!SS"&$J$26))/$D11) -> 0 | ST11: =IF($D11=0,0,SUMIF('Полная ст-ть с уч.НЗС (Авто)'!$YO$11:INDIRECT("'Полная ст-ть с уч.НЗС (Авто)'!YO"&$J$26),$C11,'Полная ст-ть с уч.НЗС (Авто)'!ST$11:INDIRECT("'Полная ст-ть с уч.НЗС (Авто)'!ST"&$J$26))/$D11) -> 0 | SU11: =IF($D11=0,0,SUMIF('Полная ст-ть с уч.НЗС (Авто)'!$YO$11:INDIRECT("'Полная ст-ть с уч.НЗС (Авто)'!YO"&$J$26),$C11,'Полная ст-ть с уч.НЗС (Авто)'!SU$11:INDIRECT("'Полная ст-ть с уч.НЗС (Авто)'!SU"&$J$26))/$D11) -> 0 | SV11: =IF($D11=0,0,SUMIF('Полная ст-ть с уч.НЗС (Авто)'!$YO$11:INDIRECT("'Полная ст-ть с уч.НЗС (Авто)'!YO"&$J$26),$C11,'Полная ст-ть с уч.НЗС (Авто)'!SV$11:INDIRECT("'Полная ст-ть с уч.НЗС (Авто)'!SV"&$J$26))/$D11) -> 0 | SW11: =IF($D11=0,0,SUMIF('Полная ст-ть с уч.НЗС (Авто)'!$YO$11:INDIRECT("'Полная ст-ть с уч.НЗС (Авто)'!YO"&$J$26),$C11,'Полная ст-ть с уч.НЗС (Авто)'!SW$11:INDIRECT("'Полная ст-ть с уч.НЗС (Авто)'!SW"&$J$26))/$D11) -> 0 | SX11: =IF($D11=0,0,SUMIF('Полная ст-ть с уч.НЗС (Авто)'!$YO$11:INDIRECT("'Полная ст-ть с уч.НЗС (Авто)'!YO"&$J$26),$C11,'Полная ст-ть с уч.НЗС (Авто)'!SX$11:INDIRECT("'Полная ст-ть с уч.НЗС (Авто)'!SX"&$J$26))/$D11) -> 0 | SY11: =IF($D11=0,0,SUMIF('Полная ст-ть с уч.НЗС (Авто)'!$YO$11:INDIRECT("'Полная ст-ть с уч.НЗС (Авто)'!YO"&$J$26),$C11,'Полная ст-ть с уч.НЗС (Авто)'!SY$11:INDIRECT("'Полная ст-ть с уч.НЗС (Авто)'!SY"&$J$26))/$D11) -> 0 | SZ11: =IF($D11=0,0,SUMIF('Полная ст-ть с уч.НЗС (Авто)'!$YO$11:INDIRECT("'Полная ст-ть с уч.НЗС (Авто)'!YO"&$J$26),$C11,'Полная ст-ть с уч.НЗС (Авто)'!SZ$11:INDIRECT("'Полная ст-ть с уч.НЗС (Авто)'!SZ"&$J$26))/$D11) -> 0 | TA11: =IF($D11=0,0,SUMIF('Полная ст-ть с уч.НЗС (Авто)'!$YO$11:INDIRECT("'Полная ст-ть с уч.НЗС (Авто)'!YO"&$J$26),$C11,'Полная ст-ть с уч.НЗС (Авто)'!TA$11:INDIRECT("'Полная ст-ть с уч.НЗС (Авто)'!TA"&$J$26))/$D11) -> 0 | TB11: =IF($D11=0,0,SUMIF('Полная ст-ть с уч.НЗС (Авто)'!$YO$11:INDIRECT("'Полная ст-ть с уч.НЗС (Авто)'!YO"&$J$26),$C11,'Полная ст-ть с уч.НЗС (Авто)'!TB$11:INDIRECT("'Полная ст-ть с уч.НЗС (Авто)'!TB"&$J$26))/$D11) -> 0 | TC11: =IF($D11=0,0,SUMIF('Полная ст-ть с уч.НЗС (Авто)'!$YO$11:INDIRECT("'Полная ст-ть с уч.НЗС (Авто)'!YO"&$J$26),$C11,'Полная ст-ть с уч.НЗС (Авто)'!TC$11:INDIRECT("'Полная ст-ть с уч.НЗС (Авто)'!TC"&$J$26))/$D11) -> 0 | TD11: =IF($D11=0,0,SUMIF('Полная ст-ть с уч.НЗС (Авто)'!$YO$11:INDIRECT("'Полная ст-ть с уч.НЗС (Авто)'!YO"&$J$26),$C11,'Полная ст-ть с уч.НЗС (Авто)'!TD$11:INDIRECT("'Полная ст-ть с уч.НЗС (Авто)'!TD"&$J$26))/$D11) -> 0 | TE11: =IF($D11=0,0,SUMIF('Полная ст-ть с уч.НЗС (Авто)'!$YO$11:INDIRECT("'Полная ст-ть с уч.НЗС (Авто)'!YO"&$J$26),$C11,'Полная ст-ть с уч.НЗС (Авто)'!TE$11:INDIRECT("'Полная ст-ть с уч.НЗС (Авто)'!TE"&$J$26))/$D11) -> 0 | TF11: =IF($D11=0,0,SUMIF('Полная ст-ть с уч.НЗС (Авто)'!$YO$11:INDIRECT("'Полная ст-ть с уч.НЗС (Авто)'!YO"&$J$26),$C11,'Полная ст-ть с уч.НЗС (Авто)'!TF$11:INDIRECT("'Полная ст-ть с уч.НЗС (Авто)'!TF"&$J$26))/$D11) -> 0 | TG11: =IF($D11=0,0,SUMIF('Полная ст-ть с уч.НЗС (Авто)'!$YO$11:INDIRECT("'Полная ст-ть с уч.НЗС (Авто)'!YO"&$J$26),$C11,'Полная ст-ть с уч.НЗС (Авто)'!TG$11:INDIRECT("'Полная ст-ть с уч.НЗС (Авто)'!TG"&$J$26))/$D11) -> 0 | TH11: =IF($D11=0,0,SUMIF('Полная ст-ть с уч.НЗС (Авто)'!$YO$11:INDIRECT("'Полная ст-ть с уч.НЗС (Авто)'!YO"&$J$26),$C11,'Полная ст-ть с уч.НЗС (Авто)'!TH$11:INDIRECT("'Полная ст-ть с уч.НЗС (Авто)'!TH"&$J$26))/$D11) -> 0 | TI11: =IF($D11=0,0,SUMIF('Полная ст-ть с уч.НЗС (Авто)'!$YO$11:INDIRECT("'Полная ст-ть с уч.НЗС (Авто)'!YO"&$J$26),$C11,'Полная ст-ть с уч.НЗС (Авто)'!TI$11:INDIRECT("'Полная ст-ть с уч.НЗС (Авто)'!TI"&$J$26))/$D11) -> 0 | TJ11: =IF($D11=0,0,SUMIF('Полная ст-ть с уч.НЗС (Авто)'!$YO$11:INDIRECT("'Полная ст-ть с уч.НЗС (Авто)'!YO"&$J$26),$C11,'Полная ст-ть с уч.НЗС (Авто)'!TJ$11:INDIRECT("'Полная ст-ть с уч.НЗС (Авто)'!TJ"&$J$26))/$D11) -> 0 | TK11: =IF($D11=0,0,SUMIF('Полная ст-ть с уч.НЗС (Авто)'!$YO$11:INDIRECT("'Полная ст-ть с уч.НЗС (Авто)'!YO"&$J$26),$C11,'Полная ст-ть с уч.НЗС (Авто)'!TK$11:INDIRECT("'Полная ст-ть с уч.НЗС (Авто)'!TK"&$J$26))/$D11) -> 0 | TL11: =IF($D11=0,0,SUMIF('Полная ст-ть с уч.НЗС (Авто)'!$YO$11:INDIRECT("'Полная ст-ть с уч.НЗС (Авто)'!YO"&$J$26),$C11,'Полная ст-ть с уч.НЗС (Авто)'!TL$11:INDIRECT("'Полная ст-ть с уч.НЗС (Авто)'!TL"&$J$26))/$D11) -> 0 | TM11: =IF($D11=0,0,SUMIF('Полная ст-ть с уч.НЗС (Авто)'!$YO$11:INDIRECT("'Полная ст-ть с уч.НЗС (Авто)'!YO"&$J$26),$C11,'Полная ст-ть с уч.НЗС (Авто)'!TM$11:INDIRECT("'Полная ст-ть с уч.НЗС (Авто)'!TM"&$J$26))/$D11) -> 0 | TN11: =IF($D11=0,0,SUMIF('Полная ст-ть с уч.НЗС (Авто)'!$YO$11:INDIRECT("'Полная ст-ть с уч.НЗС (Авто)'!YO"&$J$26),$C11,'Полная ст-ть с уч.НЗС (Авто)'!TN$11:INDIRECT("'Полная ст-ть с уч.НЗС (Авто)'!TN"&$J$26))/$D11) -> 0 | TO11: =IF($D11=0,0,SUMIF('Полная ст-ть с уч.НЗС (Авто)'!$YO$11:INDIRECT("'Полная ст-ть с уч.НЗС (Авто)'!YO"&$J$26),$C11,'Полная ст-ть с уч.НЗС (Авто)'!TO$11:INDIRECT("'Полная ст-ть с уч.НЗС (Авто)'!TO"&$J$26))/$D11) -> 0 | TP11: =IF($D11=0,0,SUMIF('Полная ст-ть с уч.НЗС (Авто)'!$YO$11:INDIRECT("'Полная ст-ть с уч.НЗС (Авто)'!YO"&$J$26),$C11,'Полная ст-ть с уч.НЗС (Авто)'!TP$11:INDIRECT("'Полная ст-ть с уч.НЗС (Авто)'!TP"&$J$26))/$D11) -> 0 | TQ11: =IF($D11=0,0,SUMIF('Полная ст-ть с уч.НЗС (Авто)'!$YO$11:INDIRECT("'Полная ст-ть с уч.НЗС (Авто)'!YO"&$J$26),$C11,'Полная ст-ть с уч.НЗС (Авто)'!TQ$11:INDIRECT("'Полная ст-ть с уч.НЗС (Авто)'!TQ"&$J$26))/$D11) -> 0 | TR11: =IF($D11=0,0,SUMIF('Полная ст-ть с уч.НЗС (Авто)'!$YO$11:INDIRECT("'Полная ст-ть с уч.НЗС (Авто)'!YO"&$J$26),$C11,'Полная ст-ть с уч.НЗС (Авто)'!TR$11:INDIRECT("'Полная ст-ть с уч.НЗС (Авто)'!TR"&$J$26))/$D11) -> 0 | TS11: =IF($D11=0,0,SUMIF('Полная ст-ть с уч.НЗС (Авто)'!$YO$11:INDIRECT("'Полная ст-ть с уч.НЗС (Авто)'!YO"&$J$26),$C11,'Полная ст-ть с уч.НЗС (Авто)'!TS$11:INDIRECT("'Полная ст-ть с уч.НЗС (Авто)'!TS"&$J$26))/$D11) -> 0 | TT11: =IF($D11=0,0,SUMIF('Полная ст-ть с уч.НЗС (Авто)'!$YO$11:INDIRECT("'Полная ст-ть с уч.НЗС (Авто)'!YO"&$J$26),$C11,'Полная ст-ть с уч.НЗС (Авто)'!TT$11:INDIRECT("'Полная ст-ть с уч.НЗС (Авто)'!TT"&$J$26))/$D11) -> 0 | TU11: =IF($D11=0,0,SUMIF('Полная ст-ть с уч.НЗС (Авто)'!$YO$11:INDIRECT("'Полная ст-ть с уч.НЗС (Авто)'!YO"&$J$26),$C11,'Полная ст-ть с уч.НЗС (Авто)'!TU$11:INDIRECT("'Полная ст-ть с уч.НЗС (Авто)'!TU"&$J$26))/$D11) -> 0 | TV11: =IF($D11=0,0,SUMIF('Полная ст-ть с уч.НЗС (Авто)'!$YO$11:INDIRECT("'Полная ст-ть с уч.НЗС (Авто)'!YO"&$J$26),$C11,'Полная ст-ть с уч.НЗС (Авто)'!TV$11:INDIRECT("'Полная ст-ть с уч.НЗС (Авто)'!TV"&$J$26))/$D11) -> 0 | TW11: =IF($D11=0,0,SUMIF('Полная ст-ть с уч.НЗС (Авто)'!$YO$11:INDIRECT("'Полная ст-ть с уч.НЗС (Авто)'!YO"&$J$26),$C11,'Полная ст-ть с уч.НЗС (Авто)'!TW$11:INDIRECT("'Полная ст-ть с уч.НЗС (Авто)'!TW"&$J$26))/$D11) -> 0 | TX11: =IF($D11=0,0,SUMIF('Полная ст-ть с уч.НЗС (Авто)'!$YO$11:INDIRECT("'Полная ст-ть с уч.НЗС (Авто)'!YO"&$J$26),$C11,'Полная ст-ть с уч.НЗС (Авто)'!TX$11:INDIRECT("'Полная ст-ть с уч.НЗС (Авто)'!TX"&$J$26))/$D11) -> 0 | TY11: =IF($D11=0,0,SUMIF('Полная ст-ть с уч.НЗС (Авто)'!$YO$11:INDIRECT("'Полная ст-ть с уч.НЗС (Авто)'!YO"&$J$26),$C11,'Полная ст-ть с уч.НЗС (Авто)'!TY$11:INDIRECT("'Полная ст-ть с уч.НЗС (Авто)'!TY"&$J$26))/$D11) -> 0 | TZ11: =IF($D11=0,0,SUMIF('Полная ст-ть с уч.НЗС (Авто)'!$YO$11:INDIRECT("'Полная ст-ть с уч.НЗС (Авто)'!YO"&$J$26),$C11,'Полная ст-ть с уч.НЗС (Авто)'!TZ$11:INDIRECT("'Полная ст-ть с уч.НЗС (Авто)'!TZ"&$J$26))/$D11) -> 0 | UA11: =IF($D11=0,0,SUMIF('Полная ст-ть с уч.НЗС (Авто)'!$YO$11:INDIRECT("'Полная ст-ть с уч.НЗС (Авто)'!YO"&$J$26),$C11,'Полная ст-ть с уч.НЗС (Авто)'!UA$11:INDIRECT("'Полная ст-ть с уч.НЗС (Авто)'!UA"&$J$26))/$D11) -> 0 | UB11: =IF($D11=0,0,SUMIF('Полная ст-ть с уч.НЗС (Авто)'!$YO$11:INDIRECT("'Полная ст-ть с уч.НЗС (Авто)'!YO"&$J$26),$C11,'Полная ст-ть с уч.НЗС (Авто)'!UB$11:INDIRECT("'Полная ст-ть с уч.НЗС (Авто)'!UB"&$J$26))/$D11) -> 0 | UC11: =IF($D11=0,0,SUMIF('Полная ст-ть с уч.НЗС (Авто)'!$YO$11:INDIRECT("'Полная ст-ть с уч.НЗС (Авто)'!YO"&$J$26),$C11,'Полная ст-ть с уч.НЗС (Авто)'!UC$11:INDIRECT("'Полная ст-ть с уч.НЗС (Авто)'!UC"&$J$26))/$D11) -> 0 | UD11: =IF($D11=0,0,SUMIF('Полная ст-ть с уч.НЗС (Авто)'!$YO$11:INDIRECT("'Полная ст-ть с уч.НЗС (Авто)'!YO"&$J$26),$C11,'Полная ст-ть с уч.НЗС (Авто)'!UD$11:INDIRECT("'Полная ст-ть с уч.НЗС (Авто)'!UD"&$J$26))/$D11) -> 0 | UE11: =IF($D11=0,0,SUMIF('Полная ст-ть с уч.НЗС (Авто)'!$YO$11:INDIRECT("'Полная ст-ть с уч.НЗС (Авто)'!YO"&$J$26),$C11,'Полная ст-ть с уч.НЗС (Авто)'!UE$11:INDIRECT("'Полная ст-ть с уч.НЗС (Авто)'!UE"&$J$26))/$D11) -> 0 | UF11: =IF($D11=0,0,SUMIF('Полная ст-ть с уч.НЗС (Авто)'!$YO$11:INDIRECT("'Полная ст-ть с уч.НЗС (Авто)'!YO"&$J$26),$C11,'Полная ст-ть с уч.НЗС (Авто)'!UF$11:INDIRECT("'Полная ст-ть с уч.НЗС (Авто)'!UF"&$J$26))/$D11) -> 0 | UG11: =IF($D11=0,0,SUMIF('Полная ст-ть с уч.НЗС (Авто)'!$YO$11:INDIRECT("'Полная ст-ть с уч.НЗС (Авто)'!YO"&$J$26),$C11,'Полная ст-ть с уч.НЗС (Авто)'!UG$11:INDIRECT("'Полная ст-ть с уч.НЗС (Авто)'!UG"&$J$26))/$D11) -> 0 | UH11: =IF($D11=0,0,SUMIF('Полная ст-ть с уч.НЗС (Авто)'!$YO$11:INDIRECT("'Полная ст-ть с уч.НЗС (Авто)'!YO"&$J$26),$C11,'Полная ст-ть с уч.НЗС (Авто)'!UH$11:INDIRECT("'Полная ст-ть с уч.НЗС (Авто)'!UH"&$J$26))/$D11) -> 0 | UI11: =IF($D11=0,0,SUMIF('Полная ст-ть с уч.НЗС (Авто)'!$YO$11:INDIRECT("'Полная ст-ть с уч.НЗС (Авто)'!YO"&$J$26),$C11,'Полная ст-ть с уч.НЗС (Авто)'!UI$11:INDIRECT("'Полная ст-ть с уч.НЗС (Авто)'!UI"&$J$26))/$D11) -> 0 | UJ11: =IF($D11=0,0,SUMIF('Полная ст-ть с уч.НЗС (Авто)'!$YO$11:INDIRECT("'Полная ст-ть с уч.НЗС (Авто)'!YO"&$J$26),$C11,'Полная ст-ть с уч.НЗС (Авто)'!UJ$11:INDIRECT("'Полная ст-ть с уч.НЗС (Авто)'!UJ"&$J$26))/$D11) -> 0 | UK11: =IF($D11=0,0,SUMIF('Полная ст-ть с уч.НЗС (Авто)'!$YO$11:INDIRECT("'Полная ст-ть с уч.НЗС (Авто)'!YO"&$J$26),$C11,'Полная ст-ть с уч.НЗС (Авто)'!UK$11:INDIRECT("'Полная ст-ть с уч.НЗС (Авто)'!UK"&$J$26))/$D11) -> 0 | UL11: =IF($D11=0,0,SUMIF('Полная ст-ть с уч.НЗС (Авто)'!$YO$11:INDIRECT("'Полная ст-ть с уч.НЗС (Авто)'!YO"&$J$26),$C11,'Полная ст-ть с уч.НЗС (Авто)'!UL$11:INDIRECT("'Полная ст-ть с уч.НЗС (Авто)'!UL"&$J$26))/$D11) -> 0 | UM11: =IF($D11=0,0,SUMIF('Полная ст-ть с уч.НЗС (Авто)'!$YO$11:INDIRECT("'Полная ст-ть с уч.НЗС (Авто)'!YO"&$J$26),$C11,'Полная ст-ть с уч.НЗС (Авто)'!UM$11:INDIRECT("'Полная ст-ть с уч.НЗС (Авто)'!UM"&$J$26))/$D11) -> 0 | UN11: =IF($D11=0,0,SUMIF('Полная ст-ть с уч.НЗС (Авто)'!$YO$11:INDIRECT("'Полная ст-ть с уч.НЗС (Авто)'!YO"&$J$26),$C11,'Полная ст-ть с уч.НЗС (Авто)'!UN$11:INDIRECT("'Полная ст-ть с уч.НЗС (Авто)'!UN"&$J$26))/$D11) -> 0 | UO11: =IF($D11=0,0,SUMIF('Полная ст-ть с уч.НЗС (Авто)'!$YO$11:INDIRECT("'Полная ст-ть с уч.НЗС (Авто)'!YO"&$J$26),$C11,'Полная ст-ть с уч.НЗС (Авто)'!UO$11:INDIRECT("'Полная ст-ть с уч.НЗС (Авто)'!UO"&$J$26))/$D11) -> 0 | UP11: =IF($D11=0,0,SUMIF('Полная ст-ть с уч.НЗС (Авто)'!$YO$11:INDIRECT("'Полная ст-ть с уч.НЗС (Авто)'!YO"&$J$26),$C11,'Полная ст-ть с уч.НЗС (Авто)'!UP$11:INDIRECT("'Полная ст-ть с уч.НЗС (Авто)'!UP"&$J$26))/$D11) -> 0 | UQ11: =IF($D11=0,0,SUMIF('Полная ст-ть с уч.НЗС (Авто)'!$YO$11:INDIRECT("'Полная ст-ть с уч.НЗС (Авто)'!YO"&$J$26),$C11,'Полная ст-ть с уч.НЗС (Авто)'!UQ$11:INDIRECT("'Полная ст-ть с уч.НЗС (Авто)'!UQ"&$J$26))/$D11) -> 0 | UR11: =IF($D11=0,0,SUMIF('Полная ст-ть с уч.НЗС (Авто)'!$YO$11:INDIRECT("'Полная ст-ть с уч.НЗС (Авто)'!YO"&$J$26),$C11,'Полная ст-ть с уч.НЗС (Авто)'!UR$11:INDIRECT("'Полная ст-ть с уч.НЗС (Авто)'!UR"&$J$26))/$D11) -> 0 | US11: =IF($D11=0,0,SUMIF('Полная ст-ть с уч.НЗС (Авто)'!$YO$11:INDIRECT("'Полная ст-ть с уч.НЗС (Авто)'!YO"&$J$26),$C11,'Полная ст-ть с уч.НЗС (Авто)'!US$11:INDIRECT("'Полная ст-ть с уч.НЗС (Авто)'!US"&$J$26))/$D11) -> 0 | UT11: =IF($D11=0,0,SUMIF('Полная ст-ть с уч.НЗС (Авто)'!$YO$11:INDIRECT("'Полная ст-ть с уч.НЗС (Авто)'!YO"&$J$26),$C11,'Полная ст-ть с уч.НЗС (Авто)'!UT$11:INDIRECT("'Полная ст-ть с уч.НЗС (Авто)'!UT"&$J$26))/$D11) -> 0 | UU11: =IF($D11=0,0,SUMIF('Полная ст-ть с уч.НЗС (Авто)'!$YO$11:INDIRECT("'Полная ст-ть с уч.НЗС (Авто)'!YO"&$J$26),$C11,'Полная ст-ть с уч.НЗС (Авто)'!UU$11:INDIRECT("'Полная ст-ть с уч.НЗС (Авто)'!UU"&$J$26))/$D11) -> 0 | UV11: =IF($D11=0,0,SUMIF('Полная ст-ть с уч.НЗС (Авто)'!$YO$11:INDIRECT("'Полная ст-ть с уч.НЗС (Авто)'!YO"&$J$26),$C11,'Полная ст-ть с уч.НЗС (Авто)'!UV$11:INDIRECT("'Полная ст-ть с уч.НЗС (Авто)'!UV"&$J$26))/$D11) -> 0 | UW11: =IF($D11=0,0,SUMIF('Полная ст-ть с уч.НЗС (Авто)'!$YO$11:INDIRECT("'Полная ст-ть с уч.НЗС (Авто)'!YO"&$J$26),$C11,'Полная ст-ть с уч.НЗС (Авто)'!UW$11:INDIRECT("'Полная ст-ть с уч.НЗС (Авто)'!UW"&$J$26))/$D11) -> 0 | UX11: =IF($D11=0,0,SUMIF('Полная ст-ть с уч.НЗС (Авто)'!$YO$11:INDIRECT("'Полная ст-ть с уч.НЗС (Авто)'!YO"&$J$26),$C11,'Полная ст-ть с уч.НЗС (Авто)'!UX$11:INDIRECT("'Полная ст-ть с уч.НЗС (Авто)'!UX"&$J$26))/$D11) -> 0 | UY11: =IF($D11=0,0,SUMIF('Полная ст-ть с уч.НЗС (Авто)'!$YO$11:INDIRECT("'Полная ст-ть с уч.НЗС (Авто)'!YO"&$J$26),$C11,'Полная ст-ть с уч.НЗС (Авто)'!UY$11:INDIRECT("'Полная ст-ть с уч.НЗС (Авто)'!UY"&$J$26))/$D11) -> 0 | UZ11: =IF($D11=0,0,SUMIF('Полная ст-ть с уч.НЗС (Авто)'!$YO$11:INDIRECT("'Полная ст-ть с уч.НЗС (Авто)'!YO"&$J$26),$C11,'Полная ст-ть с уч.НЗС (Авто)'!UZ$11:INDIRECT("'Полная ст-ть с уч.НЗС (Авто)'!UZ"&$J$26))/$D11) -> 0 | VA11: =IF($D11=0,0,SUMIF('Полная ст-ть с уч.НЗС (Авто)'!$YO$11:INDIRECT("'Полная ст-ть с уч.НЗС (Авто)'!YO"&$J$26),$C11,'Полная ст-ть с уч.НЗС (Авто)'!VA$11:INDIRECT("'Полная ст-ть с уч.НЗС (Авто)'!VA"&$J$26))/$D11) -> 0 | VB11: =IF($D11=0,0,SUMIF('Полная ст-ть с уч.НЗС (Авто)'!$YO$11:INDIRECT("'Полная ст-ть с уч.НЗС (Авто)'!YO"&$J$26),$C11,'Полная ст-ть с уч.НЗС (Авто)'!VB$11:INDIRECT("'Полная ст-ть с уч.НЗС (Авто)'!VB"&$J$26))/$D11) -> 0 | VC11: =IF($D11=0,0,SUMIF('Полная ст-ть с уч.НЗС (Авто)'!$YO$11:INDIRECT("'Полная ст-ть с уч.НЗС (Авто)'!YO"&$J$26),$C11,'Полная ст-ть с уч.НЗС (Авто)'!VC$11:INDIRECT("'Полная ст-ть с уч.НЗС (Авто)'!VC"&$J$26))/$D11) -> 0 | VD11: =IF($D11=0,0,SUMIF('Полная ст-ть с уч.НЗС (Авто)'!$YO$11:INDIRECT("'Полная ст-ть с уч.НЗС (Авто)'!YO"&$J$26),$C11,'Полная ст-ть с уч.НЗС (Авто)'!VD$11:INDIRECT("'Полная ст-ть с уч.НЗС (Авто)'!VD"&$J$26))/$D11) -> 0 | VE11: =IF($D11=0,0,SUMIF('Полная ст-ть с уч.НЗС (Авто)'!$YO$11:INDIRECT("'Полная ст-ть с уч.НЗС (Авто)'!YO"&$J$26),$C11,'Полная ст-ть с уч.НЗС (Авто)'!VE$11:INDIRECT("'Полная ст-ть с уч.НЗС (Авто)'!VE"&$J$26))/$D11) -> 0 | VF11: =IF($D11=0,0,SUMIF('Полная ст-ть с уч.НЗС (Авто)'!$YO$11:INDIRECT("'Полная ст-ть с уч.НЗС (Авто)'!YO"&$J$26),$C11,'Полная ст-ть с уч.НЗС (Авто)'!VF$11:INDIRECT("'Полная ст-ть с уч.НЗС (Авто)'!VF"&$J$26))/$D11) -> 0 | VG11: =IF($D11=0,0,SUMIF('Полная ст-ть с уч.НЗС (Авто)'!$YO$11:INDIRECT("'Полная ст-ть с уч.НЗС (Авто)'!YO"&$J$26),$C11,'Полная ст-ть с уч.НЗС (Авто)'!VG$11:INDIRECT("'Полная ст-ть с уч.НЗС (Авто)'!VG"&$J$26))/$D11) -> 0 | VH11: =IF($D11=0,0,SUMIF('Полная ст-ть с уч.НЗС (Авто)'!$YO$11:INDIRECT("'Полная ст-ть с уч.НЗС (Авто)'!YO"&$J$26),$C11,'Полная ст-ть с уч.НЗС (Авто)'!VH$11:INDIRECT("'Полная ст-ть с уч.НЗС (Авто)'!VH"&$J$26))/$D11) -> 0 | VI11: =IF($D11=0,0,SUMIF('Полная ст-ть с уч.НЗС (Авто)'!$YO$11:INDIRECT("'Полная ст-ть с уч.НЗС (Авто)'!YO"&$J$26),$C11,'Полная ст-ть с уч.НЗС (Авто)'!VI$11:INDIRECT("'Полная ст-ть с уч.НЗС (Авто)'!VI"&$J$26))/$D11) -> 0 | VJ11: =IF($D11=0,0,SUMIF('Полная ст-ть с уч.НЗС (Авто)'!$YO$11:INDIRECT("'Полная ст-ть с уч.НЗС (Авто)'!YO"&$J$26),$C11,'Полная ст-ть с уч.НЗС (Авто)'!VJ$11:INDIRECT("'Полная ст-ть с уч.НЗС (Авто)'!VJ"&$J$26))/$D11) -> 0 | VK11: =IF($D11=0,0,SUMIF('Полная ст-ть с уч.НЗС (Авто)'!$YO$11:INDIRECT("'Полная ст-ть с уч.НЗС (Авто)'!YO"&$J$26),$C11,'Полная ст-ть с уч.НЗС (Авто)'!VK$11:INDIRECT("'Полная ст-ть с уч.НЗС (Авто)'!VK"&$J$26))/$D11) -> 0 | VL11: =IF($D11=0,0,SUMIF('Полная ст-ть с уч.НЗС (Авто)'!$YO$11:INDIRECT("'Полная ст-ть с уч.НЗС (Авто)'!YO"&$J$26),$C11,'Полная ст-ть с уч.НЗС (Авто)'!VL$11:INDIRECT("'Полная ст-ть с уч.НЗС (Авто)'!VL"&$J$26))/$D11) -> 0 | VM11: =IF($D11=0,0,SUMIF('Полная ст-ть с уч.НЗС (Авто)'!$YO$11:INDIRECT("'Полная ст-ть с уч.НЗС (Авто)'!YO"&$J$26),$C11,'Полная ст-ть с уч.НЗС (Авто)'!VM$11:INDIRECT("'Полная ст-ть с уч.НЗС (Авто)'!VM"&$J$26))/$D11) -> 0 | VN11: =IF($D11=0,0,SUMIF('Полная ст-ть с уч.НЗС (Авто)'!$YO$11:INDIRECT("'Полная ст-ть с уч.НЗС (Авто)'!YO"&$J$26),$C11,'Полная ст-ть с уч.НЗС (Авто)'!VN$11:INDIRECT("'Полная ст-ть с уч.НЗС (Авто)'!VN"&$J$26))/$D11) -> 0 | VO11: =IF($D11=0,0,SUMIF('Полная ст-ть с уч.НЗС (Авто)'!$YO$11:INDIRECT("'Полная ст-ть с уч.НЗС (Авто)'!YO"&$J$26),$C11,'Полная ст-ть с уч.НЗС (Авто)'!VO$11:INDIRECT("'Полная ст-ть с уч.НЗС (Авто)'!VO"&$J$26))/$D11) -> 0 | VP11: =IF($D11=0,0,SUMIF('Полная ст-ть с уч.НЗС (Авто)'!$YO$11:INDIRECT("'Полная ст-ть с уч.НЗС (Авто)'!YO"&$J$26),$C11,'Полная ст-ть с уч.НЗС (Авто)'!VP$11:INDIRECT("'Полная ст-ть с уч.НЗС (Авто)'!VP"&$J$26))/$D11) -> 0 | VQ11: =IF($D11=0,0,SUMIF('Полная ст-ть с уч.НЗС (Авто)'!$YO$11:INDIRECT("'Полная ст-ть с уч.НЗС (Авто)'!YO"&$J$26),$C11,'Полная ст-ть с уч.НЗС (Авто)'!VQ$11:INDIRECT("'Полная ст-ть с уч.НЗС (Авто)'!VQ"&$J$26))/$D11) -> 0 | VR11: =IF($D11=0,0,SUMIF('Полная ст-ть с уч.НЗС (Авто)'!$YO$11:INDIRECT("'Полная ст-ть с уч.НЗС (Авто)'!YO"&$J$26),$C11,'Полная ст-ть с уч.НЗС (Авто)'!VR$11:INDIRECT("'Полная ст-ть с уч.НЗС (Авто)'!VR"&$J$26))/$D11) -> 0 | VS11: =IF($D11=0,0,SUMIF('Полная ст-ть с уч.НЗС (Авто)'!$YO$11:INDIRECT("'Полная ст-ть с уч.НЗС (Авто)'!YO"&$J$26),$C11,'Полная ст-ть с уч.НЗС (Авто)'!VS$11:INDIRECT("'Полная ст-ть с уч.НЗС (Авто)'!VS"&$J$26))/$D11) -> 0 | VT11: =IF($D11=0,0,SUMIF('Полная ст-ть с уч.НЗС (Авто)'!$YO$11:INDIRECT("'Полная ст-ть с уч.НЗС (Авто)'!YO"&$J$26),$C11,'Полная ст-ть с уч.НЗС (Авто)'!VT$11:INDIRECT("'Полная ст-ть с уч.НЗС (Авто)'!VT"&$J$26))/$D11) -> 0 | VU11: =IF($D11=0,0,SUMIF('Полная ст-ть с уч.НЗС (Авто)'!$YO$11:INDIRECT("'Полная ст-ть с уч.НЗС (Авто)'!YO"&$J$26),$C11,'Полная ст-ть с уч.НЗС (Авто)'!VU$11:INDIRECT("'Полная ст-ть с уч.НЗС (Авто)'!VU"&$J$26))/$D11) -> 0 | VV11: =IF($D11=0,0,SUMIF('Полная ст-ть с уч.НЗС (Авто)'!$YO$11:INDIRECT("'Полная ст-ть с уч.НЗС (Авто)'!YO"&$J$26),$C11,'Полная ст-ть с уч.НЗС (Авто)'!VV$11:INDIRECT("'Полная ст-ть с уч.НЗС (Авто)'!VV"&$J$26))/$D11) -> 0 | VW11: =IF($D11=0,0,SUMIF('Полная ст-ть с уч.НЗС (Авто)'!$YO$11:INDIRECT("'Полная ст-ть с уч.НЗС (Авто)'!YO"&$J$26),$C11,'Полная ст-ть с уч.НЗС (Авто)'!VW$11:INDIRECT("'Полная ст-ть с уч.НЗС (Авто)'!VW"&$J$26))/$D11) -> 0 | VX11: =IF($D11=0,0,SUMIF('Полная ст-ть с уч.НЗС (Авто)'!$YO$11:INDIRECT("'Полная ст-ть с уч.НЗС (Авто)'!YO"&$J$26),$C11,'Полная ст-ть с уч.НЗС (Авто)'!VX$11:INDIRECT("'Полная ст-ть с уч.НЗС (Авто)'!VX"&$J$26))/$D11) -> 0 | VY11: =IF($D11=0,0,SUMIF('Полная ст-ть с уч.НЗС (Авто)'!$YO$11:INDIRECT("'Полная ст-ть с уч.НЗС (Авто)'!YO"&$J$26),$C11,'Полная ст-ть с уч.НЗС (Авто)'!VY$11:INDIRECT("'Полная ст-ть с уч.НЗС (Авто)'!VY"&$J$26))/$D11) -> 0 | VZ11: =IF($D11=0,0,SUMIF('Полная ст-ть с уч.НЗС (Авто)'!$YO$11:INDIRECT("'Полная ст-ть с уч.НЗС (Авто)'!YO"&$J$26),$C11,'Полная ст-ть с уч.НЗС (Авто)'!VZ$11:INDIRECT("'Полная ст-ть с уч.НЗС (Авто)'!VZ"&$J$26))/$D11) -> 0 | WA11: =IF($D11=0,0,SUMIF('Полная ст-ть с уч.НЗС (Авто)'!$YO$11:INDIRECT("'Полная ст-ть с уч.НЗС (Авто)'!YO"&$J$26),$C11,'Полная ст-ть с уч.НЗС (Авто)'!WA$11:INDIRECT("'Полная ст-ть с уч.НЗС (Авто)'!WA"&$J$26))/$D11) -> 0 | WB11: =IF($D11=0,0,SUMIF('Полная ст-ть с уч.НЗС (Авто)'!$YO$11:INDIRECT("'Полная ст-ть с уч.НЗС (Авто)'!YO"&$J$26),$C11,'Полная ст-ть с уч.НЗС (Авто)'!WB$11:INDIRECT("'Полная ст-ть с уч.НЗС (Авто)'!WB"&$J$26))/$D11) -> 0 | WC11: =IF($D11=0,0,SUMIF('Полная ст-ть с уч.НЗС (Авто)'!$YO$11:INDIRECT("'Полная ст-ть с уч.НЗС (Авто)'!YO"&$J$26),$C11,'Полная ст-ть с уч.НЗС (Авто)'!WC$11:INDIRECT("'Полная ст-ть с уч.НЗС (Авто)'!WC"&$J$26))/$D11) -> 0 | WD11: =IF($D11=0,0,SUMIF('Полная ст-ть с уч.НЗС (Авто)'!$YO$11:INDIRECT("'Полная ст-ть с уч.НЗС (Авто)'!YO"&$J$26),$C11,'Полная ст-ть с уч.НЗС (Авто)'!WD$11:INDIRECT("'Полная ст-ть с уч.НЗС (Авто)'!WD"&$J$26))/$D11) -> 0 | WE11: =IF($D11=0,0,SUMIF('Полная ст-ть с уч.НЗС (Авто)'!$YO$11:INDIRECT("'Полная ст-ть с уч.НЗС (Авто)'!YO"&$J$26),$C11,'Полная ст-ть с уч.НЗС (Авто)'!WE$11:INDIRECT("'Полная ст-ть с уч.НЗС (Авто)'!WE"&$J$26))/$D11) -> 0 | WF11: =IF($D11=0,0,SUMIF('Полная ст-ть с уч.НЗС (Авто)'!$YO$11:INDIRECT("'Полная ст-ть с уч.НЗС (Авто)'!YO"&$J$26),$C11,'Полная ст-ть с уч.НЗС (Авто)'!WF$11:INDIRECT("'Полная ст-ть с уч.НЗС (Авто)'!WF"&$J$26))/$D11) -> 0 | WG11: =IF($D11=0,0,SUMIF('Полная ст-ть с уч.НЗС (Авто)'!$YO$11:INDIRECT("'Полная ст-ть с уч.НЗС (Авто)'!YO"&$J$26),$C11,'Полная ст-ть с уч.НЗС (Авто)'!WG$11:INDIRECT("'Полная ст-ть с уч.НЗС (Авто)'!WG"&$J$26))/$D11) -> 0 | WH11: =IF($D11=0,0,SUMIF('Полная ст-ть с уч.НЗС (Авто)'!$YO$11:INDIRECT("'Полная ст-ть с уч.НЗС (Авто)'!YO"&$J$26),$C11,'Полная ст-ть с уч.НЗС (Авто)'!WH$11:INDIRECT("'Полная ст-ть с уч.НЗС (Авто)'!WH"&$J$26))/$D11) -> 0 | WI11: =IF($D11=0,0,SUMIF('Полная ст-ть с уч.НЗС (Авто)'!$YO$11:INDIRECT("'Полная ст-ть с уч.НЗС (Авто)'!YO"&$J$26),$C11,'Полная ст-ть с уч.НЗС (Авто)'!WI$11:INDIRECT("'Полная ст-ть с уч.НЗС (Авто)'!WI"&$J$26))/$D11) -> 0 | WJ11: =IF($D11=0,0,SUMIF('Полная ст-ть с уч.НЗС (Авто)'!$YO$11:INDIRECT("'Полная ст-ть с уч.НЗС (Авто)'!YO"&$J$26),$C11,'Полная ст-ть с уч.НЗС (Авто)'!WJ$11:INDIRECT("'Полная ст-ть с уч.НЗС (Авто)'!WJ"&$J$26))/$D11) -> 0 | WK11: =IF($D11=0,0,SUMIF('Полная ст-ть с уч.НЗС (Авто)'!$YO$11:INDIRECT("'Полная ст-ть с уч.НЗС (Авто)'!YO"&$J$26),$C11,'Полная ст-ть с уч.НЗС (Авто)'!WK$11:INDIRECT("'Полная ст-ть с уч.НЗС (Авто)'!WK"&$J$26))/$D11) -> 0 | WL11: =IF($D11=0,0,SUMIF('Полная ст-ть с уч.НЗС (Авто)'!$YO$11:INDIRECT("'Полная ст-ть с уч.НЗС (Авто)'!YO"&$J$26),$C11,'Полная ст-ть с уч.НЗС (Авто)'!WL$11:INDIRECT("'Полная ст-ть с уч.НЗС (Авто)'!WL"&$J$26))/$D11) -> 0 | WM11: =IF($D11=0,0,SUMIF('Полная ст-ть с уч.НЗС (Авто)'!$YO$11:INDIRECT("'Полная ст-ть с уч.НЗС (Авто)'!YO"&$J$26),$C11,'Полная ст-ть с уч.НЗС (Авто)'!WM$11:INDIRECT("'Полная ст-ть с уч.НЗС (Авто)'!WM"&$J$26))/$D11) -> 0 | WN11: =IF($D11=0,0,SUMIF('Полная ст-ть с уч.НЗС (Авто)'!$YO$11:INDIRECT("'Полная ст-ть с уч.НЗС (Авто)'!YO"&$J$26),$C11,'Полная ст-ть с уч.НЗС (Авто)'!WN$11:INDIRECT("'Полная ст-ть с уч.НЗС (Авто)'!WN"&$J$26))/$D11) -> 0 | WO11: =IF($D11=0,0,SUMIF('Полная ст-ть с уч.НЗС (Авто)'!$YO$11:INDIRECT("'Полная ст-ть с уч.НЗС (Авто)'!YO"&$J$26),$C11,'Полная ст-ть с уч.НЗС (Авто)'!WO$11:INDIRECT("'Полная ст-ть с уч.НЗС (Авто)'!WO"&$J$26))/$D11) -> 0 | WP11: =IF($D11=0,0,SUMIF('Полная ст-ть с уч.НЗС (Авто)'!$YO$11:INDIRECT("'Полная ст-ть с уч.НЗС (Авто)'!YO"&$J$26),$C11,'Полная ст-ть с уч.НЗС (Авто)'!WP$11:INDIRECT("'Полная ст-ть с уч.НЗС (Авто)'!WP"&$J$26))/$D11) -> 0 | WQ11: =IF($D11=0,0,SUMIF('Полная ст-ть с уч.НЗС (Авто)'!$YO$11:INDIRECT("'Полная ст-ть с уч.НЗС (Авто)'!YO"&$J$26),$C11,'Полная ст-ть с уч.НЗС (Авто)'!WQ$11:INDIRECT("'Полная ст-ть с уч.НЗС (Авто)'!WQ"&$J$26))/$D11) -> 0 | WR11: =IF($D11=0,0,SUMIF('Полная ст-ть с уч.НЗС (Авто)'!$YO$11:INDIRECT("'Полная ст-ть с уч.НЗС (Авто)'!YO"&$J$26),$C11,'Полная ст-ть с уч.НЗС (Авто)'!WR$11:INDIRECT("'Полная ст-ть с уч.НЗС (Авто)'!WR"&$J$26))/$D11) -> 0 | WS11: =IF($D11=0,0,SUMIF('Полная ст-ть с уч.НЗС (Авто)'!$YO$11:INDIRECT("'Полная ст-ть с уч.НЗС (Авто)'!YO"&$J$26),$C11,'Полная ст-ть с уч.НЗС (Авто)'!WS$11:INDIRECT("'Полная ст-ть с уч.НЗС (Авто)'!WS"&$J$26))/$D11) -> 0 | WT11: =IF($D11=0,0,SUMIF('Полная ст-ть с уч.НЗС (Авто)'!$YO$11:INDIRECT("'Полная ст-ть с уч.НЗС (Авто)'!YO"&$J$26),$C11,'Полная ст-ть с уч.НЗС (Авто)'!WT$11:INDIRECT("'Полная ст-ть с уч.НЗС (Авто)'!WT"&$J$26))/$D11) -> 0 | WU11: =IF($D11=0,0,SUMIF('Полная ст-ть с уч.НЗС (Авто)'!$YO$11:INDIRECT("'Полная ст-ть с уч.НЗС (Авто)'!YO"&$J$26),$C11,'Полная ст-ть с уч.НЗС (Авто)'!WU$11:INDIRECT("'Полная ст-ть с уч.НЗС (Авто)'!WU"&$J$26))/$D11) -> 0 | WV11: =IF($D11=0,0,SUMIF('Полная ст-ть с уч.НЗС (Авто)'!$YO$11:INDIRECT("'Полная ст-ть с уч.НЗС (Авто)'!YO"&$J$26),$C11,'Полная ст-ть с уч.НЗС (Авто)'!WV$11:INDIRECT("'Полная ст-ть с уч.НЗС (Авто)'!WV"&$J$26))/$D11) -> 0 | WW11: =IF($D11=0,0,SUMIF('Полная ст-ть с уч.НЗС (Авто)'!$YO$11:INDIRECT("'Полная ст-ть с уч.НЗС (Авто)'!YO"&$J$26),$C11,'Полная ст-ть с уч.НЗС (Авто)'!WW$11:INDIRECT("'Полная ст-ть с уч.НЗС (Авто)'!WW"&$J$26))/$D11) -> 0 | WX11: =IF($D11=0,0,SUMIF('Полная ст-ть с уч.НЗС (Авто)'!$YO$11:INDIRECT("'Полная ст-ть с уч.НЗС (Авто)'!YO"&$J$26),$C11,'Полная ст-ть с уч.НЗС (Авто)'!WX$11:INDIRECT("'Полная ст-ть с уч.НЗС (Авто)'!WX"&$J$26))/$D11) -> 0 | WY11: =IF($D11=0,0,SUMIF('Полная ст-ть с уч.НЗС (Авто)'!$YO$11:INDIRECT("'Полная ст-ть с уч.НЗС (Авто)'!YO"&$J$26),$C11,'Полная ст-ть с уч.НЗС (Авто)'!WY$11:INDIRECT("'Полная ст-ть с уч.НЗС (Авто)'!WY"&$J$26))/$D11) -> 0 | WZ11: =IF($D11=0,0,SUMIF('Полная ст-ть с уч.НЗС (Авто)'!$YO$11:INDIRECT("'Полная ст-ть с уч.НЗС (Авто)'!YO"&$J$26),$C11,'Полная ст-ть с уч.НЗС (Авто)'!WZ$11:INDIRECT("'Полная ст-ть с уч.НЗС (Авто)'!WZ"&$J$26))/$D11) -> 0 | XA11: =IF($D11=0,0,SUMIF('Полная ст-ть с уч.НЗС (Авто)'!$YO$11:INDIRECT("'Полная ст-ть с уч.НЗС (Авто)'!YO"&$J$26),$C11,'Полная ст-ть с уч.НЗС (Авто)'!XA$11:INDIRECT("'Полная ст-ть с уч.НЗС (Авто)'!XA"&$J$26))/$D11) -> 0 | XB11: =IF($D11=0,0,SUMIF('Полная ст-ть с уч.НЗС (Авто)'!$YO$11:INDIRECT("'Полная ст-ть с уч.НЗС (Авто)'!YO"&$J$26),$C11,'Полная ст-ть с уч.НЗС (Авто)'!XB$11:INDIRECT("'Полная ст-ть с уч.НЗС (Авто)'!XB"&$J$26))/$D11) -> 0 | XC11: =IF($D11=0,0,SUMIF('Полная ст-ть с уч.НЗС (Авто)'!$YO$11:INDIRECT("'Полная ст-ть с уч.НЗС (Авто)'!YO"&$J$26),$C11,'Полная ст-ть с уч.НЗС (Авто)'!XC$11:INDIRECT("'Полная ст-ть с уч.НЗС (Авто)'!XC"&$J$26))/$D11) -> 0 | XD11: =IF($D11=0,0,SUMIF('Полная ст-ть с уч.НЗС (Авто)'!$YO$11:INDIRECT("'Полная ст-ть с уч.НЗС (Авто)'!YO"&$J$26),$C11,'Полная ст-ть с уч.НЗС (Авто)'!XD$11:INDIRECT("'Полная ст-ть с уч.НЗС (Авто)'!XD"&$J$26))/$D11) -> 0 | XE11: =IF($D11=0,0,SUMIF('Полная ст-ть с уч.НЗС (Авто)'!$YO$11:INDIRECT("'Полная ст-ть с уч.НЗС (Авто)'!YO"&$J$26),$C11,'Полная ст-ть с уч.НЗС (Авто)'!XE$11:INDIRECT("'Полная ст-ть с уч.НЗС (Авто)'!XE"&$J$26))/$D11) -> 0 | XF11: =IF($D11=0,0,SUMIF('Полная ст-ть с уч.НЗС (Авто)'!$YO$11:INDIRECT("'Полная ст-ть с уч.НЗС (Авто)'!YO"&$J$26),$C11,'Полная ст-ть с уч.НЗС (Авто)'!XF$11:INDIRECT("'Полная ст-ть с уч.НЗС (Авто)'!XF"&$J$26))/$D11) -> 0 | XG11: =IF($D11=0,0,SUMIF('Полная ст-ть с уч.НЗС (Авто)'!$YO$11:INDIRECT("'Полная ст-ть с уч.НЗС (Авто)'!YO"&$J$26),$C11,'Полная ст-ть с уч.НЗС (Авто)'!XG$11:INDIRECT("'Полная ст-ть с уч.НЗС (Авто)'!XG"&$J$26))/$D11) -> 0 | XH11: =IF($D11=0,0,SUMIF('Полная ст-ть с уч.НЗС (Авто)'!$YO$11:INDIRECT("'Полная ст-ть с уч.НЗС (Авто)'!YO"&$J$26),$C11,'Полная ст-ть с уч.НЗС (Авто)'!XH$11:INDIRECT("'Полная ст-ть с уч.НЗС (Авто)'!XH"&$J$26))/$D11) -> 0 | XI11: =IF($D11=0,0,SUMIF('Полная ст-ть с уч.НЗС (Авто)'!$YO$11:INDIRECT("'Полная ст-ть с уч.НЗС (Авто)'!YO"&$J$26),$C11,'Полная ст-ть с уч.НЗС (Авто)'!XI$11:INDIRECT("'Полная ст-ть с уч.НЗС (Авто)'!XI"&$J$26))/$D11) -> 0 | XJ11: =IF($D11=0,0,SUMIF('Полная ст-ть с уч.НЗС (Авто)'!$YO$11:INDIRECT("'Полная ст-ть с уч.НЗС (Авто)'!YO"&$J$26),$C11,'Полная ст-ть с уч.НЗС (Авто)'!XJ$11:INDIRECT("'Полная ст-ть с уч.НЗС (Авто)'!XJ"&$J$26))/$D11) -> 0 | XK11: =IF($D11=0,0,SUMIF('Полная ст-ть с уч.НЗС (Авто)'!$YO$11:INDIRECT("'Полная ст-ть с уч.НЗС (Авто)'!YO"&$J$26),$C11,'Полная ст-ть с уч.НЗС (Авто)'!XK$11:INDIRECT("'Полная ст-ть с уч.НЗС (Авто)'!XK"&$J$26))/$D11) -> 0 | XL11: =IF($D11=0,0,SUMIF('Полная ст-ть с уч.НЗС (Авто)'!$YO$11:INDIRECT("'Полная ст-ть с уч.НЗС (Авто)'!YO"&$J$26),$C11,'Полная ст-ть с уч.НЗС (Авто)'!XL$11:INDIRECT("'Полная ст-ть с уч.НЗС (Авто)'!XL"&$J$26))/$D11) -> 0 | XM11: =IF($D11=0,0,SUMIF('Полная ст-ть с уч.НЗС (Авто)'!$YO$11:INDIRECT("'Полная ст-ть с уч.НЗС (Авто)'!YO"&$J$26),$C11,'Полная ст-ть с уч.НЗС (Авто)'!XM$11:INDIRECT("'Полная ст-ть с уч.НЗС (Авто)'!XM"&$J$26))/$D11) -> 0 | XN11: =IF($D11=0,0,SUMIF('Полная ст-ть с уч.НЗС (Авто)'!$YO$11:INDIRECT("'Полная ст-ть с уч.НЗС (Авто)'!YO"&$J$26),$C11,'Полная ст-ть с уч.НЗС (Авто)'!XN$11:INDIRECT("'Полная ст-ть с уч.НЗС (Авто)'!XN"&$J$26))/$D11) -> 0 | XO11: =IF($D11=0,0,SUMIF('Полная ст-ть с уч.НЗС (Авто)'!$YO$11:INDIRECT("'Полная ст-ть с уч.НЗС (Авто)'!YO"&$J$26),$C11,'Полная ст-ть с уч.НЗС (Авто)'!XO$11:INDIRECT("'Полная ст-ть с уч.НЗС (Авто)'!XO"&$J$26))/$D11) -> 0 | XP11: =IF($D11=0,0,SUMIF('Полная ст-ть с уч.НЗС (Авто)'!$YO$11:INDIRECT("'Полная ст-ть с уч.НЗС (Авто)'!YO"&$J$26),$C11,'Полная ст-ть с уч.НЗС (Авто)'!XP$11:INDIRECT("'Полная ст-ть с уч.НЗС (Авто)'!XP"&$J$26))/$D11) -> 0 | XQ11: =IF($D11=0,0,SUMIF('Полная ст-ть с уч.НЗС (Авто)'!$YO$11:INDIRECT("'Полная ст-ть с уч.НЗС (Авто)'!YO"&$J$26),$C11,'Полная ст-ть с уч.НЗС (Авто)'!XQ$11:INDIRECT("'Полная ст-ть с уч.НЗС (Авто)'!XQ"&$J$26))/$D11) -> 0 | XR11: =IF($D11=0,0,SUMIF('Полная ст-ть с уч.НЗС (Авто)'!$YO$11:INDIRECT("'Полная ст-ть с уч.НЗС (Авто)'!YO"&$J$26),$C11,'Полная ст-ть с уч.НЗС (Авто)'!XR$11:INDIRECT("'Полная ст-ть с уч.НЗС (Авто)'!XR"&$J$26))/$D11) -> 0 | XS11: =IF($D11=0,0,SUMIF('Полная ст-ть с уч.НЗС (Авто)'!$YO$11:INDIRECT("'Полная ст-ть с уч.НЗС (Авто)'!YO"&$J$26),$C11,'Полная ст-ть с уч.НЗС (Авто)'!XS$11:INDIRECT("'Полная ст-ть с уч.НЗС (Авто)'!XS"&$J$26))/$D11) -> 0 | XT11: =IF($D11=0,0,SUMIF('Полная ст-ть с уч.НЗС (Авто)'!$YO$11:INDIRECT("'Полная ст-ть с уч.НЗС (Авто)'!YO"&$J$26),$C11,'Полная ст-ть с уч.НЗС (Авто)'!XT$11:INDIRECT("'Полная ст-ть с уч.НЗС (Авто)'!XT"&$J$26))/$D11) -> 0 | XU11: =IF($D11=0,0,SUMIF('Полная ст-ть с уч.НЗС (Авто)'!$YO$11:INDIRECT("'Полная ст-ть с уч.НЗС (Авто)'!YO"&$J$26),$C11,'Полная ст-ть с уч.НЗС (Авто)'!XU$11:INDIRECT("'Полная ст-ть с уч.НЗС (Авто)'!XU"&$J$26))/$D11) -> 0 | XV11: =IF($D11=0,0,SUMIF('Полная ст-ть с уч.НЗС (Авто)'!$YO$11:INDIRECT("'Полная ст-ть с уч.НЗС (Авто)'!YO"&$J$26),$C11,'Полная ст-ть с уч.НЗС (Авто)'!XV$11:INDIRECT("'Полная ст-ть с уч.НЗС (Авто)'!XV"&$J$26))/$D11) -> 0 | XW11: =IF($D11=0,0,SUMIF('Полная ст-ть с уч.НЗС (Авто)'!$YO$11:INDIRECT("'Полная ст-ть с уч.НЗС (Авто)'!YO"&$J$26),$C11,'Полная ст-ть с уч.НЗС (Авто)'!XW$11:INDIRECT("'Полная ст-ть с уч.НЗС (Авто)'!XW"&$J$26))/$D11) -> 0 | XX11: =IF($D11=0,0,SUMIF('Полная ст-ть с уч.НЗС (Авто)'!$YO$11:INDIRECT("'Полная ст-ть с уч.НЗС (Авто)'!YO"&$J$26),$C11,'Полная ст-ть с уч.НЗС (Авто)'!XX$11:INDIRECT("'Полная ст-ть с уч.НЗС (Авто)'!XX"&$J$26))/$D11) -> 0 | XY11: =IF($D11=0,0,SUMIF('Полная ст-ть с уч.НЗС (Авто)'!$YO$11:INDIRECT("'Полная ст-ть с уч.НЗС (Авто)'!YO"&$J$26),$C11,'Полная ст-ть с уч.НЗС (Авто)'!XY$11:INDIRECT("'Полная ст-ть с уч.НЗС (Авто)'!XY"&$J$26))/$D11) -> 0 | XZ11: =IF($D11=0,0,SUMIF('Полная ст-ть с уч.НЗС (Авто)'!$YO$11:INDIRECT("'Полная ст-ть с уч.НЗС (Авто)'!YO"&$J$26),$C11,'Полная ст-ть с уч.НЗС (Авто)'!XZ$11:INDIRECT("'Полная ст-ть с уч.НЗС (Авто)'!XZ"&$J$26))/$D11) -> 0 | YA11: =IF($D11=0,0,SUMIF('Полная ст-ть с уч.НЗС (Авто)'!$YO$11:INDIRECT("'Полная ст-ть с уч.НЗС (Авто)'!YO"&$J$26),$C11,'Полная ст-ть с уч.НЗС (Авто)'!YA$11:INDIRECT("'Полная ст-ть с уч.НЗС (Авто)'!YA"&$J$26))/$D11) -> 0 | YB11: =IF($D11=0,0,SUMIF('Полная ст-ть с уч.НЗС (Авто)'!$YO$11:INDIRECT("'Полная ст-ть с уч.НЗС (Авто)'!YO"&$J$26),$C11,'Полная ст-ть с уч.НЗС (Авто)'!YB$11:INDIRECT("'Полная ст-ть с уч.НЗС (Авто)'!YB"&$J$26))/$D11) -> 0 | YC11: =IF($D11=0,0,SUMIF('Полная ст-ть с уч.НЗС (Авто)'!$YO$11:INDIRECT("'Полная ст-ть с уч.НЗС (Авто)'!YO"&$J$26),$C11,'Полная ст-ть с уч.НЗС (Авто)'!YC$11:INDIRECT("'Полная ст-ть с уч.НЗС (Авто)'!YC"&$J$26))/$D11) -> 0 | YD11: =IF($D11=0,0,SUMIF('Полная ст-ть с уч.НЗС (Авто)'!$YO$11:INDIRECT("'Полная ст-ть с уч.НЗС (Авто)'!YO"&$J$26),$C11,'Полная ст-ть с уч.НЗС (Авто)'!YD$11:INDIRECT("'Полная ст-ть с уч.НЗС (Авто)'!YD"&$J$26))/$D11) -> 0 | YE11: =IF($D11=0,0,SUMIF('Полная ст-ть с уч.НЗС (Авто)'!$YO$11:INDIRECT("'Полная ст-ть с уч.НЗС (Авто)'!YO"&$J$26),$C11,'Полная ст-ть с уч.НЗС (Авто)'!YE$11:INDIRECT("'Полная ст-ть с уч.НЗС (Авто)'!YE"&$J$26))/$D11) -> 0
