Workbook
Name ___Dec1: 0
Name ___Dec2: 0
Name ___w306: [1]wells_graf!$A$47:$P$69
Name ___w5221: [1]wells_graf!$A$24:$P$46
Name ___w606: [1]wells_graf!$A$1:$H$23
Name ___w628: [1]wells_graf!$I$47:$P$69
Name ___w68: [1]wells_graf!$I$24:$P$46
Name ___W688: [2]wells_graf!$I$24:$P$46
Name __Dec1: 0
Name __Dec2: 0
Name __w306: [1]wells_graf!$A$47:$P$69
Name __w5221: [1]wells_graf!$A$24:$P$46
Name __w606: [1]wells_graf!$A$1:$H$23
Name __w628: [1]wells_graf!$I$47:$P$69
Name __w68: [1]wells_graf!$I$24:$P$46
Name __W688: [2]wells_graf!$I$24:$P$46
Name _2049_2050: '[3]311-1Á10'!#REF!
Name _2049_2050: '[3]311-1Á10'!#REF!
Name _2049_2050: '[3]311-1Á10'!#REF!
Name _2049_2050: '[3]311-1Á10'!#REF!
Name _2049_2050: '[3]311-1Á10'!#REF!
Name _2049_2050: '[3]311-1Á10'!#REF!
Name _2049_2050: '[3]311-1Á10'!#REF!
Name _2049_2050: '[3]311-1Á10'!#REF!
Name _2049_2050: '[3]311-1Á10'!#REF!
Name _2049_2050: '[3]311-1Á10'!#REF!
Name _2049_2050: '[3]311-1Á10'!#REF!
Name _2049_2050: '[3]311-1Á10'!#REF!
Name _2049_2050: '[3]311-1Á10'!#REF!
Name _2049_2050: '[3]311-1Á10'!#REF!
Name _2049_2050: '[3]311-1Á10'!#REF!
Name _2049_2050: '[3]311-1Á10'!#REF!
Name _2049_2050: '[3]311-1Á10'!#REF!
Name _Dec1: 0
Name _Dec2: 0
Name _w306: [1]wells_graf!$A$47:$P$69
Name _w5221: [1]wells_graf!$A$24:$P$46
Name _w606: [1]wells_graf!$A$1:$H$23
Name _w628: [1]wells_graf!$I$47:$P$69
Name _w68: [1]wells_graf!$I$24:$P$46
Name _W688: [2]wells_graf!$I$24:$P$46
Name add1_1Q: [4]Resources!$C$172
Name add1_2Q: [4]Resources!$C$173
Name add1_3D_seismic: [4]Resources!$C$188
Name add1_3Q: [4]Resources!$C$174
Name add1_4Q: [4]Resources!$C$175
Name add1_bases: [4]Resources!$C$195
Name add1_capex_investments: [4]Resources!$C$183
Name add1_cell_sidetracking: '[4]1'!$C$41
Name add1_development_of_drilling_facilities: [4]Resources!$C$187
Name add1_drilling: [4]Resources!$C$185
Name add1_frac_costs: [4]Resources!$C$203
Name add1_inflow_stimulation: [4]Resources!$C$186
Name add1_investment_designation: [4]Resources!$C$169
Name add1_investments: [4]Resources!$C$182
Name add1_modernization: [4]Resources!$C$189
Name add1_motorways: [4]Resources!$C$193
Name add1_new_construction: [4]Resources!$C$198
Name add1_oil_production: [4]Resources!$C$176
Name add1_oil_production_wells_1Q: [4]Resources!$C$177

Sheet Титул 
B1: Проект: | C1: Бурение
C2: Вид проекта
B4: Название проекта: | C4: Бурение скважин в 2016-2018 гг.
G5: куст №21б Приобского месторождения
B7: Наименование организации: | C7: ОАО "Газпромнефть-Хантос"
B9: Начало проведения (мес/год) | C9: 42401 | D9: (мес/год)
B10: Конец проведения работ (мес/год) | C10: 42795 | D10: (мес/год)
B11: Буровой подрядчик | C11: не определен | F11: (наименование организации)
B12: Тип буровго станка | C12: БУ-3000 ЭУК | F12: (наименование типа БУ)
B13: Наличие ВСП | C13: да | D13: (Да/ Нет)
B14: Наличие АвИЭС | C14: нет | D14: (Да/ Нет)
B15: Наличие автономности | C15: нет | D15: (Да/ Нет/ Частично на межсезонье)
B17: ОТВЕТСТВЕННЫЕ СПЕЦИАЛИСТЫ ПО ПРОЕКТУ
B18: По технико-технологическим показателям | C18: Столбовой С.В. | H18: 925-202 | I18: Начальник производственного отдела УСС
C19: Ф.И.О. | H19: тел. | I19: должность
B20: По экономическим показателям | C20: Игумнов М.С. | H20: 354-882 | I20: Начальник планово-договорного отдела УСС
C21: Ф.И.О. | H21: тел. | I21: должность
B23: Тэхнико-экономические показатели строительства по проекту:
B25: Наименование показателя | C25: Ед. изм. | D25: Кол-во скважин, законченных бурением | F25: Кол-во скважин, законченных освоением | H25: Проходка по скважинам, м | J25: Время бурения, сут. | L25: Время осовения, сут.
D26: 2014-2016 | E26: Всего скв. | F26: =D26 -> 2014-2016 | G26: Всего скв. | H26: Всего | I26: Ср. значение на 1 скв. | J26: Всего | K26: Ср. значение на 1 скв. | L26: Всего | M26: Ср. значение на 1 скв.
B27: Итого | C27: скв. | D27: =SUM(D28:D43) -> 8 | E27: =SUM(E28:E43) -> 8 | F27: =SUM(F28:F43) -> 8 | G27: =SUM(G28:G43) -> 8 | H27: =SUM(H28:H43) -> 35000 | I27: =H27/E27 -> 4375 | J27: =SUM(J28:J43) -> 270 | K27: =J27/E27 -> 33.75 | L27: =SUM(L28:L43) -> 152 | M27: =L27/G27 -> 19
B28: Перв.скв. (тип скв) | C28: скв. | D28: 1 | E28: =D28 -> 1 | F28: =D28 -> 1 | G28: =F28 -> 1 | H28: =$E28*I28 -> 5500 | I28: ='Перв. скв '!$D$8 -> 5500 | J28: =$E28*K28 -> 45 | K28: ='Перв. скв '!$O$6 -> 45 | L28: =$G28*M28 -> 19 | M28: ='Перв. скв '!$R$6 -> 19
B29: ННС до 1300 | C29: скв. | D29: 0 | E29: =D29 -> 0 | F29: =D29 -> 0 | G29: =F29 -> 0 | H29: =$E29*I29 -> 0 | I29: =ННСдо1300!$D$8 -> 3000 | J29: =$E29*K29 -> 0 | K29: =ННСдо1300!$O$6 -> 12 | L29: =$G29*M29 -> 0 | M29: =ННСдо1300!$R$6 -> 17
B30: ННС от 1300 до 1500 | C30: скв. | D30: 0 | E30: =D30 -> 0 | F30: =D30 -> 0 | G30: =F30 -> 0 | H30: =$E30*I30 -> 0 | I30: =ННСот1300до1500!$D$8 -> 3250 | J30: =$E30*K30 -> 0 | K30: =ННСот1300до1500!$O$6 -> 12 | L30: =$G30*M30 -> 0 | M30: =ННСот1300до1500!$R$6 -> 17
B31: ННС от 1500 до 2000 | C31: скв. | D31: 0 | E31: =D31 -> 0 | F31: =D31 -> 0 | G31: =F31 -> 0 | H31: =$E31*I31 -> 0 | I31: =ННСот1500до2000!$D$8 -> 3450 | J31: =$E31*K31 -> 0 | K31: =ННСот1500до2000!$O$6 -> 15 | L31: =$G31*M31 -> 0 | M31: =ННСот1500до2000!$R$6 -> 17
B32: ННС от 2000 до 2200 | C32: скв. | D32: 0 | E32: =D32 -> 0 | F32: =D32 -> 0 | G32: =F32 -> 0 | H32: =$E32*I32 -> 0 | I32: =ННСот2000до2200!$D$8 -> 3600 | J32: =$E32*K32 -> 0 | K32: =ННСот2000до2200!$O$6 -> 16 | L32: =$G32*M32 -> 0 | M32: =ННСот2000до2200!$R$6 -> 17
B33: ННС более 2200 | C33: скв. | D33: 0 | E33: =D33 -> 0 | F33: =D33 -> 0 | G33: =F33 -> 0 | H33: =$E33*I33 -> 0 | I33: =ННСболее2200!$D$8 -> 3700 | J33: =$E33*K33 -> 0 | K33: =ННСболее2200!$O$6 -> 18 | L33: =$G33*M33 -> 0 | M33: =ННСболее2200!$R$6 -> 17
B34: Оценочная | C34: скв. | D34: 0 | E34: =D34 -> 0 | F34: =D34 -> 0 | G34: =F34 -> 0 | H34: =$E34*I34 -> 0 | I34: =Оценочная!$D$8 -> 3000 | J34: =$E34*K34 -> 0 | K34: =Оценочная!$O$6 -> 12 | L34: =$G34*M34 -> 0 | M34: =Оценочная!$R$6 -> 0
B35: ННС Юра >800 | C35: скв. | E35: =D35 -> 0 | F35: =D35 -> 0 | G35: =F35 -> 0 | H35: =$E35*I35 -> 0 | I35: ='ННСЮра>800'!$D$8 -> 0 | J35: =$E35*K35 -> 0 | K35: ='ННСЮра>800'!$O$6 -> 0 | L35: =$G35*M35 -> 0 | M35: ='ННСЮра>800'!$R$6 -> 0
B36: ГС с пилотом | C36: скв. | D36: 0 | E36: =D36 -> 0 | F36: =D36 -> 0 | G36: =F36 -> 0 | H36: =$E36*I36 -> 0 | I36: ='ГС пил'!$D$8 -> 5500 | J36: =$E36*K36 -> 0 | K36: ='ГС пил'!$O$6 -> 45 | L36: =$G36*M36 -> 0 | M36: ='ГС пил'!$R$6 -> 19
B37: ГС без пилота | C37: скв. | D37: 6 | E37: =D37 -> 6 | F37: =D37 -> 6 | G37: =F37 -> 6 | H37: =$E37*I37 -> 24000 | I37: ='ГС без пил'!$D$8 -> 4000 | J37: =$E37*K37 -> 180 | K37: ='ГС без пил'!$O$6 -> 30 | L37: =$G37*M37 -> 114 | M37: ='ГС без пил'!$R$6 -> 19
B38: ГС с пилотом и МСГРП | C38: скв. | E38: =D38 -> 0 | F38: =D38 -> 0 | G38: =F38 -> 0 | H38: =$E38*I38 -> 0 | I38: ='ГС пил МСГРП'!$D$8 -> 0 | J38: =$E38*K38 -> 0 | K38: ='ГС пил МСГРП'!$O$6 -> 0 | L38: =$G38*M38 -> 0 | M38: ='ГС пил МСГРП'!$R$6 -> 0
B39: ГС Юра с пилотом | C39: скв. | F39: =D39 -> 0 | G39: =F39 -> 0 | H39: =$E39*I39 -> 0 | I39: ='ГСЮра пил'!$D$8 -> 0 | J39: =$E39*K39 -> 0 | K39: ='ГСЮра пил'!$O$6 -> 0 | L39: =$G39*M39 -> 0 | M39: ='ГСЮра пил'!$R$6 -> 0
B40: ГС Юра без пилота | C40: скв. | F40: =D40 -> 0 | G40: =F40 -> 0 | H40: =$E40*I40 -> 0 | I40: ='ГСЮра без пил'!$D$8 -> 0 | J40: =$E40*K40 -> 0 | K40: ='ГСЮра без пил'!$O$6 -> 0 | L40: =$G40*M40 -> 0 | M40: ='ГСЮра без пил'!$R$6 -> 0
B41: ГС Юра с пилотом и МСГРП | C41: скв. | F41: =D41 -> 0 | G41: =F41 -> 0 | H41: =$E41*I41 -> 0 | I41: ='ГСЮра пил МСГРП'!$D$8 -> 0 | J41: =$E41*K41 -> 0 | K41: ='ГСЮра пил МСГРП'!$O$6 -> 0 | L41: =$G41*M41 -> 0 | M41: ='ГСЮра пил МСГРП'!$R$6 -> 0
B42: Вод/з | C42: скв. | F42: =D42 -> 0 | G42: =F42 -> 0 | H42: =$E42*I42 -> 0 | I42: =ВЗ!$D$8 -> 0 | J42: =$E42*K42 -> 0 | K42: =ВЗ!$O$6 -> 0 | L42: =$G42*M42 -> 0 | M42: =ВЗ!$R$6 -> 0
B43: Посл.скв. | C43: скв. | D43: 1 | E43: =D43 -> 1 | F43: =D43 -> 1 | G43: =F43 -> 1 | H43: =$E43*I43 -> 5500 | I43: ='Посл. скв'!$D$8 -> 5500 | J43: =$E43*K43 -> 45 | K43: ='Посл. скв'!$O$6 -> 45 | L43: =$G43*M43 -> 19 | M43: ='Посл. скв'!$R$6 -> 19
B45: Среднее по ННС | C45: скв. | D45: 0 | E45: 0 | F45: 0 | G45: 0 | H45: 0 | I45: 0 | J45: 0 | K45: 0 | L45: 0 | M45: 0
B46: Среднее по ГС | C46: скв. | D46: =D43+D37+D36+D28 -> 8 | E46: =E43+E37+E36+E28 -> 8 | F46: =F43+F37+F36+F28 -> 8 | G46: =G43+G37+G36+G28 -> 8 | H46: =H43+H37+H36+H28 -> 35000 | I46: =H46/D46 -> 4375 | J46: =J43+J37+J36+J28 -> 270 | K46: =J46/D46 -> 33.75 | L46: =L43+L37+L36+L28 -> 152 | M46: =L46/D46 -> 19
C47: ='[8]Куст №40А'!$AD$2160 -> 265913.3 | E47: =C47-E52 -> -556692.06
B48: Экономические показатели строительства по проекту:
M49: (без НДС)
B50: Наименование показателя | C50: Ст-ть работ, тыс.руб. | F50: Всего ст-ть работ, тыс.руб. | H50: Ст-ть бурения, тыс.руб. | J50: Ст-ть освоения, тыс.руб. | L50: Ст-ть ВМР, тыс.руб. | M50: Ст-ть обор-ия, тыс.руб.
C51: Бурение (без ВМР) | D51: Освоение | E51: Всего с ВМР и обор. | F51: Итого | G51: Ср. значение на 1 скв. | H51: Всего | I51: Ср. значение на 1 скв. | J51: Всего | K51: Ср. значение на 1 скв.
B52: Итого | C52: =SUM(C53:C68) -> 493444.61 | D52: =SUM(D53:D68) -> 295235.89 | E52: =SUM(E53:E68) -> 822605.36 | F52: =SUM(F53:F68) -> 822605.36 | G52: =F52/G27 -> 102825.67 | H52: =SUM(H53:H68) -> 493444.61 | I52: =H52/E27 -> 61680.576 | J52: =SUM(J53:J68) -> 295235.89 | K52: =J52/G27 -> 36904.487 | L52: =SUM(L53:L68) -> 33924.862 | M52: =SUM(M53:M68) -> 0
B53: Перв.скв. (тип скв) | C53: =I53*D28 -> 69765.317 | D53: =K53*F28 -> 36904.487 | E53: =IFERROR(C53+D53+L53/E28*D28+M53/G28*F28,0) -> 132383.93 | F53: =H53+J53+L53+M53 -> 132383.93 | G53: =IFERROR(F53/G28,0) -> 132383.93 | H53: =E28*I53 -> 69765.317 | I53: ='Перв. скв '!$E$9/1000 -> 69765.317 | J53: =G28*K53 -> 36904.487 | K53: ='Перв. скв '!$E$11/1000 -> 36904.487 | L53: ='Перв. скв '!$E$7/1000*D28 -> 25714.124 | M53: ='Перв. скв '!$E$13/1000*G28 -> 0
B54: ННС до 1300 | C54: =I54*D29 -> 0 | D54: =K54*F29 -> 0 | E54: =IFERROR(C54+D54+L54/E29*D29+M54/G29*F29,0) -> 0 | F54: =H54+J54+L54+M54 -> 0 | G54: =IFERROR(F54/G29,0) -> 0 | H54: =E29*I54 -> 0 | I54: =ННСдо1300!$E$9/1000 -> 68837.029 | J54: =G29*K54 -> 0 | K54: =ННСдо1300!$E$11/1000 -> 36904.487 | L54: =ННСдо1300!$E$7/1000*E29 -> 0 | M54: =ННСдо1300!$E$13/1000*G29 -> 0
B55: ННС от 1300 до 1500 | C55: =I55*D30 -> 0 | D55: =K55*F30 -> 0 | E55: =IFERROR(C55+D55+L55/E30*D30+M55/G30*F30,0) -> 0 | F55: =H55+J55+L55+M55 -> 0 | G55: =IFERROR(F55/G30,0) -> 0 | H55: =E30*I55 -> 0 | I55: =ННСот1300до1500!$E$9/1000 -> 71125.996 | J55: =G30*K55 -> 0 | K55: =ННСот1300до1500!$E$11/1000 -> 36904.487 | L55: =ННСот1300до1500!$E$7/1000*E30 -> 0 | M55: =ННСот1300до1500!$E$13/1000*G30 -> 0
B56: ННС от 1500 до 2000 | C56: =I56*D31 -> 0 | D56: =K56*F31 -> 0 | E56: =IFERROR(C56+D56+L56/E31*D31+M56/G31*F31,0) -> 0 | F56: =H56+J56+L56+M56 -> 0 | G56: =IFERROR(F56/G31,0) -> 0 | H56: =E31*I56 -> 0 | I56: =ННСот1500до2000!$E$9/1000 -> 73675.058 | J56: =G31*K56 -> 0 | K56: =ННСот1500до2000!$E$11/1000 -> 36904.487 | L56: =ННСот1500до2000!$E$7/1000*E31 -> 0 | M56: =ННСот1500до2000!$E$13/1000*G31 -> 0
B57: ННС от 2000 до 2200 | C57: =I57*D32 -> 0 | D57: =K57*F32 -> 0 | E57: =IFERROR(C57+D57+L57/E32*D32+M57/G32*F32,0) -> 0 | F57: =H57+J57+L57+M57 -> 0 | G57: =IFERROR(F57/G32,0) -> 0 | H57: =E32*I57 -> 0 | I57: =ННСот2000до2200!$E$9/1000 -> 75472.271 | J57: =G32*K57 -> 0 | K57: =ННСот2000до2200!$E$11/1000 -> 36904.487 | L57: =ННСот2000до2200!$E$7/1000*E32 -> 0 | M57: =ННСот2000до2200!$E$13/1000*G32 -> 0
B58: ННС более 2200 | C58: =I58*D33 -> 0 | D58: =K58*F33 -> 0 | E58: =IFERROR(C58+D58+L58/E33*D33+M58/G33*F33,0) -> 0 | F58: =H58+J58+L58+M58 -> 0 | G58: =IFERROR(F58/G33,0) -> 0 | H58: =E33*I58 -> 0 | I58: =ННСболее2200!$E$9/1000 -> 30207.616 | J58: =G33*K58 -> 0 | K58: =ННСболее2200!$E$11/1000 -> 36904.487 | L58: =ННСболее2200!$E$7/1000*E33 -> 0 | M58: =ННСболее2200!$E$13/1000*G33 -> 0
B59: Оценочная | C59: =I59*D34 -> 0 | D59: =K59*F34 -> 0 | E59: =IFERROR(C59+D59+L59/E34*D34+M59/G34*F34,0) -> 0 | F59: =H59+J59+L59+M59 -> 0 | G59: =IFERROR(F59/G34,0) -> 0 | H59: =E34*I59 -> 0 | I59: =Оценочная!$E$9/1000 -> 111580.21 | J59: =G34*K59 -> 0 | K59: =Оценочная!$E$11/1000 -> 36904.487 | L59: =Оценочная!$E$7/1000*E34 -> 0 | M59: =Оценочная!$E$13/1000*G34 -> 0
B60: ННС Юра >800 | C60: =I60*D35 -> 0 | D60: =K60*F35 -> 0 | E60: =IFERROR(C60+D60+L60/E35*D35+M60/G35*F35,0) -> 0 | F60: =H60+J60+L60+M60 -> 0 | G60: =IFERROR(F60/G35,0) -> 0 | H60: =E35*I60 -> 0 | I60: ='ННСЮра>800'!$E$9/1000 -> 0 | J60: =G35*K60 -> 0 | K60: ='ННСЮра>800'!$E$11/1000 -> 0 | L60: ='ННСЮра>800'!$E$7/1000*E35 -> 0 | M60: ='ННСЮра>800'!$E$13/1000*G35 -> 0
B61: ГС с пилотом | C61: =I61*D36 -> 0 | D61: =K61*F36 -> 0 | E61: =IFERROR(C61+D61+L61/E36*D36+M61/G36*F36,0) -> 0 | F61: =H61+J61+L61+M61 -> 0 | G61: =IFERROR(F61/G36,0) -> 0 | H61: =E36*I61 -> 0 | I61: ='ГС пил'!$E$9/1000 -> 70362.507 | J61: =G36*K61 -> 0 | K61: ='ГС пил'!$E$11/1000 -> 36904.487 | L61: ='ГС пил'!$E$7/1000*E36 -> 0 | M61: ='ГС пил'!$E$13/1000*G36 -> 0
B62: ГС без пилота | C62: =I62*D37 -> 353913.98 | D62: =K62*F37 -> 221426.92 | E62: =IFERROR(C62+D62+L62/E37*D37+M62/G37*F37,0) -> 576933.09 | F62: =H62+J62+L62+M62 -> 576933.09 | G62: =IFERROR(F62/G37,0) -> 96155.514 | H62: =E37*I62 -> 353913.98 | I62: ='ГС без пил'!$E$9/1000 -> 58985.663 | J62: =G37*K62 -> 221426.92 | K62: ='ГС без пил'!$E$11/1000 -> 36904.487 | L62: ='ГС без пил'!$E$7/1000*E37 -> 1592.19 | M62: ='ГС без пил'!$E$13/1000*G37 -> 0
B63: ГС с пилотом и МСГРП | C63: =I63*D38 -> 0 | D63: =K63*F38 -> 0 | E63: =IFERROR(C63+D63+L63/E38*D38+M63/G38*F38,0) -> 0 | F63: =H63+J63+L63+M63 -> 0 | G63: =IFERROR(F63/G38,0) -> 0 | H63: =E38*I63 -> 0 | I63: ='ГС пил МСГРП'!$E$9/1000 -> 0 | J63: =G38*K63 -> 0 | K63: ='ГС пил МСГРП'!$E$11/1000 -> 0 | L63: ='ГС пил МСГРП'!$E$7/1000*E38 -> 0 | M63: ='ГС пил МСГРП'!$E$13/1000*G38 -> 0
B64: ГС Юра с пилотом | C64: =I64*D39 -> 0 | D64: =K64*F39 -> 0 | E64: =IFERROR(C64+D64+L64/E39*D39+M64/G39*F39,0) -> 0 | F64: =H64+J64+L64+M64 -> 0 | G64: =IFERROR(F64/G39,0) -> 0 | H64: =E39*I64 -> 0 | I64: ='ГСЮра пил'!$E$9/1000 -> 0 | J64: =G39*K64 -> 0 | K64: ='ГСЮра пил'!$E$11/1000 -> 0 | L64: ='ГСЮра пил'!$E$7/1000*E39 -> 0 | M64: ='ГСЮра пил'!$E$13/1000*G39 -> 0
B65: ГС Юра без пилота | C65: =I65*D40 -> 0 | D65: =K65*F40 -> 0 | E65: =IFERROR(C65+D65+L65/E40*D40+M65/G40*F40,0) -> 0 | F65: =H65+J65+L65+M65 -> 0 | G65: =IFERROR(F65/G40,0) -> 0 | H65: =E40*I65 -> 0 | I65: ='ГСЮра без пил'!$E$9/1000 -> 0 | J65: =G40*K65 -> 0 | K65: ='ГСЮра без пил'!$E$11/1000 -> 0 | L65: ='ГСЮра без пил'!$E$7/1000*E40 -> 0 | M65: ='ГСЮра без пил'!$E$13/1000*G40 -> 0
B66: ГС Юра с пилотом и МСГРП | C66: =I66*D41 -> 0 | D66: =K66*F41 -> 0 | E66: =IFERROR(C66+D66+L66/E41*D41+M66/G41*F41,0) -> 0 | F66: =H66+J66+L66+M66 -> 0 | G66: =IFERROR(F66/G41,0) -> 0 | H66: =E41*I66 -> 0 | I66: ='ГСЮра пил МСГРП'!$E$9/1000 -> 0 | J66: =G41*K66 -> 0 | K66: ='ГСЮра пил МСГРП'!$E$11/1000 -> 0 | L66: ='ГСЮра пил МСГРП'!$E$7/1000*E41 -> 0 | M66: ='ГСЮра пил МСГРП'!$E$13/1000*G41 -> 0
B67: Вод/з | C67: =I67*D42 -> 0 | D67: =K67*F42 -> 0 | E67: =IFERROR(C67+D67+L67/E42*D42+M67/G42*F42,0) -> 0 | F67: =H67+J67+L67+M67 -> 0 | G67: =IFERROR(F67/G42,0) -> 0 | H67: =E42*I67 -> 0 | I67: =ВЗ!$E$9/1000 -> 0 | J67: =G42*K67 -> 0 | K67: =ВЗ!$E$11/1000 -> 0 | L67: =ВЗ!$E$7/1000*E42 -> 0 | M67: =ВЗ!$E$13/1000*G42 -> 0
B68: Посл.скв. | C68: =I68*D43 -> 69765.317 | D68: =K68*F43 -> 36904.487 | E68: =IFERROR(C68+D68+L68/E43*D43+M68/G43*F43,0) -> 113288.35 | F68: =H68+J68+L68+M68 -> 113288.35 | G68: =IFERROR(F68/G43,0) -> 113288.35 | H68: =E43*I68 -> 69765.317 | I68: ='Посл. скв'!$E$9/1000 -> 69765.317 | J68: =G43*K68 -> 36904.487 | K68: ='Посл. скв'!$E$11/1000 -> 36904.487 | L68: ='Посл. скв'!$E$7/1000*E43 -> 6618.548 | M68: ='Посл. скв'!$E$13/1000*G43 -> 0
B70: Среднее по ННС на 1 скв. | C70: =IFERROR((C53+C54+C55+C56+C57+C58+C59+C60+C68)/D45,0) -> 0 | D70: =IFERROR((D53+D54+D55+D56+D57+D58+D59+D60+D68)/E45,0) -> 0 | E70: =IFERROR((E53+E54+E55+E56+E57+E58+E59+E60+E68)/F45,0) -> 0 | F70: =IFERROR((F53+F54+F55+F56+F57+F58+F59+F60+F68)/E45,0) -> 0 | G70: =IFERROR((G53+G54+G55+G56+G57+G58+G59+G60+G68)/G45,0) -> 0 | H70: =IFERROR((H53+H54+H55+H56+H57+H58+H59+H60+H68)/G45,0) -> 0 | I70: =I52 -> 61680.576 | J70: =IFERROR((J53+J54+J55+J56+J57+J58+J59+J60+J68)/G45,0) -> 0 | K70: =K52 -> 36904.487 | L70: =IFERROR((L53+L54+L55+L56+L57+L58+L59+L60+L68)/G45,0) -> 0 | M70: =IFERROR((M53+M54+M55+M56+M57+M58+M59+M60+M68)/N45,0) -> 0
B71: Среднее по ГС на 1 скв. | C71: =IFERROR((C61+C62+C63+C64+C65+C66)/D46,0) -> 44239.247 | D71: =IFERROR((D61+D62+D63+D64+D65+D66)/E46,0) -> 27678.365 | E71: =IFERROR((E61+E62+E63+E64+E65+E66)/F46,0) -> 72116.636 | F71: =IFERROR((F61+F62+F63+F64+F65+F66)/G46,0) -> 72116.636 | H71: =IFERROR((H61+H62+H63+H64+H65+H66)/I46,0) -> 80.894623 | J71: =IFERROR((J61+J62+J63+J64+J65+J66)/K46,0) -> 6560.7976 | L71: =IFERROR((L61+L62+L63+L64+L65+L66)/M46,0) -> 83.799474 | M71: =IFERROR((M61+M62+M63+M64+M65+M66)/N46,0) -> 0
B73: ОПИСАНИЕ И ОСОБЕННОСТИ ПРОЕКТА
B85: Примечания по заполнению:
B86: Создана библиотека видов работ, ед. измерения и стоимости за ед. изм. | F86: в листе "первая скважина", данные из которого тиражируются во все остальные листы с типами скважин.
B87: При заполнени стоимости в поле "статья затрат" нужно указывать по аналогичной ст-ти какого из подрядчиков взята цена для расчета.
B88: Основные места для заполнения выделены желтым или белым цветом
B89: Автоматические расчеты и места заполняемые из других, первоначальных источников выделены серым цветом | I89: или зеленым | K89: или
B90: В случае изменения кол-ва строк, необходимо производить замену во всех листах типовых форм скважин и в листе "ТЭП".

Sheet ТЭП
A2: ПОДРОБНАЯ СМЕТНАЯ СТОИМОСТЬ СКВАЖИНЫ
C4: Месторождение/ куст: | D4: ='Титул '!G5 -> куст №21б Приобского месторождения | E4: ВСЕГО СТ-ТЬ
C5: Подрядчик по бурению: | D5: ='Титул '!C11 -> не определен | E5: =E7+E9+E11+E13 -> 8.2260536e+08 | F5: =E5/1000-'Титул '!F52 -> 0
C6: Тип буровой установки: | D6: ='Титул '!C12 -> БУ-3000 ЭУК | E6: Всего ВМР
C7: Тип скважины: | D7: Наклонно-направленная | E7: =AN41 -> 33924862
C8: Проходка всего (м): | E8: Всего Бурение
C9: Наличие СВП: | D9: ='Титул '!C13 -> да | E9: =AN190 -> 4.9344461e+08
C10: Наличие АИЭС: | D10: ='Титул '!C14 -> нет | E10: Всего Освоение
C11: Наличие автономности: | D11: ='Титул '!C15 -> нет | E11: =AN206 -> 2.9523589e+08 | AN11: (руб. без НДС)
C12: Кол-во обсадных колонн (включая направл.): | E12: Обор-ие устья | F12: Вид скв. | G12: ='Титул '!B28 -> Перв.скв. (тип скв) | I12: ='Титул '!B29 -> ННС до 1300 | K12: ='Титул '!B30 -> ННС от 1300 до 1500 | M12: ='Титул '!B31 -> ННС от 1500 до 2000 | O12: ='Титул '!B32 -> ННС от 2000 до 2200 | Q12: ='Титул '!B33 -> ННС более 2200 | S12: ='Титул '!B34 -> Оценочная | U12: ='Титул '!B35 -> ННС Юра >800 | W12: ='Титул '!B36 -> ГС с пилотом | Y12: ='Титул '!B37 -> ГС без пилота | AA12: ='Титул '!B38 -> ГС с пилотом и МСГРП | AC12: ='Титул '!B39 -> ГС Юра с пилотом | AE12: ='Титул '!B40 -> ГС Юра без пилота | AG12: ='Титул '!B41 -> ГС Юра с пилотом и МСГРП | AI12: ='Титул '!B42 -> Вод/з | AK12: ='Титул '!B43 -> Посл.скв. | AM12: ИТОГО
C13: Прочие существенные условия: | E13: =AN212 -> 0 | F13: Кол-во скв. | G13: ='Титул '!E28 -> 1 | I13: ='Титул '!E29 -> 0 | K13: ='Титул '!E30 -> 0 | M13: ='Титул '!E31 -> 0 | O13: ='Титул '!E32 -> 0 | Q13: ='Титул '!E33 -> 0 | S13: ='Титул '!E34 -> 0 | U13: ='Титул '!E35 -> 0 | W13: ='Титул '!E36 -> 0 | Y13: 6 | AA13: ='Титул '!E38 -> 0 | AC13: ='Титул '!E39 -> 0 | AE13: ='Титул '!E40 -> 0 | AG13: ='Титул '!E41 -> 0 | AI13: ='Титул '!E42 -> 0 | AK13: ='Титул '!E43 -> 1 | AM13: =SUM(G13:AL13) -> 8
A15: ОПИСАНИЕ РАБОТ И УСЛУГ
A16: КОД | B16: добавочный код | C16: СТАТЬЯ ЗАТРАТ | D16: ОПИСАНИЕ | E16: Подрядчик | F16: Единица измерения | G16: Кол-во | H16: Ст-ть работ | I16: Кол-во | J16: Ст-ть работ | K16: Кол-во | L16: Ст-ть работ | M16: Кол-во | N16: Ст-ть работ | O16: Кол-во | P16: Ст-ть работ | Q16: Кол-во | R16: Ст-ть работ | S16: Кол-во | T16: Ст-ть работ | U16: Кол-во | V16: Ст-ть работ | W16: Кол-во | X16: Ст-ть работ | Y16: Кол-во | Z16: Ст-ть работ | AA16: Кол-во | AB16: Ст-ть работ | AC16: Кол-во | AD16: Ст-ть работ | AE16: Кол-во | AF16: Ст-ть работ | AG16: Кол-во | AH16: Ст-ть работ | AI16: Кол-во | AJ16: Ст-ть работ | AK16: Кол-во | AL16: Ст-ть работ | AM16: Кол-во | AN16: Ст-ть работ | AS16: Ст-ть работ
AN17: 0 | AS17: 0
C18: 1. ЭТАП ВМР
C19: ='Перв. скв '!C19 -> не определен | D19: Описание работ/услуг | AN19: 0 | AS19: 0
D20: ='Перв. скв '!D20 -> Монтаж | E20: ='Перв. скв '!E20 -> не определен | F20: ='Перв. скв '!F20 -> опер. | G20: ='Перв. скв '!$V20*G$13 -> 1 | H20: ='Перв. скв '!$W20*G$13 -> 9401938 | I20: =ННСдо1300!$V20*I$13 -> 0 | J20: =ННСдо1300!$W20*I$13 -> 0 | K20: =ННСот1300до1500!$V20*K$13 -> 0 | L20: =ННСот1300до1500!$W20*K$13 -> 0 | M20: =ННСот1500до2000!$V20*M$13 -> 0 | N20: =ННСот1500до2000!$W20*M$13 -> 0 | O20: =ННСот2000до2200!$V20*O$13 -> 0 | P20: =ННСот2000до2200!$W20*O$13 -> 0 | Q20: =ННСболее2200!$V20*Q$13 -> 0 | R20: =ННСболее2200!$W20*Q$13 -> 0 | S20: =Оценочная!$V20*S$13 -> 0 | T20: =Оценочная!$W20*S$13 -> 0 | U20: ='ННСЮра>800'!$V20*U$13 -> 0 | V20: ='ННСЮра>800'!$W20*U$13 -> 0 | W20: ='ГС пил'!V20*$W$13 -> 0 | X20: ='ГС пил'!W20*$W$13 -> 0 | Y20: ='ГС без пил'!$V20*Y$13 -> 0 | Z20: ='ГС без пил'!$W20*Y$13 -> 0 | AA20: ='ГС пил МСГРП'!$V20*AA$13 -> 0 | AB20: ='ГС пил МСГРП'!$W20*AA$13 -> 0 | AC20: ='ГСЮра пил'!$V20*AC$13 -> 0 | AD20: ='ГСЮра пил'!$W20*AC$13 -> 0 | AE20: ='ГСЮра без пил'!$V20*AE$13 -> 0 | AF20: ='ГСЮра без пил'!$W20*AE$13 -> 0 | AG20: ='ГСЮра пил МСГРП'!$V20*AG$13 -> 0 | AH20: ='ГСЮра пил МСГРП'!$W20*AG$13 -> 0 | AI20: =ВЗ!$V20*AI$13 -> 0 | AJ20: =ВЗ!$W20*AI$13 -> 0 | AK20: ='Посл. скв'!$V20*AK$13 -> 0 | AL20: ='Посл. скв'!$W20*AK$13 -> 0 | AM20: =AK20+AI20+AG20+AE20+AC20+AA20+Y20+W20++U20+S20+Q20+M20+O20+K20+I20+G20 -> 1 | AN20: =AL20+AJ20+AH20+AF20+AD20+AB20+Z20+X20++V20+T20+R20+N20+P20+L20+J20+H20 -> 9401938 | AO20: =('[8]Куст №40А'!AD1998)*1000 -> 0 | AP20: =AO20-AN20 -> -9401938 | AR20: =AS20-AN20 -> 0 | AS20: 9401938
D21: ='Перв. скв '!D21 -> Демонтаж | E21: ='Перв. скв '!E21 -> не определен | F21: ='Перв. скв '!F21 -> опер. | G21: ='Перв. скв '!$V21*G$13 -> 0 | H21: ='Перв. скв '!$W21*G$13 -> 0 | I21: =ННСдо1300!$V21*I$13 -> 0 | J21: =ННСдо1300!$W21*I$13 -> 0 | K21: =ННСот1300до1500!$V21*K$13 -> 0 | L21: =ННСот1300до1500!$W21*K$13 -> 0 | M21: =ННСот1500до2000!$V21*M$13 -> 0 | N21: =ННСот1500до2000!$W21*M$13 -> 0 | O21: =ННСот2000до2200!$V21*O$13 -> 0 | P21: =ННСот2000до2200!$W21*O$13 -> 0 | Q21: =ННСболее2200!$V21*Q$13 -> 0 | R21: =ННСболее2200!$W21*Q$13 -> 0 | S21: =Оценочная!$V21*S$13 -> 0 | T21: =Оценочная!$W21*S$13 -> 0 | U21: ='ННСЮра>800'!$V21*U$13 -> 0 | V21: ='ННСЮра>800'!$W21*U$13 -> 0 | W21: ='ГС пил'!V21*$W$13 -> 0 | X21: ='ГС пил'!W21*$W$13 -> 0 | Y21: ='ГС без пил'!$V21*Y$13 -> 0 | Z21: ='ГС без пил'!$W21*Y$13 -> 0 | AA21: ='ГС пил МСГРП'!$V21*AA$13 -> 0 | AB21: ='ГС пил МСГРП'!$W21*AA$13 -> 0 | AC21: ='ГСЮра пил'!$V21*AC$13 -> 0 | AD21: ='ГСЮра пил'!$W21*AC$13 -> 0 | AE21: ='ГСЮра без пил'!$V21*AE$13 -> 0 | AF21: ='ГСЮра без пил'!$W21*AE$13 -> 0 | AG21: ='ГСЮра пил МСГРП'!$V21*AG$13 -> 0 | AH21: ='ГСЮра пил МСГРП'!$W21*AG$13 -> 0 | AI21: =ВЗ!$V21*AI$13 -> 0 | AJ21: =ВЗ!$W21*AI$13 -> 0 | AK21: ='Посл. скв'!$V21*AK$13 -> 1 | AL21: ='Посл. скв'!$W21*AK$13 -> 2344149 | AM21: =AK21+AI21+AG21+AE21+AC21+AA21+Y21+W21++U21+S21+Q21+M21+O21+K21+I21+G21 -> 1 | AN21: =AL21+AJ21+AH21+AF21+AD21+AB21+Z21+X21++V21+T21+R21+N21+P21+L21+J21+H21 -> 2344149 | AO21: =('[8]Куст №40А'!AD1999)*1000 -> 0 | AP21: =AO21-AN21 -> -2344149 | AR21: =AS21-AN21 -> 0 | AS21: 2344149
D22: ='Перв. скв '!D22 -> Эксплуатация АВЭС | E22: ='Перв. скв '!E22 -> не определен | F22: ='Перв. скв '!F22 -> опер. | G22: ='Перв. скв '!$V22*G$13 -> 0 | H22: ='Перв. скв '!$W22*G$13 -> 0 | I22: =ННСдо1300!$V22*I$13 -> 0 | J22: =ННСдо1300!$W22*I$13 -> 0 | K22: =ННСот1300до1500!$V22*K$13 -> 0 | L22: =ННСот1300до1500!$W22*K$13 -> 0 | M22: =ННСот1500до2000!$V22*M$13 -> 0 | N22: =ННСот1500до2000!$W22*M$13 -> 0 | O22: =ННСот2000до2200!$V22*O$13 -> 0 | P22: =ННСот2000до2200!$W22*O$13 -> 0 | Q22: =ННСболее2200!$V22*Q$13 -> 0 | R22: =ННСболее2200!$W22*Q$13 -> 0 | S22: =Оценочная!$V22*S$13 -> 0 | T22: =Оценочная!$W22*S$13 -> 0 | U22: ='ННСЮра>800'!$V22*U$13 -> 0 | V22: ='ННСЮра>800'!$W22*U$13 -> 0 | W22: ='ГС пил'!V22*$W$13 -> 0 | X22: ='ГС пил'!W22*$W$13 -> 0 | Y22: ='ГС без пил'!$V22*Y$13 -> 0 | Z22: ='ГС без пил'!$W22*Y$13 -> 0 | AA22: ='ГС пил МСГРП'!$V22*AA$13 -> 0 | AB22: ='ГС пил МСГРП'!$W22*AA$13 -> 0 | AC22: ='ГСЮра пил'!$V22*AC$13 -> 0 | AD22: ='ГСЮра пил'!$W22*AC$13 -> 0 | AE22: ='ГСЮра без пил'!$V22*AE$13 -> 0 | AF22: ='ГСЮра без пил'!$W22*AE$13 -> 0 | AG22: ='ГСЮра пил МСГРП'!$V22*AG$13 -> 0 | AH22: ='ГСЮра пил МСГРП'!$W22*AG$13 -> 0 | AI22: =ВЗ!$V22*AI$13 -> 0 | AJ22: =ВЗ!$W22*AI$13 -> 0 | AK22: ='Посл. скв'!$V22*AK$13 -> 0 | AL22: ='Посл. скв'!$W22*AK$13 -> 0 | AM22: =AK22+AI22+AG22+AE22+AC22+AA22+Y22+W22++U22+S22+Q22+M22+O22+K22+I22+G22 -> 0 | AN22: =AL22+AJ22+AH22+AF22+AD22+AB22+Z22+X22++V22+T22+R22+N22+P22+L22+J22+H22 -> 0 | AO22: =('[8]Куст №40А'!AD2000)*1000 -> 0 | AP22: =AO22-AN22 -> 0 | AR22: =AS22-AN22 -> 0 | AS22: 0
D23: ='Перв. скв '!D23 -> Передислокация БУ в пределах м-я | E23: ='Перв. скв '!E23 -> не определен | F23: ='Перв. скв '!F23 -> опер. | G23: ='Перв. скв '!$V23*G$13 -> 0 | H23: ='Перв. скв '!$W23*G$13 -> 0 | I23: =ННСдо1300!$V23*I$13 -> 0 | J23: =ННСдо1300!$W23*I$13 -> 0 | K23: =ННСот1300до1500!$V23*K$13 -> 0 | L23: =ННСот1300до1500!$W23*K$13 -> 0 | M23: =ННСот1500до2000!$V23*M$13 -> 0 | N23: =ННСот1500до2000!$W23*M$13 -> 0 | O23: =ННСот2000до2200!$V23*O$13 -> 0 | P23: =ННСот2000до2200!$W23*O$13 -> 0 | Q23: =ННСболее2200!$V23*Q$13 -> 0 | R23: =ННСболее2200!$W23*Q$13 -> 0 | S23: =Оценочная!$V23*S$13 -> 0 | T23: =Оценочная!$W23*S$13 -> 0 | U23: ='ННСЮра>800'!$V23*U$13 -> 0 | V23: ='ННСЮра>800'!$W23*U$13 -> 0 | W23: ='ГС пил'!V23*$W$13 -> 0 | X23: ='ГС пил'!W23*$W$13 -> 0 | Y23: ='ГС без пил'!$V23*Y$13 -> 0 | Z23: ='ГС без пил'!$W23*Y$13 -> 0 | AA23: ='ГС пил МСГРП'!$V23*AA$13 -> 0 | AB23: ='ГС пил МСГРП'!$W23*AA$13 -> 0 | AC23: ='ГСЮра пил'!$V23*AC$13 -> 0 | AD23: ='ГСЮра пил'!$W23*AC$13 -> 0 | AE23: ='ГСЮра без пил'!$V23*AE$13 -> 0 | AF23: ='ГСЮра без пил'!$W23*AE$13 -> 0 | AG23: ='ГСЮра пил МСГРП'!$V23*AG$13 -> 0 | AH23: ='ГСЮра пил МСГРП'!$W23*AG$13 -> 0 | AI23: =ВЗ!$V23*AI$13 -> 0 | AJ23: =ВЗ!$W23*AI$13 -> 0 | AK23: ='Посл. скв'!$V23*AK$13 -> 0 | AL23: ='Посл. скв'!$W23*AK$13 -> 0 | AM23: =AK23+AI23+AG23+AE23+AC23+AA23+Y23+W23++U23+S23+Q23+M23+O23+K23+I23+G23 -> 0 | AN23: =AL23+AJ23+AH23+AF23+AD23+AB23+Z23+X23++V23+T23+R23+N23+P23+L23+J23+H23 -> 0 | AO23: =('[8]Куст №40А'!AD2001)*1000 -> 0 | AP23: =AO23-AN23 -> 0 | AR23: =AS23-AN23 -> 693236 | AS23: 693236
D24: ='Перв. скв '!D24 -> Передислокация БУ 250-500 км. | E24: ='Перв. скв '!E24 -> не определен | F24: ='Перв. скв '!F24 -> опер. | G24: ='Перв. скв '!$V24*G$13 -> 1 | H24: ='Перв. скв '!$W24*G$13 -> 9837322 | I24: =ННСдо1300!$V24*I$13 -> 0 | J24: =ННСдо1300!$W24*I$13 -> 0 | K24: =ННСот1300до1500!$V24*K$13 -> 0 | L24: =ННСот1300до1500!$W24*K$13 -> 0 | M24: =ННСот1500до2000!$V24*M$13 -> 0 | N24: =ННСот1500до2000!$W24*M$13 -> 0 | O24: =ННСот2000до2200!$V24*O$13 -> 0 | P24: =ННСот2000до2200!$W24*O$13 -> 0 | Q24: =ННСболее2200!$V24*Q$13 -> 0 | R24: =ННСболее2200!$W24*Q$13 -> 0 | S24: =Оценочная!$V24*S$13 -> 0 | T24: =Оценочная!$W24*S$13 -> 0 | U24: ='ННСЮра>800'!$V24*U$13 -> 0 | V24: ='ННСЮра>800'!$W24*U$13 -> 0 | W24: ='ГС пил'!V24*$W$13 -> 0 | X24: ='ГС пил'!W24*$W$13 -> 0 | Y24: ='ГС без пил'!$V24*Y$13 -> 0 | Z24: ='ГС без пил'!$W24*Y$13 -> 0 | AA24: ='ГС пил МСГРП'!$V24*AA$13 -> 0 | AB24: ='ГС пил МСГРП'!$W24*AA$13 -> 0 | AC24: ='ГСЮра пил'!$V24*AC$13 -> 0 | AD24: ='ГСЮра пил'!$W24*AC$13 -> 0 | AE24: ='ГСЮра без пил'!$V24*AE$13 -> 0 | AF24: ='ГСЮра без пил'!$W24*AE$13 -> 0 | AG24: ='ГСЮра пил МСГРП'!$V24*AG$13 -> 0 | AH24: ='ГСЮра пил МСГРП'!$W24*AG$13 -> 0 | AI24: =ВЗ!$V24*AI$13 -> 0 | AJ24: =ВЗ!$W24*AI$13 -> 0 | AK24: ='Посл. скв'!$V24*AK$13 -> 0 | AL24: ='Посл. скв'!$W24*AK$13 -> 0 | AM24: =AK24+AI24+AG24+AE24+AC24+AA24+Y24+W24++U24+S24+Q24+M24+O24+K24+I24+G24 -> 1 | AN24: =AL24+AJ24+AH24+AF24+AD24+AB24+Z24+X24++V24+T24+R24+N24+P24+L24+J24+H24 -> 9837322 | AO24: =('[8]Куст №40А'!AD2002)*1000 -> 0 | AP24: =AO24-AN24 -> -9837322 | AR24: =AS24-AN24 -> -9837322 | AS24: 0
D25: ='Перв. скв '!D25 -> Передислокация бр. бур в пределах м-я | E25: ='Перв. скв '!E25 -> не определен | F25: ='Перв. скв '!F25 -> опер. | G25: ='Перв. скв '!$V25*G$13 -> 0 | H25: ='Перв. скв '!$W25*G$13 -> 0 | I25: =ННСдо1300!$V25*I$13 -> 0 | J25: =ННСдо1300!$W25*I$13 -> 0 | K25: =ННСот1300до1500!$V25*K$13 -> 0 | L25: =ННСот1300до1500!$W25*K$13 -> 0 | M25: =ННСот1500до2000!$V25*M$13 -> 0 | N25: =ННСот1500до2000!$W25*M$13 -> 0 | O25: =ННСот2000до2200!$V25*O$13 -> 0 | P25: =ННСот2000до2200!$W25*O$13 -> 0 | Q25: =ННСболее2200!$V25*Q$13 -> 0 | R25: =ННСболее2200!$W25*Q$13 -> 0 | S25: =Оценочная!$V25*S$13 -> 0 | T25: =Оценочная!$W25*S$13 -> 0 | U25: ='ННСЮра>800'!$V25*U$13 -> 0 | V25: ='ННСЮра>800'!$W25*U$13 -> 0 | W25: ='ГС пил'!V25*$W$13 -> 0 | X25: ='ГС пил'!W25*$W$13 -> 0 | Y25: ='ГС без пил'!$V25*Y$13 -> 0 | Z25: ='ГС без пил'!$W25*Y$13 -> 0 | AA25: ='ГС пил МСГРП'!$V25*AA$13 -> 0 | AB25: ='ГС пил МСГРП'!$W25*AA$13 -> 0 | AC25: ='ГСЮра пил'!$V25*AC$13 -> 0 | AD25: ='ГСЮра пил'!$W25*AC$13 -> 0 | AE25: ='ГСЮра без пил'!$V25*AE$13 -> 0 | AF25: ='ГСЮра без пил'!$W25*AE$13 -> 0 | AG25: ='ГСЮра пил МСГРП'!$V25*AG$13 -> 0 | AH25: ='ГСЮра пил МСГРП'!$W25*AG$13 -> 0 | AI25: =ВЗ!$V25*AI$13 -> 0 | AJ25: =ВЗ!$W25*AI$13 -> 0 | AK25: ='Посл. скв'!$V25*AK$13 -> 0 | AL25: ='Посл. скв'!$W25*AK$13 -> 0 | AM25: =AK25+AI25+AG25+AE25+AC25+AA25+Y25+W25++U25+S25+Q25+M25+O25+K25+I25+G25 -> 0 | AN25: =AL25+AJ25+AH25+AF25+AD25+AB25+Z25+X25++V25+T25+R25+N25+P25+L25+J25+H25 -> 0 | AO25: =('[8]Куст №40А'!AD2003)*1000 -> 0 | AP25: =AO25-AN25 -> 0 | AR25: =AS25-AN25 -> 130867 | AS25: 130867
D26: ='Перв. скв '!D26 -> Передислокация бр. бур 250-500 км. | E26: ='Перв. скв '!E26 -> не определен | F26: ='Перв. скв '!F26 -> опер. | G26: ='Перв. скв '!$V26*G$13 -> 1 | H26: ='Перв. скв '!$W26*G$13 -> 1788526 | I26: =ННСдо1300!$V26*I$13 -> 0 | J26: =ННСдо1300!$W26*I$13 -> 0 | K26: =ННСот1300до1500!$V26*K$13 -> 0 | L26: =ННСот1300до1500!$W26*K$13 -> 0 | M26: =ННСот1500до2000!$V26*M$13 -> 0 | N26: =ННСот1500до2000!$W26*M$13 -> 0 | O26: =ННСот2000до2200!$V26*O$13 -> 0 | P26: =ННСот2000до2200!$W26*O$13 -> 0 | Q26: =ННСболее2200!$V26*Q$13 -> 0 | R26: =ННСболее2200!$W26*Q$13 -> 0 | S26: =Оценочная!$V26*S$13 -> 0 | T26: =Оценочная!$W26*S$13 -> 0 | U26: ='ННСЮра>800'!$V26*U$13 -> 0 | V26: ='ННСЮра>800'!$W26*U$13 -> 0 | W26: ='ГС пил'!V26*$W$13 -> 0 | X26: ='ГС пил'!W26*$W$13 -> 0 | Y26: ='ГС без пил'!$V26*Y$13 -> 0 | Z26: ='ГС без пил'!$W26*Y$13 -> 0 | AA26: ='ГС пил МСГРП'!$V26*AA$13 -> 0 | AB26: ='ГС пил МСГРП'!$W26*AA$13 -> 0 | AC26: ='ГСЮра пил'!$V26*AC$13 -> 0 | AD26: ='ГСЮра пил'!$W26*AC$13 -> 0 | AE26: ='ГСЮра без пил'!$V26*AE$13 -> 0 | AF26: ='ГСЮра без пил'!$W26*AE$13 -> 0 | AG26: ='ГСЮра пил МСГРП'!$V26*AG$13 -> 0 | AH26: ='ГСЮра пил МСГРП'!$W26*AG$13 -> 0 | AI26: =ВЗ!$V26*AI$13 -> 0 | AJ26: =ВЗ!$W26*AI$13 -> 0 | AK26: ='Посл. скв'!$V26*AK$13 -> 0 | AL26: ='Посл. скв'!$W26*AK$13 -> 0 | AM26: =AK26+AI26+AG26+AE26+AC26+AA26+Y26+W26++U26+S26+Q26+M26+O26+K26+I26+G26 -> 1 | AN26: =AL26+AJ26+AH26+AF26+AD26+AB26+Z26+X26++V26+T26+R26+N26+P26+L26+J26+H26 -> 1788526 | AO26: =('[8]Куст №40А'!AD2004)*1000 -> 0 | AP26: =AO26-AN26 -> -1788526 | AR26: =AS26-AN26 -> -1788526 | AS26: 0
D27: ='Перв. скв '!D27 -> Передислокация бригады ВМР в пределах м-я | E27: ='Перв. скв '!E27 -> не определен | F27: ='Перв. скв '!F27 -> опер. | G27: ='Перв. скв '!$V27*G$13 -> 0 | H27: ='Перв. скв '!$W27*G$13 -> 0 | I27: =ННСдо1300!$V27*I$13 -> 0 | J27: =ННСдо1300!$W27*I$13 -> 0 | K27: =ННСот1300до1500!$V27*K$13 -> 0 | L27: =ННСот1300до1500!$W27*K$13 -> 0 | M27: =ННСот1500до2000!$V27*M$13 -> 0 | N27: =ННСот1500до2000!$W27*M$13 -> 0 | O27: =ННСот2000до2200!$V27*O$13 -> 0 | P27: =ННСот2000до2200!$W27*O$13 -> 0 | Q27: =ННСболее2200!$V27*Q$13 -> 0 | R27: =ННСболее2200!$W27*Q$13 -> 0 | S27: =Оценочная!$V27*S$13 -> 0 | T27: =Оценочная!$W27*S$13 -> 0 | U27: ='ННСЮра>800'!$V27*U$13 -> 0 | V27: ='ННСЮра>800'!$W27*U$13 -> 0 | W27: ='ГС пил'!V27*$W$13 -> 0 | X27: ='ГС пил'!W27*$W$13 -> 0 | Y27: ='ГС без пил'!$V27*Y$13 -> 0 | Z27: ='ГС без пил'!$W27*Y$13 -> 0 | AA27: ='ГС пил МСГРП'!$V27*AA$13 -> 0 | AB27: ='ГС пил МСГРП'!$W27*AA$13 -> 0 | AC27: ='ГСЮра пил'!$V27*AC$13 -> 0 | AD27: ='ГСЮра пил'!$W27*AC$13 -> 0 | AE27: ='ГСЮра без пил'!$V27*AE$13 -> 0 | AF27: ='ГСЮра без пил'!$W27*AE$13 -> 0 | AG27: ='ГСЮра пил МСГРП'!$V27*AG$13 -> 0 | AH27: ='ГСЮра пил МСГРП'!$W27*AG$13 -> 0 | AI27: =ВЗ!$V27*AI$13 -> 0 | AJ27: =ВЗ!$W27*AI$13 -> 0 | AK27: ='Посл. скв'!$V27*AK$13 -> 0 | AL27: ='Посл. скв'!$W27*AK$13 -> 0 | AM27: =AK27+AI27+AG27+AE27+AC27+AA27+Y27+W27++U27+S27+Q27+M27+O27+K27+I27+G27 -> 0 | AN27: =AL27+AJ27+AH27+AF27+AD27+AB27+Z27+X27++V27+T27+R27+N27+P27+L27+J27+H27 -> 0 | AO27: =('[8]Куст №40А'!AD2005)*1000 -> 0 | AP27: =AO27-AN27 -> 0 | AR27: =AS27-AN27 -> 130867 | AS27: 130867
D28: ='Перв. скв '!D28 -> Передислокация бригады ВМР 250-500 км. | E28: ='Перв. скв '!E28 -> не определен | F28: ='Перв. скв '!F28 -> опер. | G28: ='Перв. скв '!$V28*G$13 -> 2 | H28: ='Перв. скв '!$W28*G$13 -> 3577052 | I28: =ННСдо1300!$V28*I$13 -> 0 | J28: =ННСдо1300!$W28*I$13 -> 0 | K28: =ННСот1300до1500!$V28*K$13 -> 0 | L28: =ННСот1300до1500!$W28*K$13 -> 0 | M28: =ННСот1500до2000!$V28*M$13 -> 0 | N28: =ННСот1500до2000!$W28*M$13 -> 0 | O28: =ННСот2000до2200!$V28*O$13 -> 0 | P28: =ННСот2000до2200!$W28*O$13 -> 0 | Q28: =ННСболее2200!$V28*Q$13 -> 0 | R28: =ННСболее2200!$W28*Q$13 -> 0 | S28: =Оценочная!$V28*S$13 -> 0 | T28: =Оценочная!$W28*S$13 -> 0 | U28: ='ННСЮра>800'!$V28*U$13 -> 0 | V28: ='ННСЮра>800'!$W28*U$13 -> 0 | W28: ='ГС пил'!V28*$W$13 -> 0 | X28: ='ГС пил'!W28*$W$13 -> 0 | Y28: ='ГС без пил'!$V28*Y$13 -> 0 | Z28: ='ГС без пил'!$W28*Y$13 -> 0 | AA28: ='ГС пил МСГРП'!$V28*AA$13 -> 0 | AB28: ='ГС пил МСГРП'!$W28*AA$13 -> 0 | AC28: ='ГСЮра пил'!$V28*AC$13 -> 0 | AD28: ='ГСЮра пил'!$W28*AC$13 -> 0 | AE28: ='ГСЮра без пил'!$V28*AE$13 -> 0 | AF28: ='ГСЮра без пил'!$W28*AE$13 -> 0 | AG28: ='ГСЮра пил МСГРП'!$V28*AG$13 -> 0 | AH28: ='ГСЮра пил МСГРП'!$W28*AG$13 -> 0 | AI28: =ВЗ!$V28*AI$13 -> 0 | AJ28: =ВЗ!$W28*AI$13 -> 0 | AK28: ='Посл. скв'!$V28*AK$13 -> 2 | AL28: ='Посл. скв'!$W28*AK$13 -> 3577052 | AM28: =AK28+AI28+AG28+AE28+AC28+AA28+Y28+W28++U28+S28+Q28+M28+O28+K28+I28+G28 -> 4 | AN28: =AL28+AJ28+AH28+AF28+AD28+AB28+Z28+X28++V28+T28+R28+N28+P28+L28+J28+H28 -> 7154104 | AO28: =('[8]Куст №40А'!AD2006)*1000 -> 0 | AP28: =AO28-AN28 -> -7154104 | AR28: =AS28-AN28 -> -7154104 | AS28: 0
D29: ='Перв. скв '!D29 -> Передвижка 5 м. | E29: ='Перв. скв '!E29 -> не определен | F29: ='Перв. скв '!F29 -> опер. | G29: ='Перв. скв '!$V29*G$13 -> 0 | H29: ='Перв. скв '!$W29*G$13 -> 0 | I29: =ННСдо1300!$V29*I$13 -> 0 | J29: =ННСдо1300!$W29*I$13 -> 0 | K29: =ННСот1300до1500!$V29*K$13 -> 0 | L29: =ННСот1300до1500!$W29*K$13 -> 0 | M29: =ННСот1500до2000!$V29*M$13 -> 0 | N29: =ННСот1500до2000!$W29*M$13 -> 0 | O29: =ННСот2000до2200!$V29*O$13 -> 0 | P29: =ННСот2000до2200!$W29*O$13 -> 0 | Q29: =ННСболее2200!$V29*Q$13 -> 0 | R29: =ННСболее2200!$W29*Q$13 -> 0 | S29: =Оценочная!$V29*S$13 -> 0 | T29: =Оценочная!$W29*S$13 -> 0 | U29: ='ННСЮра>800'!$V29*U$13 -> 0 | V29: ='ННСЮра>800'!$W29*U$13 -> 0 | W29: ='ГС пил'!V29*$W$13 -> 0 | X29: ='ГС пил'!W29*$W$13 -> 0 | Y29: ='ГС без пил'!$V29*Y$13 -> 0 | Z29: ='ГС без пил'!$W29*Y$13 -> 0 | AA29: ='ГС пил МСГРП'!$V29*AA$13 -> 0 | AB29: ='ГС пил МСГРП'!$W29*AA$13 -> 0 | AC29: ='ГСЮра пил'!$V29*AC$13 -> 0 | AD29: ='ГСЮра пил'!$W29*AC$13 -> 0 | AE29: ='ГСЮра без пил'!$V29*AE$13 -> 0 | AF29: ='ГСЮра без пил'!$W29*AE$13 -> 0 | AG29: ='ГСЮра пил МСГРП'!$V29*AG$13 -> 0 | AH29: ='ГСЮра пил МСГРП'!$W29*AG$13 -> 0 | AI29: =ВЗ!$V29*AI$13 -> 0 | AJ29: =ВЗ!$W29*AI$13 -> 0 | AK29: ='Посл. скв'!$V29*AK$13 -> 0 | AL29: ='Посл. скв'!$W29*AK$13 -> 0 | AM29: =AK29+AI29+AG29+AE29+AC29+AA29+Y29+W29++U29+S29+Q29+M29+O29+K29+I29+G29 -> 0 | AN29: =AL29+AJ29+AH29+AF29+AD29+AB29+Z29+X29++V29+T29+R29+N29+P29+L29+J29+H29 -> 0 | AO29: =('[8]Куст №40А'!AD2007)*1000 -> 0 | AP29: =AO29-AN29 -> 0 | AR29: =AS29-AN29 -> 0 | AS29: 0
D30: ='Перв. скв '!D30 -> Передвижка 9 м. | E30: ='Перв. скв '!E30 -> не определен | F30: ='Перв. скв '!F30 -> опер. | G30: ='Перв. скв '!$V30*G$13 -> 0 | H30: ='Перв. скв '!$W30*G$13 -> 0 | I30: =ННСдо1300!$V30*I$13 -> 0 | J30: =ННСдо1300!$W30*I$13 -> 0 | K30: =ННСот1300до1500!$V30*K$13 -> 0 | L30: =ННСот1300до1500!$W30*K$13 -> 0 | M30: =ННСот1500до2000!$V30*M$13 -> 0 | N30: =ННСот1500до2000!$W30*M$13 -> 0 | O30: =ННСот2000до2200!$V30*O$13 -> 0 | P30: =ННСот2000до2200!$W30*O$13 -> 0 | Q30: =ННСболее2200!$V30*Q$13 -> 0 | R30: =ННСболее2200!$W30*Q$13 -> 0 | S30: =Оценочная!$V30*S$13 -> 0 | T30: =Оценочная!$W30*S$13 -> 0 | U30: ='ННСЮра>800'!$V30*U$13 -> 0 | V30: ='ННСЮра>800'!$W30*U$13 -> 0 | W30: ='ГС пил'!V30*$W$13 -> 0 | X30: ='ГС пил'!W30*$W$13 -> 0 | Y30: ='ГС без пил'!$V30*Y$13 -> 6 | Z30: ='ГС без пил'!$W30*Y$13 -> 1592190 | AA30: ='ГС пил МСГРП'!$V30*AA$13 -> 0 | AB30: ='ГС пил МСГРП'!$W30*AA$13 -> 0 | AC30: ='ГСЮра пил'!$V30*AC$13 -> 0 | AD30: ='ГСЮра пил'!$W30*AC$13 -> 0 | AE30: ='ГСЮра без пил'!$V30*AE$13 -> 0 | AF30: ='ГСЮра без пил'!$W30*AE$13 -> 0 | AG30: ='ГСЮра пил МСГРП'!$V30*AG$13 -> 0 | AH30: ='ГСЮра пил МСГРП'!$W30*AG$13 -> 0 | AI30: =ВЗ!$V30*AI$13 -> 0 | AJ30: =ВЗ!$W30*AI$13 -> 0 | AK30: ='Посл. скв'!$V30*AK$13 -> 0 | AL30: ='Посл. скв'!$W30*AK$13 -> 0 | AM30: =AK30+AI30+AG30+AE30+AC30+AA30+Y30+W30++U30+S30+Q30+M30+O30+K30+I30+G30 -> 6 | AN30: =AL30+AJ30+AH30+AF30+AD30+AB30+Z30+X30++V30+T30+R30+N30+P30+L30+J30+H30 -> 1592190 | AO30: =('[8]Куст №40А'!AD2008)*1000 -> 1532030 | AP30: =AO30-AN30 -> -60160 | AR30: =AS30-AN30 -> 0 | AS30: 1592190
D31: ='Перв. скв '!D31 -> Передвижка 18 м. | E31: ='Перв. скв '!E31 -> не определен | F31: ='Перв. скв '!F31 -> опер. | G31: ='Перв. скв '!$V31*G$13 -> 0 | H31: ='Перв. скв '!$W31*G$13 -> 0 | I31: =ННСдо1300!$V31*I$13 -> 0 | J31: =ННСдо1300!$W31*I$13 -> 0 | K31: =ННСот1300до1500!$V31*K$13 -> 0 | L31: =ННСот1300до1500!$W31*K$13 -> 0 | M31: =ННСот1500до2000!$V31*M$13 -> 0 | N31: =ННСот1500до2000!$W31*M$13 -> 0 | O31: =ННСот2000до2200!$V31*O$13 -> 0 | P31: =ННСот2000до2200!$W31*O$13 -> 0 | Q31: =ННСболее2200!$V31*Q$13 -> 0 | R31: =ННСболее2200!$W31*Q$13 -> 0 | S31: =Оценочная!$V31*S$13 -> 0 | T31: =Оценочная!$W31*S$13 -> 0 | U31: ='ННСЮра>800'!$V31*U$13 -> 0 | V31: ='ННСЮра>800'!$W31*U$13 -> 0 | W31: ='ГС пил'!V31*$W$13 -> 0 | X31: ='ГС пил'!W31*$W$13 -> 0 | Y31: ='ГС без пил'!$V31*Y$13 -> 0 | Z31: ='ГС без пил'!$W31*Y$13 -> 0 | AA31: ='ГС пил МСГРП'!$V31*AA$13 -> 0 | AB31: ='ГС пил МСГРП'!$W31*AA$13 -> 0 | AC31: ='ГСЮра пил'!$V31*AC$13 -> 0 | AD31: ='ГСЮра пил'!$W31*AC$13 -> 0 | AE31: ='ГСЮра без пил'!$V31*AE$13 -> 0 | AF31: ='ГСЮра без пил'!$W31*AE$13 -> 0 | AG31: ='ГСЮра пил МСГРП'!$V31*AG$13 -> 0 | AH31: ='ГСЮра пил МСГРП'!$W31*AG$13 -> 0 | AI31: =ВЗ!$V31*AI$13 -> 0 | AJ31: =ВЗ!$W31*AI$13 -> 0 | AK31: ='Посл. скв'!$V31*AK$13 -> 1 | AL31: ='Посл. скв'!$W31*AK$13 -> 406328 | AM31: =AK31+AI31+AG31+AE31+AC31+AA31+Y31+W31++U31+S31+Q31+M31+O31+K31+I31+G31 -> 1 | AN31: =AL31+AJ31+AH31+AF31+AD31+AB31+Z31+X31++V31+T31+R31+N31+P31+L31+J31+H31 -> 406328 | AO31: =('[8]Куст №40А'!AD2009)*1000 -> 813354 | AP31: =AO31-AN31 -> 407026 | AR31: =AS31-AN31 -> 0 | AS31: 406328
... D40: ='Перв. скв '!D40 -> Завоз и монтаж новой насосной группы | E40: ='Перв. скв '!E40 -> не определен | F40: ='Перв. скв '!F40 -> опер. | G40: ='Перв. скв '!$V40*G$13 -> 0 | H40: ='Перв. скв '!$W40*G$13 -> 0 | I40: =ННСдо1300!$V40*I$13 -> 0 | J40: =ННСдо1300!$W40*I$13 -> 0 | K40: =ННСот1300до1500!$V40*K$13 -> 0 | L40: =ННСот1300до1500!$W40*K$13 -> 0 | M40: =ННСот1500до2000!$V40*M$13 -> 0 | N40: =ННСот1500до2000!$W40*M$13 -> 0 | O40: =ННСот2000до2200!$V40*O$13 -> 0 | P40: =ННСот2000до2200!$W40*O$13 -> 0 | Q40: =ННСболее2200!$V40*Q$13 -> 0 | R40: =ННСболее2200!$W40*Q$13 -> 0 | S40: =Оценочная!$V40*S$13 -> 0 | T40: =Оценочная!$W40*S$13 -> 0 | U40: ='ННСЮра>800'!$V40*U$13 -> 0 | V40: ='ННСЮра>800'!$W40*U$13 -> 0 | W40: ='ГС пил'!V40*$W$13 -> 0 | X40: ='ГС пил'!W40*$W$13 -> 0 | Y40: ='ГС без пил'!$V40*Y$13 -> 0 | Z40: ='ГС без пил'!$W40*Y$13 -> 0 | AA40: ='ГС пил МСГРП'!$V40*AA$13 -> 0 | AB40: ='ГС пил МСГРП'!$W40*AA$13 -> 0 | AC40: ='ГСЮра пил'!$V40*AC$13 -> 0 | AD40: ='ГСЮра пил'!$W40*AC$13 -> 0 | AE40: ='ГСЮра без пил'!$V40*AE$13 -> 0 | AF40: ='ГСЮра без пил'!$W40*AE$13 -> 0 | AG40: ='ГСЮра пил МСГРП'!$V40*AG$13 -> 0 | AH40: ='ГСЮра пил МСГРП'!$W40*AG$13 -> 0 | AI40: =ВЗ!$V40*AI$13 -> 0 | AJ40: =ВЗ!$W40*AI$13 -> 0 | AK40: ='Посл. скв'!$V40*AK$13 -> 0 | AL40: ='Посл. скв'!$W40*AK$13 -> 0 | AM40: =AK40+AI40+AG40+AE40+AC40+AA40+Y40+W40++U40+S40+Q40+M40+O40+K40+I40+G40 -> 0 | AN40: =AL40+AJ40+AH40+AF40+AD40+AB40+Z40+X40++V40+T40+R40+N40+P40+L40+J40+H40 -> 0 | AO40: =('[8]Куст №40А'!AD2018)*1000 -> 0 | AP40: =AO40-AN40 -> 0 | AR40: =AS40-AN40 -> 0 | AS40: 0
C41: ОБЩАЯ СТОИМОСТЬ ВМР | H41: =SUM(H20:H40) -> 25714124 | J41: =SUM(J20:J40) -> 0 | L41: =SUM(L20:L40) -> 0 | N41: =SUM(N20:N40) -> 0 | P41: =SUM(P20:P40) -> 0 | R41: =SUM(R20:R40) -> 0 | T41: =SUM(T20:T40) -> 0 | V41: =SUM(V20:V40) -> 0 | X41: =SUM(X20:X40) -> 0 | Z41: =SUM(Z20:Z40) -> 1592190 | AB41: =SUM(AB20:AB40) -> 0 | AD41: =SUM(AD20:AD40) -> 0 | AF41: =SUM(AF20:AF40) -> 0 | AH41: =SUM(AH20:AH40) -> 0 | AJ41: =SUM(AJ20:AJ40) -> 0 | AL41: =SUM(AL20:AL40) -> 6618548 | AN41: =SUM(AN20:AN40) -> 33924862 | AR41: =AS41-AN41 -> -17824982 | AS41: 16099880
AN42: 0 | AR42: =AS42-AN42 -> 0 | AS42: 0
C43: 2. ЭТАП БУРЕНИЯ: | AR43: =AS43-AN43 -> 0
C44: ='Перв. скв '!C44 -> не определен | D44: Описание работ/услуг | AN44: 0 | AR44: =AS44-AN44 -> 0 | AS44: 0
C45: (технико-технологичексие особенности) | D45: ='Перв. скв '!D45 -> Фиксированная ставка за скважину с отходом до 1300 м. | E45: ='Перв. скв '!E45 -> не определен | F45: ='Перв. скв '!F45 -> скв. | G45: ='Перв. скв '!$V45*G$13 -> 0 | H45: ='Перв. скв '!$W45*G$13 -> 0 | I45: =ННСдо1300!$V45*I$13 -> 0 | J45: =ННСдо1300!$W45*I$13 -> 0 | K45: =ННСот1300до1500!$V45*K$13 -> 0 | L45: =ННСот1300до1500!$W45*K$13 -> 0 | M45: =ННСот1500до2000!$V45*M$13 -> 0 | N45: =ННСот1500до2000!$W45*M$13 -> 0 | O45: =ННСот2000до2200!$V45*O$13 -> 0 | P45: =ННСот2000до2200!$W45*O$13 -> 0 | Q45: =ННСболее2200!$V45*Q$13 -> 0 | R45: =ННСболее2200!$W45*Q$13 -> 0 | S45: =Оценочная!$V45*S$13 -> 0 | T45: =Оценочная!$W45*S$13 -> 0 | U45: ='ННСЮра>800'!$V45*U$13 -> 0 | V45: ='ННСЮра>800'!$W45*U$13 -> 0 | W45: ='ГС пил'!V45*$W$13 -> 0 | X45: ='ГС пил'!W45*$W$13 -> 0 | Y45: ='ГС без пил'!$V45*Y$13 -> 0 | Z45: ='ГС без пил'!$W45*Y$13 -> 0 | AA45: ='ГС пил МСГРП'!$V45*AA$13 -> 0 | AB45: ='ГС пил МСГРП'!$W45*AA$13 -> 0 | AC45: ='ГСЮра пил'!$V45*AC$13 -> 0 | AD45: ='ГСЮра пил'!$W45*AC$13 -> 0 | AE45: ='ГСЮра без пил'!$V45*AE$13 -> 0 | AF45: ='ГСЮра без пил'!$W45*AE$13 -> 0 | AG45: ='ГСЮра пил МСГРП'!$V45*AG$13 -> 0 | AH45: ='ГСЮра пил МСГРП'!$W45*AG$13 -> 0 | AI45: =ВЗ!$V45*AI$13 -> 0 | AJ45: =ВЗ!$W45*AI$13 -> 0 | AK45: ='Посл. скв'!$V45*AK$13 -> 0 | AL45: ='Посл. скв'!$W45*AK$13 -> 0 | AM45: =AK45+AI45+AG45+AE45+AC45+AA45+Y45+W45++U45+S45+Q45+M45+O45+K45+I45+G45 -> 0 | AN45: =AL45+AJ45+AH45+AF45+AD45+AB45+Z45+X45++V45+T45+R45+N45+P45+L45+J45+H45 -> 0 | AO45: =('[8]Куст №40А'!$AD$170)*1000 -> 33813075 | AP45: =AO45-AN45 -> 33813075 | AR45: =AS45-AN45 -> 0 | AS45: 0
D46: ='Перв. скв '!D46 -> Фиксированная ставка за скважину с отходом от 1300 до 1500 м. | E46: ='Перв. скв '!E46 -> не определен | F46: ='Перв. скв '!F46 -> скв. | G46: ='Перв. скв '!$V46*G$13 -> 0 | H46: ='Перв. скв '!$W46*G$13 -> 0 | I46: =ННСдо1300!$V46*I$13 -> 0 | J46: =ННСдо1300!$W46*I$13 -> 0 | K46: =ННСот1300до1500!$V46*K$13 -> 0 | L46: =ННСот1300до1500!$W46*K$13 -> 0 | M46: =ННСот1500до2000!$V46*M$13 -> 0 | N46: =ННСот1500до2000!$W46*M$13 -> 0 | O46: =ННСот2000до2200!$V46*O$13 -> 0 | P46: =ННСот2000до2200!$W46*O$13 -> 0 | Q46: =ННСболее2200!$V46*Q$13 -> 0 | R46: =ННСболее2200!$W46*Q$13 -> 0 | S46: =Оценочная!$V46*S$13 -> 0 | T46: =Оценочная!$W46*S$13 -> 0 | U46: ='ННСЮра>800'!$V46*U$13 -> 0 | V46: ='ННСЮра>800'!$W46*U$13 -> 0 | W46: ='ГС пил'!V46*$W$13 -> 0 | X46: ='ГС пил'!W46*$W$13 -> 0 | Y46: ='ГС без пил'!$V46*Y$13 -> 0 | Z46: ='ГС без пил'!$W46*Y$13 -> 0 | AA46: ='ГС пил МСГРП'!$V46*AA$13 -> 0 | AB46: ='ГС пил МСГРП'!$W46*AA$13 -> 0 | AC46: ='ГСЮра пил'!$V46*AC$13 -> 0 | AD46: ='ГСЮра пил'!$W46*AC$13 -> 0 | AE46: ='ГСЮра без пил'!$V46*AE$13 -> 0 | AF46: ='ГСЮра без пил'!$W46*AE$13 -> 0 | AG46: ='ГСЮра пил МСГРП'!$V46*AG$13 -> 0 | AH46: ='ГСЮра пил МСГРП'!$W46*AG$13 -> 0 | AI46: =ВЗ!$V46*AI$13 -> 0 | AJ46: =ВЗ!$W46*AI$13 -> 0 | AK46: ='Посл. скв'!$V46*AK$13 -> 0 | AL46: ='Посл. скв'!$W46*AK$13 -> 0 | AM46: =AK46+AI46+AG46+AE46+AC46+AA46+Y46+W46++U46+S46+Q46+M46+O46+K46+I46+G46 -> 0 | AN46: =AL46+AJ46+AH46+AF46+AD46+AB46+Z46+X46++V46+T46+R46+N46+P46+L46+J46+H46 -> 0 | AO46: =('[8]Куст №40А'!$AD$445)*1000 -> 16666394 | AP46: =AO46-AN46 -> 16666394 | AR46: =AS46-AN46 -> 0 | AS46: 0
D47: ='Перв. скв '!D47 -> Фиксированная ставка за скважину с отходом от 1500 до 2000 м. | E47: ='Перв. скв '!E47 -> не определен | F47: ='Перв. скв '!F47 -> скв. | G47: ='Перв. скв '!$V47*G$13 -> 0 | H47: ='Перв. скв '!$W47*G$13 -> 0 | I47: =ННСдо1300!$V47*I$13 -> 0 | J47: =ННСдо1300!$W47*I$13 -> 0 | K47: =ННСот1300до1500!$V47*K$13 -> 0 | L47: =ННСот1300до1500!$W47*K$13 -> 0 | M47: =ННСот1500до2000!$V47*M$13 -> 0 | N47: =ННСот1500до2000!$W47*M$13 -> 0 | O47: =ННСот2000до2200!$V47*O$13 -> 0 | P47: =ННСот2000до2200!$W47*O$13 -> 0 | Q47: =ННСболее2200!$V47*Q$13 -> 0 | R47: =ННСболее2200!$W47*Q$13 -> 0 | S47: =Оценочная!$V47*S$13 -> 0 | T47: =Оценочная!$W47*S$13 -> 0 | U47: ='ННСЮра>800'!$V47*U$13 -> 0 | V47: ='ННСЮра>800'!$W47*U$13 -> 0 | W47: ='ГС пил'!V47*$W$13 -> 0 | X47: ='ГС пил'!W47*$W$13 -> 0 | Y47: ='ГС без пил'!$V47*Y$13 -> 0 | Z47: ='ГС без пил'!$W47*Y$13 -> 0 | AA47: ='ГС пил МСГРП'!$V47*AA$13 -> 0 | AB47: ='ГС пил МСГРП'!$W47*AA$13 -> 0 | AC47: ='ГСЮра пил'!$V47*AC$13 -> 0 | AD47: ='ГСЮра пил'!$W47*AC$13 -> 0 | AE47: ='ГСЮра без пил'!$V47*AE$13 -> 0 | AF47: ='ГСЮра без пил'!$W47*AE$13 -> 0 | AG47: ='ГСЮра пил МСГРП'!$V47*AG$13 -> 0 | AH47: ='ГСЮра пил МСГРП'!$W47*AG$13 -> 0 | AI47: =ВЗ!$V47*AI$13 -> 0 | AJ47: =ВЗ!$W47*AI$13 -> 0 | AK47: ='Посл. скв'!$V47*AK$13 -> 0 | AL47: ='Посл. скв'!$W47*AK$13 -> 0 | AM47: =AK47+AI47+AG47+AE47+AC47+AA47+Y47+W47++U47+S47+Q47+M47+O47+K47+I47+G47 -> 0 | AN47: =AL47+AJ47+AH47+AF47+AD47+AB47+Z47+X47++V47+T47+R47+N47+P47+L47+J47+H47 -> 0 | AO47: =('[8]Куст №40А'!$AD$720)*1000 -> 0 | AP47: =AO47-AN47 -> 0 | AR47: =AS47-AN47 -> 0 | AS47: 0
D48: ='Перв. скв '!D48 -> Фиксированная ставка за скважину с отходом от 2000 до 2200 м. | E48: ='Перв. скв '!E48 -> не определен | F48: ='Перв. скв '!F48 -> скв. | G48: ='Перв. скв '!$V48*G$13 -> 0 | H48: ='Перв. скв '!$W48*G$13 -> 0 | I48: =ННСдо1300!$V48*I$13 -> 0 | J48: =ННСдо1300!$W48*I$13 -> 0 | K48: =ННСот1300до1500!$V48*K$13 -> 0 | L48: =ННСот1300до1500!$W48*K$13 -> 0 | M48: =ННСот1500до2000!$V48*M$13 -> 0 | N48: =ННСот1500до2000!$W48*M$13 -> 0 | O48: =ННСот2000до2200!$V48*O$13 -> 0 | P48: =ННСот2000до2200!$W48*O$13 -> 0 | Q48: =ННСболее2200!$V48*Q$13 -> 0 | R48: =ННСболее2200!$W48*Q$13 -> 0 | S48: =Оценочная!$V48*S$13 -> 0 | T48: =Оценочная!$W48*S$13 -> 0 | U48: ='ННСЮра>800'!$V48*U$13 -> 0 | V48: ='ННСЮра>800'!$W48*U$13 -> 0 | W48: ='ГС пил'!V48*$W$13 -> 0 | X48: ='ГС пил'!W48*$W$13 -> 0 | Y48: ='ГС без пил'!$V48*Y$13 -> 0 | Z48: ='ГС без пил'!$W48*Y$13 -> 0 | AA48: ='ГС пил МСГРП'!$V48*AA$13 -> 0 | AB48: ='ГС пил МСГРП'!$W48*AA$13 -> 0 | AC48: ='ГСЮра пил'!$V48*AC$13 -> 0 | AD48: ='ГСЮра пил'!$W48*AC$13 -> 0 | AE48: ='ГСЮра без пил'!$V48*AE$13 -> 0 | AF48: ='ГСЮра без пил'!$W48*AE$13 -> 0 | AG48: ='ГСЮра пил МСГРП'!$V48*AG$13 -> 0 | AH48: ='ГСЮра пил МСГРП'!$W48*AG$13 -> 0 | AI48: =ВЗ!$V48*AI$13 -> 0 | AJ48: =ВЗ!$W48*AI$13 -> 0 | AK48: ='Посл. скв'!$V48*AK$13 -> 0 | AL48: ='Посл. скв'!$W48*AK$13 -> 0 | AM48: =AK48+AI48+AG48+AE48+AC48+AA48+Y48+W48++U48+S48+Q48+M48+O48+K48+I48+G48 -> 0 | AN48: =AL48+AJ48+AH48+AF48+AD48+AB48+Z48+X48++V48+T48+R48+N48+P48+L48+J48+H48 -> 0 | AO48: =('[8]Куст №40А'!$AD$994)*1000 -> 0 | AP48: =AO48-AN48 -> 0 | AR48: =AS48-AN48 -> 0 | AS48: 0
D49: ='Перв. скв '!D49 -> Фиксированная ставка за скважину с отходом более 2200 м. | E49: ='Перв. скв '!E49 -> не определен | F49: ='Перв. скв '!F49 -> скв. | G49: ='Перв. скв '!$V49*G$13 -> 0 | H49: ='Перв. скв '!$W49*G$13 -> 0 | I49: =ННСдо1300!$V49*I$13 -> 0 | J49: =ННСдо1300!$W49*I$13 -> 0 | K49: =ННСот1300до1500!$V49*K$13 -> 0 | L49: =ННСот1300до1500!$W49*K$13 -> 0 | M49: =ННСот1500до2000!$V49*M$13 -> 0 | N49: =ННСот1500до2000!$W49*M$13 -> 0 | O49: =ННСот2000до2200!$V49*O$13 -> 0 | P49: =ННСот2000до2200!$W49*O$13 -> 0 | Q49: =ННСболее2200!$V49*Q$13 -> 0 | R49: =ННСболее2200!$W49*Q$13 -> 0 | S49: =Оценочная!$V49*S$13 -> 0 | T49: =Оценочная!$W49*S$13 -> 0 | U49: ='ННСЮра>800'!$V49*U$13 -> 0 | V49: ='ННСЮра>800'!$W49*U$13 -> 0 | W49: ='ГС пил'!V49*$W$13 -> 0 | X49: ='ГС пил'!W49*$W$13 -> 0 | Y49: ='ГС без пил'!$V49*Y$13 -> 0 | Z49: ='ГС без пил'!$W49*Y$13 -> 0 | AA49: ='ГС пил МСГРП'!$V49*AA$13 -> 0 | AB49: ='ГС пил МСГРП'!$W49*AA$13 -> 0 | AC49: ='ГСЮра пил'!$V49*AC$13 -> 0 | AD49: ='ГСЮра пил'!$W49*AC$13 -> 0 | AE49: ='ГСЮра без пил'!$V49*AE$13 -> 0 | AF49: ='ГСЮра без пил'!$W49*AE$13 -> 0 | AG49: ='ГСЮра пил МСГРП'!$V49*AG$13 -> 0 | AH49: ='ГСЮра пил МСГРП'!$W49*AG$13 -> 0 | AI49: =ВЗ!$V49*AI$13 -> 0 | AJ49: =ВЗ!$W49*AI$13 -> 0 | AK49: ='Посл. скв'!$V49*AK$13 -> 0 | AL49: ='Посл. скв'!$W49*AK$13 -> 0 | AM49: =AK49+AI49+AG49+AE49+AC49+AA49+Y49+W49++U49+S49+Q49+M49+O49+K49+I49+G49 -> 0 | AN49: =AL49+AJ49+AH49+AF49+AD49+AB49+Z49+X49++V49+T49+R49+N49+P49+L49+J49+H49 -> 0 | AO49: =('[8]Куст №40А'!$AD$1268)*1000 -> 0 | AP49: =AO49-AN49 -> 0 | AR49: =AS49-AN49 -> 0 | AS49: 0
D50: ='Перв. скв '!D50 -> Расчет объема капитальных вложений по ГС | E50: ='Перв. скв '!E50 -> не определен | F50: ='Перв. скв '!F50 -> сут. | G50: ='Перв. скв '!$V50*G$13 -> 1 | H50: ='Перв. скв '!$W50*G$13 -> 31646673 | I50: =ННСдо1300!$V50*I$13 -> 0 | J50: =ННСдо1300!$W50*I$13 -> 0 | K50: =ННСот1300до1500!$V50*K$13 -> 0 | L50: =ННСот1300до1500!$W50*K$13 -> 0 | M50: =ННСот1500до2000!$V50*M$13 -> 0 | N50: =ННСот1500до2000!$W50*M$13 -> 0 | O50: =ННСот2000до2200!$V50*O$13 -> 0 | P50: =ННСот2000до2200!$W50*O$13 -> 0 | Q50: =ННСболее2200!$V50*Q$13 -> 0 | R50: =ННСболее2200!$W50*Q$13 -> 0 | S50: =Оценочная!$V50*S$13 -> 0 | T50: =Оценочная!$W50*S$13 -> 0 | U50: ='ННСЮра>800'!$V50*U$13 -> 0 | V50: ='ННСЮра>800'!$W50*U$13 -> 0 | W50: ='ГС пил'!V50*$W$13 -> 0 | X50: ='ГС пил'!W50*$W$13 -> 0 | Y50: ='ГС без пил'!$V50*Y$13 -> 6 | Z50: ='ГС без пил'!$W50*Y$13 -> 168266778 | AA50: ='ГС пил МСГРП'!$V50*AA$13 -> 0 | AB50: ='ГС пил МСГРП'!$W50*AA$13 -> 0 | AC50: ='ГСЮра пил'!$V50*AC$13 -> 0 | AD50: ='ГСЮра пил'!$W50*AC$13 -> 0 | AE50: ='ГСЮра без пил'!$V50*AE$13 -> 0 | AF50: ='ГСЮра без пил'!$W50*AE$13 -> 0 | AG50: ='ГСЮра пил МСГРП'!$V50*AG$13 -> 0 | AH50: ='ГСЮра пил МСГРП'!$W50*AG$13 -> 0 | AI50: =ВЗ!$V50*AI$13 -> 0 | AJ50: =ВЗ!$W50*AI$13 -> 0 | AK50: ='Посл. скв'!$V50*AK$13 -> 1 | AL50: ='Посл. скв'!$W50*AK$13 -> 31646673 | AM50: =AK50+AI50+AG50+AE50+AC50+AA50+Y50+W50++U50+S50+Q50+M50+O50+K50+I50+G50 -> 8 | AN50: =AL50+AJ50+AH50+AF50+AD50+AB50+Z50+X50++V50+T50+R50+N50+P50+L50+J50+H50 -> 2.3156012e+08 | AO50: =('[8]Куст №40А'!$AD$1542)*1000 -> 0 | AP50: =AO50-AN50 -> -2.3156012e+08 | AR50: =AS50-AN50 -> 0 | AS50: 2.3156012e+08
D51: ='Перв. скв '!D51 -> Переработка бурового шлама | E51: ='Перв. скв '!E51 -> не определен | F51: ='Перв. скв '!F51 -> скв. | G51: ='Перв. скв '!$V51*G$13 -> 810.39 | H51: ='Перв. скв '!$W51*G$13 -> 2325008.9 | I51: =ННСдо1300!$V51*I$13 -> 0 | J51: =ННСдо1300!$W51*I$13 -> 0 | K51: =ННСот1300до1500!$V51*K$13 -> 0 | L51: =ННСот1300до1500!$W51*K$13 -> 0 | M51: =ННСот1500до2000!$V51*M$13 -> 0 | N51: =ННСот1500до2000!$W51*M$13 -> 0 | O51: =ННСот2000до2200!$V51*O$13 -> 0 | P51: =ННСот2000до2200!$W51*O$13 -> 0 | Q51: =ННСболее2200!$V51*Q$13 -> 0 | R51: =ННСболее2200!$W51*Q$13 -> 0 | S51: =Оценочная!$V51*S$13 -> 0 | T51: =Оценочная!$W51*S$13 -> 0 | U51: ='ННСЮра>800'!$V51*U$13 -> 0 | V51: ='ННСЮра>800'!$W51*U$13 -> 0 | W51: ='ГС пил'!V51*$W$13 -> 0 | X51: ='ГС пил'!W51*$W$13 -> 0 | Y51: ='ГС без пил'!$V51*Y$13 -> 4157.64 | Z51: ='ГС без пил'!$W51*Y$13 -> 11928269 | AA51: ='ГС пил МСГРП'!$V51*AA$13 -> 0 | AB51: ='ГС пил МСГРП'!$W51*AA$13 -> 0 | AC51: ='ГСЮра пил'!$V51*AC$13 -> 0 | AD51: ='ГСЮра пил'!$W51*AC$13 -> 0 | AE51: ='ГСЮра без пил'!$V51*AE$13 -> 0 | AF51: ='ГСЮра без пил'!$W51*AE$13 -> 0 | AG51: ='ГСЮра пил МСГРП'!$V51*AG$13 -> 0 | AH51: ='ГСЮра пил МСГРП'!$W51*AG$13 -> 0 | AI51: =ВЗ!$V51*AI$13 -> 0 | AJ51: =ВЗ!$W51*AI$13 -> 0 | AK51: ='Посл. скв'!$V51*AK$13 -> 810.39 | AL51: ='Посл. скв'!$W51*AK$13 -> 2325008.9 | AM51: =AK51+AI51+AG51+AE51+AC51+AA51+Y51+W51++U51+S51+Q51+M51+O51+K51+I51+G51 -> 5778.42 | AN51: =AL51+AJ51+AH51+AF51+AD51+AB51+Z51+X51++V51+T51+R51+N51+P51+L51+J51+H51 -> 16578287 | AO51: =('[8]Куст №40А'!$AD$1818)*1000 -> 10206000 | AP51: =AO51-AN51 -> -6372287 | AR51: =AS51-AN51 -> 0 | AS51: 16578287
D52: ='Перв. скв '!D52 -> Нефть | E52: ='Перв. скв '!E52 -> не определен | F52: ='Перв. скв '!F52 -> шт. | G52: ='Перв. скв '!$V52*G$13 -> 1 | H52: ='Перв. скв '!$W52*G$13 -> 166946 | I52: =ННСдо1300!$V52*I$13 -> 0 | J52: =ННСдо1300!$W52*I$13 -> 0 | K52: =ННСот1300до1500!$V52*K$13 -> 0 | L52: =ННСот1300до1500!$W52*K$13 -> 0 | M52: =ННСот1500до2000!$V52*M$13 -> 0 | N52: =ННСот1500до2000!$W52*M$13 -> 0 | O52: =ННСот2000до2200!$V52*O$13 -> 0 | P52: =ННСот2000до2200!$W52*O$13 -> 0 | Q52: =ННСболее2200!$V52*Q$13 -> 0 | R52: =ННСболее2200!$W52*Q$13 -> 0 | S52: =Оценочная!$V52*S$13 -> 0 | T52: =Оценочная!$W52*S$13 -> 0 | U52: ='ННСЮра>800'!$V52*U$13 -> 0 | V52: ='ННСЮра>800'!$W52*U$13 -> 0 | W52: ='ГС пил'!V52*$W$13 -> 0 | X52: ='ГС пил'!W52*$W$13 -> 0 | Y52: ='ГС без пил'!$V52*Y$13 -> 6 | Z52: ='ГС без пил'!$W52*Y$13 -> 1001676 | AA52: ='ГС пил МСГРП'!$V52*AA$13 -> 0 | AB52: ='ГС пил МСГРП'!$W52*AA$13 -> 0 | AC52: ='ГСЮра пил'!$V52*AC$13 -> 0 | AD52: ='ГСЮра пил'!$W52*AC$13 -> 0 | AE52: ='ГСЮра без пил'!$V52*AE$13 -> 0 | AF52: ='ГСЮра без пил'!$W52*AE$13 -> 0 | AG52: ='ГСЮра пил МСГРП'!$V52*AG$13 -> 0 | AH52: ='ГСЮра пил МСГРП'!$W52*AG$13 -> 0 | AI52: =ВЗ!$V52*AI$13 -> 0 | AJ52: =ВЗ!$W52*AI$13 -> 0 | AK52: ='Посл. скв'!$V52*AK$13 -> 1 | AL52: ='Посл. скв'!$W52*AK$13 -> 166946 | AM52: =AK52+AI52+AG52+AE52+AC52+AA52+Y52+W52++U52+S52+Q52+M52+O52+K52+I52+G52 -> 8 | AN52: =AL52+AJ52+AH52+AF52+AD52+AB52+Z52+X52++V52+T52+R52+N52+P52+L52+J52+H52 -> 1335568 | AO52: =('[8]Куст №40А'!$AD$1819)*1000 -> 1315174 | AP52: =AO52-AN52 -> -20394 | AR52: =AS52-AN52 -> 0 | AS52: 1335568
D53: ='Перв. скв '!D53 -> Эксплуатация верхнего привода | E53: ='Перв. скв '!E53 -> не определен | F53: ='Перв. скв '!F53 -> опер. | G53: ='Перв. скв '!$V53*G$13 -> 45 | H53: ='Перв. скв '!$W53*G$13 -> 3327390 | I53: =ННСдо1300!$V53*I$13 -> 0 | J53: =ННСдо1300!$W53*I$13 -> 0 | K53: =ННСот1300до1500!$V53*K$13 -> 0 | L53: =ННСот1300до1500!$W53*K$13 -> 0 | M53: =ННСот1500до2000!$V53*M$13 -> 0 | N53: =ННСот1500до2000!$W53*M$13 -> 0 | O53: =ННСот2000до2200!$V53*O$13 -> 0 | P53: =ННСот2000до2200!$W53*O$13 -> 0 | Q53: =ННСболее2200!$V53*Q$13 -> 0 | R53: =ННСболее2200!$W53*Q$13 -> 0 | S53: =Оценочная!$V53*S$13 -> 0 | T53: =Оценочная!$W53*S$13 -> 0 | U53: ='ННСЮра>800'!$V53*U$13 -> 0 | V53: ='ННСЮра>800'!$W53*U$13 -> 0 | W53: ='ГС пил'!V53*$W$13 -> 0 | X53: ='ГС пил'!W53*$W$13 -> 0 | Y53: ='ГС без пил'!$V53*Y$13 -> 180 | Z53: ='ГС без пил'!$W53*Y$13 -> 13309560 | AA53: ='ГС пил МСГРП'!$V53*AA$13 -> 0 | AB53: ='ГС пил МСГРП'!$W53*AA$13 -> 0 | AC53: ='ГСЮра пил'!$V53*AC$13 -> 0 | AD53: ='ГСЮра пил'!$W53*AC$13 -> 0 | AE53: ='ГСЮра без пил'!$V53*AE$13 -> 0 | AF53: ='ГСЮра без пил'!$W53*AE$13 -> 0 | AG53: ='ГСЮра пил МСГРП'!$V53*AG$13 -> 0 | AH53: ='ГСЮра пил МСГРП'!$W53*AG$13 -> 0 | AI53: =ВЗ!$V53*AI$13 -> 0 | AJ53: =ВЗ!$W53*AI$13 -> 0 | AK53: ='Посл. скв'!$V53*AK$13 -> 45 | AL53: ='Посл. скв'!$W53*AK$13 -> 3327390 | AM53: =AK53+AI53+AG53+AE53+AC53+AA53+Y53+W53++U53+S53+Q53+M53+O53+K53+I53+G53 -> 270 | AN53: =AL53+AJ53+AH53+AF53+AD53+AB53+Z53+X53++V53+T53+R53+N53+P53+L53+J53+H53 -> 19964340 | AO53: =('[8]Куст №40А'!$AD$1820)*1000 -> 0 | AP53: =AO53-AN53 -> -19964340 | AR53: =AS53-AN53 -> 0 | AS53: 19964340
D54: ='Перв. скв '!D54 -> Эксплуатация системы очистки | E54: ='Перв. скв '!E54 -> не определен | F54: ='Перв. скв '!F54 -> опер. | G54: ='Перв. скв '!$V54*G$13 -> 45 | H54: ='Перв. скв '!$W54*G$13 -> 1565820 | I54: =ННСдо1300!$V54*I$13 -> 0 | J54: =ННСдо1300!$W54*I$13 -> 0 | K54: =ННСот1300до1500!$V54*K$13 -> 0 | L54: =ННСот1300до1500!$W54*K$13 -> 0 | M54: =ННСот1500до2000!$V54*M$13 -> 0 | N54: =ННСот1500до2000!$W54*M$13 -> 0 | O54: =ННСот2000до2200!$V54*O$13 -> 0 | P54: =ННСот2000до2200!$W54*O$13 -> 0 | Q54: =ННСболее2200!$V54*Q$13 -> 0 | R54: =ННСболее2200!$W54*Q$13 -> 0 | S54: =Оценочная!$V54*S$13 -> 0 | T54: =Оценочная!$W54*S$13 -> 0 | U54: ='ННСЮра>800'!$V54*U$13 -> 0 | V54: ='ННСЮра>800'!$W54*U$13 -> 0 | W54: ='ГС пил'!V54*$W$13 -> 0 | X54: ='ГС пил'!W54*$W$13 -> 0 | Y54: ='ГС без пил'!$V54*Y$13 -> 180 | Z54: ='ГС без пил'!$W54*Y$13 -> 6263280 | AA54: ='ГС пил МСГРП'!$V54*AA$13 -> 0 | AB54: ='ГС пил МСГРП'!$W54*AA$13 -> 0 | AC54: ='ГСЮра пил'!$V54*AC$13 -> 0 | AD54: ='ГСЮра пил'!$W54*AC$13 -> 0 | AE54: ='ГСЮра без пил'!$V54*AE$13 -> 0 | AF54: ='ГСЮра без пил'!$W54*AE$13 -> 0 | AG54: ='ГСЮра пил МСГРП'!$V54*AG$13 -> 0 | AH54: ='ГСЮра пил МСГРП'!$W54*AG$13 -> 0 | AI54: =ВЗ!$V54*AI$13 -> 0 | AJ54: =ВЗ!$W54*AI$13 -> 0 | AK54: ='Посл. скв'!$V54*AK$13 -> 45 | AL54: ='Посл. скв'!$W54*AK$13 -> 1565820 | AM54: =AK54+AI54+AG54+AE54+AC54+AA54+Y54+W54++U54+S54+Q54+M54+O54+K54+I54+G54 -> 270 | AN54: =AL54+AJ54+AH54+AF54+AD54+AB54+Z54+X54++V54+T54+R54+N54+P54+L54+J54+H54 -> 9394920 | AO54: =('[8]Куст №40А'!$AD$1821)*1000 -> 0 | AP54: =AO54-AN54 -> -9394920 | AR54: =AS54-AN54 -> 0 | AS54: 9394920
D55: ='Перв. скв '!D55 -> Бурение по суточной ставке (геологическая нагрузка) | E55: ='Перв. скв '!E55 -> не определен | F55: ='Перв. скв '!F55 -> опер. | G55: ='Перв. скв '!$V55*G$13 -> 0 | H55: ='Перв. скв '!$W55*G$13 -> 0 | I55: =ННСдо1300!$V55*I$13 -> 0 | J55: =ННСдо1300!$W55*I$13 -> 0 | K55: =ННСот1300до1500!$V55*K$13 -> 0 | L55: =ННСот1300до1500!$W55*K$13 -> 0 | M55: =ННСот1500до2000!$V55*M$13 -> 0 | N55: =ННСот1500до2000!$W55*M$13 -> 0 | O55: =ННСот2000до2200!$V55*O$13 -> 0 | P55: =ННСот2000до2200!$W55*O$13 -> 0 | Q55: =ННСболее2200!$V55*Q$13 -> 0 | R55: =ННСболее2200!$W55*Q$13 -> 0 | S55: =Оценочная!$V55*S$13 -> 0 | T55: =Оценочная!$W55*S$13 -> 0 | U55: ='ННСЮра>800'!$V55*U$13 -> 0 | V55: ='ННСЮра>800'!$W55*U$13 -> 0 | W55: ='ГС пил'!V55*$W$13 -> 0 | X55: ='ГС пил'!W55*$W$13 -> 0 | Y55: ='ГС без пил'!$V55*Y$13 -> 0 | Z55: ='ГС без пил'!$W55*Y$13 -> 0 | AA55: ='ГС пил МСГРП'!$V55*AA$13 -> 0 | AB55: ='ГС пил МСГРП'!$W55*AA$13 -> 0 | AC55: ='ГСЮра пил'!$V55*AC$13 -> 0 | AD55: ='ГСЮра пил'!$W55*AC$13 -> 0 | AE55: ='ГСЮра без пил'!$V55*AE$13 -> 0 | AF55: ='ГСЮра без пил'!$W55*AE$13 -> 0 | AG55: ='ГСЮра пил МСГРП'!$V55*AG$13 -> 0 | AH55: ='ГСЮра пил МСГРП'!$W55*AG$13 -> 0 | AI55: =ВЗ!$V55*AI$13 -> 0 | AJ55: =ВЗ!$W55*AI$13 -> 0 | AK55: ='Посл. скв'!$V55*AK$13 -> 0 | AL55: ='Посл. скв'!$W55*AK$13 -> 0 | AM55: =AK55+AI55+AG55+AE55+AC55+AA55+Y55+W55++U55+S55+Q55+M55+O55+K55+I55+G55 -> 0 | AN55: =AL55+AJ55+AH55+AF55+AD55+AB55+Z55+X55++V55+T55+R55+N55+P55+L55+J55+H55 -> 0 | AO55: =('[8]Куст №40А'!$AD$1817)*1000 -> 0 | AP55: =AO55-AN55 -> 0 | AR55: =AS55-AN55 -> 0 | AS55: 0
C56: ПОДРЯДЧИК ПО ДОЛОТАМ: | AR56: =AS56-AN56 -> 0
C57: ='Перв. скв '!C57 -> 0 | D57: Описание работ/услуг | AN57: 0 | AR57: =AS57-AN57 -> 0 | AS57: 0
C58: (технико-технологичексие особенности) | D58: ='Перв. скв '!D58 -> 550 мм долото для бурения под направление (долото+сервис) | E58: ='Перв. скв '!E58 -> 0 | F58: ='Перв. скв '!F58 -> м | G58: ='Перв. скв '!$V58*G$13 -> 5500 | H58: ='Перв. скв '!$W58*G$13 -> 495000 | I58: =ННСдо1300!$V58*I$13 -> 0 | J58: =ННСдо1300!$W58*I$13 -> 0 | K58: =ННСот1300до1500!$V58*K$13 -> 0 | L58: =ННСот1300до1500!$W58*K$13 -> 0 | M58: =ННСот1500до2000!$V58*M$13 -> 0 | N58: =ННСот1500до2000!$W58*M$13 -> 0 | O58: =ННСот2000до2200!$V58*O$13 -> 0 | P58: =ННСот2000до2200!$W58*O$13 -> 0 | Q58: =ННСболее2200!$V58*Q$13 -> 0 | R58: =ННСболее2200!$W58*Q$13 -> 0 | S58: =Оценочная!$V58*S$13 -> 0 | T58: =Оценочная!$W58*S$13 -> 0 | U58: ='ННСЮра>800'!$V58*U$13 -> 0 | V58: ='ННСЮра>800'!$W58*U$13 -> 0 | W58: ='ГС пил'!V58*$W$13 -> 0 | X58: ='ГС пил'!W58*$W$13 -> 0 | Y58: ='ГС без пил'!$V58*Y$13 -> 24000 | Z58: ='ГС без пил'!$W58*Y$13 -> 2160000 | AA58: ='ГС пил МСГРП'!$V58*AA$13 -> 0 | AB58: ='ГС пил МСГРП'!$W58*AA$13 -> 0 | AC58: ='ГСЮра пил'!$V58*AC$13 -> 0 | AD58: ='ГСЮра пил'!$W58*AC$13 -> 0 | AE58: ='ГСЮра без пил'!$V58*AE$13 -> 0 | AF58: ='ГСЮра без пил'!$W58*AE$13 -> 0 | AG58: ='ГСЮра пил МСГРП'!$V58*AG$13 -> 0 | AH58: ='ГСЮра пил МСГРП'!$W58*AG$13 -> 0 | AI58: =ВЗ!$V58*AI$13 -> 0 | AJ58: =ВЗ!$W58*AI$13 -> 0 | AK58: ='Посл. скв'!$V58*AK$13 -> 5500 | AL58: ='Посл. скв'!$W58*AK$13 -> 495000 | AM58: =AK58+AI58+AG58+AE58+AC58+AA58+Y58+W58++U58+S58+Q58+M58+O58+K58+I58+G58 -> 35000 | AN58: =AL58+AJ58+AH58+AF58+AD58+AB58+Z58+X58++V58+T58+R58+N58+P58+L58+J58+H58 -> 3150000 | AP58: ='[8]Куст №40А'!$AD$1878*1000 -> 3118500 | AR58: =AS58-AN58 -> 0 | AS58: 3150000
D59: ='Перв. скв '!D59 -> 393,7 мм долото для бурения под направление (долото+сервис) | E59: ='Перв. скв '!E59 -> 0 | F59: ='Перв. скв '!F59 -> м | G59: ='Перв. скв '!$V59*G$13 -> 0 | H59: ='Перв. скв '!$W59*G$13 -> 0 | I59: =ННСдо1300!$V59*I$13 -> 0 | J59: =ННСдо1300!$W59*I$13 -> 0 | K59: =ННСот1300до1500!$V59*K$13 -> 0 | L59: =ННСот1300до1500!$W59*K$13 -> 0 | M59: =ННСот1500до2000!$V59*M$13 -> 0 | N59: =ННСот1500до2000!$W59*M$13 -> 0 | O59: =ННСот2000до2200!$V59*O$13 -> 0 | P59: =ННСот2000до2200!$W59*O$13 -> 0 | Q59: =ННСболее2200!$V59*Q$13 -> 0 | R59: =ННСболее2200!$W59*Q$13 -> 0 | S59: =Оценочная!$V59*S$13 -> 0 | T59: =Оценочная!$W59*S$13 -> 0 | U59: ='ННСЮра>800'!$V59*U$13 -> 0 | V59: ='ННСЮра>800'!$W59*U$13 -> 0 | W59: ='ГС пил'!V59*$W$13 -> 0 | X59: ='ГС пил'!W59*$W$13 -> 0 | Y59: ='ГС без пил'!$V59*Y$13 -> 0 | Z59: ='ГС без пил'!$W59*Y$13 -> 0 | AA59: ='ГС пил МСГРП'!$V59*AA$13 -> 0 | AB59: ='ГС пил МСГРП'!$W59*AA$13 -> 0 | AC59: ='ГСЮра пил'!$V59*AC$13 -> 0 | AD59: ='ГСЮра пил'!$W59*AC$13 -> 0 | AE59: ='ГСЮра без пил'!$V59*AE$13 -> 0 | AF59: ='ГСЮра без пил'!$W59*AE$13 -> 0 | AG59: ='ГСЮра пил МСГРП'!$V59*AG$13 -> 0 | AH59: ='ГСЮра пил МСГРП'!$W59*AG$13 -> 0 | AI59: =ВЗ!$V59*AI$13 -> 0 | AJ59: =ВЗ!$W59*AI$13 -> 0 | AK59: ='Посл. скв'!$V59*AK$13 -> 0 | AL59: ='Посл. скв'!$W59*AK$13 -> 0 | AM59: =AK59+AI59+AG59+AE59+AC59+AA59+Y59+W59++U59+S59+Q59+M59+O59+K59+I59+G59 -> 0 | AN59: =AL59+AJ59+AH59+AF59+AD59+AB59+Z59+X59++V59+T59+R59+N59+P59+L59+J59+H59 -> 0 | AP59: =SUM(AN58:AN64) -> 3150000 | AQ59: =AP59-AP58 -> 31500 | AR59: =AS59-AN59 -> 0 | AS59: 0
D60: ='Перв. скв '!D60 -> 295,3 мм долото для бурения под кондуктор (долото+сервис) | E60: ='Перв. скв '!E60 -> 0 | F60: ='Перв. скв '!F60 -> м | G60: ='Перв. скв '!$V60*G$13 -> 0 | H60: ='Перв. скв '!$W60*G$13 -> 0 | I60: =ННСдо1300!$V60*I$13 -> 0 | J60: =ННСдо1300!$W60*I$13 -> 0 | K60: =ННСот1300до1500!$V60*K$13 -> 0 | L60: =ННСот1300до1500!$W60*K$13 -> 0 | M60: =ННСот1500до2000!$V60*M$13 -> 0 | N60: =ННСот1500до2000!$W60*M$13 -> 0 | O60: =ННСот2000до2200!$V60*O$13 -> 0 | P60: =ННСот2000до2200!$W60*O$13 -> 0 | Q60: =ННСболее2200!$V60*Q$13 -> 0 | R60: =ННСболее2200!$W60*Q$13 -> 0 | S60: =Оценочная!$V60*S$13 -> 0 | T60: =Оценочная!$W60*S$13 -> 0 | U60: ='ННСЮра>800'!$V60*U$13 -> 0 | V60: ='ННСЮра>800'!$W60*U$13 -> 0 | W60: ='ГС пил'!V60*$W$13 -> 0 | X60: ='ГС пил'!W60*$W$13 -> 0 | Y60: ='ГС без пил'!$V60*Y$13 -> 0 | Z60: ='ГС без пил'!$W60*Y$13 -> 0 | AA60: ='ГС пил МСГРП'!$V60*AA$13 -> 0 | AB60: ='ГС пил МСГРП'!$W60*AA$13 -> 0 | AC60: ='ГСЮра пил'!$V60*AC$13 -> 0 | AD60: ='ГСЮра пил'!$W60*AC$13 -> 0 | AE60: ='ГСЮра без пил'!$V60*AE$13 -> 0 | AF60: ='ГСЮра без пил'!$W60*AE$13 -> 0 | AG60: ='ГСЮра пил МСГРП'!$V60*AG$13 -> 0 | AH60: ='ГСЮра пил МСГРП'!$W60*AG$13 -> 0 | AI60: =ВЗ!$V60*AI$13 -> 0 | AJ60: =ВЗ!$W60*AI$13 -> 0 | AK60: ='Посл. скв'!$V60*AK$13 -> 0 | AL60: ='Посл. скв'!$W60*AK$13 -> 0 | AM60: =AK60+AI60+AG60+AE60+AC60+AA60+Y60+W60++U60+S60+Q60+M60+O60+K60+I60+G60 -> 0 | AN60: =AL60+AJ60+AH60+AF60+AD60+AB60+Z60+X60++V60+T60+R60+N60+P60+L60+J60+H60 -> 0 | AP60: =AP58=AP59 -> FALSE | AR60: =AS60-AN60 -> 0 | AS60: 0
D61: ='Перв. скв '!D61 -> 220,7 мм долото для бурения эксплуатационную колонну (долото+сервис) | E61: ='Перв. скв '!E61 -> 0 | F61: ='Перв. скв '!F61 -> м | G61: ='Перв. скв '!$V61*G$13 -> 0 | H61: ='Перв. скв '!$W61*G$13 -> 0 | I61: =ННСдо1300!$V61*I$13 -> 0 | J61: =ННСдо1300!$W61*I$13 -> 0 | K61: =ННСот1300до1500!$V61*K$13 -> 0 | L61: =ННСот1300до1500!$W61*K$13 -> 0 | M61: =ННСот1500до2000!$V61*M$13 -> 0 | N61: =ННСот1500до2000!$W61*M$13 -> 0 | O61: =ННСот2000до2200!$V61*O$13 -> 0 | P61: =ННСот2000до2200!$W61*O$13 -> 0 | Q61: =ННСболее2200!$V61*Q$13 -> 0 | R61: =ННСболее2200!$W61*Q$13 -> 0 | S61: =Оценочная!$V61*S$13 -> 0 | T61: =Оценочная!$W61*S$13 -> 0 | U61: ='ННСЮра>800'!$V61*U$13 -> 0 | V61: ='ННСЮра>800'!$W61*U$13 -> 0 | W61: ='ГС пил'!V61*$W$13 -> 0 | X61: ='ГС пил'!W61*$W$13 -> 0 | Y61: ='ГС без пил'!$V61*Y$13 -> 0 | Z61: ='ГС без пил'!$W61*Y$13 -> 0 | AA61: ='ГС пил МСГРП'!$V61*AA$13 -> 0 | AB61: ='ГС пил МСГРП'!$W61*AA$13 -> 0 | AC61: ='ГСЮра пил'!$V61*AC$13 -> 0 | AD61: ='ГСЮра пил'!$W61*AC$13 -> 0 | AE61: ='ГСЮра без пил'!$V61*AE$13 -> 0 | AF61: ='ГСЮра без пил'!$W61*AE$13 -> 0 | AG61: ='ГСЮра пил МСГРП'!$V61*AG$13 -> 0 | AH61: ='ГСЮра пил МСГРП'!$W61*AG$13 -> 0 | AI61: =ВЗ!$V61*AI$13 -> 0 | AJ61: =ВЗ!$W61*AI$13 -> 0 | AK61: ='Посл. скв'!$V61*AK$13 -> 0 | AL61: ='Посл. скв'!$W61*AK$13 -> 0 | AM61: =AK61+AI61+AG61+AE61+AC61+AA61+Y61+W61++U61+S61+Q61+M61+O61+K61+I61+G61 -> 0 | AN61: =AL61+AJ61+AH61+AF61+AD61+AB61+Z61+X61++V61+T61+R61+N61+P61+L61+J61+H61 -> 0 | AR61: =AS61-AN61 -> 0 | AS61: 0
D62: ='Перв. скв '!D62 -> 155,6 мм долото для бурения под хвостовик (долото+сервис) | E62: ='Перв. скв '!E62 -> 0 | F62: ='Перв. скв '!F62 -> м | G62: ='Перв. скв '!$V62*G$13 -> 0 | H62: ='Перв. скв '!$W62*G$13 -> 0 | I62: =ННСдо1300!$V62*I$13 -> 0 | J62: =ННСдо1300!$W62*I$13 -> 0 | K62: =ННСот1300до1500!$V62*K$13 -> 0 | L62: =ННСот1300до1500!$W62*K$13 -> 0 | M62: =ННСот1500до2000!$V62*M$13 -> 0 | N62: =ННСот1500до2000!$W62*M$13 -> 0 | O62: =ННСот2000до2200!$V62*O$13 -> 0 | P62: =ННСот2000до2200!$W62*O$13 -> 0 | Q62: =ННСболее2200!$V62*Q$13 -> 0 | R62: =ННСболее2200!$W62*Q$13 -> 0 | S62: =Оценочная!$V62*S$13 -> 0 | T62: =Оценочная!$W62*S$13 -> 0 | U62: ='ННСЮра>800'!$V62*U$13 -> 0 | V62: ='ННСЮра>800'!$W62*U$13 -> 0 | W62: ='ГС пил'!V62*$W$13 -> 0 | X62: ='ГС пил'!W62*$W$13 -> 0 | Y62: ='ГС без пил'!$V62*Y$13 -> 0 | Z62: ='ГС без пил'!$W62*Y$13 -> 0 | AA62: ='ГС пил МСГРП'!$V62*AA$13 -> 0 | AB62: ='ГС пил МСГРП'!$W62*AA$13 -> 0 | AC62: ='ГСЮра пил'!$V62*AC$13 -> 0 | AD62: ='ГСЮра пил'!$W62*AC$13 -> 0 | AE62: ='ГСЮра без пил'!$V62*AE$13 -> 0 | AF62: ='ГСЮра без пил'!$W62*AE$13 -> 0 | AG62: ='ГСЮра пил МСГРП'!$V62*AG$13 -> 0 | AH62: ='ГСЮра пил МСГРП'!$W62*AG$13 -> 0 | AI62: =ВЗ!$V62*AI$13 -> 0 | AJ62: =ВЗ!$W62*AI$13 -> 0 | AK62: ='Посл. скв'!$V62*AK$13 -> 0 | AL62: ='Посл. скв'!$W62*AK$13 -> 0 | AM62: =AK62+AI62+AG62+AE62+AC62+AA62+Y62+W62++U62+S62+Q62+M62+O62+K62+I62+G62 -> 0 | AN62: =AL62+AJ62+AH62+AF62+AD62+AB62+Z62+X62++V62+T62+R62+N62+P62+L62+J62+H62 -> 0 | AR62: =AS62-AN62 -> 0 | AS62: 0
D63: ='Перв. скв '!D63 -> _________ мм долото для бурения (долото+сервис) | E63: ='Перв. скв '!E63 -> 0 | F63: ='Перв. скв '!F63 -> м | G63: ='Перв. скв '!$V63*G$13 -> 0 | H63: ='Перв. скв '!$W63*G$13 -> 0 | I63: =ННСдо1300!$V63*I$13 -> 0 | J63: =ННСдо1300!$W63*I$13 -> 0 | K63: =ННСот1300до1500!$V63*K$13 -> 0 | L63: =ННСот1300до1500!$W63*K$13 -> 0 | M63: =ННСот1500до2000!$V63*M$13 -> 0 | N63: =ННСот1500до2000!$W63*M$13 -> 0 | O63: =ННСот2000до2200!$V63*O$13 -> 0 | P63: =ННСот2000до2200!$W63*O$13 -> 0 | Q63: =ННСболее2200!$V63*Q$13 -> 0 | R63: =ННСболее2200!$W63*Q$13 -> 0 | S63: =Оценочная!$V63*S$13 -> 0 | T63: =Оценочная!$W63*S$13 -> 0 | U63: ='ННСЮра>800'!$V63*U$13 -> 0 | V63: ='ННСЮра>800'!$W63*U$13 -> 0 | W63: ='ГС пил'!V63*$W$13 -> 0 | X63: ='ГС пил'!W63*$W$13 -> 0 | Y63: ='ГС без пил'!$V63*Y$13 -> 0 | Z63: ='ГС без пил'!$W63*Y$13 -> 0 | AA63: ='ГС пил МСГРП'!$V63*AA$13 -> 0 | AB63: ='ГС пил МСГРП'!$W63*AA$13 -> 0 | AC63: ='ГСЮра пил'!$V63*AC$13 -> 0 | AD63: ='ГСЮра пил'!$W63*AC$13 -> 0 | AE63: ='ГСЮра без пил'!$V63*AE$13 -> 0 | AF63: ='ГСЮра без пил'!$W63*AE$13 -> 0 | AG63: ='ГСЮра пил МСГРП'!$V63*AG$13 -> 0 | AH63: ='ГСЮра пил МСГРП'!$W63*AG$13 -> 0 | AI63: =ВЗ!$V63*AI$13 -> 0 | AJ63: =ВЗ!$W63*AI$13 -> 0 | AK63: ='Посл. скв'!$V63*AK$13 -> 0 | AL63: ='Посл. скв'!$W63*AK$13 -> 0 | AM63: =AK63+AI63+AG63+AE63+AC63+AA63+Y63+W63++U63+S63+Q63+M63+O63+K63+I63+G63 -> 0 | AN63: =AL63+AJ63+AH63+AF63+AD63+AB63+Z63+X63++V63+T63+R63+N63+P63+L63+J63+H63 -> 0 | AR63: =AS63-AN63 -> 0 | AS63: 0
D64: ='Перв. скв '!D64 -> Расширитель раздвижной | E64: ='Перв. скв '!E64 -> 0 | F64: ='Перв. скв '!F64 -> м | G64: ='Перв. скв '!$V64*G$13 -> 0 | H64: ='Перв. скв '!$W64*G$13 -> 0 | I64: =ННСдо1300!$V64*I$13 -> 0 | J64: =ННСдо1300!$W64*I$13 -> 0 | K64: =ННСот1300до1500!$V64*K$13 -> 0 | L64: =ННСот1300до1500!$W64*K$13 -> 0 | M64: =ННСот1500до2000!$V64*M$13 -> 0 | N64: =ННСот1500до2000!$W64*M$13 -> 0 | O64: =ННСот2000до2200!$V64*O$13 -> 0 | P64: =ННСот2000до2200!$W64*O$13 -> 0 | Q64: =ННСболее2200!$V64*Q$13 -> 0 | R64: =ННСболее2200!$W64*Q$13 -> 0 | S64: =Оценочная!$V64*S$13 -> 0 | T64: =Оценочная!$W64*S$13 -> 0 | U64: ='ННСЮра>800'!$V64*U$13 -> 0 | V64: ='ННСЮра>800'!$W64*U$13 -> 0 | W64: ='ГС пил'!V64*$W$13 -> 0 | X64: ='ГС пил'!W64*$W$13 -> 0 | Y64: ='ГС без пил'!$V64*Y$13 -> 0 | Z64: ='ГС без пил'!$W64*Y$13 -> 0 | AA64: ='ГС пил МСГРП'!$V64*AA$13 -> 0 | AB64: ='ГС пил МСГРП'!$W64*AA$13 -> 0 | AC64: ='ГСЮра пил'!$V64*AC$13 -> 0 | AD64: ='ГСЮра пил'!$W64*AC$13 -> 0 | AE64: ='ГСЮра без пил'!$V64*AE$13 -> 0 | AF64: ='ГСЮра без пил'!$W64*AE$13 -> 0 | AG64: ='ГСЮра пил МСГРП'!$V64*AG$13 -> 0 | AH64: ='ГСЮра пил МСГРП'!$W64*AG$13 -> 0 | AI64: =ВЗ!$V64*AI$13 -> 0 | AJ64: =ВЗ!$W64*AI$13 -> 0 | AK64: ='Посл. скв'!$V64*AK$13 -> 0 | AL64: ='Посл. скв'!$W64*AK$13 -> 0 | AM64: =AK64+AI64+AG64+AE64+AC64+AA64+Y64+W64++U64+S64+Q64+M64+O64+K64+I64+G64 -> 0 | AN64: =AL64+AJ64+AH64+AF64+AD64+AB64+Z64+X64++V64+T64+R64+N64+P64+L64+J64+H64 -> 0 | AR64: =AS64-AN64 -> 0 | AS64: 0
C65: ПОДРЯДЧИК ПО ТЕХНОЛОГИЧЕСКОМУ И ТЕЛЕМЕТРИЧЕСКОМУ СОПРОВОЖДЕНИЮ: | AR65: =AS65-AN65 -> 0
C66: ='Перв. скв '!C66 -> 0 | D66: Описание работ/услуг | AN66: 0 | AR66: =AS66-AN66 -> 0 | AS66: 0
C67: (технико-технологичексие особенности) | D67: ='Перв. скв '!D67 -> Фиксированная ставка за скважину с отходом до 1300 м. | E67: ='Перв. скв '!E67 -> 0 | F67: ='Перв. скв '!F67 -> скв. | G67: ='Перв. скв '!$V67*G$13 -> 0 | H67: ='Перв. скв '!$W67*G$13 -> 0 | I67: =ННСдо1300!$V67*I$13 -> 0 | J67: =ННСдо1300!$W67*I$13 -> 0 | K67: =ННСот1300до1500!$V67*K$13 -> 0 | L67: =ННСот1300до1500!$W67*K$13 -> 0 | M67: =ННСот1500до2000!$V67*M$13 -> 0 | N67: =ННСот1500до2000!$W67*M$13 -> 0 | O67: =ННСот2000до2200!$V67*O$13 -> 0 | P67: =ННСот2000до2200!$W67*O$13 -> 0 | Q67: =ННСболее2200!$V67*Q$13 -> 0 | R67: =ННСболее2200!$W67*Q$13 -> 0 | S67: =Оценочная!$V67*S$13 -> 0 | T67: =Оценочная!$W67*S$13 -> 0 | U67: ='ННСЮра>800'!$V67*U$13 -> 0 | V67: ='ННСЮра>800'!$W67*U$13 -> 0 | W67: ='ГС пил'!V67*$W$13 -> 0 | X67: ='ГС пил'!W67*$W$13 -> 0 | Y67: ='ГС без пил'!$V67*Y$13 -> 0 | Z67: ='ГС без пил'!$W67*Y$13 -> 0 | AA67: ='ГС пил МСГРП'!$V67*AA$13 -> 0 | AB67: ='ГС пил МСГРП'!$W67*AA$13 -> 0 | AC67: ='ГСЮра пил'!$V67*AC$13 -> 0 | AD67: ='ГСЮра пил'!$W67*AC$13 -> 0 | AE67: ='ГСЮра без пил'!$V67*AE$13 -> 0 | AF67: ='ГСЮра без пил'!$W67*AE$13 -> 0 | AG67: ='ГСЮра пил МСГРП'!$V67*AG$13 -> 0 | AH67: ='ГСЮра пил МСГРП'!$W67*AG$13 -> 0 | AI67: =ВЗ!$V67*AI$13 -> 0 | AJ67: =ВЗ!$W67*AI$13 -> 0 | AK67: ='Посл. скв'!$V67*AK$13 -> 0 | AL67: ='Посл. скв'!$W67*AK$13 -> 0 | AM67: =AK67+AI67+AG67+AE67+AC67+AA67+Y67+W67++U67+S67+Q67+M67+O67+K67+I67+G67 -> 0 | AN67: =AL67+AJ67+AH67+AF67+AD67+AB67+Z67+X67++V67+T67+R67+N67+P67+L67+J67+H67 -> 0 | AO67: =('[8]Куст №40А'!$AD$206)*1000 -> 8750000 | AP67: =AO67-AN67 -> 8750000 | AR67: =AS67-AN67 -> 0 | AS67: 0
D68: ='Перв. скв '!D68 -> Фиксированная ставка за скважину с отходом от 1300 до 1500 м. | E68: ='Перв. скв '!E68 -> 0 | F68: ='Перв. скв '!F68 -> скв. | G68: ='Перв. скв '!$V68*G$13 -> 0 | H68: ='Перв. скв '!$W68*G$13 -> 0 | I68: =ННСдо1300!$V68*I$13 -> 0 | J68: =ННСдо1300!$W68*I$13 -> 0 | K68: =ННСот1300до1500!$V68*K$13 -> 0 | L68: =ННСот1300до1500!$W68*K$13 -> 0 | M68: =ННСот1500до2000!$V68*M$13 -> 0 | N68: =ННСот1500до2000!$W68*M$13 -> 0 | O68: =ННСот2000до2200!$V68*O$13 -> 0 | P68: =ННСот2000до2200!$W68*O$13 -> 0 | Q68: =ННСболее2200!$V68*Q$13 -> 0 | R68: =ННСболее2200!$W68*Q$13 -> 0 | S68: =Оценочная!$V68*S$13 -> 0 | T68: =Оценочная!$W68*S$13 -> 0 | U68: ='ННСЮра>800'!$V68*U$13 -> 0 | V68: ='ННСЮра>800'!$W68*U$13 -> 0 | W68: ='ГС пил'!V68*$W$13 -> 0 | X68: ='ГС пил'!W68*$W$13 -> 0 | Y68: ='ГС без пил'!$V68*Y$13 -> 0 | Z68: ='ГС без пил'!$W68*Y$13 -> 0 | AA68: ='ГС пил МСГРП'!$V68*AA$13 -> 0 | AB68: ='ГС пил МСГРП'!$W68*AA$13 -> 0 | AC68: ='ГСЮра пил'!$V68*AC$13 -> 0 | AD68: ='ГСЮра пил'!$W68*AC$13 -> 0 | AE68: ='ГСЮра без пил'!$V68*AE$13 -> 0 | AF68: ='ГСЮра без пил'!$W68*AE$13 -> 0 | AG68: ='ГСЮра пил МСГРП'!$V68*AG$13 -> 0 | AH68: ='ГСЮра пил МСГРП'!$W68*AG$13 -> 0 | AI68: =ВЗ!$V68*AI$13 -> 0 | AJ68: =ВЗ!$W68*AI$13 -> 0 | AK68: ='Посл. скв'!$V68*AK$13 -> 0 | AL68: ='Посл. скв'!$W68*AK$13 -> 0 | AM68: =AK68+AI68+AG68+AE68+AC68+AA68+Y68+W68++U68+S68+Q68+M68+O68+K68+I68+G68 -> 0 | AN68: =AL68+AJ68+AH68+AF68+AD68+AB68+Z68+X68++V68+T68+R68+N68+P68+L68+J68+H68 -> 0 | AO68: =('[8]Куст №40А'!$AD$481)*1000 -> 3922852 | AP68: =AO68-AN68 -> 3922852 | AR68: =AS68-AN68 -> 0 | AS68: 0
D69: ='Перв. скв '!D69 -> Фиксированная ставка за скважину с отходом от 1500 до 2000 м. | E69: ='Перв. скв '!E69 -> 0 | F69: ='Перв. скв '!F69 -> скв. | G69: ='Перв. скв '!$V69*G$13 -> 0 | H69: ='Перв. скв '!$W69*G$13 -> 0 | I69: =ННСдо1300!$V69*I$13 -> 0 | J69: =ННСдо1300!$W69*I$13 -> 0 | K69: =ННСот1300до1500!$V69*K$13 -> 0 | L69: =ННСот1300до1500!$W69*K$13 -> 0 | M69: =ННСот1500до2000!$V69*M$13 -> 0 | N69: =ННСот1500до2000!$W69*M$13 -> 0 | O69: =ННСот2000до2200!$V69*O$13 -> 0 | P69: =ННСот2000до2200!$W69*O$13 -> 0 | Q69: =ННСболее2200!$V69*Q$13 -> 0 | R69: =ННСболее2200!$W69*Q$13 -> 0 | S69: =Оценочная!$V69*S$13 -> 0 | T69: =Оценочная!$W69*S$13 -> 0 | U69: ='ННСЮра>800'!$V69*U$13 -> 0 | V69: ='ННСЮра>800'!$W69*U$13 -> 0 | W69: ='ГС пил'!V69*$W$13 -> 0 | X69: ='ГС пил'!W69*$W$13 -> 0 | Y69: ='ГС без пил'!$V69*Y$13 -> 0 | Z69: ='ГС без пил'!$W69*Y$13 -> 0 | AA69: ='ГС пил МСГРП'!$V69*AA$13 -> 0 | AB69: ='ГС пил МСГРП'!$W69*AA$13 -> 0 | AC69: ='ГСЮра пил'!$V69*AC$13 -> 0 | AD69: ='ГСЮра пил'!$W69*AC$13 -> 0 | AE69: ='ГСЮра без пил'!$V69*AE$13 -> 0 | AF69: ='ГСЮра без пил'!$W69*AE$13 -> 0 | AG69: ='ГСЮра пил МСГРП'!$V69*AG$13 -> 0 | AH69: ='ГСЮра пил МСГРП'!$W69*AG$13 -> 0 | AI69: =ВЗ!$V69*AI$13 -> 0 | AJ69: =ВЗ!$W69*AI$13 -> 0 | AK69: ='Посл. скв'!$V69*AK$13 -> 0 | AL69: ='Посл. скв'!$W69*AK$13 -> 0 | AM69: =AK69+AI69+AG69+AE69+AC69+AA69+Y69+W69++U69+S69+Q69+M69+O69+K69+I69+G69 -> 0 | AN69: =AL69+AJ69+AH69+AF69+AD69+AB69+Z69+X69++V69+T69+R69+N69+P69+L69+J69+H69 -> 0 | AO69: =('[8]Куст №40А'!$AD$756)*1000 -> 0 | AP69: =AO69-AN69 -> 0 | AR69: =AS69-AN69 -> 0 | AS69: 0
D70: ='Перв. скв '!D70 -> Фиксированная ставка за скважину с отходом от 2000 до 2200 м. | E70: ='Перв. скв '!E70 -> 0 | F70: ='Перв. скв '!F70 -> скв. | G70: ='Перв. скв '!$V70*G$13 -> 0 | H70: ='Перв. скв '!$W70*G$13 -> 0 | I70: =ННСдо1300!$V70*I$13 -> 0 | J70: =ННСдо1300!$W70*I$13 -> 0 | K70: =ННСот1300до1500!$V70*K$13 -> 0 | L70: =ННСот1300до1500!$W70*K$13 -> 0 | M70: =ННСот1500до2000!$V70*M$13 -> 0 | N70: =ННСот1500до2000!$W70*M$13 -> 0 | O70: =ННСот2000до2200!$V70*O$13 -> 0 | P70: =ННСот2000до2200!$W70*O$13 -> 0 | Q70: =ННСболее2200!$V70*Q$13 -> 0 | R70: =ННСболее2200!$W70*Q$13 -> 0 | S70: =Оценочная!$V70*S$13 -> 0 | T70: =Оценочная!$W70*S$13 -> 0 | U70: ='ННСЮра>800'!$V70*U$13 -> 0 | V70: ='ННСЮра>800'!$W70*U$13 -> 0 | W70: ='ГС пил'!V70*$W$13 -> 0 | X70: ='ГС пил'!W70*$W$13 -> 0 | Y70: ='ГС без пил'!$V70*Y$13 -> 0 | Z70: ='ГС без пил'!$W70*Y$13 -> 0 | AA70: ='ГС пил МСГРП'!$V70*AA$13 -> 0 | AB70: ='ГС пил МСГРП'!$W70*AA$13 -> 0 | AC70: ='ГСЮра пил'!$V70*AC$13 -> 0 | AD70: ='ГСЮра пил'!$W70*AC$13 -> 0 | AE70: ='ГСЮра без пил'!$V70*AE$13 -> 0 | AF70: ='ГСЮра без пил'!$W70*AE$13 -> 0 | AG70: ='ГСЮра пил МСГРП'!$V70*AG$13 -> 0 | AH70: ='ГСЮра пил МСГРП'!$W70*AG$13 -> 0 | AI70: =ВЗ!$V70*AI$13 -> 0 | AJ70: =ВЗ!$W70*AI$13 -> 0 | AK70: ='Посл. скв'!$V70*AK$13 -> 0 | AL70: ='Посл. скв'!$W70*AK$13 -> 0 | AM70: =AK70+AI70+AG70+AE70+AC70+AA70+Y70+W70++U70+S70+Q70+M70+O70+K70+I70+G70 -> 0 | AN70: =AL70+AJ70+AH70+AF70+AD70+AB70+Z70+X70++V70+T70+R70+N70+P70+L70+J70+H70 -> 0 | AO70: =('[8]Куст №40А'!$AD$1030)*1000 -> 0 | AP70: =AO70-AN70 -> 0 | AR70: =AS70-AN70 -> 0 | AS70: 0
D71: ='Перв. скв '!D71 -> Фиксированная ставка за скважину с отходом более 2200 м. | E71: ='Перв. скв '!E71 -> 0 | F71: ='Перв. скв '!F71 -> скв. | G71: ='Перв. скв '!$V71*G$13 -> 0 | H71: ='Перв. скв '!$W71*G$13 -> 0 | I71: =ННСдо1300!$V71*I$13 -> 0 | J71: =ННСдо1300!$W71*I$13 -> 0 | K71: =ННСот1300до1500!$V71*K$13 -> 0 | L71: =ННСот1300до1500!$W71*K$13 -> 0 | M71: =ННСот1500до2000!$V71*M$13 -> 0 | N71: =ННСот1500до2000!$W71*M$13 -> 0 | O71: =ННСот2000до2200!$V71*O$13 -> 0 | P71: =ННСот2000до2200!$W71*O$13 -> 0 | Q71: =ННСболее2200!$V71*Q$13 -> 0 | R71: =ННСболее2200!$W71*Q$13 -> 0 | S71: =Оценочная!$V71*S$13 -> 0 | T71: =Оценочная!$W71*S$13 -> 0 | U71: ='ННСЮра>800'!$V71*U$13 -> 0 | V71: ='ННСЮра>800'!$W71*U$13 -> 0 | W71: ='ГС пил'!V71*$W$13 -> 0 | X71: ='ГС пил'!W71*$W$13 -> 0 | Y71: ='ГС без пил'!$V71*Y$13 -> 0 | Z71: ='ГС без пил'!$W71*Y$13 -> 0 | AA71: ='ГС пил МСГРП'!$V71*AA$13 -> 0 | AB71: ='ГС пил МСГРП'!$W71*AA$13 -> 0 | AC71: ='ГСЮра пил'!$V71*AC$13 -> 0 | AD71: ='ГСЮра пил'!$W71*AC$13 -> 0 | AE71: ='ГСЮра без пил'!$V71*AE$13 -> 0 | AF71: ='ГСЮра без пил'!$W71*AE$13 -> 0 | AG71: ='ГСЮра пил МСГРП'!$V71*AG$13 -> 0 | AH71: ='ГСЮра пил МСГРП'!$W71*AG$13 -> 0 | AI71: =ВЗ!$V71*AI$13 -> 0 | AJ71: =ВЗ!$W71*AI$13 -> 0 | AK71: ='Посл. скв'!$V71*AK$13 -> 0 | AL71: ='Посл. скв'!$W71*AK$13 -> 0 | AM71: =AK71+AI71+AG71+AE71+AC71+AA71+Y71+W71++U71+S71+Q71+M71+O71+K71+I71+G71 -> 0 | AN71: =AL71+AJ71+AH71+AF71+AD71+AB71+Z71+X71++V71+T71+R71+N71+P71+L71+J71+H71 -> 0 | AO71: =('[8]Куст №40А'!$AD$1304)*1000 -> 0 | AP71: =AO71-AN71 -> 0 | AR71: =AS71-AN71 -> 0 | AS71: 0
D72: ='Перв. скв '!D72 -> Фиксированная ставка за горизонтальную скважину | E72: ='Перв. скв '!E72 -> 0 | F72: ='Перв. скв '!F72 -> скв. | G72: ='Перв. скв '!$V72*G$13 -> 1 | H72: ='Перв. скв '!$W72*G$13 -> 8986126 | I72: =ННСдо1300!$V72*I$13 -> 0 | J72: =ННСдо1300!$W72*I$13 -> 0 | K72: =ННСот1300до1500!$V72*K$13 -> 0 | L72: =ННСот1300до1500!$W72*K$13 -> 0 | M72: =ННСот1500до2000!$V72*M$13 -> 0 | N72: =ННСот1500до2000!$W72*M$13 -> 0 | O72: =ННСот2000до2200!$V72*O$13 -> 0 | P72: =ННСот2000до2200!$W72*O$13 -> 0 | Q72: =ННСболее2200!$V72*Q$13 -> 0 | R72: =ННСболее2200!$W72*Q$13 -> 0 | S72: =Оценочная!$V72*S$13 -> 0 | T72: =Оценочная!$W72*S$13 -> 0 | U72: ='ННСЮра>800'!$V72*U$13 -> 0 | V72: ='ННСЮра>800'!$W72*U$13 -> 0 | W72: ='ГС пил'!V72*$W$13 -> 0 | X72: ='ГС пил'!W72*$W$13 -> 0 | Y72: ='ГС без пил'!$V72*Y$13 -> 6 | Z72: ='ГС без пил'!$W72*Y$13 -> 39518202 | AA72: ='ГС пил МСГРП'!$V72*AA$13 -> 0 | AB72: ='ГС пил МСГРП'!$W72*AA$13 -> 0 | AC72: ='ГСЮра пил'!$V72*AC$13 -> 0 | AD72: ='ГСЮра пил'!$W72*AC$13 -> 0 | AE72: ='ГСЮра без пил'!$V72*AE$13 -> 0 | AF72: ='ГСЮра без пил'!$W72*AE$13 -> 0 | AG72: ='ГСЮра пил МСГРП'!$V72*AG$13 -> 0 | AH72: ='ГСЮра пил МСГРП'!$W72*AG$13 -> 0 | AI72: =ВЗ!$V72*AI$13 -> 0 | AJ72: =ВЗ!$W72*AI$13 -> 0 | AK72: ='Посл. скв'!$V72*AK$13 -> 1 | AL72: ='Посл. скв'!$W72*AK$13 -> 8986126 | AM72: =AK72+AI72+AG72+AE72+AC72+AA72+Y72+W72++U72+S72+Q72+M72+O72+K72+I72+G72 -> 8 | AN72: =AL72+AJ72+AH72+AF72+AD72+AB72+Z72+X72++V72+T72+R72+N72+P72+L72+J72+H72 -> 57490454 | AO72: =('[8]Куст №40А'!$AD$1578)*1000 -> 0 | AP72: =AO72-AN72 -> -57490454 | AR72: =AS72-AN72 -> 0 | AS72: 57490454
D73: ='Перв. скв '!D73 -> 0 | E73: ='Перв. скв '!E73 -> 0 | F73: ='Перв. скв '!F73 -> сут | G73: ='Перв. скв '!$V73*G$13 -> 0 | H73: ='Перв. скв '!$W73*G$13 -> 0 | I73: =ННСдо1300!$V73*I$13 -> 0 | J73: =ННСдо1300!$W73*I$13 -> 0 | K73: =ННСот1300до1500!$V73*K$13 -> 0 | L73: =ННСот1300до1500!$W73*K$13 -> 0 | M73: =ННСот1500до2000!$V73*M$13 -> 0 | N73: =ННСот1500до2000!$W73*M$13 -> 0 | O73: =ННСот2000до2200!$V73*O$13 -> 0 | P73: =ННСот2000до2200!$W73*O$13 -> 0 | Q73: =ННСболее2200!$V73*Q$13 -> 0 | R73: =ННСболее2200!$W73*Q$13 -> 0 | S73: =Оценочная!$V73*S$13 -> 0 | T73: =Оценочная!$W73*S$13 -> 0 | U73: ='ННСЮра>800'!$V73*U$13 -> 0 | V73: ='ННСЮра>800'!$W73*U$13 -> 0 | W73: ='ГС пил'!V73*$W$13 -> 0 | X73: ='ГС пил'!W73*$W$13 -> 0 | Y73: ='ГС без пил'!$V73*Y$13 -> 0 | Z73: ='ГС без пил'!$W73*Y$13 -> 0 | AA73: ='ГС пил МСГРП'!$V73*AA$13 -> 0 | AB73: ='ГС пил МСГРП'!$W73*AA$13 -> 0 | AC73: ='ГСЮра пил'!$V73*AC$13 -> 0 | AD73: ='ГСЮра пил'!$W73*AC$13 -> 0 | AE73: ='ГСЮра без пил'!$V73*AE$13 -> 0 | AF73: ='ГСЮра без пил'!$W73*AE$13 -> 0 | AG73: ='ГСЮра пил МСГРП'!$V73*AG$13 -> 0 | AH73: ='ГСЮра пил МСГРП'!$W73*AG$13 -> 0 | AI73: =ВЗ!$V73*AI$13 -> 0 | AJ73: =ВЗ!$W73*AI$13 -> 0 | AK73: ='Посл. скв'!$V73*AK$13 -> 0 | AL73: ='Посл. скв'!$W73*AK$13 -> 0 | AM73: =AK73+AI73+AG73+AE73+AC73+AA73+Y73+W73++U73+S73+Q73+M73+O73+K73+I73+G73 -> 0 | AN73: =AL73+AJ73+AH73+AF73+AD73+AB73+Z73+X73++V73+T73+R73+N73+P73+L73+J73+H73 -> 0 | AR73: =AS73-AN73 -> 0 | AS73: 0
D74: ='Перв. скв '!D74 -> 0 | E74: ='Перв. скв '!E74 -> 0 | F74: ='Перв. скв '!F74 -> сут | G74: ='Перв. скв '!$V74*G$13 -> 0 | H74: ='Перв. скв '!$W74*G$13 -> 0 | I74: =ННСдо1300!$V74*I$13 -> 0 | J74: =ННСдо1300!$W74*I$13 -> 0 | K74: =ННСот1300до1500!$V74*K$13 -> 0 | L74: =ННСот1300до1500!$W74*K$13 -> 0 | M74: =ННСот1500до2000!$V74*M$13 -> 0 | N74: =ННСот1500до2000!$W74*M$13 -> 0 | O74: =ННСот2000до2200!$V74*O$13 -> 0 | P74: =ННСот2000до2200!$W74*O$13 -> 0 | Q74: =ННСболее2200!$V74*Q$13 -> 0 | R74: =ННСболее2200!$W74*Q$13 -> 0 | S74: =Оценочная!$V74*S$13 -> 0 | T74: =Оценочная!$W74*S$13 -> 0 | U74: ='ННСЮра>800'!$V74*U$13 -> 0 | V74: ='ННСЮра>800'!$W74*U$13 -> 0 | W74: ='ГС пил'!V74*$W$13 -> 0 | X74: ='ГС пил'!W74*$W$13 -> 0 | Y74: ='ГС без пил'!$V74*Y$13 -> 0 | Z74: ='ГС без пил'!$W74*Y$13 -> 0 | AA74: ='ГС пил МСГРП'!$V74*AA$13 -> 0 | AB74: ='ГС пил МСГРП'!$W74*AA$13 -> 0 | AC74: ='ГСЮра пил'!$V74*AC$13 -> 0 | AD74: ='ГСЮра пил'!$W74*AC$13 -> 0 | AE74: ='ГСЮра без пил'!$V74*AE$13 -> 0 | AF74: ='ГСЮра без пил'!$W74*AE$13 -> 0 | AG74: ='ГСЮра пил МСГРП'!$V74*AG$13 -> 0 | AH74: ='ГСЮра пил МСГРП'!$W74*AG$13 -> 0 | AI74: =ВЗ!$V74*AI$13 -> 0 | AJ74: =ВЗ!$W74*AI$13 -> 0 | AK74: ='Посл. скв'!$V74*AK$13 -> 0 | AL74: ='Посл. скв'!$W74*AK$13 -> 0 | AM74: =AK74+AI74+AG74+AE74+AC74+AA74+Y74+W74++U74+S74+Q74+M74+O74+K74+I74+G74 -> 0 | AN74: =AL74+AJ74+AH74+AF74+AD74+AB74+Z74+X74++V74+T74+R74+N74+P74+L74+J74+H74 -> 0 | AR74: =AS74-AN74 -> 0 | AS74: 0
D75: ='Перв. скв '!D75 -> 0 | E75: ='Перв. скв '!E75 -> 0 | F75: ='Перв. скв '!F75 -> сут | G75: ='Перв. скв '!$V75*G$13 -> 0 | H75: ='Перв. скв '!$W75*G$13 -> 0 | I75: =ННСдо1300!$V75*I$13 -> 0 | J75: =ННСдо1300!$W75*I$13 -> 0 | K75: =ННСот1300до1500!$V75*K$13 -> 0 | L75: =ННСот1300до1500!$W75*K$13 -> 0 | M75: =ННСот1500до2000!$V75*M$13 -> 0 | N75: =ННСот1500до2000!$W75*M$13 -> 0 | O75: =ННСот2000до2200!$V75*O$13 -> 0 | P75: =ННСот2000до2200!$W75*O$13 -> 0 | Q75: =ННСболее2200!$V75*Q$13 -> 0 | R75: =ННСболее2200!$W75*Q$13 -> 0 | S75: =Оценочная!$V75*S$13 -> 0 | T75: =Оценочная!$W75*S$13 -> 0 | U75: ='ННСЮра>800'!$V75*U$13 -> 0 | V75: ='ННСЮра>800'!$W75*U$13 -> 0 | W75: ='ГС пил'!V75*$W$13 -> 0 | X75: ='ГС пил'!W75*$W$13 -> 0 | Y75: ='ГС без пил'!$V75*Y$13 -> 0 | Z75: ='ГС без пил'!$W75*Y$13 -> 0 | AA75: ='ГС пил МСГРП'!$V75*AA$13 -> 0 | AB75: ='ГС пил МСГРП'!$W75*AA$13 -> 0 | AC75: ='ГСЮра пил'!$V75*AC$13 -> 0 | AD75: ='ГСЮра пил'!$W75*AC$13 -> 0 | AE75: ='ГСЮра без пил'!$V75*AE$13 -> 0 | AF75: ='ГСЮра без пил'!$W75*AE$13 -> 0 | AG75: ='ГСЮра пил МСГРП'!$V75*AG$13 -> 0 | AH75: ='ГСЮра пил МСГРП'!$W75*AG$13 -> 0 | AI75: =ВЗ!$V75*AI$13 -> 0 | AJ75: =ВЗ!$W75*AI$13 -> 0 | AK75: ='Посл. скв'!$V75*AK$13 -> 0 | AL75: ='Посл. скв'!$W75*AK$13 -> 0 | AM75: =AK75+AI75+AG75+AE75+AC75+AA75+Y75+W75++U75+S75+Q75+M75+O75+K75+I75+G75 -> 0 | AN75: =AL75+AJ75+AH75+AF75+AD75+AB75+Z75+X75++V75+T75+R75+N75+P75+L75+J75+H75 -> 0 | AR75: =AS75-AN75 -> 0 | AS75: 0
D76: ='Перв. скв '!D76 -> Мобилизация на объект работ | E76: ='Перв. скв '!E76 -> 0 | F76: ='Перв. скв '!F76 -> опер. | G76: ='Перв. скв '!$V76*G$13 -> 0 | H76: ='Перв. скв '!$W76*G$13 -> 0 | I76: =ННСдо1300!$V76*I$13 -> 0 | J76: =ННСдо1300!$W76*I$13 -> 0 | K76: =ННСот1300до1500!$V76*K$13 -> 0 | L76: =ННСот1300до1500!$W76*K$13 -> 0 | M76: =ННСот1500до2000!$V76*M$13 -> 0 | N76: =ННСот1500до2000!$W76*M$13 -> 0 | O76: =ННСот2000до2200!$V76*O$13 -> 0 | P76: =ННСот2000до2200!$W76*O$13 -> 0 | Q76: =ННСболее2200!$V76*Q$13 -> 0 | R76: =ННСболее2200!$W76*Q$13 -> 0 | S76: =Оценочная!$V76*S$13 -> 0 | T76: =Оценочная!$W76*S$13 -> 0 | U76: ='ННСЮра>800'!$V76*U$13 -> 0 | V76: ='ННСЮра>800'!$W76*U$13 -> 0 | W76: ='ГС пил'!V76*$W$13 -> 0 | X76: ='ГС пил'!W76*$W$13 -> 0 | Y76: ='ГС без пил'!$V76*Y$13 -> 0 | Z76: ='ГС без пил'!$W76*Y$13 -> 0 | AA76: ='ГС пил МСГРП'!$V76*AA$13 -> 0 | AB76: ='ГС пил МСГРП'!$W76*AA$13 -> 0 | AC76: ='ГСЮра пил'!$V76*AC$13 -> 0 | AD76: ='ГСЮра пил'!$W76*AC$13 -> 0 | AE76: ='ГСЮра без пил'!$V76*AE$13 -> 0 | AF76: ='ГСЮра без пил'!$W76*AE$13 -> 0 | AG76: ='ГСЮра пил МСГРП'!$V76*AG$13 -> 0 | AH76: ='ГСЮра пил МСГРП'!$W76*AG$13 -> 0 | AI76: =ВЗ!$V76*AI$13 -> 0 | AJ76: =ВЗ!$W76*AI$13 -> 0 | AK76: ='Посл. скв'!$V76*AK$13 -> 0 | AL76: ='Посл. скв'!$W76*AK$13 -> 0 | AM76: =AK76+AI76+AG76+AE76+AC76+AA76+Y76+W76++U76+S76+Q76+M76+O76+K76+I76+G76 -> 0 | AN76: =AL76+AJ76+AH76+AF76+AD76+AB76+Z76+X76++V76+T76+R76+N76+P76+L76+J76+H76 -> 0 | AR76: =AS76-AN76 -> 0 | AS76: 0
D77: ='Перв. скв '!D77 -> Демобилизация | E77: ='Перв. скв '!E77 -> 0 | F77: ='Перв. скв '!F77 -> опер. | G77: ='Перв. скв '!$V77*G$13 -> 0 | H77: ='Перв. скв '!$W77*G$13 -> 0 | I77: =ННСдо1300!$V77*I$13 -> 0 | J77: =ННСдо1300!$W77*I$13 -> 0 | K77: =ННСот1300до1500!$V77*K$13 -> 0 | L77: =ННСот1300до1500!$W77*K$13 -> 0 | M77: =ННСот1500до2000!$V77*M$13 -> 0 | N77: =ННСот1500до2000!$W77*M$13 -> 0 | O77: =ННСот2000до2200!$V77*O$13 -> 0 | P77: =ННСот2000до2200!$W77*O$13 -> 0 | Q77: =ННСболее2200!$V77*Q$13 -> 0 | R77: =ННСболее2200!$W77*Q$13 -> 0 | S77: =Оценочная!$V77*S$13 -> 0 | T77: =Оценочная!$W77*S$13 -> 0 | U77: ='ННСЮра>800'!$V77*U$13 -> 0 | V77: ='ННСЮра>800'!$W77*U$13 -> 0 | W77: ='ГС пил'!V77*$W$13 -> 0 | X77: ='ГС пил'!W77*$W$13 -> 0 | Y77: ='ГС без пил'!$V77*Y$13 -> 0 | Z77: ='ГС без пил'!$W77*Y$13 -> 0 | AA77: ='ГС пил МСГРП'!$V77*AA$13 -> 0 | AB77: ='ГС пил МСГРП'!$W77*AA$13 -> 0 | AC77: ='ГСЮра пил'!$V77*AC$13 -> 0 | AD77: ='ГСЮра пил'!$W77*AC$13 -> 0 | AE77: ='ГСЮра без пил'!$V77*AE$13 -> 0 | AF77: ='ГСЮра без пил'!$W77*AE$13 -> 0 | AG77: ='ГСЮра пил МСГРП'!$V77*AG$13 -> 0 | AH77: ='ГСЮра пил МСГРП'!$W77*AG$13 -> 0 | AI77: =ВЗ!$V77*AI$13 -> 0 | AJ77: =ВЗ!$W77*AI$13 -> 0 | AK77: ='Посл. скв'!$V77*AK$13 -> 0 | AL77: ='Посл. скв'!$W77*AK$13 -> 0 | AM77: =AK77+AI77+AG77+AE77+AC77+AA77+Y77+W77++U77+S77+Q77+M77+O77+K77+I77+G77 -> 0 | AN77: =AL77+AJ77+AH77+AF77+AD77+AB77+Z77+X77++V77+T77+R77+N77+P77+L77+J77+H77 -> 0 | AR77: =AS77-AN77 -> 0 | AS77: 0
C78: ='Перв. скв '!C78 -> 0 | D78: Описание работ/услуг | AN78: 0 | AR78: =AS78-AN78 -> 0 | AS78: 0
C79: (технико-технологичексие особенности) | D79: ='Перв. скв '!D79 -> Операционная ставка в режиме работы | E79: ='Перв. скв '!E79 -> 0 | F79: ='Перв. скв '!F79 -> сут | G79: ='Перв. скв '!$V79*G$13 -> 0 | H79: ='Перв. скв '!$W79*G$13 -> 0 | I79: =ННСдо1300!$V79*I$13 -> 0 | J79: =ННСдо1300!$W79*I$13 -> 0 | K79: =ННСот1300до1500!$V79*K$13 -> 0 | L79: =ННСот1300до1500!$W79*K$13 -> 0 | M79: =ННСот1500до2000!$V79*M$13 -> 0 | N79: =ННСот1500до2000!$W79*M$13 -> 0 | O79: =ННСот2000до2200!$V79*O$13 -> 0 | P79: =ННСот2000до2200!$W79*O$13 -> 0 | Q79: =ННСболее2200!$V79*Q$13 -> 0 | R79: =ННСболее2200!$W79*Q$13 -> 0 | S79: =Оценочная!$V79*S$13 -> 0 | T79: =Оценочная!$W79*S$13 -> 0 | U79: ='ННСЮра>800'!$V79*U$13 -> 0 | V79: ='ННСЮра>800'!$W79*U$13 -> 0 | W79: ='ГС пил'!V79*$W$13 -> 0 | X79: ='ГС пил'!W79*$W$13 -> 0 | Y79: ='ГС без пил'!$V79*Y$13 -> 0 | Z79: ='ГС без пил'!$W79*Y$13 -> 0 | AA79: ='ГС пил МСГРП'!$V79*AA$13 -> 0 | AB79: ='ГС пил МСГРП'!$W79*AA$13 -> 0 | AC79: ='ГСЮра пил'!$V79*AC$13 -> 0 | AD79: ='ГСЮра пил'!$W79*AC$13 -> 0 | AE79: ='ГСЮра без пил'!$V79*AE$13 -> 0 | AF79: ='ГСЮра без пил'!$W79*AE$13 -> 0 | AG79: ='ГСЮра пил МСГРП'!$V79*AG$13 -> 0 | AH79: ='ГСЮра пил МСГРП'!$W79*AG$13 -> 0 | AI79: =ВЗ!$V79*AI$13 -> 0 | AJ79: =ВЗ!$W79*AI$13 -> 0 | AK79: ='Посл. скв'!$V79*AK$13 -> 40.5 | AL79: ='Посл. скв'!$W79*AK$13 -> 0 | AM79: =AK79+AI79+AG79+AE79+AC79+AA79+Y79+W79+U79+S79+Q79+M79+O79+K79+I79+G79 -> 40.5 | AN79: =AL79+AJ79+AH79+AF79+AD79+AB79+Z79+X79+V79+T79+R79+N79+P79+L79+J79+H79 -> 0 | AR79: =AS79-AN79 -> 0 | AS79: 0
D80: ='Перв. скв '!D80 -> Операционная ставка в режиме ожидания | E80: ='Перв. скв '!E80 -> 0 | F80: ='Перв. скв '!F80 -> сут | G80: ='Перв. скв '!$V80*G$13 -> 0 | H80: ='Перв. скв '!$W80*G$13 -> 0 | I80: =ННСдо1300!$V80*I$13 -> 0 | J80: =ННСдо1300!$W80*I$13 -> 0 | K80: =ННСот1300до1500!$V80*K$13 -> 0 | L80: =ННСот1300до1500!$W80*K$13 -> 0 | M80: =ННСот1500до2000!$V80*M$13 -> 0 | N80: =ННСот1500до2000!$W80*M$13 -> 0 | O80: =ННСот2000до2200!$V80*O$13 -> 0 | P80: =ННСот2000до2200!$W80*O$13 -> 0 | Q80: =ННСболее2200!$V80*Q$13 -> 0 | R80: =ННСболее2200!$W80*Q$13 -> 0 | S80: =Оценочная!$V80*S$13 -> 0 | T80: =Оценочная!$W80*S$13 -> 0 | U80: ='ННСЮра>800'!$V80*U$13 -> 0 | V80: ='ННСЮра>800'!$W80*U$13 -> 0 | W80: ='ГС пил'!V80*$W$13 -> 0 | X80: ='ГС пил'!W80*$W$13 -> 0 | Y80: ='ГС без пил'!$V80*Y$13 -> 0 | Z80: ='ГС без пил'!$W80*Y$13 -> 0 | AA80: ='ГС пил МСГРП'!$V80*AA$13 -> 0 | AB80: ='ГС пил МСГРП'!$W80*AA$13 -> 0 | AC80: ='ГСЮра пил'!$V80*AC$13 -> 0 | AD80: ='ГСЮра пил'!$W80*AC$13 -> 0 | AE80: ='ГСЮра без пил'!$V80*AE$13 -> 0 | AF80: ='ГСЮра без пил'!$W80*AE$13 -> 0 | AG80: ='ГСЮра пил МСГРП'!$V80*AG$13 -> 0 | AH80: ='ГСЮра пил МСГРП'!$W80*AG$13 -> 0 | AI80: =ВЗ!$V80*AI$13 -> 0 | AJ80: =ВЗ!$W80*AI$13 -> 0 | AK80: ='Посл. скв'!$V80*AK$13 -> 4.5 | AL80: ='Посл. скв'!$W80*AK$13 -> 0 | AM80: =AK80+AI80+AG80+AE80+AC80+AA80+Y80+W80+U80+S80+Q80+M80+O80+K80+I80+G80 -> 4.5 | AN80: =AL80+AJ80+AH80+AF80+AD80+AB80+Z80+X80+V80+T80+R80+N80+P80+L80+J80+H80 -> 0 | AR80: =AS80-AN80 -> 0 | AS80: 0
D81: ='Перв. скв '!D81 -> Гамма -каротаж и сопротивление в режиме записи | E81: ='Перв. скв '!E81 -> 0 | F81: ='Перв. скв '!F81 -> сут | G81: ='Перв. скв '!$V81*G$13 -> 0 | H81: ='Перв. скв '!$W81*G$13 -> 0 | I81: =ННСдо1300!$V81*I$13 -> 0 | J81: =ННСдо1300!$W81*I$13 -> 0 | K81: =ННСот1300до1500!$V81*K$13 -> 0 | L81: =ННСот1300до1500!$W81*K$13 -> 0 | M81: =ННСот1500до2000!$V81*M$13 -> 0 | N81: =ННСот1500до2000!$W81*M$13 -> 0 | O81: =ННСот2000до2200!$V81*O$13 -> 0 | P81: =ННСот2000до2200!$W81*O$13 -> 0 | Q81: =ННСболее2200!$V81*Q$13 -> 0 | R81: =ННСболее2200!$W81*Q$13 -> 0 | S81: =Оценочная!$V81*S$13 -> 0 | T81: =Оценочная!$W81*S$13 -> 0 | U81: ='ННСЮра>800'!$V81*U$13 -> 0 | V81: ='ННСЮра>800'!$W81*U$13 -> 0 | W81: ='ГС пил'!V81*$W$13 -> 0 | X81: ='ГС пил'!W81*$W$13 -> 0 | Y81: ='ГС без пил'!$V81*Y$13 -> 0 | Z81: ='ГС без пил'!$W81*Y$13 -> 0 | AA81: ='ГС пил МСГРП'!$V81*AA$13 -> 0 | AB81: ='ГС пил МСГРП'!$W81*AA$13 -> 0 | AC81: ='ГСЮра пил'!$V81*AC$13 -> 0 | AD81: ='ГСЮра пил'!$W81*AC$13 -> 0 | AE81: ='ГСЮра без пил'!$V81*AE$13 -> 0 | AF81: ='ГСЮра без пил'!$W81*AE$13 -> 0 | AG81: ='ГСЮра пил МСГРП'!$V81*AG$13 -> 0 | AH81: ='ГСЮра пил МСГРП'!$W81*AG$13 -> 0 | AI81: =ВЗ!$V81*AI$13 -> 0 | AJ81: =ВЗ!$W81*AI$13 -> 0 | AK81: ='Посл. скв'!$V81*AK$13 -> 0 | AL81: ='Посл. скв'!$W81*AK$13 -> 0 | AM81: =AK81+AI81+AG81+AE81+AC81+AA81+Y81+W81+U81+S81+Q81+M81+O81+K81+I81+G81 -> 0 | AN81: =AL81+AJ81+AH81+AF81+AD81+AB81+Z81+X81+V81+T81+R81+N81+P81+L81+J81+H81 -> 0 | AR81: =AS81-AN81 -> 0 | AS81: 0
D82: ='Перв. скв '!D82 -> Гамма -каротаж и сопротивление в режиме реального времени | E82: ='Перв. скв '!E82 -> 0 | F82: ='Перв. скв '!F82 -> сут | G82: ='Перв. скв '!$V82*G$13 -> 0 | H82: ='Перв. скв '!$W82*G$13 -> 0 | I82: =ННСдо1300!$V82*I$13 -> 0 | J82: =ННСдо1300!$W82*I$13 -> 0 | K82: =ННСот1300до1500!$V82*K$13 -> 0 | L82: =ННСот1300до1500!$W82*K$13 -> 0 | M82: =ННСот1500до2000!$V82*M$13 -> 0 | N82: =ННСот1500до2000!$W82*M$13 -> 0 | O82: =ННСот2000до2200!$V82*O$13 -> 0 | P82: =ННСот2000до2200!$W82*O$13 -> 0 | Q82: =ННСболее2200!$V82*Q$13 -> 0 | R82: =ННСболее2200!$W82*Q$13 -> 0 | S82: =Оценочная!$V82*S$13 -> 0 | T82: =Оценочная!$W82*S$13 -> 0 | U82: ='ННСЮра>800'!$V82*U$13 -> 0 | V82: ='ННСЮра>800'!$W82*U$13 -> 0 | W82: ='ГС пил'!V82*$W$13 -> 0 | X82: ='ГС пил'!W82*$W$13 -> 0 | Y82: ='ГС без пил'!$V82*Y$13 -> 0 | Z82: ='ГС без пил'!$W82*Y$13 -> 0 | AA82: ='ГС пил МСГРП'!$V82*AA$13 -> 0 | AB82: ='ГС пил МСГРП'!$W82*AA$13 -> 0 | AC82: ='ГСЮра пил'!$V82*AC$13 -> 0 | AD82: ='ГСЮра пил'!$W82*AC$13 -> 0 | AE82: ='ГСЮра без пил'!$V82*AE$13 -> 0 | AF82: ='ГСЮра без пил'!$W82*AE$13 -> 0 | AG82: ='ГСЮра пил МСГРП'!$V82*AG$13 -> 0 | AH82: ='ГСЮра пил МСГРП'!$W82*AG$13 -> 0 | AI82: =ВЗ!$V82*AI$13 -> 0 | AJ82: =ВЗ!$W82*AI$13 -> 0 | AK82: ='Посл. скв'!$V82*AK$13 -> 0 | AL82: ='Посл. скв'!$W82*AK$13 -> 0 | AM82: =AK82+AI82+AG82+AE82+AC82+AA82+Y82+W82+U82+S82+Q82+M82+O82+K82+I82+G82 -> 0 | AN82: =AL82+AJ82+AH82+AF82+AD82+AB82+Z82+X82+V82+T82+R82+N82+P82+L82+J82+H82 -> 0 | AR82: =AS82-AN82 -> 0 | AS82: 0
D83: ='Перв. скв '!D83 -> Гамма -каротаж в режиме записи | E83: ='Перв. скв '!E83 -> 0 | F83: ='Перв. скв '!F83 -> сут | G83: ='Перв. скв '!$V83*G$13 -> 0 | H83: ='Перв. скв '!$W83*G$13 -> 0 | I83: =ННСдо1300!$V83*I$13 -> 0 | J83: =ННСдо1300!$W83*I$13 -> 0 | K83: =ННСот1300до1500!$V83*K$13 -> 0 | L83: =ННСот1300до1500!$W83*K$13 -> 0 | M83: =ННСот1500до2000!$V83*M$13 -> 0 | N83: =ННСот1500до2000!$W83*M$13 -> 0 | O83: =ННСот2000до2200!$V83*O$13 -> 0 | P83: =ННСот2000до2200!$W83*O$13 -> 0 | Q83: =ННСболее2200!$V83*Q$13 -> 0 | R83: =ННСболее2200!$W83*Q$13 -> 0 | S83: =Оценочная!$V83*S$13 -> 0 | T83: =Оценочная!$W83*S$13 -> 0 | U83: ='ННСЮра>800'!$V83*U$13 -> 0 | V83: ='ННСЮра>800'!$W83*U$13 -> 0 | W83: ='ГС пил'!V83*$W$13 -> 0 | X83: ='ГС пил'!W83*$W$13 -> 0 | Y83: ='ГС без пил'!$V83*Y$13 -> 0 | Z83: ='ГС без пил'!$W83*Y$13 -> 0 | AA83: ='ГС пил МСГРП'!$V83*AA$13 -> 0 | AB83: ='ГС пил МСГРП'!$W83*AA$13 -> 0 | AC83: ='ГСЮра пил'!$V83*AC$13 -> 0 | AD83: ='ГСЮра пил'!$W83*AC$13 -> 0 | AE83: ='ГСЮра без пил'!$V83*AE$13 -> 0 | AF83: ='ГСЮра без пил'!$W83*AE$13 -> 0 | AG83: ='ГСЮра пил МСГРП'!$V83*AG$13 -> 0 | AH83: ='ГСЮра пил МСГРП'!$W83*AG$13 -> 0 | AI83: =ВЗ!$V83*AI$13 -> 0 | AJ83: =ВЗ!$W83*AI$13 -> 0 | AK83: ='Посл. скв'!$V83*AK$13 -> 0 | AL83: ='Посл. скв'!$W83*AK$13 -> 0 | AM83: =AK83+AI83+AG83+AE83+AC83+AA83+Y83+W83+U83+S83+Q83+M83+O83+K83+I83+G83 -> 0 | AN83: =AL83+AJ83+AH83+AF83+AD83+AB83+Z83+X83+V83+T83+R83+N83+P83+L83+J83+H83 -> 0 | AR83: =AS83-AN83 -> 0 | AS83: 0
D84: ='Перв. скв '!D84 -> Гамма -каротаж в режиме реального времени | E84: ='Перв. скв '!E84 -> 0 | F84: ='Перв. скв '!F84 -> сут | G84: ='Перв. скв '!$V84*G$13 -> 0 | H84: ='Перв. скв '!$W84*G$13 -> 0 | I84: =ННСдо1300!$V84*I$13 -> 0 | J84: =ННСдо1300!$W84*I$13 -> 0 | K84: =ННСот1300до1500!$V84*K$13 -> 0 | L84: =ННСот1300до1500!$W84*K$13 -> 0 | M84: =ННСот1500до2000!$V84*M$13 -> 0 | N84: =ННСот1500до2000!$W84*M$13 -> 0 | O84: =ННСот2000до2200!$V84*O$13 -> 0 | P84: =ННСот2000до2200!$W84*O$13 -> 0 | Q84: =ННСболее2200!$V84*Q$13 -> 0 | R84: =ННСболее2200!$W84*Q$13 -> 0 | S84: =Оценочная!$V84*S$13 -> 0 | T84: =Оценочная!$W84*S$13 -> 0 | U84: ='ННСЮра>800'!$V84*U$13 -> 0 | V84: ='ННСЮра>800'!$W84*U$13 -> 0 | W84: ='ГС пил'!V84*$W$13 -> 0 | X84: ='ГС пил'!W84*$W$13 -> 0 | Y84: ='ГС без пил'!$V84*Y$13 -> 0 | Z84: ='ГС без пил'!$W84*Y$13 -> 0 | AA84: ='ГС пил МСГРП'!$V84*AA$13 -> 0 | AB84: ='ГС пил МСГРП'!$W84*AA$13 -> 0 | AC84: ='ГСЮра пил'!$V84*AC$13 -> 0 | AD84: ='ГСЮра пил'!$W84*AC$13 -> 0 | AE84: ='ГСЮра без пил'!$V84*AE$13 -> 0 | AF84: ='ГСЮра без пил'!$W84*AE$13 -> 0 | AG84: ='ГСЮра пил МСГРП'!$V84*AG$13 -> 0 | AH84: ='ГСЮра пил МСГРП'!$W84*AG$13 -> 0 | AI84: =ВЗ!$V84*AI$13 -> 0 | AJ84: =ВЗ!$W84*AI$13 -> 0 | AK84: ='Посл. скв'!$V84*AK$13 -> 0 | AL84: ='Посл. скв'!$W84*AK$13 -> 0 | AM84: =AK84+AI84+AG84+AE84+AC84+AA84+Y84+W84+U84+S84+Q84+M84+O84+K84+I84+G84 -> 0 | AN84: =AL84+AJ84+AH84+AF84+AD84+AB84+Z84+X84+V84+T84+R84+N84+P84+L84+J84+H84 -> 0 | AR84: =AS84-AN84 -> 0 | AS84: 0
D85: ='Перв. скв '!D85 -> Услуги персонала телеметрического и технологического сопровождения | E85: ='Перв. скв '!E85 -> 0 | F85: ='Перв. скв '!F85 -> сут | G85: ='Перв. скв '!$V85*G$13 -> 0 | H85: ='Перв. скв '!$W85*G$13 -> 0 | I85: =ННСдо1300!$V85*I$13 -> 0 | J85: =ННСдо1300!$W85*I$13 -> 0 | K85: =ННСот1300до1500!$V85*K$13 -> 0 | L85: =ННСот1300до1500!$W85*K$13 -> 0 | M85: =ННСот1500до2000!$V85*M$13 -> 0 | N85: =ННСот1500до2000!$W85*M$13 -> 0 | O85: =ННСот2000до2200!$V85*O$13 -> 0 | P85: =ННСот2000до2200!$W85*O$13 -> 0 | Q85: =ННСболее2200!$V85*Q$13 -> 0 | R85: =ННСболее2200!$W85*Q$13 -> 0 | S85: =Оценочная!$V85*S$13 -> 0 | T85: =Оценочная!$W85*S$13 -> 0 | U85: ='ННСЮра>800'!$V85*U$13 -> 0 | V85: ='ННСЮра>800'!$W85*U$13 -> 0 | W85: ='ГС пил'!V85*$W$13 -> 0 | X85: ='ГС пил'!W85*$W$13 -> 0 | Y85: ='ГС без пил'!$V85*Y$13 -> 0 | Z85: ='ГС без пил'!$W85*Y$13 -> 0 | AA85: ='ГС пил МСГРП'!$V85*AA$13 -> 0 | AB85: ='ГС пил МСГРП'!$W85*AA$13 -> 0 | AC85: ='ГСЮра пил'!$V85*AC$13 -> 0 | AD85: ='ГСЮра пил'!$W85*AC$13 -> 0 | AE85: ='ГСЮра без пил'!$V85*AE$13 -> 0 | AF85: ='ГСЮра без пил'!$W85*AE$13 -> 0 | AG85: ='ГСЮра пил МСГРП'!$V85*AG$13 -> 0 | AH85: ='ГСЮра пил МСГРП'!$W85*AG$13 -> 0 | AI85: =ВЗ!$V85*AI$13 -> 0 | AJ85: =ВЗ!$W85*AI$13 -> 0 | AK85: ='Посл. скв'!$V85*AK$13 -> 0 | AL85: ='Посл. скв'!$W85*AK$13 -> 0 | AM85: =AK85+AI85+AG85+AE85+AC85+AA85+Y85+W85+U85+S85+Q85+M85+O85+K85+I85+G85 -> 0 | AN85: =AL85+AJ85+AH85+AF85+AD85+AB85+Z85+X85+V85+T85+R85+N85+P85+L85+J85+H85 -> 0 | AR85: =AS85-AN85 -> 0 | AS85: 0
C86: ПОДРЯДЧИК ПО БУРОВЫМ РАСТВОРАМ: | AR86: =AS86-AN86 -> 0
C87: ='Перв. скв '!C87 -> 0 | D87: Описание работ/услуг | AN87: 0 | AR87: =AS87-AN87 -> 0 | AS87: 0
C88: (технико-технологичексие особенности) | D88: ='Перв. скв '!D88 -> Фиксированная ставка за скважину с отходом до 1300 м. | E88: ='Перв. скв '!E88 -> 0 | F88: ='Перв. скв '!F88 -> скв. | G88: ='Перв. скв '!$V88*G$13 -> 0 | H88: ='Перв. скв '!$W88*G$13 -> 0 | I88: =ННСдо1300!$V88*I$13 -> 0 | J88: =ННСдо1300!$W88*I$13 -> 0 | K88: =ННСот1300до1500!$V88*K$13 -> 0 | L88: =ННСот1300до1500!$W88*K$13 -> 0 | M88: =ННСот1500до2000!$V88*M$13 -> 0 | N88: =ННСот1500до2000!$W88*M$13 -> 0 | O88: =ННСот2000до2200!$V88*O$13 -> 0 | P88: =ННСот2000до2200!$W88*O$13 -> 0 | Q88: =ННСболее2200!$V88*Q$13 -> 0 | R88: =ННСболее2200!$W88*Q$13 -> 0 | S88: =Оценочная!$V88*S$13 -> 0 | T88: =Оценочная!$W88*S$13 -> 0 | U88: ='ННСЮра>800'!$V88*U$13 -> 0 | V88: ='ННСЮра>800'!$W88*U$13 -> 0 | W88: ='ГС пил'!V88*$W$13 -> 0 | X88: ='ГС пил'!W88*$W$13 -> 0 | Y88: ='ГС без пил'!$V88*Y$13 -> 0 | Z88: ='ГС без пил'!$W88*Y$13 -> 0 | AA88: ='ГС пил МСГРП'!$V88*AA$13 -> 0 | AB88: ='ГС пил МСГРП'!$W88*AA$13 -> 0 | AC88: ='ГСЮра пил'!$V88*AC$13 -> 0 | AD88: ='ГСЮра пил'!$W88*AC$13 -> 0 | AE88: ='ГСЮра без пил'!$V88*AE$13 -> 0 | AF88: ='ГСЮра без пил'!$W88*AE$13 -> 0 | AG88: ='ГСЮра пил МСГРП'!$V88*AG$13 -> 0 | AH88: ='ГСЮра пил МСГРП'!$W88*AG$13 -> 0 | AI88: =ВЗ!$V88*AI$13 -> 0 | AJ88: =ВЗ!$W88*AI$13 -> 0 | AK88: ='Посл. скв'!$V88*AK$13 -> 0 | AL88: ='Посл. скв'!$W88*AK$13 -> 0 | AM88: =AK88+AI88+AG88+AE88+AC88+AA88+Y88+W88+U88+S88+Q88+M88+O88+K88+I88+G88 -> 0 | AN88: =AL88+AJ88+AH88+AF88+AD88+AB88+Z88+X88+V88+T88+R88+N88+P88+L88+J88+H88 -> 0 | AO88: =('[8]Куст №40А'!$AD$240)*1000 -> 4349555 | AP88: =AO88-AN88 -> 4349555 | AR88: =AS88-AN88 -> 0 | AS88: 0
D89: ='Перв. скв '!D89 -> Фиксированная ставка за скважину с отходом от 1300 до 1500 м. | E89: ='Перв. скв '!E89 -> 0 | F89: ='Перв. скв '!F89 -> скв. | G89: ='Перв. скв '!$V89*G$13 -> 0 | H89: ='Перв. скв '!$W89*G$13 -> 0 | I89: =ННСдо1300!$V89*I$13 -> 0 | J89: =ННСдо1300!$W89*I$13 -> 0 | K89: =ННСот1300до1500!$V89*K$13 -> 0 | L89: =ННСот1300до1500!$W89*K$13 -> 0 | M89: =ННСот1500до2000!$V89*M$13 -> 0 | N89: =ННСот1500до2000!$W89*M$13 -> 0 | O89: =ННСот2000до2200!$V89*O$13 -> 0 | P89: =ННСот2000до2200!$W89*O$13 -> 0 | Q89: =ННСболее2200!$V89*Q$13 -> 0 | R89: =ННСболее2200!$W89*Q$13 -> 0 | S89: =Оценочная!$V89*S$13 -> 0 | T89: =Оценочная!$W89*S$13 -> 0 | U89: ='ННСЮра>800'!$V89*U$13 -> 0 | V89: ='ННСЮра>800'!$W89*U$13 -> 0 | W89: ='ГС пил'!V89*$W$13 -> 0 | X89: ='ГС пил'!W89*$W$13 -> 0 | Y89: ='ГС без пил'!$V89*Y$13 -> 0 | Z89: ='ГС без пил'!$W89*Y$13 -> 0 | AA89: ='ГС пил МСГРП'!$V89*AA$13 -> 0 | AB89: ='ГС пил МСГРП'!$W89*AA$13 -> 0 | AC89: ='ГСЮра пил'!$V89*AC$13 -> 0 | AD89: ='ГСЮра пил'!$W89*AC$13 -> 0 | AE89: ='ГСЮра без пил'!$V89*AE$13 -> 0 | AF89: ='ГСЮра без пил'!$W89*AE$13 -> 0 | AG89: ='ГСЮра пил МСГРП'!$V89*AG$13 -> 0 | AH89: ='ГСЮра пил МСГРП'!$W89*AG$13 -> 0 | AI89: =ВЗ!$V89*AI$13 -> 0 | AJ89: =ВЗ!$W89*AI$13 -> 0 | AK89: ='Посл. скв'!$V89*AK$13 -> 0 | AL89: ='Посл. скв'!$W89*AK$13 -> 0 | AM89: =AK89+AI89+AG89+AE89+AC89+AA89+Y89+W89+U89+S89+Q89+M89+O89+K89+I89+G89 -> 0 | AN89: =AL89+AJ89+AH89+AF89+AD89+AB89+Z89+X89+V89+T89+R89+N89+P89+L89+J89+H89 -> 0 | AO89: =('[8]Куст №40А'!$AD$515)*1000 -> 1961406 | AP89: =AO89-AN89 -> 1961406 | AR89: =AS89-AN89 -> 0 | AS89: 0
D90: ='Перв. скв '!D90 -> Фиксированная ставка за скважину с отходом от 1500 до 2000 м. | E90: ='Перв. скв '!E90 -> 0 | F90: ='Перв. скв '!F90 -> скв. | G90: ='Перв. скв '!$V90*G$13 -> 0 | H90: ='Перв. скв '!$W90*G$13 -> 0 | I90: =ННСдо1300!$V90*I$13 -> 0 | J90: =ННСдо1300!$W90*I$13 -> 0 | K90: =ННСот1300до1500!$V90*K$13 -> 0 | L90: =ННСот1300до1500!$W90*K$13 -> 0 | M90: =ННСот1500до2000!$V90*M$13 -> 0 | N90: =ННСот1500до2000!$W90*M$13 -> 0 | O90: =ННСот2000до2200!$V90*O$13 -> 0 | P90: =ННСот2000до2200!$W90*O$13 -> 0 | Q90: =ННСболее2200!$V90*Q$13 -> 0 | R90: =ННСболее2200!$W90*Q$13 -> 0 | S90: =Оценочная!$V90*S$13 -> 0 | T90: =Оценочная!$W90*S$13 -> 0 | U90: ='ННСЮра>800'!$V90*U$13 -> 0 | V90: ='ННСЮра>800'!$W90*U$13 -> 0 | W90: ='ГС пил'!V90*$W$13 -> 0 | X90: ='ГС пил'!W90*$W$13 -> 0 | Y90: ='ГС без пил'!$V90*Y$13 -> 0 | Z90: ='ГС без пил'!$W90*Y$13 -> 0 | AA90: ='ГС пил МСГРП'!$V90*AA$13 -> 0 | AB90: ='ГС пил МСГРП'!$W90*AA$13 -> 0 | AC90: ='ГСЮра пил'!$V90*AC$13 -> 0 | AD90: ='ГСЮра пил'!$W90*AC$13 -> 0 | AE90: ='ГСЮра без пил'!$V90*AE$13 -> 0 | AF90: ='ГСЮра без пил'!$W90*AE$13 -> 0 | AG90: ='ГСЮра пил МСГРП'!$V90*AG$13 -> 0 | AH90: ='ГСЮра пил МСГРП'!$W90*AG$13 -> 0 | AI90: =ВЗ!$V90*AI$13 -> 0 | AJ90: =ВЗ!$W90*AI$13 -> 0 | AK90: ='Посл. скв'!$V90*AK$13 -> 0 | AL90: ='Посл. скв'!$W90*AK$13 -> 0 | AM90: =AK90+AI90+AG90+AE90+AC90+AA90+Y90+W90+U90+S90+Q90+M90+O90+K90+I90+G90 -> 0 | AN90: =AL90+AJ90+AH90+AF90+AD90+AB90+Z90+X90+V90+T90+R90+N90+P90+L90+J90+H90 -> 0 | AO90: =('[8]Куст №40А'!$AD$790)*1000 -> 0 | AP90: =AO90-AN90 -> 0 | AR90: =AS90-AN90 -> 0 | AS90: 0
D91: ='Перв. скв '!D91 -> Фиксированная ставка за скважину с отходом от 2000 до 2200 м. | E91: ='Перв. скв '!E91 -> 0 | F91: ='Перв. скв '!F91 -> скв. | G91: ='Перв. скв '!$V91*G$13 -> 0 | H91: ='Перв. скв '!$W91*G$13 -> 0 | I91: =ННСдо1300!$V91*I$13 -> 0 | J91: =ННСдо1300!$W91*I$13 -> 0 | K91: =ННСот1300до1500!$V91*K$13 -> 0 | L91: =ННСот1300до1500!$W91*K$13 -> 0 | M91: =ННСот1500до2000!$V91*M$13 -> 0 | N91: =ННСот1500до2000!$W91*M$13 -> 0 | O91: =ННСот2000до2200!$V91*O$13 -> 0 | P91: =ННСот2000до2200!$W91*O$13 -> 0 | Q91: =ННСболее2200!$V91*Q$13 -> 0 | R91: =ННСболее2200!$W91*Q$13 -> 0 | S91: =Оценочная!$V91*S$13 -> 0 | T91: =Оценочная!$W91*S$13 -> 0 | U91: ='ННСЮра>800'!$V91*U$13 -> 0 | V91: ='ННСЮра>800'!$W91*U$13 -> 0 | W91: ='ГС пил'!V91*$W$13 -> 0 | X91: ='ГС пил'!W91*$W$13 -> 0 | Y91: ='ГС без пил'!$V91*Y$13 -> 0 | Z91: ='ГС без пил'!$W91*Y$13 -> 0 | AA91: ='ГС пил МСГРП'!$V91*AA$13 -> 0 | AB91: ='ГС пил МСГРП'!$W91*AA$13 -> 0 | AC91: ='ГСЮра пил'!$V91*AC$13 -> 0 | AD91: ='ГСЮра пил'!$W91*AC$13 -> 0 | AE91: ='ГСЮра без пил'!$V91*AE$13 -> 0 | AF91: ='ГСЮра без пил'!$W91*AE$13 -> 0 | AG91: ='ГСЮра пил МСГРП'!$V91*AG$13 -> 0 | AH91: ='ГСЮра пил МСГРП'!$W91*AG$13 -> 0 | AI91: =ВЗ!$V91*AI$13 -> 0 | AJ91: =ВЗ!$W91*AI$13 -> 0 | AK91: ='Посл. скв'!$V91*AK$13 -> 0 | AL91: ='Посл. скв'!$W91*AK$13 -> 0 | AM91: =AK91+AI91+AG91+AE91+AC91+AA91+Y91+W91+U91+S91+Q91+M91+O91+K91+I91+G91 -> 0 | AN91: =AL91+AJ91+AH91+AF91+AD91+AB91+Z91+X91+V91+T91+R91+N91+P91+L91+J91+H91 -> 0 | AO91: =('[8]Куст №40А'!$AD$1064)*1000 -> 0 | AP91: =AO91-AN91 -> 0 | AR91: =AS91-AN91 -> 0 | AS91: 0
D92: ='Перв. скв '!D92 -> Фиксированная ставка за скважину с отходом более 2200 м. | E92: ='Перв. скв '!E92 -> 0 | F92: ='Перв. скв '!F92 -> сут. | G92: ='Перв. скв '!$V92*G$13 -> 0 | H92: ='Перв. скв '!$W92*G$13 -> 0 | I92: =ННСдо1300!$V92*I$13 -> 0 | J92: =ННСдо1300!$W92*I$13 -> 0 | K92: =ННСот1300до1500!$V92*K$13 -> 0 | L92: =ННСот1300до1500!$W92*K$13 -> 0 | M92: =ННСот1500до2000!$V92*M$13 -> 0 | N92: =ННСот1500до2000!$W92*M$13 -> 0 | O92: =ННСот2000до2200!$V92*O$13 -> 0 | P92: =ННСот2000до2200!$W92*O$13 -> 0 | Q92: =ННСболее2200!$V92*Q$13 -> 0 | R92: =ННСболее2200!$W92*Q$13 -> 0 | S92: =Оценочная!$V92*S$13 -> 0 | T92: =Оценочная!$W92*S$13 -> 0 | U92: ='ННСЮра>800'!$V92*U$13 -> 0 | V92: ='ННСЮра>800'!$W92*U$13 -> 0 | W92: ='ГС пил'!V92*$W$13 -> 0 | X92: ='ГС пил'!W92*$W$13 -> 0 | Y92: ='ГС без пил'!$V92*Y$13 -> 0 | Z92: ='ГС без пил'!$W92*Y$13 -> 0 | AA92: ='ГС пил МСГРП'!$V92*AA$13 -> 0 | AB92: ='ГС пил МСГРП'!$W92*AA$13 -> 0 | AC92: ='ГСЮра пил'!$V92*AC$13 -> 0 | AD92: ='ГСЮра пил'!$W92*AC$13 -> 0 | AE92: ='ГСЮра без пил'!$V92*AE$13 -> 0 | AF92: ='ГСЮра без пил'!$W92*AE$13 -> 0 | AG92: ='ГСЮра пил МСГРП'!$V92*AG$13 -> 0 | AH92: ='ГСЮра пил МСГРП'!$W92*AG$13 -> 0 | AI92: =ВЗ!$V92*AI$13 -> 0 | AJ92: =ВЗ!$W92*AI$13 -> 0 | AK92: ='Посл. скв'!$V92*AK$13 -> 0 | AL92: ='Посл. скв'!$W92*AK$13 -> 0 | AM92: =AK92+AI92+AG92+AE92+AC92+AA92+Y92+W92+U92+S92+Q92+M92+O92+K92+I92+G92 -> 0 | AN92: =AL92+AJ92+AH92+AF92+AD92+AB92+Z92+X92+V92+T92+R92+N92+P92+L92+J92+H92 -> 0 | AO92: =('[8]Куст №40А'!$AD$1338)*1000 -> 0 | AP92: =AO92-AN92 -> 0 | AR92: =AS92-AN92 -> 0 | AS92: 0
D93: ='Перв. скв '!D93 -> Фиксированная ставка за горизонтальную скважину | E93: ='Перв. скв '!E93 -> 0 | F93: ='Перв. скв '!F93 -> скв. | G93: ='Перв. скв '!$V93*G$13 -> 1 | H93: ='Перв. скв '!$W93*G$13 -> 5521715.7 | I93: =ННСдо1300!$V93*I$13 -> 0 | J93: =ННСдо1300!$W93*I$13 -> 0 | K93: =ННСот1300до1500!$V93*K$13 -> 0 | L93: =ННСот1300до1500!$W93*K$13 -> 0 | M93: =ННСот1500до2000!$V93*M$13 -> 0 | N93: =ННСот1500до2000!$W93*M$13 -> 0 | O93: =ННСот2000до2200!$V93*O$13 -> 0 | P93: =ННСот2000до2200!$W93*O$13 -> 0 | Q93: =ННСболее2200!$V93*Q$13 -> 0 | R93: =ННСболее2200!$W93*Q$13 -> 0 | S93: =Оценочная!$V93*S$13 -> 0 | T93: =Оценочная!$W93*S$13 -> 0 | U93: ='ННСЮра>800'!$V93*U$13 -> 0 | V93: ='ННСЮра>800'!$W93*U$13 -> 0 | W93: ='ГС пил'!V93*$W$13 -> 0 | X93: ='ГС пил'!W93*$W$13 -> 0 | Y93: ='ГС без пил'!$V93*Y$13 -> 6 | Z93: ='ГС без пил'!$W93*Y$13 -> 24127379 | AA93: ='ГС пил МСГРП'!$V93*AA$13 -> 0 | AB93: ='ГС пил МСГРП'!$W93*AA$13 -> 0 | AC93: ='ГСЮра пил'!$V93*AC$13 -> 0 | AD93: ='ГСЮра пил'!$W93*AC$13 -> 0 | AE93: ='ГСЮра без пил'!$V93*AE$13 -> 0 | AF93: ='ГСЮра без пил'!$W93*AE$13 -> 0 | AG93: ='ГСЮра пил МСГРП'!$V93*AG$13 -> 0 | AH93: ='ГСЮра пил МСГРП'!$W93*AG$13 -> 0 | AI93: =ВЗ!$V93*AI$13 -> 0 | AJ93: =ВЗ!$W93*AI$13 -> 0 | AK93: ='Посл. скв'!$V93*AK$13 -> 1 | AL93: ='Посл. скв'!$W93*AK$13 -> 5521715.7 | AM93: =AK93+AI93+AG93+AE93+AC93+AA93+Y93+W93+U93+S93+Q93+M93+O93+K93+I93+G93 -> 8 | AN93: =AL93+AJ93+AH93+AF93+AD93+AB93+Z93+X93+V93+T93+R93+N93+P93+L93+J93+H93 -> 35170811 | AO93: =('[8]Куст №40А'!$AD$1612)*1000 -> 0 | AP93: =AO93-AN93 -> -35170811 | AR93: =AS93-AN93 -> 0 | AS93: 35170811
C94: ПОДРЯДЧИК ПО ЦЕМЕНТИРОВАНИЮ: | AR94: =AS94-AN94 -> 0
C95: ='Перв. скв '!C95 -> 0 | D95: Описание работ/услуг | AN95: 0 | AR95: =AS95-AN95 -> 0 | AS95: 0
C96: 426 | D96: ='Перв. скв '!D96 -> Цементирование направления НН 426 мм (услуги, цемент, материалы) | E96: ='Перв. скв '!E96 -> 0 | F96: ='Перв. скв '!F96 -> опер | G96: ='Перв. скв '!$V96*G$13 -> 1 | H96: ='Перв. скв '!$W96*G$13 -> 261088 | I96: =ННСдо1300!$V96*I$13 -> 0 | J96: =ННСдо1300!$W96*I$13 -> 0 | K96: =ННСот1300до1500!$V96*K$13 -> 0 | L96: =ННСот1300до1500!$W96*K$13 -> 0 | M96: =ННСот1500до2000!$V96*M$13 -> 0 | N96: =ННСот1500до2000!$W96*M$13 -> 0 | O96: =ННСот2000до2200!$V96*O$13 -> 0 | P96: =ННСот2000до2200!$W96*O$13 -> 0 | Q96: =ННСболее2200!$V96*Q$13 -> 0 | R96: =ННСболее2200!$W96*Q$13 -> 0 | S96: =Оценочная!$V96*S$13 -> 0 | T96: =Оценочная!$W96*S$13 -> 0 | U96: ='ННСЮра>800'!$V96*U$13 -> 0 | V96: ='ННСЮра>800'!$W96*U$13 -> 0 | W96: ='ГС пил'!V96*$W$13 -> 0 | X96: ='ГС пил'!W96*$W$13 -> 0 | Y96: ='ГС без пил'!$V96*Y$13 -> 6 | Z96: ='ГС без пил'!$W96*Y$13 -> 1566528 | AA96: ='ГС пил МСГРП'!$V96*AA$13 -> 0 | AB96: ='ГС пил МСГРП'!$W96*AA$13 -> 0 | AC96: ='ГСЮра пил'!$V96*AC$13 -> 0 | AD96: ='ГСЮра пил'!$W96*AC$13 -> 0 | AE96: ='ГСЮра без пил'!$V96*AE$13 -> 0 | AF96: ='ГСЮра без пил'!$W96*AE$13 -> 0 | AG96: ='ГСЮра пил МСГРП'!$V96*AG$13 -> 0 | AH96: ='ГСЮра пил МСГРП'!$W96*AG$13 -> 0 | AI96: =ВЗ!$V96*AI$13 -> 0 | AJ96: =ВЗ!$W96*AI$13 -> 0 | AK96: ='Посл. скв'!$V96*AK$13 -> 1 | AL96: ='Посл. скв'!$W96*AK$13 -> 261088 | AM96: =AK96+AI96+AG96+AE96+AC96+AA96+Y96+W96+U96+S96+Q96+M96+O96+K96+I96+G96 -> 8 | AN96: =AL96+AJ96+AH96+AF96+AD96+AB96+Z96+X96+V96+T96+R96+N96+P96+L96+J96+H96 -> 2088704 | AO96: =('[8]Куст №40А'!$AD$1834)*1000 -> 1645000 | AP96: ='[8]Куст №40А'!$AD$2110*1000 -> 21233931 | AR96: =AS96-AN96 -> 0 | AS96: 2088704
C97: 324 | D97: ='Перв. скв '!D97 -> Цементирование кондуктора НН 324 мм (услуги, цемент, материалы) | E97: ='Перв. скв '!E97 -> 0 | F97: ='Перв. скв '!F97 -> опер | G97: ='Перв. скв '!$V97*G$13 -> 1 | H97: ='Перв. скв '!$W97*G$13 -> 450018 | I97: =ННСдо1300!$V97*I$13 -> 0 | J97: =ННСдо1300!$W97*I$13 -> 0 | K97: =ННСот1300до1500!$V97*K$13 -> 0 | L97: =ННСот1300до1500!$W97*K$13 -> 0 | M97: =ННСот1500до2000!$V97*M$13 -> 0 | N97: =ННСот1500до2000!$W97*M$13 -> 0 | O97: =ННСот2000до2200!$V97*O$13 -> 0 | P97: =ННСот2000до2200!$W97*O$13 -> 0 | Q97: =ННСболее2200!$V97*Q$13 -> 0 | R97: =ННСболее2200!$W97*Q$13 -> 0 | S97: =Оценочная!$V97*S$13 -> 0 | T97: =Оценочная!$W97*S$13 -> 0 | U97: ='ННСЮра>800'!$V97*U$13 -> 0 | V97: ='ННСЮра>800'!$W97*U$13 -> 0 | W97: ='ГС пил'!V97*$W$13 -> 0 | X97: ='ГС пил'!W97*$W$13 -> 0 | Y97: ='ГС без пил'!$V97*Y$13 -> 6 | Z97: ='ГС без пил'!$W97*Y$13 -> 2700108 | AA97: ='ГС пил МСГРП'!$V97*AA$13 -> 0 | AB97: ='ГС пил МСГРП'!$W97*AA$13 -> 0 | AC97: ='ГСЮра пил'!$V97*AC$13 -> 0 | AD97: ='ГСЮра пил'!$W97*AC$13 -> 0 | AE97: ='ГСЮра без пил'!$V97*AE$13 -> 0 | AF97: ='ГСЮра без пил'!$W97*AE$13 -> 0 | AG97: ='ГСЮра пил МСГРП'!$V97*AG$13 -> 0 | AH97: ='ГСЮра пил МСГРП'!$W97*AG$13 -> 0 | AI97: =ВЗ!$V97*AI$13 -> 0 | AJ97: =ВЗ!$W97*AI$13 -> 0 | AK97: ='Посл. скв'!$V97*AK$13 -> 1 | AL97: ='Посл. скв'!$W97*AK$13 -> 450018 | AM97: =AK97+AI97+AG97+AE97+AC97+AA97+Y97+W97+U97+S97+Q97+M97+O97+K97+I97+G97 -> 8 | AN97: =AL97+AJ97+AH97+AF97+AD97+AB97+Z97+X97+V97+T97+R97+N97+P97+L97+J97+H97 -> 3600144 | AO97: =('[8]Куст №40А'!$AD$1835)*1000 -> 3745000 | AP97: =SUM(AN96:AN111) -> 18043908 | AR97: =AS97-AN97 -> 0 | AS97: 3600144
C98: 245 | D98: ='Перв. скв '!D98 -> Цементирование технической колонны Гор 245 мм (услуги, цемент, материалы) | E98: ='Перв. скв '!E98 -> 0 | F98: ='Перв. скв '!F98 -> опер | G98: ='Перв. скв '!$V98*G$13 -> 0 | H98: ='Перв. скв '!$W98*G$13 -> 0 | I98: =ННСдо1300!$V98*I$13 -> 0 | J98: =ННСдо1300!$W98*I$13 -> 0 | K98: =ННСот1300до1500!$V98*K$13 -> 0 | L98: =ННСот1300до1500!$W98*K$13 -> 0 | M98: =ННСот1500до2000!$V98*M$13 -> 0 | N98: =ННСот1500до2000!$W98*M$13 -> 0 | O98: =ННСот2000до2200!$V98*O$13 -> 0 | P98: =ННСот2000до2200!$W98*O$13 -> 0 | Q98: =ННСболее2200!$V98*Q$13 -> 0 | R98: =ННСболее2200!$W98*Q$13 -> 0 | S98: =Оценочная!$V98*S$13 -> 0 | T98: =Оценочная!$W98*S$13 -> 0 | U98: ='ННСЮра>800'!$V98*U$13 -> 0 | V98: ='ННСЮра>800'!$W98*U$13 -> 0 | W98: ='ГС пил'!V98*$W$13 -> 0 | X98: ='ГС пил'!W98*$W$13 -> 0 | Y98: ='ГС без пил'!$V98*Y$13 -> 0 | Z98: ='ГС без пил'!$W98*Y$13 -> 0 | AA98: ='ГС пил МСГРП'!$V98*AA$13 -> 0 | AB98: ='ГС пил МСГРП'!$W98*AA$13 -> 0 | AC98: ='ГСЮра пил'!$V98*AC$13 -> 0 | AD98: ='ГСЮра пил'!$W98*AC$13 -> 0 | AE98: ='ГСЮра без пил'!$V98*AE$13 -> 0 | AF98: ='ГСЮра без пил'!$W98*AE$13 -> 0 | AG98: ='ГСЮра пил МСГРП'!$V98*AG$13 -> 0 | AH98: ='ГСЮра пил МСГРП'!$W98*AG$13 -> 0 | AI98: =ВЗ!$V98*AI$13 -> 0 | AJ98: =ВЗ!$W98*AI$13 -> 0 | AK98: ='Посл. скв'!$V98*AK$13 -> 0 | AL98: ='Посл. скв'!$W98*AK$13 -> 0 | AM98: =AK98+AI98+AG98+AE98+AC98+AA98+Y98+W98+U98+S98+Q98+M98+O98+K98+I98+G98 -> 0 | AN98: =AL98+AJ98+AH98+AF98+AD98+AB98+Z98+X98+V98+T98+R98+N98+P98+L98+J98+H98 -> 0 | AP98: =AP97=AP96 -> FALSE | AR98: =AS98-AN98 -> 0 | AS98: 0
C99: 178 | D99: ='Перв. скв '!D99 -> Цементирование эксплуатационной колонны 178мм (услуги, цемент, материалы) | E99: ='Перв. скв '!E99 -> 0 | F99: ='Перв. скв '!F99 -> опер | G99: ='Перв. скв '!$V99*G$13 -> 1 | H99: ='Перв. скв '!$W99*G$13 -> 1433230 | I99: =ННСдо1300!$V99*I$13 -> 0 | J99: =ННСдо1300!$W99*I$13 -> 0 | K99: =ННСот1300до1500!$V99*K$13 -> 0 | L99: =ННСот1300до1500!$W99*K$13 -> 0 | M99: =ННСот1500до2000!$V99*M$13 -> 0 | N99: =ННСот1500до2000!$W99*M$13 -> 0 | O99: =ННСот2000до2200!$V99*O$13 -> 0 | P99: =ННСот2000до2200!$W99*O$13 -> 0 | Q99: =ННСболее2200!$V99*Q$13 -> 0 | R99: =ННСболее2200!$W99*Q$13 -> 0 | S99: =Оценочная!$V99*S$13 -> 0 | T99: =Оценочная!$W99*S$13 -> 0 | U99: ='ННСЮра>800'!$V99*U$13 -> 0 | V99: ='ННСЮра>800'!$W99*U$13 -> 0 | W99: ='ГС пил'!V99*$W$13 -> 0 | X99: ='ГС пил'!W99*$W$13 -> 0 | Y99: ='ГС без пил'!$V99*Y$13 -> 6 | Z99: ='ГС без пил'!$W99*Y$13 -> 8599380 | AA99: ='ГС пил МСГРП'!$V99*AA$13 -> 0 | AB99: ='ГС пил МСГРП'!$W99*AA$13 -> 0 | AC99: ='ГСЮра пил'!$V99*AC$13 -> 0 | AD99: ='ГСЮра пил'!$W99*AC$13 -> 0 | AE99: ='ГСЮра без пил'!$V99*AE$13 -> 0 | AF99: ='ГСЮра без пил'!$W99*AE$13 -> 0 | AG99: ='ГСЮра пил МСГРП'!$V99*AG$13 -> 0 | AH99: ='ГСЮра пил МСГРП'!$W99*AG$13 -> 0 | AI99: =ВЗ!$V99*AI$13 -> 0 | AJ99: =ВЗ!$W99*AI$13 -> 0 | AK99: ='Посл. скв'!$V99*AK$13 -> 1 | AL99: ='Посл. скв'!$W99*AK$13 -> 1433230 | AM99: =AK99+AI99+AG99+AE99+AC99+AA99+Y99+W99+U99+S99+Q99+M99+O99+K99+I99+G99 -> 8 | AN99: =AL99+AJ99+AH99+AF99+AD99+AB99+Z99+X99+V99+T99+R99+N99+P99+L99+J99+H99 -> 11465840 | AO99: =('[8]Куст №40А'!$AD$1837)*1000 -> 8575000 | AR99: =AS99-AN99 -> 0 | AS99: 11465840
D100: ='Перв. скв '!D100 -> Цементирование направления НН 324 мм (услуги, цемент, материалы) | E100: ='Перв. скв '!E100 -> 0 | F100: ='Перв. скв '!F100 -> опер | G100: ='Перв. скв '!$V100*G$13 -> 0 | H100: ='Перв. скв '!$W100*G$13 -> 0 | I100: =ННСдо1300!$V100*I$13 -> 0 | J100: =ННСдо1300!$W100*I$13 -> 0 | K100: =ННСот1300до1500!$V100*K$13 -> 0 | L100: =ННСот1300до1500!$W100*K$13 -> 0 | M100: =ННСот1500до2000!$V100*M$13 -> 0 | N100: =ННСот1500до2000!$W100*M$13 -> 0 | O100: =ННСот2000до2200!$V100*O$13 -> 0 | P100: =ННСот2000до2200!$W100*O$13 -> 0 | Q100: =ННСболее2200!$V100*Q$13 -> 0 | R100: =ННСболее2200!$W100*Q$13 -> 0 | S100: =Оценочная!$V100*S$13 -> 0 | T100: =Оценочная!$W100*S$13 -> 0 | U100: ='ННСЮра>800'!$V100*U$13 -> 0 | V100: ='ННСЮра>800'!$W100*U$13 -> 0 | W100: ='ГС пил'!V100*$W$13 -> 0 | X100: ='ГС пил'!W100*$W$13 -> 0 | Y100: ='ГС без пил'!$V100*Y$13 -> 0 | Z100: ='ГС без пил'!$W100*Y$13 -> 0 | AA100: ='ГС пил МСГРП'!$V100*AA$13 -> 0 | AB100: ='ГС пил МСГРП'!$W100*AA$13 -> 0 | AC100: ='ГСЮра пил'!$V100*AC$13 -> 0 | AD100: ='ГСЮра пил'!$W100*AC$13 -> 0 | AE100: ='ГСЮра без пил'!$V100*AE$13 -> 0 | AF100: ='ГСЮра без пил'!$W100*AE$13 -> 0 | AG100: ='ГСЮра пил МСГРП'!$V100*AG$13 -> 0 | AH100: ='ГСЮра пил МСГРП'!$W100*AG$13 -> 0 | AI100: =ВЗ!$V100*AI$13 -> 0 | AJ100: =ВЗ!$W100*AI$13 -> 0 | AK100: ='Посл. скв'!$V100*AK$13 -> 0 | AL100: ='Посл. скв'!$W100*AK$13 -> 0 | AM100: =AK100+AI100+AG100+AE100+AC100+AA100+Y100+W100+U100+S100+Q100+M100+O100+K100+I100+G100 -> 0 | AN100: =AL100+AJ100+AH100+AF100+AD100+AB100+Z100+X100+V100+T100+R100+N100+P100+L100+J100+H100 -> 0 | AR100: =AS100-AN100 -> 0 | AS100: 0
D101: ='Перв. скв '!D101 -> Цементирование кондуктора НН 245 мм (услуги, цемент, материалы) | E101: ='Перв. скв '!E101 -> 0 | F101: ='Перв. скв '!F101 -> опер | G101: ='Перв. скв '!$V101*G$13 -> 0 | H101: ='Перв. скв '!$W101*G$13 -> 0 | I101: =ННСдо1300!$V101*I$13 -> 0 | J101: =ННСдо1300!$W101*I$13 -> 0 | K101: =ННСот1300до1500!$V101*K$13 -> 0 | L101: =ННСот1300до1500!$W101*K$13 -> 0 | M101: =ННСот1500до2000!$V101*M$13 -> 0 | N101: =ННСот1500до2000!$W101*M$13 -> 0 | O101: =ННСот2000до2200!$V101*O$13 -> 0 | P101: =ННСот2000до2200!$W101*O$13 -> 0 | Q101: =ННСболее2200!$V101*Q$13 -> 0 | R101: =ННСболее2200!$W101*Q$13 -> 0 | S101: =Оценочная!$V101*S$13 -> 0 | T101: =Оценочная!$W101*S$13 -> 0 | U101: ='ННСЮра>800'!$V101*U$13 -> 0 | V101: ='ННСЮра>800'!$W101*U$13 -> 0 | W101: ='ГС пил'!V101*$W$13 -> 0 | X101: ='ГС пил'!W101*$W$13 -> 0 | Y101: ='ГС без пил'!$V101*Y$13 -> 0 | Z101: ='ГС без пил'!$W101*Y$13 -> 0 | AA101: ='ГС пил МСГРП'!$V101*AA$13 -> 0 | AB101: ='ГС пил МСГРП'!$W101*AA$13 -> 0 | AC101: ='ГСЮра пил'!$V101*AC$13 -> 0 | AD101: ='ГСЮра пил'!$W101*AC$13 -> 0 | AE101: ='ГСЮра без пил'!$V101*AE$13 -> 0 | AF101: ='ГСЮра без пил'!$W101*AE$13 -> 0 | AG101: ='ГСЮра пил МСГРП'!$V101*AG$13 -> 0 | AH101: ='ГСЮра пил МСГРП'!$W101*AG$13 -> 0 | AI101: =ВЗ!$V101*AI$13 -> 0 | AJ101: =ВЗ!$W101*AI$13 -> 0 | AK101: ='Посл. скв'!$V101*AK$13 -> 0 | AL101: ='Посл. скв'!$W101*AK$13 -> 0 | AM101: =AK101+AI101+AG101+AE101+AC101+AA101+Y101+W101+U101+S101+Q101+M101+O101+K101+I101+G101 -> 0 | AN101: =AL101+AJ101+AH101+AF101+AD101+AB101+Z101+X101+V101+T101+R101+N101+P101+L101+J101+H101 -> 0 | AR101: =AS101-AN101 -> 0 | AS101: 0
D102: ='Перв. скв '!D102 -> Цементирование эксплуатационной колонны НН 178мм (услуги, цемент, материалы) | E102: ='Перв. скв '!E102 -> 0 | F102: ='Перв. скв '!F102 -> опер | G102: ='Перв. скв '!$V102*G$13 -> 0 | H102: ='Перв. скв '!$W102*G$13 -> 0 | I102: =ННСдо1300!$V102*I$13 -> 0 | J102: =ННСдо1300!$W102*I$13 -> 0 | K102: =ННСот1300до1500!$V102*K$13 -> 0 | L102: =ННСот1300до1500!$W102*K$13 -> 0 | M102: =ННСот1500до2000!$V102*M$13 -> 0 | N102: =ННСот1500до2000!$W102*M$13 -> 0 | O102: =ННСот2000до2200!$V102*O$13 -> 0 | P102: =ННСот2000до2200!$W102*O$13 -> 0 | Q102: =ННСболее2200!$V102*Q$13 -> 0 | R102: =ННСболее2200!$W102*Q$13 -> 0 | S102: =Оценочная!$V102*S$13 -> 0 | T102: =Оценочная!$W102*S$13 -> 0 | U102: ='ННСЮра>800'!$V102*U$13 -> 0 | V102: ='ННСЮра>800'!$W102*U$13 -> 0 | W102: ='ГС пил'!V102*$W$13 -> 0 | X102: ='ГС пил'!W102*$W$13 -> 0 | Y102: ='ГС без пил'!$V102*Y$13 -> 0 | Z102: ='ГС без пил'!$W102*Y$13 -> 0 | AA102: ='ГС пил МСГРП'!$V102*AA$13 -> 0 | AB102: ='ГС пил МСГРП'!$W102*AA$13 -> 0 | AC102: ='ГСЮра пил'!$V102*AC$13 -> 0 | AD102: ='ГСЮра пил'!$W102*AC$13 -> 0 | AE102: ='ГСЮра без пил'!$V102*AE$13 -> 0 | AF102: ='ГСЮра без пил'!$W102*AE$13 -> 0 | AG102: ='ГСЮра пил МСГРП'!$V102*AG$13 -> 0 | AH102: ='ГСЮра пил МСГРП'!$W102*AG$13 -> 0 | AI102: =ВЗ!$V102*AI$13 -> 0 | AJ102: =ВЗ!$W102*AI$13 -> 0 | AK102: ='Посл. скв'!$V102*AK$13 -> 0 | AL102: ='Посл. скв'!$W102*AK$13 -> 0 | AM102: =AK102+AI102+AG102+AE102+AC102+AA102+Y102+W102+U102+S102+Q102+M102+O102+K102+I102+G102 -> 0 | AN102: =AL102+AJ102+AH102+AF102+AD102+AB102+Z102+X102+V102+T102+R102+N102+P102+L102+J102+H102 -> 0 | AR102: =AS102-AN102 -> 0 | AS102: 0
D103: ='Перв. скв '!D103 -> Цементирование хвостовика НН 127мм (услуги, цемент, материалы) | E103: ='Перв. скв '!E103 -> 0 | F103: ='Перв. скв '!F103 -> опер | G103: ='Перв. скв '!$V103*G$13 -> 0 | H103: ='Перв. скв '!$W103*G$13 -> 0 | I103: =ННСдо1300!$V103*I$13 -> 0 | J103: =ННСдо1300!$W103*I$13 -> 0 | K103: =ННСот1300до1500!$V103*K$13 -> 0 | L103: =ННСот1300до1500!$W103*K$13 -> 0 | M103: =ННСот1500до2000!$V103*M$13 -> 0 | N103: =ННСот1500до2000!$W103*M$13 -> 0 | O103: =ННСот2000до2200!$V103*O$13 -> 0 | P103: =ННСот2000до2200!$W103*O$13 -> 0 | Q103: =ННСболее2200!$V103*Q$13 -> 0 | R103: =ННСболее2200!$W103*Q$13 -> 0 | S103: =Оценочная!$V103*S$13 -> 0 | T103: =Оценочная!$W103*S$13 -> 0 | U103: ='ННСЮра>800'!$V103*U$13 -> 0 | V103: ='ННСЮра>800'!$W103*U$13 -> 0 | W103: ='ГС пил'!V103*$W$13 -> 0 | X103: ='ГС пил'!W103*$W$13 -> 0 | Y103: ='ГС без пил'!$V103*Y$13 -> 0 | Z103: ='ГС без пил'!$W103*Y$13 -> 0 | AA103: ='ГС пил МСГРП'!$V103*AA$13 -> 0 | AB103: ='ГС пил МСГРП'!$W103*AA$13 -> 0 | AC103: ='ГСЮра пил'!$V103*AC$13 -> 0 | AD103: ='ГСЮра пил'!$W103*AC$13 -> 0 | AE103: ='ГСЮра без пил'!$V103*AE$13 -> 0 | AF103: ='ГСЮра без пил'!$W103*AE$13 -> 0 | AG103: ='ГСЮра пил МСГРП'!$V103*AG$13 -> 0 | AH103: ='ГСЮра пил МСГРП'!$W103*AG$13 -> 0 | AI103: =ВЗ!$V103*AI$13 -> 0 | AJ103: =ВЗ!$W103*AI$13 -> 0 | AK103: ='Посл. скв'!$V103*AK$13 -> 0 | AL103: ='Посл. скв'!$W103*AK$13 -> 0 | AM103: =AK103+AI103+AG103+AE103+AC103+AA103+Y103+W103+U103+S103+Q103+M103+O103+K103+I103+G103 -> 0 | AN103: =AL103+AJ103+AH103+AF103+AD103+AB103+Z103+X103+V103+T103+R103+N103+P103+L103+J103+H103 -> 0 | AO103: =('[8]Куст №40А'!$AD$1838)*1000 -> 0 | AR103: =AS103-AN103 -> 0 | AS103: 0
D104: ='Перв. скв '!D104 -> Цементирование технической колонны НН 245 мм (услуги, цемент, материалы) | E104: ='Перв. скв '!E104 -> 0 | F104: ='Перв. скв '!F104 -> опер | G104: ='Перв. скв '!$V104*G$13 -> 0 | H104: ='Перв. скв '!$W104*G$13 -> 0 | I104: =ННСдо1300!$V104*I$13 -> 0 | J104: =ННСдо1300!$W104*I$13 -> 0 | K104: =ННСот1300до1500!$V104*K$13 -> 0 | L104: =ННСот1300до1500!$W104*K$13 -> 0 | M104: =ННСот1500до2000!$V104*M$13 -> 0 | N104: =ННСот1500до2000!$W104*M$13 -> 0 | O104: =ННСот2000до2200!$V104*O$13 -> 0 | P104: =ННСот2000до2200!$W104*O$13 -> 0 | Q104: =ННСболее2200!$V104*Q$13 -> 0 | R104: =ННСболее2200!$W104*Q$13 -> 0 | S104: =Оценочная!$V104*S$13 -> 0 | T104: =Оценочная!$W104*S$13 -> 0 | U104: ='ННСЮра>800'!$V104*U$13 -> 0 | V104: ='ННСЮра>800'!$W104*U$13 -> 0 | W104: ='ГС пил'!V104*$W$13 -> 0 | X104: ='ГС пил'!W104*$W$13 -> 0 | Y104: ='ГС без пил'!$V104*Y$13 -> 0 | Z104: ='ГС без пил'!$W104*Y$13 -> 0 | AA104: ='ГС пил МСГРП'!$V104*AA$13 -> 0 | AB104: ='ГС пил МСГРП'!$W104*AA$13 -> 0 | AC104: ='ГСЮра пил'!$V104*AC$13 -> 0 | AD104: ='ГСЮра пил'!$W104*AC$13 -> 0 | AE104: ='ГСЮра без пил'!$V104*AE$13 -> 0 | AF104: ='ГСЮра без пил'!$W104*AE$13 -> 0 | AG104: ='ГСЮра пил МСГРП'!$V104*AG$13 -> 0 | AH104: ='ГСЮра пил МСГРП'!$W104*AG$13 -> 0 | AI104: =ВЗ!$V104*AI$13 -> 0 | AJ104: =ВЗ!$W104*AI$13 -> 0 | AK104: ='Посл. скв'!$V104*AK$13 -> 0 | AL104: ='Посл. скв'!$W104*AK$13 -> 0 | AM104: =AK104+AI104+AG104+AE104+AC104+AA104+Y104+W104+U104+S104+Q104+M104+O104+K104+I104+G104 -> 0 | AN104: =AL104+AJ104+AH104+AF104+AD104+AB104+Z104+X104+V104+T104+R104+N104+P104+L104+J104+H104 -> 0 | AR104: =AS104-AN104 -> 0 | AS104: 0
D105: ='Перв. скв '!D105 -> Транспортировка цемента | E105: ='Перв. скв '!E105 -> 0 | F105: ='Перв. скв '!F105 -> опер | G105: ='Перв. скв '!$V105*G$13 -> 0 | H105: ='Перв. скв '!$W105*G$13 -> 0 | I105: =ННСдо1300!$V105*I$13 -> 0 | J105: =ННСдо1300!$W105*I$13 -> 0 | K105: =ННСот1300до1500!$V105*K$13 -> 0 | L105: =ННСот1300до1500!$W105*K$13 -> 0 | M105: =ННСот1500до2000!$V105*M$13 -> 0 | N105: =ННСот1500до2000!$W105*M$13 -> 0 | O105: =ННСот2000до2200!$V105*O$13 -> 0 | P105: =ННСот2000до2200!$W105*O$13 -> 0 | Q105: =ННСболее2200!$V105*Q$13 -> 0 | R105: =ННСболее2200!$W105*Q$13 -> 0 | S105: =Оценочная!$V105*S$13 -> 0 | T105: =Оценочная!$W105*S$13 -> 0 | U105: ='ННСЮра>800'!$V105*U$13 -> 0 | V105: ='ННСЮра>800'!$W105*U$13 -> 0 | W105: ='ГС пил'!V105*$W$13 -> 0 | X105: ='ГС пил'!W105*$W$13 -> 0 | Y105: ='ГС без пил'!$V105*Y$13 -> 0 | Z105: ='ГС без пил'!$W105*Y$13 -> 0 | AA105: ='ГС пил МСГРП'!$V105*AA$13 -> 0 | AB105: ='ГС пил МСГРП'!$W105*AA$13 -> 0 | AC105: ='ГСЮра пил'!$V105*AC$13 -> 0 | AD105: ='ГСЮра пил'!$W105*AC$13 -> 0 | AE105: ='ГСЮра без пил'!$V105*AE$13 -> 0 | AF105: ='ГСЮра без пил'!$W105*AE$13 -> 0 | AG105: ='ГСЮра пил МСГРП'!$V105*AG$13 -> 0 | AH105: ='ГСЮра пил МСГРП'!$W105*AG$13 -> 0 | AI105: =ВЗ!$V105*AI$13 -> 0 | AJ105: =ВЗ!$W105*AI$13 -> 0 | AK105: ='Посл. скв'!$V105*AK$13 -> 0 | AL105: ='Посл. скв'!$W105*AK$13 -> 0 | AM105: =AK105+AI105+AG105+AE105+AC105+AA105+Y105+W105+U105+S105+Q105+M105+O105+K105+I105+G105 -> 0 | AN105: =AL105+AJ105+AH105+AF105+AD105+AB105+Z105+X105+V105+T105+R105+N105+P105+L105+J105+H105 -> 0 | AO105: =('[8]Куст №40А'!$AD$2029)*1000 -> 562489.48 | AR105: =AS105-AN105 -> 0 | AS105: 0
D106: ='Перв. скв '!D106 -> Стоимость услуг цементировочного флота | E106: ='Перв. скв '!E106 -> 0 | F106: ='Перв. скв '!F106 -> опер | G106: ='Перв. скв '!$V106*G$13 -> 0 | H106: ='Перв. скв '!$W106*G$13 -> 0 | I106: =ННСдо1300!$V106*I$13 -> 0 | J106: =ННСдо1300!$W106*I$13 -> 0 | K106: =ННСот1300до1500!$V106*K$13 -> 0 | L106: =ННСот1300до1500!$W106*K$13 -> 0 | M106: =ННСот1500до2000!$V106*M$13 -> 0 | N106: =ННСот1500до2000!$W106*M$13 -> 0 | O106: =ННСот2000до2200!$V106*O$13 -> 0 | P106: =ННСот2000до2200!$W106*O$13 -> 0 | Q106: =ННСболее2200!$V106*Q$13 -> 0 | R106: =ННСболее2200!$W106*Q$13 -> 0 | S106: =Оценочная!$V106*S$13 -> 0 | T106: =Оценочная!$W106*S$13 -> 0 | U106: ='ННСЮра>800'!$V106*U$13 -> 0 | V106: ='ННСЮра>800'!$W106*U$13 -> 0 | W106: ='ГС пил'!V106*$W$13 -> 0 | X106: ='ГС пил'!W106*$W$13 -> 0 | Y106: ='ГС без пил'!$V106*Y$13 -> 0 | Z106: ='ГС без пил'!$W106*Y$13 -> 0 | AA106: ='ГС пил МСГРП'!$V106*AA$13 -> 0 | AB106: ='ГС пил МСГРП'!$W106*AA$13 -> 0 | AC106: ='ГСЮра пил'!$V106*AC$13 -> 0 | AD106: ='ГСЮра пил'!$W106*AC$13 -> 0 | AE106: ='ГСЮра без пил'!$V106*AE$13 -> 0 | AF106: ='ГСЮра без пил'!$W106*AE$13 -> 0 | AG106: ='ГСЮра пил МСГРП'!$V106*AG$13 -> 0 | AH106: ='ГСЮра пил МСГРП'!$W106*AG$13 -> 0 | AI106: =ВЗ!$V106*AI$13 -> 0 | AJ106: =ВЗ!$W106*AI$13 -> 0 | AK106: ='Посл. скв'!$V106*AK$13 -> 0 | AL106: ='Посл. скв'!$W106*AK$13 -> 0 | AM106: =AK106+AI106+AG106+AE106+AC106+AA106+Y106+W106+U106+S106+Q106+M106+O106+K106+I106+G106 -> 0 | AN106: =AL106+AJ106+AH106+AF106+AD106+AB106+Z106+X106+V106+T106+R106+N106+P106+L106+J106+H106 -> 0 | AR106: =AS106-AN106 -> 0 | AS106: 0
D107: ='Перв. скв '!D107 -> Стоимость оснастки | E107: ='Перв. скв '!E107 -> 0 | F107: ='Перв. скв '!F107 -> опер | G107: ='Перв. скв '!$V107*G$13 -> 0 | H107: ='Перв. скв '!$W107*G$13 -> 0 | I107: =ННСдо1300!$V107*I$13 -> 0 | J107: =ННСдо1300!$W107*I$13 -> 0 | K107: =ННСот1300до1500!$V107*K$13 -> 0 | L107: =ННСот1300до1500!$W107*K$13 -> 0 | M107: =ННСот1500до2000!$V107*M$13 -> 0 | N107: =ННСот1500до2000!$W107*M$13 -> 0 | O107: =ННСот2000до2200!$V107*O$13 -> 0 | P107: =ННСот2000до2200!$W107*O$13 -> 0 | Q107: =ННСболее2200!$V107*Q$13 -> 0 | R107: =ННСболее2200!$W107*Q$13 -> 0 | S107: =Оценочная!$V107*S$13 -> 0 | T107: =Оценочная!$W107*S$13 -> 0 | U107: ='ННСЮра>800'!$V107*U$13 -> 0 | V107: ='ННСЮра>800'!$W107*U$13 -> 0 | W107: ='ГС пил'!V107*$W$13 -> 0 | X107: ='ГС пил'!W107*$W$13 -> 0 | Y107: ='ГС без пил'!$V107*Y$13 -> 0 | Z107: ='ГС без пил'!$W107*Y$13 -> 0 | AA107: ='ГС пил МСГРП'!$V107*AA$13 -> 0 | AB107: ='ГС пил МСГРП'!$W107*AA$13 -> 0 | AC107: ='ГСЮра пил'!$V107*AC$13 -> 0 | AD107: ='ГСЮра пил'!$W107*AC$13 -> 0 | AE107: ='ГСЮра без пил'!$V107*AE$13 -> 0 | AF107: ='ГСЮра без пил'!$W107*AE$13 -> 0 | AG107: ='ГСЮра пил МСГРП'!$V107*AG$13 -> 0 | AH107: ='ГСЮра пил МСГРП'!$W107*AG$13 -> 0 | AI107: =ВЗ!$V107*AI$13 -> 0 | AJ107: =ВЗ!$W107*AI$13 -> 0 | AK107: ='Посл. скв'!$V107*AK$13 -> 0 | AL107: ='Посл. скв'!$W107*AK$13 -> 0 | AM107: =AK107+AI107+AG107+AE107+AC107+AA107+Y107+W107+U107+S107+Q107+M107+O107+K107+I107+G107 -> 0 | AN107: =AL107+AJ107+AH107+AF107+AD107+AB107+Z107+X107+V107+T107+R107+N107+P107+L107+J107+H107 -> 0 | AR107: =AS107-AN107 -> 0 | AS107: 0
D108: ='Перв. скв '!D108 -> Стоимость услуг инженерного сопровождения | E108: ='Перв. скв '!E108 -> 0 | F108: ='Перв. скв '!F108 -> опер | G108: ='Перв. скв '!$V108*G$13 -> 0 | H108: ='Перв. скв '!$W108*G$13 -> 0 | I108: =ННСдо1300!$V108*I$13 -> 0 | J108: =ННСдо1300!$W108*I$13 -> 0 | K108: =ННСот1300до1500!$V108*K$13 -> 0 | L108: =ННСот1300до1500!$W108*K$13 -> 0 | M108: =ННСот1500до2000!$V108*M$13 -> 0 | N108: =ННСот1500до2000!$W108*M$13 -> 0 | O108: =ННСот2000до2200!$V108*O$13 -> 0 | P108: =ННСот2000до2200!$W108*O$13 -> 0 | Q108: =ННСболее2200!$V108*Q$13 -> 0 | R108: =ННСболее2200!$W108*Q$13 -> 0 | S108: =Оценочная!$V108*S$13 -> 0 | T108: =Оценочная!$W108*S$13 -> 0 | U108: ='ННСЮра>800'!$V108*U$13 -> 0 | V108: ='ННСЮра>800'!$W108*U$13 -> 0 | W108: ='ГС пил'!V108*$W$13 -> 0 | X108: ='ГС пил'!W108*$W$13 -> 0 | Y108: ='ГС без пил'!$V108*Y$13 -> 0 | Z108: ='ГС без пил'!$W108*Y$13 -> 0 | AA108: ='ГС пил МСГРП'!$V108*AA$13 -> 0 | AB108: ='ГС пил МСГРП'!$W108*AA$13 -> 0 | AC108: ='ГСЮра пил'!$V108*AC$13 -> 0 | AD108: ='ГСЮра пил'!$W108*AC$13 -> 0 | AE108: ='ГСЮра без пил'!$V108*AE$13 -> 0 | AF108: ='ГСЮра без пил'!$W108*AE$13 -> 0 | AG108: ='ГСЮра пил МСГРП'!$V108*AG$13 -> 0 | AH108: ='ГСЮра пил МСГРП'!$W108*AG$13 -> 0 | AI108: =ВЗ!$V108*AI$13 -> 0 | AJ108: =ВЗ!$W108*AI$13 -> 0 | AK108: ='Посл. скв'!$V108*AK$13 -> 0 | AL108: ='Посл. скв'!$W108*AK$13 -> 0 | AM108: =AK108+AI108+AG108+AE108+AC108+AA108+Y108+W108+U108+S108+Q108+M108+O108+K108+I108+G108 -> 0 | AN108: =AL108+AJ108+AH108+AF108+AD108+AB108+Z108+X108+V108+T108+R108+N108+P108+L108+J108+H108 -> 0 | AR108: =AS108-AN108 -> 0 | AS108: 0
D109: ='Перв. скв '!D109 -> Стоимость услуг цементировочного флота | E109: ='Перв. скв '!E109 -> 0 | F109: ='Перв. скв '!F109 -> опер | G109: ='Перв. скв '!$V109*G$13 -> 0 | H109: ='Перв. скв '!$W109*G$13 -> 0 | I109: =ННСдо1300!$V109*I$13 -> 0 | J109: =ННСдо1300!$W109*I$13 -> 0 | K109: =ННСот1300до1500!$V109*K$13 -> 0 | L109: =ННСот1300до1500!$W109*K$13 -> 0 | M109: =ННСот1500до2000!$V109*M$13 -> 0 | N109: =ННСот1500до2000!$W109*M$13 -> 0 | O109: =ННСот2000до2200!$V109*O$13 -> 0 | P109: =ННСот2000до2200!$W109*O$13 -> 0 | Q109: =ННСболее2200!$V109*Q$13 -> 0 | R109: =ННСболее2200!$W109*Q$13 -> 0 | S109: =Оценочная!$V109*S$13 -> 0 | T109: =Оценочная!$W109*S$13 -> 0 | U109: ='ННСЮра>800'!$V109*U$13 -> 0 | V109: ='ННСЮра>800'!$W109*U$13 -> 0 | W109: ='ГС пил'!V109*$W$13 -> 0 | X109: ='ГС пил'!W109*$W$13 -> 0 | Y109: ='ГС без пил'!$V109*Y$13 -> 0 | Z109: ='ГС без пил'!$W109*Y$13 -> 0 | AA109: ='ГС пил МСГРП'!$V109*AA$13 -> 0 | AB109: ='ГС пил МСГРП'!$W109*AA$13 -> 0 | AC109: ='ГСЮра пил'!$V109*AC$13 -> 0 | AD109: ='ГСЮра пил'!$W109*AC$13 -> 0 | AE109: ='ГСЮра без пил'!$V109*AE$13 -> 0 | AF109: ='ГСЮра без пил'!$W109*AE$13 -> 0 | AG109: ='ГСЮра пил МСГРП'!$V109*AG$13 -> 0 | AH109: ='ГСЮра пил МСГРП'!$W109*AG$13 -> 0 | AI109: =ВЗ!$V109*AI$13 -> 0 | AJ109: =ВЗ!$W109*AI$13 -> 0 | AK109: ='Посл. скв'!$V109*AK$13 -> 0 | AL109: ='Посл. скв'!$W109*AK$13 -> 0 | AM109: =AK109+AI109+AG109+AE109+AC109+AA109+Y109+W109+U109+S109+Q109+M109+O109+K109+I109+G109 -> 0 | AN109: =AL109+AJ109+AH109+AF109+AD109+AB109+Z109+X109+V109+T109+R109+N109+P109+L109+J109+H109 -> 0 | AR109: =AS109-AN109 -> 0 | AS109: 0
D110: ='Перв. скв '!D110 -> Стоимость оснастки | E110: ='Перв. скв '!E110 -> 0 | F110: ='Перв. скв '!F110 -> опер | G110: ='Перв. скв '!$V110*G$13 -> 0 | H110: ='Перв. скв '!$W110*G$13 -> 0 | I110: =ННСдо1300!$V110*I$13 -> 0 | J110: =ННСдо1300!$W110*I$13 -> 0 | K110: =ННСот1300до1500!$V110*K$13 -> 0 | L110: =ННСот1300до1500!$W110*K$13 -> 0 | M110: =ННСот1500до2000!$V110*M$13 -> 0 | N110: =ННСот1500до2000!$W110*M$13 -> 0 | O110: =ННСот2000до2200!$V110*O$13 -> 0 | P110: =ННСот2000до2200!$W110*O$13 -> 0 | Q110: =ННСболее2200!$V110*Q$13 -> 0 | R110: =ННСболее2200!$W110*Q$13 -> 0 | S110: =Оценочная!$V110*S$13 -> 0 | T110: =Оценочная!$W110*S$13 -> 0 | U110: ='ННСЮра>800'!$V110*U$13 -> 0 | V110: ='ННСЮра>800'!$W110*U$13 -> 0 | W110: ='ГС пил'!V110*$W$13 -> 0 | X110: ='ГС пил'!W110*$W$13 -> 0 | Y110: ='ГС без пил'!$V110*Y$13 -> 0 | Z110: ='ГС без пил'!$W110*Y$13 -> 0 | AA110: ='ГС пил МСГРП'!$V110*AA$13 -> 0 | AB110: ='ГС пил МСГРП'!$W110*AA$13 -> 0 | AC110: ='ГСЮра пил'!$V110*AC$13 -> 0 | AD110: ='ГСЮра пил'!$W110*AC$13 -> 0 | AE110: ='ГСЮра без пил'!$V110*AE$13 -> 0 | AF110: ='ГСЮра без пил'!$W110*AE$13 -> 0 | AG110: ='ГСЮра пил МСГРП'!$V110*AG$13 -> 0 | AH110: ='ГСЮра пил МСГРП'!$W110*AG$13 -> 0 | AI110: =ВЗ!$V110*AI$13 -> 0 | AJ110: =ВЗ!$W110*AI$13 -> 0 | AK110: ='Посл. скв'!$V110*AK$13 -> 0 | AL110: ='Посл. скв'!$W110*AK$13 -> 0 | AM110: =AK110+AI110+AG110+AE110+AC110+AA110+Y110+W110+U110+S110+Q110+M110+O110+K110+I110+G110 -> 0 | AN110: =AL110+AJ110+AH110+AF110+AD110+AB110+Z110+X110+V110+T110+R110+N110+P110+L110+J110+H110 -> 0 | AR110: =AS110-AN110 -> 0 | AS110: 0
C111: ЦЕМ.мост | D111: ='Перв. скв '!D111 -> Установка цем моста | E111: ='Перв. скв '!E111 -> 0 | F111: ='Перв. скв '!F111 -> опер | G111: ='Перв. скв '!$V111*G$13 -> 1 | H111: ='Перв. скв '!$W111*G$13 -> 444610 | I111: =ННСдо1300!$V111*I$13 -> 0 | J111: =ННСдо1300!$W111*I$13 -> 0 | K111: =ННСот1300до1500!$V111*K$13 -> 0 | L111: =ННСот1300до1500!$W111*K$13 -> 0 | M111: =ННСот1500до2000!$V111*M$13 -> 0 | N111: =ННСот1500до2000!$W111*M$13 -> 0 | O111: =ННСот2000до2200!$V111*O$13 -> 0 | P111: =ННСот2000до2200!$W111*O$13 -> 0 | Q111: =ННСболее2200!$V111*Q$13 -> 0 | R111: =ННСболее2200!$W111*Q$13 -> 0 | S111: =Оценочная!$V111*S$13 -> 0 | T111: =Оценочная!$W111*S$13 -> 0 | U111: ='ННСЮра>800'!$V111*U$13 -> 0 | V111: ='ННСЮра>800'!$W111*U$13 -> 0 | W111: ='ГС пил'!V111*$W$13 -> 0 | X111: ='ГС пил'!W111*$W$13 -> 0 | Y111: ='ГС без пил'!$V111*Y$13 -> 0 | Z111: ='ГС без пил'!$W111*Y$13 -> 0 | AA111: ='ГС пил МСГРП'!$V111*AA$13 -> 0 | AB111: ='ГС пил МСГРП'!$W111*AA$13 -> 0 | AC111: ='ГСЮра пил'!$V111*AC$13 -> 0 | AD111: ='ГСЮра пил'!$W111*AC$13 -> 0 | AE111: ='ГСЮра без пил'!$V111*AE$13 -> 0 | AF111: ='ГСЮра без пил'!$W111*AE$13 -> 0 | AG111: ='ГСЮра пил МСГРП'!$V111*AG$13 -> 0 | AH111: ='ГСЮра пил МСГРП'!$W111*AG$13 -> 0 | AI111: =ВЗ!$V111*AI$13 -> 0 | AJ111: =ВЗ!$W111*AI$13 -> 0 | AK111: ='Посл. скв'!$V111*AK$13 -> 1 | AL111: ='Посл. скв'!$W111*AK$13 -> 444610 | AM111: =AK111+AI111+AG111+AE111+AC111+AA111+Y111+W111+U111+S111+Q111+M111+O111+K111+I111+G111 -> 2 | AN111: =AL111+AJ111+AH111+AF111+AD111+AB111+Z111+X111+V111+T111+R111+N111+P111+L111+J111+H111 -> 889220 | AO111: ='[8]Куст №40А'!$AD$1839*1000 -> 0 | AR111: =AS111-AN111 -> 0 | AS111: 889220
...

Sheet Перв. скв 
A2: ПОДРОБНАЯ СМЕТНАЯ СТОИМОСТЬ СКВАЖИНЫ
C4: Месторождение/ куст: | D4: Приобского_ месторождения | E4: ВСЕГО СТ-ТЬ | F4: Исходные данные | H4: Перед забуркой | I4: Направление | J4: Кондуктор | K4: Техническая колонна | L4: Эксплуат-ая колонна | M4: Крепление колонн | N4: Хвостовик | O4: ВСЕГО БУРЕНИЕ | P4: Исходные данные | R4: ВСЕГО ОСВОЕНИЕ
C5: Подрядчик по бурению: | D5: не определен | E5: =IF(($L$45+$L$46+$L$47+$L$48+$L$49+$L$50)>0,$D$214,0) -> 1.3238393e+08
C6: Тип буровой установки: | D6: БУ-3000 ЭУК | E6: Всего ВМР | F6: Время бурения секции, сут: | I6: 1 | J6: 4 | L6: 21 | M6: 3 | N6: 16 | O6: =SUM(I6:N6) -> 45 | P6: Время освоения, сут: | R6: =R8+R9+R10 -> 19
C7: Тип скважины: | D7: Горизонт | E7: =IF(($L$45+$L$46+$L$47+$L$48+$L$49+$L$50)>0,$W$41,0) -> 25714124 | F7: Глубина (по стволу), м: | I7: 120 | J7: 1250 | L7: 3200 | N7: 4100 | O7: ВСЕГО ПРОХОДКА | P7: В т.ч.время работы бригад КРС
C8: Проходка всего (м): | D8: 5500 | E8: Всего Бурение | F8: Диаметр долота, мм: | I8: 393 | J8: 300 | L8: 220 | N8: 155.6 | P8: - ПЗР к ГРП/МСГРП, сут. | R8: 11
C9: Наличие СВП: | D9: да | E9: =IF(($L$45+$L$46+$L$47+$L$48+$L$49+$L$50)>0,$W$190,0) -> 69765317 | F9: Диаметр колонны, мм: | I9: 324 | J9: 245 | L9: 178 | N9: 114 | O9: =D8 -> 5500 | P9: - проведение ГРП/МСГРП, сут. | R9: 1
C10: Наличие АИЭС: | D10: нет | E10: Всего Освоение | F10: Исходные данные | H10: Отход | I10: Пилот ГС | J10: Перебур | K10: Гориз.уч. 1 | L10: Гориз.уч. 2 | M10: Керн | O10: ГЛУБИНА ПО ВЕРТ-ЛИ | P10: - проведение ГНКТ, сут. | R10: 7
C11: Наличие автономности: | D11: нет | E11: =IF(($L$45+$L$46+$L$47+$L$48+$L$49+$L$50)>0,$W$206,0) -> 36904487 | F11: Отдельные стволы, керн, м: | P11: - кол-во стадий МСГРП, шт. | R11: 6
C12: Кол-во обсадных колонн (включая направл.): | D12: 4 | E12: Обор-ие устья | F12: Примечание: | P12: Примечание:
C13: Прочие существенные условия: | E13: =IF(($L$45+$L$46+$L$47+$L$48+$L$49+$L$50)>0,$W$212,0) -> 0
A15: ОПИСАНИЕ РАБОТ И УСЛУГ | H15: КОЛИЧЕСТВО | O15: СТОИМОСТЬ | V15: ВСЕГО
A16: КОД | B16: добавочный код | C16: СТАТЬЯ ЗАТРАТ | D16: ОПИСАНИЕ | E16: Подрядчик | F16: Единица измерения | G16: Руб. / Ед.изм. | H16: ПЗР (в т.ч. ВМР и осв.) | I16: =+I4 -> Направление | J16: =+J4 -> Кондуктор | K16: =+K4 -> Техническая колонна | L16: =+L4 -> Эксплуат-ая колонна | M16: Крепление колонн | N16: =+N4 -> Хвостовик | O16: ПЗР (в т.ч. ВМР и осв.) | P16: =+I16 -> Направление | Q16: =+J16 -> Кондуктор | R16: =+K16 -> Техническая колонна | S16: =+L16 -> Эксплуат-ая колонна | T16: Крепление колонн | U16: =+N16 -> Хвостовик | V16: Количество | W16: Стоимость (руб) | X16: ВСЕГО СТОИМОСТЬ
C18: 1. ЭТАП ВМР | X18: =SUM(W20:W40) -> 25714124
C19: =D5 -> не определен | D19: Описание работ/услуг
D20: Монтаж | E20: =D$5 -> не определен | F20: опер. | G20: 9401938 | H20: 1 | O20: =H20*G20 -> 9401938 | V20: =SUM(H20:N20) -> 1 | W20: =SUM(O20:U20) -> 9401938
D21: Демонтаж | E21: =D$5 -> не определен | F21: опер. | G21: 2344149 | O21: =H21*G21 -> 0 | V21: =SUM(H21:N21) -> 0 | W21: =SUM(O21:U21) -> 0
D22: Эксплуатация АВЭС | E22: =D$5 -> не определен | F22: опер. | G22: 0 | O22: =H22*G22 -> 0 | V22: =SUM(H22:N22) -> 0 | W22: =SUM(O22:U22) -> 0
D23: Передислокация БУ в пределах м-я | E23: =D$5 -> не определен | F23: опер. | G23: 693236 | O23: =H23*G23 -> 0 | V23: =SUM(H23:N23) -> 0 | W23: =SUM(O23:U23) -> 0
D24: Передислокация БУ 250-500 км. | E24: =D$5 -> не определен | F24: опер. | G24: 9837322 | H24: 1 | O24: =H24*G24 -> 9837322 | V24: =SUM(H24:N24) -> 1 | W24: =SUM(O24:U24) -> 9837322
D25: Передислокация бр. бур в пределах м-я | E25: =D$5 -> не определен | F25: опер. | G25: 130867 | O25: =H25*G25 -> 0 | V25: =SUM(H25:N25) -> 0 | W25: =SUM(O25:U25) -> 0
D26: Передислокация бр. бур 250-500 км. | E26: =D$5 -> не определен | F26: опер. | G26: 1788526 | H26: 1 | O26: =H26*G26 -> 1788526 | V26: =SUM(H26:N26) -> 1 | W26: =SUM(O26:U26) -> 1788526
D27: Передислокация бригады ВМР в пределах м-я | E27: =D$5 -> не определен | F27: опер. | G27: 130867 | O27: =H27*G27 -> 0 | V27: =SUM(H27:N27) -> 0 | W27: =SUM(O27:U27) -> 0
D28: Передислокация бригады ВМР 250-500 км. | E28: =D$5 -> не определен | F28: опер. | G28: 1788526 | H28: 2 | O28: =H28*G28 -> 3577052 | V28: =SUM(H28:N28) -> 2 | W28: =SUM(O28:U28) -> 3577052
D29: Передвижка 5 м. | E29: =D$5 -> не определен | F29: опер. | G29: 244497 | O29: =H29*G29 -> 0 | V29: =SUM(H29:N29) -> 0 | W29: =SUM(O29:U29) -> 0
D30: Передвижка 9 м. | E30: =D$5 -> не определен | F30: опер. | G30: 265365 | O30: =H30*G30 -> 0 | V30: =SUM(H30:N30) -> 0 | W30: =SUM(O30:U30) -> 0
D31: Передвижка 18 м. | E31: =D$5 -> не определен | F31: опер. | G31: 406328 | O31: =H31*G31 -> 0 | V31: =SUM(H31:N31) -> 0 | W31: =SUM(O31:U31) -> 0
D32: Передвижка 25 м. | E32: =D$5 -> не определен | F32: опер. | G32: 462462 | O32: =H32*G32 -> 0 | V32: =SUM(H32:N32) -> 0 | W32: =SUM(O32:U32) -> 0
D33: Передвижка 50 м. | E33: =D$5 -> не определен | F33: опер. | G33: 889289 | O33: =H33*G33 -> 0 | V33: =SUM(H33:N33) -> 0 | W33: =SUM(O33:U33) -> 0
D34: Сдвижка 25 м. | E34: =D$5 -> не определен | F34: опер. | G34: 291019 | O34: =H34*G34 -> 0 | V34: =SUM(H34:N34) -> 0 | W34: =SUM(O34:U34) -> 0
D35: Пуско-наладочные работы | E35: =D$5 -> не определен | F35: опер. | G35: 633406 | H35: 1 | O35: =H35*G35 -> 633406 | V35: =SUM(H35:N35) -> 1 | W35: =SUM(O35:U35) -> 633406
D36: Артезианская скважина | E36: =D$5 -> не определен | F36: опер. | G36: 475880 | H36: 1 | O36: =H36*G36 -> 475880 | V36: =SUM(H36:N36) -> 1 | W36: =SUM(O36:U36) -> 475880
D37: Авиапревозки | E37: =D$5 -> не определен | F37: опер. | G37: 205937.12 | O37: =H37*G37 -> 0 | V37: =SUM(H37:N37) -> 0 | W37: =SUM(O37:U37) -> 0
D38: Мобилизация и монтаж энергокомплекса | E38: =D$5 -> не определен | F38: опер. | G38: 0 | O38: =H38*G38 -> 0 | V38: =SUM(H38:N38) -> 0 | W38: =SUM(O38:U38) -> 0
D39: Завоз и монтаж верхнего силового привода | E39: =D$5 -> не определен | F39: опер. | G39: ='[9]Исходные данные'!$O$3110*1000 -> 2078246 | O39: =H39*G39 -> 0 | V39: =SUM(H39:N39) -> 0 | W39: =SUM(O39:U39) -> 0
D40: Завоз и монтаж новой насосной группы | E40: =D$5 -> не определен | F40: опер. | G40: ='[9]Исходные данные'!$N$3111*1000 -> 899742 | O40: =H40*G40 -> 0 | V40: =SUM(H40:N40) -> 0 | W40: =SUM(O40:U40) -> 0
C41: ОБЩАЯ СТОИМОСТЬ ВМР | D41: =W41 -> 25714124 | O41: =SUM(O20:O40) -> 25714124 | W41: =SUM(W20:W40) -> 25714124
C43: 2. ЭТАП БУРЕНИЯ: | X43: =SUM(W45:W55) -> 39031838
C44: =D5 -> не определен | D44: Описание работ/услуг
C45: (технико-технологичексие особенности) | D45: Фиксированная ставка за скважину с отходом до 1300 м. | E45: =D$5 -> не определен | F45: скв. | G45: 6559232 | O45: =H45*G45 -> 0 | P45: =I45*G45 -> 0 | Q45: =J45*G45 -> 0 | R45: =K45*G45 -> 0 | S45: =L45*G45 -> 0 | T45: =M45*G45 -> 0 | U45: =N45*G45 -> 0 | V45: =SUM(H45:N45) -> 0 | W45: =SUM(O45:U45) -> 0
D46: Фиксированная ставка за скважину с отходом от 1300 до 1500 м. | E46: =D$5 -> не определен | F46: скв. | G46: 8212084 | O46: =H46*G46 -> 0 | P46: =I46*G46 -> 0 | Q46: =J46*G46 -> 0 | R46: =K46*G46 -> 0 | S46: =L46*G46 -> 0 | T46: =M46*G46 -> 0 | U46: =N46*G46 -> 0 | V46: =SUM(H46:N46) -> 0 | W46: =SUM(O46:U46) -> 0 | AN46: =AL46+AJ46+AH46+AF46+AD46+AB46+Z46+X46++V46+T46+R46+N46+P46+L46+J46+H46 -> 0
D47: Фиксированная ставка за скважину с отходом от 1500 до 2000 м. | E47: =D$5 -> не определен | F47: скв. | G47: 9493878 | O47: =H47*G47 -> 0 | P47: =I47*G47 -> 0 | Q47: =J47*G47 -> 0 | R47: =K47*G47 -> 0 | S47: =L47*G47 -> 0 | T47: =M47*G47 -> 0 | U47: =N47*G47 -> 0 | V47: =SUM(H47:N47) -> 0 | W47: =SUM(O47:U47) -> 0
D48: Фиксированная ставка за скважину с отходом от 2000 до 2200 м. | E48: =D$5 -> не определен | F48: скв. | G48: 10414909 | O48: =H48*G48 -> 0 | P48: =I48*G48 -> 0 | Q48: =J48*G48 -> 0 | R48: =K48*G48 -> 0 | S48: =L48*G48 -> 0 | T48: =M48*G48 -> 0 | U48: =N48*G48 -> 0 | V48: =SUM(H48:N48) -> 0 | W48: =SUM(O48:U48) -> 0
D49: Фиксированная ставка за скважину с отходом более 2200 м. | E49: =D$5 -> не определен | F49: скв. | G49: 10993516 | O49: =H49*G49 -> 0 | P49: =I49*G49 -> 0 | Q49: =J49*G49 -> 0 | R49: =K49*G49 -> 0 | S49: =L49*G49 -> 0 | T49: =M49*G49 -> 0 | U49: =N49*G49 -> 0 | V49: =SUM(H49:N49) -> 0 | W49: =SUM(O49:U49) -> 0
D50: Расчет объема капитальных вложений по ГС | E50: =D$5 -> не определен | F50: сут. | G50: 31646673 | L50: 1 | O50: =H50*G50 -> 0 | P50: =I50*G50 -> 0 | Q50: =J50*G50 -> 0 | R50: =K50*G50 -> 0 | S50: =L50*G50 -> 31646673 | T50: =M50*G50 -> 0 | U50: =N50*G50 -> 0 | V50: =SUM(H50:N50) -> 1 | W50: =SUM(O50:U50) -> 31646673
D51: Переработка бурового шлама | E51: =D$5 -> не определен | F51: скв. | G51: 2869 | L51: 810.39 | O51: =H51*G51 -> 0 | P51: =I51*G51 -> 0 | Q51: =J51*G51 -> 0 | R51: =K51*G51 -> 0 | S51: =L51*G51 -> 2325008.9 | T51: =M51*G51 -> 0 | U51: =N51*G51 -> 0 | V51: =SUM(H51:N51) -> 810.39 | W51: =SUM(O51:U51) -> 2325008.9
D52: Нефть | E52: =D$5 -> не определен | F52: шт. | G52: 166946 | L52: 1 | O52: =H52*G52 -> 0 | P52: =I52*G52 -> 0 | Q52: =J52*G52 -> 0 | R52: =K52*G52 -> 0 | S52: =L52*G52 -> 166946 | T52: =M52*G52 -> 0 | U52: =N52*G52 -> 0 | V52: =SUM(H52:N52) -> 1 | W52: =SUM(O52:U52) -> 166946
D53: Эксплуатация верхнего привода | E53: =D$5 -> не определен | F53: опер. | G53: 73942 | L53: =O6 -> 45 | O53: =H53*G53 -> 0 | P53: =I53*G53 -> 0 | Q53: =J53*G53 -> 0 | R53: =K53*G53 -> 0 | S53: =L53*G53 -> 3327390 | T53: =M53*G53 -> 0 | U53: =N53*G53 -> 0 | V53: =SUM(H53:N53) -> 45 | W53: =SUM(O53:U53) -> 3327390
D54: Эксплуатация системы очистки | E54: =D$5 -> не определен | F54: опер. | G54: 34796 | L54: =O6 -> 45 | O54: =H54*G54 -> 0 | P54: =I54*G54 -> 0 | Q54: =J54*G54 -> 0 | R54: =K54*G54 -> 0 | S54: =L54*G54 -> 1565820 | T54: =M54*G54 -> 0 | U54: =N54*G54 -> 0 | V54: =SUM(H54:N54) -> 45 | W54: =SUM(O54:U54) -> 1565820
D55: Бурение по суточной ставке (геологическая нагрузка) | E55: =D$5 -> не определен | F55: опер. | G55: 703259.4 | O55: =H55*G55 -> 0 | P55: =I55*G55 -> 0 | Q55: =J55*G55 -> 0 | R55: =K55*G55 -> 0 | S55: =L55*G55 -> 0 | T55: =M55*G55 -> 0 | U55: =N55*G55 -> 0 | V55: =SUM(H55:N55) -> 0 | W55: =SUM(O55:U55) -> 0
C56: ПОДРЯДЧИК ПО ДОЛОТАМ: | X56: =SUM(W58:W64) -> 495000
D57: Описание работ/услуг
C58: (технико-технологичексие особенности) | D58: 550 мм долото для бурения под направление (долото+сервис) | E58: =C$57 -> 0 | F58: м | G58: 90 | L58: =O9 -> 5500 | O58: =H58*G58 -> 0 | P58: =I58*G58 -> 0 | Q58: =J58*G58 -> 0 | R58: =K58*G58 -> 0 | S58: =L58*G58 -> 495000 | T58: =M58*G58 -> 0 | U58: =N58*G58 -> 0 | V58: =SUM(H58:N58) -> 5500 | W58: =SUM(O58:U58) -> 495000 | Z58: =W58 -> 495000
D59: 393,7 мм долото для бурения под направление (долото+сервис) | E59: =C$57 -> 0 | F59: м | G59: 90 | O59: =H59*G59 -> 0 | P59: =I59*G59 -> 0 | Q59: =J59*G59 -> 0 | R59: =K59*G59 -> 0 | S59: =L59*G59 -> 0 | T59: =M59*G59 -> 0 | U59: =N59*G59 -> 0 | V59: =SUM(H59:N59) -> 0 | W59: =SUM(O59:U59) -> 0 | Z59: 472105.26 | AB59: =Z59/G59 -> 5245.614
D60: 295,3 мм долото для бурения под кондуктор (долото+сервис) | E60: =C$57 -> 0 | F60: м | G60: 90 | O60: =H60*G60 -> 0 | P60: =I60*G60 -> 0 | Q60: =J60*G60 -> 0 | R60: =K60*G60 -> 0 | S60: =L60*G60 -> 0 | T60: =M60*G60 -> 0 | U60: =N60*G60 -> 0 | V60: =SUM(H60:N60) -> 0 | W60: =SUM(O60:U60) -> 0
D61: 220,7 мм долото для бурения эксплуатационную колонну (долото+сервис) | E61: =C$57 -> 0 | F61: м | G61: 90 | O61: =H61*G61 -> 0 | P61: =I61*G61 -> 0 | Q61: =J61*G61 -> 0 | R61: =K61*G61 -> 0 | S61: =L61*G61 -> 0 | T61: =M61*G61 -> 0 | U61: =N61*G61 -> 0 | V61: =SUM(H61:N61) -> 0 | W61: =SUM(O61:U61) -> 0 | Z61: =Z59-Z58 -> -22894.737
D62: 155,6 мм долото для бурения под хвостовик (долото+сервис) | E62: =C$57 -> 0 | F62: м | G62: 90 | O62: =H62*G62 -> 0 | P62: =I62*G62 -> 0 | Q62: =J62*G62 -> 0 | R62: =K62*G62 -> 0 | S62: =L62*G62 -> 0 | T62: =M62*G62 -> 0 | U62: =N62*G62 -> 0 | V62: =SUM(H62:N62) -> 0 | W62: =SUM(O62:U62) -> 0
D63: _________ мм долото для бурения (долото+сервис) | E63: =C$57 -> 0 | F63: м | O63: =H63*G63 -> 0 | P63: =I63*G63 -> 0 | Q63: =J63*G63 -> 0 | R63: =K63*G63 -> 0 | S63: =L63*G63 -> 0 | T63: =M63*G63 -> 0 | U63: =N63*G63 -> 0 | V63: =SUM(H63:N63) -> 0 | W63: =SUM(O63:U63) -> 0
D64: Расширитель раздвижной | E64: =C$57 -> 0 | F64: м | O64: =H64*G64 -> 0 | P64: =I64*G64 -> 0 | Q64: =J64*G64 -> 0 | R64: =K64*G64 -> 0 | S64: =L64*G64 -> 0 | T64: =M64*G64 -> 0 | U64: =N64*G64 -> 0 | V64: =SUM(H64:N64) -> 0 | W64: =SUM(O64:U64) -> 0
C65: ПОДРЯДЧИК ПО ТЕХНОЛОГИЧЕСКОМУ И ТЕЛЕМЕТРИЧЕСКОМУ СОПРОВОЖДЕНИЮ: | X65: =SUM(W67:W85) -> 8986126
D66: Описание работ/услуг
C67: (технико-технологичексие особенности) | D67: Фиксированная ставка за скважину с отходом до 1300 м. | E67: =C$66 -> 0 | F67: скв. | G67: 1974979.6 | L67: =$L$45 -> 0 | O67: =H67*G67 -> 0 | P67: =I67*G67 -> 0 | Q67: =J67*G67 -> 0 | R67: =K67*G67 -> 0 | S67: =L67*G67 -> 0 | T67: =M67*G67 -> 0 | U67: =N67*G67 -> 0 | V67: =SUM(H67:N67) -> 0 | W67: =SUM(O67:U67) -> 0
D68: Фиксированная ставка за скважину с отходом от 1300 до 1500 м. | E68: =C$66 -> 0 | F68: скв. | G68: 2121689.5 | L68: =$L$46 -> 0 | O68: =H68*G68 -> 0 | P68: =I68*G68 -> 0 | Q68: =J68*G68 -> 0 | R68: =K68*G68 -> 0 | S68: =L68*G68 -> 0 | T68: =M68*G68 -> 0 | U68: =N68*G68 -> 0 | V68: =SUM(H68:N68) -> 0 | W68: =SUM(O68:U68) -> 0
D69: Фиксированная ставка за скважину с отходом от 1500 до 2000 м. | E69: =C$66 -> 0 | F69: скв. | G69: 2436096.7 | L69: =$L$47 -> 0 | O69: =H69*G69 -> 0 | P69: =I69*G69 -> 0 | Q69: =J69*G69 -> 0 | R69: =K69*G69 -> 0 | S69: =L69*G69 -> 0 | T69: =M69*G69 -> 0 | U69: =N69*G69 -> 0 | V69: =SUM(H69:N69) -> 0 | W69: =SUM(O69:U69) -> 0
D70: Фиксированная ставка за скважину с отходом от 2000 до 2200 м. | E70: =C$66 -> 0 | F70: скв. | G70: 2743673.1 | L70: =$L$48 -> 0 | O70: =H70*G70 -> 0 | P70: =I70*G70 -> 0 | Q70: =J70*G70 -> 0 | R70: =K70*G70 -> 0 | S70: =L70*G70 -> 0 | T70: =M70*G70 -> 0 | U70: =N70*G70 -> 0 | V70: =SUM(H70:N70) -> 0 | W70: =SUM(O70:U70) -> 0
D71: Фиксированная ставка за скважину с отходом более 2200 м. | E71: =C$66 -> 0 | F71: скв. | G71: 2903714.7 | L71: =$L$49 -> 0 | O71: =H71*G71 -> 0 | P71: =I71*G71 -> 0 | Q71: =J71*G71 -> 0 | R71: =K71*G71 -> 0 | S71: =L71*G71 -> 0 | T71: =M71*G71 -> 0 | U71: =N71*G71 -> 0 | V71: =SUM(H71:N71) -> 0 | W71: =SUM(O71:U71) -> 0
D72: Фиксированная ставка за горизонтальную скважину | E72: =C$66 -> 0 | F72: скв. | G72: 8986126 | L72: 1 | O72: =H72*G72 -> 0 | P72: =I72*G72 -> 0 | Q72: =J72*G72 -> 0 | R72: =K72*G72 -> 0 | S72: =L72*G72 -> 8986126 | T72: =M72*G72 -> 0 | U72: =N72*G72 -> 0 | V72: =SUM(H72:N72) -> 1 | W72: =SUM(O72:U72) -> 8986126
E73: =C$66 -> 0 | F73: сут | O73: =H73*G73 -> 0 | P73: =I73*G73 -> 0 | Q73: =J73*G73 -> 0 | R73: =K73*G73 -> 0 | S73: =L73*G73 -> 0 | T73: =M73*G73 -> 0 | U73: =N73*G73 -> 0 | V73: =SUM(H73:N73) -> 0 | W73: =SUM(O73:U73) -> 0
E74: =C$66 -> 0 | F74: сут | O74: =H74*G74 -> 0 | P74: =I74*G74 -> 0 | Q74: =J74*G74 -> 0 | R74: =K74*G74 -> 0 | S74: =L74*G74 -> 0 | T74: =M74*G74 -> 0 | U74: =N74*G74 -> 0 | V74: =SUM(H74:N74) -> 0 | W74: =SUM(O74:U74) -> 0
E75: =C$66 -> 0 | F75: сут | O75: =H75*G75 -> 0 | P75: =I75*G75 -> 0 | Q75: =J75*G75 -> 0 | R75: =K75*G75 -> 0 | S75: =L75*G75 -> 0 | T75: =M75*G75 -> 0 | U75: =N75*G75 -> 0 | V75: =SUM(H75:N75) -> 0 | W75: =SUM(O75:U75) -> 0
D76: Мобилизация на объект работ | E76: =C$66 -> 0 | F76: опер. | O76: =H76*G76 -> 0 | P76: =I76*G76 -> 0 | Q76: =J76*G76 -> 0 | R76: =K76*G76 -> 0 | S76: =L76*G76 -> 0 | T76: =M76*G76 -> 0 | U76: =N76*G76 -> 0 | V76: =SUM(H76:N76) -> 0 | W76: =SUM(O76:U76) -> 0
D77: Демобилизация | E77: =C$66 -> 0 | F77: опер. | O77: =H77*G77 -> 0 | P77: =I77*G77 -> 0 | Q77: =J77*G77 -> 0 | R77: =K77*G77 -> 0 | S77: =L77*G77 -> 0 | T77: =M77*G77 -> 0 | U77: =N77*G77 -> 0 | V77: =SUM(H77:N77) -> 0 | W77: =SUM(O77:U77) -> 0
D78: Описание работ/услуг
C79: (технико-технологичексие особенности) | D79: Операционная ставка в режиме работы | E79: =C$78 -> 0 | F79: сут | O79: =H79*G79 -> 0 | P79: =I79*G79 -> 0 | Q79: =J79*G79 -> 0 | R79: =K79*G79 -> 0 | S79: =L79*G79 -> 0 | T79: =M79*G79 -> 0 | U79: =N79*G79 -> 0 | V79: =SUM(H79:N79) -> 0 | W79: =SUM(O79:U79) -> 0
D80: Операционная ставка в режиме ожидания | E80: =C$78 -> 0 | F80: сут | O80: =H80*G80 -> 0 | P80: =I80*G80 -> 0 | Q80: =J80*G80 -> 0 | R80: =K80*G80 -> 0 | S80: =L80*G80 -> 0 | T80: =M80*G80 -> 0 | U80: =N80*G80 -> 0 | V80: =SUM(H80:N80) -> 0 | W80: =SUM(O80:U80) -> 0
D81: Гамма -каротаж и сопротивление в режиме записи | E81: =C$78 -> 0 | F81: сут | O81: =H81*G81 -> 0 | P81: =I81*G81 -> 0 | Q81: =J81*G81 -> 0 | R81: =K81*G81 -> 0 | S81: =L81*G81 -> 0 | T81: =M81*G81 -> 0 | U81: =N81*G81 -> 0 | V81: =SUM(H81:N81) -> 0 | W81: =SUM(O81:U81) -> 0
D82: Гамма -каротаж и сопротивление в режиме реального времени | E82: =C$78 -> 0 | F82: сут | O82: =H82*G82 -> 0 | P82: =I82*G82 -> 0 | Q82: =J82*G82 -> 0 | R82: =K82*G82 -> 0 | S82: =L82*G82 -> 0 | T82: =M82*G82 -> 0 | U82: =N82*G82 -> 0 | V82: =SUM(H82:N82) -> 0 | W82: =SUM(O82:U82) -> 0
D83: Гамма -каротаж в режиме записи | E83: =C$78 -> 0 | F83: сут | O83: =H83*G83 -> 0 | P83: =I83*G83 -> 0 | Q83: =J83*G83 -> 0 | R83: =K83*G83 -> 0 | S83: =L83*G83 -> 0 | T83: =M83*G83 -> 0 | U83: =N83*G83 -> 0 | V83: =SUM(H83:N83) -> 0 | W83: =SUM(O83:U83) -> 0
D84: Гамма -каротаж в режиме реального времени | E84: =C$78 -> 0 | F84: сут | O84: =H84*G84 -> 0 | P84: =I84*G84 -> 0 | Q84: =J84*G84 -> 0 | R84: =K84*G84 -> 0 | S84: =L84*G84 -> 0 | T84: =M84*G84 -> 0 | U84: =N84*G84 -> 0 | V84: =SUM(H84:N84) -> 0 | W84: =SUM(O84:U84) -> 0
D85: Услуги персонала телеметрического и технологического сопровождения | E85: =C$78 -> 0 | F85: сут | O85: =H85*G85 -> 0 | P85: =I85*G85 -> 0 | Q85: =J85*G85 -> 0 | R85: =K85*G85 -> 0 | S85: =L85*G85 -> 0 | T85: =M85*G85 -> 0 | U85: =N85*G85 -> 0 | V85: =SUM(H85:N85) -> 0 | W85: =SUM(O85:U85) -> 0
C86: ПОДРЯДЧИК ПО БУРОВЫМ РАСТВОРАМ: | X86: =SUM(W88:W93) -> 5521715.7
D87: Описание работ/услуг
C88: (технико-технологичексие особенности) | D88: Фиксированная ставка за скважину с отходом до 1300 м. | E88: =C$87 -> 0 | F88: скв. | G88: 807557.8 | L88: =$L$45 -> 0 | O88: =H88*G88 -> 0 | P88: =I88*G88 -> 0 | Q88: =J88*G88 -> 0 | R88: =K88*G88 -> 0 | S88: =L88*G88 -> 0 | T88: =M88*G88 -> 0 | U88: =N88*G88 -> 0 | V88: =SUM(H88:N88) -> 0 | W88: =SUM(O88:U88) -> 0
D89: Фиксированная ставка за скважину с отходом от 1300 до 1500 м. | E89: =C$87 -> 0 | F89: скв. | G89: 883911 | L89: =$L$46 -> 0 | O89: =H89*G89 -> 0 | P89: =I89*G89 -> 0 | Q89: =J89*G89 -> 0 | R89: =K89*G89 -> 0 | S89: =L89*G89 -> 0 | T89: =M89*G89 -> 0 | U89: =N89*G89 -> 0 | V89: =SUM(H89:N89) -> 0 | W89: =SUM(O89:U89) -> 0
D90: Фиксированная ставка за скважину с отходом от 1500 до 2000 м. | E90: =C$87 -> 0 | F90: скв. | G90: 883911 | L90: =$L$47 -> 0 | O90: =H90*G90 -> 0 | P90: =I90*G90 -> 0 | Q90: =J90*G90 -> 0 | R90: =K90*G90 -> 0 | S90: =L90*G90 -> 0 | T90: =M90*G90 -> 0 | U90: =N90*G90 -> 0 | V90: =SUM(H90:N90) -> 0 | W90: =SUM(O90:U90) -> 0
D91: Фиксированная ставка за скважину с отходом от 2000 до 2200 м. | E91: =C$87 -> 0 | F91: скв. | G91: 1125553 | L91: =$L$48 -> 0 | O91: =H91*G91 -> 0 | P91: =I91*G91 -> 0 | Q91: =J91*G91 -> 0 | R91: =K91*G91 -> 0 | S91: =L91*G91 -> 0 | T91: =M91*G91 -> 0 | U91: =N91*G91 -> 0 | V91: =SUM(H91:N91) -> 0 | W91: =SUM(O91:U91) -> 0
D92: Фиксированная ставка за скважину с отходом более 2200 м. | E92: =C$87 -> 0 | F92: сут. | G92: 1381613.2 | L92: =$L$49 -> 0 | O92: =H92*G92 -> 0 | P92: =I92*G92 -> 0 | Q92: =J92*G92 -> 0 | R92: =K92*G92 -> 0 | S92: =L92*G92 -> 0 | T92: =M92*G92 -> 0 | U92: =N92*G92 -> 0 | V92: =SUM(H92:N92) -> 0 | W92: =SUM(O92:U92) -> 0
D93: Фиксированная ставка за горизонтальную скважину | E93: =C$87 -> 0 | F93: скв. | G93: 5521715.7 | L93: 1 | O93: =H93*G93 -> 0 | P93: =I93*G93 -> 0 | Q93: =J93*G93 -> 0 | R93: =K93*G93 -> 0 | S93: =L93*G93 -> 5521715.7 | T93: =M93*G93 -> 0 | U93: =N93*G93 -> 0 | V93: =SUM(H93:N93) -> 1 | W93: =SUM(O93:U93) -> 5521715.7
C94: ПОДРЯДЧИК ПО ЦЕМЕНТИРОВАНИЮ: | X94: =SUM(W96:W111) -> 2588946
D95: Описание работ/услуг
D96: Цементирование направления НН 426 мм (услуги, цемент, материалы) | E96: =C$95 -> 0 | F96: опер | G96: ='[10]Куст №64'!$G$1560*1000 -> 261088 | L96: 1 | O96: =H96*G96 -> 0 | P96: =I96*G96 -> 0 | Q96: =J96*G96 -> 0 | R96: =K96*G96 -> 0 | S96: =L96*G96 -> 261088 | T96: =M96*G96 -> 0 | U96: =N96*G96 -> 0 | V96: =SUM(H96:N96) -> 1 | W96: =SUM(O96:U96) -> 261088
D97: Цементирование кондуктора НН 324 мм (услуги, цемент, материалы) | E97: =C$95 -> 0 | F97: опер | G97: ='[10]Куст №64'!$G$1561*1000 -> 450018 | L97: 1 | O97: =H97*G97 -> 0 | P97: =I97*G97 -> 0 | Q97: =J97*G97 -> 0 | R97: =K97*G97 -> 0 | S97: =L97*G97 -> 450018 | T97: =M97*G97 -> 0 | U97: =N97*G97 -> 0 | V97: =SUM(H97:N97) -> 1 | W97: =SUM(O97:U97) -> 450018
D98: Цементирование технической колонны Гор 245 мм (услуги, цемент, материалы) | E98: =C$95 -> 0 | F98: опер | O98: =H98*G98 -> 0 | P98: =I98*G98 -> 0 | Q98: =J98*G98 -> 0 | R98: =K98*G98 -> 0 | S98: =L98*G98 -> 0 | T98: =M98*G98 -> 0 | U98: =N98*G98 -> 0 | V98: =SUM(H98:N98) -> 0 | W98: =SUM(O98:U98) -> 0
D99: Цементирование эксплуатационной колонны 178мм (услуги, цемент, материалы) | E99: =C$95 -> 0 | F99: опер | G99: ='[10]Куст №64'!$G$1563*1000 -> 1433230 | L99: 1 | O99: =H99*G99 -> 0 | P99: =I99*G99 -> 0 | Q99: =J99*G99 -> 0 | R99: =K99*G99 -> 0 | S99: =L99*G99 -> 1433230 | T99: =M99*G99 -> 0 | U99: =N99*G99 -> 0 | V99: =SUM(H99:N99) -> 1 | W99: =SUM(O99:U99) -> 1433230
D100: Цементирование направления НН 324 мм (услуги, цемент, материалы) | E100: =C$95 -> 0 | F100: опер | O100: =H100*G100 -> 0 | P100: =I100*G100 -> 0 | Q100: =J100*G100 -> 0 | R100: =K100*G100 -> 0 | S100: =L100*G100 -> 0 | T100: =M100*G100 -> 0 | U100: =N100*G100 -> 0 | V100: =SUM(H100:N100) -> 0 | W100: =SUM(O100:U100) -> 0
D101: Цементирование кондуктора НН 245 мм (услуги, цемент, материалы) | E101: =C$95 -> 0 | F101: опер | O101: =H101*G101 -> 0 | P101: =I101*G101 -> 0 | Q101: =J101*G101 -> 0 | R101: =K101*G101 -> 0 | S101: =L101*G101 -> 0 | T101: =M101*G101 -> 0 | U101: =N101*G101 -> 0 | V101: =SUM(H101:N101) -> 0 | W101: =SUM(O101:U101) -> 0
D102: Цементирование эксплуатационной колонны НН 178мм (услуги, цемент, материалы) | E102: =C$95 -> 0 | F102: опер | O102: =H102*G102 -> 0 | P102: =I102*G102 -> 0 | Q102: =J102*G102 -> 0 | R102: =K102*G102 -> 0 | S102: =L102*G102 -> 0 | T102: =M102*G102 -> 0 | U102: =N102*G102 -> 0 | V102: =SUM(H102:N102) -> 0 | W102: =SUM(O102:U102) -> 0
D103: Цементирование хвостовика НН 127мм (услуги, цемент, материалы) | E103: =C$95 -> 0 | F103: опер | G103: 0 | O103: =H103*G103 -> 0 | P103: =I103*G103 -> 0 | Q103: =J103*G103 -> 0 | R103: =K103*G103 -> 0 | S103: =L103*G103 -> 0 | T103: =M103*G103 -> 0 | U103: =N103*G103 -> 0 | V103: =SUM(H103:N103) -> 0 | W103: =SUM(O103:U103) -> 0
D104: Цементирование технической колонны НН 245 мм (услуги, цемент, материалы) | E104: =C$95 -> 0 | F104: опер | O104: =H104*G104 -> 0 | P104: =I104*G104 -> 0 | Q104: =J104*G104 -> 0 | R104: =K104*G104 -> 0 | S104: =L104*G104 -> 0 | T104: =M104*G104 -> 0 | U104: =N104*G104 -> 0 | V104: =SUM(H104:N104) -> 0 | W104: =SUM(O104:U104) -> 0
D105: Транспортировка цемента | E105: =C$95 -> 0 | F105: опер | G105: 0 | O105: =H105*G105 -> 0 | P105: =I105*G105 -> 0 | Q105: =J105*G105 -> 0 | R105: =K105*G105 -> 0 | S105: =L105*G105 -> 0 | T105: =M105*G105 -> 0 | U105: =N105*G105 -> 0 | V105: =SUM(H105:N105) -> 0 | W105: =SUM(O105:U105) -> 0
...

Sheet ННСдо1300
A2: ПОДРОБНАЯ СМЕТНАЯ СТОИМОСТЬ СКВАЖИНЫ
C4: Месторождение/ куст: | D4: ='Титул '!G5 -> куст №21б Приобского месторождения | E4: ВСЕГО СТ-ТЬ | F4: Исходные данные | H4: Перед забуркой | I4: Направление | J4: Кондуктор | K4: Техническая колонна | L4: Эксплуат-ая колонна | M4: Крепление колонн | N4: Хвостовик | O4: ВСЕГО БУРЕНИЕ | P4: Исходные данные | R4: ВСЕГО ОСВОЕНИЕ
C5: Подрядчик по бурению: | D5: ='Титул '!C11 -> не определен | E5: =IF(($L$45+$L$46+$L$47+$L$48+$L$49+$L$50)>0,$D$214,0) -> 1.0621282e+08
C6: Тип буровой установки: | D6: ='Титул '!C12 -> БУ-3000 ЭУК | E6: Всего ВМР | F6: Время бурения секции, сут: | I6: 1 | J6: 2.5 | L6: 5.5 | M6: 3 | N6: 0 | O6: =IF(($L$45+$L$46+$L$47+$L$48+$L$49+$L$50)>0,SUM(I6:N6),0) -> 12 | P6: Время освоения, сут: | R6: =IF(($L$45+$L$46+$L$47+$L$48+$L$49+$L$50)>0,SUM(R8:R10),0) -> 17
C7: Тип скважины: | D7: Наклонно-направленная | E7: =IF(($L$45+$L$46+$L$47+$L$48+$L$49+$L$50)>0,$W$41,0) -> 471302.12 | F7: Глубина (по стволу), м: | I7: 120 | J7: 1280 | L7: 3000 | O7: ВСЕГО ПРОХОДКА | P7: В т.ч.время работы бригад КРС
C8: Проходка всего (м): | D8: 3000 | E8: Всего Бурение | F8: Диаметр долота, мм: | I8: 393 | J8: 300 | L8: 220 | P8: - ПЗР к ГРП/МСГРП, сут. | R8: 13
C9: Наличие СВП: | D9: ='Титул '!C13 -> да | E9: =IF(($L$45+$L$46+$L$47+$L$48+$L$49+$L$50)>0,$W$190,0) -> 68837029 | F9: Диаметр колонны, мм: | I9: 324 | J9: 245 | L9: 168 | O9: =D8 -> 3000 | P9: - проведение ГРП/МСГРП, сут. | R9: 1
C10: Наличие АИЭС: | D10: ='Титул '!C14 -> нет | E10: Всего Освоение | F10: Исходные данные | H10: Отход | I10: Пилот ГС | J10: Перебур | K10: Гориз.уч. 1 | L10: Гориз.уч. 2 | M10: Керн | O10: ГЛУБИНА ПО ВЕРТ-ЛИ | P10: - проведение ГНКТ, сут. | R10: 3
C11: Наличие автономности: | D11: ='Титул '!C15 -> нет | E11: =IF(($L$45+$L$46+$L$47+$L$48+$L$49+$L$50)>0,$W$206,0) -> 36904487 | F11: Отдельные стволы, керн, м: | P11: - кол-во стадий МСГРП, шт. | R11: 2
C12: Кол-во обсадных колонн (включая направл.): | D12: 3 | E12: Обор-ие устья | F12: Примечание: | P12: Примечание:
C13: Прочие существенные условия: | E13: =IF(($L$45+$L$46+$L$47+$L$48+$L$49+$L$50)>0,$W$212,0) -> 0
A15: ОПИСАНИЕ РАБОТ И УСЛУГ | H15: КОЛИЧЕСТВО | O15: СТОИМОСТЬ | V15: ВСЕГО
A16: КОД | B16: добавочный код | C16: СТАТЬЯ ЗАТРАТ | D16: ОПИСАНИЕ | E16: Подрядчик | F16: Единица измерения | G16: Руб. / Ед.изм. | H16: ПЗР (в т.ч. ВМР и осв.) | I16: =+I4 -> Направление | J16: =+J4 -> Кондуктор | K16: =+K4 -> Техническая колонна | L16: =+L4 -> Эксплуат-ая колонна | M16: Крепление колонн | N16: =+N4 -> Хвостовик | O16: ПЗР (в т.ч. ВМР и осв.) | P16: =+I16 -> Направление | Q16: =+J16 -> Кондуктор | R16: =+K16 -> Техническая колонна | S16: =+L16 -> Эксплуат-ая колонна | T16: Крепление колонн | U16: =+N16 -> Хвостовик | V16: Количество | W16: Стоимость (руб) | X16: ВСЕГО СТОИМОСТЬ
C18: 1. ЭТАП ВМР | X18: =SUM(W20:W40) -> 471302.12
C19: ='Перв. скв '!C19 -> не определен | D19: Описание работ/услуг
D20: ='Перв. скв '!D20 -> Монтаж | E20: =D$5 -> не определен | F20: ='Перв. скв '!F20 -> опер. | G20: ='Перв. скв '!G20 -> 9401938 | O20: =H20*G20 -> 0 | V20: =SUM(H20:N20) -> 0 | W20: =SUM(O20:U20) -> 0
D21: ='Перв. скв '!D21 -> Демонтаж | E21: =D$5 -> не определен | F21: ='Перв. скв '!F21 -> опер. | G21: ='Перв. скв '!G21 -> 2344149 | O21: =H21*G21 -> 0 | V21: =SUM(H21:N21) -> 0 | W21: =SUM(O21:U21) -> 0
D22: ='Перв. скв '!D22 -> Эксплуатация АВЭС | E22: =D$5 -> не определен | F22: ='Перв. скв '!F22 -> опер. | G22: ='Перв. скв '!G22 -> 0 | O22: =H22*G22 -> 0 | V22: =SUM(H22:N22) -> 0 | W22: =SUM(O22:U22) -> 0
D23: ='Перв. скв '!D23 -> Передислокация БУ в пределах м-я | E23: =D$5 -> не определен | F23: ='Перв. скв '!F23 -> опер. | G23: ='Перв. скв '!G23 -> 693236 | O23: =H23*G23 -> 0 | V23: =SUM(H23:N23) -> 0 | W23: =SUM(O23:U23) -> 0
D24: ='Перв. скв '!D24 -> Передислокация БУ 250-500 км. | E24: =D$5 -> не определен | F24: ='Перв. скв '!F24 -> опер. | G24: ='Перв. скв '!G24 -> 9837322 | O24: =H24*G24 -> 0 | V24: =SUM(H24:N24) -> 0 | W24: =SUM(O24:U24) -> 0
D25: ='Перв. скв '!D25 -> Передислокация бр. бур в пределах м-я | E25: =D$5 -> не определен | F25: ='Перв. скв '!F25 -> опер. | G25: ='Перв. скв '!G25 -> 130867 | O25: =H25*G25 -> 0 | V25: =SUM(H25:N25) -> 0 | W25: =SUM(O25:U25) -> 0
D26: ='Перв. скв '!D26 -> Передислокация бр. бур 250-500 км. | E26: =D$5 -> не определен | F26: ='Перв. скв '!F26 -> опер. | G26: ='Перв. скв '!G26 -> 1788526 | O26: =H26*G26 -> 0 | V26: =SUM(H26:N26) -> 0 | W26: =SUM(O26:U26) -> 0
D27: ='Перв. скв '!D27 -> Передислокация бригады ВМР в пределах м-я | E27: =D$5 -> не определен | F27: ='Перв. скв '!F27 -> опер. | G27: ='Перв. скв '!G27 -> 130867 | O27: =H27*G27 -> 0 | V27: =SUM(H27:N27) -> 0 | W27: =SUM(O27:U27) -> 0
D28: ='Перв. скв '!D28 -> Передислокация бригады ВМР 250-500 км. | E28: =D$5 -> не определен | F28: ='Перв. скв '!F28 -> опер. | G28: ='Перв. скв '!G28 -> 1788526 | O28: =H28*G28 -> 0 | V28: =SUM(H28:N28) -> 0 | W28: =SUM(O28:U28) -> 0
D29: ='Перв. скв '!D29 -> Передвижка 5 м. | E29: =D$5 -> не определен | F29: ='Перв. скв '!F29 -> опер. | G29: ='Перв. скв '!G29 -> 244497 | O29: =H29*G29 -> 0 | V29: =SUM(H29:N29) -> 0 | W29: =SUM(O29:U29) -> 0
D30: ='Перв. скв '!D30 -> Передвижка 9 м. | E30: =D$5 -> не определен | F30: ='Перв. скв '!F30 -> опер. | G30: ='Перв. скв '!G30 -> 265365 | H30: 1 | O30: =H30*G30 -> 265365 | V30: =SUM(H30:N30) -> 1 | W30: =SUM(O30:U30) -> 265365
D31: ='Перв. скв '!D31 -> Передвижка 18 м. | E31: =D$5 -> не определен | F31: ='Перв. скв '!F31 -> опер. | G31: ='Перв. скв '!G31 -> 406328 | O31: =H31*G31 -> 0 | V31: =SUM(H31:N31) -> 0 | W31: =SUM(O31:U31) -> 0
D32: ='Перв. скв '!D32 -> Передвижка 25 м. | E32: =D$5 -> не определен | F32: ='Перв. скв '!F32 -> опер. | G32: ='Перв. скв '!G32 -> 462462 | O32: =H32*G32 -> 0 | V32: =SUM(H32:N32) -> 0 | W32: =SUM(O32:U32) -> 0
D33: ='Перв. скв '!D33 -> Передвижка 50 м. | E33: =D$5 -> не определен | F33: ='Перв. скв '!F33 -> опер. | G33: ='Перв. скв '!G33 -> 889289 | O33: =H33*G33 -> 0 | V33: =SUM(H33:N33) -> 0 | W33: =SUM(O33:U33) -> 0
D34: ='Перв. скв '!D34 -> Сдвижка 25 м. | E34: =D$5 -> не определен | F34: ='Перв. скв '!F34 -> опер. | G34: ='Перв. скв '!G34 -> 291019 | O34: =H34*G34 -> 0 | V34: =SUM(H34:N34) -> 0 | W34: =SUM(O34:U34) -> 0
D35: ='Перв. скв '!D35 -> Пуско-наладочные работы | E35: =D$5 -> не определен | F35: ='Перв. скв '!F35 -> опер. | G35: ='Перв. скв '!G35 -> 633406 | O35: =H35*G35 -> 0 | V35: =SUM(H35:N35) -> 0 | W35: =SUM(O35:U35) -> 0
D36: ='Перв. скв '!D36 -> Артезианская скважина | E36: =D$5 -> не определен | F36: ='Перв. скв '!F36 -> опер. | G36: ='Перв. скв '!G36 -> 475880 | O36: =H36*G36 -> 0 | V36: =SUM(H36:N36) -> 0 | W36: =SUM(O36:U36) -> 0
D37: ='Перв. скв '!D37 -> Авиапревозки | E37: =D$5 -> не определен | F37: ='Перв. скв '!F37 -> опер. | G37: ='Перв. скв '!G37 -> 205937.12 | H37: 1 | O37: =H37*G37 -> 205937.12 | V37: =SUM(H37:N37) -> 1 | W37: =SUM(O37:U37) -> 205937.12
D38: ='Перв. скв '!D38 -> Мобилизация и монтаж энергокомплекса | E38: =D$5 -> не определен | F38: ='Перв. скв '!F38 -> опер. | G38: ='Перв. скв '!G38 -> 0 | O38: =H38*G38 -> 0 | V38: =SUM(H38:N38) -> 0 | W38: =SUM(O38:U38) -> 0
D39: ='Перв. скв '!D39 -> Завоз и монтаж верхнего силового привода | E39: =D$5 -> не определен | F39: ='Перв. скв '!F39 -> опер. | G39: ='Перв. скв '!G39 -> 2078246 | O39: =H39*G39 -> 0 | V39: =SUM(H39:N39) -> 0 | W39: =SUM(O39:U39) -> 0
D40: ='Перв. скв '!D40 -> Завоз и монтаж новой насосной группы | E40: =D$5 -> не определен | F40: ='Перв. скв '!F40 -> опер. | G40: ='Перв. скв '!G40 -> 899742 | O40: =H40*G40 -> 0 | V40: =SUM(H40:N40) -> 0 | W40: =SUM(O40:U40) -> 0
C41: ОБЩАЯ СТОИМОСТЬ ВМР | D41: =W41 -> 471302.12 | O41: =SUM(O20:O40) -> 471302.12 | W41: =SUM(W20:W40) -> 471302.12
C43: 2. ЭТАП БУРЕНИЯ: | X43: =SUM(W45:W55) -> 40617487
C44: ='Перв. скв '!C44 -> не определен | D44: Описание работ/услуг
C45: (технико-технологичексие особенности) | D45: ='Перв. скв '!D45 -> Фиксированная ставка за скважину с отходом до 1300 м. | E45: =D$5 -> не определен | F45: ='Перв. скв '!F45 -> скв. | G45: ='Перв. скв '!G45 -> 6559232 | H45: ='Перв. скв '!H45 -> 0 | I45: ='Перв. скв '!I45 -> 0 | J45: ='Перв. скв '!J45 -> 0 | K45: ='Перв. скв '!K45 -> 0 | L45: 1 | M45: ='Перв. скв '!M45 -> 0 | N45: ='Перв. скв '!N45 -> 0 | O45: =H45*G45 -> 0 | P45: =I45*G45 -> 0 | Q45: =J45*G45 -> 0 | R45: =K45*G45 -> 0 | S45: =L45*G45 -> 6559232 | T45: =M45*G45 -> 0 | U45: =N45*G45 -> 0 | V45: =SUM(H45:N45) -> 1 | W45: =SUM(O45:U45) -> 6559232
D46: ='Перв. скв '!D46 -> Фиксированная ставка за скважину с отходом от 1300 до 1500 м. | E46: =D$5 -> не определен | F46: ='Перв. скв '!F46 -> скв. | G46: ='Перв. скв '!G46 -> 8212084 | H46: ='Перв. скв '!H46 -> 0 | I46: ='Перв. скв '!I46 -> 0 | J46: ='Перв. скв '!J46 -> 0 | K46: ='Перв. скв '!K46 -> 0 | L46: ='Перв. скв '!L46 -> 0 | M46: ='Перв. скв '!M46 -> 0 | N46: ='Перв. скв '!N46 -> 0 | O46: =H46*G46 -> 0 | P46: =I46*G46 -> 0 | Q46: =J46*G46 -> 0 | R46: =K46*G46 -> 0 | S46: =L46*G46 -> 0 | T46: =M46*G46 -> 0 | U46: =N46*G46 -> 0 | V46: =SUM(H46:N46) -> 0 | W46: =SUM(O46:U46) -> 0 | AN46: =AL46+AJ46+AH46+AF46+AD46+AB46+Z46+X46++V46+T46+R46+N46+P46+L46+J46+H46 -> 0
D47: ='Перв. скв '!D47 -> Фиксированная ставка за скважину с отходом от 1500 до 2000 м. | E47: =D$5 -> не определен | F47: ='Перв. скв '!F47 -> скв. | G47: ='Перв. скв '!G47 -> 9493878 | H47: ='Перв. скв '!H47 -> 0 | I47: ='Перв. скв '!I47 -> 0 | J47: ='Перв. скв '!J47 -> 0 | K47: ='Перв. скв '!K47 -> 0 | L47: ='Перв. скв '!L47 -> 0 | M47: ='Перв. скв '!M47 -> 0 | N47: ='Перв. скв '!N47 -> 0 | O47: =H47*G47 -> 0 | P47: =I47*G47 -> 0 | Q47: =J47*G47 -> 0 | R47: =K47*G47 -> 0 | S47: =L47*G47 -> 0 | T47: =M47*G47 -> 0 | U47: =N47*G47 -> 0 | V47: =SUM(H47:N47) -> 0 | W47: =SUM(O47:U47) -> 0
D48: ='Перв. скв '!D48 -> Фиксированная ставка за скважину с отходом от 2000 до 2200 м. | E48: =D$5 -> не определен | F48: ='Перв. скв '!F48 -> скв. | G48: ='Перв. скв '!G48 -> 10414909 | H48: ='Перв. скв '!H48 -> 0 | I48: ='Перв. скв '!I48 -> 0 | J48: ='Перв. скв '!J48 -> 0 | K48: ='Перв. скв '!K48 -> 0 | L48: ='Перв. скв '!L48 -> 0 | M48: ='Перв. скв '!M48 -> 0 | N48: ='Перв. скв '!N48 -> 0 | O48: =H48*G48 -> 0 | P48: =I48*G48 -> 0 | Q48: =J48*G48 -> 0 | R48: =K48*G48 -> 0 | S48: =L48*G48 -> 0 | T48: =M48*G48 -> 0 | U48: =N48*G48 -> 0 | V48: =SUM(H48:N48) -> 0 | W48: =SUM(O48:U48) -> 0
D49: ='Перв. скв '!D49 -> Фиксированная ставка за скважину с отходом более 2200 м. | E49: =D$5 -> не определен | F49: ='Перв. скв '!F49 -> скв. | G49: ='Перв. скв '!G49 -> 10993516 | H49: ='Перв. скв '!H49 -> 0 | I49: ='Перв. скв '!I49 -> 0 | J49: ='Перв. скв '!J49 -> 0 | K49: ='Перв. скв '!K49 -> 0 | L49: ='Перв. скв '!L49 -> 0 | M49: ='Перв. скв '!M49 -> 0 | N49: ='Перв. скв '!N49 -> 0 | O49: =H49*G49 -> 0 | P49: =I49*G49 -> 0 | Q49: =J49*G49 -> 0 | R49: =K49*G49 -> 0 | S49: =L49*G49 -> 0 | T49: =M49*G49 -> 0 | U49: =N49*G49 -> 0 | V49: =SUM(H49:N49) -> 0 | W49: =SUM(O49:U49) -> 0
D50: ='Перв. скв '!D50 -> Расчет объема капитальных вложений по ГС | E50: =D$5 -> не определен | F50: ='Перв. скв '!F50 -> сут. | G50: ='Перв. скв '!G50 -> 31646673 | H50: ='Перв. скв '!H50 -> 0 | I50: ='Перв. скв '!I50 -> 0 | J50: ='Перв. скв '!J50 -> 0 | K50: ='Перв. скв '!K50 -> 0 | L50: ='Перв. скв '!L50 -> 1 | M50: ='Перв. скв '!M50 -> 0 | N50: ='Перв. скв '!N50 -> 0 | O50: =H50*G50 -> 0 | P50: =I50*G50 -> 0 | Q50: =J50*G50 -> 0 | R50: =K50*G50 -> 0 | S50: =L50*G50 -> 31646673 | T50: =M50*G50 -> 0 | U50: =N50*G50 -> 0 | V50: =SUM(H50:N50) -> 1 | W50: =SUM(O50:U50) -> 31646673
D51: ='Перв. скв '!D51 -> Переработка бурового шлама | E51: =D$5 -> не определен | F51: ='Перв. скв '!F51 -> скв. | G51: ='Перв. скв '!G51 -> 2869 | H51: ='Перв. скв '!H51 -> 0 | I51: ='Перв. скв '!I51 -> 0 | J51: ='Перв. скв '!J51 -> 0 | K51: ='Перв. скв '!K51 -> 0 | L51: 482.2 | M51: ='Перв. скв '!M51 -> 0 | N51: ='Перв. скв '!N51 -> 0 | O51: =H51*G51 -> 0 | P51: =I51*G51 -> 0 | Q51: =J51*G51 -> 0 | R51: =K51*G51 -> 0 | S51: =L51*G51 -> 1383431.8 | T51: =M51*G51 -> 0 | U51: =N51*G51 -> 0 | V51: =SUM(H51:N51) -> 482.2 | W51: =SUM(O51:U51) -> 1383431.8
D52: ='Перв. скв '!D52 -> Нефть | E52: =D$5 -> не определен | F52: ='Перв. скв '!F52 -> шт. | G52: ='Перв. скв '!G52 -> 166946 | H52: ='Перв. скв '!H52 -> 0 | I52: ='Перв. скв '!I52 -> 0 | J52: ='Перв. скв '!J52 -> 0 | K52: ='Перв. скв '!K52 -> 0 | L52: 1 | M52: ='Перв. скв '!M52 -> 0 | N52: ='Перв. скв '!N52 -> 0 | O52: =H52*G52 -> 0 | P52: =I52*G52 -> 0 | Q52: =J52*G52 -> 0 | R52: =K52*G52 -> 0 | S52: =L52*G52 -> 166946 | T52: =M52*G52 -> 0 | U52: =N52*G52 -> 0 | V52: =SUM(H52:N52) -> 1 | W52: =SUM(O52:U52) -> 166946
D53: Эксплуатация верхнего привода | E53: =D$5 -> не определен | G53: ='Перв. скв '!G53 -> 73942 | H53: ='Перв. скв '!H53 -> 0 | I53: ='Перв. скв '!I53 -> 0 | J53: ='Перв. скв '!J53 -> 0 | K53: ='Перв. скв '!K53 -> 0 | L53: =O6/2 -> 6 | M53: ='Перв. скв '!M53 -> 0 | N53: ='Перв. скв '!N53 -> 0 | O53: =H53*G53 -> 0 | P53: =I53*G53 -> 0 | Q53: =J53*G53 -> 0 | R53: =K53*G53 -> 0 | S53: =L53*G53 -> 443652 | T53: =M53*G53 -> 0 | U53: =N53*G53 -> 0 | V53: =SUM(H53:N53) -> 6 | W53: =SUM(O53:U53) -> 443652
D54: Эксплуатация системы очистки | E54: =D$5 -> не определен | G54: ='Перв. скв '!G54 -> 34796 | H54: ='Перв. скв '!H54 -> 0 | I54: ='Перв. скв '!I54 -> 0 | J54: ='Перв. скв '!J54 -> 0 | K54: ='Перв. скв '!K54 -> 0 | L54: =O6 -> 12 | M54: ='Перв. скв '!M54 -> 0 | N54: ='Перв. скв '!N54 -> 0 | O54: =H54*G54 -> 0 | P54: =I54*G54 -> 0 | Q54: =J54*G54 -> 0 | R54: =K54*G54 -> 0 | S54: =L54*G54 -> 417552 | T54: =M54*G54 -> 0 | U54: =N54*G54 -> 0 | V54: =SUM(H54:N54) -> 12 | W54: =SUM(O54:U54) -> 417552
D55: ='Перв. скв '!D55 -> Бурение по суточной ставке (геологическая нагрузка) | E55: =D$5 -> не определен | F55: ='Перв. скв '!F55 -> опер. | G55: ='Перв. скв '!G55 -> 703259.4 | H55: ='Перв. скв '!H55 -> 0 | I55: ='Перв. скв '!I55 -> 0 | J55: ='Перв. скв '!J55 -> 0 | K55: ='Перв. скв '!K55 -> 0 | L55: 0 | M55: ='Перв. скв '!M55 -> 0 | N55: ='Перв. скв '!N55 -> 0 | O55: =H55*G55 -> 0 | P55: =I55*G55 -> 0 | Q55: =J55*G55 -> 0 | R55: =K55*G55 -> 0 | S55: =L55*G55 -> 0 | T55: =M55*G55 -> 0 | U55: =N55*G55 -> 0 | V55: =SUM(H55:N55) -> 0 | W55: =SUM(O55:U55) -> 0
C56: ПОДРЯДЧИК ПО ДОЛОТАМ: | X56: =SUM(W58:W64) -> 270000
C57: ='Перв. скв '!C57 -> 0 | D57: Описание работ/услуг
C58: (технико-технологичексие особенности) | D58: ='Перв. скв '!D58 -> 550 мм долото для бурения под направление (долото+сервис) | E58: =C$57 -> 0 | F58: ='Перв. скв '!F58 -> м | G58: ='Перв. скв '!G58 -> 90 | H58: ='Перв. скв '!H58 -> 0 | I58: ='Перв. скв '!I58 -> 0 | J58: ='Перв. скв '!J58 -> 0 | K58: ='Перв. скв '!K58 -> 0 | L58: =O9 -> 3000 | M58: ='Перв. скв '!M58 -> 0 | N58: ='Перв. скв '!N58 -> 0 | O58: =H58*G58 -> 0 | P58: =I58*G58 -> 0 | Q58: =J58*G58 -> 0 | R58: =K58*G58 -> 0 | S58: =L58*G58 -> 270000 | T58: =M58*G58 -> 0 | U58: =N58*G58 -> 0 | V58: =SUM(H58:N58) -> 3000 | W58: =SUM(O58:U58) -> 270000
D59: ='Перв. скв '!D59 -> 393,7 мм долото для бурения под направление (долото+сервис) | E59: =C$57 -> 0 | F59: ='Перв. скв '!F59 -> м | G59: ='Перв. скв '!G59 -> 90 | H59: ='Перв. скв '!H59 -> 0 | I59: ='Перв. скв '!I59 -> 0 | J59: ='Перв. скв '!J59 -> 0 | K59: ='Перв. скв '!K59 -> 0 | L59: ='Перв. скв '!L59 -> 0 | M59: ='Перв. скв '!M59 -> 0 | N59: ='Перв. скв '!N59 -> 0 | O59: =H59*G59 -> 0 | P59: =I59*G59 -> 0 | Q59: =J59*G59 -> 0 | R59: =K59*G59 -> 0 | S59: =L59*G59 -> 0 | T59: =M59*G59 -> 0 | U59: =N59*G59 -> 0 | V59: =SUM(H59:N59) -> 0 | W59: =SUM(O59:U59) -> 0
D60: ='Перв. скв '!D60 -> 295,3 мм долото для бурения под кондуктор (долото+сервис) | E60: =C$57 -> 0 | F60: ='Перв. скв '!F60 -> м | G60: ='Перв. скв '!G60 -> 90 | H60: ='Перв. скв '!H60 -> 0 | I60: ='Перв. скв '!I60 -> 0 | J60: ='Перв. скв '!J60 -> 0 | K60: ='Перв. скв '!K60 -> 0 | L60: ='Перв. скв '!L60 -> 0 | M60: ='Перв. скв '!M60 -> 0 | N60: ='Перв. скв '!N60 -> 0 | O60: =H60*G60 -> 0 | P60: =I60*G60 -> 0 | Q60: =J60*G60 -> 0 | R60: =K60*G60 -> 0 | S60: =L60*G60 -> 0 | T60: =M60*G60 -> 0 | U60: =N60*G60 -> 0 | V60: =SUM(H60:N60) -> 0 | W60: =SUM(O60:U60) -> 0
D61: ='Перв. скв '!D61 -> 220,7 мм долото для бурения эксплуатационную колонну (долото+сервис) | E61: =C$57 -> 0 | F61: ='Перв. скв '!F61 -> м | G61: ='Перв. скв '!G61 -> 90 | H61: ='Перв. скв '!H61 -> 0 | I61: ='Перв. скв '!I61 -> 0 | J61: ='Перв. скв '!J61 -> 0 | K61: ='Перв. скв '!K61 -> 0 | L61: ='Перв. скв '!L61 -> 0 | M61: ='Перв. скв '!M61 -> 0 | N61: ='Перв. скв '!N61 -> 0 | O61: =H61*G61 -> 0 | P61: =I61*G61 -> 0 | Q61: =J61*G61 -> 0 | R61: =K61*G61 -> 0 | S61: =L61*G61 -> 0 | T61: =M61*G61 -> 0 | U61: =N61*G61 -> 0 | V61: =SUM(H61:N61) -> 0 | W61: =SUM(O61:U61) -> 0
D62: ='Перв. скв '!D62 -> 155,6 мм долото для бурения под хвостовик (долото+сервис) | E62: =C$57 -> 0 | F62: ='Перв. скв '!F62 -> м | G62: ='Перв. скв '!G62 -> 90 | H62: ='Перв. скв '!H62 -> 0 | I62: ='Перв. скв '!I62 -> 0 | J62: ='Перв. скв '!J62 -> 0 | K62: ='Перв. скв '!K62 -> 0 | L62: ='Перв. скв '!L62 -> 0 | M62: ='Перв. скв '!M62 -> 0 | N62: ='Перв. скв '!N62 -> 0 | O62: =H62*G62 -> 0 | P62: =I62*G62 -> 0 | Q62: =J62*G62 -> 0 | R62: =K62*G62 -> 0 | S62: =L62*G62 -> 0 | T62: =M62*G62 -> 0 | U62: =N62*G62 -> 0 | V62: =SUM(H62:N62) -> 0 | W62: =SUM(O62:U62) -> 0
D63: ='Перв. скв '!D63 -> _________ мм долото для бурения (долото+сервис) | E63: =C$57 -> 0 | F63: ='Перв. скв '!F63 -> м | G63: ='Перв. скв '!G63 -> 0 | H63: ='Перв. скв '!H63 -> 0 | I63: ='Перв. скв '!I63 -> 0 | J63: ='Перв. скв '!J63 -> 0 | K63: ='Перв. скв '!K63 -> 0 | L63: ='Перв. скв '!L63 -> 0 | M63: ='Перв. скв '!M63 -> 0 | N63: ='Перв. скв '!N63 -> 0 | O63: =H63*G63 -> 0 | P63: =I63*G63 -> 0 | Q63: =J63*G63 -> 0 | R63: =K63*G63 -> 0 | S63: =L63*G63 -> 0 | T63: =M63*G63 -> 0 | U63: =N63*G63 -> 0 | V63: =SUM(H63:N63) -> 0 | W63: =SUM(O63:U63) -> 0
D64: ='Перв. скв '!D64 -> Расширитель раздвижной | E64: =C$57 -> 0 | F64: ='Перв. скв '!F64 -> м | G64: ='Перв. скв '!G64 -> 0 | H64: ='Перв. скв '!H64 -> 0 | I64: ='Перв. скв '!I64 -> 0 | J64: ='Перв. скв '!J64 -> 0 | K64: ='Перв. скв '!K64 -> 0 | L64: ='Перв. скв '!L64 -> 0 | M64: ='Перв. скв '!M64 -> 0 | N64: ='Перв. скв '!N64 -> 0 | O64: =H64*G64 -> 0 | P64: =I64*G64 -> 0 | Q64: =J64*G64 -> 0 | R64: =K64*G64 -> 0 | S64: =L64*G64 -> 0 | T64: =M64*G64 -> 0 | U64: =N64*G64 -> 0 | V64: =SUM(H64:N64) -> 0 | W64: =SUM(O64:U64) -> 0
C65: ПОДРЯДЧИК ПО ТЕХНОЛОГИЧЕСКОМУ И ТЕЛЕМЕТРИЧЕСКОМУ СОПРОВОЖДЕНИЮ: | X65: =SUM(W67:W85) -> 10961106
C66: ='Перв. скв '!C66 -> 0 | D66: Описание работ/услуг
C67: (технико-технологичексие особенности) | D67: ='Перв. скв '!D67 -> Фиксированная ставка за скважину с отходом до 1300 м. | E67: =C$66 -> 0 | F67: ='Перв. скв '!F67 -> скв. | G67: ='Перв. скв '!G67 -> 1974979.6 | H67: ='Перв. скв '!H67 -> 0 | I67: ='Перв. скв '!I67 -> 0 | J67: ='Перв. скв '!J67 -> 0 | K67: ='Перв. скв '!K67 -> 0 | L67: =$L$45 -> 1 | M67: ='Перв. скв '!M67 -> 0 | N67: ='Перв. скв '!N67 -> 0 | O67: =H67*G67 -> 0 | P67: =I67*G67 -> 0 | Q67: =J67*G67 -> 0 | R67: =K67*G67 -> 0 | S67: =L67*G67 -> 1974979.6 | T67: =M67*G67 -> 0 | U67: =N67*G67 -> 0 | V67: =SUM(H67:N67) -> 1 | W67: =SUM(O67:U67) -> 1974979.6
D68: ='Перв. скв '!D68 -> Фиксированная ставка за скважину с отходом от 1300 до 1500 м. | E68: =C$66 -> 0 | F68: ='Перв. скв '!F68 -> скв. | G68: ='Перв. скв '!G68 -> 2121689.5 | H68: ='Перв. скв '!H68 -> 0 | I68: ='Перв. скв '!I68 -> 0 | J68: ='Перв. скв '!J68 -> 0 | K68: ='Перв. скв '!K68 -> 0 | L68: =$L$46 -> 0 | M68: ='Перв. скв '!M68 -> 0 | N68: ='Перв. скв '!N68 -> 0 | O68: =H68*G68 -> 0 | P68: =I68*G68 -> 0 | Q68: =J68*G68 -> 0 | R68: =K68*G68 -> 0 | S68: =L68*G68 -> 0 | T68: =M68*G68 -> 0 | U68: =N68*G68 -> 0 | V68: =SUM(H68:N68) -> 0 | W68: =SUM(O68:U68) -> 0
D69: ='Перв. скв '!D69 -> Фиксированная ставка за скважину с отходом от 1500 до 2000 м. | E69: =C$66 -> 0 | F69: ='Перв. скв '!F69 -> скв. | G69: ='Перв. скв '!G69 -> 2436096.7 | H69: ='Перв. скв '!H69 -> 0 | I69: ='Перв. скв '!I69 -> 0 | J69: ='Перв. скв '!J69 -> 0 | K69: ='Перв. скв '!K69 -> 0 | L69: =$L$47 -> 0 | M69: ='Перв. скв '!M69 -> 0 | N69: ='Перв. скв '!N69 -> 0 | O69: =H69*G69 -> 0 | P69: =I69*G69 -> 0 | Q69: =J69*G69 -> 0 | R69: =K69*G69 -> 0 | S69: =L69*G69 -> 0 | T69: =M69*G69 -> 0 | U69: =N69*G69 -> 0 | V69: =SUM(H69:N69) -> 0 | W69: =SUM(O69:U69) -> 0
D70: ='Перв. скв '!D70 -> Фиксированная ставка за скважину с отходом от 2000 до 2200 м. | E70: =C$66 -> 0 | F70: ='Перв. скв '!F70 -> скв. | G70: ='Перв. скв '!G70 -> 2743673.1 | H70: ='Перв. скв '!H70 -> 0 | I70: ='Перв. скв '!I70 -> 0 | J70: ='Перв. скв '!J70 -> 0 | K70: ='Перв. скв '!K70 -> 0 | L70: =$L$48 -> 0 | M70: ='Перв. скв '!M70 -> 0 | N70: ='Перв. скв '!N70 -> 0 | O70: =H70*G70 -> 0 | P70: =I70*G70 -> 0 | Q70: =J70*G70 -> 0 | R70: =K70*G70 -> 0 | S70: =L70*G70 -> 0 | T70: =M70*G70 -> 0 | U70: =N70*G70 -> 0 | V70: =SUM(H70:N70) -> 0 | W70: =SUM(O70:U70) -> 0
D71: ='Перв. скв '!D71 -> Фиксированная ставка за скважину с отходом более 2200 м. | E71: =C$66 -> 0 | F71: ='Перв. скв '!F71 -> скв. | G71: ='Перв. скв '!G71 -> 2903714.7 | H71: ='Перв. скв '!H71 -> 0 | I71: ='Перв. скв '!I71 -> 0 | J71: ='Перв. скв '!J71 -> 0 | K71: ='Перв. скв '!K71 -> 0 | L71: =$L$49 -> 0 | M71: ='Перв. скв '!M71 -> 0 | N71: ='Перв. скв '!N71 -> 0 | O71: =H71*G71 -> 0 | P71: =I71*G71 -> 0 | Q71: =J71*G71 -> 0 | R71: =K71*G71 -> 0 | S71: =L71*G71 -> 0 | T71: =M71*G71 -> 0 | U71: =N71*G71 -> 0 | V71: =SUM(H71:N71) -> 0 | W71: =SUM(O71:U71) -> 0
D72: ='Перв. скв '!D72 -> Фиксированная ставка за горизонтальную скважину | E72: =C$66 -> 0 | F72: ='Перв. скв '!F72 -> скв. | G72: ='Перв. скв '!G72 -> 8986126 | H72: ='Перв. скв '!H72 -> 0 | I72: ='Перв. скв '!I72 -> 0 | J72: ='Перв. скв '!J72 -> 0 | K72: ='Перв. скв '!K72 -> 0 | L72: =$L$50 -> 1 | M72: ='Перв. скв '!M72 -> 0 | N72: ='Перв. скв '!N72 -> 0 | O72: =H72*G72 -> 0 | P72: =I72*G72 -> 0 | Q72: =J72*G72 -> 0 | R72: =K72*G72 -> 0 | S72: =L72*G72 -> 8986126 | T72: =M72*G72 -> 0 | U72: =N72*G72 -> 0 | V72: =SUM(H72:N72) -> 1 | W72: =SUM(O72:U72) -> 8986126
D73: ='Перв. скв '!D73 -> 0 | E73: =C$66 -> 0 | F73: ='Перв. скв '!F73 -> сут | G73: ='Перв. скв '!G73 -> 0 | O73: =H73*G73 -> 0 | P73: =I73*G73 -> 0 | Q73: =J73*G73 -> 0 | R73: =K73*G73 -> 0 | S73: =L73*G73 -> 0 | T73: =M73*G73 -> 0 | U73: =N73*G73 -> 0 | V73: =SUM(H73:N73) -> 0 | W73: =SUM(O73:U73) -> 0
D74: ='Перв. скв '!D74 -> 0 | E74: =C$66 -> 0 | F74: ='Перв. скв '!F74 -> сут | G74: ='Перв. скв '!G74 -> 0 | O74: =H74*G74 -> 0 | P74: =I74*G74 -> 0 | Q74: =J74*G74 -> 0 | R74: =K74*G74 -> 0 | S74: =L74*G74 -> 0 | T74: =M74*G74 -> 0 | U74: =N74*G74 -> 0 | V74: =SUM(H74:N74) -> 0 | W74: =SUM(O74:U74) -> 0
D75: ='Перв. скв '!D75 -> 0 | E75: =C$66 -> 0 | F75: ='Перв. скв '!F75 -> сут | G75: ='Перв. скв '!G75 -> 0 | O75: =H75*G75 -> 0 | P75: =I75*G75 -> 0 | Q75: =J75*G75 -> 0 | R75: =K75*G75 -> 0 | S75: =L75*G75 -> 0 | T75: =M75*G75 -> 0 | U75: =N75*G75 -> 0 | V75: =SUM(H75:N75) -> 0 | W75: =SUM(O75:U75) -> 0
D76: ='Перв. скв '!D76 -> Мобилизация на объект работ | E76: =C$66 -> 0 | F76: ='Перв. скв '!F76 -> опер. | G76: ='Перв. скв '!G76 -> 0 | O76: =H76*G76 -> 0 | P76: =I76*G76 -> 0 | Q76: =J76*G76 -> 0 | R76: =K76*G76 -> 0 | S76: =L76*G76 -> 0 | T76: =M76*G76 -> 0 | U76: =N76*G76 -> 0 | V76: =SUM(H76:N76) -> 0 | W76: =SUM(O76:U76) -> 0
D77: ='Перв. скв '!D77 -> Демобилизация | E77: =C$66 -> 0 | F77: ='Перв. скв '!F77 -> опер. | G77: ='Перв. скв '!G77 -> 0 | O77: =H77*G77 -> 0 | P77: =I77*G77 -> 0 | Q77: =J77*G77 -> 0 | R77: =K77*G77 -> 0 | S77: =L77*G77 -> 0 | T77: =M77*G77 -> 0 | U77: =N77*G77 -> 0 | V77: =SUM(H77:N77) -> 0 | W77: =SUM(O77:U77) -> 0
C78: ='Перв. скв '!C78 -> 0 | D78: Описание работ/услуг
C79: (технико-технологичексие особенности) | D79: ='Перв. скв '!D79 -> Операционная ставка в режиме работы | E79: =C$78 -> 0 | F79: ='Перв. скв '!F79 -> сут | G79: ='Перв. скв '!G79 -> 0 | O79: =H79*G79 -> 0 | P79: =I79*G79 -> 0 | Q79: =J79*G79 -> 0 | R79: =K79*G79 -> 0 | S79: =L79*G79 -> 0 | T79: =M79*G79 -> 0 | U79: =N79*G79 -> 0 | V79: =SUM(H79:N79) -> 0 | W79: =SUM(O79:U79) -> 0
D80: ='Перв. скв '!D80 -> Операционная ставка в режиме ожидания | E80: =C$78 -> 0 | F80: ='Перв. скв '!F80 -> сут | G80: ='Перв. скв '!G80 -> 0 | O80: =H80*G80 -> 0 | P80: =I80*G80 -> 0 | Q80: =J80*G80 -> 0 | R80: =K80*G80 -> 0 | S80: =L80*G80 -> 0 | T80: =M80*G80 -> 0 | U80: =N80*G80 -> 0 | V80: =SUM(H80:N80) -> 0 | W80: =SUM(O80:U80) -> 0
D81: ='Перв. скв '!D81 -> Гамма -каротаж и сопротивление в режиме записи | E81: =C$78 -> 0 | F81: ='Перв. скв '!F81 -> сут | G81: ='Перв. скв '!G81 -> 0 | O81: =H81*G81 -> 0 | P81: =I81*G81 -> 0 | Q81: =J81*G81 -> 0 | R81: =K81*G81 -> 0 | S81: =L81*G81 -> 0 | T81: =M81*G81 -> 0 | U81: =N81*G81 -> 0 | V81: =SUM(H81:N81) -> 0 | W81: =SUM(O81:U81) -> 0
D82: ='Перв. скв '!D82 -> Гамма -каротаж и сопротивление в режиме реального времени | E82: =C$78 -> 0 | F82: ='Перв. скв '!F82 -> сут | G82: ='Перв. скв '!G82 -> 0 | O82: =H82*G82 -> 0 | P82: =I82*G82 -> 0 | Q82: =J82*G82 -> 0 | R82: =K82*G82 -> 0 | S82: =L82*G82 -> 0 | T82: =M82*G82 -> 0 | U82: =N82*G82 -> 0 | V82: =SUM(H82:N82) -> 0 | W82: =SUM(O82:U82) -> 0
D83: ='Перв. скв '!D83 -> Гамма -каротаж в режиме записи | E83: =C$78 -> 0 | F83: ='Перв. скв '!F83 -> сут | G83: ='Перв. скв '!G83 -> 0 | O83: =H83*G83 -> 0 | P83: =I83*G83 -> 0 | Q83: =J83*G83 -> 0 | R83: =K83*G83 -> 0 | S83: =L83*G83 -> 0 | T83: =M83*G83 -> 0 | U83: =N83*G83 -> 0 | V83: =SUM(H83:N83) -> 0 | W83: =SUM(O83:U83) -> 0
D84: ='Перв. скв '!D84 -> Гамма -каротаж в режиме реального времени | E84: =C$78 -> 0 | F84: ='Перв. скв '!F84 -> сут | G84: ='Перв. скв '!G84 -> 0 | O84: =H84*G84 -> 0 | P84: =I84*G84 -> 0 | Q84: =J84*G84 -> 0 | R84: =K84*G84 -> 0 | S84: =L84*G84 -> 0 | T84: =M84*G84 -> 0 | U84: =N84*G84 -> 0 | V84: =SUM(H84:N84) -> 0 | W84: =SUM(O84:U84) -> 0
D85: ='Перв. скв '!D85 -> Услуги персонала телеметрического и технологического сопровождения | E85: =C$78 -> 0 | F85: ='Перв. скв '!F85 -> сут | G85: ='Перв. скв '!G85 -> 0 | O85: =H85*G85 -> 0 | P85: =I85*G85 -> 0 | Q85: =J85*G85 -> 0 | R85: =K85*G85 -> 0 | S85: =L85*G85 -> 0 | T85: =M85*G85 -> 0 | U85: =N85*G85 -> 0 | V85: =SUM(H85:N85) -> 0 | W85: =SUM(O85:U85) -> 0
C86: ПОДРЯДЧИК ПО БУРОВЫМ РАСТВОРАМ: | X86: =SUM(W88:W93) -> 6329273.5
C87: ='Перв. скв '!C87 -> 0 | D87: Описание работ/услуг
C88: (технико-технологичексие особенности) | D88: ='Перв. скв '!D88 -> Фиксированная ставка за скважину с отходом до 1300 м. | E88: =C$87 -> 0 | F88: ='Перв. скв '!F88 -> скв. | G88: ='Перв. скв '!G88 -> 807557.8 | H88: ='Перв. скв '!H88 -> 0 | I88: ='Перв. скв '!I88 -> 0 | J88: ='Перв. скв '!J88 -> 0 | K88: ='Перв. скв '!K88 -> 0 | L88: =$L$45 -> 1 | M88: ='Перв. скв '!M88 -> 0 | N88: ='Перв. скв '!N88 -> 0 | O88: =H88*G88 -> 0 | P88: =I88*G88 -> 0 | Q88: =J88*G88 -> 0 | R88: =K88*G88 -> 0 | S88: =L88*G88 -> 807557.8 | T88: =M88*G88 -> 0 | U88: =N88*G88 -> 0 | V88: =SUM(H88:N88) -> 1 | W88: =SUM(O88:U88) -> 807557.8
D89: ='Перв. скв '!D89 -> Фиксированная ставка за скважину с отходом от 1300 до 1500 м. | E89: =C$87 -> 0 | F89: ='Перв. скв '!F89 -> скв. | G89: ='Перв. скв '!G89 -> 883911 | H89: ='Перв. скв '!H89 -> 0 | I89: ='Перв. скв '!I89 -> 0 | J89: ='Перв. скв '!J89 -> 0 | K89: ='Перв. скв '!K89 -> 0 | L89: =$L$46 -> 0 | M89: ='Перв. скв '!M89 -> 0 | N89: ='Перв. скв '!N89 -> 0 | O89: =H89*G89 -> 0 | P89: =I89*G89 -> 0 | Q89: =J89*G89 -> 0 | R89: =K89*G89 -> 0 | S89: =L89*G89 -> 0 | T89: =M89*G89 -> 0 | U89: =N89*G89 -> 0 | V89: =SUM(H89:N89) -> 0 | W89: =SUM(O89:U89) -> 0
D90: ='Перв. скв '!D90 -> Фиксированная ставка за скважину с отходом от 1500 до 2000 м. | E90: =C$87 -> 0 | F90: ='Перв. скв '!F90 -> скв. | G90: ='Перв. скв '!G90 -> 883911 | H90: ='Перв. скв '!H90 -> 0 | I90: ='Перв. скв '!I90 -> 0 | J90: ='Перв. скв '!J90 -> 0 | K90: ='Перв. скв '!K90 -> 0 | L90: =$L$47 -> 0 | M90: ='Перв. скв '!M90 -> 0 | N90: ='Перв. скв '!N90 -> 0 | O90: =H90*G90 -> 0 | P90: =I90*G90 -> 0 | Q90: =J90*G90 -> 0 | R90: =K90*G90 -> 0 | S90: =L90*G90 -> 0 | T90: =M90*G90 -> 0 | U90: =N90*G90 -> 0 | V90: =SUM(H90:N90) -> 0 | W90: =SUM(O90:U90) -> 0
D91: ='Перв. скв '!D91 -> Фиксированная ставка за скважину с отходом от 2000 до 2200 м. | E91: =C$87 -> 0 | F91: ='Перв. скв '!F91 -> скв. | G91: ='Перв. скв '!G91 -> 1125553 | H91: ='Перв. скв '!H91 -> 0 | I91: ='Перв. скв '!I91 -> 0 | J91: ='Перв. скв '!J91 -> 0 | K91: ='Перв. скв '!K91 -> 0 | L91: =$L$48 -> 0 | M91: ='Перв. скв '!M91 -> 0 | N91: ='Перв. скв '!N91 -> 0 | O91: =H91*G91 -> 0 | P91: =I91*G91 -> 0 | Q91: =J91*G91 -> 0 | R91: =K91*G91 -> 0 | S91: =L91*G91 -> 0 | T91: =M91*G91 -> 0 | U91: =N91*G91 -> 0 | V91: =SUM(H91:N91) -> 0 | W91: =SUM(O91:U91) -> 0
D92: ='Перв. скв '!D92 -> Фиксированная ставка за скважину с отходом более 2200 м. | E92: =C$87 -> 0 | F92: ='Перв. скв '!F92 -> сут. | G92: ='Перв. скв '!G92 -> 1381613.2 | H92: ='Перв. скв '!H92 -> 0 | I92: ='Перв. скв '!I92 -> 0 | J92: ='Перв. скв '!J92 -> 0 | K92: ='Перв. скв '!K92 -> 0 | L92: =$L$49 -> 0 | M92: ='Перв. скв '!M92 -> 0 | N92: ='Перв. скв '!N92 -> 0 | O92: =H92*G92 -> 0 | P92: =I92*G92 -> 0 | Q92: =J92*G92 -> 0 | R92: =K92*G92 -> 0 | S92: =L92*G92 -> 0 | T92: =M92*G92 -> 0 | U92: =N92*G92 -> 0 | V92: =SUM(H92:N92) -> 0 | W92: =SUM(O92:U92) -> 0
D93: ='Перв. скв '!D93 -> Фиксированная ставка за горизонтальную скважину | E93: =C$87 -> 0 | F93: ='Перв. скв '!F93 -> скв. | G93: ='Перв. скв '!G93 -> 5521715.7 | H93: ='Перв. скв '!H93 -> 0 | I93: ='Перв. скв '!I93 -> 0 | J93: ='Перв. скв '!J93 -> 0 | K93: ='Перв. скв '!K93 -> 0 | L93: =$L$50 -> 1 | M93: ='Перв. скв '!M93 -> 0 | N93: ='Перв. скв '!N93 -> 0 | O93: =H93*G93 -> 0 | P93: =I93*G93 -> 0 | Q93: =J93*G93 -> 0 | R93: =K93*G93 -> 0 | S93: =L93*G93 -> 5521715.7 | T93: =M93*G93 -> 0 | U93: =N93*G93 -> 0 | V93: =SUM(H93:N93) -> 1 | W93: =SUM(O93:U93) -> 5521715.7
C94: ПОДРЯДЧИК ПО ЦЕМЕНТИРОВАНИЮ: | X94: =SUM(W96:W111) -> 2588946
C95: ='Перв. скв '!C95 -> 0 | D95: Описание работ/услуг
C96: 324 | D96: ='Перв. скв '!D96 -> Цементирование направления НН 426 мм (услуги, цемент, материалы) | E96: =C$95 -> 0 | F96: ='Перв. скв '!F96 -> опер | G96: ='Перв. скв '!G96 -> 261088 | H96: ='Перв. скв '!H96 -> 0 | I96: ='Перв. скв '!I96 -> 0 | J96: ='Перв. скв '!J96 -> 0 | K96: ='Перв. скв '!K96 -> 0 | L96: ='Перв. скв '!L96 -> 1 | M96: ='Перв. скв '!M96 -> 0 | N96: ='Перв. скв '!N96 -> 0 | O96: =H96*G96 -> 0 | P96: =I96*G96 -> 0 | Q96: =J96*G96 -> 0 | R96: =K96*G96 -> 0 | S96: =L96*G96 -> 261088 | T96: =M96*G96 -> 0 | U96: =N96*G96 -> 0 | V96: =SUM(H96:N96) -> 1 | W96: =SUM(O96:U96) -> 261088
C97: 245 | D97: ='Перв. скв '!D97 -> Цементирование кондуктора НН 324 мм (услуги, цемент, материалы) | E97: =C$95 -> 0 | F97: ='Перв. скв '!F97 -> опер | G97: ='Перв. скв '!G97 -> 450018 | H97: ='Перв. скв '!H97 -> 0 | I97: ='Перв. скв '!I97 -> 0 | J97: ='Перв. скв '!J97 -> 0 | K97: ='Перв. скв '!K97 -> 0 | L97: ='Перв. скв '!L97 -> 1 | M97: ='Перв. скв '!M97 -> 0 | N97: ='Перв. скв '!N97 -> 0 | O97: =H97*G97 -> 0 | P97: =I97*G97 -> 0 | Q97: =J97*G97 -> 0 | R97: =K97*G97 -> 0 | S97: =L97*G97 -> 450018 | T97: =M97*G97 -> 0 | U97: =N97*G97 -> 0 | V97: =SUM(H97:N97) -> 1 | W97: =SUM(O97:U97) -> 450018
C98: 178 | D98: ='Перв. скв '!D98 -> Цементирование технической колонны Гор 245 мм (услуги, цемент, материалы) | E98: =C$95 -> 0 | F98: ='Перв. скв '!F98 -> опер | G98: ='Перв. скв '!G98 -> 0 | H98: ='Перв. скв '!H98 -> 0 | I98: ='Перв. скв '!I98 -> 0 | J98: ='Перв. скв '!J98 -> 0 | K98: ='Перв. скв '!K98 -> 0 | L98: ='Перв. скв '!L98 -> 0 | M98: ='Перв. скв '!M98 -> 0 | N98: ='Перв. скв '!N98 -> 0 | O98: =H98*G98 -> 0 | P98: =I98*G98 -> 0 | Q98: =J98*G98 -> 0 | R98: =K98*G98 -> 0 | S98: =L98*G98 -> 0 | T98: =M98*G98 -> 0 | U98: =N98*G98 -> 0 | V98: =SUM(H98:N98) -> 0 | W98: =SUM(O98:U98) -> 0
C99: 324 | D99: ='Перв. скв '!D99 -> Цементирование эксплуатационной колонны 178мм (услуги, цемент, материалы) | E99: =C$95 -> 0 | F99: ='Перв. скв '!F99 -> опер | G99: ='Перв. скв '!G99 -> 1433230 | H99: ='Перв. скв '!H99 -> 0 | I99: ='Перв. скв '!I99 -> 0 | J99: ='Перв. скв '!J99 -> 0 | K99: ='Перв. скв '!K99 -> 0 | L99: ='Перв. скв '!L99 -> 1 | M99: ='Перв. скв '!M99 -> 0 | N99: ='Перв. скв '!N99 -> 0 | O99: =H99*G99 -> 0 | P99: =I99*G99 -> 0 | Q99: =J99*G99 -> 0 | R99: =K99*G99 -> 0 | S99: =L99*G99 -> 1433230 | T99: =M99*G99 -> 0 | U99: =N99*G99 -> 0 | V99: =SUM(H99:N99) -> 1 | W99: =SUM(O99:U99) -> 1433230
C100: 245 | D100: ='Перв. скв '!D100 -> Цементирование направления НН 324 мм (услуги, цемент, материалы) | E100: =C$95 -> 0 | F100: ='Перв. скв '!F100 -> опер | G100: ='Перв. скв '!G100 -> 0 | H100: ='Перв. скв '!H100 -> 0 | I100: ='Перв. скв '!I100 -> 0 | J100: ='Перв. скв '!J100 -> 0 | K100: ='Перв. скв '!K100 -> 0 | L100: ='Перв. скв '!L100 -> 0 | M100: ='Перв. скв '!M100 -> 0 | N100: ='Перв. скв '!N100 -> 0 | O100: =H100*G100 -> 0 | P100: =I100*G100 -> 0 | Q100: =J100*G100 -> 0 | R100: =K100*G100 -> 0 | S100: =L100*G100 -> 0 | T100: =M100*G100 -> 0 | U100: =N100*G100 -> 0 | V100: =SUM(H100:N100) -> 0 | W100: =SUM(O100:U100) -> 0
C101: 178 | D101: ='Перв. скв '!D101 -> Цементирование кондуктора НН 245 мм (услуги, цемент, материалы) | E101: =C$95 -> 0 | F101: ='Перв. скв '!F101 -> опер | G101: ='Перв. скв '!G101 -> 0 | H101: ='Перв. скв '!H101 -> 0 | I101: ='Перв. скв '!I101 -> 0 | J101: ='Перв. скв '!J101 -> 0 | K101: ='Перв. скв '!K101 -> 0 | L101: ='Перв. скв '!L101 -> 0 | M101: ='Перв. скв '!M101 -> 0 | N101: ='Перв. скв '!N101 -> 0 | O101: =H101*G101 -> 0 | P101: =I101*G101 -> 0 | Q101: =J101*G101 -> 0 | R101: =K101*G101 -> 0 | S101: =L101*G101 -> 0 | T101: =M101*G101 -> 0 | U101: =N101*G101 -> 0 | V101: =SUM(H101:N101) -> 0 | W101: =SUM(O101:U101) -> 0
C102: 324 | D102: ='Перв. скв '!D102 -> Цементирование эксплуатационной колонны НН 178мм (услуги, цемент, материалы) | E102: =C$95 -> 0 | F102: ='Перв. скв '!F102 -> опер | G102: ='Перв. скв '!G102 -> 0 | H102: ='Перв. скв '!H102 -> 0 | I102: ='Перв. скв '!I102 -> 0 | J102: ='Перв. скв '!J102 -> 0 | K102: ='Перв. скв '!K102 -> 0 | L102: ='Перв. скв '!L102 -> 0 | M102: ='Перв. скв '!M102 -> 0 | N102: ='Перв. скв '!N102 -> 0 | O102: =H102*G102 -> 0 | P102: =I102*G102 -> 0 | Q102: =J102*G102 -> 0 | R102: =K102*G102 -> 0 | S102: =L102*G102 -> 0 | T102: =M102*G102 -> 0 | U102: =N102*G102 -> 0 | V102: =SUM(H102:N102) -> 0 | W102: =SUM(O102:U102) -> 0
D103: ='Перв. скв '!D103 -> Цементирование хвостовика НН 127мм (услуги, цемент, материалы) | E103: =C$95 -> 0 | F103: ='Перв. скв '!F103 -> опер | G103: ='Перв. скв '!G103 -> 0 | H103: ='Перв. скв '!H103 -> 0 | I103: ='Перв. скв '!I103 -> 0 | J103: ='Перв. скв '!J103 -> 0 | K103: ='Перв. скв '!K103 -> 0 | L103: ='Перв. скв '!L103 -> 0 | M103: ='Перв. скв '!M103 -> 0 | N103: ='Перв. скв '!N103 -> 0 | O103: =H103*G103 -> 0 | P103: =I103*G103 -> 0 | Q103: =J103*G103 -> 0 | R103: =K103*G103 -> 0 | S103: =L103*G103 -> 0 | T103: =M103*G103 -> 0 | U103: =N103*G103 -> 0 | V103: =SUM(H103:N103) -> 0 | W103: =SUM(O103:U103) -> 0
D104: ='Перв. скв '!D104 -> Цементирование технической колонны НН 245 мм (услуги, цемент, материалы) | E104: =C$95 -> 0 | F104: ='Перв. скв '!F104 -> опер | G104: ='Перв. скв '!G104 -> 0 | H104: ='Перв. скв '!H104 -> 0 | I104: ='Перв. скв '!I104 -> 0 | J104: ='Перв. скв '!J104 -> 0 | K104: ='Перв. скв '!K104 -> 0 | L104: ='Перв. скв '!L104 -> 0 | M104: ='Перв. скв '!M104 -> 0 | N104: ='Перв. скв '!N104 -> 0 | O104: =H104*G104 -> 0 | P104: =I104*G104 -> 0 | Q104: =J104*G104 -> 0 | R104: =K104*G104 -> 0 | S104: =L104*G104 -> 0 | T104: =M104*G104 -> 0 | U104: =N104*G104 -> 0 | V104: =SUM(H104:N104) -> 0 | W104: =SUM(O104:U104) -> 0
C105: 245 | D105: ='Перв. скв '!D105 -> Транспортировка цемента | E105: =C$95 -> 0 | F105: ='Перв. скв '!F105 -> опер | G105: ='Перв. скв '!G105 -> 0 | H105: ='Перв. скв '!H105 -> 0 | I105: ='Перв. скв '!I105 -> 0 | J105: ='Перв. скв '!J105 -> 0 | K105: ='Перв. скв '!K105 -> 0 | L105: ='Перв. скв '!L105 -> 0 | M105: ='Перв. скв '!M105 -> 0 | N105: ='Перв. скв '!N105 -> 0 | O105: =H105*G105 -> 0 | P105: =I105*G105 -> 0 | Q105: =J105*G105 -> 0 | R105: =K105*G105 -> 0 | S105: =L105*G105 -> 0 | T105: =M105*G105 -> 0 | U105: =N105*G105 -> 0 | V105: =SUM(H105:N105) -> 0 | W105: =SUM(O105:U105) -> 0
...

Sheet ННСот1300до1500
A2: ПОДРОБНАЯ СМЕТНАЯ СТОИМОСТЬ СКВАЖИНЫ
C4: Месторождение/ куст: | D4: ='Титул '!G5 -> куст №21б Приобского месторождения | E4: ВСЕГО СТ-ТЬ | F4: Исходные данные | H4: Перед забуркой | I4: Направление | J4: Кондуктор | K4: Техническая колонна | L4: Эксплуат-ая колонна | M4: Крепление колонн | N4: Хвостовик | O4: ВСЕГО БУРЕНИЕ | P4: Исходные данные | R4: ВСЕГО ОСВОЕНИЕ
C5: Подрядчик по бурению: | D5: ='Титул '!C11 -> не определен | E5: =IF(($L$45+$L$46+$L$47+$L$48+$L$49+$L$50)>0,$D$214,0) -> 1.0850179e+08
C6: Тип буровой установки: | D6: ='Титул '!C12 -> БУ-3000 ЭУК | E6: Всего ВМР | F6: Время бурения секции, сут: | I6: 1 | J6: 3 | L6: 5 | M6: 3 | N6: 0 | O6: =IF(($L$45+$L$46+$L$47+$L$48+$L$49+$L$50)>0,SUM(I6:N6),0) -> 12 | P6: Время освоения, сут: | R6: =IF(($L$45+$L$46+$L$47+$L$48+$L$49+$L$50)>0,SUM(R8:R10),0) -> 17
C7: Тип скважины: | D7: Наклонно-направленная | E7: =IF(($L$45+$L$46+$L$47+$L$48+$L$49+$L$50)>0,$W$41,0) -> 471302.12 | F7: Глубина (по стволу), м: | I7: 120 | J7: 1280 | L7: 3250 | O7: ВСЕГО ПРОХОДКА | P7: В т.ч.время работы бригад КРС
C8: Проходка всего (м): | D8: 3250 | E8: Всего Бурение | F8: Диаметр долота, мм: | I8: 393 | J8: 300 | L8: 220 | P8: - ПЗР к ГРП/МСГРП, сут. | R8: 13
C9: Наличие СВП: | D9: ='Титул '!C13 -> да | E9: =IF(($L$45+$L$46+$L$47+$L$48+$L$49+$L$50)>0,$W$190,0) -> 71125996 | F9: Диаметр колонны, мм: | I9: 324 | J9: 245 | L9: 168 | O9: =D8 -> 3250 | P9: - проведение ГРП/МСГРП, сут. | R9: 1
C10: Наличие АИЭС: | D10: ='Титул '!C14 -> нет | E10: Всего Освоение | F10: Исходные данные | H10: Отход | I10: Пилот ГС | J10: Перебур | K10: Гориз.уч. 1 | L10: Гориз.уч. 2 | M10: Керн | O10: ГЛУБИНА ПО ВЕРТ-ЛИ | P10: - проведение ГНКТ, сут. | R10: 3
C11: Наличие автономности: | D11: ='Титул '!C15 -> нет | E11: =IF(($L$45+$L$46+$L$47+$L$48+$L$49+$L$50)>0,$W$206,0) -> 36904487 | F11: Отдельные стволы, керн, м: | P11: - кол-во стадий МСГРП, шт. | R11: 2
C12: Кол-во обсадных колонн (включая направл.): | D12: 3 | E12: Обор-ие устья | F12: Примечание: | P12: Примечание:
C13: Прочие существенные условия: | E13: =IF(($L$45+$L$46+$L$47+$L$48+$L$49+$L$50)>0,$W$212,0) -> 0
A15: ОПИСАНИЕ РАБОТ И УСЛУГ | H15: КОЛИЧЕСТВО | O15: СТОИМОСТЬ | V15: ВСЕГО
A16: КОД | B16: добавочный код | C16: СТАТЬЯ ЗАТРАТ | D16: ОПИСАНИЕ | E16: Подрядчик | F16: Единица измерения | G16: Руб. / Ед.изм. | H16: ПЗР (в т.ч. ВМР и осв.) | I16: =+I4 -> Направление | J16: =+J4 -> Кондуктор | K16: =+K4 -> Техническая колонна | L16: =+L4 -> Эксплуат-ая колонна | M16: Крепление колонн | N16: =+N4 -> Хвостовик | O16: ПЗР (в т.ч. ВМР и осв.) | P16: =+I16 -> Направление | Q16: =+J16 -> Кондуктор | R16: =+K16 -> Техническая колонна | S16: =+L16 -> Эксплуат-ая колонна | T16: Крепление колонн | U16: =+N16 -> Хвостовик | V16: Количество | W16: Стоимость (руб) | X16: ВСЕГО СТОИМОСТЬ
C18: 1. ЭТАП ВМР | X18: =SUM(W20:W40) -> 471302.12
C19: ='Перв. скв '!C19 -> не определен | D19: Описание работ/услуг
D20: ='Перв. скв '!D20 -> Монтаж | E20: =D$5 -> не определен | F20: ='Перв. скв '!F20 -> опер. | G20: ='Перв. скв '!G20 -> 9401938 | O20: =H20*G20 -> 0 | V20: =SUM(H20:N20) -> 0 | W20: =SUM(O20:U20) -> 0
D21: ='Перв. скв '!D21 -> Демонтаж | E21: =D$5 -> не определен | F21: ='Перв. скв '!F21 -> опер. | G21: ='Перв. скв '!G21 -> 2344149 | O21: =H21*G21 -> 0 | V21: =SUM(H21:N21) -> 0 | W21: =SUM(O21:U21) -> 0
D22: ='Перв. скв '!D22 -> Эксплуатация АВЭС | E22: =D$5 -> не определен | F22: ='Перв. скв '!F22 -> опер. | G22: ='Перв. скв '!G22 -> 0 | O22: =H22*G22 -> 0 | V22: =SUM(H22:N22) -> 0 | W22: =SUM(O22:U22) -> 0
D23: ='Перв. скв '!D23 -> Передислокация БУ в пределах м-я | E23: =D$5 -> не определен | F23: ='Перв. скв '!F23 -> опер. | G23: ='Перв. скв '!G23 -> 693236 | O23: =H23*G23 -> 0 | V23: =SUM(H23:N23) -> 0 | W23: =SUM(O23:U23) -> 0
D24: ='Перв. скв '!D24 -> Передислокация БУ 250-500 км. | E24: =D$5 -> не определен | F24: ='Перв. скв '!F24 -> опер. | G24: ='Перв. скв '!G24 -> 9837322 | O24: =H24*G24 -> 0 | V24: =SUM(H24:N24) -> 0 | W24: =SUM(O24:U24) -> 0
D25: ='Перв. скв '!D25 -> Передислокация бр. бур в пределах м-я | E25: =D$5 -> не определен | F25: ='Перв. скв '!F25 -> опер. | G25: ='Перв. скв '!G25 -> 130867 | O25: =H25*G25 -> 0 | V25: =SUM(H25:N25) -> 0 | W25: =SUM(O25:U25) -> 0
D26: ='Перв. скв '!D26 -> Передислокация бр. бур 250-500 км. | E26: =D$5 -> не определен | F26: ='Перв. скв '!F26 -> опер. | G26: ='Перв. скв '!G26 -> 1788526 | O26: =H26*G26 -> 0 | V26: =SUM(H26:N26) -> 0 | W26: =SUM(O26:U26) -> 0
D27: ='Перв. скв '!D27 -> Передислокация бригады ВМР в пределах м-я | E27: =D$5 -> не определен | F27: ='Перв. скв '!F27 -> опер. | G27: ='Перв. скв '!G27 -> 130867 | O27: =H27*G27 -> 0 | V27: =SUM(H27:N27) -> 0 | W27: =SUM(O27:U27) -> 0
D28: ='Перв. скв '!D28 -> Передислокация бригады ВМР 250-500 км. | E28: =D$5 -> не определен | F28: ='Перв. скв '!F28 -> опер. | G28: ='Перв. скв '!G28 -> 1788526 | O28: =H28*G28 -> 0 | V28: =SUM(H28:N28) -> 0 | W28: =SUM(O28:U28) -> 0
D29: ='Перв. скв '!D29 -> Передвижка 5 м. | E29: =D$5 -> не определен | F29: ='Перв. скв '!F29 -> опер. | G29: ='Перв. скв '!G29 -> 244497 | O29: =H29*G29 -> 0 | V29: =SUM(H29:N29) -> 0 | W29: =SUM(O29:U29) -> 0
D30: ='Перв. скв '!D30 -> Передвижка 9 м. | E30: =D$5 -> не определен | F30: ='Перв. скв '!F30 -> опер. | G30: ='Перв. скв '!G30 -> 265365 | H30: 1 | O30: =H30*G30 -> 265365 | V30: =SUM(H30:N30) -> 1 | W30: =SUM(O30:U30) -> 265365
D31: ='Перв. скв '!D31 -> Передвижка 18 м. | E31: =D$5 -> не определен | F31: ='Перв. скв '!F31 -> опер. | G31: ='Перв. скв '!G31 -> 406328 | O31: =H31*G31 -> 0 | V31: =SUM(H31:N31) -> 0 | W31: =SUM(O31:U31) -> 0
D32: ='Перв. скв '!D32 -> Передвижка 25 м. | E32: =D$5 -> не определен | F32: ='Перв. скв '!F32 -> опер. | G32: ='Перв. скв '!G32 -> 462462 | O32: =H32*G32 -> 0 | V32: =SUM(H32:N32) -> 0 | W32: =SUM(O32:U32) -> 0
D33: ='Перв. скв '!D33 -> Передвижка 50 м. | E33: =D$5 -> не определен | F33: ='Перв. скв '!F33 -> опер. | G33: ='Перв. скв '!G33 -> 889289 | O33: =H33*G33 -> 0 | V33: =SUM(H33:N33) -> 0 | W33: =SUM(O33:U33) -> 0
