Workbook
Name ___Dec1: 0
Name ___Dec2: 0
Name ___w306: [1]wells_graf!$A$47:$P$69
Name ___w5221: [1]wells_graf!$A$24:$P$46
Name ___w606: [1]wells_graf!$A$1:$H$23
Name ___w628: [1]wells_graf!$I$47:$P$69
Name ___w68: [1]wells_graf!$I$24:$P$46
Name ___W688: [2]wells_graf!$I$24:$P$46
Name __Dec1: 0
Name __Dec2: 0
Name __w306: [1]wells_graf!$A$47:$P$69
Name __w5221: [1]wells_graf!$A$24:$P$46
Name __w606: [1]wells_graf!$A$1:$H$23
Name __w628: [1]wells_graf!$I$47:$P$69
Name __w68: [1]wells_graf!$I$24:$P$46
Name __W688: [2]wells_graf!$I$24:$P$46
Name _2049_2050: '[3]311-1Á10'!#REF!
Name _2049_2050: '[3]311-1Á10'!#REF!
Name _2049_2050: '[3]311-1Á10'!#REF!
Name _2049_2050: '[3]311-1Á10'!#REF!
Name _2049_2050: '[3]311-1Á10'!#REF!
Name _2049_2050: '[3]311-1Á10'!#REF!
Name _2049_2050: '[3]311-1Á10'!#REF!
Name _2049_2050: '[3]311-1Á10'!#REF!
Name _2049_2050: '[3]311-1Á10'!#REF!
Name _2049_2050: '[3]311-1Á10'!#REF!
Name _2049_2050: '[3]311-1Á10'!#REF!
Name _2049_2050: '[3]311-1Á10'!#REF!
Name _2049_2050: '[3]311-1Á10'!#REF!
Name _2049_2050: '[3]311-1Á10'!#REF!
Name _2049_2050: '[3]311-1Á10'!#REF!
Name _2049_2050: '[3]311-1Á10'!#REF!
Name _2049_2050: '[3]311-1Á10'!#REF!
Name _2049_2050: '[3]311-1Á10'!#REF!
Name _Dec1: 0
Name _Dec2: 0
Name _w306: [1]wells_graf!$A$47:$P$69
Name _w5221: [1]wells_graf!$A$24:$P$46
Name _w606: [1]wells_graf!$A$1:$H$23
Name _w628: [1]wells_graf!$I$47:$P$69
Name _w68: [1]wells_graf!$I$24:$P$46
Name _W688: [2]wells_graf!$I$24:$P$46
Name add1_1Q: [4]Resources!$C$172
Name add1_2Q: [4]Resources!$C$173
Name add1_3D_seismic: [4]Resources!$C$188
Name add1_3Q: [4]Resources!$C$174
Name add1_4Q: [4]Resources!$C$175
Name add1_bases: [4]Resources!$C$195
Name add1_capex_investments: [4]Resources!$C$183
Name add1_cell_sidetracking: '[4]1'!$C$41
Name add1_development_of_drilling_facilities: [4]Resources!$C$187
Name add1_drilling: [4]Resources!$C$185
Name add1_frac_costs: [4]Resources!$C$203
Name add1_inflow_stimulation: [4]Resources!$C$186
Name add1_investment_designation: [4]Resources!$C$169
Name add1_investments: [4]Resources!$C$182
Name add1_modernization: [4]Resources!$C$189
Name add1_motorways: [4]Resources!$C$193
Name add1_new_construction: [4]Resources!$C$198
Name add1_oil_production: [4]Resources!$C$176

Sheet Справочник подстановки
A1: Справочник выплывающих значений
A2: Тип скважины | C2: Кол-во колонн | D2: Наличие пилотного ствола (ликвидированного по геологич.причинам) | E2: Кол-во пил.стволов | F2: Многозабойность | G2: Кол-во продуктивных стволов | H2: Проведение ГРП | I2: количество стадий ГРП | J2: Назначение скважины | K2: Отход | L2: Примечание | M2: ед.изм | N2: да/нет
A3: ННС | B3: ЮРА | C3: 2к | D3: пилот | E3: 1 | F3: многозабойная | G3: 1 | H3: ГРП | I3: 1ст | J3: Добывающая | K3: <800 | L3: 2гор.уч. | M3: сут | N3: да
A4: ГС | B4: Палеозой | C4: 3к | D4: без пилота | E4: 2 | G4: 2 | H4: МГРП | I4: 2ст | J4: Нагнетательная | K4: 800-1300 | L4: 3гор.уч. | M4: операция | N4: нет
A5: ВЗ | B5: Бажен | C5: 4к | E5: 3 | G5: 3 | I5: 3ст | J5: Водозаборная | K5: 1300-1800 | L5: 2Пилота | M5: шт | N5: Частично на межсезонье
C6: 5к | E6: 4 | G6: 4 | I6: 4ст | J6: Газовая | K6: 1800-2200 | L6: 3Пилота | M6: пог.м.
C7: 6к | E7: 5 | G7: 5 | I7: 5ст | J7: Разведочная | K7: >2200 | L7: Газовая | M7: тн
C8: 7к | G8: 6 | I8: 6ст | J8: Пьезометрическая | L8: Пологая | M8: комплекс
I9: 7ст | L9: Разведочная | M9: бр.ч.
I10: 8ст | L10: Оценочная | M10: м3
I11: 9ст | M11: к-т
I12: 10ст | M12: м
I13: 11ст | M13: скв
I14: 12ст
I15: 13ст
I16: 14ст
I17: 15ст
I18: 16ст
I19: 17ст
I20: 18ст
I21: 19ст
I22: 20ст

Sheet Титул 
B1: Проект: | K1: Бурение
K2: Вид проекта
B4: Название проекта: | K4: Бурение скважин в 2014 - 2017 гг.
K5: 3 куст Новопортовского месторождения
B7: Наименование организации: | K7: ООО "Газпром нефть Новый Порт"
B9: Начало поведения (мес/год) | K9: 41792 | L9: (мес/год)
B10: Конец проведения работ (мес/год) | K10: 42775 | L10: (мес/год)
B11: Буровой подрядчик | K11: ООО "Буровая компания "Евразия" | N11: (наименование организации)
B12: Тип буровго станка | K12: ZJ-50 | N12: (наименование типа БУ)
B13: Наличие ВСП | L13: (Да/ Нет)
B14: Наличие АвИЭС | K14: да | L14: (Да/ Нет)
B15: Наличие автономности | K15: да | L15: (Да/ Нет/ Частично на межсезонье)
B17: ОТВЕТСТВЕННЫЕ СПЕЦИАЛИСТЫ ПО ПРОЕКТУ
B18: По технико-технологическим показателям | K18: Пильник Сергей Васильевич | Q18: Начальник отдела инжиниринга
K19: Ф.И.О. | P19: тел. | Q19: должность
B20: По экономическим показателям | K20: Полубояринова Эвелина Вячеславовна | Q20: Начальник отдела экономического анализа
K21: Ф.И.О. | P21: тел. | Q21: должность
B23: Тэхнико-экономические показатели строительства по проекту:
B25: Наименование показателя | K25: Ед. изм. | L25: Кол-во скважин, законченных бурением | N25: Кол-во скважин, законченных освоением | P25: Проходка по скважинам, м | R25: Время бурения, сут. | T25: Время осовения, сут.
L26: Текущий год | M26: Всего скв. | N26: Текущий год | O26: Всего скв. | P26: Всего | Q26: Ср. значение на 1 скв. | R26: Всего | S26: Ср. значение на 1 скв. | T26: Всего | U26: Ср. значение на 1 скв.
B27: № п/п | C27: Тип скважины | E27: Отход от вертикали | F27: Пилотный ствол | G27: (М)ГРП | H27: кол-во стадий ГРП | I27: Кол-во колонн | J27: Примечание | K27: скв. | L27: =SUM(L28:L44) -> 0 | M27: =SUM(M28:M44) -> 32 | N27: =SUM(N28:N44) -> 0 | O27: =SUM(O28:O44) -> 32 | P27: =SUM(P28:P44) -> 128505 | Q27: =SUM(Q28:Q44) -> 26218 | R27: =SUM(R28:R44) -> 1162 | S27: =SUM(S28:S44) -> 292 | ... U27: =SUM(U28:U44) -> 0
B28: 1 (Первая) | C28: ГС | D28: ЮРА | F28: без пилота | G28: МГРП | H28: 8ст | K28: скв. | M28: 2 | O28: =M28 -> 2 | P28: =$M28*Q28 -> 9456 | Q28: ='Перв. скв '!$D$8 -> 4728 | R28: =$M28*S28 -> 68 | S28: ='Перв. скв '!$O$6 -> 34 | T28: =$O28*U28 -> 0 | U28: ='Перв. скв '!$R$6 -> 0
B29: 2 | C29: ГС | K29: скв. | P29: =$M29*Q29 -> 0 | Q29: ='2'!$D$8 -> 0 | R29: =$M29*S29 -> 0 | S29: ='2'!$O$6 -> 0 | T29: =$O29*U29 -> 0 | U29: ='2'!$R$6 -> 0
B30: 3 | C30: ННС | K30: скв. | P30: =$M30*Q30 -> 0 | Q30: ='3'!$D$8 -> 0 | R30: =$M30*S30 -> 0 | S30: ='3'!$O$6 -> 0 | T30: =$O30*U30 -> 0 | U30: ='3'!$R$6 -> 0
B31: 4 | C31: ГС | K31: скв. | P31: =$M31*Q31 -> 0 | Q31: ='4'!$D$8 -> 0 | R31: =$M31*S31 -> 0 | S31: ='4'!$O$6 -> 0 | T31: =$O31*U31 -> 0 | U31: ='4'!$R$6 -> 0
B32: 5 | C32: ГС | K32: скв. | P32: =$M32*Q32 -> 0 | Q32: ='5'!$D$8 -> 0 | R32: =$M32*S32 -> 0 | S32: ='5'!$O$6 -> 0 | T32: =$O32*U32 -> 0 | U32: ='5'!$R$6 -> 0
B33: 6 | C33: ГС | K33: скв. | P33: =$M33*Q33 -> 0 | Q33: ='6'!$D$8 -> 0 | R33: =$M33*S33 -> 0 | S33: ='6'!$O$6 -> 0 | T33: =$O33*U33 -> 0 | U33: ='6'!$R$6 -> 0
B34: 7 | C34: ГС | K34: скв. | P34: =$M34*Q34 -> 0 | Q34: ='7'!$D$8 -> 0 | R34: =$M34*S34 -> 0 | S34: ='7'!$O$6 -> 0 | T34: =$O34*U34 -> 0 | U34: ='7'!$R$6 -> 0
B35: 8 | C35: ГС | K35: скв. | P35: =$M35*Q35 -> 0 | Q35: ='8'!$D$8 -> 0 | R35: =$M35*S35 -> 0 | S35: ='8'!$O$6 -> 0 | T35: =$O35*U35 -> 0 | U35: ='8'!$R$6 -> 0
B36: 9 | C36: ГС | K36: скв. | P36: =$M36*Q36 -> 0 | Q36: ='9'!$D$8 -> 0 | R36: =$M36*S36 -> 0 | S36: ='9'!$O$6 -> 0 | T36: =$O36*U36 -> 0 | U36: ='9'!$R$6 -> 0
B37: 10 | C37: ВЗ | F37: без пилота | K37: скв. | M37: =ВЗ!B12 -> 2 | O37: =M37 -> 2 | P37: =$M37*Q37 -> 2796 | Q37: =ВЗ!$D$8 -> 1398 | R37: =$M37*S37 -> 80 | S37: =ВЗ!$O$6 -> 40 | T37: =$O37*U37 -> 0 | U37: =ВЗ!$R$6 -> 0
B38: 11 | C38: ГС | F38: без пилота | K38: скв. | M38: ='ГС без пил 1000м гор'!B12 -> 8 | O38: =M38 -> 8 | P38: =$M38*Q38 -> 31432 | Q38: ='ГС без пил 1000м гор'!$D$8 -> 3929 | R38: =$M38*S38 -> 264 | S38: ='ГС без пил 1000м гор'!$O$6 -> 33 | T38: =$O38*U38 -> 0 | U38: ='ГС без пил 1000м гор'!$R$6 -> 0
B39: 12 | C39: ГС | F39: пилот | K39: скв. | M39: ='ГС пил 1500м гор'!B12 -> 0 | O39: =M39 -> 0 | P39: =$M39*Q39 -> 0 | Q39: ='ГС пил 1500м гор'!$D$8 -> 0 | R39: =$M39*S39 -> 0 | S39: ='ГС пил 1500м гор'!$O$6 -> 0 | T39: =$O39*U39 -> 0 | U39: ='ГС пил 1500м гор'!$R$6 -> 0
B40: 13 | C40: ГС | F40: без пилота | K40: скв. | M40: ='ГС без пилот 1500м гор'!B12 -> 6 | O40: =M40 -> 6 | P40: =$M40*Q40 -> 25938 | Q40: ='ГС без пилот 1500м гор'!$D$8 -> 4323 | R40: =$M40*S40 -> 204 | S40: ='ГС без пилот 1500м гор'!$O$6 -> 34 | T40: =$O40*U40 -> 0 | U40: ='ГС без пилот 1500м гор'!$R$6 -> 0
B41: 14 | C41: ГС | D41: ЮРА | F41: без пилота | G41: МГРП | H41: 8ст | K41: скв. | M41: ='ГСЮра без пил МГРП'!B12-2 -> 9 | O41: =M41 -> 9 | P41: =$M41*Q41 -> 36990 | Q41: ='ГСЮра без пил МГРП'!$D$8 -> 4110 | R41: =$M41*S41 -> 306 | S41: ='ГСЮра без пил МГРП'!$O$6 -> 34 | T41: =$O41*U41 -> 0 | U41: ='ГСЮра без пил МГРП'!$R$6 -> 0
B42: 15 | C42: ГС | D42: ЮРА | F42: пилот | G42: МГРП | H42: 8ст | K42: скв. | M42: ='ГСЮра пил МСГРП'!B12 -> 4 | O42: =M42 -> 4 | P42: =$M42*Q42 -> 18884 | Q42: ='ГСЮра пил МСГРП'!$D$8 -> 4721 | R42: =$M42*S42 -> 164 | S42: ='ГСЮра пил МСГРП'!$O$6 -> 41 | T42: =$O42*U42 -> 0 | U42: ='ГСЮра пил МСГРП'!$R$6 -> 0
B43: 16 | C43: ГС | D43: ЮРА | K43: скв. | M43: ='ГСЮра керн ГИС'!B12 -> 1 | O43: =M43 -> 1 | P43: =$M43*Q43 -> 3009 | Q43: ='ГСЮра керн ГИС'!$D$8 -> 3009 | R43: =$M43*S43 -> 76 | S43: ='ГСЮра керн ГИС'!$O$6 -> 76 | T43: =$O43*U43 -> 0 | U43: ='ГСЮра керн ГИС'!$R$6 -> 0
B44: 17 (Последняя) | C44: ГС | K44: скв. | P44: =$M44*Q44 -> 0 | Q44: =Посл.скв.!$D$8 -> 0 | R44: =$M44*S44 -> 0 | S44: =Посл.скв.!$O$6 -> 0 | T44: =$O44*U44 -> 0 | U44: =Посл.скв.!$R$6 -> 0
B46: Среднее по ННС | K46: скв. | L46: =SUMIF($C$28:$C$44,"ННС",L28:L44)+SUMIF($C$28:$C$44,"ВЗ",L28:L44) -> 0 | M46: =SUMIF($C$28:$C$44,"ННС",M28:M44)+SUMIF($C$28:$C$44,"ВЗ",M28:M44) -> 2 | N46: =SUMIF($C$28:$C$44,"ННС",N28:N44)+SUMIF($C$28:$C$44,"ВЗ",N28:N44) -> 0 | O46: =SUMIF($C$28:$C$44,"ННС",O28:O44)+SUMIF($C$28:$C$44,"ВЗ",O28:O44) -> 2 | P46: =SUMIF($C$28:$C$44,"ННС",P28:P44)+SUMIF($C$28:$C$44,"ВЗ",P28:P44) -> 2796 | Q46: =IF(M46=0,0,P46/$M$46) -> 1398 | R46: =SUMIF($C$28:$C$44,"ННС",R28:R44)+SUMIF($C$28:$C$44,"ВЗ",R28:R44) -> 80 | S46: =IF(M46=0,0,R46/$M$46) -> 40 | T46: =SUMIF($C$28:$C$44,"ННС",T28:T44)+SUMIF($C$28:$C$44,"ВЗ",T28:T44) -> 0 | U46: =IF(M46=0,0,T46/$M$46) -> 0
B47: Среднее по ГС | K47: скв. | L47: =SUMIF($C$28:$C$44,"ГС",L28:L44) -> 0 | M47: =SUMIF($C$28:$C$44,"ГС",M28:M44) -> 30 | N47: =SUMIF($C$28:$C$44,"ГС",N28:N44) -> 0 | O47: =SUMIF($C$28:$C$44,"ГС",O28:O44) -> 30 | P47: =SUMIF($C$28:$C$44,"ГС",P28:P44) -> 125709 | Q47: =IF(M47=0,0,P47/$M$46) -> 62854.5 | R47: =SUMIF($C$28:$C$44,"ГС",R28:R44) -> 1082 | S47: =IF(M47=0,0,R47/$M$47) -> 36.066667 | T47: =SUMIF($C$28:$C$44,"ГС",T28:T44) -> 0 | U47: =IF(M47=0,0,T47/$M$47) -> 0
B49: Экономические показатели строительства по проекту:
U50: (без НДС)
B51: Наименование показателя | K51: Ст-ть работ текущего года, тыс.руб. | N51: Всего ст-ть работ, тыс.руб. | P51: Ст-ть бурения, тыс.руб. | R51: Ст-ть освоения, тыс.руб. | T51: Ст-ть ВМР, тыс.руб. | U51: Ст-ть обор-ия, тыс.руб.
K52: Бурение (без ВМР) | L52: Освоение | M52: Всего с ВМР и обор. | N52: Итого | O52: Ср. значение на 1 скв. | P52: Всего | Q52: Ср. значение на 1 скв. | R52: Всего | S52: Ср. значение на 1 скв.
B53: № п/п | K53: =SUM(K54:K70) -> 0 | L53: =SUM(L54:L70) -> 0 | M53: =SUM(M54:M70) -> 0 | N53: =SUM(N54:N70) -> 6.3867824e+09 | O53: =IF(O27=0,0,N53/O27) -> 1.9958695e+08 | P53: =SUM(P54:P70) -> 4.4222181e+09 | Q53: =IF(M27=0,0,P53/M27) -> 1.3819431e+08 | R53: =SUM(R54:R70) -> 1.6570569e+09 | S53: =IF(O27=0,0,R53/O27) -> 51783029 | T53: =SUM(T54:T70) -> 3.0750741e+08 | U53: =SUM(U54:U70) -> 0
B54: 1 (Первая) | C54: =C28 -> ГС | D54: =D28 -> ЮРА | E54: =E28 -> 0 | F54: =F28 -> без пилота | G54: =G28 -> МГРП | H54: =H28 -> 8ст | I54: =I28 -> 0 | J54: =J28 -> 0 | K54: =Q54*L28 -> 0 | L54: =S54*N28 -> 0 | M54: =K54+L54+IF(M28=0,0,T54/M28)*L28+IF(O28=0,0,U54/O28)*N28 -> 0 | N54: =P54+R54+T54+U54 -> 7.2437548e+08 | O54: =IF(O28=0,0,N54/O28) -> 3.6218774e+08 | P54: =M28*Q54 -> 2.7288115e+08 | Q54: ='Перв. скв '!$E$9 -> 1.3644058e+08 | R54: =O28*S54 -> 1.9362885e+08 | S54: ='Перв. скв '!$E$11 -> 96814424 | T54: ='Перв. скв '!$E$7*M28 -> 2.5786548e+08 | U54: ='Перв. скв '!$E$13*N28 -> 0
B55: 2 | C55: =C29 -> ГС | D55: =D29 -> 0 | E55: =E29 -> 0 | F55: =F29 -> 0 | G55: =G29 -> 0 | H55: =H29 -> 0 | I55: =I29 -> 0 | J55: =J29 -> 0 | K55: =Q55*L29 -> 0 | L55: =S55*N29 -> 0 | M55: =K55+L55+IF(M29=0,0,T55/M29)*L29+IF(O29=0,0,U55/O29)*N29 -> 0 | N55: =P55+R55+T55+U55 -> 0 | O55: =IF(O29=0,0,N55/O29) -> 0 | P55: =M29*Q55 -> 0 | Q55: ='2'!$E$9 -> 0 | R55: =O29*S55 -> 0 | S55: ='2'!$E$11 -> 0 | T55: ='2'!$E$7*M29 -> 0 | U55: ='2'!$E$13*N29 -> 0
B56: 3 | C56: =C30 -> ННС | D56: =D30 -> 0 | E56: =E30 -> 0 | F56: =F30 -> 0 | G56: =G30 -> 0 | H56: =H30 -> 0 | I56: =I30 -> 0 | J56: =J30 -> 0 | K56: =Q56*L30 -> 0 | L56: =S56*N30 -> 0 | M56: =K56+L56+IF(M30=0,0,T56/M30)*L30+IF(O30=0,0,U56/O30)*N30 -> 0 | N56: =P56+R56+T56+U56 -> 0 | O56: =IF(O30=0,0,N56/O30) -> 0 | P56: =M30*Q56 -> 0 | Q56: ='3'!$E$9 -> 0 | R56: =O30*S56 -> 0 | S56: ='3'!$E$11 -> 0 | T56: ='3'!$E$7*M30 -> 0 | U56: ='3'!$E$13*N30 -> 0
B57: 4 | C57: =C31 -> ГС | D57: =D31 -> 0 | E57: =E31 -> 0 | F57: =F31 -> 0 | G57: =G31 -> 0 | H57: =H31 -> 0 | I57: =I31 -> 0 | J57: =J31 -> 0 | K57: =Q57*L31 -> 0 | L57: =S57*N31 -> 0 | M57: =K57+L57+IF(M31=0,0,T57/M31)*L31+IF(O31=0,0,U57/O31)*N31 -> 0 | N57: =P57+R57+T57+U57 -> 0 | O57: =IF(O31=0,0,N57/O31) -> 0 | P57: =M31*Q57 -> 0 | Q57: ='4'!$E$9 -> 0 | R57: =O31*S57 -> 0 | S57: ='4'!$E$11 -> 0 | T57: ='4'!$E$7*M31 -> 0 | U57: ='4'!$E$13*N31 -> 0
B58: 5 | C58: =C32 -> ГС | D58: =D32 -> 0 | E58: =E32 -> 0 | F58: =F32 -> 0 | G58: =G32 -> 0 | H58: =H32 -> 0 | I58: =I32 -> 0 | J58: =J32 -> 0 | K58: =Q58*L32 -> 0 | L58: =S58*N32 -> 0 | M58: =K58+L58+IF(M32=0,0,T58/M32)*L32+IF(O32=0,0,U58/O32)*N32 -> 0 | N58: =P58+R58+T58+U58 -> 0 | O58: =IF(O32=0,0,N58/O32) -> 0 | P58: =M32*Q58 -> 0 | Q58: ='5'!$E$9 -> 0 | R58: =O32*S58 -> 0 | S58: ='5'!$E$11 -> 0 | T58: ='5'!$E$7*M32 -> 0 | U58: ='5'!$E$13*N32 -> 0
B59: 6 | C59: =C33 -> ГС | D59: =D33 -> 0 | E59: =E33 -> 0 | F59: =F33 -> 0 | G59: =G33 -> 0 | H59: =H33 -> 0 | I59: =I33 -> 0 | J59: =J33 -> 0 | K59: =Q59*L33 -> 0 | L59: =S59*N33 -> 0 | M59: =K59+L59+IF(M33=0,0,T59/M33)*L33+IF(O33=0,0,U59/O33)*N33 -> 0 | N59: =P59+R59+T59+U59 -> 0 | O59: =IF(O33=0,0,N59/O33) -> 0 | P59: =M33*Q59 -> 0 | Q59: ='6'!$E$9 -> 0 | R59: =O33*S59 -> 0 | S59: ='6'!$E$11 -> 0 | T59: ='6'!$E$7*M33 -> 0 | U59: ='6'!$E$13*N33 -> 0
B60: 7 | C60: =C34 -> ГС | D60: =D34 -> 0 | E60: =E34 -> 0 | F60: =F34 -> 0 | G60: =G34 -> 0 | H60: =H34 -> 0 | I60: =I34 -> 0 | J60: =J34 -> 0 | K60: =Q60*L34 -> 0 | L60: =S60*N34 -> 0 | M60: =K60+L60+IF(M34=0,0,T60/M34)*L34+IF(O34=0,0,U60/O34)*N34 -> 0 | N60: =P60+R60+T60+U60 -> 0 | O60: =IF(O34=0,0,N60/O34) -> 0 | P60: =M34*Q60 -> 0 | Q60: ='7'!$E$9 -> 0 | R60: =O34*S60 -> 0 | S60: ='7'!$E$11 -> 0 | T60: ='7'!$E$7*M34 -> 0 | U60: ='7'!$E$13*N34 -> 0
B61: 8 | C61: =C35 -> ГС | D61: =D35 -> 0 | E61: =E35 -> 0 | F61: =F35 -> 0 | G61: =G35 -> 0 | H61: =H35 -> 0 | I61: =I35 -> 0 | J61: =J35 -> 0 | K61: =Q61*L35 -> 0 | L61: =S61*N35 -> 0 | M61: =K61+L61+IF(M35=0,0,T61/M35)*L35+IF(O35=0,0,U61/O35)*N35 -> 0 | N61: =P61+R61+T61+U61 -> 0 | O61: =IF(O35=0,0,N61/O35) -> 0 | P61: =M35*Q61 -> 0 | Q61: ='8'!$E$9 -> 0 | R61: =O35*S61 -> 0 | S61: ='8'!$E$11 -> 0 | T61: ='8'!$E$7*M35 -> 0 | U61: ='8'!$E$13*N35 -> 0
B62: 9 | C62: =C36 -> ГС | D62: =D36 -> 0 | E62: =E36 -> 0 | F62: =F36 -> 0 | G62: =G36 -> 0 | H62: =H36 -> 0 | I62: =I36 -> 0 | J62: =J36 -> 0 | K62: =Q62*L36 -> 0 | L62: =S62*N36 -> 0 | M62: =K62+L62+IF(M36=0,0,T62/M36)*L36+IF(O36=0,0,U62/O36)*N36 -> 0 | N62: =P62+R62+T62+U62 -> 0 | O62: =IF(O36=0,0,N62/O36) -> 0 | P62: =M36*Q62 -> 0 | Q62: ='9'!$E$9 -> 0 | R62: =O36*S62 -> 0 | S62: ='9'!$E$11 -> 0 | T62: ='9'!$E$7*M36 -> 0 | U62: ='9'!$E$13*N36 -> 0
B63: 10 | C63: =C37 -> ВЗ | D63: =D37 -> 0 | E63: =E37 -> 0 | F63: =F37 -> без пилота | G63: =G37 -> 0 | H63: =H37 -> 0 | I63: =I37 -> 0 | J63: =J37 -> 0 | K63: =Q63*L37 -> 0 | L63: =S63*N37 -> 0 | M63: =K63+L63+IF(M37=0,0,T63/M37)*L37+IF(O37=0,0,U63/O37)*N37 -> 0 | N63: =P63+R63+T63+U63 -> 1.1198164e+08 | O63: =IF(O37=0,0,N63/O37) -> 55990820 | P63: =M37*Q63 -> 88719303 | Q63: =ВЗ!$E$9 -> 44359651 | R63: =O37*S63 -> 20292103 | S63: =ВЗ!$E$11 -> 10146052 | T63: =ВЗ!$E$7*M37 -> 2970233.4 | U63: =ВЗ!$E$13*N37 -> 0
B64: 11 | C64: =C38 -> ГС | D64: =D38 -> 0 | E64: =E38 -> 0 | F64: =F38 -> без пилота | G64: =G38 -> 0 | H64: =H38 -> 0 | I64: =I38 -> 0 | J64: =J38 -> 0 | K64: =Q64*L38 -> 0 | L64: =S64*N38 -> 0 | M64: =K64+L64+IF(M38=0,0,T64/M38)*L38+IF(O38=0,0,U64/O38)*N38 -> 0 | N64: =P64+R64+T64+U64 -> 1.2835767e+09 | O64: =IF(O38=0,0,N64/O38) -> 1.6044709e+08 | P64: =M38*Q64 -> 1.2115047e+09 | Q64: ='ГС без пил 1000м гор'!$E$9 -> 1.5143809e+08 | R64: =O38*S64 -> 56930472 | S64: ='ГС без пил 1000м гор'!$E$11 -> 7116309 | T64: ='ГС без пил 1000м гор'!$E$7*M38 -> 15141530 | U64: ='ГС без пил 1000м гор'!$E$13*N38 -> 0
B65: 12 | C65: =C39 -> ГС | D65: =D39 -> 0 | E65: =E39 -> 0 | F65: =F39 -> пилот | G65: =G39 -> 0 | H65: =H39 -> 0 | I65: =I39 -> 0 | J65: =J39 -> 0 | K65: =Q65*L39 -> 0 | L65: =S65*N39 -> 0 | M65: =K65+L65+IF(M39=0,0,T65/M39)*L39+IF(O39=0,0,U65/O39)*N39 -> 0 | N65: =P65+R65+T65+U65 -> 0 | O65: =IF(O39=0,0,N65/O39) -> 0 | P65: =M39*Q65 -> 0 | Q65: ='ГС пил 1500м гор'!$E$9 -> 0 | R65: =O39*S65 -> 0 | S65: ='ГС пил 1500м гор'!$E$11 -> 0 | T65: ='ГС пил 1500м гор'!$E$7*M39 -> 0 | U65: ='ГС пил 1500м гор'!$E$13*N39 -> 0
B66: 13 | C66: =C40 -> ГС | D66: =D40 -> 0 | E66: =E40 -> 0 | F66: =F40 -> без пилота | G66: =G40 -> 0 | H66: =H40 -> 0 | I66: =I40 -> 0 | J66: =J40 -> 0 | K66: =Q66*L40 -> 0 | L66: =S66*N40 -> 0 | M66: =K66+L66+IF(M40=0,0,T66/M40)*L40+IF(O40=0,0,U66/O40)*N40 -> 0 | N66: =P66+R66+T66+U66 -> 8.7549026e+08 | O66: =IF(O40=0,0,N66/O40) -> 1.4591504e+08 | P66: =M40*Q66 -> 8.3192039e+08 | Q66: ='ГС без пилот 1500м гор'!$E$9 -> 1.386534e+08 | R66: =O40*S66 -> 33932002 | S66: ='ГС без пилот 1500м гор'!$E$11 -> 5655333.6 | T66: ='ГС без пилот 1500м гор'!$E$7*M40 -> 9637869.5 | U66: ='ГС без пилот 1500м гор'!$E$13*N40 -> 0
B67: 14 | C67: =C41 -> ГС | D67: =D41 -> ЮРА | E67: =E41 -> 0 | F67: =F41 -> без пилота | G67: =G41 -> МГРП | H67: =H41 -> 8ст | I67: =I41 -> 0 | J67: =J41 -> 0 | K67: =Q67*L41 -> 0 | L67: =S67*N41 -> 0 | M67: =K67+L67+IF(M41=0,0,T67/M41)*L41+IF(O41=0,0,U67/O41)*N41 -> 0 | N67: =P67+R67+T67+U67 -> 2.1134209e+09 | O67: =IF(O41=0,0,N67/O41) -> 2.3482454e+08 | P67: =M41*Q67 -> 1.227982e+09 | Q67: ='ГСЮра без пил МГРП'!$E$9 -> 1.3644244e+08 | R67: =O41*S67 -> 8.7132981e+08 | S67: ='ГСЮра без пил МГРП'!$E$11 -> 96814424 | T67: ='ГСЮра без пил МГРП'!$E$7*M41 -> 14109099 | U67: ='ГСЮра без пил МГРП'!$E$13*N41 -> 0
B68: 15 | C68: =C42 -> ГС | D68: =D42 -> ЮРА | E68: =E42 -> 0 | F68: =F42 -> пилот | G68: =G42 -> МГРП | H68: =H42 -> 8ст | I68: =I42 -> 0 | J68: =J42 -> 0 | K68: =Q68*L42 -> 0 | L68: =S68*N42 -> 0 | M68: =K68+L68+IF(M42=0,0,T68/M42)*L42+IF(O42=0,0,U68/O42)*N42 -> 0 | N68: =P68+R68+T68+U68 -> 9.1260354e+08 | O68: =IF(O42=0,0,N68/O42) -> 2.2815088e+08 | P68: =M42*Q68 -> 5.8799265e+08 | Q68: ='ГСЮра пил МСГРП'!$E$9 -> 1.4699816e+08 | R68: =O42*S68 -> 3.1836778e+08 | S68: ='ГСЮра пил МСГРП'!$E$11 -> 79591944 | T68: ='ГСЮра пил МСГРП'!$E$7*M42 -> 6243114.8 | U68: ='ГСЮра пил МСГРП'!$E$13*N42 -> 0
B69: 16 | C69: =C43 -> ГС | D69: =D43 -> ЮРА | E69: =E43 -> 0 | F69: =F43 -> 0 | G69: =G43 -> 0 | H69: =H43 -> 0 | I69: =I43 -> 0 | J69: =J43 -> 0 | K69: =Q69*L43 -> 0 | L69: =S69*N43 -> 0 | M69: =K69+L69+IF(M43=0,0,T69/M43)*L43+IF(O43=0,0,U69/O43)*N43 -> 0 | N69: =P69+R69+T69+U69 -> 3.6533392e+08 | O69: =IF(O43=0,0,N69/O43) -> 3.6533392e+08 | P69: =M43*Q69 -> 2.0121793e+08 | Q69: ='ГСЮра керн ГИС'!$E$9 -> 2.0121793e+08 | R69: =O43*S69 -> 1.6257591e+08 | S69: ='ГСЮра керн ГИС'!$E$11 -> 1.6257591e+08 | T69: ='ГСЮра керн ГИС'!$E$7*M43 -> 1540081.9 | U69: ='ГСЮра керн ГИС'!$E$13*N43 -> 0
B70: 17 (Последняя) | C70: =C44 -> ГС | D70: =D44 -> 0 | E70: =E44 -> 0 | F70: =F44 -> 0 | G70: =G44 -> 0 | H70: =H44 -> 0 | I70: =I44 -> 0 | J70: =J44 -> 0 | K70: =Q70*L44 -> 0 | L70: =S70*N44 -> 0 | M70: =K70+L70+IF(M44=0,0,T70/M44)*L44+IF(O44=0,0,U70/O44)*N44 -> 0 | N70: =P70+R70+T70+U70 -> 0 | O70: =IF(O44=0,0,N70/O44) -> 0 | P70: =M44*Q70 -> 0 | Q70: =Посл.скв.!$E$9 -> 0 | R70: =O44*S70 -> 0 | S70: =Посл.скв.!$E$11 -> 0 | T70: =Посл.скв.!$E$7*M44 -> 0 | U70: =Посл.скв.!$E$13*N44 -> 0
B72: Среднее по ННС на 1 скв. | K72: =SUMIF($C$54:$C$70,"ННС",K54:K70)+SUMIF($C$54:$C$70,"ВЗ",K54:K70) -> 0 | L72: =SUMIF($C$54:$C$70,"ННС",L54:L70)+SUMIF($C$54:$C$70,"ВЗ",L54:L70) -> 0 | M72: =SUMIF($C$54:$C$70,"ННС",M54:M70)+SUMIF($C$54:$C$70,"ВЗ",M54:M70) -> 0 | N72: =SUMIF($C$54:$C$70,"ННС",N54:N70)+SUMIF($C$54:$C$70,"ВЗ",N54:N70) -> 1.1198164e+08 | O72: =IF(O46=0,0,N72/O46) -> 55990820 | P72: =SUMIF($C$54:$C$70,"ННС",P54:P70)+SUMIF($C$54:$C$70,"ВЗ",P54:P70) -> 88719303 | Q72: =IF(M46=0,0,P72/M46) -> 44359651 | R72: =SUMIF($C$54:$C$70,"ННС",R54:R70)+SUMIF($C$54:$C$70,"ВЗ",R54:R70) -> 20292103 | S72: =IF(O46=0,0,R72/O46) -> 10146052 | T72: =SUMIF($C$54:$C$70,"ННС",T54:T70)+SUMIF($C$54:$C$70,"ВЗ",T54:T70) -> 2970233.4 | U72: =SUMIF($C$54:$C$70,"ННС",U54:U70)+SUMIF($C$54:$C$70,"ВЗ",U54:U70) -> 0
B73: Среднее по ГС на 1 скв. | K73: =SUMIF($C$54:$C$70,"ГС",K54:K70) -> 0 | L73: =SUMIF($C$54:$C$70,"ГС",L54:L70) -> 0 | M73: =SUMIF($C$54:$C$70,"ГС",M54:M70) -> 0 | N73: =SUMIF($C$54:$C$70,"ГС",N54:N70) -> 6.2748008e+09 | O73: =IF(O47=0,0,N73/O47) -> 2.0916003e+08 | P73: =SUMIF($C$54:$C$70,"ГС",P54:P70) -> 4.3334988e+09 | Q73: =IF(M47=0,0,P73/M47) -> 1.4444996e+08 | R73: =SUMIF($C$54:$C$70,"ГС",R54:R70) -> 1.6367648e+09 | S73: =IF(O47=0,0,R73/O47) -> 54558827 | T73: =SUMIF($C$54:$C$70,"ГС",T54:T70) -> 3.0453718e+08 | U73: =SUMIF($C$54:$C$70,"ГС",U54:U70) -> 0
B75: ОПИСАНИЕ И ОСОБЕННОСТИ ПРОЕКТА
B87: Примечания по заполнению:
B88: Создана библиотека видов работ, ед. измерения и стоимости за ед. изм. | N88: в листе "первая скважина", данные из которого тиражируются во все остальные листы с типами скважин.
B89: При заполнени стоимости в поле "статья затрат" нужно указывать по аналогичной ст-ти какого из подрядчиков взята цена для расчета.
B90: Основные места для заполнения выделены желтым или белым цветом
B91: Автоматические расчеты и места заполняемые из других, первоначальных источников выделены серым цветом | Q91: или зеленым | S91: или
B92: В случае изменения кол-ва строк, необходимо производить замену во всех листах типовых форм скважин и в листе "ТЭП".

Sheet ТЭП
A2: ПОДРОБНАЯ СМЕТНАЯ СТОИМОСТЬ СКВАЖИНЫ
C4: Месторождение/ куст: | D4: ='Титул '!$K$5 -> 3 куст Новопортовского месторождения | E4: ВСЕГО СТ-ТЬ
C5: Подрядчик по бурению: | D5: ='Титул '!K11 -> ООО "Буровая компания "Евразия" | E5: =E7+E9+E11+E13 -> 6.3867824e+09
C6: Тип буровой установки: | D6: ='Титул '!K12 -> ZJ-50 | E6: Всего ВМР
C7: Тип скважины: | E7: =AP69 -> 3.0750741e+08
C8: Проходка всего (м): | E8: Всего Бурение
C9: Наличие СВП: | D9: ='Титул '!K13 -> 0 | E9: =AP341 -> 4.4222181e+09
C10: Наличие АИЭС: | D10: ='Титул '!K14 -> да | E10: Всего Освоение
C11: Наличие автономности: | D11: ='Титул '!K15 -> да | E11: =AP361 -> 1.6570569e+09 | AP11: (руб. без НДС)
C12: Кол-во обсадных колонн (включая направл.): | E12: Обор-ие устья | F12: Вид скв. | G12: =CONCATENATE('Титул '!$C$28," ",'Титул '!$D$28," ",'Титул '!$E$28," ",'Титул '!$F$28," ",'Титул '!$G$28," ",'Титул '!$H$28," ",'Титул '!$J$28," ",'Титул '!$I$28) -> ГС ЮРА без пилота МГРП 8ст | I12: =CONCATENATE('Титул '!$C$29," ",'Титул '!$D$29," ",'Титул '!$E$29," ",'Титул '!$F$29," ",'Титул '!$G$29," ",'Титул '!$H$29," ",'Титул '!$J$29," ",'Титул '!$I$29) -> ГС | K12: =CONCATENATE('Титул '!$C$30," ",'Титул '!$D$30," ",'Титул '!$E$30," ",'Титул '!$F$30," ",'Титул '!$G$30," ",'Титул '!$H$30," ",'Титул '!$J$30," ",'Титул '!$I$30) -> ННС | M12: =CONCATENATE('Титул '!$C$31," ",'Титул '!$D$31," ",'Титул '!$E$31," ",'Титул '!$F$31," ",'Титул '!$G$31," ",'Титул '!$H$31," ",'Титул '!$J$31," ",'Титул '!$I$31) -> ГС | O12: =CONCATENATE('Титул '!$C$32," ",'Титул '!$D$32," ",'Титул '!$E$32," ",'Титул '!$F$32," ",'Титул '!$G$32," ",'Титул '!$H$32," ",'Титул '!$J$32," ",'Титул '!$I$32) -> ГС | Q12: =CONCATENATE('Титул '!$C$33," ",'Титул '!$D$33," ",'Титул '!$E$33," ",'Титул '!$F$33," ",'Титул '!$G$33," ",'Титул '!$H$33," ",'Титул '!$J$33," ",'Титул '!$I$33) -> ГС | S12: =CONCATENATE('Титул '!$C$34," ",'Титул '!$D$34," ",'Титул '!$E$34," ",'Титул '!$F$34," ",'Титул '!$G$34," ",'Титул '!$H$34," ",'Титул '!$J$34," ",'Титул '!$I$34) -> ГС | U12: =CONCATENATE('Титул '!$C$35," ",'Титул '!$D$35," ",'Титул '!$E$35," ",'Титул '!$F$35," ",'Титул '!$G$35," ",'Титул '!$H$35," ",'Титул '!$J$35," ",'Титул '!$I$35) -> ГС | W12: =CONCATENATE('Титул '!$C$36," ",'Титул '!$D$36," ",'Титул '!$E$36," ",'Титул '!$F$36," ",'Титул '!$G$36," ",'Титул '!$H$36," ",'Титул '!$J$36," ",'Титул '!$I$36) -> ГС | Y12: =CONCATENATE('Титул '!$C$37," ",'Титул '!$D$37," ",'Титул '!$E$37," ",'Титул '!$F$37," ",'Титул '!$G$37," ",'Титул '!$H$37," ",'Титул '!$J$37," ",'Титул '!$I$37) -> ВЗ без пилота | AA12: =CONCATENATE('Титул '!$C$38," ",'Титул '!$D$38," ",'Титул '!$E$38," ",'Титул '!$F$38," ",'Титул '!$G$38," ",'Титул '!$H$38," ",'Титул '!$J$38," ",'Титул '!$I$38) -> ГС без пилота | AC12: =CONCATENATE('Титул '!$C$39," ",'Титул '!$D$39," ",'Титул '!$E$39," ",'Титул '!$F$39," ",'Титул '!$G$39," ",'Титул '!$H$39," ",'Титул '!$J$39," ",'Титул '!$I$39) -> ГС пилот | AE12: =CONCATENATE('Титул '!$C$40," ",'Титул '!$D$40," ",'Титул '!$E$40," ",'Титул '!$F$40," ",'Титул '!$G$40," ",'Титул '!$H$40," ",'Титул '!$J$40," ",'Титул '!$I$40) -> ГС без пилота | AG12: =CONCATENATE('Титул '!$C$41," ",'Титул '!$D$41," ",'Титул '!$E$41," ",'Титул '!$F$41," ",'Титул '!$G$41," ",'Титул '!$H$41," ",'Титул '!$J$41," ",'Титул '!$I$41) -> ГС ЮРА без пилота МГРП 8ст | AI12: =CONCATENATE('Титул '!$C$42," ",'Титул '!$D$42," ",'Титул '!$E$42," ",'Титул '!$F$42," ",'Титул '!$G$42," ",'Титул '!$H$42," ",'Титул '!$J$42," ",'Титул '!$I$42) -> ГС ЮРА пилот МГРП 8ст | AK12: =CONCATENATE('Титул '!$C$43," ",'Титул '!$D$43," ",'Титул '!$E$43," ",'Титул '!$F$43," ",'Титул '!$G$43," ",'Титул '!$H$43," ",'Титул '!$J$43," ",'Титул '!$I$43) -> ГС ЮРА | AM12: =CONCATENATE('Титул '!$C$44," ",'Титул '!$D$44," ",'Титул '!$E$44," ",'Титул '!$F$44," ",'Титул '!$G$44," ",'Титул '!$H$44," ",'Титул '!$J$44," ",'Титул '!$I$44) -> ГС | AO12: ИТОГО
C13: Прочие существенные условия: | E13: =AP367 -> 0 | F13: Кол-во скв. | G13: ='Титул '!$M$28 -> 2 | I13: ='Титул '!$M$29 -> 0 | K13: ='Титул '!$M$30 -> 0 | M13: ='Титул '!$M$31 -> 0 | O13: ='Титул '!$M$32 -> 0 | Q13: ='Титул '!$M$33 -> 0 | S13: ='Титул '!$M$34 -> 0 | U13: ='Титул '!$M$35 -> 0 | W13: ='Титул '!$M$36 -> 0 | Y13: ='Титул '!$M$37 -> 2 | AA13: ='Титул '!$M$38 -> 8 | AC13: ='Титул '!$M$39 -> 0 | AE13: ='Титул '!$M$40 -> 6 | AG13: ='Титул '!$M$41 -> 9 | AI13: ='Титул '!$M$42 -> 4 | AK13: ='Титул '!$M$43 -> 1 | AM13: ='Титул '!$M$44 -> 0 | AO13: =SUM(G13:AN13) -> 32
A15: ОПИСАНИЕ РАБОТ И УСЛУГ
A16: КОД | B16: добавочный код | C16: СТАТЬЯ ЗАТРАТ | D16: ОПИСАНИЕ | E16: Подрядчик | F16: Единица измерения | G16: Кол-во | H16: Ст-ть работ | I16: Кол-во | J16: Ст-ть работ | K16: Кол-во | L16: Ст-ть работ | M16: Кол-во | N16: Ст-ть работ | O16: Кол-во | P16: Ст-ть работ | Q16: Кол-во | R16: Ст-ть работ | S16: Кол-во | T16: Ст-ть работ | U16: Кол-во | V16: Ст-ть работ | W16: Кол-во | X16: Ст-ть работ | Y16: Кол-во | Z16: Ст-ть работ | AA16: Кол-во | AB16: Ст-ть работ | AC16: Кол-во | AD16: Ст-ть работ | AE16: Кол-во | AF16: Ст-ть работ | AG16: Кол-во | AH16: Ст-ть работ | AI16: Кол-во | AJ16: Ст-ть работ | AK16: Кол-во | AL16: Ст-ть работ | AM16: Кол-во | AN16: Ст-ть работ | AO16: Кол-во | AP16: Ст-ть работ
C18: 1. ЭТАП ВМР
C19: ='Перв. скв '!C19 -> ООО "Буровая компания "Евразия" | D19: Описание работ/услуг
C20: ='Перв. скв '!C20 -> Работы, связанные с мобилизацией БУ (переездом), а так же прочего бурового оборудования и бригадного хозяйства, автономного источника энергоснабжения, материалов подрядчика и прочее. | D20: ='Перв. скв '!D20 -> Мобилизация БУ (переезд) | E20: ='Перв. скв '!E20 -> ООО "Буровая компания "Евразия" | F20: ='Перв. скв '!F20 -> операция | G20: ='Перв. скв '!$V20*G$13 -> 2 | H20: ='Перв. скв '!$W20*G$13 -> 2.5786548e+08 | I20: ='2'!$V20*I$13 -> 0 | J20: ='2'!$W20*I$13 -> 0 | K20: ='3'!$V20*K$13 -> 0 | L20: ='3'!$W20*K$13 -> 0 | M20: ='4'!$V20*M$13 -> 0 | N20: ='4'!$W20*M$13 -> 0 | O20: ='5'!$V20*O$13 -> 0 | P20: ='5'!$W20*O$13 -> 0 | Q20: ='6'!$V20*Q$13 -> 0 | R20: ='6'!$W20*Q$13 -> 0 | S20: ='7'!$V20*S$13 -> 0 | T20: ='7'!$W20*S$13 -> 0 | U20: ='8'!$V20*U$13 -> 0 | V20: ='8'!$W20*U$13 -> 0 | W20: ='9'!$V20*W$13 -> 0 | X20: ='9'!$W20*W$13 -> 0 | Y20: =ВЗ!$V20*Y$13 -> 0 | Z20: =ВЗ!$W20*Y$13 -> 0 | AA20: ='ГС без пил 1000м гор'!$V20*AA$13 -> 0 | AB20: ='ГС без пил 1000м гор'!$W20*AA$13 -> 0 | AC20: ='ГС пил 1500м гор'!$V20*AC$13 -> 0 | AD20: ='ГС пил 1500м гор'!$W20*AC$13 -> 0 | AE20: ='ГС без пилот 1500м гор'!$V20*AE$13 -> 0 | AF20: ='ГС без пилот 1500м гор'!$W20*AE$13 -> 0 | AG20: ='ГСЮра без пил МГРП'!$V20*AG$13 -> 0 | AH20: ='ГСЮра без пил МГРП'!$W20*AG$13 -> 0 | AI20: ='ГСЮра пил МСГРП'!$V20*AI$13 -> 0 | AJ20: ='ГСЮра пил МСГРП'!$W20*AI$13 -> 0 | AK20: ='ГСЮра керн ГИС'!$V20*AK$13 -> 0 | AL20: ='ГСЮра керн ГИС'!$W20*AK$13 -> 0 | AM20: =Посл.скв.!$V20*AM$13 -> 0 | AN20: =Посл.скв.!$W20*AM$13 -> 0 | AO20: =AM20+AK20+AI20+AG20+AE20+AC20+AA20+Y20++W20+U20+S20+Q20+M20+O20+K20+I20+G20 -> 2 | AP20: =AN20+AL20+AJ20+AH20+AF20+AD20+AB20+Z20++X20+V20+T20+R20+N20+P20+L20+J20+H20 -> 2.5786548e+08
C21: ='Перв. скв '!C21 -> 0 | D21: ='Перв. скв '!D21 -> - мобилизация БУ (переезд) | E21: ='Перв. скв '!E21 -> ООО "Буровая компания "Евразия" | F21: ='Перв. скв '!F21 -> операция | G21: ='Перв. скв '!$V21*G$13 -> 0 | H21: ='Перв. скв '!$W21*G$13 -> 0 | I21: ='2'!$V21*I$13 -> 0 | J21: ='2'!$W21*I$13 -> 0 | K21: ='3'!$V21*K$13 -> 0 | L21: ='3'!$W21*K$13 -> 0 | M21: ='4'!$V21*M$13 -> 0 | N21: ='4'!$W21*M$13 -> 0 | O21: ='5'!$V21*O$13 -> 0 | P21: ='5'!$W21*O$13 -> 0 | Q21: ='6'!$V21*Q$13 -> 0 | R21: ='6'!$W21*Q$13 -> 0 | S21: ='7'!$V21*S$13 -> 0 | T21: ='7'!$W21*S$13 -> 0 | U21: ='8'!$V21*U$13 -> 0 | V21: ='8'!$W21*U$13 -> 0 | W21: ='9'!$V21*W$13 -> 0 | X21: ='9'!$W21*W$13 -> 0 | Y21: =ВЗ!$V21*Y$13 -> 0 | Z21: =ВЗ!$W21*Y$13 -> 0 | AA21: ='ГС без пил 1000м гор'!$V21*AA$13 -> 0 | AB21: ='ГС без пил 1000м гор'!$W21*AA$13 -> 0 | AC21: ='ГС пил 1500м гор'!$V21*AC$13 -> 0 | AD21: ='ГС пил 1500м гор'!$W21*AC$13 -> 0 | AE21: ='ГС без пилот 1500м гор'!$V21*AE$13 -> 0 | AF21: ='ГС без пилот 1500м гор'!$W21*AE$13 -> 0 | AG21: ='ГСЮра без пил МГРП'!$V21*AG$13 -> 0 | AH21: ='ГСЮра без пил МГРП'!$W21*AG$13 -> 0 | AI21: ='ГСЮра пил МСГРП'!$V21*AI$13 -> 0 | AJ21: ='ГСЮра пил МСГРП'!$W21*AI$13 -> 0 | AK21: ='ГСЮра керн ГИС'!$V21*AK$13 -> 0 | AL21: ='ГСЮра керн ГИС'!$W21*AK$13 -> 0 | AM21: =Посл.скв.!$V21*AM$13 -> 0 | AN21: =Посл.скв.!$W21*AM$13 -> 0 | AO21: =AM21+AK21+AI21+AG21+AE21+AC21+AA21+Y21++W21+U21+S21+Q21+M21+O21+K21+I21+G21 -> 0 | AP21: =AN21+AL21+AJ21+AH21+AF21+AD21+AB21+Z21++X21+V21+T21+R21+N21+P21+L21+J21+H21 -> 0
C22: ='Перв. скв '!C22 -> 0 | D22: ='Перв. скв '!D22 -> - мобилизация БХ и БИ (перевозка) | E22: ='Перв. скв '!E22 -> ООО "Буровая компания "Евразия" | F22: ='Перв. скв '!F22 -> операция | G22: ='Перв. скв '!$V22*G$13 -> 0 | H22: ='Перв. скв '!$W22*G$13 -> 0 | I22: ='2'!$V22*I$13 -> 0 | J22: ='2'!$W22*I$13 -> 0 | K22: ='3'!$V22*K$13 -> 0 | L22: ='3'!$W22*K$13 -> 0 | M22: ='4'!$V22*M$13 -> 0 | N22: ='4'!$W22*M$13 -> 0 | O22: ='5'!$V22*O$13 -> 0 | P22: ='5'!$W22*O$13 -> 0 | Q22: ='6'!$V22*Q$13 -> 0 | R22: ='6'!$W22*Q$13 -> 0 | S22: ='7'!$V22*S$13 -> 0 | T22: ='7'!$W22*S$13 -> 0 | U22: ='8'!$V22*U$13 -> 0 | V22: ='8'!$W22*U$13 -> 0 | W22: ='9'!$V22*W$13 -> 0 | X22: ='9'!$W22*W$13 -> 0 | Y22: =ВЗ!$V22*Y$13 -> 0 | Z22: =ВЗ!$W22*Y$13 -> 0 | AA22: ='ГС без пил 1000м гор'!$V22*AA$13 -> 0 | AB22: ='ГС без пил 1000м гор'!$W22*AA$13 -> 0 | AC22: ='ГС пил 1500м гор'!$V22*AC$13 -> 0 | AD22: ='ГС пил 1500м гор'!$W22*AC$13 -> 0 | AE22: ='ГС без пилот 1500м гор'!$V22*AE$13 -> 0 | AF22: ='ГС без пилот 1500м гор'!$W22*AE$13 -> 0 | AG22: ='ГСЮра без пил МГРП'!$V22*AG$13 -> 0 | AH22: ='ГСЮра без пил МГРП'!$W22*AG$13 -> 0 | AI22: ='ГСЮра пил МСГРП'!$V22*AI$13 -> 0 | AJ22: ='ГСЮра пил МСГРП'!$W22*AI$13 -> 0 | AK22: ='ГСЮра керн ГИС'!$V22*AK$13 -> 0 | AL22: ='ГСЮра керн ГИС'!$W22*AK$13 -> 0 | AM22: =Посл.скв.!$V22*AM$13 -> 0 | AN22: =Посл.скв.!$W22*AM$13 -> 0 | AO22: =AM22+AK22+AI22+AG22+AE22+AC22+AA22+Y22++W22+U22+S22+Q22+M22+O22+K22+I22+G22 -> 0 | AP22: =AN22+AL22+AJ22+AH22+AF22+AD22+AB22+Z22++X22+V22+T22+R22+N22+P22+L22+J22+H22 -> 0
C23: ='Перв. скв '!C23 -> 0 | D23: ='Перв. скв '!D23 -> - мобилизация АвИЭС (переезд) | E23: ='Перв. скв '!E23 -> ООО "Буровая компания "Евразия" | F23: ='Перв. скв '!F23 -> операция | G23: ='Перв. скв '!$V23*G$13 -> 0 | H23: ='Перв. скв '!$W23*G$13 -> 0 | I23: ='2'!$V23*I$13 -> 0 | J23: ='2'!$W23*I$13 -> 0 | K23: ='3'!$V23*K$13 -> 0 | L23: ='3'!$W23*K$13 -> 0 | M23: ='4'!$V23*M$13 -> 0 | N23: ='4'!$W23*M$13 -> 0 | O23: ='5'!$V23*O$13 -> 0 | P23: ='5'!$W23*O$13 -> 0 | Q23: ='6'!$V23*Q$13 -> 0 | R23: ='6'!$W23*Q$13 -> 0 | S23: ='7'!$V23*S$13 -> 0 | T23: ='7'!$W23*S$13 -> 0 | U23: ='8'!$V23*U$13 -> 0 | V23: ='8'!$W23*U$13 -> 0 | W23: ='9'!$V23*W$13 -> 0 | X23: ='9'!$W23*W$13 -> 0 | Y23: =ВЗ!$V23*Y$13 -> 0 | Z23: =ВЗ!$W23*Y$13 -> 0 | AA23: ='ГС без пил 1000м гор'!$V23*AA$13 -> 0 | AB23: ='ГС без пил 1000м гор'!$W23*AA$13 -> 0 | AC23: ='ГС пил 1500м гор'!$V23*AC$13 -> 0 | AD23: ='ГС пил 1500м гор'!$W23*AC$13 -> 0 | AE23: ='ГС без пилот 1500м гор'!$V23*AE$13 -> 0 | AF23: ='ГС без пилот 1500м гор'!$W23*AE$13 -> 0 | AG23: ='ГСЮра без пил МГРП'!$V23*AG$13 -> 0 | AH23: ='ГСЮра без пил МГРП'!$W23*AG$13 -> 0 | AI23: ='ГСЮра пил МСГРП'!$V23*AI$13 -> 0 | AJ23: ='ГСЮра пил МСГРП'!$W23*AI$13 -> 0 | AK23: ='ГСЮра керн ГИС'!$V23*AK$13 -> 0 | AL23: ='ГСЮра керн ГИС'!$W23*AK$13 -> 0 | AM23: =Посл.скв.!$V23*AM$13 -> 0 | AN23: =Посл.скв.!$W23*AM$13 -> 0 | AO23: =AM23+AK23+AI23+AG23+AE23+AC23+AA23+Y23++W23+U23+S23+Q23+M23+O23+K23+I23+G23 -> 0 | AP23: =AN23+AL23+AJ23+AH23+AF23+AD23+AB23+Z23++X23+V23+T23+R23+N23+P23+L23+J23+H23 -> 0
C24: ='Перв. скв '!C24 -> 0 | D24: ='Перв. скв '!D24 -> 0 | E24: ='Перв. скв '!E24 -> ООО "Буровая компания "Евразия" | F24: ='Перв. скв '!F24 -> операция | G24: ='Перв. скв '!$V24*G$13 -> 0 | H24: ='Перв. скв '!$W24*G$13 -> 0 | I24: ='2'!$V24*I$13 -> 0 | J24: ='2'!$W24*I$13 -> 0 | K24: ='3'!$V24*K$13 -> 0 | L24: ='3'!$W24*K$13 -> 0 | M24: ='4'!$V24*M$13 -> 0 | N24: ='4'!$W24*M$13 -> 0 | O24: ='5'!$V24*O$13 -> 0 | P24: ='5'!$W24*O$13 -> 0 | Q24: ='6'!$V24*Q$13 -> 0 | R24: ='6'!$W24*Q$13 -> 0 | S24: ='7'!$V24*S$13 -> 0 | T24: ='7'!$W24*S$13 -> 0 | U24: ='8'!$V24*U$13 -> 0 | V24: ='8'!$W24*U$13 -> 0 | W24: ='9'!$V24*W$13 -> 0 | X24: ='9'!$W24*W$13 -> 0 | Y24: =ВЗ!$V24*Y$13 -> 0 | Z24: =ВЗ!$W24*Y$13 -> 0 | AA24: ='ГС без пил 1000м гор'!$V24*AA$13 -> 0 | AB24: ='ГС без пил 1000м гор'!$W24*AA$13 -> 0 | AC24: ='ГС пил 1500м гор'!$V24*AC$13 -> 0 | AD24: ='ГС пил 1500м гор'!$W24*AC$13 -> 0 | AE24: ='ГС без пилот 1500м гор'!$V24*AE$13 -> 0 | AF24: ='ГС без пилот 1500м гор'!$W24*AE$13 -> 0 | AG24: ='ГСЮра без пил МГРП'!$V24*AG$13 -> 0 | AH24: ='ГСЮра без пил МГРП'!$W24*AG$13 -> 0 | AI24: ='ГСЮра пил МСГРП'!$V24*AI$13 -> 0 | AJ24: ='ГСЮра пил МСГРП'!$W24*AI$13 -> 0 | AK24: ='ГСЮра керн ГИС'!$V24*AK$13 -> 0 | AL24: ='ГСЮра керн ГИС'!$W24*AK$13 -> 0 | AM24: =Посл.скв.!$V24*AM$13 -> 0 | AN24: =Посл.скв.!$W24*AM$13 -> 0 | AO24: =AM24+AK24+AI24+AG24+AE24+AC24+AA24+Y24++W24+U24+S24+Q24+M24+O24+K24+I24+G24 -> 0 | AP24: =AN24+AL24+AJ24+AH24+AF24+AD24+AB24+Z24++X24+V24+T24+R24+N24+P24+L24+J24+H24 -> 0
C25: ='Перв. скв '!C25 -> 0 | D25: ='Перв. скв '!D25 -> 0 | E25: ='Перв. скв '!E25 -> ООО "Буровая компания "Евразия" | F25: ='Перв. скв '!F25 -> операция | G25: ='Перв. скв '!$V25*G$13 -> 0 | H25: ='Перв. скв '!$W25*G$13 -> 0 | I25: ='2'!$V25*I$13 -> 0 | J25: ='2'!$W25*I$13 -> 0 | K25: ='3'!$V25*K$13 -> 0 | L25: ='3'!$W25*K$13 -> 0 | M25: ='4'!$V25*M$13 -> 0 | N25: ='4'!$W25*M$13 -> 0 | O25: ='5'!$V25*O$13 -> 0 | P25: ='5'!$W25*O$13 -> 0 | Q25: ='6'!$V25*Q$13 -> 0 | R25: ='6'!$W25*Q$13 -> 0 | S25: ='7'!$V25*S$13 -> 0 | T25: ='7'!$W25*S$13 -> 0 | U25: ='8'!$V25*U$13 -> 0 | V25: ='8'!$W25*U$13 -> 0 | W25: ='9'!$V25*W$13 -> 0 | X25: ='9'!$W25*W$13 -> 0 | Y25: =ВЗ!$V25*Y$13 -> 0 | Z25: =ВЗ!$W25*Y$13 -> 0 | AA25: ='ГС без пил 1000м гор'!$V25*AA$13 -> 0 | AB25: ='ГС без пил 1000м гор'!$W25*AA$13 -> 0 | AC25: ='ГС пил 1500м гор'!$V25*AC$13 -> 0 | AD25: ='ГС пил 1500м гор'!$W25*AC$13 -> 0 | AE25: ='ГС без пилот 1500м гор'!$V25*AE$13 -> 0 | AF25: ='ГС без пилот 1500м гор'!$W25*AE$13 -> 0 | AG25: ='ГСЮра без пил МГРП'!$V25*AG$13 -> 0 | AH25: ='ГСЮра без пил МГРП'!$W25*AG$13 -> 0 | AI25: ='ГСЮра пил МСГРП'!$V25*AI$13 -> 0 | AJ25: ='ГСЮра пил МСГРП'!$W25*AI$13 -> 0 | AK25: ='ГСЮра керн ГИС'!$V25*AK$13 -> 0 | AL25: ='ГСЮра керн ГИС'!$W25*AK$13 -> 0 | AM25: =Посл.скв.!$V25*AM$13 -> 0 | AN25: =Посл.скв.!$W25*AM$13 -> 0 | AO25: =AM25+AK25+AI25+AG25+AE25+AC25+AA25+Y25++W25+U25+S25+Q25+M25+O25+K25+I25+G25 -> 0 | AP25: =AN25+AL25+AJ25+AH25+AF25+AD25+AB25+Z25++X25+V25+T25+R25+N25+P25+L25+J25+H25 -> 0
C26: ='Перв. скв '!C26 -> 0 | D26: ='Перв. скв '!D26 -> 0 | E26: ='Перв. скв '!E26 -> ООО "Буровая компания "Евразия" | F26: ='Перв. скв '!F26 -> операция | G26: ='Перв. скв '!$V26*G$13 -> 0 | H26: ='Перв. скв '!$W26*G$13 -> 0 | I26: ='2'!$V26*I$13 -> 0 | J26: ='2'!$W26*I$13 -> 0 | K26: ='3'!$V26*K$13 -> 0 | L26: ='3'!$W26*K$13 -> 0 | M26: ='4'!$V26*M$13 -> 0 | N26: ='4'!$W26*M$13 -> 0 | O26: ='5'!$V26*O$13 -> 0 | P26: ='5'!$W26*O$13 -> 0 | Q26: ='6'!$V26*Q$13 -> 0 | R26: ='6'!$W26*Q$13 -> 0 | S26: ='7'!$V26*S$13 -> 0 | T26: ='7'!$W26*S$13 -> 0 | U26: ='8'!$V26*U$13 -> 0 | V26: ='8'!$W26*U$13 -> 0 | W26: ='9'!$V26*W$13 -> 0 | X26: ='9'!$W26*W$13 -> 0 | Y26: =ВЗ!$V26*Y$13 -> 0 | Z26: =ВЗ!$W26*Y$13 -> 0 | AA26: ='ГС без пил 1000м гор'!$V26*AA$13 -> 0 | AB26: ='ГС без пил 1000м гор'!$W26*AA$13 -> 0 | AC26: ='ГС пил 1500м гор'!$V26*AC$13 -> 0 | AD26: ='ГС пил 1500м гор'!$W26*AC$13 -> 0 | AE26: ='ГС без пилот 1500м гор'!$V26*AE$13 -> 0 | AF26: ='ГС без пилот 1500м гор'!$W26*AE$13 -> 0 | AG26: ='ГСЮра без пил МГРП'!$V26*AG$13 -> 0 | AH26: ='ГСЮра без пил МГРП'!$W26*AG$13 -> 0 | AI26: ='ГСЮра пил МСГРП'!$V26*AI$13 -> 0 | AJ26: ='ГСЮра пил МСГРП'!$W26*AI$13 -> 0 | AK26: ='ГСЮра керн ГИС'!$V26*AK$13 -> 0 | AL26: ='ГСЮра керн ГИС'!$W26*AK$13 -> 0 | AM26: =Посл.скв.!$V26*AM$13 -> 0 | AN26: =Посл.скв.!$W26*AM$13 -> 0 | AO26: =AM26+AK26+AI26+AG26+AE26+AC26+AA26+Y26++W26+U26+S26+Q26+M26+O26+K26+I26+G26 -> 0 | AP26: =AN26+AL26+AJ26+AH26+AF26+AD26+AB26+Z26++X26+V26+T26+R26+N26+P26+L26+J26+H26 -> 0
C27: ='Перв. скв '!C27 -> 0 | D27: ='Перв. скв '!D27 -> 0 | E27: ='Перв. скв '!E27 -> ООО "Буровая компания "Евразия" | F27: ='Перв. скв '!F27 -> операция | G27: ='Перв. скв '!$V27*G$13 -> 0 | H27: ='Перв. скв '!$W27*G$13 -> 0 | I27: ='2'!$V27*I$13 -> 0 | J27: ='2'!$W27*I$13 -> 0 | K27: ='3'!$V27*K$13 -> 0 | L27: ='3'!$W27*K$13 -> 0 | M27: ='4'!$V27*M$13 -> 0 | N27: ='4'!$W27*M$13 -> 0 | O27: ='5'!$V27*O$13 -> 0 | P27: ='5'!$W27*O$13 -> 0 | Q27: ='6'!$V27*Q$13 -> 0 | R27: ='6'!$W27*Q$13 -> 0 | S27: ='7'!$V27*S$13 -> 0 | T27: ='7'!$W27*S$13 -> 0 | U27: ='8'!$V27*U$13 -> 0 | V27: ='8'!$W27*U$13 -> 0 | W27: ='9'!$V27*W$13 -> 0 | X27: ='9'!$W27*W$13 -> 0 | Y27: =ВЗ!$V27*Y$13 -> 0 | Z27: =ВЗ!$W27*Y$13 -> 0 | AA27: ='ГС без пил 1000м гор'!$V27*AA$13 -> 0 | AB27: ='ГС без пил 1000м гор'!$W27*AA$13 -> 0 | AC27: ='ГС пил 1500м гор'!$V27*AC$13 -> 0 | AD27: ='ГС пил 1500м гор'!$W27*AC$13 -> 0 | AE27: ='ГС без пилот 1500м гор'!$V27*AE$13 -> 0 | AF27: ='ГС без пилот 1500м гор'!$W27*AE$13 -> 0 | AG27: ='ГСЮра без пил МГРП'!$V27*AG$13 -> 0 | AH27: ='ГСЮра без пил МГРП'!$W27*AG$13 -> 0 | AI27: ='ГСЮра пил МСГРП'!$V27*AI$13 -> 0 | AJ27: ='ГСЮра пил МСГРП'!$W27*AI$13 -> 0 | AK27: ='ГСЮра керн ГИС'!$V27*AK$13 -> 0 | AL27: ='ГСЮра керн ГИС'!$W27*AK$13 -> 0 | AM27: =Посл.скв.!$V27*AM$13 -> 0 | AN27: =Посл.скв.!$W27*AM$13 -> 0 | AO27: =AM27+AK27+AI27+AG27+AE27+AC27+AA27+Y27++W27+U27+S27+Q27+M27+O27+K27+I27+G27 -> 0 | AP27: =AN27+AL27+AJ27+AH27+AF27+AD27+AB27+Z27++X27+V27+T27+R27+N27+P27+L27+J27+H27 -> 0
C28: ='Перв. скв '!C28 -> 0 | D28: ='Перв. скв '!D28 -> 0 | E28: ='Перв. скв '!E28 -> ООО "Буровая компания "Евразия" | F28: ='Перв. скв '!F28 -> операция | G28: ='Перв. скв '!$V28*G$13 -> 0 | H28: ='Перв. скв '!$W28*G$13 -> 0 | I28: ='2'!$V28*I$13 -> 0 | J28: ='2'!$W28*I$13 -> 0 | K28: ='3'!$V28*K$13 -> 0 | L28: ='3'!$W28*K$13 -> 0 | M28: ='4'!$V28*M$13 -> 0 | N28: ='4'!$W28*M$13 -> 0 | O28: ='5'!$V28*O$13 -> 0 | P28: ='5'!$W28*O$13 -> 0 | Q28: ='6'!$V28*Q$13 -> 0 | R28: ='6'!$W28*Q$13 -> 0 | S28: ='7'!$V28*S$13 -> 0 | T28: ='7'!$W28*S$13 -> 0 | U28: ='8'!$V28*U$13 -> 0 | V28: ='8'!$W28*U$13 -> 0 | W28: ='9'!$V28*W$13 -> 0 | X28: ='9'!$W28*W$13 -> 0 | Y28: =ВЗ!$V28*Y$13 -> 0 | Z28: =ВЗ!$W28*Y$13 -> 0 | AA28: ='ГС без пил 1000м гор'!$V28*AA$13 -> 0 | AB28: ='ГС без пил 1000м гор'!$W28*AA$13 -> 0 | AC28: ='ГС пил 1500м гор'!$V28*AC$13 -> 0 | AD28: ='ГС пил 1500м гор'!$W28*AC$13 -> 0 | AE28: ='ГС без пилот 1500м гор'!$V28*AE$13 -> 0 | AF28: ='ГС без пилот 1500м гор'!$W28*AE$13 -> 0 | AG28: ='ГСЮра без пил МГРП'!$V28*AG$13 -> 0 | AH28: ='ГСЮра без пил МГРП'!$W28*AG$13 -> 0 | AI28: ='ГСЮра пил МСГРП'!$V28*AI$13 -> 0 | AJ28: ='ГСЮра пил МСГРП'!$W28*AI$13 -> 0 | AK28: ='ГСЮра керн ГИС'!$V28*AK$13 -> 0 | AL28: ='ГСЮра керн ГИС'!$W28*AK$13 -> 0 | AM28: =Посл.скв.!$V28*AM$13 -> 0 | AN28: =Посл.скв.!$W28*AM$13 -> 0 | AO28: =AM28+AK28+AI28+AG28+AE28+AC28+AA28+Y28++W28+U28+S28+Q28+M28+O28+K28+I28+G28 -> 0 | AP28: =AN28+AL28+AJ28+AH28+AF28+AD28+AB28+Z28++X28+V28+T28+R28+N28+P28+L28+J28+H28 -> 0
C29: ='Перв. скв '!C29 -> Работы связанные со сборкой (монтажем) и подключением БУ, бурового и вспомогательного оборудования | D29: ='Перв. скв '!D29 -> Монтаж БУ | E29: ='Перв. скв '!E29 -> ООО "Буровая компания "Евразия" | F29: ='Перв. скв '!F29 -> операция | G29: ='Перв. скв '!$V29*G$13 -> 0 | H29: ='Перв. скв '!$W29*G$13 -> 0 | I29: ='2'!$V29*I$13 -> 0 | J29: ='2'!$W29*I$13 -> 0 | K29: ='3'!$V29*K$13 -> 0 | L29: ='3'!$W29*K$13 -> 0 | M29: ='4'!$V29*M$13 -> 0 | N29: ='4'!$W29*M$13 -> 0 | O29: ='5'!$V29*O$13 -> 0 | P29: ='5'!$W29*O$13 -> 0 | Q29: ='6'!$V29*Q$13 -> 0 | R29: ='6'!$W29*Q$13 -> 0 | S29: ='7'!$V29*S$13 -> 0 | T29: ='7'!$W29*S$13 -> 0 | U29: ='8'!$V29*U$13 -> 0 | V29: ='8'!$W29*U$13 -> 0 | W29: ='9'!$V29*W$13 -> 0 | X29: ='9'!$W29*W$13 -> 0 | Y29: =ВЗ!$V29*Y$13 -> 0 | Z29: =ВЗ!$W29*Y$13 -> 0 | AA29: ='ГС без пил 1000м гор'!$V29*AA$13 -> 0 | AB29: ='ГС без пил 1000м гор'!$W29*AA$13 -> 0 | AC29: ='ГС пил 1500м гор'!$V29*AC$13 -> 0 | AD29: ='ГС пил 1500м гор'!$W29*AC$13 -> 0 | AE29: ='ГС без пилот 1500м гор'!$V29*AE$13 -> 0 | AF29: ='ГС без пилот 1500м гор'!$W29*AE$13 -> 0 | AG29: ='ГСЮра без пил МГРП'!$V29*AG$13 -> 0 | AH29: ='ГСЮра без пил МГРП'!$W29*AG$13 -> 0 | AI29: ='ГСЮра пил МСГРП'!$V29*AI$13 -> 0 | AJ29: ='ГСЮра пил МСГРП'!$W29*AI$13 -> 0 | AK29: ='ГСЮра керн ГИС'!$V29*AK$13 -> 0 | AL29: ='ГСЮра керн ГИС'!$W29*AK$13 -> 0 | AM29: =Посл.скв.!$V29*AM$13 -> 0 | AN29: =Посл.скв.!$W29*AM$13 -> 0 | AO29: =AM29+AK29+AI29+AG29+AE29+AC29+AA29+Y29++W29+U29+S29+Q29+M29+O29+K29+I29+G29 -> 0 | AP29: =AN29+AL29+AJ29+AH29+AF29+AD29+AB29+Z29++X29+V29+T29+R29+N29+P29+L29+J29+H29 -> 0
C30: ='Перв. скв '!C30 -> 0 | D30: ='Перв. скв '!D30 -> - монтаж БУ | E30: ='Перв. скв '!E30 -> ООО "Буровая компания "Евразия" | F30: ='Перв. скв '!F30 -> операция | G30: ='Перв. скв '!$V30*G$13 -> 0 | H30: ='Перв. скв '!$W30*G$13 -> 0 | I30: ='2'!$V30*I$13 -> 0 | J30: ='2'!$W30*I$13 -> 0 | K30: ='3'!$V30*K$13 -> 0 | L30: ='3'!$W30*K$13 -> 0 | M30: ='4'!$V30*M$13 -> 0 | N30: ='4'!$W30*M$13 -> 0 | O30: ='5'!$V30*O$13 -> 0 | P30: ='5'!$W30*O$13 -> 0 | Q30: ='6'!$V30*Q$13 -> 0 | R30: ='6'!$W30*Q$13 -> 0 | S30: ='7'!$V30*S$13 -> 0 | T30: ='7'!$W30*S$13 -> 0 | U30: ='8'!$V30*U$13 -> 0 | V30: ='8'!$W30*U$13 -> 0 | W30: ='9'!$V30*W$13 -> 0 | X30: ='9'!$W30*W$13 -> 0 | Y30: =ВЗ!$V30*Y$13 -> 0 | Z30: =ВЗ!$W30*Y$13 -> 0 | AA30: ='ГС без пил 1000м гор'!$V30*AA$13 -> 0 | AB30: ='ГС без пил 1000м гор'!$W30*AA$13 -> 0 | AC30: ='ГС пил 1500м гор'!$V30*AC$13 -> 0 | AD30: ='ГС пил 1500м гор'!$W30*AC$13 -> 0 | AE30: ='ГС без пилот 1500м гор'!$V30*AE$13 -> 0 | AF30: ='ГС без пилот 1500м гор'!$W30*AE$13 -> 0 | AG30: ='ГСЮра без пил МГРП'!$V30*AG$13 -> 0 | AH30: ='ГСЮра без пил МГРП'!$W30*AG$13 -> 0 | AI30: ='ГСЮра пил МСГРП'!$V30*AI$13 -> 0 | AJ30: ='ГСЮра пил МСГРП'!$W30*AI$13 -> 0 | AK30: ='ГСЮра керн ГИС'!$V30*AK$13 -> 0 | AL30: ='ГСЮра керн ГИС'!$W30*AK$13 -> 0 | AM30: =Посл.скв.!$V30*AM$13 -> 0 | AN30: =Посл.скв.!$W30*AM$13 -> 0 | AO30: =AM30+AK30+AI30+AG30+AE30+AC30+AA30+Y30++W30+U30+S30+Q30+M30+O30+K30+I30+G30 -> 0 | AP30: =AN30+AL30+AJ30+AH30+AF30+AD30+AB30+Z30++X30+V30+T30+R30+N30+P30+L30+J30+H30 -> 0
C31: ='Перв. скв '!C31 -> 0 | D31: ='Перв. скв '!D31 -> - монтаж АвИЭС | E31: ='Перв. скв '!E31 -> ООО "Буровая компания "Евразия" | F31: ='Перв. скв '!F31 -> операция | G31: ='Перв. скв '!$V31*G$13 -> 0 | H31: ='Перв. скв '!$W31*G$13 -> 0 | I31: ='2'!$V31*I$13 -> 0 | J31: ='2'!$W31*I$13 -> 0 | K31: ='3'!$V31*K$13 -> 0 | L31: ='3'!$W31*K$13 -> 0 | M31: ='4'!$V31*M$13 -> 0 | N31: ='4'!$W31*M$13 -> 0 | O31: ='5'!$V31*O$13 -> 0 | P31: ='5'!$W31*O$13 -> 0 | Q31: ='6'!$V31*Q$13 -> 0 | R31: ='6'!$W31*Q$13 -> 0 | S31: ='7'!$V31*S$13 -> 0 | T31: ='7'!$W31*S$13 -> 0 | U31: ='8'!$V31*U$13 -> 0 | V31: ='8'!$W31*U$13 -> 0 | W31: ='9'!$V31*W$13 -> 0 | X31: ='9'!$W31*W$13 -> 0 | Y31: =ВЗ!$V31*Y$13 -> 0 | Z31: =ВЗ!$W31*Y$13 -> 0 | AA31: ='ГС без пил 1000м гор'!$V31*AA$13 -> 0 | AB31: ='ГС без пил 1000м гор'!$W31*AA$13 -> 0 | AC31: ='ГС пил 1500м гор'!$V31*AC$13 -> 0 | AD31: ='ГС пил 1500м гор'!$W31*AC$13 -> 0 | AE31: ='ГС без пилот 1500м гор'!$V31*AE$13 -> 0 | AF31: ='ГС без пилот 1500м гор'!$W31*AE$13 -> 0 | AG31: ='ГСЮра без пил МГРП'!$V31*AG$13 -> 0 | AH31: ='ГСЮра без пил МГРП'!$W31*AG$13 -> 0 | AI31: ='ГСЮра пил МСГРП'!$V31*AI$13 -> 0 | AJ31: ='ГСЮра пил МСГРП'!$W31*AI$13 -> 0 | AK31: ='ГСЮра керн ГИС'!$V31*AK$13 -> 0 | AL31: ='ГСЮра керн ГИС'!$W31*AK$13 -> 0 | AM31: =Посл.скв.!$V31*AM$13 -> 0 | AN31: =Посл.скв.!$W31*AM$13 -> 0 | AO31: =AM31+AK31+AI31+AG31+AE31+AC31+AA31+Y31++W31+U31+S31+Q31+M31+O31+K31+I31+G31 -> 0 | AP31: =AN31+AL31+AJ31+AH31+AF31+AD31+AB31+Z31++X31+V31+T31+R31+N31+P31+L31+J31+H31 -> 0
... C35: ='Перв. скв '!C35 -> 0 | D35: ='Перв. скв '!D35 -> 0 | E35: ='Перв. скв '!E35 -> ООО "Буровая компания "Евразия" | F35: ='Перв. скв '!F35 -> операция | G35: ='Перв. скв '!$V35*G$13 -> 0 | H35: ='Перв. скв '!$W35*G$13 -> 0 | I35: ='2'!$V35*I$13 -> 0 | J35: ='2'!$W35*I$13 -> 0 | K35: ='3'!$V35*K$13 -> 0 | L35: ='3'!$W35*K$13 -> 0 | M35: ='4'!$V35*M$13 -> 0 | N35: ='4'!$W35*M$13 -> 0 | O35: ='5'!$V35*O$13 -> 0 | P35: ='5'!$W35*O$13 -> 0 | Q35: ='6'!$V35*Q$13 -> 0 | R35: ='6'!$W35*Q$13 -> 0 | S35: ='7'!$V35*S$13 -> 0 | T35: ='7'!$W35*S$13 -> 0 | U35: ='8'!$V35*U$13 -> 0 | V35: ='8'!$W35*U$13 -> 0 | W35: ='9'!$V35*W$13 -> 0 | X35: ='9'!$W35*W$13 -> 0 | Y35: =ВЗ!$V35*Y$13 -> 0 | Z35: =ВЗ!$W35*Y$13 -> 0 | AA35: ='ГС без пил 1000м гор'!$V35*AA$13 -> 0 | AB35: ='ГС без пил 1000м гор'!$W35*AA$13 -> 0 | AC35: ='ГС пил 1500м гор'!$V35*AC$13 -> 0 | AD35: ='ГС пил 1500м гор'!$W35*AC$13 -> 0 | AE35: ='ГС без пилот 1500м гор'!$V35*AE$13 -> 0 | AF35: ='ГС без пилот 1500м гор'!$W35*AE$13 -> 0 | AG35: ='ГСЮра без пил МГРП'!$V35*AG$13 -> 0 | AH35: ='ГСЮра без пил МГРП'!$W35*AG$13 -> 0 | AI35: ='ГСЮра пил МСГРП'!$V35*AI$13 -> 0 | AJ35: ='ГСЮра пил МСГРП'!$W35*AI$13 -> 0 | AK35: ='ГСЮра керн ГИС'!$V35*AK$13 -> 0 | AL35: ='ГСЮра керн ГИС'!$W35*AK$13 -> 0 | AM35: =Посл.скв.!$V35*AM$13 -> 0 | AN35: =Посл.скв.!$W35*AM$13 -> 0 | AO35: =AM35+AK35+AI35+AG35+AE35+AC35+AA35+Y35++W35+U35+S35+Q35+M35+O35+K35+I35+G35 -> 0 | AP35: =AN35+AL35+AJ35+AH35+AF35+AD35+AB35+Z35++X35+V35+T35+R35+N35+P35+L35+J35+H35 -> 0
D36: ='Перв. скв '!D36 -> 0 | E36: ='Перв. скв '!E36 -> ООО "Буровая компания "Евразия" | F36: ='Перв. скв '!F36 -> операция | G36: ='Перв. скв '!$V36*G$13 -> 0 | H36: ='Перв. скв '!$W36*G$13 -> 0 | I36: ='2'!$V36*I$13 -> 0 | J36: ='2'!$W36*I$13 -> 0 | K36: ='3'!$V36*K$13 -> 0 | L36: ='3'!$W36*K$13 -> 0 | M36: ='4'!$V36*M$13 -> 0 | N36: ='4'!$W36*M$13 -> 0 | O36: ='5'!$V36*O$13 -> 0 | P36: ='5'!$W36*O$13 -> 0 | Q36: ='6'!$V36*Q$13 -> 0 | R36: ='6'!$W36*Q$13 -> 0 | S36: ='7'!$V36*S$13 -> 0 | T36: ='7'!$W36*S$13 -> 0 | U36: ='8'!$V36*U$13 -> 0 | V36: ='8'!$W36*U$13 -> 0 | W36: ='9'!$V36*W$13 -> 0 | X36: ='9'!$W36*W$13 -> 0 | Y36: =ВЗ!$V36*Y$13 -> 0 | Z36: =ВЗ!$W36*Y$13 -> 0 | AA36: ='ГС без пил 1000м гор'!$V36*AA$13 -> 0 | AB36: ='ГС без пил 1000м гор'!$W36*AA$13 -> 0 | AC36: ='ГС пил 1500м гор'!$V36*AC$13 -> 0 | AD36: ='ГС пил 1500м гор'!$W36*AC$13 -> 0 | AE36: ='ГС без пилот 1500м гор'!$V36*AE$13 -> 0 | AF36: ='ГС без пилот 1500м гор'!$W36*AE$13 -> 0 | AG36: ='ГСЮра без пил МГРП'!$V36*AG$13 -> 0 | AH36: ='ГСЮра без пил МГРП'!$W36*AG$13 -> 0 | AI36: ='ГСЮра пил МСГРП'!$V36*AI$13 -> 0 | AJ36: ='ГСЮра пил МСГРП'!$W36*AI$13 -> 0 | AK36: ='ГСЮра керн ГИС'!$V36*AK$13 -> 0 | AL36: ='ГСЮра керн ГИС'!$W36*AK$13 -> 0 | AM36: =Посл.скв.!$V36*AM$13 -> 0 | AN36: =Посл.скв.!$W36*AM$13 -> 0 | AO36: =AM36+AK36+AI36+AG36+AE36+AC36+AA36+Y36++W36+U36+S36+Q36+M36+O36+K36+I36+G36 -> 0 | AP36: =AN36+AL36+AJ36+AH36+AF36+AD36+AB36+Z36++X36+V36+T36+R36+N36+P36+L36+J36+H36 -> 0
C37: ='Перв. скв '!C37 -> 0 | D37: ='Перв. скв '!D37 -> 0 | E37: ='Перв. скв '!E37 -> ООО "Буровая компания "Евразия" | F37: ='Перв. скв '!F37 -> операция | G37: ='Перв. скв '!$V37*G$13 -> 0 | H37: ='Перв. скв '!$W37*G$13 -> 0 | I37: ='2'!$V37*I$13 -> 0 | J37: ='2'!$W37*I$13 -> 0 | K37: ='3'!$V37*K$13 -> 0 | L37: ='3'!$W37*K$13 -> 0 | M37: ='4'!$V37*M$13 -> 0 | N37: ='4'!$W37*M$13 -> 0 | O37: ='5'!$V37*O$13 -> 0 | P37: ='5'!$W37*O$13 -> 0 | Q37: ='6'!$V37*Q$13 -> 0 | R37: ='6'!$W37*Q$13 -> 0 | S37: ='7'!$V37*S$13 -> 0 | T37: ='7'!$W37*S$13 -> 0 | U37: ='8'!$V37*U$13 -> 0 | V37: ='8'!$W37*U$13 -> 0 | W37: ='9'!$V37*W$13 -> 0 | X37: ='9'!$W37*W$13 -> 0 | Y37: =ВЗ!$V37*Y$13 -> 0 | Z37: =ВЗ!$W37*Y$13 -> 0 | AA37: ='ГС без пил 1000м гор'!$V37*AA$13 -> 0 | AB37: ='ГС без пил 1000м гор'!$W37*AA$13 -> 0 | AC37: ='ГС пил 1500м гор'!$V37*AC$13 -> 0 | AD37: ='ГС пил 1500м гор'!$W37*AC$13 -> 0 | AE37: ='ГС без пилот 1500м гор'!$V37*AE$13 -> 0 | AF37: ='ГС без пилот 1500м гор'!$W37*AE$13 -> 0 | AG37: ='ГСЮра без пил МГРП'!$V37*AG$13 -> 0 | AH37: ='ГСЮра без пил МГРП'!$W37*AG$13 -> 0 | AI37: ='ГСЮра пил МСГРП'!$V37*AI$13 -> 0 | AJ37: ='ГСЮра пил МСГРП'!$W37*AI$13 -> 0 | AK37: ='ГСЮра керн ГИС'!$V37*AK$13 -> 0 | AL37: ='ГСЮра керн ГИС'!$W37*AK$13 -> 0 | AM37: =Посл.скв.!$V37*AM$13 -> 0 | AN37: =Посл.скв.!$W37*AM$13 -> 0 | AO37: =AM37+AK37+AI37+AG37+AE37+AC37+AA37+Y37++W37+U37+S37+Q37+M37+O37+K37+I37+G37 -> 0 | AP37: =AN37+AL37+AJ37+AH37+AF37+AD37+AB37+Z37++X37+V37+T37+R37+N37+P37+L37+J37+H37 -> 0
C38: ='Перв. скв '!C38 -> 0 | D38: ='Перв. скв '!D38 -> 0 | E38: ='Перв. скв '!E38 -> ООО "Буровая компания "Евразия" | F38: ='Перв. скв '!F38 -> операция | G38: ='Перв. скв '!$V38*G$13 -> 0 | H38: ='Перв. скв '!$W38*G$13 -> 0 | I38: ='2'!$V38*I$13 -> 0 | J38: ='2'!$W38*I$13 -> 0 | K38: ='3'!$V38*K$13 -> 0 | L38: ='3'!$W38*K$13 -> 0 | M38: ='4'!$V38*M$13 -> 0 | N38: ='4'!$W38*M$13 -> 0 | O38: ='5'!$V38*O$13 -> 0 | P38: ='5'!$W38*O$13 -> 0 | Q38: ='6'!$V38*Q$13 -> 0 | R38: ='6'!$W38*Q$13 -> 0 | S38: ='7'!$V38*S$13 -> 0 | T38: ='7'!$W38*S$13 -> 0 | U38: ='8'!$V38*U$13 -> 0 | V38: ='8'!$W38*U$13 -> 0 | W38: ='9'!$V38*W$13 -> 0 | X38: ='9'!$W38*W$13 -> 0 | Y38: =ВЗ!$V38*Y$13 -> 0 | Z38: =ВЗ!$W38*Y$13 -> 0 | AA38: ='ГС без пил 1000м гор'!$V38*AA$13 -> 0 | AB38: ='ГС без пил 1000м гор'!$W38*AA$13 -> 0 | AC38: ='ГС пил 1500м гор'!$V38*AC$13 -> 0 | AD38: ='ГС пил 1500м гор'!$W38*AC$13 -> 0 | AE38: ='ГС без пилот 1500м гор'!$V38*AE$13 -> 0 | AF38: ='ГС без пилот 1500м гор'!$W38*AE$13 -> 0 | AG38: ='ГСЮра без пил МГРП'!$V38*AG$13 -> 0 | AH38: ='ГСЮра без пил МГРП'!$W38*AG$13 -> 0 | AI38: ='ГСЮра пил МСГРП'!$V38*AI$13 -> 0 | AJ38: ='ГСЮра пил МСГРП'!$W38*AI$13 -> 0 | AK38: ='ГСЮра керн ГИС'!$V38*AK$13 -> 0 | AL38: ='ГСЮра керн ГИС'!$W38*AK$13 -> 0 | AM38: =Посл.скв.!$V38*AM$13 -> 0 | AN38: =Посл.скв.!$W38*AM$13 -> 0 | AO38: =AM38+AK38+AI38+AG38+AE38+AC38+AA38+Y38++W38+U38+S38+Q38+M38+O38+K38+I38+G38 -> 0 | AP38: =AN38+AL38+AJ38+AH38+AF38+AD38+AB38+Z38++X38+V38+T38+R38+N38+P38+L38+J38+H38 -> 0
C39: ='Перв. скв '!C39 -> Работы, свзянные с передвижкой БУ между скважинами на кустовой площадке | D39: ='Перв. скв '!D39 -> Передвижка 5 м. | E39: ='Перв. скв '!E39 -> ООО "Буровая компания "Евразия" | F39: ='Перв. скв '!F39 -> операция | G39: ='Перв. скв '!$V39*G$13 -> 0 | H39: ='Перв. скв '!$W39*G$13 -> 0 | I39: ='2'!$V39*I$13 -> 0 | J39: ='2'!$W39*I$13 -> 0 | K39: ='3'!$V39*K$13 -> 0 | L39: ='3'!$W39*K$13 -> 0 | M39: ='4'!$V39*M$13 -> 0 | N39: ='4'!$W39*M$13 -> 0 | O39: ='5'!$V39*O$13 -> 0 | P39: ='5'!$W39*O$13 -> 0 | Q39: ='6'!$V39*Q$13 -> 0 | R39: ='6'!$W39*Q$13 -> 0 | S39: ='7'!$V39*S$13 -> 0 | T39: ='7'!$W39*S$13 -> 0 | U39: ='8'!$V39*U$13 -> 0 | V39: ='8'!$W39*U$13 -> 0 | W39: ='9'!$V39*W$13 -> 0 | X39: ='9'!$W39*W$13 -> 0 | Y39: =ВЗ!$V39*Y$13 -> 0 | Z39: =ВЗ!$W39*Y$13 -> 0 | AA39: ='ГС без пил 1000м гор'!$V39*AA$13 -> 0 | AB39: ='ГС без пил 1000м гор'!$W39*AA$13 -> 0 | AC39: ='ГС пил 1500м гор'!$V39*AC$13 -> 0 | AD39: ='ГС пил 1500м гор'!$W39*AC$13 -> 0 | AE39: ='ГС без пилот 1500м гор'!$V39*AE$13 -> 0 | AF39: ='ГС без пилот 1500м гор'!$W39*AE$13 -> 0 | AG39: ='ГСЮра без пил МГРП'!$V39*AG$13 -> 0 | AH39: ='ГСЮра без пил МГРП'!$W39*AG$13 -> 0 | AI39: ='ГСЮра пил МСГРП'!$V39*AI$13 -> 0 | AJ39: ='ГСЮра пил МСГРП'!$W39*AI$13 -> 0 | AK39: ='ГСЮра керн ГИС'!$V39*AK$13 -> 0 | AL39: ='ГСЮра керн ГИС'!$W39*AK$13 -> 0 | AM39: =Посл.скв.!$V39*AM$13 -> 0 | AN39: =Посл.скв.!$W39*AM$13 -> 0 | AO39: =AM39+AK39+AI39+AG39+AE39+AC39+AA39+Y39++W39+U39+S39+Q39+M39+O39+K39+I39+G39 -> 0 | AP39: =AN39+AL39+AJ39+AH39+AF39+AD39+AB39+Z39++X39+V39+T39+R39+N39+P39+L39+J39+H39 -> 0
C40: ='Перв. скв '!C40 -> 0 | D40: ='Перв. скв '!D40 -> Передвижка 9 м. | E40: ='Перв. скв '!E40 -> ООО "Буровая компания "Евразия" | F40: ='Перв. скв '!F40 -> операция | G40: ='Перв. скв '!$V40*G$13 -> 0 | H40: ='Перв. скв '!$W40*G$13 -> 0 | I40: ='2'!$V40*I$13 -> 0 | J40: ='2'!$W40*I$13 -> 0 | K40: ='3'!$V40*K$13 -> 0 | L40: ='3'!$W40*K$13 -> 0 | M40: ='4'!$V40*M$13 -> 0 | N40: ='4'!$W40*M$13 -> 0 | O40: ='5'!$V40*O$13 -> 0 | P40: ='5'!$W40*O$13 -> 0 | Q40: ='6'!$V40*Q$13 -> 0 | R40: ='6'!$W40*Q$13 -> 0 | S40: ='7'!$V40*S$13 -> 0 | T40: ='7'!$W40*S$13 -> 0 | U40: ='8'!$V40*U$13 -> 0 | V40: ='8'!$W40*U$13 -> 0 | W40: ='9'!$V40*W$13 -> 0 | X40: ='9'!$W40*W$13 -> 0 | Y40: =ВЗ!$V40*Y$13 -> 0 | Z40: =ВЗ!$W40*Y$13 -> 0 | AA40: ='ГС без пил 1000м гор'!$V40*AA$13 -> 0 | AB40: ='ГС без пил 1000м гор'!$W40*AA$13 -> 0 | AC40: ='ГС пил 1500м гор'!$V40*AC$13 -> 0 | AD40: ='ГС пил 1500м гор'!$W40*AC$13 -> 0 | AE40: ='ГС без пилот 1500м гор'!$V40*AE$13 -> 0 | AF40: ='ГС без пилот 1500м гор'!$W40*AE$13 -> 0 | AG40: ='ГСЮра без пил МГРП'!$V40*AG$13 -> 0 | AH40: ='ГСЮра без пил МГРП'!$W40*AG$13 -> 0 | AI40: ='ГСЮра пил МСГРП'!$V40*AI$13 -> 0 | AJ40: ='ГСЮра пил МСГРП'!$W40*AI$13 -> 0 | AK40: ='ГСЮра керн ГИС'!$V40*AK$13 -> 0 | AL40: ='ГСЮра керн ГИС'!$W40*AK$13 -> 0 | AM40: =Посл.скв.!$V40*AM$13 -> 0 | AN40: =Посл.скв.!$W40*AM$13 -> 0 | AO40: =AM40+AK40+AI40+AG40+AE40+AC40+AA40+Y40++W40+U40+S40+Q40+M40+O40+K40+I40+G40 -> 0 | AP40: =AN40+AL40+AJ40+AH40+AF40+AD40+AB40+Z40++X40+V40+T40+R40+N40+P40+L40+J40+H40 -> 0
C41: ='Перв. скв '!C41 -> 0 | D41: ='Перв. скв '!D41 -> Передвижка 18 м. | E41: ='Перв. скв '!E41 -> ООО "Буровая компания "Евразия" | F41: ='Перв. скв '!F41 -> операция | G41: ='Перв. скв '!$V41*G$13 -> 0 | H41: ='Перв. скв '!$W41*G$13 -> 0 | I41: ='2'!$V41*I$13 -> 0 | J41: ='2'!$W41*I$13 -> 0 | K41: ='3'!$V41*K$13 -> 0 | L41: ='3'!$W41*K$13 -> 0 | M41: ='4'!$V41*M$13 -> 0 | N41: ='4'!$W41*M$13 -> 0 | O41: ='5'!$V41*O$13 -> 0 | P41: ='5'!$W41*O$13 -> 0 | Q41: ='6'!$V41*Q$13 -> 0 | R41: ='6'!$W41*Q$13 -> 0 | S41: ='7'!$V41*S$13 -> 0 | T41: ='7'!$W41*S$13 -> 0 | U41: ='8'!$V41*U$13 -> 0 | V41: ='8'!$W41*U$13 -> 0 | W41: ='9'!$V41*W$13 -> 0 | X41: ='9'!$W41*W$13 -> 0 | Y41: =ВЗ!$V41*Y$13 -> 2 | Z41: =ВЗ!$W41*Y$13 -> 2970233.4 | AA41: ='ГС без пил 1000м гор'!$V41*AA$13 -> 8 | AB41: ='ГС без пил 1000м гор'!$W41*AA$13 -> 15141530 | AC41: ='ГС пил 1500м гор'!$V41*AC$13 -> 0 | AD41: ='ГС пил 1500м гор'!$W41*AC$13 -> 0 | AE41: ='ГС без пилот 1500м гор'!$V41*AE$13 -> 6 | AF41: ='ГС без пилот 1500м гор'!$W41*AE$13 -> 9637869.5 | AG41: ='ГСЮра без пил МГРП'!$V41*AG$13 -> 9 | AH41: ='ГСЮра без пил МГРП'!$W41*AG$13 -> 14109099 | AI41: ='ГСЮра пил МСГРП'!$V41*AI$13 -> 4 | AJ41: ='ГСЮра пил МСГРП'!$W41*AI$13 -> 6243114.8 | AK41: ='ГСЮра керн ГИС'!$V41*AK$13 -> 1 | AL41: ='ГСЮра керн ГИС'!$W41*AK$13 -> 1540081.9 | AM41: =Посл.скв.!$V41*AM$13 -> 0 | AN41: =Посл.скв.!$W41*AM$13 -> 0 | AO41: =AM41+AK41+AI41+AG41+AE41+AC41+AA41+Y41++W41+U41+S41+Q41+M41+O41+K41+I41+G41 -> 30 | AP41: =AN41+AL41+AJ41+AH41+AF41+AD41+AB41+Z41++X41+V41+T41+R41+N41+P41+L41+J41+H41 -> 49641928
C42: ='Перв. скв '!C42 -> 0 | D42: ='Перв. скв '!D42 -> Передвижка 25 м. | E42: ='Перв. скв '!E42 -> ООО "Буровая компания "Евразия" | F42: ='Перв. скв '!F42 -> операция | G42: ='Перв. скв '!$V42*G$13 -> 0 | H42: ='Перв. скв '!$W42*G$13 -> 0 | I42: ='2'!$V42*I$13 -> 0 | J42: ='2'!$W42*I$13 -> 0 | K42: ='3'!$V42*K$13 -> 0 | L42: ='3'!$W42*K$13 -> 0 | M42: ='4'!$V42*M$13 -> 0 | N42: ='4'!$W42*M$13 -> 0 | O42: ='5'!$V42*O$13 -> 0 | P42: ='5'!$W42*O$13 -> 0 | Q42: ='6'!$V42*Q$13 -> 0 | R42: ='6'!$W42*Q$13 -> 0 | S42: ='7'!$V42*S$13 -> 0 | T42: ='7'!$W42*S$13 -> 0 | U42: ='8'!$V42*U$13 -> 0 | V42: ='8'!$W42*U$13 -> 0 | W42: ='9'!$V42*W$13 -> 0 | X42: ='9'!$W42*W$13 -> 0 | Y42: =ВЗ!$V42*Y$13 -> 0 | Z42: =ВЗ!$W42*Y$13 -> 0 | AA42: ='ГС без пил 1000м гор'!$V42*AA$13 -> 0 | AB42: ='ГС без пил 1000м гор'!$W42*AA$13 -> 0 | AC42: ='ГС пил 1500м гор'!$V42*AC$13 -> 0 | AD42: ='ГС пил 1500м гор'!$W42*AC$13 -> 0 | AE42: ='ГС без пилот 1500м гор'!$V42*AE$13 -> 0 | AF42: ='ГС без пилот 1500м гор'!$W42*AE$13 -> 0 | AG42: ='ГСЮра без пил МГРП'!$V42*AG$13 -> 0 | AH42: ='ГСЮра без пил МГРП'!$W42*AG$13 -> 0 | AI42: ='ГСЮра пил МСГРП'!$V42*AI$13 -> 0 | AJ42: ='ГСЮра пил МСГРП'!$W42*AI$13 -> 0 | AK42: ='ГСЮра керн ГИС'!$V42*AK$13 -> 0 | AL42: ='ГСЮра керн ГИС'!$W42*AK$13 -> 0 | AM42: =Посл.скв.!$V42*AM$13 -> 0 | AN42: =Посл.скв.!$W42*AM$13 -> 0 | AO42: =AM42+AK42+AI42+AG42+AE42+AC42+AA42+Y42++W42+U42+S42+Q42+M42+O42+K42+I42+G42 -> 0 | AP42: =AN42+AL42+AJ42+AH42+AF42+AD42+AB42+Z42++X42+V42+T42+R42+N42+P42+L42+J42+H42 -> 0
C43: ='Перв. скв '!C43 -> 0 | D43: ='Перв. скв '!D43 -> Передвижка 75 м. | E43: ='Перв. скв '!E43 -> ООО "Буровая компания "Евразия" | F43: ='Перв. скв '!F43 -> операция | G43: ='Перв. скв '!$V43*G$13 -> 0 | H43: ='Перв. скв '!$W43*G$13 -> 0 | I43: ='2'!$V43*I$13 -> 0 | J43: ='2'!$W43*I$13 -> 0 | K43: ='3'!$V43*K$13 -> 0 | L43: ='3'!$W43*K$13 -> 0 | M43: ='4'!$V43*M$13 -> 0 | N43: ='4'!$W43*M$13 -> 0 | O43: ='5'!$V43*O$13 -> 0 | P43: ='5'!$W43*O$13 -> 0 | Q43: ='6'!$V43*Q$13 -> 0 | R43: ='6'!$W43*Q$13 -> 0 | S43: ='7'!$V43*S$13 -> 0 | T43: ='7'!$W43*S$13 -> 0 | U43: ='8'!$V43*U$13 -> 0 | V43: ='8'!$W43*U$13 -> 0 | W43: ='9'!$V43*W$13 -> 0 | X43: ='9'!$W43*W$13 -> 0 | Y43: =ВЗ!$V43*Y$13 -> 0 | Z43: =ВЗ!$W43*Y$13 -> 0 | AA43: ='ГС без пил 1000м гор'!$V43*AA$13 -> 0 | AB43: ='ГС без пил 1000м гор'!$W43*AA$13 -> 0 | AC43: ='ГС пил 1500м гор'!$V43*AC$13 -> 0 | AD43: ='ГС пил 1500м гор'!$W43*AC$13 -> 0 | AE43: ='ГС без пилот 1500м гор'!$V43*AE$13 -> 0 | AF43: ='ГС без пилот 1500м гор'!$W43*AE$13 -> 0 | AG43: ='ГСЮра без пил МГРП'!$V43*AG$13 -> 0 | AH43: ='ГСЮра без пил МГРП'!$W43*AG$13 -> 0 | AI43: ='ГСЮра пил МСГРП'!$V43*AI$13 -> 0 | AJ43: ='ГСЮра пил МСГРП'!$W43*AI$13 -> 0 | AK43: ='ГСЮра керн ГИС'!$V43*AK$13 -> 0 | AL43: ='ГСЮра керн ГИС'!$W43*AK$13 -> 0 | AM43: =Посл.скв.!$V43*AM$13 -> 0 | AN43: =Посл.скв.!$W43*AM$13 -> 0 | AO43: =AM43+AK43+AI43+AG43+AE43+AC43+AA43+Y43++W43+U43+S43+Q43+M43+O43+K43+I43+G43 -> 0 | AP43: =AN43+AL43+AJ43+AH43+AF43+AD43+AB43+Z43++X43+V43+T43+R43+N43+P43+L43+J43+H43 -> 0
C44: ='Перв. скв '!C44 -> 0 | D44: ='Перв. скв '!D44 -> Передвижка нестандартная | E44: ='Перв. скв '!E44 -> ООО "Буровая компания "Евразия" | F44: ='Перв. скв '!F44 -> операция | G44: ='Перв. скв '!$V44*G$13 -> 0 | H44: ='Перв. скв '!$W44*G$13 -> 0 | I44: ='2'!$V44*I$13 -> 0 | J44: ='2'!$W44*I$13 -> 0 | K44: ='3'!$V44*K$13 -> 0 | L44: ='3'!$W44*K$13 -> 0 | M44: ='4'!$V44*M$13 -> 0 | N44: ='4'!$W44*M$13 -> 0 | O44: ='5'!$V44*O$13 -> 0 | P44: ='5'!$W44*O$13 -> 0 | Q44: ='6'!$V44*Q$13 -> 0 | R44: ='6'!$W44*Q$13 -> 0 | S44: ='7'!$V44*S$13 -> 0 | T44: ='7'!$W44*S$13 -> 0 | U44: ='8'!$V44*U$13 -> 0 | V44: ='8'!$W44*U$13 -> 0 | W44: ='9'!$V44*W$13 -> 0 | X44: ='9'!$W44*W$13 -> 0 | Y44: =ВЗ!$V44*Y$13 -> 0 | Z44: =ВЗ!$W44*Y$13 -> 0 | AA44: ='ГС без пил 1000м гор'!$V44*AA$13 -> 0 | AB44: ='ГС без пил 1000м гор'!$W44*AA$13 -> 0 | AC44: ='ГС пил 1500м гор'!$V44*AC$13 -> 0 | AD44: ='ГС пил 1500м гор'!$W44*AC$13 -> 0 | AE44: ='ГС без пилот 1500м гор'!$V44*AE$13 -> 0 | AF44: ='ГС без пилот 1500м гор'!$W44*AE$13 -> 0 | AG44: ='ГСЮра без пил МГРП'!$V44*AG$13 -> 0 | AH44: ='ГСЮра без пил МГРП'!$W44*AG$13 -> 0 | AI44: ='ГСЮра пил МСГРП'!$V44*AI$13 -> 0 | AJ44: ='ГСЮра пил МСГРП'!$W44*AI$13 -> 0 | AK44: ='ГСЮра керн ГИС'!$V44*AK$13 -> 0 | AL44: ='ГСЮра керн ГИС'!$W44*AK$13 -> 0 | AM44: =Посл.скв.!$V44*AM$13 -> 0 | AN44: =Посл.скв.!$W44*AM$13 -> 0 | AO44: =AM44+AK44+AI44+AG44+AE44+AC44+AA44+Y44++W44+U44+S44+Q44+M44+O44+K44+I44+G44 -> 0 | AP44: =AN44+AL44+AJ44+AH44+AF44+AD44+AB44+Z44++X44+V44+T44+R44+N44+P44+L44+J44+H44 -> 0
C45: ='Перв. скв '!C45 -> Работы связанные с демонтажем БУ, бурового и вспомогательного оборудования | D45: ='Перв. скв '!D45 -> Демонтаж БУ | E45: ='Перв. скв '!E45 -> ООО "Буровая компания "Евразия" | F45: ='Перв. скв '!F45 -> операция | G45: ='Перв. скв '!$V45*G$13 -> 0 | H45: ='Перв. скв '!$W45*G$13 -> 0 | I45: ='2'!$V45*I$13 -> 0 | J45: ='2'!$W45*I$13 -> 0 | K45: ='3'!$V45*K$13 -> 0 | L45: ='3'!$W45*K$13 -> 0 | M45: ='4'!$V45*M$13 -> 0 | N45: ='4'!$W45*M$13 -> 0 | O45: ='5'!$V45*O$13 -> 0 | P45: ='5'!$W45*O$13 -> 0 | Q45: ='6'!$V45*Q$13 -> 0 | R45: ='6'!$W45*Q$13 -> 0 | S45: ='7'!$V45*S$13 -> 0 | T45: ='7'!$W45*S$13 -> 0 | U45: ='8'!$V45*U$13 -> 0 | V45: ='8'!$W45*U$13 -> 0 | W45: ='9'!$V45*W$13 -> 0 | X45: ='9'!$W45*W$13 -> 0 | Y45: =ВЗ!$V45*Y$13 -> 0 | Z45: =ВЗ!$W45*Y$13 -> 0 | AA45: ='ГС без пил 1000м гор'!$V45*AA$13 -> 0 | AB45: ='ГС без пил 1000м гор'!$W45*AA$13 -> 0 | AC45: ='ГС пил 1500м гор'!$V45*AC$13 -> 0 | AD45: ='ГС пил 1500м гор'!$W45*AC$13 -> 0 | AE45: ='ГС без пилот 1500м гор'!$V45*AE$13 -> 0 | AF45: ='ГС без пилот 1500м гор'!$W45*AE$13 -> 0 | AG45: ='ГСЮра без пил МГРП'!$V45*AG$13 -> 0 | AH45: ='ГСЮра без пил МГРП'!$W45*AG$13 -> 0 | AI45: ='ГСЮра пил МСГРП'!$V45*AI$13 -> 0 | AJ45: ='ГСЮра пил МСГРП'!$W45*AI$13 -> 0 | AK45: ='ГСЮра керн ГИС'!$V45*AK$13 -> 0 | AL45: ='ГСЮра керн ГИС'!$W45*AK$13 -> 0 | AM45: =Посл.скв.!$V45*AM$13 -> 0 | AN45: =Посл.скв.!$W45*AM$13 -> 0 | AO45: =AM45+AK45+AI45+AG45+AE45+AC45+AA45+Y45++W45+U45+S45+Q45+M45+O45+K45+I45+G45 -> 0 | AP45: =AN45+AL45+AJ45+AH45+AF45+AD45+AB45+Z45++X45+V45+T45+R45+N45+P45+L45+J45+H45 -> 0
C46: ='Перв. скв '!C46 -> 0 | D46: ='Перв. скв '!D46 -> - демонтаж БУ | E46: ='Перв. скв '!E46 -> ООО "Буровая компания "Евразия" | F46: ='Перв. скв '!F46 -> операция | G46: ='Перв. скв '!$V46*G$13 -> 0 | H46: ='Перв. скв '!$W46*G$13 -> 0 | I46: ='2'!$V46*I$13 -> 0 | J46: ='2'!$W46*I$13 -> 0 | K46: ='3'!$V46*K$13 -> 0 | L46: ='3'!$W46*K$13 -> 0 | M46: ='4'!$V46*M$13 -> 0 | N46: ='4'!$W46*M$13 -> 0 | O46: ='5'!$V46*O$13 -> 0 | P46: ='5'!$W46*O$13 -> 0 | Q46: ='6'!$V46*Q$13 -> 0 | R46: ='6'!$W46*Q$13 -> 0 | S46: ='7'!$V46*S$13 -> 0 | T46: ='7'!$W46*S$13 -> 0 | U46: ='8'!$V46*U$13 -> 0 | V46: ='8'!$W46*U$13 -> 0 | W46: ='9'!$V46*W$13 -> 0 | X46: ='9'!$W46*W$13 -> 0 | Y46: =ВЗ!$V46*Y$13 -> 0 | Z46: =ВЗ!$W46*Y$13 -> 0 | AA46: ='ГС без пил 1000м гор'!$V46*AA$13 -> 0 | AB46: ='ГС без пил 1000м гор'!$W46*AA$13 -> 0 | AC46: ='ГС пил 1500м гор'!$V46*AC$13 -> 0 | AD46: ='ГС пил 1500м гор'!$W46*AC$13 -> 0 | AE46: ='ГС без пилот 1500м гор'!$V46*AE$13 -> 0 | AF46: ='ГС без пилот 1500м гор'!$W46*AE$13 -> 0 | AG46: ='ГСЮра без пил МГРП'!$V46*AG$13 -> 0 | AH46: ='ГСЮра без пил МГРП'!$W46*AG$13 -> 0 | AI46: ='ГСЮра пил МСГРП'!$V46*AI$13 -> 0 | AJ46: ='ГСЮра пил МСГРП'!$W46*AI$13 -> 0 | AK46: ='ГСЮра керн ГИС'!$V46*AK$13 -> 0 | AL46: ='ГСЮра керн ГИС'!$W46*AK$13 -> 0 | AM46: =Посл.скв.!$V46*AM$13 -> 0 | AN46: =Посл.скв.!$W46*AM$13 -> 0 | AO46: =AM46+AK46+AI46+AG46+AE46+AC46+AA46+Y46++W46+U46+S46+Q46+M46+O46+K46+I46+G46 -> 0 | AP46: =AN46+AL46+AJ46+AH46+AF46+AD46+AB46+Z46++X46+V46+T46+R46+N46+P46+L46+J46+H46 -> 0
C47: ='Перв. скв '!C47 -> 0 | D47: ='Перв. скв '!D47 -> - демонтаж АвИЭС | E47: ='Перв. скв '!E47 -> ООО "Буровая компания "Евразия" | F47: ='Перв. скв '!F47 -> операция | G47: ='Перв. скв '!$V47*G$13 -> 0 | H47: ='Перв. скв '!$W47*G$13 -> 0 | I47: ='2'!$V47*I$13 -> 0 | J47: ='2'!$W47*I$13 -> 0 | K47: ='3'!$V47*K$13 -> 0 | L47: ='3'!$W47*K$13 -> 0 | M47: ='4'!$V47*M$13 -> 0 | N47: ='4'!$W47*M$13 -> 0 | O47: ='5'!$V47*O$13 -> 0 | P47: ='5'!$W47*O$13 -> 0 | Q47: ='6'!$V47*Q$13 -> 0 | R47: ='6'!$W47*Q$13 -> 0 | S47: ='7'!$V47*S$13 -> 0 | T47: ='7'!$W47*S$13 -> 0 | U47: ='8'!$V47*U$13 -> 0 | V47: ='8'!$W47*U$13 -> 0 | W47: ='9'!$V47*W$13 -> 0 | X47: ='9'!$W47*W$13 -> 0 | Y47: =ВЗ!$V47*Y$13 -> 0 | Z47: =ВЗ!$W47*Y$13 -> 0 | AA47: ='ГС без пил 1000м гор'!$V47*AA$13 -> 0 | AB47: ='ГС без пил 1000м гор'!$W47*AA$13 -> 0 | AC47: ='ГС пил 1500м гор'!$V47*AC$13 -> 0 | AD47: ='ГС пил 1500м гор'!$W47*AC$13 -> 0 | AE47: ='ГС без пилот 1500м гор'!$V47*AE$13 -> 0 | AF47: ='ГС без пилот 1500м гор'!$W47*AE$13 -> 0 | AG47: ='ГСЮра без пил МГРП'!$V47*AG$13 -> 0 | AH47: ='ГСЮра без пил МГРП'!$W47*AG$13 -> 0 | AI47: ='ГСЮра пил МСГРП'!$V47*AI$13 -> 0 | AJ47: ='ГСЮра пил МСГРП'!$W47*AI$13 -> 0 | AK47: ='ГСЮра керн ГИС'!$V47*AK$13 -> 0 | AL47: ='ГСЮра керн ГИС'!$W47*AK$13 -> 0 | AM47: =Посл.скв.!$V47*AM$13 -> 0 | AN47: =Посл.скв.!$W47*AM$13 -> 0 | AO47: =AM47+AK47+AI47+AG47+AE47+AC47+AA47+Y47++W47+U47+S47+Q47+M47+O47+K47+I47+G47 -> 0 | AP47: =AN47+AL47+AJ47+AH47+AF47+AD47+AB47+Z47++X47+V47+T47+R47+N47+P47+L47+J47+H47 -> 0
C48: ='Перв. скв '!C48 -> 0 | D48: ='Перв. скв '!D48 -> - демонтаж БДЕ, ПВО | E48: ='Перв. скв '!E48 -> ООО "Буровая компания "Евразия" | F48: ='Перв. скв '!F48 -> операция | G48: ='Перв. скв '!$V48*G$13 -> 0 | H48: ='Перв. скв '!$W48*G$13 -> 0 | I48: ='2'!$V48*I$13 -> 0 | J48: ='2'!$W48*I$13 -> 0 | K48: ='3'!$V48*K$13 -> 0 | L48: ='3'!$W48*K$13 -> 0 | M48: ='4'!$V48*M$13 -> 0 | N48: ='4'!$W48*M$13 -> 0 | O48: ='5'!$V48*O$13 -> 0 | P48: ='5'!$W48*O$13 -> 0 | Q48: ='6'!$V48*Q$13 -> 0 | R48: ='6'!$W48*Q$13 -> 0 | S48: ='7'!$V48*S$13 -> 0 | T48: ='7'!$W48*S$13 -> 0 | U48: ='8'!$V48*U$13 -> 0 | V48: ='8'!$W48*U$13 -> 0 | W48: ='9'!$V48*W$13 -> 0 | X48: ='9'!$W48*W$13 -> 0 | Y48: =ВЗ!$V48*Y$13 -> 0 | Z48: =ВЗ!$W48*Y$13 -> 0 | AA48: ='ГС без пил 1000м гор'!$V48*AA$13 -> 0 | AB48: ='ГС без пил 1000м гор'!$W48*AA$13 -> 0 | AC48: ='ГС пил 1500м гор'!$V48*AC$13 -> 0 | AD48: ='ГС пил 1500м гор'!$W48*AC$13 -> 0 | AE48: ='ГС без пилот 1500м гор'!$V48*AE$13 -> 0 | AF48: ='ГС без пилот 1500м гор'!$W48*AE$13 -> 0 | AG48: ='ГСЮра без пил МГРП'!$V48*AG$13 -> 0 | AH48: ='ГСЮра без пил МГРП'!$W48*AG$13 -> 0 | AI48: ='ГСЮра пил МСГРП'!$V48*AI$13 -> 0 | AJ48: ='ГСЮра пил МСГРП'!$W48*AI$13 -> 0 | AK48: ='ГСЮра керн ГИС'!$V48*AK$13 -> 0 | AL48: ='ГСЮра керн ГИС'!$W48*AK$13 -> 0 | AM48: =Посл.скв.!$V48*AM$13 -> 0 | AN48: =Посл.скв.!$W48*AM$13 -> 0 | AO48: =AM48+AK48+AI48+AG48+AE48+AC48+AA48+Y48++W48+U48+S48+Q48+M48+O48+K48+I48+G48 -> 0 | AP48: =AN48+AL48+AJ48+AH48+AF48+AD48+AB48+Z48++X48+V48+T48+R48+N48+P48+L48+J48+H48 -> 0
... C67: ='Перв. скв '!C67 -> 0 | D67: ='Перв. скв '!D67 -> 0 | E67: ='Перв. скв '!E67 -> ООО "Буровая компания "Евразия" | F67: ='Перв. скв '!F67 -> операция | G67: ='Перв. скв '!$V67*G$13 -> 0 | H67: ='Перв. скв '!$W67*G$13 -> 0 | I67: ='2'!$V67*I$13 -> 0 | J67: ='2'!$W67*I$13 -> 0 | K67: ='3'!$V67*K$13 -> 0 | L67: ='3'!$W67*K$13 -> 0 | M67: ='4'!$V67*M$13 -> 0 | N67: ='4'!$W67*M$13 -> 0 | O67: ='5'!$V67*O$13 -> 0 | P67: ='5'!$W67*O$13 -> 0 | Q67: ='6'!$V67*Q$13 -> 0 | R67: ='6'!$W67*Q$13 -> 0 | S67: ='7'!$V67*S$13 -> 0 | T67: ='7'!$W67*S$13 -> 0 | U67: ='8'!$V67*U$13 -> 0 | V67: ='8'!$W67*U$13 -> 0 | W67: ='9'!$V67*W$13 -> 0 | X67: ='9'!$W67*W$13 -> 0 | Y67: =ВЗ!$V67*Y$13 -> 0 | Z67: =ВЗ!$W67*Y$13 -> 0 | AA67: ='ГС без пил 1000м гор'!$V67*AA$13 -> 0 | AB67: ='ГС без пил 1000м гор'!$W67*AA$13 -> 0 | AC67: ='ГС пил 1500м гор'!$V67*AC$13 -> 0 | AD67: ='ГС пил 1500м гор'!$W67*AC$13 -> 0 | AE67: ='ГС без пилот 1500м гор'!$V67*AE$13 -> 0 | AF67: ='ГС без пилот 1500м гор'!$W67*AE$13 -> 0 | AG67: ='ГСЮра без пил МГРП'!$V67*AG$13 -> 0 | AH67: ='ГСЮра без пил МГРП'!$W67*AG$13 -> 0 | AI67: ='ГСЮра пил МСГРП'!$V67*AI$13 -> 0 | AJ67: ='ГСЮра пил МСГРП'!$W67*AI$13 -> 0 | AK67: ='ГСЮра керн ГИС'!$V67*AK$13 -> 0 | AL67: ='ГСЮра керн ГИС'!$W67*AK$13 -> 0 | AM67: =Посл.скв.!$V67*AM$13 -> 0 | AN67: =Посл.скв.!$W67*AM$13 -> 0 | AO67: =AM67+AK67+AI67+AG67+AE67+AC67+AA67+Y67++W67+U67+S67+Q67+M67+O67+K67+I67+G67 -> 0 | AP67: =AN67+AL67+AJ67+AH67+AF67+AD67+AB67+Z67++X67+V67+T67+R67+N67+P67+L67+J67+H67 -> 0
C68: ='Перв. скв '!C68 -> 0 | E68: ='Перв. скв '!E68 -> ООО "Буровая компания "Евразия" | F68: ='Перв. скв '!F68 -> операция | G68: ='Перв. скв '!$V68*G$13 -> 0 | H68: ='Перв. скв '!$W68*G$13 -> 0 | I68: ='2'!$V68*I$13 -> 0 | J68: ='2'!$W68*I$13 -> 0 | K68: ='3'!$V68*K$13 -> 0 | L68: ='3'!$W68*K$13 -> 0 | M68: ='4'!$V68*M$13 -> 0 | N68: ='4'!$W68*M$13 -> 0 | O68: ='5'!$V68*O$13 -> 0 | P68: ='5'!$W68*O$13 -> 0 | Q68: ='6'!$V68*Q$13 -> 0 | R68: ='6'!$W68*Q$13 -> 0 | S68: ='7'!$V68*S$13 -> 0 | T68: ='7'!$W68*S$13 -> 0 | U68: ='8'!$V68*U$13 -> 0 | V68: ='8'!$W68*U$13 -> 0 | W68: ='9'!$V68*W$13 -> 0 | X68: ='9'!$W68*W$13 -> 0 | Y68: =ВЗ!$V68*Y$13 -> 0 | Z68: =ВЗ!$W68*Y$13 -> 0 | AA68: ='ГС без пил 1000м гор'!$V68*AA$13 -> 0 | AB68: ='ГС без пил 1000м гор'!$W68*AA$13 -> 0 | AC68: ='ГС пил 1500м гор'!$V68*AC$13 -> 0 | AD68: ='ГС пил 1500м гор'!$W68*AC$13 -> 0 | AE68: ='ГС без пилот 1500м гор'!$V68*AE$13 -> 0 | AF68: ='ГС без пилот 1500м гор'!$W68*AE$13 -> 0 | AG68: ='ГСЮра без пил МГРП'!$V68*AG$13 -> 0 | AH68: ='ГСЮра без пил МГРП'!$W68*AG$13 -> 0 | AI68: ='ГСЮра пил МСГРП'!$V68*AI$13 -> 0 | AJ68: ='ГСЮра пил МСГРП'!$W68*AI$13 -> 0 | AK68: ='ГСЮра керн ГИС'!$V68*AK$13 -> 0 | AL68: ='ГСЮра керн ГИС'!$W68*AK$13 -> 0 | AM68: =Посл.скв.!$V68*AM$13 -> 0 | AN68: =Посл.скв.!$W68*AM$13 -> 0 | AO68: =AM68+AK68+AI68+AG68+AE68+AC68+AA68+Y68++W68+U68+S68+Q68+M68+O68+K68+I68+G68 -> 0 | AP68: =AN68+AL68+AJ68+AH68+AF68+AD68+AB68+Z68++X68+V68+T68+R68+N68+P68+L68+J68+H68 -> 0
C69: ОБЩАЯ СТОИМОСТЬ ВМР | H69: =SUM(H20:H68) -> 2.5786548e+08 | J69: =SUM(J20:J68) -> 0 | L69: =SUM(L20:L68) -> 0 | N69: =SUM(N20:N68) -> 0 | P69: =SUM(P20:P68) -> 0 | R69: =SUM(R20:R68) -> 0 | T69: =SUM(T20:T68) -> 0 | V69: =SUM(V20:V68) -> 0 | X69: =SUM(X20:X68) -> 0 | Z69: =SUM(Z20:Z68) -> 2970233.4 | AB69: =SUM(AB20:AB68) -> 15141530 | AD69: =SUM(AD20:AD68) -> 0 | AF69: =SUM(AF20:AF68) -> 9637869.5 | AH69: =SUM(AH20:AH68) -> 14109099 | AJ69: =SUM(AJ20:AJ68) -> 6243114.8 | AL69: =SUM(AL20:AL68) -> 1540081.9 | AN69: =SUM(AN20:AN68) -> 0 | AP69: =SUM(AP20:AP68) -> 3.0750741e+08
C71: 2. ЭТАП БУРЕНИЯ:
C72: ='Перв. скв '!C72 -> ООО "Буровая компания "Евразия" | D72: Описание работ/услуг
C73: ='Перв. скв '!C73 -> Стоимость работ буровой бригады, а так же стоимость услуг АвИЭС | D73: ='Перв. скв '!D73 -> Суточная ставка работы буровой бригады | E73: ='Перв. скв '!E73 -> ООО "Буровая компания "Евразия" | F73: ='Перв. скв '!F73 -> сут | G73: ='Перв. скв '!$V73*G$13 -> 68 | H73: ='Перв. скв '!$W73*G$13 -> 97165796 | I73: ='2'!$V73*I$13 -> 0 | J73: ='2'!$W73*I$13 -> 0 | K73: ='3'!$V73*K$13 -> 0 | L73: ='3'!$W73*K$13 -> 0 | M73: ='4'!$V73*M$13 -> 0 | N73: ='4'!$W73*M$13 -> 0 | O73: ='5'!$V73*O$13 -> 0 | P73: ='5'!$W73*O$13 -> 0 | Q73: ='6'!$V73*Q$13 -> 0 | R73: ='6'!$W73*Q$13 -> 0 | S73: ='7'!$V73*S$13 -> 0 | T73: ='7'!$W73*S$13 -> 0 | U73: ='8'!$V73*U$13 -> 0 | V73: ='8'!$W73*U$13 -> 0 | W73: ='9'!$V73*W$13 -> 0 | X73: ='9'!$W73*W$13 -> 0 | Y73: =ВЗ!$V73*Y$13 -> 80 | Z73: =ВЗ!$W73*Y$13 -> 25645916 | AA73: ='ГС без пил 1000м гор'!$V73*AA$13 -> 264 | AB73: ='ГС без пил 1000м гор'!$W73*AA$13 -> 4.5284391e+08 | AC73: ='ГС пил 1500м гор'!$V73*AC$13 -> 0 | AD73: ='ГС пил 1500м гор'!$W73*AC$13 -> 0 | AE73: ='ГС без пилот 1500м гор'!$V73*AE$13 -> 204 | AF73: ='ГС без пилот 1500м гор'!$W73*AE$13 -> 2.8976393e+08 | AG73: ='ГСЮра без пил МГРП'!$V73*AG$13 -> 306 | AH73: ='ГСЮра без пил МГРП'!$W73*AG$13 -> 4.3724608e+08 | AI73: ='ГСЮра пил МСГРП'!$V73*AI$13 -> 164 | AJ73: ='ГСЮра пил МСГРП'!$W73*AI$13 -> 2.0035027e+08 | AK73: ='ГСЮра керн ГИС'!$V73*AK$13 -> 76 | AL73: ='ГСЮра керн ГИС'!$W73*AK$13 -> 88236316 | AM73: =Посл.скв.!$V73*AM$13 -> 0 | AN73: =Посл.скв.!$W73*AM$13 -> 0 | AO73: =AM73+AK73+AI73+AG73+AE73+AC73+AA73+Y73++W73+U73+S73+Q73+M73+O73+K73+I73+G73 -> 1162 | AP73: =AN73+AL73+AJ73+AH73+AF73+AD73+AB73+Z73++X73+V73+T73+R73+N73+P73+L73+J73+H73 -> 1.5912522e+09
D74: ='Перв. скв '!D74 -> Оплата по резервной ставке | E74: ='Перв. скв '!E74 -> ООО "Буровая компания "Евразия" | F74: ='Перв. скв '!F74 -> сут | G74: ='Перв. скв '!$V74*G$13 -> 0 | H74: ='Перв. скв '!$W74*G$13 -> 0 | I74: ='2'!$V74*I$13 -> 0 | J74: ='2'!$W74*I$13 -> 0 | K74: ='3'!$V74*K$13 -> 0 | L74: ='3'!$W74*K$13 -> 0 | M74: ='4'!$V74*M$13 -> 0 | N74: ='4'!$W74*M$13 -> 0 | O74: ='5'!$V74*O$13 -> 0 | P74: ='5'!$W74*O$13 -> 0 | Q74: ='6'!$V74*Q$13 -> 0 | R74: ='6'!$W74*Q$13 -> 0 | S74: ='7'!$V74*S$13 -> 0 | T74: ='7'!$W74*S$13 -> 0 | U74: ='8'!$V74*U$13 -> 0 | V74: ='8'!$W74*U$13 -> 0 | W74: ='9'!$V74*W$13 -> 0 | X74: ='9'!$W74*W$13 -> 0 | Y74: =ВЗ!$V74*Y$13 -> 0 | Z74: =ВЗ!$W74*Y$13 -> 0 | AA74: ='ГС без пил 1000м гор'!$V74*AA$13 -> 0 | AB74: ='ГС без пил 1000м гор'!$W74*AA$13 -> 0 | AC74: ='ГС пил 1500м гор'!$V74*AC$13 -> 0 | AD74: ='ГС пил 1500м гор'!$W74*AC$13 -> 0 | AE74: ='ГС без пилот 1500м гор'!$V74*AE$13 -> 0 | AF74: ='ГС без пилот 1500м гор'!$W74*AE$13 -> 0 | AG74: ='ГСЮра без пил МГРП'!$V74*AG$13 -> 0 | AH74: ='ГСЮра без пил МГРП'!$W74*AG$13 -> 0 | AI74: ='ГСЮра пил МСГРП'!$V74*AI$13 -> 0 | AJ74: ='ГСЮра пил МСГРП'!$W74*AI$13 -> 0 | AK74: ='ГСЮра керн ГИС'!$V74*AK$13 -> 0 | AL74: ='ГСЮра керн ГИС'!$W74*AK$13 -> 0 | AM74: =Посл.скв.!$V74*AM$13 -> 0 | AN74: =Посл.скв.!$W74*AM$13 -> 0 | AO74: =AM74+AK74+AI74+AG74+AE74+AC74+AA74+Y74++W74+U74+S74+Q74+M74+O74+K74+I74+G74 -> 0 | AP74: =AN74+AL74+AJ74+AH74+AF74+AD74+AB74+Z74++X74+V74+T74+R74+N74+P74+L74+J74+H74 -> 0
D75: ='Перв. скв '!D75 -> Оплата по ставке дежурства | E75: ='Перв. скв '!E75 -> ООО "Буровая компания "Евразия" | F75: ='Перв. скв '!F75 -> сут | G75: ='Перв. скв '!$V75*G$13 -> 0 | H75: ='Перв. скв '!$W75*G$13 -> 0 | I75: ='2'!$V75*I$13 -> 0 | J75: ='2'!$W75*I$13 -> 0 | K75: ='3'!$V75*K$13 -> 0 | L75: ='3'!$W75*K$13 -> 0 | M75: ='4'!$V75*M$13 -> 0 | N75: ='4'!$W75*M$13 -> 0 | O75: ='5'!$V75*O$13 -> 0 | P75: ='5'!$W75*O$13 -> 0 | Q75: ='6'!$V75*Q$13 -> 0 | R75: ='6'!$W75*Q$13 -> 0 | S75: ='7'!$V75*S$13 -> 0 | T75: ='7'!$W75*S$13 -> 0 | U75: ='8'!$V75*U$13 -> 0 | V75: ='8'!$W75*U$13 -> 0 | W75: ='9'!$V75*W$13 -> 0 | X75: ='9'!$W75*W$13 -> 0 | Y75: =ВЗ!$V75*Y$13 -> 0 | Z75: =ВЗ!$W75*Y$13 -> 0 | AA75: ='ГС без пил 1000м гор'!$V75*AA$13 -> 0 | AB75: ='ГС без пил 1000м гор'!$W75*AA$13 -> 0 | AC75: ='ГС пил 1500м гор'!$V75*AC$13 -> 0 | AD75: ='ГС пил 1500м гор'!$W75*AC$13 -> 0 | AE75: ='ГС без пилот 1500м гор'!$V75*AE$13 -> 0 | AF75: ='ГС без пилот 1500м гор'!$W75*AE$13 -> 0 | AG75: ='ГСЮра без пил МГРП'!$V75*AG$13 -> 0 | AH75: ='ГСЮра без пил МГРП'!$W75*AG$13 -> 0 | AI75: ='ГСЮра пил МСГРП'!$V75*AI$13 -> 0 | AJ75: ='ГСЮра пил МСГРП'!$W75*AI$13 -> 0 | AK75: ='ГСЮра керн ГИС'!$V75*AK$13 -> 0 | AL75: ='ГСЮра керн ГИС'!$W75*AK$13 -> 0 | AM75: =Посл.скв.!$V75*AM$13 -> 0 | AN75: =Посл.скв.!$W75*AM$13 -> 0 | AO75: =AM75+AK75+AI75+AG75+AE75+AC75+AA75+Y75++W75+U75+S75+Q75+M75+O75+K75+I75+G75 -> 0 | AP75: =AN75+AL75+AJ75+AH75+AF75+AD75+AB75+Z75++X75+V75+T75+R75+N75+P75+L75+J75+H75 -> 0
D76: ='Перв. скв '!D76 -> Монт/демонт ПВО и ФА, доп.работы | E76: ='Перв. скв '!E76 -> ООО "Буровая компания "Евразия" | F76: ='Перв. скв '!F76 -> сут | G76: ='Перв. скв '!$V76*G$13 -> 0 | H76: ='Перв. скв '!$W76*G$13 -> 0 | I76: ='2'!$V76*I$13 -> 0 | J76: ='2'!$W76*I$13 -> 0 | K76: ='3'!$V76*K$13 -> 0 | L76: ='3'!$W76*K$13 -> 0 | M76: ='4'!$V76*M$13 -> 0 | N76: ='4'!$W76*M$13 -> 0 | O76: ='5'!$V76*O$13 -> 0 | P76: ='5'!$W76*O$13 -> 0 | Q76: ='6'!$V76*Q$13 -> 0 | R76: ='6'!$W76*Q$13 -> 0 | S76: ='7'!$V76*S$13 -> 0 | T76: ='7'!$W76*S$13 -> 0 | U76: ='8'!$V76*U$13 -> 0 | V76: ='8'!$W76*U$13 -> 0 | W76: ='9'!$V76*W$13 -> 0 | X76: ='9'!$W76*W$13 -> 0 | Y76: =ВЗ!$V76*Y$13 -> 0 | Z76: =ВЗ!$W76*Y$13 -> 0 | AA76: ='ГС без пил 1000м гор'!$V76*AA$13 -> 0 | AB76: ='ГС без пил 1000м гор'!$W76*AA$13 -> 0 | AC76: ='ГС пил 1500м гор'!$V76*AC$13 -> 0 | AD76: ='ГС пил 1500м гор'!$W76*AC$13 -> 0 | AE76: ='ГС без пилот 1500м гор'!$V76*AE$13 -> 0 | AF76: ='ГС без пилот 1500м гор'!$W76*AE$13 -> 0 | AG76: ='ГСЮра без пил МГРП'!$V76*AG$13 -> 0 | AH76: ='ГСЮра без пил МГРП'!$W76*AG$13 -> 0 | AI76: ='ГСЮра пил МСГРП'!$V76*AI$13 -> 0 | AJ76: ='ГСЮра пил МСГРП'!$W76*AI$13 -> 0 | AK76: ='ГСЮра керн ГИС'!$V76*AK$13 -> 0 | AL76: ='ГСЮра керн ГИС'!$W76*AK$13 -> 0 | AM76: =Посл.скв.!$V76*AM$13 -> 0 | AN76: =Посл.скв.!$W76*AM$13 -> 0 | AO76: =AM76+AK76+AI76+AG76+AE76+AC76+AA76+Y76++W76+U76+S76+Q76+M76+O76+K76+I76+G76 -> 0 | AP76: =AN76+AL76+AJ76+AH76+AF76+AD76+AB76+Z76++X76+V76+T76+R76+N76+P76+L76+J76+H76 -> 0
D77: ='Перв. скв '!D77 -> Суточная ставка АвИЭС | E77: ='Перв. скв '!E77 -> ООО "Буровая компания "Евразия" | F77: ='Перв. скв '!F77 -> сут | G77: ='Перв. скв '!$V77*G$13 -> 68 | H77: ='Перв. скв '!$W77*G$13 -> 7065877.3 | I77: ='2'!$V77*I$13 -> 0 | J77: ='2'!$W77*I$13 -> 0 | K77: ='3'!$V77*K$13 -> 0 | L77: ='3'!$W77*K$13 -> 0 | M77: ='4'!$V77*M$13 -> 0 | N77: ='4'!$W77*M$13 -> 0 | O77: ='5'!$V77*O$13 -> 0 | P77: ='5'!$W77*O$13 -> 0 | Q77: ='6'!$V77*Q$13 -> 0 | R77: ='6'!$W77*Q$13 -> 0 | S77: ='7'!$V77*S$13 -> 0 | T77: ='7'!$W77*S$13 -> 0 | U77: ='8'!$V77*U$13 -> 0 | V77: ='8'!$W77*U$13 -> 0 | W77: ='9'!$V77*W$13 -> 0 | X77: ='9'!$W77*W$13 -> 0 | Y77: =ВЗ!$V77*Y$13 -> 80 | Z77: =ВЗ!$W77*Y$13 -> 8312796.8 | AA77: ='ГС без пил 1000м гор'!$V77*AA$13 -> 264 | AB77: ='ГС без пил 1000м гор'!$W77*AA$13 -> 27432229 | AC77: ='ГС пил 1500м гор'!$V77*AC$13 -> 0 | AD77: ='ГС пил 1500м гор'!$W77*AC$13 -> 0 | AE77: ='ГС без пилот 1500м гор'!$V77*AE$13 -> 204 | AF77: ='ГС без пилот 1500м гор'!$W77*AE$13 -> 21197632 | AG77: ='ГСЮра без пил МГРП'!$V77*AG$13 -> 306 | AH77: ='ГСЮра без пил МГРП'!$W77*AG$13 -> 31796448 | AI77: ='ГСЮра пил МСГРП'!$V77*AI$13 -> 164 | AJ77: ='ГСЮра пил МСГРП'!$W77*AI$13 -> 17041233 | AK77: ='ГСЮра керн ГИС'!$V77*AK$13 -> 76 | AL77: ='ГСЮра керн ГИС'!$W77*AK$13 -> 7897157 | AM77: =Посл.скв.!$V77*AM$13 -> 0 | AN77: =Посл.скв.!$W77*AM$13 -> 0 | AO77: =AM77+AK77+AI77+AG77+AE77+AC77+AA77+Y77++W77+U77+S77+Q77+M77+O77+K77+I77+G77 -> 1162 | AP77: =AN77+AL77+AJ77+AH77+AF77+AD77+AB77+Z77++X77+V77+T77+R77+N77+P77+L77+J77+H77 -> 1.2074337e+08
D78: ='Перв. скв '!D78 -> Ставка дежурства АвИЭС | E78: ='Перв. скв '!E78 -> ООО "Буровая компания "Евразия" | F78: ='Перв. скв '!F78 -> сут | G78: ='Перв. скв '!$V78*G$13 -> 0 | H78: ='Перв. скв '!$W78*G$13 -> 0 | I78: ='2'!$V78*I$13 -> 0 | J78: ='2'!$W78*I$13 -> 0 | K78: ='3'!$V78*K$13 -> 0 | L78: ='3'!$W78*K$13 -> 0 | M78: ='4'!$V78*M$13 -> 0 | N78: ='4'!$W78*M$13 -> 0 | O78: ='5'!$V78*O$13 -> 0 | P78: ='5'!$W78*O$13 -> 0 | Q78: ='6'!$V78*Q$13 -> 0 | R78: ='6'!$W78*Q$13 -> 0 | S78: ='7'!$V78*S$13 -> 0 | T78: ='7'!$W78*S$13 -> 0 | U78: ='8'!$V78*U$13 -> 0 | V78: ='8'!$W78*U$13 -> 0 | W78: ='9'!$V78*W$13 -> 0 | X78: ='9'!$W78*W$13 -> 0 | Y78: =ВЗ!$V78*Y$13 -> 0 | Z78: =ВЗ!$W78*Y$13 -> 0 | AA78: ='ГС без пил 1000м гор'!$V78*AA$13 -> 0 | AB78: ='ГС без пил 1000м гор'!$W78*AA$13 -> 0 | AC78: ='ГС пил 1500м гор'!$V78*AC$13 -> 0 | AD78: ='ГС пил 1500м гор'!$W78*AC$13 -> 0 | AE78: ='ГС без пилот 1500м гор'!$V78*AE$13 -> 0 | AF78: ='ГС без пилот 1500м гор'!$W78*AE$13 -> 0 | AG78: ='ГСЮра без пил МГРП'!$V78*AG$13 -> 0 | AH78: ='ГСЮра без пил МГРП'!$W78*AG$13 -> 0 | AI78: ='ГСЮра пил МСГРП'!$V78*AI$13 -> 0 | AJ78: ='ГСЮра пил МСГРП'!$W78*AI$13 -> 0 | AK78: ='ГСЮра керн ГИС'!$V78*AK$13 -> 0 | AL78: ='ГСЮра керн ГИС'!$W78*AK$13 -> 0 | AM78: =Посл.скв.!$V78*AM$13 -> 0 | AN78: =Посл.скв.!$W78*AM$13 -> 0 | AO78: =AM78+AK78+AI78+AG78+AE78+AC78+AA78+Y78++W78+U78+S78+Q78+M78+O78+K78+I78+G78 -> 0 | AP78: =AN78+AL78+AJ78+AH78+AF78+AD78+AB78+Z78++X78+V78+T78+R78+N78+P78+L78+J78+H78 -> 0
D79: ='Перв. скв '!D79 -> Прочее | E79: ='Перв. скв '!E79 -> ООО "Буровая компания "Евразия" | F79: ='Перв. скв '!F79 -> 0 | G79: ='Перв. скв '!$V79*G$13 -> 2 | H79: ='Перв. скв '!$W79*G$13 -> 10183195 | I79: ='2'!$V79*I$13 -> 0 | J79: ='2'!$W79*I$13 -> 0 | K79: ='3'!$V79*K$13 -> 0 | L79: ='3'!$W79*K$13 -> 0 | M79: ='4'!$V79*M$13 -> 0 | N79: ='4'!$W79*M$13 -> 0 | O79: ='5'!$V79*O$13 -> 0 | P79: ='5'!$W79*O$13 -> 0 | Q79: ='6'!$V79*Q$13 -> 0 | R79: ='6'!$W79*Q$13 -> 0 | S79: ='7'!$V79*S$13 -> 0 | T79: ='7'!$W79*S$13 -> 0 | U79: ='8'!$V79*U$13 -> 0 | V79: ='8'!$W79*U$13 -> 0 | W79: ='9'!$V79*W$13 -> 0 | X79: ='9'!$W79*W$13 -> 0 | Y79: =ВЗ!$V79*Y$13 -> 2 | Z79: =ВЗ!$W79*Y$13 -> 4242705 | AA79: ='ГС без пил 1000м гор'!$V79*AA$13 -> 8 | AB79: ='ГС без пил 1000м гор'!$W79*AA$13 -> 53351372 | AC79: ='ГС пил 1500м гор'!$V79*AC$13 -> 0 | AD79: ='ГС пил 1500м гор'!$W79*AC$13 -> 0 | AE79: ='ГС без пилот 1500м гор'!$V79*AE$13 -> 6 | AF79: ='ГС без пилот 1500м гор'!$W79*AE$13 -> 29916256 | AG79: ='ГСЮра без пил МГРП'!$V79*AG$13 -> 9 | AH79: ='ГСЮра без пил МГРП'!$W79*AG$13 -> 43386043 | AI79: ='ГСЮра пил МСГРП'!$V79*AI$13 -> 4 | AJ79: ='ГСЮра пил МСГРП'!$W79*AI$13 -> 17788776 | AK79: ='ГСЮра керн ГИС'!$V79*AK$13 -> 1 | AL79: ='ГСЮра керн ГИС'!$W79*AK$13 -> 7378540.3 | AM79: =Посл.скв.!$V79*AM$13 -> 0 | AN79: =Посл.скв.!$W79*AM$13 -> 0 | AO79: =AM79+AK79+AI79+AG79+AE79+AC79+AA79+Y79++W79+U79+S79+Q79+M79+O79+K79+I79+G79 -> 32 | AP79: =AN79+AL79+AJ79+AH79+AF79+AD79+AB79+Z79++X79+V79+T79+R79+N79+P79+L79+J79+H79 -> 1.6624689e+08
D80: ='Перв. скв '!D80 -> 0 | E80: ='Перв. скв '!E80 -> ООО "Буровая компания "Евразия" | F80: ='Перв. скв '!F80 -> 0 | G80: ='Перв. скв '!$V80*G$13 -> 0 | H80: ='Перв. скв '!$W80*G$13 -> 0 | I80: ='2'!$V80*I$13 -> 0 | J80: ='2'!$W80*I$13 -> 0 | K80: ='3'!$V80*K$13 -> 0 | L80: ='3'!$W80*K$13 -> 0 | M80: ='4'!$V80*M$13 -> 0 | N80: ='4'!$W80*M$13 -> 0 | O80: ='5'!$V80*O$13 -> 0 | P80: ='5'!$W80*O$13 -> 0 | Q80: ='6'!$V80*Q$13 -> 0 | R80: ='6'!$W80*Q$13 -> 0 | S80: ='7'!$V80*S$13 -> 0 | T80: ='7'!$W80*S$13 -> 0 | U80: ='8'!$V80*U$13 -> 0 | V80: ='8'!$W80*U$13 -> 0 | W80: ='9'!$V80*W$13 -> 0 | X80: ='9'!$W80*W$13 -> 0 | Y80: =ВЗ!$V80*Y$13 -> 0 | Z80: =ВЗ!$W80*Y$13 -> 0 | AA80: ='ГС без пил 1000м гор'!$V80*AA$13 -> 0 | AB80: ='ГС без пил 1000м гор'!$W80*AA$13 -> 0 | AC80: ='ГС пил 1500м гор'!$V80*AC$13 -> 0 | AD80: ='ГС пил 1500м гор'!$W80*AC$13 -> 0 | AE80: ='ГС без пилот 1500м гор'!$V80*AE$13 -> 0 | AF80: ='ГС без пилот 1500м гор'!$W80*AE$13 -> 0 | AG80: ='ГСЮра без пил МГРП'!$V80*AG$13 -> 0 | AH80: ='ГСЮра без пил МГРП'!$W80*AG$13 -> 0 | AI80: ='ГСЮра пил МСГРП'!$V80*AI$13 -> 0 | AJ80: ='ГСЮра пил МСГРП'!$W80*AI$13 -> 0 | AK80: ='ГСЮра керн ГИС'!$V80*AK$13 -> 0 | AL80: ='ГСЮра керн ГИС'!$W80*AK$13 -> 0 | AM80: =Посл.скв.!$V80*AM$13 -> 0 | AN80: =Посл.скв.!$W80*AM$13 -> 0 | AO80: =AM80+AK80+AI80+AG80+AE80+AC80+AA80+Y80++W80+U80+S80+Q80+M80+O80+K80+I80+G80 -> 0 | AP80: =AN80+AL80+AJ80+AH80+AF80+AD80+AB80+Z80++X80+V80+T80+R80+N80+P80+L80+J80+H80 -> 0
D81: ='Перв. скв '!D81 -> 0 | E81: ='Перв. скв '!E81 -> ООО "Буровая компания "Евразия" | F81: ='Перв. скв '!F81 -> 0 | G81: ='Перв. скв '!$V81*G$13 -> 0 | H81: ='Перв. скв '!$W81*G$13 -> 0 | I81: ='2'!$V81*I$13 -> 0 | J81: ='2'!$W81*I$13 -> 0 | K81: ='3'!$V81*K$13 -> 0 | L81: ='3'!$W81*K$13 -> 0 | M81: ='4'!$V81*M$13 -> 0 | N81: ='4'!$W81*M$13 -> 0 | O81: ='5'!$V81*O$13 -> 0 | P81: ='5'!$W81*O$13 -> 0 | Q81: ='6'!$V81*Q$13 -> 0 | R81: ='6'!$W81*Q$13 -> 0 | S81: ='7'!$V81*S$13 -> 0 | T81: ='7'!$W81*S$13 -> 0 | U81: ='8'!$V81*U$13 -> 0 | V81: ='8'!$W81*U$13 -> 0 | W81: ='9'!$V81*W$13 -> 0 | X81: ='9'!$W81*W$13 -> 0 | Y81: =ВЗ!$V81*Y$13 -> 0 | Z81: =ВЗ!$W81*Y$13 -> 0 | AA81: ='ГС без пил 1000м гор'!$V81*AA$13 -> 0 | AB81: ='ГС без пил 1000м гор'!$W81*AA$13 -> 0 | AC81: ='ГС пил 1500м гор'!$V81*AC$13 -> 0 | AD81: ='ГС пил 1500м гор'!$W81*AC$13 -> 0 | AE81: ='ГС без пилот 1500м гор'!$V81*AE$13 -> 0 | AF81: ='ГС без пилот 1500м гор'!$W81*AE$13 -> 0 | AG81: ='ГСЮра без пил МГРП'!$V81*AG$13 -> 0 | AH81: ='ГСЮра без пил МГРП'!$W81*AG$13 -> 0 | AI81: ='ГСЮра пил МСГРП'!$V81*AI$13 -> 0 | AJ81: ='ГСЮра пил МСГРП'!$W81*AI$13 -> 0 | AK81: ='ГСЮра керн ГИС'!$V81*AK$13 -> 0 | AL81: ='ГСЮра керн ГИС'!$W81*AK$13 -> 0 | AM81: =Посл.скв.!$V81*AM$13 -> 0 | AN81: =Посл.скв.!$W81*AM$13 -> 0 | AO81: =AM81+AK81+AI81+AG81+AE81+AC81+AA81+Y81++W81+U81+S81+Q81+M81+O81+K81+I81+G81 -> 0 | AP81: =AN81+AL81+AJ81+AH81+AF81+AD81+AB81+Z81++X81+V81+T81+R81+N81+P81+L81+J81+H81 -> 0
D82: ='Перв. скв '!D82 -> 0 | E82: ='Перв. скв '!E82 -> ООО "Буровая компания "Евразия" | F82: ='Перв. скв '!F82 -> 0 | G82: ='Перв. скв '!$V82*G$13 -> 0 | H82: ='Перв. скв '!$W82*G$13 -> 0 | I82: ='2'!$V82*I$13 -> 0 | J82: ='2'!$W82*I$13 -> 0 | K82: ='3'!$V82*K$13 -> 0 | L82: ='3'!$W82*K$13 -> 0 | M82: ='4'!$V82*M$13 -> 0 | N82: ='4'!$W82*M$13 -> 0 | O82: ='5'!$V82*O$13 -> 0 | P82: ='5'!$W82*O$13 -> 0 | Q82: ='6'!$V82*Q$13 -> 0 | R82: ='6'!$W82*Q$13 -> 0 | S82: ='7'!$V82*S$13 -> 0 | T82: ='7'!$W82*S$13 -> 0 | U82: ='8'!$V82*U$13 -> 0 | V82: ='8'!$W82*U$13 -> 0 | W82: ='9'!$V82*W$13 -> 0 | X82: ='9'!$W82*W$13 -> 0 | Y82: =ВЗ!$V82*Y$13 -> 0 | Z82: =ВЗ!$W82*Y$13 -> 0 | AA82: ='ГС без пил 1000м гор'!$V82*AA$13 -> 0 | AB82: ='ГС без пил 1000м гор'!$W82*AA$13 -> 0 | AC82: ='ГС пил 1500м гор'!$V82*AC$13 -> 0 | AD82: ='ГС пил 1500м гор'!$W82*AC$13 -> 0 | AE82: ='ГС без пилот 1500м гор'!$V82*AE$13 -> 0 | AF82: ='ГС без пилот 1500м гор'!$W82*AE$13 -> 0 | AG82: ='ГСЮра без пил МГРП'!$V82*AG$13 -> 0 | AH82: ='ГСЮра без пил МГРП'!$W82*AG$13 -> 0 | AI82: ='ГСЮра пил МСГРП'!$V82*AI$13 -> 0 | AJ82: ='ГСЮра пил МСГРП'!$W82*AI$13 -> 0 | AK82: ='ГСЮра керн ГИС'!$V82*AK$13 -> 0 | AL82: ='ГСЮра керн ГИС'!$W82*AK$13 -> 0 | AM82: =Посл.скв.!$V82*AM$13 -> 0 | AN82: =Посл.скв.!$W82*AM$13 -> 0 | AO82: =AM82+AK82+AI82+AG82+AE82+AC82+AA82+Y82++W82+U82+S82+Q82+M82+O82+K82+I82+G82 -> 0 | AP82: =AN82+AL82+AJ82+AH82+AF82+AD82+AB82+Z82++X82+V82+T82+R82+N82+P82+L82+J82+H82 -> 0
D83: ='Перв. скв '!D83 -> 0 | E83: ='Перв. скв '!E83 -> ООО "Буровая компания "Евразия" | F83: ='Перв. скв '!F83 -> 0 | G83: ='Перв. скв '!$V83*G$13 -> 0 | H83: ='Перв. скв '!$W83*G$13 -> 0 | I83: ='2'!$V83*I$13 -> 0 | J83: ='2'!$W83*I$13 -> 0 | K83: ='3'!$V83*K$13 -> 0 | L83: ='3'!$W83*K$13 -> 0 | M83: ='4'!$V83*M$13 -> 0 | N83: ='4'!$W83*M$13 -> 0 | O83: ='5'!$V83*O$13 -> 0 | P83: ='5'!$W83*O$13 -> 0 | Q83: ='6'!$V83*Q$13 -> 0 | R83: ='6'!$W83*Q$13 -> 0 | S83: ='7'!$V83*S$13 -> 0 | T83: ='7'!$W83*S$13 -> 0 | U83: ='8'!$V83*U$13 -> 0 | V83: ='8'!$W83*U$13 -> 0 | W83: ='9'!$V83*W$13 -> 0 | X83: ='9'!$W83*W$13 -> 0 | Y83: =ВЗ!$V83*Y$13 -> 0 | Z83: =ВЗ!$W83*Y$13 -> 0 | AA83: ='ГС без пил 1000м гор'!$V83*AA$13 -> 0 | AB83: ='ГС без пил 1000м гор'!$W83*AA$13 -> 0 | AC83: ='ГС пил 1500м гор'!$V83*AC$13 -> 0 | AD83: ='ГС пил 1500м гор'!$W83*AC$13 -> 0 | AE83: ='ГС без пилот 1500м гор'!$V83*AE$13 -> 0 | AF83: ='ГС без пилот 1500м гор'!$W83*AE$13 -> 0 | AG83: ='ГСЮра без пил МГРП'!$V83*AG$13 -> 0 | AH83: ='ГСЮра без пил МГРП'!$W83*AG$13 -> 0 | AI83: ='ГСЮра пил МСГРП'!$V83*AI$13 -> 0 | AJ83: ='ГСЮра пил МСГРП'!$W83*AI$13 -> 0 | AK83: ='ГСЮра керн ГИС'!$V83*AK$13 -> 0 | AL83: ='ГСЮра керн ГИС'!$W83*AK$13 -> 0 | AM83: =Посл.скв.!$V83*AM$13 -> 0 | AN83: =Посл.скв.!$W83*AM$13 -> 0 | AO83: =AM83+AK83+AI83+AG83+AE83+AC83+AA83+Y83++W83+U83+S83+Q83+M83+O83+K83+I83+G83 -> 0 | AP83: =AN83+AL83+AJ83+AH83+AF83+AD83+AB83+Z83++X83+V83+T83+R83+N83+P83+L83+J83+H83 -> 0
D84: ='Перв. скв '!D84 -> 0 | E84: ='Перв. скв '!E84 -> ООО "Буровая компания "Евразия" | F84: ='Перв. скв '!F84 -> 0 | G84: ='Перв. скв '!$V84*G$13 -> 0 | H84: ='Перв. скв '!$W84*G$13 -> 0 | I84: ='2'!$V84*I$13 -> 0 | J84: ='2'!$W84*I$13 -> 0 | K84: ='3'!$V84*K$13 -> 0 | L84: ='3'!$W84*K$13 -> 0 | M84: ='4'!$V84*M$13 -> 0 | N84: ='4'!$W84*M$13 -> 0 | O84: ='5'!$V84*O$13 -> 0 | P84: ='5'!$W84*O$13 -> 0 | Q84: ='6'!$V84*Q$13 -> 0 | R84: ='6'!$W84*Q$13 -> 0 | S84: ='7'!$V84*S$13 -> 0 | T84: ='7'!$W84*S$13 -> 0 | U84: ='8'!$V84*U$13 -> 0 | V84: ='8'!$W84*U$13 -> 0 | W84: ='9'!$V84*W$13 -> 0 | X84: ='9'!$W84*W$13 -> 0 | Y84: =ВЗ!$V84*Y$13 -> 0 | Z84: =ВЗ!$W84*Y$13 -> 0 | AA84: ='ГС без пил 1000м гор'!$V84*AA$13 -> 0 | AB84: ='ГС без пил 1000м гор'!$W84*AA$13 -> 0 | AC84: ='ГС пил 1500м гор'!$V84*AC$13 -> 0 | AD84: ='ГС пил 1500м гор'!$W84*AC$13 -> 0 | AE84: ='ГС без пилот 1500м гор'!$V84*AE$13 -> 0 | AF84: ='ГС без пилот 1500м гор'!$W84*AE$13 -> 0 | AG84: ='ГСЮра без пил МГРП'!$V84*AG$13 -> 0 | AH84: ='ГСЮра без пил МГРП'!$W84*AG$13 -> 0 | AI84: ='ГСЮра пил МСГРП'!$V84*AI$13 -> 0 | AJ84: ='ГСЮра пил МСГРП'!$W84*AI$13 -> 0 | AK84: ='ГСЮра керн ГИС'!$V84*AK$13 -> 0 | AL84: ='ГСЮра керн ГИС'!$W84*AK$13 -> 0 | AM84: =Посл.скв.!$V84*AM$13 -> 0 | AN84: =Посл.скв.!$W84*AM$13 -> 0 | AO84: =AM84+AK84+AI84+AG84+AE84+AC84+AA84+Y84++W84+U84+S84+Q84+M84+O84+K84+I84+G84 -> 0 | AP84: =AN84+AL84+AJ84+AH84+AF84+AD84+AB84+Z84++X84+V84+T84+R84+N84+P84+L84+J84+H84 -> 0
D85: ='Перв. скв '!D85 -> 0 | E85: ='Перв. скв '!E85 -> ООО "Буровая компания "Евразия" | F85: ='Перв. скв '!F85 -> 0 | G85: ='Перв. скв '!$V85*G$13 -> 0 | H85: ='Перв. скв '!$W85*G$13 -> 0 | I85: ='2'!$V85*I$13 -> 0 | J85: ='2'!$W85*I$13 -> 0 | K85: ='3'!$V85*K$13 -> 0 | L85: ='3'!$W85*K$13 -> 0 | M85: ='4'!$V85*M$13 -> 0 | N85: ='4'!$W85*M$13 -> 0 | O85: ='5'!$V85*O$13 -> 0 | P85: ='5'!$W85*O$13 -> 0 | Q85: ='6'!$V85*Q$13 -> 0 | R85: ='6'!$W85*Q$13 -> 0 | S85: ='7'!$V85*S$13 -> 0 | T85: ='7'!$W85*S$13 -> 0 | U85: ='8'!$V85*U$13 -> 0 | V85: ='8'!$W85*U$13 -> 0 | W85: ='9'!$V85*W$13 -> 0 | X85: ='9'!$W85*W$13 -> 0 | Y85: =ВЗ!$V85*Y$13 -> 0 | Z85: =ВЗ!$W85*Y$13 -> 0 | AA85: ='ГС без пил 1000м гор'!$V85*AA$13 -> 0 | AB85: ='ГС без пил 1000м гор'!$W85*AA$13 -> 0 | AC85: ='ГС пил 1500м гор'!$V85*AC$13 -> 0 | AD85: ='ГС пил 1500м гор'!$W85*AC$13 -> 0 | AE85: ='ГС без пилот 1500м гор'!$V85*AE$13 -> 0 | AF85: ='ГС без пилот 1500м гор'!$W85*AE$13 -> 0 | AG85: ='ГСЮра без пил МГРП'!$V85*AG$13 -> 0 | AH85: ='ГСЮра без пил МГРП'!$W85*AG$13 -> 0 | AI85: ='ГСЮра пил МСГРП'!$V85*AI$13 -> 0 | AJ85: ='ГСЮра пил МСГРП'!$W85*AI$13 -> 0 | AK85: ='ГСЮра керн ГИС'!$V85*AK$13 -> 0 | AL85: ='ГСЮра керн ГИС'!$W85*AK$13 -> 0 | AM85: =Посл.скв.!$V85*AM$13 -> 0 | AN85: =Посл.скв.!$W85*AM$13 -> 0 | AO85: =AM85+AK85+AI85+AG85+AE85+AC85+AA85+Y85++W85+U85+S85+Q85+M85+O85+K85+I85+G85 -> 0 | AP85: =AN85+AL85+AJ85+AH85+AF85+AD85+AB85+Z85++X85+V85+T85+R85+N85+P85+L85+J85+H85 -> 0
... D102: ='Перв. скв '!D102 -> 0 | E102: ='Перв. скв '!E102 -> ООО "Буровая компания "Евразия" | F102: ='Перв. скв '!F102 -> 0 | G102: ='Перв. скв '!$V102*G$13 -> 0 | H102: ='Перв. скв '!$W102*G$13 -> 0 | I102: ='2'!$V102*I$13 -> 0 | J102: ='2'!$W102*I$13 -> 0 | K102: ='3'!$V102*K$13 -> 0 | L102: ='3'!$W102*K$13 -> 0 | M102: ='4'!$V102*M$13 -> 0 | N102: ='4'!$W102*M$13 -> 0 | O102: ='5'!$V102*O$13 -> 0 | P102: ='5'!$W102*O$13 -> 0 | Q102: ='6'!$V102*Q$13 -> 0 | R102: ='6'!$W102*Q$13 -> 0 | S102: ='7'!$V102*S$13 -> 0 | T102: ='7'!$W102*S$13 -> 0 | U102: ='8'!$V102*U$13 -> 0 | V102: ='8'!$W102*U$13 -> 0 | W102: ='9'!$V102*W$13 -> 0 | X102: ='9'!$W102*W$13 -> 0 | Y102: =ВЗ!$V102*Y$13 -> 0 | Z102: =ВЗ!$W102*Y$13 -> 0 | AA102: ='ГС без пил 1000м гор'!$V102*AA$13 -> 0 | AB102: ='ГС без пил 1000м гор'!$W102*AA$13 -> 0 | AC102: ='ГС пил 1500м гор'!$V102*AC$13 -> 0 | AD102: ='ГС пил 1500м гор'!$W102*AC$13 -> 0 | AE102: ='ГС без пилот 1500м гор'!$V102*AE$13 -> 0 | AF102: ='ГС без пилот 1500м гор'!$W102*AE$13 -> 0 | AG102: ='ГСЮра без пил МГРП'!$V102*AG$13 -> 0 | AH102: ='ГСЮра без пил МГРП'!$W102*AG$13 -> 0 | AI102: ='ГСЮра пил МСГРП'!$V102*AI$13 -> 0 | AJ102: ='ГСЮра пил МСГРП'!$W102*AI$13 -> 0 | AK102: ='ГСЮра керн ГИС'!$V102*AK$13 -> 0 | AL102: ='ГСЮра керн ГИС'!$W102*AK$13 -> 0 | AM102: =Посл.скв.!$V102*AM$13 -> 0 | AN102: =Посл.скв.!$W102*AM$13 -> 0 | AO102: =AM102+AK102+AI102+AG102+AE102+AC102+AA102+Y102++W102+U102+S102+Q102+M102+O102+K102+I102+G102 -> 0 | AP102: =AN102+AL102+AJ102+AH102+AF102+AD102+AB102+Z102++X102+V102+T102+R102+N102+P102+L102+J102+H102 -> 0
C103: ПОДРЯДЧИК ПО ДОЛОТАМ:
C104: ='Перв. скв '!C104 -> 0 | D104: Описание работ/услуг
C105: ='Перв. скв '!C105 -> Стоимость услуг по долотному сопровождению (долото + сервис) включая стоимость мобилизации и демобилизации | D105: ='Перв. скв '!D105 -> 550 мм долото для бурения под направление (долото+сервис) | E105: ='Перв. скв '!E105 -> 0 | F105: ='Перв. скв '!F105 -> м | G105: ='Перв. скв '!$V105*G$13 -> 0 | H105: ='Перв. скв '!$W105*G$13 -> 0 | I105: ='2'!$V105*I$13 -> 0 | J105: ='2'!$W105*I$13 -> 0 | K105: ='3'!$V105*K$13 -> 0 | L105: ='3'!$W105*K$13 -> 0 | M105: ='4'!$V105*M$13 -> 0 | N105: ='4'!$W105*M$13 -> 0 | O105: ='5'!$V105*O$13 -> 0 | P105: ='5'!$W105*O$13 -> 0 | Q105: ='6'!$V105*Q$13 -> 0 | R105: ='6'!$W105*Q$13 -> 0 | S105: ='7'!$V105*S$13 -> 0 | T105: ='7'!$W105*S$13 -> 0 | U105: ='8'!$V105*U$13 -> 0 | V105: ='8'!$W105*U$13 -> 0 | W105: ='9'!$V105*W$13 -> 0 | X105: ='9'!$W105*W$13 -> 0 | Y105: =ВЗ!$V105*Y$13 -> 0 | Z105: =ВЗ!$W105*Y$13 -> 0 | AA105: ='ГС без пил 1000м гор'!$V105*AA$13 -> 0 | AB105: ='ГС без пил 1000м гор'!$W105*AA$13 -> 0 | AC105: ='ГС пил 1500м гор'!$V105*AC$13 -> 0 | AD105: ='ГС пил 1500м гор'!$W105*AC$13 -> 0 | AE105: ='ГС без пилот 1500м гор'!$V105*AE$13 -> 0 | AF105: ='ГС без пилот 1500м гор'!$W105*AE$13 -> 0 | AG105: ='ГСЮра без пил МГРП'!$V105*AG$13 -> 0 | AH105: ='ГСЮра без пил МГРП'!$W105*AG$13 -> 0 | AI105: ='ГСЮра пил МСГРП'!$V105*AI$13 -> 0 | AJ105: ='ГСЮра пил МСГРП'!$W105*AI$13 -> 0 | AK105: ='ГСЮра керн ГИС'!$V105*AK$13 -> 0 | AL105: ='ГСЮра керн ГИС'!$W105*AK$13 -> 0 | AM105: =Посл.скв.!$V105*AM$13 -> 0 | AN105: =Посл.скв.!$W105*AM$13 -> 0 | AO105: =AM105+AK105+AI105+AG105+AE105+AC105+AA105+Y105++W105+U105+S105+Q105+M105+O105+K105+I105+G105 -> 0 | AP105: =AN105+AL105+AJ105+AH105+AF105+AD105+AB105+Z105++X105+V105+T105+R105+N105+P105+L105+J105+H105 -> 0
D106: ='Перв. скв '!D106 -> 393,7 мм долото для бурения под направление (долото+сервис) | E106: ='Перв. скв '!E106 -> 0 | F106: ='Перв. скв '!F106 -> м | G106: ='Перв. скв '!$V106*G$13 -> 100 | H106: ='Перв. скв '!$W106*G$13 -> 16857.323 | I106: ='2'!$V106*I$13 -> 0 | J106: ='2'!$W106*I$13 -> 0 | K106: ='3'!$V106*K$13 -> 0 | L106: ='3'!$W106*K$13 -> 0 | M106: ='4'!$V106*M$13 -> 0 | N106: ='4'!$W106*M$13 -> 0 | O106: ='5'!$V106*O$13 -> 0 | P106: ='5'!$W106*O$13 -> 0 | Q106: ='6'!$V106*Q$13 -> 0 | R106: ='6'!$W106*Q$13 -> 0 | S106: ='7'!$V106*S$13 -> 0 | T106: ='7'!$W106*S$13 -> 0 | U106: ='8'!$V106*U$13 -> 0 | V106: ='8'!$W106*U$13 -> 0 | W106: ='9'!$V106*W$13 -> 0 | X106: ='9'!$W106*W$13 -> 0 | Y106: =ВЗ!$V106*Y$13 -> 100 | Z106: =ВЗ!$W106*Y$13 -> 5332.1965 | AA106: ='ГС без пил 1000м гор'!$V106*AA$13 -> 400 | AB106: ='ГС без пил 1000м гор'!$W106*AA$13 -> 53698.43 | AC106: ='ГС пил 1500м гор'!$V106*AC$13 -> 0 | AD106: ='ГС пил 1500м гор'!$W106*AC$13 -> 0 | AE106: ='ГС без пилот 1500м гор'!$V106*AE$13 -> 300 | AF106: ='ГС без пилот 1500м гор'!$W106*AE$13 -> 44090.469 | AG106: ='ГСЮра без пил МГРП'!$V106*AG$13 -> 450 | AH106: ='ГСЮра без пил МГРП'!$W106*AG$13 -> 75857.955 | AI106: ='ГСЮра пил МСГРП'!$V106*AI$13 -> 200 | AJ106: ='ГСЮра пил МСГРП'!$W106*AI$13 -> 25276.474 | AK106: ='ГСЮра керн ГИС'!$V106*AK$13 -> 50 | AL106: ='ГСЮра керн ГИС'!$W106*AK$13 -> 4304.8077 | AM106: =Посл.скв.!$V106*AM$13 -> 0 | AN106: =Посл.скв.!$W106*AM$13 -> 0 | AO106: =AM106+AK106+AI106+AG106+AE106+AC106+AA106+Y106++W106+U106+S106+Q106+M106+O106+K106+I106+G106 -> 1600 | AP106: =AN106+AL106+AJ106+AH106+AF106+AD106+AB106+Z106++X106+V106+T106+R106+N106+P106+L106+J106+H106 -> 225417.66
D107: ='Перв. скв '!D107 -> 295,3 мм долото для бурения под кондуктор (долото+сервис) | E107: ='Перв. скв '!E107 -> 0 | F107: ='Перв. скв '!F107 -> м | G107: ='Перв. скв '!$V107*G$13 -> 3320 | H107: ='Перв. скв '!$W107*G$13 -> 559663.14 | I107: ='2'!$V107*I$13 -> 0 | J107: ='2'!$W107*I$13 -> 0 | K107: ='3'!$V107*K$13 -> 0 | L107: ='3'!$W107*K$13 -> 0 | M107: ='4'!$V107*M$13 -> 0 | N107: ='4'!$W107*M$13 -> 0 | O107: ='5'!$V107*O$13 -> 0 | P107: ='5'!$W107*O$13 -> 0 | Q107: ='6'!$V107*Q$13 -> 0 | R107: ='6'!$W107*Q$13 -> 0 | S107: ='7'!$V107*S$13 -> 0 | T107: ='7'!$W107*S$13 -> 0 | U107: ='8'!$V107*U$13 -> 0 | V107: ='8'!$W107*U$13 -> 0 | W107: ='9'!$V107*W$13 -> 0 | X107: ='9'!$W107*W$13 -> 0 | Y107: =ВЗ!$V107*Y$13 -> 3320 | Z107: =ВЗ!$W107*Y$13 -> 177028.92 | AA107: ='ГС без пил 1000м гор'!$V107*AA$13 -> 13280 | AB107: ='ГС без пил 1000м гор'!$W107*AA$13 -> 1782787.9 | AC107: ='ГС пил 1500м гор'!$V107*AC$13 -> 0 | AD107: ='ГС пил 1500м гор'!$W107*AC$13 -> 0 | AE107: ='ГС без пилот 1500м гор'!$V107*AE$13 -> 9960 | AF107: ='ГС без пилот 1500м гор'!$W107*AE$13 -> 1463803.6 | AG107: ='ГСЮра без пил МГРП'!$V107*AG$13 -> 14940 | AH107: ='ГСЮра без пил МГРП'!$W107*AG$13 -> 2518484.1 | AI107: ='ГСЮра пил МСГРП'!$V107*AI$13 -> 6640 | AJ107: ='ГСЮра пил МСГРП'!$W107*AI$13 -> 839178.93 | AK107: ='ГСЮра керн ГИС'!$V107*AK$13 -> 1660 | AL107: ='ГСЮра керн ГИС'!$W107*AK$13 -> 142919.62 | AM107: =Посл.скв.!$V107*AM$13 -> 0 | AN107: =Посл.скв.!$W107*AM$13 -> 0 | AO107: =AM107+AK107+AI107+AG107+AE107+AC107+AA107+Y107++W107+U107+S107+Q107+M107+O107+K107+I107+G107 -> 53120 | AP107: =AN107+AL107+AJ107+AH107+AF107+AD107+AB107+Z107++X107+V107+T107+R107+N107+P107+L107+J107+H107 -> 7483866.2
D108: ='Перв. скв '!D108 -> 220,7 мм долото для бурения эксплуатационную колонну (долото+сервис) | E108: ='Перв. скв '!E108 -> 0 | F108: ='Перв. скв '!F108 -> м | G108: ='Перв. скв '!$V108*G$13 -> 12800 | H108: ='Перв. скв '!$W108*G$13 -> 2157737.4 | I108: ='2'!$V108*I$13 -> 0 | J108: ='2'!$W108*I$13 -> 0 | K108: ='3'!$V108*K$13 -> 0 | L108: ='3'!$W108*K$13 -> 0 | M108: ='4'!$V108*M$13 -> 0 | N108: ='4'!$W108*M$13 -> 0 | O108: ='5'!$V108*O$13 -> 0 | P108: ='5'!$W108*O$13 -> 0 | Q108: ='6'!$V108*Q$13 -> 0 | R108: ='6'!$W108*Q$13 -> 0 | S108: ='7'!$V108*S$13 -> 0 | T108: ='7'!$W108*S$13 -> 0 | U108: ='8'!$V108*U$13 -> 0 | V108: ='8'!$W108*U$13 -> 0 | W108: ='9'!$V108*W$13 -> 0 | X108: ='9'!$W108*W$13 -> 0 | Y108: =ВЗ!$V108*Y$13 -> 14900 | Z108: =ВЗ!$W108*Y$13 -> 794497.28 | AA108: ='ГС без пил 1000м гор'!$V108*AA$13 -> 52800 | AB108: ='ГС без пил 1000м гор'!$W108*AA$13 -> 7088192.8 | AC108: ='ГС пил 1500м гор'!$V108*AC$13 -> 0 | AD108: ='ГС пил 1500м гор'!$W108*AC$13 -> 0 | AE108: ='ГС без пилот 1500м гор'!$V108*AE$13 -> 38400 | AF108: ='ГС без пилот 1500м гор'!$W108*AE$13 -> 5643580 | AG108: ='ГСЮра без пил МГРП'!$V108*AG$13 -> 59400 | AH108: ='ГСЮра без пил МГРП'!$W108*AG$13 -> 10013250 | AI108: ='ГСЮра пил МСГРП'!$V108*AI$13 -> 29800 | AJ108: ='ГСЮра пил МСГРП'!$W108*AI$13 -> 3766194.6 | AK108: ='ГСЮра керн ГИС'!$V108*AK$13 -> 7650 | AL108: ='ГСЮра керн ГИС'!$W108*AK$13 -> 658635.58 | AM108: =Посл.скв.!$V108*AM$13 -> 0 | AN108: =Посл.скв.!$W108*AM$13 -> 0 | AO108: =AM108+AK108+AI108+AG108+AE108+AC108+AA108+Y108++W108+U108+S108+Q108+M108+O108+K108+I108+G108 -> 215750 | AP108: =AN108+AL108+AJ108+AH108+AF108+AD108+AB108+Z108++X108+V108+T108+R108+N108+P108+L108+J108+H108 -> 30122088
D109: ='Перв. скв '!D109 -> _________ мм долото для бурения под хвостовик (долото+сервис) | E109: ='Перв. скв '!E109 -> 0 | F109: ='Перв. скв '!F109 -> м | G109: ='Перв. скв '!$V109*G$13 -> 0 | H109: ='Перв. скв '!$W109*G$13 -> 0 | I109: ='2'!$V109*I$13 -> 0 | J109: ='2'!$W109*I$13 -> 0 | K109: ='3'!$V109*K$13 -> 0 | L109: ='3'!$W109*K$13 -> 0 | M109: ='4'!$V109*M$13 -> 0 | N109: ='4'!$W109*M$13 -> 0 | O109: ='5'!$V109*O$13 -> 0 | P109: ='5'!$W109*O$13 -> 0 | Q109: ='6'!$V109*Q$13 -> 0 | R109: ='6'!$W109*Q$13 -> 0 | S109: ='7'!$V109*S$13 -> 0 | T109: ='7'!$W109*S$13 -> 0 | U109: ='8'!$V109*U$13 -> 0 | V109: ='8'!$W109*U$13 -> 0 | W109: ='9'!$V109*W$13 -> 0 | X109: ='9'!$W109*W$13 -> 0 | Y109: =ВЗ!$V109*Y$13 -> 0 | Z109: =ВЗ!$W109*Y$13 -> 0 | AA109: ='ГС без пил 1000м гор'!$V109*AA$13 -> 0 | AB109: ='ГС без пил 1000м гор'!$W109*AA$13 -> 0 | AC109: ='ГС пил 1500м гор'!$V109*AC$13 -> 0 | AD109: ='ГС пил 1500м гор'!$W109*AC$13 -> 0 | AE109: ='ГС без пилот 1500м гор'!$V109*AE$13 -> 0 | AF109: ='ГС без пилот 1500м гор'!$W109*AE$13 -> 0 | AG109: ='ГСЮра без пил МГРП'!$V109*AG$13 -> 0 | AH109: ='ГСЮра без пил МГРП'!$W109*AG$13 -> 0 | AI109: ='ГСЮра пил МСГРП'!$V109*AI$13 -> 0 | AJ109: ='ГСЮра пил МСГРП'!$W109*AI$13 -> 0 | AK109: ='ГСЮра керн ГИС'!$V109*AK$13 -> 0 | AL109: ='ГСЮра керн ГИС'!$W109*AK$13 -> 0 | AM109: =Посл.скв.!$V109*AM$13 -> 0 | AN109: =Посл.скв.!$W109*AM$13 -> 0 | AO109: =AM109+AK109+AI109+AG109+AE109+AC109+AA109+Y109++W109+U109+S109+Q109+M109+O109+K109+I109+G109 -> 0 | AP109: =AN109+AL109+AJ109+AH109+AF109+AD109+AB109+Z109++X109+V109+T109+R109+N109+P109+L109+J109+H109 -> 0
D110: ='Перв. скв '!D110 -> _________ мм долото для бурения (долото+сервис) | E110: ='Перв. скв '!E110 -> 0 | F110: ='Перв. скв '!F110 -> м | G110: ='Перв. скв '!$V110*G$13 -> 0 | H110: ='Перв. скв '!$W110*G$13 -> 0 | I110: ='2'!$V110*I$13 -> 0 | J110: ='2'!$W110*I$13 -> 0 | K110: ='3'!$V110*K$13 -> 0 | L110: ='3'!$W110*K$13 -> 0 | M110: ='4'!$V110*M$13 -> 0 | N110: ='4'!$W110*M$13 -> 0 | O110: ='5'!$V110*O$13 -> 0 | P110: ='5'!$W110*O$13 -> 0 | Q110: ='6'!$V110*Q$13 -> 0 | R110: ='6'!$W110*Q$13 -> 0 | S110: ='7'!$V110*S$13 -> 0 | T110: ='7'!$W110*S$13 -> 0 | U110: ='8'!$V110*U$13 -> 0 | V110: ='8'!$W110*U$13 -> 0 | W110: ='9'!$V110*W$13 -> 0 | X110: ='9'!$W110*W$13 -> 0 | Y110: =ВЗ!$V110*Y$13 -> 0 | Z110: =ВЗ!$W110*Y$13 -> 0 | AA110: ='ГС без пил 1000м гор'!$V110*AA$13 -> 0 | AB110: ='ГС без пил 1000м гор'!$W110*AA$13 -> 0 | AC110: ='ГС пил 1500м гор'!$V110*AC$13 -> 0 | AD110: ='ГС пил 1500м гор'!$W110*AC$13 -> 0 | AE110: ='ГС без пилот 1500м гор'!$V110*AE$13 -> 0 | AF110: ='ГС без пилот 1500м гор'!$W110*AE$13 -> 0 | AG110: ='ГСЮра без пил МГРП'!$V110*AG$13 -> 0 | AH110: ='ГСЮра без пил МГРП'!$W110*AG$13 -> 0 | AI110: ='ГСЮра пил МСГРП'!$V110*AI$13 -> 0 | AJ110: ='ГСЮра пил МСГРП'!$W110*AI$13 -> 0 | AK110: ='ГСЮра керн ГИС'!$V110*AK$13 -> 0 | AL110: ='ГСЮра керн ГИС'!$W110*AK$13 -> 0 | AM110: =Посл.скв.!$V110*AM$13 -> 0 | AN110: =Посл.скв.!$W110*AM$13 -> 0 | AO110: =AM110+AK110+AI110+AG110+AE110+AC110+AA110+Y110++W110+U110+S110+Q110+M110+O110+K110+I110+G110 -> 0 | AP110: =AN110+AL110+AJ110+AH110+AF110+AD110+AB110+Z110++X110+V110+T110+R110+N110+P110+L110+J110+H110 -> 0
D111: ='Перв. скв '!D111 -> Расширитель раздвижной | E111: ='Перв. скв '!E111 -> 0 | F111: ='Перв. скв '!F111 -> м | G111: ='Перв. скв '!$V111*G$13 -> 0 | H111: ='Перв. скв '!$W111*G$13 -> 0 | I111: ='2'!$V111*I$13 -> 0 | J111: ='2'!$W111*I$13 -> 0 | K111: ='3'!$V111*K$13 -> 0 | L111: ='3'!$W111*K$13 -> 0 | M111: ='4'!$V111*M$13 -> 0 | N111: ='4'!$W111*M$13 -> 0 | O111: ='5'!$V111*O$13 -> 0 | P111: ='5'!$W111*O$13 -> 0 | Q111: ='6'!$V111*Q$13 -> 0 | R111: ='6'!$W111*Q$13 -> 0 | S111: ='7'!$V111*S$13 -> 0 | T111: ='7'!$W111*S$13 -> 0 | U111: ='8'!$V111*U$13 -> 0 | V111: ='8'!$W111*U$13 -> 0 | W111: ='9'!$V111*W$13 -> 0 | X111: ='9'!$W111*W$13 -> 0 | Y111: =ВЗ!$V111*Y$13 -> 0 | Z111: =ВЗ!$W111*Y$13 -> 0 | AA111: ='ГС без пил 1000м гор'!$V111*AA$13 -> 0 | AB111: ='ГС без пил 1000м гор'!$W111*AA$13 -> 0 | AC111: ='ГС пил 1500м гор'!$V111*AC$13 -> 0 | AD111: ='ГС пил 1500м гор'!$W111*AC$13 -> 0 | AE111: ='ГС без пилот 1500м гор'!$V111*AE$13 -> 0 | AF111: ='ГС без пилот 1500м гор'!$W111*AE$13 -> 0 | AG111: ='ГСЮра без пил МГРП'!$V111*AG$13 -> 0 | AH111: ='ГСЮра без пил МГРП'!$W111*AG$13 -> 0 | AI111: ='ГСЮра пил МСГРП'!$V111*AI$13 -> 0 | AJ111: ='ГСЮра пил МСГРП'!$W111*AI$13 -> 0 | AK111: ='ГСЮра керн ГИС'!$V111*AK$13 -> 0 | AL111: ='ГСЮра керн ГИС'!$W111*AK$13 -> 0 | AM111: =Посл.скв.!$V111*AM$13 -> 0 | AN111: =Посл.скв.!$W111*AM$13 -> 0 | AO111: =AM111+AK111+AI111+AG111+AE111+AC111+AA111+Y111++W111+U111+S111+Q111+M111+O111+K111+I111+G111 -> 0 | AP111: =AN111+AL111+AJ111+AH111+AF111+AD111+AB111+Z111++X111+V111+T111+R111+N111+P111+L111+J111+H111 -> 0
D112: ='Перв. скв '!D112 -> 0 | E112: ='Перв. скв '!E112 -> 0 | F112: ='Перв. скв '!F112 -> 0 | G112: ='Перв. скв '!$V112*G$13 -> 0 | H112: ='Перв. скв '!$W112*G$13 -> 0 | I112: ='2'!$V112*I$13 -> 0 | J112: ='2'!$W112*I$13 -> 0 | K112: ='3'!$V112*K$13 -> 0 | L112: ='3'!$W112*K$13 -> 0 | M112: ='4'!$V112*M$13 -> 0 | N112: ='4'!$W112*M$13 -> 0 | O112: ='5'!$V112*O$13 -> 0 | P112: ='5'!$W112*O$13 -> 0 | Q112: ='6'!$V112*Q$13 -> 0 | R112: ='6'!$W112*Q$13 -> 0 | S112: ='7'!$V112*S$13 -> 0 | T112: ='7'!$W112*S$13 -> 0 | U112: ='8'!$V112*U$13 -> 0 | V112: ='8'!$W112*U$13 -> 0 | W112: ='9'!$V112*W$13 -> 0 | X112: ='9'!$W112*W$13 -> 0 | Y112: =ВЗ!$V112*Y$13 -> 0 | Z112: =ВЗ!$W112*Y$13 -> 0 | AA112: ='ГС без пил 1000м гор'!$V112*AA$13 -> 0 | AB112: ='ГС без пил 1000м гор'!$W112*AA$13 -> 0 | AC112: ='ГС пил 1500м гор'!$V112*AC$13 -> 0 | AD112: ='ГС пил 1500м гор'!$W112*AC$13 -> 0 | AE112: ='ГС без пилот 1500м гор'!$V112*AE$13 -> 0 | AF112: ='ГС без пилот 1500м гор'!$W112*AE$13 -> 0 | AG112: ='ГСЮра без пил МГРП'!$V112*AG$13 -> 0 | AH112: ='ГСЮра без пил МГРП'!$W112*AG$13 -> 0 | AI112: ='ГСЮра пил МСГРП'!$V112*AI$13 -> 0 | AJ112: ='ГСЮра пил МСГРП'!$W112*AI$13 -> 0 | AK112: ='ГСЮра керн ГИС'!$V112*AK$13 -> 0 | AL112: ='ГСЮра керн ГИС'!$W112*AK$13 -> 0 | AM112: =Посл.скв.!$V112*AM$13 -> 0 | AN112: =Посл.скв.!$W112*AM$13 -> 0 | AO112: =AM112+AK112+AI112+AG112+AE112+AC112+AA112+Y112++W112+U112+S112+Q112+M112+O112+K112+I112+G112 -> 0 | AP112: =AN112+AL112+AJ112+AH112+AF112+AD112+AB112+Z112++X112+V112+T112+R112+N112+P112+L112+J112+H112 -> 0
D113: ='Перв. скв '!D113 -> 0 | E113: ='Перв. скв '!E113 -> 0 | F113: ='Перв. скв '!F113 -> 0 | G113: ='Перв. скв '!$V113*G$13 -> 0 | H113: ='Перв. скв '!$W113*G$13 -> 0 | I113: ='2'!$V113*I$13 -> 0 | J113: ='2'!$W113*I$13 -> 0 | K113: ='3'!$V113*K$13 -> 0 | L113: ='3'!$W113*K$13 -> 0 | M113: ='4'!$V113*M$13 -> 0 | N113: ='4'!$W113*M$13 -> 0 | O113: ='5'!$V113*O$13 -> 0 | P113: ='5'!$W113*O$13 -> 0 | Q113: ='6'!$V113*Q$13 -> 0 | R113: ='6'!$W113*Q$13 -> 0 | S113: ='7'!$V113*S$13 -> 0 | T113: ='7'!$W113*S$13 -> 0 | U113: ='8'!$V113*U$13 -> 0 | V113: ='8'!$W113*U$13 -> 0 | W113: ='9'!$V113*W$13 -> 0 | X113: ='9'!$W113*W$13 -> 0 | Y113: =ВЗ!$V113*Y$13 -> 0 | Z113: =ВЗ!$W113*Y$13 -> 0 | AA113: ='ГС без пил 1000м гор'!$V113*AA$13 -> 0 | AB113: ='ГС без пил 1000м гор'!$W113*AA$13 -> 0 | AC113: ='ГС пил 1500м гор'!$V113*AC$13 -> 0 | AD113: ='ГС пил 1500м гор'!$W113*AC$13 -> 0 | AE113: ='ГС без пилот 1500м гор'!$V113*AE$13 -> 0 | AF113: ='ГС без пилот 1500м гор'!$W113*AE$13 -> 0 | AG113: ='ГСЮра без пил МГРП'!$V113*AG$13 -> 0 | AH113: ='ГСЮра без пил МГРП'!$W113*AG$13 -> 0 | AI113: ='ГСЮра пил МСГРП'!$V113*AI$13 -> 0 | AJ113: ='ГСЮра пил МСГРП'!$W113*AI$13 -> 0 | AK113: ='ГСЮра керн ГИС'!$V113*AK$13 -> 0 | AL113: ='ГСЮра керн ГИС'!$W113*AK$13 -> 0 | AM113: =Посл.скв.!$V113*AM$13 -> 0 | AN113: =Посл.скв.!$W113*AM$13 -> 0 | AO113: =AM113+AK113+AI113+AG113+AE113+AC113+AA113+Y113++W113+U113+S113+Q113+M113+O113+K113+I113+G113 -> 0 | AP113: =AN113+AL113+AJ113+AH113+AF113+AD113+AB113+Z113++X113+V113+T113+R113+N113+P113+L113+J113+H113 -> 0
D114: ='Перв. скв '!D114 -> 0 | E114: ='Перв. скв '!E114 -> 0 | F114: ='Перв. скв '!F114 -> 0 | G114: ='Перв. скв '!$V114*G$13 -> 0 | H114: ='Перв. скв '!$W114*G$13 -> 0 | I114: ='2'!$V114*I$13 -> 0 | J114: ='2'!$W114*I$13 -> 0 | K114: ='3'!$V114*K$13 -> 0 | L114: ='3'!$W114*K$13 -> 0 | M114: ='4'!$V114*M$13 -> 0 | N114: ='4'!$W114*M$13 -> 0 | O114: ='5'!$V114*O$13 -> 0 | P114: ='5'!$W114*O$13 -> 0 | Q114: ='6'!$V114*Q$13 -> 0 | R114: ='6'!$W114*Q$13 -> 0 | S114: ='7'!$V114*S$13 -> 0 | T114: ='7'!$W114*S$13 -> 0 | U114: ='8'!$V114*U$13 -> 0 | V114: ='8'!$W114*U$13 -> 0 | W114: ='9'!$V114*W$13 -> 0 | X114: ='9'!$W114*W$13 -> 0 | Y114: =ВЗ!$V114*Y$13 -> 0 | Z114: =ВЗ!$W114*Y$13 -> 0 | AA114: ='ГС без пил 1000м гор'!$V114*AA$13 -> 0 | AB114: ='ГС без пил 1000м гор'!$W114*AA$13 -> 0 | AC114: ='ГС пил 1500м гор'!$V114*AC$13 -> 0 | AD114: ='ГС пил 1500м гор'!$W114*AC$13 -> 0 | AE114: ='ГС без пилот 1500м гор'!$V114*AE$13 -> 0 | AF114: ='ГС без пилот 1500м гор'!$W114*AE$13 -> 0 | AG114: ='ГСЮра без пил МГРП'!$V114*AG$13 -> 0 | AH114: ='ГСЮра без пил МГРП'!$W114*AG$13 -> 0 | AI114: ='ГСЮра пил МСГРП'!$V114*AI$13 -> 0 | AJ114: ='ГСЮра пил МСГРП'!$W114*AI$13 -> 0 | AK114: ='ГСЮра керн ГИС'!$V114*AK$13 -> 0 | AL114: ='ГСЮра керн ГИС'!$W114*AK$13 -> 0 | AM114: =Посл.скв.!$V114*AM$13 -> 0 | AN114: =Посл.скв.!$W114*AM$13 -> 0 | AO114: =AM114+AK114+AI114+AG114+AE114+AC114+AA114+Y114++W114+U114+S114+Q114+M114+O114+K114+I114+G114 -> 0 | AP114: =AN114+AL114+AJ114+AH114+AF114+AD114+AB114+Z114++X114+V114+T114+R114+N114+P114+L114+J114+H114 -> 0
D115: ='Перв. скв '!D115 -> 0 | E115: ='Перв. скв '!E115 -> 0 | F115: ='Перв. скв '!F115 -> 0 | G115: ='Перв. скв '!$V115*G$13 -> 0 | H115: ='Перв. скв '!$W115*G$13 -> 0 | I115: ='2'!$V115*I$13 -> 0 | J115: ='2'!$W115*I$13 -> 0 | K115: ='3'!$V115*K$13 -> 0 | L115: ='3'!$W115*K$13 -> 0 | M115: ='4'!$V115*M$13 -> 0 | N115: ='4'!$W115*M$13 -> 0 | O115: ='5'!$V115*O$13 -> 0 | P115: ='5'!$W115*O$13 -> 0 | Q115: ='6'!$V115*Q$13 -> 0 | R115: ='6'!$W115*Q$13 -> 0 | S115: ='7'!$V115*S$13 -> 0 | T115: ='7'!$W115*S$13 -> 0 | U115: ='8'!$V115*U$13 -> 0 | V115: ='8'!$W115*U$13 -> 0 | W115: ='9'!$V115*W$13 -> 0 | X115: ='9'!$W115*W$13 -> 0 | Y115: =ВЗ!$V115*Y$13 -> 0 | Z115: =ВЗ!$W115*Y$13 -> 0 | AA115: ='ГС без пил 1000м гор'!$V115*AA$13 -> 0 | AB115: ='ГС без пил 1000м гор'!$W115*AA$13 -> 0 | AC115: ='ГС пил 1500м гор'!$V115*AC$13 -> 0 | AD115: ='ГС пил 1500м гор'!$W115*AC$13 -> 0 | AE115: ='ГС без пилот 1500м гор'!$V115*AE$13 -> 0 | AF115: ='ГС без пилот 1500м гор'!$W115*AE$13 -> 0 | AG115: ='ГСЮра без пил МГРП'!$V115*AG$13 -> 0 | AH115: ='ГСЮра без пил МГРП'!$W115*AG$13 -> 0 | AI115: ='ГСЮра пил МСГРП'!$V115*AI$13 -> 0 | AJ115: ='ГСЮра пил МСГРП'!$W115*AI$13 -> 0 | AK115: ='ГСЮра керн ГИС'!$V115*AK$13 -> 0 | AL115: ='ГСЮра керн ГИС'!$W115*AK$13 -> 0 | AM115: =Посл.скв.!$V115*AM$13 -> 0 | AN115: =Посл.скв.!$W115*AM$13 -> 0 | AO115: =AM115+AK115+AI115+AG115+AE115+AC115+AA115+Y115++W115+U115+S115+Q115+M115+O115+K115+I115+G115 -> 0 | AP115: =AN115+AL115+AJ115+AH115+AF115+AD115+AB115+Z115++X115+V115+T115+R115+N115+P115+L115+J115+H115 -> 0
D116: ='Перв. скв '!D116 -> 0 | E116: ='Перв. скв '!E116 -> 0 | F116: ='Перв. скв '!F116 -> 0 | G116: ='Перв. скв '!$V116*G$13 -> 0 | H116: ='Перв. скв '!$W116*G$13 -> 0 | I116: ='2'!$V116*I$13 -> 0 | J116: ='2'!$W116*I$13 -> 0 | K116: ='3'!$V116*K$13 -> 0 | L116: ='3'!$W116*K$13 -> 0 | M116: ='4'!$V116*M$13 -> 0 | N116: ='4'!$W116*M$13 -> 0 | O116: ='5'!$V116*O$13 -> 0 | P116: ='5'!$W116*O$13 -> 0 | Q116: ='6'!$V116*Q$13 -> 0 | R116: ='6'!$W116*Q$13 -> 0 | S116: ='7'!$V116*S$13 -> 0 | T116: ='7'!$W116*S$13 -> 0 | U116: ='8'!$V116*U$13 -> 0 | V116: ='8'!$W116*U$13 -> 0 | W116: ='9'!$V116*W$13 -> 0 | X116: ='9'!$W116*W$13 -> 0 | Y116: =ВЗ!$V116*Y$13 -> 0 | Z116: =ВЗ!$W116*Y$13 -> 0 | AA116: ='ГС без пил 1000м гор'!$V116*AA$13 -> 0 | AB116: ='ГС без пил 1000м гор'!$W116*AA$13 -> 0 | AC116: ='ГС пил 1500м гор'!$V116*AC$13 -> 0 | AD116: ='ГС пил 1500м гор'!$W116*AC$13 -> 0 | AE116: ='ГС без пилот 1500м гор'!$V116*AE$13 -> 0 | AF116: ='ГС без пилот 1500м гор'!$W116*AE$13 -> 0 | AG116: ='ГСЮра без пил МГРП'!$V116*AG$13 -> 0 | AH116: ='ГСЮра без пил МГРП'!$W116*AG$13 -> 0 | AI116: ='ГСЮра пил МСГРП'!$V116*AI$13 -> 0 | AJ116: ='ГСЮра пил МСГРП'!$W116*AI$13 -> 0 | AK116: ='ГСЮра керн ГИС'!$V116*AK$13 -> 0 | AL116: ='ГСЮра керн ГИС'!$W116*AK$13 -> 0 | AM116: =Посл.скв.!$V116*AM$13 -> 0 | AN116: =Посл.скв.!$W116*AM$13 -> 0 | AO116: =AM116+AK116+AI116+AG116+AE116+AC116+AA116+Y116++W116+U116+S116+Q116+M116+O116+K116+I116+G116 -> 0 | AP116: =AN116+AL116+AJ116+AH116+AF116+AD116+AB116+Z116++X116+V116+T116+R116+N116+P116+L116+J116+H116 -> 0
D117: ='Перв. скв '!D117 -> 0 | E117: ='Перв. скв '!E117 -> 0 | F117: ='Перв. скв '!F117 -> 0 | G117: ='Перв. скв '!$V117*G$13 -> 0 | H117: ='Перв. скв '!$W117*G$13 -> 0 | I117: ='2'!$V117*I$13 -> 0 | J117: ='2'!$W117*I$13 -> 0 | K117: ='3'!$V117*K$13 -> 0 | L117: ='3'!$W117*K$13 -> 0 | M117: ='4'!$V117*M$13 -> 0 | N117: ='4'!$W117*M$13 -> 0 | O117: ='5'!$V117*O$13 -> 0 | P117: ='5'!$W117*O$13 -> 0 | Q117: ='6'!$V117*Q$13 -> 0 | R117: ='6'!$W117*Q$13 -> 0 | S117: ='7'!$V117*S$13 -> 0 | T117: ='7'!$W117*S$13 -> 0 | U117: ='8'!$V117*U$13 -> 0 | V117: ='8'!$W117*U$13 -> 0 | W117: ='9'!$V117*W$13 -> 0 | X117: ='9'!$W117*W$13 -> 0 | Y117: =ВЗ!$V117*Y$13 -> 0 | Z117: =ВЗ!$W117*Y$13 -> 0 | AA117: ='ГС без пил 1000м гор'!$V117*AA$13 -> 0 | AB117: ='ГС без пил 1000м гор'!$W117*AA$13 -> 0 | AC117: ='ГС пил 1500м гор'!$V117*AC$13 -> 0 | AD117: ='ГС пил 1500м гор'!$W117*AC$13 -> 0 | AE117: ='ГС без пилот 1500м гор'!$V117*AE$13 -> 0 | AF117: ='ГС без пилот 1500м гор'!$W117*AE$13 -> 0 | AG117: ='ГСЮра без пил МГРП'!$V117*AG$13 -> 0 | AH117: ='ГСЮра без пил МГРП'!$W117*AG$13 -> 0 | AI117: ='ГСЮра пил МСГРП'!$V117*AI$13 -> 0 | AJ117: ='ГСЮра пил МСГРП'!$W117*AI$13 -> 0 | AK117: ='ГСЮра керн ГИС'!$V117*AK$13 -> 0 | AL117: ='ГСЮра керн ГИС'!$W117*AK$13 -> 0 | AM117: =Посл.скв.!$V117*AM$13 -> 0 | AN117: =Посл.скв.!$W117*AM$13 -> 0 | AO117: =AM117+AK117+AI117+AG117+AE117+AC117+AA117+Y117++W117+U117+S117+Q117+M117+O117+K117+I117+G117 -> 0 | AP117: =AN117+AL117+AJ117+AH117+AF117+AD117+AB117+Z117++X117+V117+T117+R117+N117+P117+L117+J117+H117 -> 0
... D119: ='Перв. скв '!D119 -> 0 | E119: ='Перв. скв '!E119 -> 0 | F119: ='Перв. скв '!F119 -> 0 | G119: ='Перв. скв '!$V119*G$13 -> 0 | H119: ='Перв. скв '!$W119*G$13 -> 0 | I119: ='2'!$V119*I$13 -> 0 | J119: ='2'!$W119*I$13 -> 0 | K119: ='3'!$V119*K$13 -> 0 | L119: ='3'!$W119*K$13 -> 0 | M119: ='4'!$V119*M$13 -> 0 | N119: ='4'!$W119*M$13 -> 0 | O119: ='5'!$V119*O$13 -> 0 | P119: ='5'!$W119*O$13 -> 0 | Q119: ='6'!$V119*Q$13 -> 0 | R119: ='6'!$W119*Q$13 -> 0 | S119: ='7'!$V119*S$13 -> 0 | T119: ='7'!$W119*S$13 -> 0 | U119: ='8'!$V119*U$13 -> 0 | V119: ='8'!$W119*U$13 -> 0 | W119: ='9'!$V119*W$13 -> 0 | X119: ='9'!$W119*W$13 -> 0 | Y119: =ВЗ!$V119*Y$13 -> 0 | Z119: =ВЗ!$W119*Y$13 -> 0 | AA119: ='ГС без пил 1000м гор'!$V119*AA$13 -> 0 | AB119: ='ГС без пил 1000м гор'!$W119*AA$13 -> 0 | AC119: ='ГС пил 1500м гор'!$V119*AC$13 -> 0 | AD119: ='ГС пил 1500м гор'!$W119*AC$13 -> 0 | AE119: ='ГС без пилот 1500м гор'!$V119*AE$13 -> 0 | AF119: ='ГС без пилот 1500м гор'!$W119*AE$13 -> 0 | AG119: ='ГСЮра без пил МГРП'!$V119*AG$13 -> 0 | AH119: ='ГСЮра без пил МГРП'!$W119*AG$13 -> 0 | AI119: ='ГСЮра пил МСГРП'!$V119*AI$13 -> 0 | AJ119: ='ГСЮра пил МСГРП'!$W119*AI$13 -> 0 | AK119: ='ГСЮра керн ГИС'!$V119*AK$13 -> 0 | AL119: ='ГСЮра керн ГИС'!$W119*AK$13 -> 0 | AM119: =Посл.скв.!$V119*AM$13 -> 0 | AN119: =Посл.скв.!$W119*AM$13 -> 0 | AO119: =AM119+AK119+AI119+AG119+AE119+AC119+AA119+Y119++W119+U119+S119+Q119+M119+O119+K119+I119+G119 -> 0 | AP119: =AN119+AL119+AJ119+AH119+AF119+AD119+AB119+Z119++X119+V119+T119+R119+N119+P119+L119+J119+H119 -> 0
C120: ПОДРЯДЧИК ПО ТЕХНОЛОГИЧЕСКОМУ И ТЕЛЕМЕТРИЧЕСКОМУ СОПРОВОЖДЕНИЮ:
C121: ='Перв. скв '!C121 -> 0 | D121: Описание работ/услуг
C122: ='Перв. скв '!C122 -> Услуги направленного бурения и телеметрии (включая ГЗД) - стоимость аренды оборудования и услуг соответствующего персонала для направленного бурения, услуги ГИС/измерений во время бурения (MWD, LWD и услуги персонала) | D122: ='Перв. скв '!D122 -> Ставка работы по ННБ для секции скважин диаметром 393,7 мм. | E122: ='Перв. скв '!E122 -> 0 | F122: ='Перв. скв '!F122 -> сут | G122: ='Перв. скв '!$V122*G$13 -> 4 | H122: ='Перв. скв '!$W122*G$13 -> 1296000 | I122: ='2'!$V122*I$13 -> 0 | J122: ='2'!$W122*I$13 -> 0 | K122: ='3'!$V122*K$13 -> 0 | L122: ='3'!$W122*K$13 -> 0 | M122: ='4'!$V122*M$13 -> 0 | N122: ='4'!$W122*M$13 -> 0 | O122: ='5'!$V122*O$13 -> 0 | P122: ='5'!$W122*O$13 -> 0 | Q122: ='6'!$V122*Q$13 -> 0 | R122: ='6'!$W122*Q$13 -> 0 | S122: ='7'!$V122*S$13 -> 0 | T122: ='7'!$W122*S$13 -> 0 | U122: ='8'!$V122*U$13 -> 0 | V122: ='8'!$W122*U$13 -> 0 | W122: ='9'!$V122*W$13 -> 0 | X122: ='9'!$W122*W$13 -> 0 | Y122: =ВЗ!$V122*Y$13 -> 4 | Z122: =ВЗ!$W122*Y$13 -> 1296000 | AA122: ='ГС без пил 1000м гор'!$V122*AA$13 -> 16 | AB122: ='ГС без пил 1000м гор'!$W122*AA$13 -> 5184000 | AC122: ='ГС пил 1500м гор'!$V122*AC$13 -> 0 | AD122: ='ГС пил 1500м гор'!$W122*AC$13 -> 0 | AE122: ='ГС без пилот 1500м гор'!$V122*AE$13 -> 12 | AF122: ='ГС без пилот 1500м гор'!$W122*AE$13 -> 3888000 | AG122: ='ГСЮра без пил МГРП'!$V122*AG$13 -> 18 | AH122: ='ГСЮра без пил МГРП'!$W122*AG$13 -> 5832000 | AI122: ='ГСЮра пил МСГРП'!$V122*AI$13 -> 8 | AJ122: ='ГСЮра пил МСГРП'!$W122*AI$13 -> 2592000 | AK122: ='ГСЮра керн ГИС'!$V122*AK$13 -> 2 | AL122: ='ГСЮра керн ГИС'!$W122*AK$13 -> 648000 | AM122: =Посл.скв.!$V122*AM$13 -> 0 | AN122: =Посл.скв.!$W122*AM$13 -> 0 | AO122: =AM122+AK122+AI122+AG122+AE122+AC122+AA122+Y122++W122+U122+S122+Q122+M122+O122+K122+I122+G122 -> 64 | AP122: =AN122+AL122+AJ122+AH122+AF122+AD122+AB122+Z122++X122+V122+T122+R122+N122+P122+L122+J122+H122 -> 20736000
D123: ='Перв. скв '!D123 -> Резервная ставка по ННБ для секций скважин диаметром 393,7 мм. | E123: ='Перв. скв '!E123 -> 0 | F123: ='Перв. скв '!F123 -> сут | G123: ='Перв. скв '!$V123*G$13 -> 0 | H123: ='Перв. скв '!$W123*G$13 -> 0 | I123: ='2'!$V123*I$13 -> 0 | J123: ='2'!$W123*I$13 -> 0 | K123: ='3'!$V123*K$13 -> 0 | L123: ='3'!$W123*K$13 -> 0 | M123: ='4'!$V123*M$13 -> 0 | N123: ='4'!$W123*M$13 -> 0 | O123: ='5'!$V123*O$13 -> 0 | P123: ='5'!$W123*O$13 -> 0 | Q123: ='6'!$V123*Q$13 -> 0 | R123: ='6'!$W123*Q$13 -> 0 | S123: ='7'!$V123*S$13 -> 0 | T123: ='7'!$W123*S$13 -> 0 | U123: ='8'!$V123*U$13 -> 0 | V123: ='8'!$W123*U$13 -> 0 | W123: ='9'!$V123*W$13 -> 0 | X123: ='9'!$W123*W$13 -> 0 | Y123: =ВЗ!$V123*Y$13 -> 0 | Z123: =ВЗ!$W123*Y$13 -> 0 | AA123: ='ГС без пил 1000м гор'!$V123*AA$13 -> 0 | AB123: ='ГС без пил 1000м гор'!$W123*AA$13 -> 0 | AC123: ='ГС пил 1500м гор'!$V123*AC$13 -> 0 | AD123: ='ГС пил 1500м гор'!$W123*AC$13 -> 0 | AE123: ='ГС без пилот 1500м гор'!$V123*AE$13 -> 0 | AF123: ='ГС без пилот 1500м гор'!$W123*AE$13 -> 0 | AG123: ='ГСЮра без пил МГРП'!$V123*AG$13 -> 0 | AH123: ='ГСЮра без пил МГРП'!$W123*AG$13 -> 0 | AI123: ='ГСЮра пил МСГРП'!$V123*AI$13 -> 0 | AJ123: ='ГСЮра пил МСГРП'!$W123*AI$13 -> 0 | AK123: ='ГСЮра керн ГИС'!$V123*AK$13 -> 0 | AL123: ='ГСЮра керн ГИС'!$W123*AK$13 -> 0 | AM123: =Посл.скв.!$V123*AM$13 -> 0 | AN123: =Посл.скв.!$W123*AM$13 -> 0 | AO123: =AM123+AK123+AI123+AG123+AE123+AC123+AA123+Y123++W123+U123+S123+Q123+M123+O123+K123+I123+G123 -> 0 | AP123: =AN123+AL123+AJ123+AH123+AF123+AD123+AB123+Z123++X123+V123+T123+R123+N123+P123+L123+J123+H123 -> 0
D124: ='Перв. скв '!D124 -> Ставка работы по ННБ для секции скважин диаметром 295,3 мм. | E124: ='Перв. скв '!E124 -> 0 | F124: ='Перв. скв '!F124 -> сут | G124: ='Перв. скв '!$V124*G$13 -> 5.66 | H124: ='Перв. скв '!$W124*G$13 -> 1896100 | I124: ='2'!$V124*I$13 -> 0 | J124: ='2'!$W124*I$13 -> 0 | K124: ='3'!$V124*K$13 -> 0 | L124: ='3'!$W124*K$13 -> 0 | M124: ='4'!$V124*M$13 -> 0 | N124: ='4'!$W124*M$13 -> 0 | O124: ='5'!$V124*O$13 -> 0 | P124: ='5'!$W124*O$13 -> 0 | Q124: ='6'!$V124*Q$13 -> 0 | R124: ='6'!$W124*Q$13 -> 0 | S124: ='7'!$V124*S$13 -> 0 | T124: ='7'!$W124*S$13 -> 0 | U124: ='8'!$V124*U$13 -> 0 | V124: ='8'!$W124*U$13 -> 0 | W124: ='9'!$V124*W$13 -> 0 | X124: ='9'!$W124*W$13 -> 0 | Y124: =ВЗ!$V124*Y$13 -> 5.66 | Z124: =ВЗ!$W124*Y$13 -> 1896100 | AA124: ='ГС без пил 1000м гор'!$V124*AA$13 -> 22.64 | AB124: ='ГС без пил 1000м гор'!$W124*AA$13 -> 7584400 | AC124: ='ГС пил 1500м гор'!$V124*AC$13 -> 0 | AD124: ='ГС пил 1500м гор'!$W124*AC$13 -> 0 | AE124: ='ГС без пилот 1500м гор'!$V124*AE$13 -> 16.98 | AF124: ='ГС без пилот 1500м гор'!$W124*AE$13 -> 5688300 | AG124: ='ГСЮра без пил МГРП'!$V124*AG$13 -> 25.47 | AH124: ='ГСЮра без пил МГРП'!$W124*AG$13 -> 8532450 | AI124: ='ГСЮра пил МСГРП'!$V124*AI$13 -> 11.32 | AJ124: ='ГСЮра пил МСГРП'!$W124*AI$13 -> 3792200 | AK124: ='ГСЮра керн ГИС'!$V124*AK$13 -> 2.83 | AL124: ='ГСЮра керн ГИС'!$W124*AK$13 -> 948050 | AM124: =Посл.скв.!$V124*AM$13 -> 0 | AN124: =Посл.скв.!$W124*AM$13 -> 0 | AO124: =AM124+AK124+AI124+AG124+AE124+AC124+AA124+Y124++W124+U124+S124+Q124+M124+O124+K124+I124+G124 -> 90.56 | AP124: =AN124+AL124+AJ124+AH124+AF124+AD124+AB124+Z124++X124+V124+T124+R124+N124+P124+L124+J124+H124 -> 30337600
D125: ='Перв. скв '!D125 -> Резервная ставка по ННБ для секций скважин диаметром 295,3 мм. | E125: ='Перв. скв '!E125 -> 0 | F125: ='Перв. скв '!F125 -> сут | G125: ='Перв. скв '!$V125*G$13 -> 0 | H125: ='Перв. скв '!$W125*G$13 -> 0 | I125: ='2'!$V125*I$13 -> 0 | J125: ='2'!$W125*I$13 -> 0 | K125: ='3'!$V125*K$13 -> 0 | L125: ='3'!$W125*K$13 -> 0 | M125: ='4'!$V125*M$13 -> 0 | N125: ='4'!$W125*M$13 -> 0 | O125: ='5'!$V125*O$13 -> 0 | P125: ='5'!$W125*O$13 -> 0 | Q125: ='6'!$V125*Q$13 -> 0 | R125: ='6'!$W125*Q$13 -> 0 | S125: ='7'!$V125*S$13 -> 0 | T125: ='7'!$W125*S$13 -> 0 | U125: ='8'!$V125*U$13 -> 0 | V125: ='8'!$W125*U$13 -> 0 | W125: ='9'!$V125*W$13 -> 0 | X125: ='9'!$W125*W$13 -> 0 | Y125: =ВЗ!$V125*Y$13 -> 0 | Z125: =ВЗ!$W125*Y$13 -> 0 | AA125: ='ГС без пил 1000м гор'!$V125*AA$13 -> 0 | AB125: ='ГС без пил 1000м гор'!$W125*AA$13 -> 0 | AC125: ='ГС пил 1500м гор'!$V125*AC$13 -> 0 | AD125: ='ГС пил 1500м гор'!$W125*AC$13 -> 0 | AE125: ='ГС без пилот 1500м гор'!$V125*AE$13 -> 0 | AF125: ='ГС без пилот 1500м гор'!$W125*AE$13 -> 0 | AG125: ='ГСЮра без пил МГРП'!$V125*AG$13 -> 0 | AH125: ='ГСЮра без пил МГРП'!$W125*AG$13 -> 0 | AI125: ='ГСЮра пил МСГРП'!$V125*AI$13 -> 0 | AJ125: ='ГСЮра пил МСГРП'!$W125*AI$13 -> 0 | AK125: ='ГСЮра керн ГИС'!$V125*AK$13 -> 0 | AL125: ='ГСЮра керн ГИС'!$W125*AK$13 -> 0 | AM125: =Посл.скв.!$V125*AM$13 -> 0 | AN125: =Посл.скв.!$W125*AM$13 -> 0 | AO125: =AM125+AK125+AI125+AG125+AE125+AC125+AA125+Y125++W125+U125+S125+Q125+M125+O125+K125+I125+G125 -> 0 | AP125: =AN125+AL125+AJ125+AH125+AF125+AD125+AB125+Z125++X125+V125+T125+R125+N125+P125+L125+J125+H125 -> 0
D126: ='Перв. скв '!D126 -> Ставка работы по ННБ для секции скважин диаметром 220,7 мм. | E126: ='Перв. скв '!E126 -> 0 | F126: ='Перв. скв '!F126 -> сут | G126: ='Перв. скв '!$V126*G$13 -> 0 | H126: ='Перв. скв '!$W126*G$13 -> 0 | I126: ='2'!$V126*I$13 -> 0 | J126: ='2'!$W126*I$13 -> 0 | K126: ='3'!$V126*K$13 -> 0 | L126: ='3'!$W126*K$13 -> 0 | M126: ='4'!$V126*M$13 -> 0 | N126: ='4'!$W126*M$13 -> 0 | O126: ='5'!$V126*O$13 -> 0 | P126: ='5'!$W126*O$13 -> 0 | Q126: ='6'!$V126*Q$13 -> 0 | R126: ='6'!$W126*Q$13 -> 0 | S126: ='7'!$V126*S$13 -> 0 | T126: ='7'!$W126*S$13 -> 0 | U126: ='8'!$V126*U$13 -> 0 | V126: ='8'!$W126*U$13 -> 0 | W126: ='9'!$V126*W$13 -> 0 | X126: ='9'!$W126*W$13 -> 0 | Y126: =ВЗ!$V126*Y$13 -> 0 | Z126: =ВЗ!$W126*Y$13 -> 0 | AA126: ='ГС без пил 1000м гор'!$V126*AA$13 -> 0 | AB126: ='ГС без пил 1000м гор'!$W126*AA$13 -> 0 | AC126: ='ГС пил 1500м гор'!$V126*AC$13 -> 0 | AD126: ='ГС пил 1500м гор'!$W126*AC$13 -> 0 | AE126: ='ГС без пилот 1500м гор'!$V126*AE$13 -> 0 | AF126: ='ГС без пилот 1500м гор'!$W126*AE$13 -> 0 | AG126: ='ГСЮра без пил МГРП'!$V126*AG$13 -> 0 | AH126: ='ГСЮра без пил МГРП'!$W126*AG$13 -> 0 | AI126: ='ГСЮра пил МСГРП'!$V126*AI$13 -> 0 | AJ126: ='ГСЮра пил МСГРП'!$W126*AI$13 -> 0 | AK126: ='ГСЮра керн ГИС'!$V126*AK$13 -> 0 | AL126: ='ГСЮра керн ГИС'!$W126*AK$13 -> 0 | AM126: =Посл.скв.!$V126*AM$13 -> 0 | AN126: =Посл.скв.!$W126*AM$13 -> 0 | AO126: =AM126+AK126+AI126+AG126+AE126+AC126+AA126+Y126++W126+U126+S126+Q126+M126+O126+K126+I126+G126 -> 0 | AP126: =AN126+AL126+AJ126+AH126+AF126+AD126+AB126+Z126++X126+V126+T126+R126+N126+P126+L126+J126+H126 -> 0
D127: ='Перв. скв '!D127 -> Резервная ставка по ННБ для секций скважин диаметром 220,7 мм. | E127: ='Перв. скв '!E127 -> 0 | F127: ='Перв. скв '!F127 -> сут | G127: ='Перв. скв '!$V127*G$13 -> 0 | H127: ='Перв. скв '!$W127*G$13 -> 0 | I127: ='2'!$V127*I$13 -> 0 | J127: ='2'!$W127*I$13 -> 0 | K127: ='3'!$V127*K$13 -> 0 | L127: ='3'!$W127*K$13 -> 0 | M127: ='4'!$V127*M$13 -> 0 | N127: ='4'!$W127*M$13 -> 0 | O127: ='5'!$V127*O$13 -> 0 | P127: ='5'!$W127*O$13 -> 0 | Q127: ='6'!$V127*Q$13 -> 0 | R127: ='6'!$W127*Q$13 -> 0 | S127: ='7'!$V127*S$13 -> 0 | T127: ='7'!$W127*S$13 -> 0 | U127: ='8'!$V127*U$13 -> 0 | V127: ='8'!$W127*U$13 -> 0 | W127: ='9'!$V127*W$13 -> 0 | X127: ='9'!$W127*W$13 -> 0 | Y127: =ВЗ!$V127*Y$13 -> 0 | Z127: =ВЗ!$W127*Y$13 -> 0 | AA127: ='ГС без пил 1000м гор'!$V127*AA$13 -> 0 | AB127: ='ГС без пил 1000м гор'!$W127*AA$13 -> 0 | AC127: ='ГС пил 1500м гор'!$V127*AC$13 -> 0 | AD127: ='ГС пил 1500м гор'!$W127*AC$13 -> 0 | AE127: ='ГС без пилот 1500м гор'!$V127*AE$13 -> 0 | AF127: ='ГС без пилот 1500м гор'!$W127*AE$13 -> 0 | AG127: ='ГСЮра без пил МГРП'!$V127*AG$13 -> 0 | AH127: ='ГСЮра без пил МГРП'!$W127*AG$13 -> 0 | AI127: ='ГСЮра пил МСГРП'!$V127*AI$13 -> 0 | AJ127: ='ГСЮра пил МСГРП'!$W127*AI$13 -> 0 | AK127: ='ГСЮра керн ГИС'!$V127*AK$13 -> 0 | AL127: ='ГСЮра керн ГИС'!$W127*AK$13 -> 0 | AM127: =Посл.скв.!$V127*AM$13 -> 0 | AN127: =Посл.скв.!$W127*AM$13 -> 0 | AO127: =AM127+AK127+AI127+AG127+AE127+AC127+AA127+Y127++W127+U127+S127+Q127+M127+O127+K127+I127+G127 -> 0 | AP127: =AN127+AL127+AJ127+AH127+AF127+AD127+AB127+Z127++X127+V127+T127+R127+N127+P127+L127+J127+H127 -> 0
D128: ='Перв. скв '!D128 -> Ставка работы по ННБ для секции скважин диаметром 220,7 мм.+ГК | E128: ='Перв. скв '!E128 -> 0 | F128: ='Перв. скв '!F128 -> сут | G128: ='Перв. скв '!$V128*G$13 -> 21.58 | H128: ='Перв. скв '!$W128*G$13 -> 20468302 | I128: ='2'!$V128*I$13 -> 0 | J128: ='2'!$W128*I$13 -> 0 | K128: ='3'!$V128*K$13 -> 0 | L128: ='3'!$W128*K$13 -> 0 | M128: ='4'!$V128*M$13 -> 0 | N128: ='4'!$W128*M$13 -> 0 | O128: ='5'!$V128*O$13 -> 0 | P128: ='5'!$W128*O$13 -> 0 | Q128: ='6'!$V128*Q$13 -> 0 | R128: ='6'!$W128*Q$13 -> 0 | S128: ='7'!$V128*S$13 -> 0 | T128: ='7'!$W128*S$13 -> 0 | U128: ='8'!$V128*U$13 -> 0 | V128: ='8'!$W128*U$13 -> 0 | W128: ='9'!$V128*W$13 -> 0 | X128: ='9'!$W128*W$13 -> 0 | Y128: =ВЗ!$V128*Y$13 -> 33.58 | Z128: =ВЗ!$W128*Y$13 -> -17882809 | AA128: ='ГС без пил 1000м гор'!$V128*AA$13 -> 78.32 | AB128: ='ГС без пил 1000м гор'!$W128*AA$13 -> 95048704 | AC128: ='ГС пил 1500м гор'!$V128*AC$13 -> 0 | AD128: ='ГС пил 1500м гор'!$W128*AC$13 -> 0 | AE128: ='ГС без пилот 1500м гор'!$V128*AE$13 -> 64.74 | AF128: ='ГС без пилот 1500м гор'!$W128*AE$13 -> 69318754 | AG128: ='ГСЮра без пил МГРП'!$V128*AG$13 -> 97.11 | AH128: ='ГСЮра без пил МГРП'!$W128*AG$13 -> 92107358 | AI128: ='ГСЮра пил МСГРП'!$V128*AI$13 -> 71.16 | AJ128: ='ГСЮра пил МСГРП'!$W128*AI$13 -> 48377869 | AK128: ='ГСЮра керн ГИС'!$V128*AK$13 -> 52.79 | AL128: ='ГСЮра керн ГИС'!$W128*AK$13 -> 3148489.8 | AM128: =Посл.скв.!$V128*AM$13 -> 0 | AN128: =Посл.скв.!$W128*AM$13 -> 0 | AO128: =AM128+AK128+AI128+AG128+AE128+AC128+AA128+Y128++W128+U128+S128+Q128+M128+O128+K128+I128+G128 -> 419.28 | AP128: =AN128+AL128+AJ128+AH128+AF128+AD128+AB128+Z128++X128+V128+T128+R128+N128+P128+L128+J128+H128 -> 3.1058667e+08
D129: ='Перв. скв '!D129 -> Ставка работы по ННБ для секции скважин диаметром 155,6 мм. | E129: ='Перв. скв '!E129 -> 0 | F129: ='Перв. скв '!F129 -> сут | G129: ='Перв. скв '!$V129*G$13 -> 15.86 | H129: ='Перв. скв '!$W129*G$13 -> 12925900 | I129: ='2'!$V129*I$13 -> 0 | J129: ='2'!$W129*I$13 -> 0 | K129: ='3'!$V129*K$13 -> 0 | L129: ='3'!$W129*K$13 -> 0 | M129: ='4'!$V129*M$13 -> 0 | N129: ='4'!$W129*M$13 -> 0 | O129: ='5'!$V129*O$13 -> 0 | P129: ='5'!$W129*O$13 -> 0 | Q129: ='6'!$V129*Q$13 -> 0 | R129: ='6'!$W129*Q$13 -> 0 | S129: ='7'!$V129*S$13 -> 0 | T129: ='7'!$W129*S$13 -> 0 | U129: ='8'!$V129*U$13 -> 0 | V129: ='8'!$W129*U$13 -> 0 | W129: ='9'!$V129*W$13 -> 0 | X129: ='9'!$W129*W$13 -> 0 | Y129: =ВЗ!$V129*Y$13 -> 15.86 | Z129: =ВЗ!$W129*Y$13 -> 12925900 | AA129: ='ГС без пил 1000м гор'!$V129*AA$13 -> 63.44 | AB129: ='ГС без пил 1000м гор'!$W129*AA$13 -> 51703600 | AC129: ='ГС пил 1500м гор'!$V129*AC$13 -> 0 | AD129: ='ГС пил 1500м гор'!$W129*AC$13 -> 0 | AE129: ='ГС без пилот 1500м гор'!$V129*AE$13 -> 47.58 | AF129: ='ГС без пилот 1500м гор'!$W129*AE$13 -> 38777700 | AG129: ='ГСЮра без пил МГРП'!$V129*AG$13 -> 71.37 | AH129: ='ГСЮра без пил МГРП'!$W129*AG$13 -> 58166550 | AI129: ='ГСЮра пил МСГРП'!$V129*AI$13 -> 31.72 | AJ129: ='ГСЮра пил МСГРП'!$W129*AI$13 -> 25851800 | AK129: ='ГСЮра керн ГИС'!$V129*AK$13 -> 7.93 | AL129: ='ГСЮра керн ГИС'!$W129*AK$13 -> 6462950 | AM129: =Посл.скв.!$V129*AM$13 -> 0 | AN129: =Посл.скв.!$W129*AM$13 -> 0 | AO129: =AM129+AK129+AI129+AG129+AE129+AC129+AA129+Y129++W129+U129+S129+Q129+M129+O129+K129+I129+G129 -> 253.76 | AP129: =AN129+AL129+AJ129+AH129+AF129+AD129+AB129+Z129++X129+V129+T129+R129+N129+P129+L129+J129+H129 -> 206814400
D130: ='Перв. скв '!D130 -> Резервная ставка по ННБ для секций скважин диаметром 155,6 мм. | E130: ='Перв. скв '!E130 -> 0 | F130: ='Перв. скв '!F130 -> сут | G130: ='Перв. скв '!$V130*G$13 -> 0 | H130: ='Перв. скв '!$W130*G$13 -> 0 | I130: ='2'!$V130*I$13 -> 0 | J130: ='2'!$W130*I$13 -> 0 | K130: ='3'!$V130*K$13 -> 0 | L130: ='3'!$W130*K$13 -> 0 | M130: ='4'!$V130*M$13 -> 0 | N130: ='4'!$W130*M$13 -> 0 | O130: ='5'!$V130*O$13 -> 0 | P130: ='5'!$W130*O$13 -> 0 | Q130: ='6'!$V130*Q$13 -> 0 | R130: ='6'!$W130*Q$13 -> 0 | S130: ='7'!$V130*S$13 -> 0 | T130: ='7'!$W130*S$13 -> 0 | U130: ='8'!$V130*U$13 -> 0 | V130: ='8'!$W130*U$13 -> 0 | W130: ='9'!$V130*W$13 -> 0 | X130: ='9'!$W130*W$13 -> 0 | Y130: =ВЗ!$V130*Y$13 -> 0 | Z130: =ВЗ!$W130*Y$13 -> 0 | AA130: ='ГС без пил 1000м гор'!$V130*AA$13 -> 0 | AB130: ='ГС без пил 1000м гор'!$W130*AA$13 -> 0 | AC130: ='ГС пил 1500м гор'!$V130*AC$13 -> 0 | AD130: ='ГС пил 1500м гор'!$W130*AC$13 -> 0 | AE130: ='ГС без пилот 1500м гор'!$V130*AE$13 -> 0 | AF130: ='ГС без пилот 1500м гор'!$W130*AE$13 -> 0 | AG130: ='ГСЮра без пил МГРП'!$V130*AG$13 -> 0 | AH130: ='ГСЮра без пил МГРП'!$W130*AG$13 -> 0 | AI130: ='ГСЮра пил МСГРП'!$V130*AI$13 -> 0 | AJ130: ='ГСЮра пил МСГРП'!$W130*AI$13 -> 0 | AK130: ='ГСЮра керн ГИС'!$V130*AK$13 -> 0 | AL130: ='ГСЮра керн ГИС'!$W130*AK$13 -> 0 | AM130: =Посл.скв.!$V130*AM$13 -> 0 | AN130: =Посл.скв.!$W130*AM$13 -> 0 | AO130: =AM130+AK130+AI130+AG130+AE130+AC130+AA130+Y130++W130+U130+S130+Q130+M130+O130+K130+I130+G130 -> 0 | AP130: =AN130+AL130+AJ130+AH130+AF130+AD130+AB130+Z130++X130+V130+T130+R130+N130+P130+L130+J130+H130 -> 0
D131: ='Перв. скв '!D131 -> Мобилизация и демобилизация на объект работ | E131: ='Перв. скв '!E131 -> 0 | F131: ='Перв. скв '!F131 -> операция | G131: ='Перв. скв '!$V131*G$13 -> 2 | H131: ='Перв. скв '!$W131*G$13 -> 7154257.2 | I131: ='2'!$V131*I$13 -> 0 | J131: ='2'!$W131*I$13 -> 0 | K131: ='3'!$V131*K$13 -> 0 | L131: ='3'!$W131*K$13 -> 0 | M131: ='4'!$V131*M$13 -> 0 | N131: ='4'!$W131*M$13 -> 0 | O131: ='5'!$V131*O$13 -> 0 | P131: ='5'!$W131*O$13 -> 0 | Q131: ='6'!$V131*Q$13 -> 0 | R131: ='6'!$W131*Q$13 -> 0 | S131: ='7'!$V131*S$13 -> 0 | T131: ='7'!$W131*S$13 -> 0 | U131: ='8'!$V131*U$13 -> 0 | V131: ='8'!$W131*U$13 -> 0 | W131: ='9'!$V131*W$13 -> 0 | X131: ='9'!$W131*W$13 -> 0 | Y131: =ВЗ!$V131*Y$13 -> 2 | Z131: =ВЗ!$W131*Y$13 -> 7154257.2 | AA131: ='ГС без пил 1000м гор'!$V131*AA$13 -> 8 | AB131: ='ГС без пил 1000м гор'!$W131*AA$13 -> 28617029 | AC131: ='ГС пил 1500м гор'!$V131*AC$13 -> 0 | AD131: ='ГС пил 1500м гор'!$W131*AC$13 -> 0 | AE131: ='ГС без пилот 1500м гор'!$V131*AE$13 -> 6 | AF131: ='ГС без пилот 1500м гор'!$W131*AE$13 -> 21462772 | AG131: ='ГСЮра без пил МГРП'!$V131*AG$13 -> 9 | AH131: ='ГСЮра без пил МГРП'!$W131*AG$13 -> 32194157 | AI131: ='ГСЮра пил МСГРП'!$V131*AI$13 -> 4 | AJ131: ='ГСЮра пил МСГРП'!$W131*AI$13 -> 14308514 | AK131: ='ГСЮра керн ГИС'!$V131*AK$13 -> 1 | AL131: ='ГСЮра керн ГИС'!$W131*AK$13 -> 3577128.6 | AM131: =Посл.скв.!$V131*AM$13 -> 0 | AN131: =Посл.скв.!$W131*AM$13 -> 0 | AO131: =AM131+AK131+AI131+AG131+AE131+AC131+AA131+Y131++W131+U131+S131+Q131+M131+O131+K131+I131+G131 -> 32 | AP131: =AN131+AL131+AJ131+AH131+AF131+AD131+AB131+Z131++X131+V131+T131+R131+N131+P131+L131+J131+H131 -> 1.1446812e+08
D132: ='Перв. скв '!D132 -> 0 | E132: ='Перв. скв '!E132 -> 0 | F132: ='Перв. скв '!F132 -> операция | G132: ='Перв. скв '!$V132*G$13 -> 0 | H132: ='Перв. скв '!$W132*G$13 -> 0 | I132: ='2'!$V132*I$13 -> 0 | J132: ='2'!$W132*I$13 -> 0 | K132: ='3'!$V132*K$13 -> 0 | L132: ='3'!$W132*K$13 -> 0 | M132: ='4'!$V132*M$13 -> 0 | N132: ='4'!$W132*M$13 -> 0 | O132: ='5'!$V132*O$13 -> 0 | P132: ='5'!$W132*O$13 -> 0 | Q132: ='6'!$V132*Q$13 -> 0 | R132: ='6'!$W132*Q$13 -> 0 | S132: ='7'!$V132*S$13 -> 0 | T132: ='7'!$W132*S$13 -> 0 | U132: ='8'!$V132*U$13 -> 0 | V132: ='8'!$W132*U$13 -> 0 | W132: ='9'!$V132*W$13 -> 0 | X132: ='9'!$W132*W$13 -> 0 | Y132: =ВЗ!$V132*Y$13 -> 0 | Z132: =ВЗ!$W132*Y$13 -> 0 | AA132: ='ГС без пил 1000м гор'!$V132*AA$13 -> 0 | AB132: ='ГС без пил 1000м гор'!$W132*AA$13 -> 0 | AC132: ='ГС пил 1500м гор'!$V132*AC$13 -> 0 | AD132: ='ГС пил 1500м гор'!$W132*AC$13 -> 0 | AE132: ='ГС без пилот 1500м гор'!$V132*AE$13 -> 0 | AF132: ='ГС без пилот 1500м гор'!$W132*AE$13 -> 0 | AG132: ='ГСЮра без пил МГРП'!$V132*AG$13 -> 0 | AH132: ='ГСЮра без пил МГРП'!$W132*AG$13 -> 0 | AI132: ='ГСЮра пил МСГРП'!$V132*AI$13 -> 0 | AJ132: ='ГСЮра пил МСГРП'!$W132*AI$13 -> 0 | AK132: ='ГСЮра керн ГИС'!$V132*AK$13 -> 0 | AL132: ='ГСЮра керн ГИС'!$W132*AK$13 -> 0 | AM132: =Посл.скв.!$V132*AM$13 -> 0 | AN132: =Посл.скв.!$W132*AM$13 -> 0 | AO132: =AM132+AK132+AI132+AG132+AE132+AC132+AA132+Y132++W132+U132+S132+Q132+M132+O132+K132+I132+G132 -> 0 | AP132: =AN132+AL132+AJ132+AH132+AF132+AD132+AB132+Z132++X132+V132+T132+R132+N132+P132+L132+J132+H132 -> 0
D133: ='Перв. скв '!D133 -> 0 | E133: ='Перв. скв '!E133 -> 0 | F133: ='Перв. скв '!F133 -> 0 | G133: ='Перв. скв '!$V133*G$13 -> 0 | H133: ='Перв. скв '!$W133*G$13 -> 0 | I133: ='2'!$V133*I$13 -> 0 | J133: ='2'!$W133*I$13 -> 0 | K133: ='3'!$V133*K$13 -> 0 | L133: ='3'!$W133*K$13 -> 0 | M133: ='4'!$V133*M$13 -> 0 | N133: ='4'!$W133*M$13 -> 0 | O133: ='5'!$V133*O$13 -> 0 | P133: ='5'!$W133*O$13 -> 0 | Q133: ='6'!$V133*Q$13 -> 0 | R133: ='6'!$W133*Q$13 -> 0 | S133: ='7'!$V133*S$13 -> 0 | T133: ='7'!$W133*S$13 -> 0 | U133: ='8'!$V133*U$13 -> 0 | V133: ='8'!$W133*U$13 -> 0 | W133: ='9'!$V133*W$13 -> 0 | X133: ='9'!$W133*W$13 -> 0 | Y133: =ВЗ!$V133*Y$13 -> 0 | Z133: =ВЗ!$W133*Y$13 -> 0 | AA133: ='ГС без пил 1000м гор'!$V133*AA$13 -> 0 | AB133: ='ГС без пил 1000м гор'!$W133*AA$13 -> 0 | AC133: ='ГС пил 1500м гор'!$V133*AC$13 -> 0 | AD133: ='ГС пил 1500м гор'!$W133*AC$13 -> 0 | AE133: ='ГС без пилот 1500м гор'!$V133*AE$13 -> 0 | AF133: ='ГС без пилот 1500м гор'!$W133*AE$13 -> 0 | AG133: ='ГСЮра без пил МГРП'!$V133*AG$13 -> 0 | AH133: ='ГСЮра без пил МГРП'!$W133*AG$13 -> 0 | AI133: ='ГСЮра пил МСГРП'!$V133*AI$13 -> 0 | AJ133: ='ГСЮра пил МСГРП'!$W133*AI$13 -> 0 | AK133: ='ГСЮра керн ГИС'!$V133*AK$13 -> 0 | AL133: ='ГСЮра керн ГИС'!$W133*AK$13 -> 0 | AM133: =Посл.скв.!$V133*AM$13 -> 0 | AN133: =Посл.скв.!$W133*AM$13 -> 0 | AO133: =AM133+AK133+AI133+AG133+AE133+AC133+AA133+Y133++W133+U133+S133+Q133+M133+O133+K133+I133+G133 -> 0 | AP133: =AN133+AL133+AJ133+AH133+AF133+AD133+AB133+Z133++X133+V133+T133+R133+N133+P133+L133+J133+H133 -> 0
D134: ='Перв. скв '!D134 -> 0 | E134: ='Перв. скв '!E134 -> 0 | F134: ='Перв. скв '!F134 -> 0 | G134: ='Перв. скв '!$V134*G$13 -> 0 | H134: ='Перв. скв '!$W134*G$13 -> 0 | I134: ='2'!$V134*I$13 -> 0 | J134: ='2'!$W134*I$13 -> 0 | K134: ='3'!$V134*K$13 -> 0 | L134: ='3'!$W134*K$13 -> 0 | M134: ='4'!$V134*M$13 -> 0 | N134: ='4'!$W134*M$13 -> 0 | O134: ='5'!$V134*O$13 -> 0 | P134: ='5'!$W134*O$13 -> 0 | Q134: ='6'!$V134*Q$13 -> 0 | R134: ='6'!$W134*Q$13 -> 0 | S134: ='7'!$V134*S$13 -> 0 | T134: ='7'!$W134*S$13 -> 0 | U134: ='8'!$V134*U$13 -> 0 | V134: ='8'!$W134*U$13 -> 0 | W134: ='9'!$V134*W$13 -> 0 | X134: ='9'!$W134*W$13 -> 0 | Y134: =ВЗ!$V134*Y$13 -> 0 | Z134: =ВЗ!$W134*Y$13 -> 0 | AA134: ='ГС без пил 1000м гор'!$V134*AA$13 -> 0 | AB134: ='ГС без пил 1000м гор'!$W134*AA$13 -> 0 | AC134: ='ГС пил 1500м гор'!$V134*AC$13 -> 0 | AD134: ='ГС пил 1500м гор'!$W134*AC$13 -> 0 | AE134: ='ГС без пилот 1500м гор'!$V134*AE$13 -> 0 | AF134: ='ГС без пилот 1500м гор'!$W134*AE$13 -> 0 | AG134: ='ГСЮра без пил МГРП'!$V134*AG$13 -> 0 | AH134: ='ГСЮра без пил МГРП'!$W134*AG$13 -> 0 | AI134: ='ГСЮра пил МСГРП'!$V134*AI$13 -> 0 | AJ134: ='ГСЮра пил МСГРП'!$W134*AI$13 -> 0 | AK134: ='ГСЮра керн ГИС'!$V134*AK$13 -> 0 | AL134: ='ГСЮра керн ГИС'!$W134*AK$13 -> 0 | AM134: =Посл.скв.!$V134*AM$13 -> 0 | AN134: =Посл.скв.!$W134*AM$13 -> 0 | AO134: =AM134+AK134+AI134+AG134+AE134+AC134+AA134+Y134++W134+U134+S134+Q134+M134+O134+K134+I134+G134 -> 0 | AP134: =AN134+AL134+AJ134+AH134+AF134+AD134+AB134+Z134++X134+V134+T134+R134+N134+P134+L134+J134+H134 -> 0
... D136: ='Перв. скв '!D136 -> 0 | E136: ='Перв. скв '!E136 -> 0 | F136: ='Перв. скв '!F136 -> 0 | G136: ='Перв. скв '!$V136*G$13 -> 0 | H136: ='Перв. скв '!$W136*G$13 -> 0 | I136: ='2'!$V136*I$13 -> 0 | J136: ='2'!$W136*I$13 -> 0 | K136: ='3'!$V136*K$13 -> 0 | L136: ='3'!$W136*K$13 -> 0 | M136: ='4'!$V136*M$13 -> 0 | N136: ='4'!$W136*M$13 -> 0 | O136: ='5'!$V136*O$13 -> 0 | P136: ='5'!$W136*O$13 -> 0 | Q136: ='6'!$V136*Q$13 -> 0 | R136: ='6'!$W136*Q$13 -> 0 | S136: ='7'!$V136*S$13 -> 0 | T136: ='7'!$W136*S$13 -> 0 | U136: ='8'!$V136*U$13 -> 0 | V136: ='8'!$W136*U$13 -> 0 | W136: ='9'!$V136*W$13 -> 0 | X136: ='9'!$W136*W$13 -> 0 | Y136: =ВЗ!$V136*Y$13 -> 0 | Z136: =ВЗ!$W136*Y$13 -> 0 | AA136: ='ГС без пил 1000м гор'!$V136*AA$13 -> 0 | AB136: ='ГС без пил 1000м гор'!$W136*AA$13 -> 0 | AC136: ='ГС пил 1500м гор'!$V136*AC$13 -> 0 | AD136: ='ГС пил 1500м гор'!$W136*AC$13 -> 0 | AE136: ='ГС без пилот 1500м гор'!$V136*AE$13 -> 0 | AF136: ='ГС без пилот 1500м гор'!$W136*AE$13 -> 0 | AG136: ='ГСЮра без пил МГРП'!$V136*AG$13 -> 0 | AH136: ='ГСЮра без пил МГРП'!$W136*AG$13 -> 0 | AI136: ='ГСЮра пил МСГРП'!$V136*AI$13 -> 0 | AJ136: ='ГСЮра пил МСГРП'!$W136*AI$13 -> 0 | AK136: ='ГСЮра керн ГИС'!$V136*AK$13 -> 0 | AL136: ='ГСЮра керн ГИС'!$W136*AK$13 -> 0 | AM136: =Посл.скв.!$V136*AM$13 -> 0 | AN136: =Посл.скв.!$W136*AM$13 -> 0 | AO136: =AM136+AK136+AI136+AG136+AE136+AC136+AA136+Y136++W136+U136+S136+Q136+M136+O136+K136+I136+G136 -> 0 | AP136: =AN136+AL136+AJ136+AH136+AF136+AD136+AB136+Z136++X136+V136+T136+R136+N136+P136+L136+J136+H136 -> 0
C137: ='Перв. скв '!C137 -> 0 | D137: Описание работ/услуг
C138: ='Перв. скв '!C138 -> Услуги направленного бурения и телеметрии (включая ГЗД) - стоимость аренды оборудования и услуг соответствующего персонала для направленного бурения, услуги ГИС/измерений во время бурения (MWD, LWD и услуги персонала) | D138: ='Перв. скв '!D138 -> Операционная ставка в режиме работы | E138: ='Перв. скв '!E138 -> 0 | F138: ='Перв. скв '!F138 -> сут | G138: ='Перв. скв '!$V138*G$13 -> 0 | H138: ='Перв. скв '!$W138*G$13 -> 0 | I138: ='2'!$V138*I$13 -> 0 | J138: ='2'!$W138*I$13 -> 0 | K138: ='3'!$V138*K$13 -> 0 | L138: ='3'!$W138*K$13 -> 0 | M138: ='4'!$V138*M$13 -> 0 | N138: ='4'!$W138*M$13 -> 0 | O138: ='5'!$V138*O$13 -> 0 | P138: ='5'!$W138*O$13 -> 0 | Q138: ='6'!$V138*Q$13 -> 0 | R138: ='6'!$W138*Q$13 -> 0 | S138: ='7'!$V138*S$13 -> 0 | T138: ='7'!$W138*S$13 -> 0 | U138: ='8'!$V138*U$13 -> 0 | V138: ='8'!$W138*U$13 -> 0 | W138: ='9'!$V138*W$13 -> 0 | X138: ='9'!$W138*W$13 -> 0 | Y138: =ВЗ!$V138*Y$13 -> 0 | Z138: =ВЗ!$W138*Y$13 -> 0 | AA138: ='ГС без пил 1000м гор'!$V138*AA$13 -> 0 | AB138: ='ГС без пил 1000м гор'!$W138*AA$13 -> 0 | AC138: ='ГС пил 1500м гор'!$V138*AC$13 -> 0 | AD138: ='ГС пил 1500м гор'!$W138*AC$13 -> 0 | AE138: ='ГС без пилот 1500м гор'!$V138*AE$13 -> 0 | AF138: ='ГС без пилот 1500м гор'!$W138*AE$13 -> 0 | AG138: ='ГСЮра без пил МГРП'!$V138*AG$13 -> 0 | AH138: ='ГСЮра без пил МГРП'!$W138*AG$13 -> 0 | AI138: ='ГСЮра пил МСГРП'!$V138*AI$13 -> 0 | AJ138: ='ГСЮра пил МСГРП'!$W138*AI$13 -> 0 | AK138: ='ГСЮра керн ГИС'!$V138*AK$13 -> 0 | AL138: ='ГСЮра керн ГИС'!$W138*AK$13 -> 0 | AM138: =Посл.скв.!$V138*AM$13 -> 0 | AN138: =Посл.скв.!$W138*AM$13 -> 0 | AO138: =AM138+AK138+AI138+AG138+AE138+AC138+AA138+Y138++W138+U138+S138+Q138+M138+O138+K138+I138+G138 -> 0 | AP138: =AN138+AL138+AJ138+AH138+AF138+AD138+AB138+Z138++X138+V138+T138+R138+N138+P138+L138+J138+H138 -> 0
D139: ='Перв. скв '!D139 -> Операционная ставка в режиме ожидания | E139: ='Перв. скв '!E139 -> 0 | F139: ='Перв. скв '!F139 -> сут | G139: ='Перв. скв '!$V139*G$13 -> 0 | H139: ='Перв. скв '!$W139*G$13 -> 0 | I139: ='2'!$V139*I$13 -> 0 | J139: ='2'!$W139*I$13 -> 0 | K139: ='3'!$V139*K$13 -> 0 | L139: ='3'!$W139*K$13 -> 0 | M139: ='4'!$V139*M$13 -> 0 | N139: ='4'!$W139*M$13 -> 0 | O139: ='5'!$V139*O$13 -> 0 | P139: ='5'!$W139*O$13 -> 0 | Q139: ='6'!$V139*Q$13 -> 0 | R139: ='6'!$W139*Q$13 -> 0 | S139: ='7'!$V139*S$13 -> 0 | T139: ='7'!$W139*S$13 -> 0 | U139: ='8'!$V139*U$13 -> 0 | V139: ='8'!$W139*U$13 -> 0 | W139: ='9'!$V139*W$13 -> 0 | X139: ='9'!$W139*W$13 -> 0 | Y139: =ВЗ!$V139*Y$13 -> 0 | Z139: =ВЗ!$W139*Y$13 -> 0 | AA139: ='ГС без пил 1000м гор'!$V139*AA$13 -> 0 | AB139: ='ГС без пил 1000м гор'!$W139*AA$13 -> 0 | AC139: ='ГС пил 1500м гор'!$V139*AC$13 -> 0 | AD139: ='ГС пил 1500м гор'!$W139*AC$13 -> 0 | AE139: ='ГС без пилот 1500м гор'!$V139*AE$13 -> 0 | AF139: ='ГС без пилот 1500м гор'!$W139*AE$13 -> 0 | AG139: ='ГСЮра без пил МГРП'!$V139*AG$13 -> 0 | AH139: ='ГСЮра без пил МГРП'!$W139*AG$13 -> 0 | AI139: ='ГСЮра пил МСГРП'!$V139*AI$13 -> 0 | AJ139: ='ГСЮра пил МСГРП'!$W139*AI$13 -> 0 | AK139: ='ГСЮра керн ГИС'!$V139*AK$13 -> 0 | AL139: ='ГСЮра керн ГИС'!$W139*AK$13 -> 0 | AM139: =Посл.скв.!$V139*AM$13 -> 0 | AN139: =Посл.скв.!$W139*AM$13 -> 0 | AO139: =AM139+AK139+AI139+AG139+AE139+AC139+AA139+Y139++W139+U139+S139+Q139+M139+O139+K139+I139+G139 -> 0 | AP139: =AN139+AL139+AJ139+AH139+AF139+AD139+AB139+Z139++X139+V139+T139+R139+N139+P139+L139+J139+H139 -> 0
D140: ='Перв. скв '!D140 -> Гамма -каротаж и сопротивление в режиме записи | E140: ='Перв. скв '!E140 -> 0 | F140: ='Перв. скв '!F140 -> сут | G140: ='Перв. скв '!$V140*G$13 -> 0 | H140: ='Перв. скв '!$W140*G$13 -> 0 | I140: ='2'!$V140*I$13 -> 0 | J140: ='2'!$W140*I$13 -> 0 | K140: ='3'!$V140*K$13 -> 0 | L140: ='3'!$W140*K$13 -> 0 | M140: ='4'!$V140*M$13 -> 0 | N140: ='4'!$W140*M$13 -> 0 | O140: ='5'!$V140*O$13 -> 0 | P140: ='5'!$W140*O$13 -> 0 | Q140: ='6'!$V140*Q$13 -> 0 | R140: ='6'!$W140*Q$13 -> 0 | S140: ='7'!$V140*S$13 -> 0 | T140: ='7'!$W140*S$13 -> 0 | U140: ='8'!$V140*U$13 -> 0 | V140: ='8'!$W140*U$13 -> 0 | W140: ='9'!$V140*W$13 -> 0 | X140: ='9'!$W140*W$13 -> 0 | Y140: =ВЗ!$V140*Y$13 -> 0 | Z140: =ВЗ!$W140*Y$13 -> 0 | AA140: ='ГС без пил 1000м гор'!$V140*AA$13 -> 0 | AB140: ='ГС без пил 1000м гор'!$W140*AA$13 -> 0 | AC140: ='ГС пил 1500м гор'!$V140*AC$13 -> 0 | AD140: ='ГС пил 1500м гор'!$W140*AC$13 -> 0 | AE140: ='ГС без пилот 1500м гор'!$V140*AE$13 -> 0 | AF140: ='ГС без пилот 1500м гор'!$W140*AE$13 -> 0 | AG140: ='ГСЮра без пил МГРП'!$V140*AG$13 -> 0 | AH140: ='ГСЮра без пил МГРП'!$W140*AG$13 -> 0 | AI140: ='ГСЮра пил МСГРП'!$V140*AI$13 -> 0 | AJ140: ='ГСЮра пил МСГРП'!$W140*AI$13 -> 0 | AK140: ='ГСЮра керн ГИС'!$V140*AK$13 -> 0 | AL140: ='ГСЮра керн ГИС'!$W140*AK$13 -> 0 | AM140: =Посл.скв.!$V140*AM$13 -> 0 | AN140: =Посл.скв.!$W140*AM$13 -> 0 | AO140: =AM140+AK140+AI140+AG140+AE140+AC140+AA140+Y140++W140+U140+S140+Q140+M140+O140+K140+I140+G140 -> 0 | AP140: =AN140+AL140+AJ140+AH140+AF140+AD140+AB140+Z140++X140+V140+T140+R140+N140+P140+L140+J140+H140 -> 0
D141: ='Перв. скв '!D141 -> Гамма -каротаж и сопротивление в режиме реаьного времени | E141: ='Перв. скв '!E141 -> 0 | F141: ='Перв. скв '!F141 -> сут | G141: ='Перв. скв '!$V141*G$13 -> 0 | H141: ='Перв. скв '!$W141*G$13 -> 0 | I141: ='2'!$V141*I$13 -> 0 | J141: ='2'!$W141*I$13 -> 0 | K141: ='3'!$V141*K$13 -> 0 | L141: ='3'!$W141*K$13 -> 0 | M141: ='4'!$V141*M$13 -> 0 | N141: ='4'!$W141*M$13 -> 0 | O141: ='5'!$V141*O$13 -> 0 | P141: ='5'!$W141*O$13 -> 0 | Q141: ='6'!$V141*Q$13 -> 0 | R141: ='6'!$W141*Q$13 -> 0 | S141: ='7'!$V141*S$13 -> 0 | T141: ='7'!$W141*S$13 -> 0 | U141: ='8'!$V141*U$13 -> 0 | V141: ='8'!$W141*U$13 -> 0 | W141: ='9'!$V141*W$13 -> 0 | X141: ='9'!$W141*W$13 -> 0 | Y141: =ВЗ!$V141*Y$13 -> 0 | Z141: =ВЗ!$W141*Y$13 -> 0 | AA141: ='ГС без пил 1000м гор'!$V141*AA$13 -> 0 | AB141: ='ГС без пил 1000м гор'!$W141*AA$13 -> 0 | AC141: ='ГС пил 1500м гор'!$V141*AC$13 -> 0 | AD141: ='ГС пил 1500м гор'!$W141*AC$13 -> 0 | AE141: ='ГС без пилот 1500м гор'!$V141*AE$13 -> 0 | AF141: ='ГС без пилот 1500м гор'!$W141*AE$13 -> 0 | AG141: ='ГСЮра без пил МГРП'!$V141*AG$13 -> 0 | AH141: ='ГСЮра без пил МГРП'!$W141*AG$13 -> 0 | AI141: ='ГСЮра пил МСГРП'!$V141*AI$13 -> 0 | AJ141: ='ГСЮра пил МСГРП'!$W141*AI$13 -> 0 | AK141: ='ГСЮра керн ГИС'!$V141*AK$13 -> 0 | AL141: ='ГСЮра керн ГИС'!$W141*AK$13 -> 0 | AM141: =Посл.скв.!$V141*AM$13 -> 0 | AN141: =Посл.скв.!$W141*AM$13 -> 0 | AO141: =AM141+AK141+AI141+AG141+AE141+AC141+AA141+Y141++W141+U141+S141+Q141+M141+O141+K141+I141+G141 -> 0 | AP141: =AN141+AL141+AJ141+AH141+AF141+AD141+AB141+Z141++X141+V141+T141+R141+N141+P141+L141+J141+H141 -> 0
D142: ='Перв. скв '!D142 -> Гамма -каротаж в режиме записи | E142: ='Перв. скв '!E142 -> 0 | F142: ='Перв. скв '!F142 -> сут | G142: ='Перв. скв '!$V142*G$13 -> 0 | H142: ='Перв. скв '!$W142*G$13 -> 0 | I142: ='2'!$V142*I$13 -> 0 | J142: ='2'!$W142*I$13 -> 0 | K142: ='3'!$V142*K$13 -> 0 | L142: ='3'!$W142*K$13 -> 0 | M142: ='4'!$V142*M$13 -> 0 | N142: ='4'!$W142*M$13 -> 0 | O142: ='5'!$V142*O$13 -> 0 | P142: ='5'!$W142*O$13 -> 0 | Q142: ='6'!$V142*Q$13 -> 0 | R142: ='6'!$W142*Q$13 -> 0 | S142: ='7'!$V142*S$13 -> 0 | T142: ='7'!$W142*S$13 -> 0 | U142: ='8'!$V142*U$13 -> 0 | V142: ='8'!$W142*U$13 -> 0 | W142: ='9'!$V142*W$13 -> 0 | X142: ='9'!$W142*W$13 -> 0 | Y142: =ВЗ!$V142*Y$13 -> 0 | Z142: =ВЗ!$W142*Y$13 -> 0 | AA142: ='ГС без пил 1000м гор'!$V142*AA$13 -> 0 | AB142: ='ГС без пил 1000м гор'!$W142*AA$13 -> 0 | AC142: ='ГС пил 1500м гор'!$V142*AC$13 -> 0 | AD142: ='ГС пил 1500м гор'!$W142*AC$13 -> 0 | AE142: ='ГС без пилот 1500м гор'!$V142*AE$13 -> 0 | AF142: ='ГС без пилот 1500м гор'!$W142*AE$13 -> 0 | AG142: ='ГСЮра без пил МГРП'!$V142*AG$13 -> 0 | AH142: ='ГСЮра без пил МГРП'!$W142*AG$13 -> 0 | AI142: ='ГСЮра пил МСГРП'!$V142*AI$13 -> 0 | AJ142: ='ГСЮра пил МСГРП'!$W142*AI$13 -> 0 | AK142: ='ГСЮра керн ГИС'!$V142*AK$13 -> 0 | AL142: ='ГСЮра керн ГИС'!$W142*AK$13 -> 0 | AM142: =Посл.скв.!$V142*AM$13 -> 0 | AN142: =Посл.скв.!$W142*AM$13 -> 0 | AO142: =AM142+AK142+AI142+AG142+AE142+AC142+AA142+Y142++W142+U142+S142+Q142+M142+O142+K142+I142+G142 -> 0 | AP142: =AN142+AL142+AJ142+AH142+AF142+AD142+AB142+Z142++X142+V142+T142+R142+N142+P142+L142+J142+H142 -> 0
D143: ='Перв. скв '!D143 -> Гамма -каротаж в режиме реаьного времени | E143: ='Перв. скв '!E143 -> 0 | F143: ='Перв. скв '!F143 -> сут | G143: ='Перв. скв '!$V143*G$13 -> 0 | H143: ='Перв. скв '!$W143*G$13 -> 0 | I143: ='2'!$V143*I$13 -> 0 | J143: ='2'!$W143*I$13 -> 0 | K143: ='3'!$V143*K$13 -> 0 | L143: ='3'!$W143*K$13 -> 0 | M143: ='4'!$V143*M$13 -> 0 | N143: ='4'!$W143*M$13 -> 0 | O143: ='5'!$V143*O$13 -> 0 | P143: ='5'!$W143*O$13 -> 0 | Q143: ='6'!$V143*Q$13 -> 0 | R143: ='6'!$W143*Q$13 -> 0 | S143: ='7'!$V143*S$13 -> 0 | T143: ='7'!$W143*S$13 -> 0 | U143: ='8'!$V143*U$13 -> 0 | V143: ='8'!$W143*U$13 -> 0 | W143: ='9'!$V143*W$13 -> 0 | X143: ='9'!$W143*W$13 -> 0 | Y143: =ВЗ!$V143*Y$13 -> 0 | Z143: =ВЗ!$W143*Y$13 -> 0 | AA143: ='ГС без пил 1000м гор'!$V143*AA$13 -> 0 | AB143: ='ГС без пил 1000м гор'!$W143*AA$13 -> 0 | AC143: ='ГС пил 1500м гор'!$V143*AC$13 -> 0 | AD143: ='ГС пил 1500м гор'!$W143*AC$13 -> 0 | AE143: ='ГС без пилот 1500м гор'!$V143*AE$13 -> 0 | AF143: ='ГС без пилот 1500м гор'!$W143*AE$13 -> 0 | AG143: ='ГСЮра без пил МГРП'!$V143*AG$13 -> 0 | AH143: ='ГСЮра без пил МГРП'!$W143*AG$13 -> 0 | AI143: ='ГСЮра пил МСГРП'!$V143*AI$13 -> 0 | AJ143: ='ГСЮра пил МСГРП'!$W143*AI$13 -> 0 | AK143: ='ГСЮра керн ГИС'!$V143*AK$13 -> 0 | AL143: ='ГСЮра керн ГИС'!$W143*AK$13 -> 0 | AM143: =Посл.скв.!$V143*AM$13 -> 0 | AN143: =Посл.скв.!$W143*AM$13 -> 0 | AO143: =AM143+AK143+AI143+AG143+AE143+AC143+AA143+Y143++W143+U143+S143+Q143+M143+O143+K143+I143+G143 -> 0 | AP143: =AN143+AL143+AJ143+AH143+AF143+AD143+AB143+Z143++X143+V143+T143+R143+N143+P143+L143+J143+H143 -> 0
D144: ='Перв. скв '!D144 -> Прочее | E144: ='Перв. скв '!E144 -> 0 | F144: ='Перв. скв '!F144 -> сут | G144: ='Перв. скв '!$V144*G$13 -> 0 | H144: ='Перв. скв '!$W144*G$13 -> 0 | I144: ='2'!$V144*I$13 -> 0 | J144: ='2'!$W144*I$13 -> 0 | K144: ='3'!$V144*K$13 -> 0 | L144: ='3'!$W144*K$13 -> 0 | M144: ='4'!$V144*M$13 -> 0 | N144: ='4'!$W144*M$13 -> 0 | O144: ='5'!$V144*O$13 -> 0 | P144: ='5'!$W144*O$13 -> 0 | Q144: ='6'!$V144*Q$13 -> 0 | R144: ='6'!$W144*Q$13 -> 0 | S144: ='7'!$V144*S$13 -> 0 | T144: ='7'!$W144*S$13 -> 0 | U144: ='8'!$V144*U$13 -> 0 | V144: ='8'!$W144*U$13 -> 0 | W144: ='9'!$V144*W$13 -> 0 | X144: ='9'!$W144*W$13 -> 0 | Y144: =ВЗ!$V144*Y$13 -> 0 | Z144: =ВЗ!$W144*Y$13 -> 0 | AA144: ='ГС без пил 1000м гор'!$V144*AA$13 -> 0 | AB144: ='ГС без пил 1000м гор'!$W144*AA$13 -> 0 | AC144: ='ГС пил 1500м гор'!$V144*AC$13 -> 0 | AD144: ='ГС пил 1500м гор'!$W144*AC$13 -> 0 | AE144: ='ГС без пилот 1500м гор'!$V144*AE$13 -> 0 | AF144: ='ГС без пилот 1500м гор'!$W144*AE$13 -> 0 | AG144: ='ГСЮра без пил МГРП'!$V144*AG$13 -> 0 | AH144: ='ГСЮра без пил МГРП'!$W144*AG$13 -> 0 | AI144: ='ГСЮра пил МСГРП'!$V144*AI$13 -> 0 | AJ144: ='ГСЮра пил МСГРП'!$W144*AI$13 -> 0 | AK144: ='ГСЮра керн ГИС'!$V144*AK$13 -> 0 | AL144: ='ГСЮра керн ГИС'!$W144*AK$13 -> 0 | AM144: =Посл.скв.!$V144*AM$13 -> 0 | AN144: =Посл.скв.!$W144*AM$13 -> 0 | AO144: =AM144+AK144+AI144+AG144+AE144+AC144+AA144+Y144++W144+U144+S144+Q144+M144+O144+K144+I144+G144 -> 0 | AP144: =AN144+AL144+AJ144+AH144+AF144+AD144+AB144+Z144++X144+V144+T144+R144+N144+P144+L144+J144+H144 -> 0
...

Sheet Перв. скв 
A2: ПОДРОБНАЯ СМЕТНАЯ СТОИМОСТЬ СКВАЖИНЫ
B4: 3 | C4: Месторождение/ куст: | D4: ='Титул '!$K$5 -> 3 куст Новопортовского месторождения | E4: ВСЕГО СТ-ТЬ | F4: Исходные данные | H4: Перед забуркой | I4: Направление | J4: Кондуктор | K4: Техническая колонна | L4: Эксплуат-ая колонна | M4: Крепление колонн | N4: Хвостовик | O4: ВСЕГО БУРЕНИЕ | P4: Исходные данные | R4: ВСЕГО ОСВОЕНИЕ
C5: Подрядчик по бурению: | D5: ='Титул '!$K$11 -> ООО "Буровая компания "Евразия" | E5: =D369 -> 3.6218774e+08
C6: Тип буровой установки: | D6: ='Титул '!$K$12 -> ZJ-50 | E6: Всего ВМР | F6: Время бурения секции, сут: | H6: 0 | I6: 0.68 | J6: 2 | K6: 2.83 | L6: 10.79 | M6: 7.93 | N6: 9.77 | O6: =SUM(I6:N6) -> 34 | P6: Время освоения, сут:
C7: Тип скважины: | D7: =CONCATENATE('Титул '!$C$28," ",'Титул '!$D$28," ",'Титул '!$E$28," ",'Титул '!$F$28," ",'Титул '!$G$28," ",'Титул '!$H$28," ",'Титул '!$J$28," ",'Титул '!$I$28) -> ГС ЮРА без пилота МГРП 8ст | E7: =W69 -> 1.2893274e+08 | F7: Глубина (по стволу), м: | I7: 50 | J7: 460 | K7: 1200 | L7: 2700 | N7: 3700 | O7: ВСЕГО ПРОХОДКА | P7: В т.ч.время работы бригад КРС
C8: Проходка всего (м): | D8: 4728 | E8: Всего Бурение | F8: Диаметр долота, мм: | I8: 490 | J8: 393.7 | K8: 295.3 | L8: 220.7 | N8: 152.4 | P8: - ПЗР к ГРП/МСГРП, сут.
C9: Наличие СВП: | D9: ='Титул '!$K$13 -> 0 | E9: =W341 -> 1.3644058e+08 | F9: Диаметр колонны, мм: | I9: 630 | J9: 324 | K9: 245 | L9: 178 | N9: 114 | O9: =D8 -> 4728 | P9: - проведение ГРП/МСГРП, сут.
C10: Наличие АИЭС: | D10: ='Титул '!$K$14 -> да | E10: Всего Освоение | F10: Исходные данные | H10: Отход | I10: Пилот ГС | J10: Перебур | K10: Гориз.уч. 1 | L10: Гориз.уч. 2 | M10: Керн | O10: ГЛУБИНА ПО ВЕРТ-ЛИ | P10: - проведение ГНКТ, сут.
C11: Наличие автономности: | D11: ='Титул '!$K$15 -> да | E11: =W361 -> 96814424 | F11: Отдельные стволы, керн, м: | H11: 2000 | K11: 1500 | P11: - кол-во стадий МСГРП, шт.
B12: 1 | C12: Кол-во обсадных колонн (включая направл.): | D12: ='Титул '!I28 -> 0 | E12: Обор-ие устья | F12: Примечание: | P12: Примечание:
C13: Прочие существенные условия: | E13: =W367 -> 0
A15: ОПИСАНИЕ РАБОТ И УСЛУГ | H15: КОЛИЧЕСТВО | O15: СТОИМОСТЬ | V15: ВСЕГО
A16: КОД | B16: добавочный код | C16: СТАТЬЯ ЗАТРАТ | D16: ОПИСАНИЕ | E16: Подрядчик | F16: Единица измерения | G16: Руб. / Ед.изм. | H16: ПЗР (в т.ч. ВМР и осв.) | I16: =+I4 -> Направление | J16: =+J4 -> Кондуктор | K16: =+K4 -> Техническая колонна | L16: =+L4 -> Эксплуат-ая колонна | M16: Крепление колонн | N16: =+N4 -> Хвостовик | O16: ПЗР (в т.ч. ВМР и осв.) | P16: =+I16 -> Направление | Q16: =+J16 -> Кондуктор | R16: =+K16 -> Техническая колонна | S16: =+L16 -> Эксплуат-ая колонна | T16: Крепление колонн | U16: =+N16 -> Хвостовик | V16: Количество | W16: Стоимость (руб) | X16: ВСЕГО СТОИМОСТЬ
C18: 1. ЭТАП ВМР | X18: =SUM(W20:W68) -> 1.2893274e+08
C19: =D5 -> ООО "Буровая компания "Евразия" | D19: Описание работ/услуг
C20: Работы, связанные с мобилизацией БУ (переездом), а так же прочего бурового оборудования и бригадного хозяйства, автономного источника энергоснабжения, материалов подрядчика и прочее. | D20: Мобилизация БУ (переезд) | E20: =D$5 -> ООО "Буровая компания "Евразия" | F20: операция | G20: 1.2893274e+08 | H20: 1 | O20: =H20*G20 -> 1.2893274e+08 | V20: =SUM(H20:N20) -> 1 | W20: =SUM(O20:U20) -> 1.2893274e+08
D21: - мобилизация БУ (переезд) | E21: =D$5 -> ООО "Буровая компания "Евразия" | F21: операция | O21: =H21*G21 -> 0 | V21: =SUM(H21:N21) -> 0 | W21: =SUM(O21:U21) -> 0
D22: - мобилизация БХ и БИ (перевозка) | E22: =D$5 -> ООО "Буровая компания "Евразия" | F22: операция | O22: =H22*G22 -> 0 | V22: =SUM(H22:N22) -> 0 | W22: =SUM(O22:U22) -> 0
D23: - мобилизация АвИЭС (переезд) | E23: =D$5 -> ООО "Буровая компания "Евразия" | F23: операция | O23: =H23*G23 -> 0 | V23: =SUM(H23:N23) -> 0 | W23: =SUM(O23:U23) -> 0
E24: =D$5 -> ООО "Буровая компания "Евразия" | F24: операция | O24: =H24*G24 -> 0 | V24: =SUM(H24:N24) -> 0 | W24: =SUM(O24:U24) -> 0
E25: =D$5 -> ООО "Буровая компания "Евразия" | F25: операция | O25: =H25*G25 -> 0 | V25: =SUM(H25:N25) -> 0 | W25: =SUM(O25:U25) -> 0
E26: =D$5 -> ООО "Буровая компания "Евразия" | F26: операция | O26: =H26*G26 -> 0 | V26: =SUM(H26:N26) -> 0 | W26: =SUM(O26:U26) -> 0
E27: =D$5 -> ООО "Буровая компания "Евразия" | F27: операция | O27: =H27*G27 -> 0 | V27: =SUM(H27:N27) -> 0 | W27: =SUM(O27:U27) -> 0
E28: =D$5 -> ООО "Буровая компания "Евразия" | F28: операция | O28: =H28*G28 -> 0 | V28: =SUM(H28:N28) -> 0 | W28: =SUM(O28:U28) -> 0
C29: Работы связанные со сборкой (монтажем) и подключением БУ, бурового и вспомогательного оборудования | D29: Монтаж БУ | E29: =D$5 -> ООО "Буровая компания "Евразия" | F29: операция | O29: =H29*G29 -> 0 | V29: =SUM(H29:N29) -> 0 | W29: =SUM(O29:U29) -> 0
D30: - монтаж БУ | E30: =D$5 -> ООО "Буровая компания "Евразия" | F30: операция | O30: =H30*G30 -> 0 | V30: =SUM(H30:N30) -> 0 | W30: =SUM(O30:U30) -> 0
D31: - монтаж АвИЭС | E31: =D$5 -> ООО "Буровая компания "Евразия" | F31: операция | O31: =H31*G31 -> 0 | V31: =SUM(H31:N31) -> 0 | W31: =SUM(O31:U31) -> 0
D32: - монтаж БДЕ, ПВО | E32: =D$5 -> ООО "Буровая компания "Евразия" | F32: операция | O32: =H32*G32 -> 0 | V32: =SUM(H32:N32) -> 0 | W32: =SUM(O32:U32) -> 0
D33: - бурение водяного колодца | E33: =D$5 -> ООО "Буровая компания "Евразия" | F33: операция | O33: =H33*G33 -> 0 | V33: =SUM(H33:N33) -> 0 | W33: =SUM(O33:U33) -> 0
D34: - ПНР | E34: =D$5 -> ООО "Буровая компания "Евразия" | F34: операция | O34: =H34*G34 -> 0 | V34: =SUM(H34:N34) -> 0 | W34: =SUM(O34:U34) -> 0
E35: =D$5 -> ООО "Буровая компания "Евразия" | F35: операция | O35: =H35*G35 -> 0 | V35: =SUM(H35:N35) -> 0 | W35: =SUM(O35:U35) -> 0
E36: =D$5 -> ООО "Буровая компания "Евразия" | F36: операция | O36: =H36*G36 -> 0 | V36: =SUM(H36:N36) -> 0 | W36: =SUM(O36:U36) -> 0
E37: =D$5 -> ООО "Буровая компания "Евразия" | F37: операция | O37: =H37*G37 -> 0 | V37: =SUM(H37:N37) -> 0 | W37: =SUM(O37:U37) -> 0
E38: =D$5 -> ООО "Буровая компания "Евразия" | F38: операция | O38: =H38*G38 -> 0 | V38: =SUM(H38:N38) -> 0 | W38: =SUM(O38:U38) -> 0
C39: Работы, свзянные с передвижкой БУ между скважинами на кустовой площадке | D39: Передвижка 5 м. | E39: =D$5 -> ООО "Буровая компания "Евразия" | F39: операция | O39: =H39*G39 -> 0 | V39: =SUM(H39:N39) -> 0 | W39: =SUM(O39:U39) -> 0
D40: Передвижка 9 м. | E40: =D$5 -> ООО "Буровая компания "Евразия" | F40: операция | O40: =H40*G40 -> 0 | V40: =SUM(H40:N40) -> 0 | W40: =SUM(O40:U40) -> 0
D41: Передвижка 18 м. | E41: =D$5 -> ООО "Буровая компания "Евразия" | F41: операция | O41: =H41*G41 -> 0 | V41: =SUM(H41:N41) -> 0 | W41: =SUM(O41:U41) -> 0
D42: Передвижка 25 м. | E42: =D$5 -> ООО "Буровая компания "Евразия" | F42: операция | O42: =H42*G42 -> 0 | V42: =SUM(H42:N42) -> 0 | W42: =SUM(O42:U42) -> 0
D43: Передвижка 75 м. | E43: =D$5 -> ООО "Буровая компания "Евразия" | F43: операция | O43: =H43*G43 -> 0 | V43: =SUM(H43:N43) -> 0 | W43: =SUM(O43:U43) -> 0
D44: Передвижка нестандартная | E44: =D$5 -> ООО "Буровая компания "Евразия" | F44: операция | O44: =H44*G44 -> 0 | V44: =SUM(H44:N44) -> 0 | W44: =SUM(O44:U44) -> 0
C45: Работы связанные с демонтажем БУ, бурового и вспомогательного оборудования | D45: Демонтаж БУ | E45: =D$5 -> ООО "Буровая компания "Евразия" | F45: операция | O45: =H45*G45 -> 0 | V45: =SUM(H45:N45) -> 0 | W45: =SUM(O45:U45) -> 0
D46: - демонтаж БУ | E46: =D$5 -> ООО "Буровая компания "Евразия" | F46: операция | O46: =H46*G46 -> 0 | V46: =SUM(H46:N46) -> 0 | W46: =SUM(O46:U46) -> 0
D47: - демонтаж АвИЭС | E47: =D$5 -> ООО "Буровая компания "Евразия" | F47: операция | O47: =H47*G47 -> 0 | V47: =SUM(H47:N47) -> 0 | W47: =SUM(O47:U47) -> 0
D48: - демонтаж БДЕ, ПВО | E48: =D$5 -> ООО "Буровая компания "Евразия" | F48: операция | O48: =H48*G48 -> 0 | V48: =SUM(H48:N48) -> 0 | W48: =SUM(O48:U48) -> 0
D49: - ликвидация водяного колодца | E49: =D$5 -> ООО "Буровая компания "Евразия" | F49: операция | O49: =H49*G49 -> 0 | V49: =SUM(H49:N49) -> 0 | W49: =SUM(O49:U49) -> 0
E50: =D$5 -> ООО "Буровая компания "Евразия" | F50: операция | O50: =H50*G50 -> 0 | V50: =SUM(H50:N50) -> 0 | W50: =SUM(O50:U50) -> 0
E51: =D$5 -> ООО "Буровая компания "Евразия" | F51: операция | O51: =H51*G51 -> 0 | V51: =SUM(H51:N51) -> 0 | W51: =SUM(O51:U51) -> 0
E52: =D$5 -> ООО "Буровая компания "Евразия" | F52: операция | O52: =H52*G52 -> 0 | V52: =SUM(H52:N52) -> 0 | W52: =SUM(O52:U52) -> 0
E53: =D$5 -> ООО "Буровая компания "Евразия" | F53: операция | O53: =H53*G53 -> 0 | V53: =SUM(H53:N53) -> 0 | W53: =SUM(O53:U53) -> 0
E54: =D$5 -> ООО "Буровая компания "Евразия" | F54: операция | O54: =H54*G54 -> 0 | V54: =SUM(H54:N54) -> 0 | W54: =SUM(O54:U54) -> 0
C55: Работы, связанные с демобилизацией БУ, а так же прочего бурового оборудования и бригадного хозяйства, автономного источника энергоснабжения, материалов подрядчика и прочее. | D55: Демобилизация БУ | E55: =D$5 -> ООО "Буровая компания "Евразия" | F55: операция | O55: =H55*G55 -> 0 | V55: =SUM(H55:N55) -> 0 | W55: =SUM(O55:U55) -> 0
D56: - демобилизация БУ | E56: =D$5 -> ООО "Буровая компания "Евразия" | F56: операция | O56: =H56*G56 -> 0 | V56: =SUM(H56:N56) -> 0 | W56: =SUM(O56:U56) -> 0
D57: - демобилизация БХ и БИ | E57: =D$5 -> ООО "Буровая компания "Евразия" | F57: операция | O57: =H57*G57 -> 0 | V57: =SUM(H57:N57) -> 0 | W57: =SUM(O57:U57) -> 0
D58: - демобилизация АвИЭС | E58: =D$5 -> ООО "Буровая компания "Евразия" | F58: операция | O58: =H58*G58 -> 0 | V58: =SUM(H58:N58) -> 0 | W58: =SUM(O58:U58) -> 0
E59: =D$5 -> ООО "Буровая компания "Евразия" | F59: операция | O59: =H59*G59 -> 0 | V59: =SUM(H59:N59) -> 0 | W59: =SUM(O59:U59) -> 0
E60: =D$5 -> ООО "Буровая компания "Евразия" | F60: операция | O60: =H60*G60 -> 0 | V60: =SUM(H60:N60) -> 0 | W60: =SUM(O60:U60) -> 0
E61: =D$5 -> ООО "Буровая компания "Евразия" | F61: операция | O61: =H61*G61 -> 0 | V61: =SUM(H61:N61) -> 0 | W61: =SUM(O61:U61) -> 0
E62: =D$5 -> ООО "Буровая компания "Евразия" | F62: операция | O62: =H62*G62 -> 0 | V62: =SUM(H62:N62) -> 0 | W62: =SUM(O62:U62) -> 0
E63: =D$5 -> ООО "Буровая компания "Евразия" | F63: операция | O63: =H63*G63 -> 0 | V63: =SUM(H63:N63) -> 0 | W63: =SUM(O63:U63) -> 0
C64: Прочие ВМР | E64: =D$5 -> ООО "Буровая компания "Евразия" | F64: операция | O64: =H64*G64 -> 0 | V64: =SUM(H64:N64) -> 0 | W64: =SUM(O64:U64) -> 0
E65: =D$5 -> ООО "Буровая компания "Евразия" | F65: операция | O65: =H65*G65 -> 0 | V65: =SUM(H65:N65) -> 0 | W65: =SUM(O65:U65) -> 0
E66: =D$5 -> ООО "Буровая компания "Евразия" | F66: операция | O66: =H66*G66 -> 0 | V66: =SUM(H66:N66) -> 0 | W66: =SUM(O66:U66) -> 0
E67: =D$5 -> ООО "Буровая компания "Евразия" | F67: операция | O67: =H67*G67 -> 0 | V67: =SUM(H67:N67) -> 0 | W67: =SUM(O67:U67) -> 0
E68: =D$5 -> ООО "Буровая компания "Евразия" | F68: операция | O68: =H68*G68 -> 0 | V68: =SUM(H68:N68) -> 0 | W68: =SUM(O68:U68) -> 0
C69: ОБЩАЯ СТОИМОСТЬ ВМР | D69: =W69 -> 1.2893274e+08 | O69: =SUM(O20:O68) -> 1.2893274e+08 | W69: =SUM(W20:W68) -> 1.2893274e+08
C71: 2. ЭТАП БУРЕНИЯ: | X71: =SUM(W73:W102) -> 57207434
C72: =D5 -> ООО "Буровая компания "Евразия" | D72: Описание работ/услуг
C73: Стоимость работ буровой бригады, а так же стоимость услуг АвИЭС | D73: Суточная ставка работы буровой бригады | E73: =D$5 -> ООО "Буровая компания "Евразия" | F73: сут | G73: ='ГСЮра без пил МГРП'!G73 -> 1428908.8 | I73: =I$6 -> 0.68 | J73: =J$6 -> 2 | K73: =K$6 -> 2.83 | L73: =L$6 -> 10.79 | M73: =M$6 -> 7.93 | N73: =N$6 -> 9.77 | O73: =H73*G73 -> 0 | P73: =I73*G73 -> 971657.96 | Q73: =J73*G73 -> 2857817.5 | R73: =K73*G73 -> 4043811.8 | S73: =L73*G73 -> 15417926 | T73: =M73*G73 -> 11331246 | U73: =N73*G73 -> 13960439 | V73: =SUM(H73:N73) -> 34 | W73: =SUM(O73:U73) -> 48582898
D74: Оплата по резервной ставке | E74: =D$5 -> ООО "Буровая компания "Евразия" | F74: сут | O74: =H74*G74 -> 0 | P74: =I74*G74 -> 0 | Q74: =J74*G74 -> 0 | R74: =K74*G74 -> 0 | S74: =L74*G74 -> 0 | T74: =M74*G74 -> 0 | U74: =N74*G74 -> 0 | V74: =SUM(H74:N74) -> 0 | W74: =SUM(O74:U74) -> 0
D75: Оплата по ставке дежурства | E75: =D$5 -> ООО "Буровая компания "Евразия" | F75: сут | O75: =H75*G75 -> 0 | P75: =I75*G75 -> 0 | Q75: =J75*G75 -> 0 | R75: =K75*G75 -> 0 | S75: =L75*G75 -> 0 | T75: =M75*G75 -> 0 | U75: =N75*G75 -> 0 | V75: =SUM(H75:N75) -> 0 | W75: =SUM(O75:U75) -> 0
D76: Монт/демонт ПВО и ФА, доп.работы | E76: =D$5 -> ООО "Буровая компания "Евразия" | F76: сут | O76: =H76*G76 -> 0 | P76: =I76*G76 -> 0 | Q76: =J76*G76 -> 0 | R76: =K76*G76 -> 0 | S76: =L76*G76 -> 0 | T76: =M76*G76 -> 0 | U76: =N76*G76 -> 0 | V76: =SUM(H76:N76) -> 0 | W76: =SUM(O76:U76) -> 0
D77: Суточная ставка АвИЭС | E77: =D$5 -> ООО "Буровая компания "Евразия" | F77: сут | G77: ='ГСЮра без пил МГРП'!G77 -> 103909.96 | I77: =I$6 -> 0.68 | J77: =J$6 -> 2 | K77: =K$6 -> 2.83 | L77: =L$6 -> 10.79 | M77: =M$6 -> 7.93 | N77: =N$6 -> 9.77 | O77: =H77*G77 -> 0 | P77: =I77*G77 -> 70658.773 | Q77: =J77*G77 -> 207819.92 | R77: =K77*G77 -> 294065.19 | S77: =L77*G77 -> 1121188.5 | T77: =M77*G77 -> 824005.98 | U77: =N77*G77 -> 1015200.3 | V77: =SUM(H77:N77) -> 34 | W77: =SUM(O77:U77) -> 3532938.6
D78: Ставка дежурства АвИЭС | E78: =D$5 -> ООО "Буровая компания "Евразия" | F78: сут | O78: =H78*G78 -> 0 | P78: =I78*G78 -> 0 | Q78: =J78*G78 -> 0 | R78: =K78*G78 -> 0 | S78: =L78*G78 -> 0 | T78: =M78*G78 -> 0 | U78: =N78*G78 -> 0 | V78: =SUM(H78:N78) -> 0 | W78: =SUM(O78:U78) -> 0
D79: Прочее | E79: =D$5 -> ООО "Буровая компания "Евразия" | G79: ='ГСЮра без пил МГРП'!G79+270926.130503178 -> 5091597.6 | H79: 1 | O79: =H79*G79 -> 5091597.6 | P79: =I79*G79 -> 0 | Q79: =J79*G79 -> 0 | R79: =K79*G79 -> 0 | S79: =L79*G79 -> 0 | T79: =M79*G79 -> 0 | U79: =N79*G79 -> 0 | V79: =SUM(H79:N79) -> 1 | W79: =SUM(O79:U79) -> 5091597.6
E80: =D$5 -> ООО "Буровая компания "Евразия" | O80: =H80*G80 -> 0 | P80: =I80*G80 -> 0 | Q80: =J80*G80 -> 0 | R80: =K80*G80 -> 0 | S80: =L80*G80 -> 0 | T80: =M80*G80 -> 0 | U80: =N80*G80 -> 0 | V80: =SUM(H80:N80) -> 0 | W80: =SUM(O80:U80) -> 0
E81: =D$5 -> ООО "Буровая компания "Евразия" | O81: =H81*G81 -> 0 | P81: =I81*G81 -> 0 | Q81: =J81*G81 -> 0 | R81: =K81*G81 -> 0 | S81: =L81*G81 -> 0 | T81: =M81*G81 -> 0 | U81: =N81*G81 -> 0 | V81: =SUM(H81:N81) -> 0 | W81: =SUM(O81:U81) -> 0
E82: =D$5 -> ООО "Буровая компания "Евразия" | O82: =H82*G82 -> 0 | P82: =I82*G82 -> 0 | Q82: =J82*G82 -> 0 | R82: =K82*G82 -> 0 | S82: =L82*G82 -> 0 | T82: =M82*G82 -> 0 | U82: =N82*G82 -> 0 | V82: =SUM(H82:N82) -> 0 | W82: =SUM(O82:U82) -> 0
E83: =D$5 -> ООО "Буровая компания "Евразия" | O83: =H83*G83 -> 0 | P83: =I83*G83 -> 0 | Q83: =J83*G83 -> 0 | R83: =K83*G83 -> 0 | S83: =L83*G83 -> 0 | T83: =M83*G83 -> 0 | U83: =N83*G83 -> 0 | V83: =SUM(H83:N83) -> 0 | W83: =SUM(O83:U83) -> 0
E84: =D$5 -> ООО "Буровая компания "Евразия" | O84: =H84*G84 -> 0 | P84: =I84*G84 -> 0 | Q84: =J84*G84 -> 0 | R84: =K84*G84 -> 0 | S84: =L84*G84 -> 0 | T84: =M84*G84 -> 0 | U84: =N84*G84 -> 0 | V84: =SUM(H84:N84) -> 0 | W84: =SUM(O84:U84) -> 0
E85: =D$5 -> ООО "Буровая компания "Евразия" | O85: =H85*G85 -> 0 | P85: =I85*G85 -> 0 | Q85: =J85*G85 -> 0 | R85: =K85*G85 -> 0 | S85: =L85*G85 -> 0 | T85: =M85*G85 -> 0 | U85: =N85*G85 -> 0 | V85: =SUM(H85:N85) -> 0 | W85: =SUM(O85:U85) -> 0
E86: =D$5 -> ООО "Буровая компания "Евразия" | O86: =H86*G86 -> 0 | P86: =I86*G86 -> 0 | Q86: =J86*G86 -> 0 | R86: =K86*G86 -> 0 | S86: =L86*G86 -> 0 | T86: =M86*G86 -> 0 | U86: =N86*G86 -> 0 | V86: =SUM(H86:N86) -> 0 | W86: =SUM(O86:U86) -> 0
E87: =D$5 -> ООО "Буровая компания "Евразия" | O87: =H87*G87 -> 0 | P87: =I87*G87 -> 0 | Q87: =J87*G87 -> 0 | R87: =K87*G87 -> 0 | S87: =L87*G87 -> 0 | T87: =M87*G87 -> 0 | U87: =N87*G87 -> 0 | V87: =SUM(H87:N87) -> 0 | W87: =SUM(O87:U87) -> 0
E88: =D$5 -> ООО "Буровая компания "Евразия" | O88: =H88*G88 -> 0 | P88: =I88*G88 -> 0 | Q88: =J88*G88 -> 0 | R88: =K88*G88 -> 0 | S88: =L88*G88 -> 0 | T88: =M88*G88 -> 0 | U88: =N88*G88 -> 0 | V88: =SUM(H88:N88) -> 0 | W88: =SUM(O88:U88) -> 0
E89: =D$5 -> ООО "Буровая компания "Евразия" | O89: =H89*G89 -> 0 | P89: =I89*G89 -> 0 | Q89: =J89*G89 -> 0 | R89: =K89*G89 -> 0 | S89: =L89*G89 -> 0 | T89: =M89*G89 -> 0 | U89: =N89*G89 -> 0 | V89: =SUM(H89:N89) -> 0 | W89: =SUM(O89:U89) -> 0
E90: =D$5 -> ООО "Буровая компания "Евразия" | O90: =H90*G90 -> 0 | P90: =I90*G90 -> 0 | Q90: =J90*G90 -> 0 | R90: =K90*G90 -> 0 | S90: =L90*G90 -> 0 | T90: =M90*G90 -> 0 | U90: =N90*G90 -> 0 | V90: =SUM(H90:N90) -> 0 | W90: =SUM(O90:U90) -> 0
E91: =D$5 -> ООО "Буровая компания "Евразия" | O91: =H91*G91 -> 0 | P91: =I91*G91 -> 0 | Q91: =J91*G91 -> 0 | R91: =K91*G91 -> 0 | S91: =L91*G91 -> 0 | T91: =M91*G91 -> 0 | U91: =N91*G91 -> 0 | V91: =SUM(H91:N91) -> 0 | W91: =SUM(O91:U91) -> 0
... E102: =D$5 -> ООО "Буровая компания "Евразия" | O102: =H102*G102 -> 0 | P102: =I102*G102 -> 0 | Q102: =J102*G102 -> 0 | R102: =K102*G102 -> 0 | S102: =L102*G102 -> 0 | T102: =M102*G102 -> 0 | U102: =N102*G102 -> 0 | V102: =SUM(H102:N102) -> 0 | W102: =SUM(O102:U102) -> 0
C103: ПОДРЯДЧИК ПО ДОЛОТАМ: | X103: =SUM(W105:W111) -> 1367128.9
D104: Описание работ/услуг
C105: Стоимость услуг по долотному сопровождению (долото + сервис) включая стоимость мобилизации и демобилизации | D105: 550 мм долото для бурения под направление (долото+сервис) | F105: м | G105: ='ГСЮра без пил МГРП'!G105 -> 168.57323 | O105: =H105*G105 -> 0 | P105: =I105*G105 -> 0 | Q105: =J105*G105 -> 0 | R105: =K105*G105 -> 0 | S105: =L105*G105 -> 0 | T105: =M105*G105 -> 0 | U105: =N105*G105 -> 0 | V105: =SUM(H105:N105) -> 0 | W105: =SUM(O105:U105) -> 0
D106: 393,7 мм долото для бурения под направление (долото+сервис) | F106: м | G106: ='ГСЮра без пил МГРП'!G106 -> 168.57323 | I106: =I7 -> 50 | O106: =H106*G106 -> 0 | P106: =I106*G106 -> 8428.6617 | Q106: =J106*G106 -> 0 | R106: =K106*G106 -> 0 | S106: =L106*G106 -> 0 | T106: =M106*G106 -> 0 | U106: =N106*G106 -> 0 | V106: =SUM(H106:N106) -> 50 | W106: =SUM(O106:U106) -> 8428.6617
D107: 295,3 мм долото для бурения под кондуктор (долото+сервис) | F107: м | G107: ='ГСЮра без пил МГРП'!G107 -> 168.57323 | J107: =J7 -> 460 | K107: =K7 -> 1200 | O107: =H107*G107 -> 0 | P107: =I107*G107 -> 0 | Q107: =J107*G107 -> 77543.688 | R107: =K107*G107 -> 202287.88 | S107: =L107*G107 -> 0 | T107: =M107*G107 -> 0 | U107: =N107*G107 -> 0 | V107: =SUM(H107:N107) -> 1660 | W107: =SUM(O107:U107) -> 279831.57
D108: 220,7 мм долото для бурения эксплуатационную колонну (долото+сервис) | F108: м | G108: ='ГСЮра без пил МГРП'!G108 -> 168.57323 | L108: =L7 -> 2700 | M108: =M7 -> 0 | N108: =N7+I11 -> 3700 | O108: =H108*G108 -> 0 | P108: =I108*G108 -> 0 | Q108: =J108*G108 -> 0 | R108: =K108*G108 -> 0 | S108: =L108*G108 -> 455147.73 | T108: =M108*G108 -> 0 | U108: =N108*G108 -> 623720.97 | V108: =SUM(H108:N108) -> 6400 | W108: =SUM(O108:U108) -> 1078868.7
D109: _________ мм долото для бурения под хвостовик (долото+сервис) | F109: м | O109: =H109*G109 -> 0 | P109: =I109*G109 -> 0 | Q109: =J109*G109 -> 0 | R109: =K109*G109 -> 0 | S109: =L109*G109 -> 0 | T109: =M109*G109 -> 0 | U109: =N109*G109 -> 0 | V109: =SUM(H109:N109) -> 0 | W109: =SUM(O109:U109) -> 0
D110: _________ мм долото для бурения (долото+сервис) | F110: м | O110: =H110*G110 -> 0 | P110: =I110*G110 -> 0 | Q110: =J110*G110 -> 0 | R110: =K110*G110 -> 0 | S110: =L110*G110 -> 0 | T110: =M110*G110 -> 0 | U110: =N110*G110 -> 0 | V110: =SUM(H110:N110) -> 0 | W110: =SUM(O110:U110) -> 0
D111: Расширитель раздвижной | F111: м | O111: =H111*G111 -> 0 | P111: =I111*G111 -> 0 | Q111: =J111*G111 -> 0 | R111: =K111*G111 -> 0 | S111: =L111*G111 -> 0 | T111: =M111*G111 -> 0 | U111: =N111*G111 -> 0 | V111: =SUM(H111:N111) -> 0 | W111: =SUM(O111:U111) -> 0
O112: =H112*G112 -> 0 | P112: =I112*G112 -> 0 | Q112: =J112*G112 -> 0 | R112: =K112*G112 -> 0 | S112: =L112*G112 -> 0 | T112: =M112*G112 -> 0 | U112: =N112*G112 -> 0 | V112: =SUM(H112:N112) -> 0 | W112: =SUM(O112:U112) -> 0
O113: =H113*G113 -> 0 | P113: =I113*G113 -> 0 | Q113: =J113*G113 -> 0 | R113: =K113*G113 -> 0 | S113: =L113*G113 -> 0 | T113: =M113*G113 -> 0 | U113: =N113*G113 -> 0 | V113: =SUM(H113:N113) -> 0 | W113: =SUM(O113:U113) -> 0
O114: =H114*G114 -> 0 | P114: =I114*G114 -> 0 | Q114: =J114*G114 -> 0 | R114: =K114*G114 -> 0 | S114: =L114*G114 -> 0 | T114: =M114*G114 -> 0 | U114: =N114*G114 -> 0 | V114: =SUM(H114:N114) -> 0 | W114: =SUM(O114:U114) -> 0
O115: =H115*G115 -> 0 | P115: =I115*G115 -> 0 | Q115: =J115*G115 -> 0 | R115: =K115*G115 -> 0 | S115: =L115*G115 -> 0 | T115: =M115*G115 -> 0 | U115: =N115*G115 -> 0 | V115: =SUM(H115:N115) -> 0 | W115: =SUM(O115:U115) -> 0
...

Sheet 2
A2: ПОДРОБНАЯ СМЕТНАЯ СТОИМОСТЬ СКВАЖИНЫ
C4: Месторождение/ куст: | D4: ='Титул '!$K$5 -> 3 куст Новопортовского месторождения | E4: ВСЕГО СТ-ТЬ | F4: Исходные данные | H4: Перед забуркой | I4: Направление | J4: Кондуктор | K4: Техническая колонна | L4: Эксплуат-ая колонна | M4: Крепление колонн | N4: Хвостовик | O4: ВСЕГО БУРЕНИЕ | P4: Исходные данные | R4: ВСЕГО ОСВОЕНИЕ
C5: Подрядчик по бурению: | D5: ='Титул '!$K$11 -> ООО "Буровая компания "Евразия" | E5: =D369 -> 0
C6: Тип буровой установки: | D6: ='Титул '!$K$12 -> ZJ-50 | E6: Всего ВМР | F6: Время бурения секции, сут: | O6: =SUM(I6:N6) -> 0 | P6: Время освоения, сут:
C7: Тип скважины: | D7: =CONCATENATE('Титул '!$C$29," ",'Титул '!$D$29," ",'Титул '!$E$29," ",'Титул '!$F$29," ",'Титул '!$G$29," ",'Титул '!$H$29," ",'Титул '!$J$29," ",'Титул '!$I$29) -> ГС | E7: =W69 -> 0 | F7: Глубина (по стволу), м: | O7: ВСЕГО ПРОХОДКА | P7: В т.ч.время работы бригад КРС
C8: Проходка всего (м): | E8: Всего Бурение | F8: Диаметр долота, мм: | P8: - ПЗР к ГРП/МСГРП, сут.
C9: Наличие СВП: | D9: ='Титул '!$K$13 -> 0 | E9: =W341 -> 0 | F9: Диаметр колонны, мм: | O9: =D8 -> 0 | P9: - проведение ГРП/МСГРП, сут.
C10: Наличие АИЭС: | D10: ='Титул '!$K$14 -> да | E10: Всего Освоение | F10: Исходные данные | H10: Отход | I10: Пилот ГС | J10: Перебур | K10: Гориз.уч. 1 | L10: Гориз.уч. 2 | M10: Керн | O10: ГЛУБИНА ПО ВЕРТ-ЛИ | P10: - проведение ГНКТ, сут.
C11: Наличие автономности: | D11: ='Титул '!$K$15 -> да | E11: =W361 -> 0 | F11: Отдельные стволы, керн, м: | P11: - кол-во стадий МСГРП, шт.
C12: Кол-во обсадных колонн (включая направл.): | D12: ='Титул '!I29 -> 0 | E12: Обор-ие устья | F12: Примечание: | P12: Примечание:
C13: Прочие существенные условия: | E13: =W367 -> 0
A15: ОПИСАНИЕ РАБОТ И УСЛУГ | H15: КОЛИЧЕСТВО | O15: СТОИМОСТЬ | V15: ВСЕГО
A16: КОД | B16: добавочный код | C16: СТАТЬЯ ЗАТРАТ | D16: ОПИСАНИЕ | E16: Подрядчик | F16: Единица измерения | G16: Руб. / Ед.изм. | H16: ПЗР (в т.ч. ВМР и осв.) | I16: =+I4 -> Направление | J16: =+J4 -> Кондуктор | K16: =+K4 -> Техническая колонна | L16: =+L4 -> Эксплуат-ая колонна | M16: Крепление колонн | N16: =+N4 -> Хвостовик | O16: ПЗР (в т.ч. ВМР и осв.) | P16: =+I16 -> Направление | Q16: =+J16 -> Кондуктор | R16: =+K16 -> Техническая колонна | S16: =+L16 -> Эксплуат-ая колонна | T16: Крепление колонн | U16: =+N16 -> Хвостовик | V16: Количество | W16: Стоимость (руб) | X16: ВСЕГО СТОИМОСТЬ
C18: 1. ЭТАП ВМР | X18: =SUM(W20:W68) -> 0
C19: ='Перв. скв '!C19 -> ООО "Буровая компания "Евразия" | D19: Описание работ/услуг
C20: ='Перв. скв '!C20 -> Работы, связанные с мобилизацией БУ (переездом), а так же прочего бурового оборудования и бригадного хозяйства, автономного источника энергоснабжения, материалов подрядчика и прочее. | D20: ='Перв. скв '!D20 -> Мобилизация БУ (переезд) | E20: ='Перв. скв '!E20 -> ООО "Буровая компания "Евразия" | F20: ='Перв. скв '!F20 -> операция | G20: ='Перв. скв '!G20 -> 1.2893274e+08 | O20: =H20*G20 -> 0 | V20: =SUM(H20:N20) -> 0 | W20: =SUM(O20:U20) -> 0
C21: ='Перв. скв '!C21 -> 0 | D21: ='Перв. скв '!D21 -> - мобилизация БУ (переезд) | E21: ='Перв. скв '!E21 -> ООО "Буровая компания "Евразия" | F21: ='Перв. скв '!F21 -> операция | G21: ='Перв. скв '!G21 -> 0 | O21: =H21*G21 -> 0 | V21: =SUM(H21:N21) -> 0 | W21: =SUM(O21:U21) -> 0
C22: ='Перв. скв '!C22 -> 0 | D22: ='Перв. скв '!D22 -> - мобилизация БХ и БИ (перевозка) | E22: ='Перв. скв '!E22 -> ООО "Буровая компания "Евразия" | F22: ='Перв. скв '!F22 -> операция | G22: ='Перв. скв '!G22 -> 0 | O22: =H22*G22 -> 0 | V22: =SUM(H22:N22) -> 0 | W22: =SUM(O22:U22) -> 0
C23: ='Перв. скв '!C23 -> 0 | D23: ='Перв. скв '!D23 -> - мобилизация АвИЭС (переезд) | E23: ='Перв. скв '!E23 -> ООО "Буровая компания "Евразия" | F23: ='Перв. скв '!F23 -> операция | G23: ='Перв. скв '!G23 -> 0 | O23: =H23*G23 -> 0 | V23: =SUM(H23:N23) -> 0 | W23: =SUM(O23:U23) -> 0
C24: ='Перв. скв '!C24 -> 0 | D24: ='Перв. скв '!D24 -> 0 | E24: ='Перв. скв '!E24 -> ООО "Буровая компания "Евразия" | F24: ='Перв. скв '!F24 -> операция | G24: ='Перв. скв '!G24 -> 0 | O24: =H24*G24 -> 0 | V24: =SUM(H24:N24) -> 0 | W24: =SUM(O24:U24) -> 0
C25: ='Перв. скв '!C25 -> 0 | D25: ='Перв. скв '!D25 -> 0 | E25: ='Перв. скв '!E25 -> ООО "Буровая компания "Евразия" | F25: ='Перв. скв '!F25 -> операция | G25: ='Перв. скв '!G25 -> 0 | O25: =H25*G25 -> 0 | V25: =SUM(H25:N25) -> 0 | W25: =SUM(O25:U25) -> 0
C26: ='Перв. скв '!C26 -> 0 | D26: ='Перв. скв '!D26 -> 0 | E26: ='Перв. скв '!E26 -> ООО "Буровая компания "Евразия" | F26: ='Перв. скв '!F26 -> операция | G26: ='Перв. скв '!G26 -> 0 | O26: =H26*G26 -> 0 | V26: =SUM(H26:N26) -> 0 | W26: =SUM(O26:U26) -> 0
C27: ='Перв. скв '!C27 -> 0 | D27: ='Перв. скв '!D27 -> 0 | E27: ='Перв. скв '!E27 -> ООО "Буровая компания "Евразия" | F27: ='Перв. скв '!F27 -> операция | G27: ='Перв. скв '!G27 -> 0 | O27: =H27*G27 -> 0 | V27: =SUM(H27:N27) -> 0 | W27: =SUM(O27:U27) -> 0
C28: ='Перв. скв '!C28 -> 0 | D28: ='Перв. скв '!D28 -> 0 | E28: ='Перв. скв '!E28 -> ООО "Буровая компания "Евразия" | F28: ='Перв. скв '!F28 -> операция | G28: ='Перв. скв '!G28 -> 0 | O28: =H28*G28 -> 0 | V28: =SUM(H28:N28) -> 0 | W28: =SUM(O28:U28) -> 0
C29: ='Перв. скв '!C29 -> Работы связанные со сборкой (монтажем) и подключением БУ, бурового и вспомогательного оборудования | D29: ='Перв. скв '!D29 -> Монтаж БУ | E29: ='Перв. скв '!E29 -> ООО "Буровая компания "Евразия" | F29: ='Перв. скв '!F29 -> операция | G29: ='Перв. скв '!G29 -> 0 | O29: =H29*G29 -> 0 | V29: =SUM(H29:N29) -> 0 | W29: =SUM(O29:U29) -> 0
C30: ='Перв. скв '!C30 -> 0 | D30: ='Перв. скв '!D30 -> - монтаж БУ | E30: ='Перв. скв '!E30 -> ООО "Буровая компания "Евразия" | F30: ='Перв. скв '!F30 -> операция | G30: ='Перв. скв '!G30 -> 0 | O30: =H30*G30 -> 0 | V30: =SUM(H30:N30) -> 0 | W30: =SUM(O30:U30) -> 0
C31: ='Перв. скв '!C31 -> 0 | D31: ='Перв. скв '!D31 -> - монтаж АвИЭС | E31: ='Перв. скв '!E31 -> ООО "Буровая компания "Евразия" | F31: ='Перв. скв '!F31 -> операция | G31: ='Перв. скв '!G31 -> 0 | O31: =H31*G31 -> 0 | V31: =SUM(H31:N31) -> 0 | W31: =SUM(O31:U31) -> 0
... C35: ='Перв. скв '!C35 -> 0 | D35: ='Перв. скв '!D35 -> 0 | E35: ='Перв. скв '!E35 -> ООО "Буровая компания "Евразия" | F35: ='Перв. скв '!F35 -> операция | G35: ='Перв. скв '!G35 -> 0 | O35: =H35*G35 -> 0 | V35: =SUM(H35:N35) -> 0 | W35: =SUM(O35:U35) -> 0
D36: ='Перв. скв '!D36 -> 0 | E36: ='Перв. скв '!E36 -> ООО "Буровая компания "Евразия" | F36: ='Перв. скв '!F36 -> операция | G36: ='Перв. скв '!G36 -> 0 | O36: =H36*G36 -> 0 | V36: =SUM(H36:N36) -> 0 | W36: =SUM(O36:U36) -> 0
C37: ='Перв. скв '!C37 -> 0 | D37: ='Перв. скв '!D37 -> 0 | E37: ='Перв. скв '!E37 -> ООО "Буровая компания "Евразия" | F37: ='Перв. скв '!F37 -> операция | G37: ='Перв. скв '!G37 -> 0 | O37: =H37*G37 -> 0 | V37: =SUM(H37:N37) -> 0 | W37: =SUM(O37:U37) -> 0
C38: ='Перв. скв '!C38 -> 0 | D38: ='Перв. скв '!D38 -> 0 | E38: ='Перв. скв '!E38 -> ООО "Буровая компания "Евразия" | F38: ='Перв. скв '!F38 -> операция | G38: ='Перв. скв '!G38 -> 0 | O38: =H38*G38 -> 0 | V38: =SUM(H38:N38) -> 0 | W38: =SUM(O38:U38) -> 0
C39: ='Перв. скв '!C39 -> Работы, свзянные с передвижкой БУ между скважинами на кустовой площадке | D39: ='Перв. скв '!D39 -> Передвижка 5 м. | E39: ='Перв. скв '!E39 -> ООО "Буровая компания "Евразия" | F39: ='Перв. скв '!F39 -> операция | G39: ='Перв. скв '!G39 -> 0 | O39: =H39*G39 -> 0 | V39: =SUM(H39:N39) -> 0 | W39: =SUM(O39:U39) -> 0
C40: ='Перв. скв '!C40 -> 0 | D40: ='Перв. скв '!D40 -> Передвижка 9 м. | E40: ='Перв. скв '!E40 -> ООО "Буровая компания "Евразия" | F40: ='Перв. скв '!F40 -> операция | G40: ='Перв. скв '!G40 -> 0 | O40: =H40*G40 -> 0 | V40: =SUM(H40:N40) -> 0 | W40: =SUM(O40:U40) -> 0
C41: ='Перв. скв '!C41 -> 0 | D41: ='Перв. скв '!D41 -> Передвижка 18 м. | E41: ='Перв. скв '!E41 -> ООО "Буровая компания "Евразия" | F41: ='Перв. скв '!F41 -> операция | G41: ='Перв. скв '!G41 -> 0 | O41: =H41*G41 -> 0 | V41: =SUM(H41:N41) -> 0 | W41: =SUM(O41:U41) -> 0
C42: ='Перв. скв '!C42 -> 0 | D42: ='Перв. скв '!D42 -> Передвижка 25 м. | E42: ='Перв. скв '!E42 -> ООО "Буровая компания "Евразия" | F42: ='Перв. скв '!F42 -> операция | G42: ='Перв. скв '!G42 -> 0 | O42: =H42*G42 -> 0 | V42: =SUM(H42:N42) -> 0 | W42: =SUM(O42:U42) -> 0
C43: ='Перв. скв '!C43 -> 0 | D43: ='Перв. скв '!D43 -> Передвижка 75 м. | E43: ='Перв. скв '!E43 -> ООО "Буровая компания "Евразия" | F43: ='Перв. скв '!F43 -> операция | G43: ='Перв. скв '!G43 -> 0 | O43: =H43*G43 -> 0 | V43: =SUM(H43:N43) -> 0 | W43: =SUM(O43:U43) -> 0
C44: ='Перв. скв '!C44 -> 0 | D44: ='Перв. скв '!D44 -> Передвижка нестандартная | E44: ='Перв. скв '!E44 -> ООО "Буровая компания "Евразия" | F44: ='Перв. скв '!F44 -> операция | G44: ='Перв. скв '!G44 -> 0 | O44: =H44*G44 -> 0 | V44: =SUM(H44:N44) -> 0 | W44: =SUM(O44:U44) -> 0
C45: ='Перв. скв '!C45 -> Работы связанные с демонтажем БУ, бурового и вспомогательного оборудования | D45: ='Перв. скв '!D45 -> Демонтаж БУ | E45: ='Перв. скв '!E45 -> ООО "Буровая компания "Евразия" | F45: ='Перв. скв '!F45 -> операция | G45: ='Перв. скв '!G45 -> 0 | O45: =H45*G45 -> 0 | V45: =SUM(H45:N45) -> 0 | W45: =SUM(O45:U45) -> 0
C46: ='Перв. скв '!C46 -> 0 | D46: ='Перв. скв '!D46 -> - демонтаж БУ | E46: ='Перв. скв '!E46 -> ООО "Буровая компания "Евразия" | F46: ='Перв. скв '!F46 -> операция | G46: ='Перв. скв '!G46 -> 0 | O46: =H46*G46 -> 0 | V46: =SUM(H46:N46) -> 0 | W46: =SUM(O46:U46) -> 0
C47: ='Перв. скв '!C47 -> 0 | D47: ='Перв. скв '!D47 -> - демонтаж АвИЭС | E47: ='Перв. скв '!E47 -> ООО "Буровая компания "Евразия" | F47: ='Перв. скв '!F47 -> операция | G47: ='Перв. скв '!G47 -> 0 | O47: =H47*G47 -> 0 | V47: =SUM(H47:N47) -> 0 | W47: =SUM(O47:U47) -> 0
C48: ='Перв. скв '!C48 -> 0 | D48: ='Перв. скв '!D48 -> - демонтаж БДЕ, ПВО | E48: ='Перв. скв '!E48 -> ООО "Буровая компания "Евразия" | F48: ='Перв. скв '!F48 -> операция | G48: ='Перв. скв '!G48 -> 0 | O48: =H48*G48 -> 0 | V48: =SUM(H48:N48) -> 0 | W48: =SUM(O48:U48) -> 0
... C68: ='Перв. скв '!C68 -> 0 | D68: ='Перв. скв '!D68 -> 0 | E68: ='Перв. скв '!E68 -> ООО "Буровая компания "Евразия" | F68: ='Перв. скв '!F68 -> операция | G68: ='Перв. скв '!G68 -> 0 | O68: =H68*G68 -> 0 | V68: =SUM(H68:N68) -> 0 | W68: =SUM(O68:U68) -> 0
C69: ОБЩАЯ СТОИМОСТЬ ВМР | D69: =W69 -> 0 | O69: =SUM(O20:O68) -> 0 | W69: =SUM(W20:W68) -> 0
C71: 2. ЭТАП БУРЕНИЯ: | X71: =SUM(W73:W102) -> 0
C72: ='Перв. скв '!C72 -> ООО "Буровая компания "Евразия" | D72: Описание работ/услуг
C73: ='Перв. скв '!C73 -> Стоимость работ буровой бригады, а так же стоимость услуг АвИЭС | D73: ='Перв. скв '!D73 -> Суточная ставка работы буровой бригады | E73: ='Перв. скв '!E73 -> ООО "Буровая компания "Евразия" | F73: ='Перв. скв '!F73 -> сут | G73: ='Перв. скв '!G73 -> 1428908.8 | O73: =H73*G73 -> 0 | P73: =I73*G73 -> 0 | Q73: =J73*G73 -> 0 | R73: =K73*G73 -> 0 | S73: =L73*G73 -> 0 | T73: =M73*G73 -> 0 | U73: =N73*G73 -> 0 | V73: =SUM(H73:N73) -> 0 | W73: =SUM(O73:U73) -> 0
D74: ='Перв. скв '!D74 -> Оплата по резервной ставке | E74: ='Перв. скв '!E74 -> ООО "Буровая компания "Евразия" | F74: ='Перв. скв '!F74 -> сут | G74: ='Перв. скв '!G74 -> 0 | O74: =H74*G74 -> 0 | P74: =I74*G74 -> 0 | Q74: =J74*G74 -> 0 | R74: =K74*G74 -> 0 | S74: =L74*G74 -> 0 | T74: =M74*G74 -> 0 | U74: =N74*G74 -> 0 | V74: =SUM(H74:N74) -> 0 | W74: =SUM(O74:U74) -> 0
D75: ='Перв. скв '!D75 -> Оплата по ставке дежурства | E75: ='Перв. скв '!E75 -> ООО "Буровая компания "Евразия" | F75: ='Перв. скв '!F75 -> сут | G75: ='Перв. скв '!G75 -> 0 | O75: =H75*G75 -> 0 | P75: =I75*G75 -> 0 | Q75: =J75*G75 -> 0 | R75: =K75*G75 -> 0 | S75: =L75*G75 -> 0 | T75: =M75*G75 -> 0 | U75: =N75*G75 -> 0 | V75: =SUM(H75:N75) -> 0 | W75: =SUM(O75:U75) -> 0
D76: ='Перв. скв '!D76 -> Монт/демонт ПВО и ФА, доп.работы | E76: ='Перв. скв '!E76 -> ООО "Буровая компания "Евразия" | F76: ='Перв. скв '!F76 -> сут | G76: ='Перв. скв '!G76 -> 0 | O76: =H76*G76 -> 0 | P76: =I76*G76 -> 0 | Q76: =J76*G76 -> 0 | R76: =K76*G76 -> 0 | S76: =L76*G76 -> 0 | T76: =M76*G76 -> 0 | U76: =N76*G76 -> 0 | V76: =SUM(H76:N76) -> 0 | W76: =SUM(O76:U76) -> 0
D77: ='Перв. скв '!D77 -> Суточная ставка АвИЭС | E77: ='Перв. скв '!E77 -> ООО "Буровая компания "Евразия" | F77: ='Перв. скв '!F77 -> сут | G77: ='Перв. скв '!G77 -> 103909.96 | O77: =H77*G77 -> 0 | P77: =I77*G77 -> 0 | Q77: =J77*G77 -> 0 | R77: =K77*G77 -> 0 | S77: =L77*G77 -> 0 | T77: =M77*G77 -> 0 | U77: =N77*G77 -> 0 | V77: =SUM(H77:N77) -> 0 | W77: =SUM(O77:U77) -> 0
D78: ='Перв. скв '!D78 -> Ставка дежурства АвИЭС | E78: ='Перв. скв '!E78 -> ООО "Буровая компания "Евразия" | F78: ='Перв. скв '!F78 -> сут | G78: ='Перв. скв '!G78 -> 0 | O78: =H78*G78 -> 0 | P78: =I78*G78 -> 0 | Q78: =J78*G78 -> 0 | R78: =K78*G78 -> 0 | S78: =L78*G78 -> 0 | T78: =M78*G78 -> 0 | U78: =N78*G78 -> 0 | V78: =SUM(H78:N78) -> 0 | W78: =SUM(O78:U78) -> 0
D79: ='Перв. скв '!D79 -> Прочее | E79: ='Перв. скв '!E79 -> ООО "Буровая компания "Евразия" | F79: ='Перв. скв '!F79 -> 0 | G79: ='Перв. скв '!G79 -> 5091597.6 | O79: =H79*G79 -> 0 | P79: =I79*G79 -> 0 | Q79: =J79*G79 -> 0 | R79: =K79*G79 -> 0 | S79: =L79*G79 -> 0 | T79: =M79*G79 -> 0 | U79: =N79*G79 -> 0 | V79: =SUM(H79:N79) -> 0 | W79: =SUM(O79:U79) -> 0
D80: ='Перв. скв '!D80 -> 0 | E80: ='Перв. скв '!E80 -> ООО "Буровая компания "Евразия" | F80: ='Перв. скв '!F80 -> 0 | G80: ='Перв. скв '!G80 -> 0 | O80: =H80*G80 -> 0 | P80: =I80*G80 -> 0 | Q80: =J80*G80 -> 0 | R80: =K80*G80 -> 0 | S80: =L80*G80 -> 0 | T80: =M80*G80 -> 0 | U80: =N80*G80 -> 0 | V80: =SUM(H80:N80) -> 0 | W80: =SUM(O80:U80) -> 0
D81: ='Перв. скв '!D81 -> 0 | E81: ='Перв. скв '!E81 -> ООО "Буровая компания "Евразия" | F81: ='Перв. скв '!F81 -> 0 | G81: ='Перв. скв '!G81 -> 0 | O81: =H81*G81 -> 0 | P81: =I81*G81 -> 0 | Q81: =J81*G81 -> 0 | R81: =K81*G81 -> 0 | S81: =L81*G81 -> 0 | T81: =M81*G81 -> 0 | U81: =N81*G81 -> 0 | V81: =SUM(H81:N81) -> 0 | W81: =SUM(O81:U81) -> 0
D82: ='Перв. скв '!D82 -> 0 | E82: ='Перв. скв '!E82 -> ООО "Буровая компания "Евразия" | F82: ='Перв. скв '!F82 -> 0 | G82: ='Перв. скв '!G82 -> 0 | O82: =H82*G82 -> 0 | P82: =I82*G82 -> 0 | Q82: =J82*G82 -> 0 | R82: =K82*G82 -> 0 | S82: =L82*G82 -> 0 | T82: =M82*G82 -> 0 | U82: =N82*G82 -> 0 | V82: =SUM(H82:N82) -> 0 | W82: =SUM(O82:U82) -> 0
D83: ='Перв. скв '!D83 -> 0 | E83: ='Перв. скв '!E83 -> ООО "Буровая компания "Евразия" | F83: ='Перв. скв '!F83 -> 0 | G83: ='Перв. скв '!G83 -> 0 | O83: =H83*G83 -> 0 | P83: =I83*G83 -> 0 | Q83: =J83*G83 -> 0 | R83: =K83*G83 -> 0 | S83: =L83*G83 -> 0 | T83: =M83*G83 -> 0 | U83: =N83*G83 -> 0 | V83: =SUM(H83:N83) -> 0 | W83: =SUM(O83:U83) -> 0
D84: ='Перв. скв '!D84 -> 0 | E84: ='Перв. скв '!E84 -> ООО "Буровая компания "Евразия" | F84: ='Перв. скв '!F84 -> 0 | G84: ='Перв. скв '!G84 -> 0 | O84: =H84*G84 -> 0 | P84: =I84*G84 -> 0 | Q84: =J84*G84 -> 0 | R84: =K84*G84 -> 0 | S84: =L84*G84 -> 0 | T84: =M84*G84 -> 0 | U84: =N84*G84 -> 0 | V84: =SUM(H84:N84) -> 0 | W84: =SUM(O84:U84) -> 0
D85: ='Перв. скв '!D85 -> 0 | E85: ='Перв. скв '!E85 -> ООО "Буровая компания "Евразия" | F85: ='Перв. скв '!F85 -> 0 | G85: ='Перв. скв '!G85 -> 0 | O85: =H85*G85 -> 0 | P85: =I85*G85 -> 0 | Q85: =J85*G85 -> 0 | R85: =K85*G85 -> 0 | S85: =L85*G85 -> 0 | T85: =M85*G85 -> 0 | U85: =N85*G85 -> 0 | V85: =SUM(H85:N85) -> 0 | W85: =SUM(O85:U85) -> 0
... D102: ='Перв. скв '!D102 -> 0 | E102: ='Перв. скв '!E102 -> ООО "Буровая компания "Евразия" | F102: ='Перв. скв '!F102 -> 0 | G102: ='Перв. скв '!G102 -> 0 | O102: =H102*G102 -> 0 | P102: =I102*G102 -> 0 | Q102: =J102*G102 -> 0 | R102: =K102*G102 -> 0 | S102: =L102*G102 -> 0 | T102: =M102*G102 -> 0 | U102: =N102*G102 -> 0 | V102: =SUM(H102:N102) -> 0 | W102: =SUM(O102:U102) -> 0
C103: ПОДРЯДЧИК ПО ДОЛОТАМ: | X103: =SUM(W105:W111) -> 0
C104: ='Перв. скв '!C104 -> 0 | D104: Описание работ/услуг
C105: ='Перв. скв '!C105 -> Стоимость услуг по долотному сопровождению (долото + сервис) включая стоимость мобилизации и демобилизации | D105: ='Перв. скв '!D105 -> 550 мм долото для бурения под направление (долото+сервис) | E105: ='Перв. скв '!E105 -> 0 | F105: ='Перв. скв '!F105 -> м | G105: ='Перв. скв '!G105 -> 168.57323 | O105: =H105*G105 -> 0 | P105: =I105*G105 -> 0 | Q105: =J105*G105 -> 0 | R105: =K105*G105 -> 0 | S105: =L105*G105 -> 0 | T105: =M105*G105 -> 0 | U105: =N105*G105 -> 0 | V105: =SUM(H105:N105) -> 0 | W105: =SUM(O105:U105) -> 0
D106: ='Перв. скв '!D106 -> 393,7 мм долото для бурения под направление (долото+сервис) | E106: ='Перв. скв '!E106 -> 0 | F106: ='Перв. скв '!F106 -> м | G106: ='Перв. скв '!G106 -> 168.57323 | O106: =H106*G106 -> 0 | P106: =I106*G106 -> 0 | Q106: =J106*G106 -> 0 | R106: =K106*G106 -> 0 | S106: =L106*G106 -> 0 | T106: =M106*G106 -> 0 | U106: =N106*G106 -> 0 | V106: =SUM(H106:N106) -> 0 | W106: =SUM(O106:U106) -> 0
D107: ='Перв. скв '!D107 -> 295,3 мм долото для бурения под кондуктор (долото+сервис) | E107: ='Перв. скв '!E107 -> 0 | F107: ='Перв. скв '!F107 -> м | G107: ='Перв. скв '!G107 -> 168.57323 | O107: =H107*G107 -> 0 | P107: =I107*G107 -> 0 | Q107: =J107*G107 -> 0 | R107: =K107*G107 -> 0 | S107: =L107*G107 -> 0 | T107: =M107*G107 -> 0 | U107: =N107*G107 -> 0 | V107: =SUM(H107:N107) -> 0 | W107: =SUM(O107:U107) -> 0
D108: ='Перв. скв '!D108 -> 220,7 мм долото для бурения эксплуатационную колонну (долото+сервис) | E108: ='Перв. скв '!E108 -> 0 | F108: ='Перв. скв '!F108 -> м | G108: ='Перв. скв '!G108 -> 168.57323 | O108: =H108*G108 -> 0 | P108: =I108*G108 -> 0 | Q108: =J108*G108 -> 0 | R108: =K108*G108 -> 0 | S108: =L108*G108 -> 0 | T108: =M108*G108 -> 0 | U108: =N108*G108 -> 0 | V108: =SUM(H108:N108) -> 0 | W108: =SUM(O108:U108) -> 0
D109: ='Перв. скв '!D109 -> _________ мм долото для бурения под хвостовик (долото+сервис) | E109: ='Перв. скв '!E109 -> 0 | F109: ='Перв. скв '!F109 -> м | G109: ='Перв. скв '!G109 -> 0 | O109: =H109*G109 -> 0 | P109: =I109*G109 -> 0 | Q109: =J109*G109 -> 0 | R109: =K109*G109 -> 0 | S109: =L109*G109 -> 0 | T109: =M109*G109 -> 0 | U109: =N109*G109 -> 0 | V109: =SUM(H109:N109) -> 0 | W109: =SUM(O109:U109) -> 0
D110: ='Перв. скв '!D110 -> _________ мм долото для бурения (долото+сервис) | E110: ='Перв. скв '!E110 -> 0 | F110: ='Перв. скв '!F110 -> м | G110: ='Перв. скв '!G110 -> 0 | O110: =H110*G110 -> 0 | P110: =I110*G110 -> 0 | Q110: =J110*G110 -> 0 | R110: =K110*G110 -> 0 | S110: =L110*G110 -> 0 | T110: =M110*G110 -> 0 | U110: =N110*G110 -> 0 | V110: =SUM(H110:N110) -> 0 | W110: =SUM(O110:U110) -> 0
D111: ='Перв. скв '!D111 -> Расширитель раздвижной | E111: ='Перв. скв '!E111 -> 0 | F111: ='Перв. скв '!F111 -> м | G111: ='Перв. скв '!G111 -> 0 | O111: =H111*G111 -> 0 | P111: =I111*G111 -> 0 | Q111: =J111*G111 -> 0 | R111: =K111*G111 -> 0 | S111: =L111*G111 -> 0 | T111: =M111*G111 -> 0 | U111: =N111*G111 -> 0 | V111: =SUM(H111:N111) -> 0 | W111: =SUM(O111:U111) -> 0
D112: ='Перв. скв '!D112 -> 0 | E112: ='Перв. скв '!E112 -> 0 | F112: ='Перв. скв '!F112 -> 0 | G112: ='Перв. скв '!G112 -> 0 | O112: =H112*G112 -> 0 | P112: =I112*G112 -> 0 | Q112: =J112*G112 -> 0 | R112: =K112*G112 -> 0 | S112: =L112*G112 -> 0 | T112: =M112*G112 -> 0 | U112: =N112*G112 -> 0 | V112: =SUM(H112:N112) -> 0 | W112: =SUM(O112:U112) -> 0
D113: ='Перв. скв '!D113 -> 0 | E113: ='Перв. скв '!E113 -> 0 | F113: ='Перв. скв '!F113 -> 0 | G113: ='Перв. скв '!G113 -> 0 | O113: =H113*G113 -> 0 | P113: =I113*G113 -> 0 | Q113: =J113*G113 -> 0 | R113: =K113*G113 -> 0 | S113: =L113*G113 -> 0 | T113: =M113*G113 -> 0 | U113: =N113*G113 -> 0 | V113: =SUM(H113:N113) -> 0 | W113: =SUM(O113:U113) -> 0
D114: ='Перв. скв '!D114 -> 0 | E114: ='Перв. скв '!E114 -> 0 | F114: ='Перв. скв '!F114 -> 0 | G114: ='Перв. скв '!G114 -> 0 | O114: =H114*G114 -> 0 | P114: =I114*G114 -> 0 | Q114: =J114*G114 -> 0 | R114: =K114*G114 -> 0 | S114: =L114*G114 -> 0 | T114: =M114*G114 -> 0 | U114: =N114*G114 -> 0 | V114: =SUM(H114:N114) -> 0 | W114: =SUM(O114:U114) -> 0
D115: ='Перв. скв '!D115 -> 0 | E115: ='Перв. скв '!E115 -> 0 | F115: ='Перв. скв '!F115 -> 0 | G115: ='Перв. скв '!G115 -> 0 | O115: =H115*G115 -> 0 | P115: =I115*G115 -> 0 | Q115: =J115*G115 -> 0 | R115: =K115*G115 -> 0 | S115: =L115*G115 -> 0 | T115: =M115*G115 -> 0 | U115: =N115*G115 -> 0 | V115: =SUM(H115:N115) -> 0 | W115: =SUM(O115:U115) -> 0
D116: ='Перв. скв '!D116 -> 0 | E116: ='Перв. скв '!E116 -> 0 | F116: ='Перв. скв '!F116 -> 0 | G116: ='Перв. скв '!G116 -> 0 | O116: =H116*G116 -> 0 | P116: =I116*G116 -> 0 | Q116: =J116*G116 -> 0 | R116: =K116*G116 -> 0 | S116: =L116*G116 -> 0 | T116: =M116*G116 -> 0 | U116: =N116*G116 -> 0 | V116: =SUM(H116:N116) -> 0 | W116: =SUM(O116:U116) -> 0
D117: ='Перв. скв '!D117 -> 0 | E117: ='Перв. скв '!E117 -> 0 | F117: ='Перв. скв '!F117 -> 0 | G117: ='Перв. скв '!G117 -> 0 | O117: =H117*G117 -> 0 | P117: =I117*G117 -> 0 | Q117: =J117*G117 -> 0 | R117: =K117*G117 -> 0 | S117: =L117*G117 -> 0 | T117: =M117*G117 -> 0 | U117: =N117*G117 -> 0 | V117: =SUM(H117:N117) -> 0 | W117: =SUM(O117:U117) -> 0
... D119: ='Перв. скв '!D119 -> 0 | E119: ='Перв. скв '!E119 -> 0 | F119: ='Перв. скв '!F119 -> 0 | G119: ='Перв. скв '!G119 -> 0 | O119: =H119*G119 -> 0 | P119: =I119*G119 -> 0 | Q119: =J119*G119 -> 0 | R119: =K119*G119 -> 0 | S119: =L119*G119 -> 0 | T119: =M119*G119 -> 0 | U119: =N119*G119 -> 0 | V119: =SUM(H119:N119) -> 0 | W119: =SUM(O119:U119) -> 0
C120: ПОДРЯДЧИК ПО ТЕХНОЛОГИЧЕСКОМУ И ТЕЛЕМЕТРИЧЕСКОМУ СОПРОВОЖДЕНИЮ: | X120: =SUM(W122:W144) -> 0
C121: ='Перв. скв '!C121 -> 0 | D121: Описание работ/услуг
C122: ='Перв. скв '!C122 -> Услуги направленного бурения и телеметрии (включая ГЗД) - стоимость аренды оборудования и услуг соответствующего персонала для направленного бурения, услуги ГИС/измерений во время бурения (MWD, LWD и услуги персонала) | D122: ='Перв. скв '!D122 -> Ставка работы по ННБ для секции скважин диаметром 393,7 мм. | E122: ='Перв. скв '!E122 -> 0 | F122: ='Перв. скв '!F122 -> сут | G122: ='Перв. скв '!G122 -> 324000 | O122: =H122*G122 -> 0 | P122: =I122*G122 -> 0 | Q122: =J122*G122 -> 0 | R122: =K122*G122 -> 0 | S122: =L122*G122 -> 0 | T122: =M122*G122 -> 0 | U122: =N122*G122 -> 0 | V122: =SUM(H122:N122) -> 0 | W122: =SUM(O122:U122) -> 0
D123: ='Перв. скв '!D123 -> Резервная ставка по ННБ для секций скважин диаметром 393,7 мм. | E123: ='Перв. скв '!E123 -> 0 | F123: ='Перв. скв '!F123 -> сут | G123: ='Перв. скв '!G123 -> 32400 | O123: =H123*G123 -> 0 | P123: =I123*G123 -> 0 | Q123: =J123*G123 -> 0 | R123: =K123*G123 -> 0 | S123: =L123*G123 -> 0 | T123: =M123*G123 -> 0 | U123: =N123*G123 -> 0 | V123: =SUM(H123:N123) -> 0 | W123: =SUM(O123:U123) -> 0
D124: ='Перв. скв '!D124 -> Ставка работы по ННБ для секции скважин диаметром 295,3 мм. | E124: ='Перв. скв '!E124 -> 0 | F124: ='Перв. скв '!F124 -> сут | G124: ='Перв. скв '!G124 -> 335000 | O124: =H124*G124 -> 0 | P124: =I124*G124 -> 0 | Q124: =J124*G124 -> 0 | R124: =K124*G124 -> 0 | S124: =L124*G124 -> 0 | T124: =M124*G124 -> 0 | U124: =N124*G124 -> 0 | V124: =SUM(H124:N124) -> 0 | W124: =SUM(O124:U124) -> 0
D125: ='Перв. скв '!D125 -> Резервная ставка по ННБ для секций скважин диаметром 295,3 мм. | E125: ='Перв. скв '!E125 -> 0 | F125: ='Перв. скв '!F125 -> сут | G125: ='Перв. скв '!G125 -> 33500 | O125: =H125*G125 -> 0 | P125: =I125*G125 -> 0 | Q125: =J125*G125 -> 0 | R125: =K125*G125 -> 0 | S125: =L125*G125 -> 0 | T125: =M125*G125 -> 0 | U125: =N125*G125 -> 0 | V125: =SUM(H125:N125) -> 0 | W125: =SUM(O125:U125) -> 0
D126: ='Перв. скв '!D126 -> Ставка работы по ННБ для секции скважин диаметром 220,7 мм. | E126: ='Перв. скв '!E126 -> 0 | F126: ='Перв. скв '!F126 -> сут | G126: ='Перв. скв '!G126 -> 539000 | O126: =H126*G126 -> 0 | P126: =I126*G126 -> 0 | Q126: =J126*G126 -> 0 | R126: =K126*G126 -> 0 | S126: =L126*G126 -> 0 | T126: =M126*G126 -> 0 | U126: =N126*G126 -> 0 | V126: =SUM(H126:N126) -> 0 | W126: =SUM(O126:U126) -> 0
D127: ='Перв. скв '!D127 -> Резервная ставка по ННБ для секций скважин диаметром 220,7 мм. | E127: ='Перв. скв '!E127 -> 0 | F127: ='Перв. скв '!F127 -> сут | G127: ='Перв. скв '!G127 -> 53900 | O127: =H127*G127 -> 0 | P127: =I127*G127 -> 0 | Q127: =J127*G127 -> 0 | R127: =K127*G127 -> 0 | S127: =L127*G127 -> 0 | T127: =M127*G127 -> 0 | U127: =N127*G127 -> 0 | V127: =SUM(H127:N127) -> 0 | W127: =SUM(O127:U127) -> 0
D128: ='Перв. скв '!D128 -> Ставка работы по ННБ для секции скважин диаметром 220,7 мм.+ГК | E128: ='Перв. скв '!E128 -> 0 | F128: ='Перв. скв '!F128 -> сут | G128: ='Перв. скв '!G128 -> 948484.8 | O128: =H128*G128 -> 0 | P128: =I128*G128 -> 0 | Q128: =J128*G128 -> 0 | R128: =K128*G128 -> 0 | S128: =L128*G128 -> 0 | T128: =M128*G128 -> 0 | U128: =N128*G128 -> 0 | V128: =SUM(H128:N128) -> 0 | W128: =SUM(O128:U128) -> 0
D129: ='Перв. скв '!D129 -> Ставка работы по ННБ для секции скважин диаметром 155,6 мм. | E129: ='Перв. скв '!E129 -> 0 | F129: ='Перв. скв '!F129 -> сут | G129: ='Перв. скв '!G129 -> 815000 | O129: =H129*G129 -> 0 | P129: =I129*G129 -> 0 | Q129: =J129*G129 -> 0 | R129: =K129*G129 -> 0 | S129: =L129*G129 -> 0 | T129: =M129*G129 -> 0 | U129: =N129*G129 -> 0 | V129: =SUM(H129:N129) -> 0 | W129: =SUM(O129:U129) -> 0
D130: ='Перв. скв '!D130 -> Резервная ставка по ННБ для секций скважин диаметром 155,6 мм. | E130: ='Перв. скв '!E130 -> 0 | F130: ='Перв. скв '!F130 -> сут | G130: ='Перв. скв '!G130 -> 121500 | O130: =H130*G130 -> 0 | P130: =I130*G130 -> 0 | Q130: =J130*G130 -> 0 | R130: =K130*G130 -> 0 | S130: =L130*G130 -> 0 | T130: =M130*G130 -> 0 | U130: =N130*G130 -> 0 | V130: =SUM(H130:N130) -> 0 | W130: =SUM(O130:U130) -> 0
D131: ='Перв. скв '!D131 -> Мобилизация и демобилизация на объект работ | E131: ='Перв. скв '!E131 -> 0 | F131: ='Перв. скв '!F131 -> операция | G131: ='Перв. скв '!G131 -> 3577128.6 | O131: =H131*G131 -> 0 | P131: =I131*G131 -> 0 | Q131: =J131*G131 -> 0 | R131: =K131*G131 -> 0 | S131: =L131*G131 -> 0 | T131: =M131*G131 -> 0 | U131: =N131*G131 -> 0 | V131: =SUM(H131:N131) -> 0 | W131: =SUM(O131:U131) -> 0
D132: ='Перв. скв '!D132 -> 0 | E132: ='Перв. скв '!E132 -> 0 | F132: ='Перв. скв '!F132 -> операция | G132: ='Перв. скв '!G132 -> 0 | O132: =H132*G132 -> 0 | P132: =I132*G132 -> 0 | Q132: =J132*G132 -> 0 | R132: =K132*G132 -> 0 | S132: =L132*G132 -> 0 | T132: =M132*G132 -> 0 | U132: =N132*G132 -> 0 | V132: =SUM(H132:N132) -> 0 | W132: =SUM(O132:U132) -> 0
D133: ='Перв. скв '!D133 -> 0 | E133: ='Перв. скв '!E133 -> 0 | F133: ='Перв. скв '!F133 -> 0 | G133: ='Перв. скв '!G133 -> 0 | O133: =H133*G133 -> 0 | P133: =I133*G133 -> 0 | Q133: =J133*G133 -> 0 | R133: =K133*G133 -> 0 | S133: =L133*G133 -> 0 | T133: =M133*G133 -> 0 | U133: =N133*G133 -> 0 | V133: =SUM(H133:N133) -> 0 | W133: =SUM(O133:U133) -> 0
D134: ='Перв. скв '!D134 -> 0 | E134: ='Перв. скв '!E134 -> 0 | F134: ='Перв. скв '!F134 -> 0 | G134: ='Перв. скв '!G134 -> 0 | O134: =H134*G134 -> 0 | P134: =I134*G134 -> 0 | Q134: =J134*G134 -> 0 | R134: =K134*G134 -> 0 | S134: =L134*G134 -> 0 | T134: =M134*G134 -> 0 | U134: =N134*G134 -> 0 | V134: =SUM(H134:N134) -> 0 | W134: =SUM(O134:U134) -> 0
... D136: ='Перв. скв '!D136 -> 0 | E136: ='Перв. скв '!E136 -> 0 | F136: ='Перв. скв '!F136 -> 0 | G136: ='Перв. скв '!G136 -> 0 | O136: =H136*G136 -> 0 | P136: =I136*G136 -> 0 | Q136: =J136*G136 -> 0 | R136: =K136*G136 -> 0 | S136: =L136*G136 -> 0 | T136: =M136*G136 -> 0 | U136: =N136*G136 -> 0 | V136: =SUM(H136:N136) -> 0 | W136: =SUM(O136:U136) -> 0
C137: ='Перв. скв '!C137 -> 0 | D137: Описание работ/услуг
C138: ='Перв. скв '!C138 -> Услуги направленного бурения и телеметрии (включая ГЗД) - стоимость аренды оборудования и услуг соответствующего персонала для направленного бурения, услуги ГИС/измерений во время бурения (MWD, LWD и услуги персонала) | D138: ='Перв. скв '!D138 -> Операционная ставка в режиме работы | E138: ='Перв. скв '!E138 -> 0 | F138: ='Перв. скв '!F138 -> сут | G138: ='Перв. скв '!G138 -> 0 | O138: =H138*G138 -> 0 | P138: =I138*G138 -> 0 | Q138: =J138*G138 -> 0 | R138: =K138*G138 -> 0 | S138: =L138*G138 -> 0 | T138: =M138*G138 -> 0 | U138: =N138*G138 -> 0 | V138: =SUM(H138:N138) -> 0 | W138: =SUM(O138:U138) -> 0
D139: ='Перв. скв '!D139 -> Операционная ставка в режиме ожидания | E139: ='Перв. скв '!E139 -> 0 | F139: ='Перв. скв '!F139 -> сут | G139: ='Перв. скв '!G139 -> 0 | O139: =H139*G139 -> 0 | P139: =I139*G139 -> 0 | Q139: =J139*G139 -> 0 | R139: =K139*G139 -> 0 | S139: =L139*G139 -> 0 | T139: =M139*G139 -> 0 | U139: =N139*G139 -> 0 | V139: =SUM(H139:N139) -> 0 | W139: =SUM(O139:U139) -> 0
D140: ='Перв. скв '!D140 -> Гамма -каротаж и сопротивление в режиме записи | E140: ='Перв. скв '!E140 -> 0 | F140: ='Перв. скв '!F140 -> сут | G140: ='Перв. скв '!G140 -> 0 | O140: =H140*G140 -> 0 | P140: =I140*G140 -> 0 | Q140: =J140*G140 -> 0 | R140: =K140*G140 -> 0 | S140: =L140*G140 -> 0 | T140: =M140*G140 -> 0 | U140: =N140*G140 -> 0 | V140: =SUM(H140:N140) -> 0 | W140: =SUM(O140:U140) -> 0
D141: ='Перв. скв '!D141 -> Гамма -каротаж и сопротивление в режиме реаьного времени | E141: ='Перв. скв '!E141 -> 0 | F141: ='Перв. скв '!F141 -> сут | G141: ='Перв. скв '!G141 -> 0 | O141: =H141*G141 -> 0 | P141: =I141*G141 -> 0 | Q141: =J141*G141 -> 0 | R141: =K141*G141 -> 0 | S141: =L141*G141 -> 0 | T141: =M141*G141 -> 0 | U141: =N141*G141 -> 0 | V141: =SUM(H141:N141) -> 0 | W141: =SUM(O141:U141) -> 0
D142: ='Перв. скв '!D142 -> Гамма -каротаж в режиме записи | E142: ='Перв. скв '!E142 -> 0 | F142: ='Перв. скв '!F142 -> сут | G142: ='Перв. скв '!G142 -> 0 | O142: =H142*G142 -> 0 | P142: =I142*G142 -> 0 | Q142: =J142*G142 -> 0 | R142: =K142*G142 -> 0 | S142: =L142*G142 -> 0 | T142: =M142*G142 -> 0 | U142: =N142*G142 -> 0 | V142: =SUM(H142:N142) -> 0 | W142: =SUM(O142:U142) -> 0
D143: ='Перв. скв '!D143 -> Гамма -каротаж в режиме реаьного времени | E143: ='Перв. скв '!E143 -> 0 | F143: ='Перв. скв '!F143 -> сут | G143: ='Перв. скв '!G143 -> 0 | O143: =H143*G143 -> 0 | P143: =I143*G143 -> 0 | Q143: =J143*G143 -> 0 | R143: =K143*G143 -> 0 | S143: =L143*G143 -> 0 | T143: =M143*G143 -> 0 | U143: =N143*G143 -> 0 | V143: =SUM(H143:N143) -> 0 | W143: =SUM(O143:U143) -> 0
